Workbook

Sheet Requete_INFOTITREMINIER OK
A1: entreprise_id | B1: num_titre_minier | C1: nom_perimetre | D1: nm_nature | E1: nm_region | F1: substance_desc | G1: nm_commune | H1: nm_departement | I1: date_signature | J1: date_octroi | L1: superficie_octroye | M1: superficie_exploite | N1: superficie_rendue | O1: superficie_rehabilite | P1: date_fin
A2: 2SBCI | B2: 09142/MIM/DMG | C2: BANDIA | D2: Carrière | E2: THIES | F2: Calcaire | G2: BANDIA | H2: MBOUR | I2: 42886 | J2: 42886 | L2: 0.3 | P2: 44711 | R2: =+VLOOKUP(A2,'[1]Requete_INFOTITREMINIER OK'!$A$1:$M$117,13,0) -> 0 | S2: =N2=R2 -> TRUE
A3: AFRIGEM SL | B3: A010333/MMIAPME/DMG | C3: LINGEKHOTO | D3: Permis de recherche | E3: KEDOUGOU | F3: Or | G3: KEDOUGOU | H3: KEDOUGOU | I3: 40513 | J3: 40513 | L3: 157 | M3: 0 | N3: 120.5 | O3: 0 | P3: 43069 | R3: =+VLOOKUP(A3,'[1]Requete_INFOTITREMINIER OK'!$A$1:$M$117,13,0) -> 120.5 | S3: =N3=R3 -> TRUE
A4: AFRIGEM SL | B4: 010978/MMG/DMG/25/06/2020 | C4: BOUROUBOUROU | D4: Permis de recherche | E4: KEDOUGOU | F4: Or | G4: KEDOUGOU | H4: KEDOUGOU | I4: 40513 | J4: 40513 | L4: 187 | M4: 0 | N4: 110 | O4: 0 | P4: 44625 | R4: =+VLOOKUP(A4,'[1]Requete_INFOTITREMINIER OK'!$A$1:$M$117,13,0) -> 120.5 | S4: =N4=R4 -> FALSE
A5: AFRIGOLD SARL | B5: UTMWGS 84 ZONE 28 | C5: KARAKHAENA | D5: Permis d’exploitation | E5: KEDOUGOU | F5: Or | G5: SARAYA | H5: SARAYA | I5: 42285 | J5: 42402 | L5: 39 | M5: 39 | N5: 0 | O5: 0 | P5: 44228 | R5: =+VLOOKUP(A5,'[1]Requete_INFOTITREMINIER OK'!$A$1:$M$117,13,0) -> 0 | S5: =N5=R5 -> TRUE
A6: AGEM SENEGAL EXPLORATION SUARL | B6: 13984/MIM/DMG | C6: DAORALA | D6: Permis de recherche | E6: KEDOUGOU | F6: Or | G6: MEDINA BAFFE | H6: SARAYA | I6: 38215 | J6: 38415 | L6: 420 | M6: 0 | N6: 184 | O6: 0 | R6: =+VLOOKUP(A6,'[1]Requete_INFOTITREMINIER OK'!$A$1:$M$117,13,0) -> 184 | S6: =N6=R6 -> TRUE
A7: AGEM SENEGAL EXPLORATION SUARL | B7: 012395/MMG/DMG | C7: NOUMOUFOUKHA | D7: Permis de recherche | E7: KEDOUGOU | F7: Or | G7: MEDINA BAFFE | H7: SARAYA | I7: 43231 | J7: 43256 | L7: 79 | M7: 0 | N7: 0 | O7: 0 | P7: 45081 | R7: 0 | S7: =N7=R7 -> TRUE
A8: AGROMINE | B8: 001928MMG | C8: LAMBAYE | D8: Permis de recherche | E8: DIOURBEL | F8: Phosphate de chaux | G8: DIOURBEL | H8: DIOURBEL | I8: 43486 | J8: 43496 | L8: 567 | M8: 0 | N8: 0 | O8: 0 | P8: 401768 | R8: =+VLOOKUP(A8,'[1]Requete_INFOTITREMINIER OK'!$A$1:$M$117,13,0) -> 0 | S8: =N8=R8 -> TRUE
A9: AGROMINE | B9: 025823 | C9: Seune Sèrère | D9: Carrière | E9: THIES | F9: Basalte | G9: KEUR MOUSSA | H9: THIES | J9: 43361 | L9: 0.38 | M9: 0 | N9: 0 | O9: 0 | P9: 45278 | R9: =+VLOOKUP(A9,'[1]Requete_INFOTITREMINIER OK'!$A$1:$M$117,13,0) -> 0 | S9: =N9=R9 -> TRUE
A10: ALBINA SENEGAL SARL | B10: 017130/MMG/DMG | C10: BANDIA | D10: Carrière | E10: THIES | F10: Calcaire | G10: BANDIA | H10: THIES | J10: 43304 | L10: 0.15 | M10: 0.15 | P10: 45129 | R10: =+VLOOKUP(A10,'[1]Requete_INFOTITREMINIER OK'!$A$1:$M$117,13,0) -> 0 | S10: =N10=R10 -> TRUE
A11: AMAFRIQUE SENEGAL | B11: A018603/MMG/DMG | C11: Thilogne | D11: Permis de recherche | E11: MATAM | F11: Phosphate de chaux | G11: AGNAM-CIVOL | H11: MATAM | I11: 42157 | J11: 42200 | L11: 1590 | M11: 0 | N11: 401 | O11: 0 | P11: 44420 | R11: =+VLOOKUP(A11,'[1]Requete_INFOTITREMINIER OK'!$A$1:$M$117,13,0) -> 401 | S11: =N11=R11 -> TRUE
A12: ARDIMINES SARL | B12: 002734 | C12: Tombo | D12: Permis de recherche | E12: KEDOUGOU | F12: Or | G12: TOMBORONKOTO | H12: KEDOUGOU | I12: 42682 | J12: 43510 | L12: 22 | M12: 0 | N12: 0 | O12: 0 | P12: 44971 | R12: =+VLOOKUP(A12,'[1]Requete_INFOTITREMINIER OK'!$A$1:$M$117,13,0) -> 0 | S12: =N12=R12 -> TRUE
A13: ATIC SARL | B13: 09MAI2018009738 | C13: ATIC SILEX | D13: Carrière | E13: THIES | F13: Silex | G13: M’BORO | H13: TIVAOUANE | I13: 43186 | J13: 43229 | L13: 1.2 | M13: 1.2 | N13: 0 | O13: 0 | P13: 401768 | R13: =+VLOOKUP(A13,'[1]Requete_INFOTITREMINIER OK'!$A$1:$M$117,13,0) -> 0 | S13: =N13=R13 -> TRUE
A14: BAMBADJI SA | B14: 012394/ MMG/DMG | C14: BAMBADJI | D14: Permis de recherche | E14: KEDOUGOU | F14: Or | G14: MADINA BAFFE | H14: SARAYA | I14: 43231 | J14: 43256 | L14: 314.5 | M14: 0 | N14: 0 | O14: 0 | P14: 401768 | R14: =+VLOOKUP(A14,'[1]Requete_INFOTITREMINIER OK'!$A$1:$M$117,13,0) -> 0 | S14: =N14=R14 -> TRUE
A15: BAMBUK MINERALS SARL | B15: 014934 | C15: SANGOLA | D15: Permis de recherche | E15: KEDOUGOU | F15: Or | G15: BANDAFASSI | H15: KEDOUGOU | I15: 42529 | J15: 43623 | L15: 381 | M15: 0 | N15: 0 | O15: 0 | P15: 45084 | R15: =+VLOOKUP(A15,'[1]Requete_INFOTITREMINIER OK'!$A$1:$M$117,13,0) -> 0 | S15: =N15=R15 -> TRUE
A16: BAMBUK MINERALS SARL | B16: 023735 | C16: KOULOUNTOU EST | D16: Permis de recherche | E16: KEDOUGOU | F16: Or | G16: TOMBORONKOTO | H16: KEDOUGOU | I16: 42682 | J16: 43410 | L16: 381 | M16: 0 | N16: 0 | O16: 0 | P16: 401768 | R16: =+VLOOKUP(A16,'[1]Requete_INFOTITREMINIER OK'!$A$1:$M$117,13,0) -> 0 | S16: =N16=R16 -> TRUE
A17: BB FIRST COMMODITY HOLDING LIMITED | B17: 00487/MMG/DMG | C17: MADINA FOULBE | D17: Permis de recherche | E17: TAMBACOUNDA | F17: Or | G17: MADINA FOULBE | H17: BAKEL | I17: 40305 | J17: 43115 | L17: 260 | M17: 0 | N17: 65 | O17: 0 | P17: 401768 | R17: =+VLOOKUP(A17,'[1]Requete_INFOTITREMINIER OK'!$A$1:$M$117,13,0) -> 65 | S17: =N17=R17 -> TRUE
A18: BHAIRAVA AGRICOLE SARL | B18: 10566 | C18: KAOUROU | D18: Permis de recherche | E18: KEDOUGOU | F18: Or | G18: Bakel | H18: BAKEL | L18: 144 | R18: =+VLOOKUP(A18,'[1]Requete_INFOTITREMINIER OK'!$A$1:$M$117,13,0) -> #N/A | S18: =N18=R18 -> #N/A
A19: BMCC SA | B19: 001840/MMG/DMG | C19: CHERIF LO NGAKHAM | D19: Permis d’exploitation | E19: DIOURBEL | F19: Phosphates | G19: CHERIF Lo | H19: Diourbel | I19: 43367 | L19: 75 | M19: 5 | N19: 0 | O19: 0 | R19: =+VLOOKUP(A19,'[1]Requete_INFOTITREMINIER OK'!$A$1:$M$117,13,0) -> 0 | S19: =N19=R19 -> TRUE
A20: BOSFOR SARL | B20: 0062254 MEMDMGBD | C20: bandia/thiés | D20: Carrière | E20: THIES | F20: Calcaire | G20: DIASS | H20: MBOUR | J20: 41143 | L20: 0.2 | M20: 0 | O20: 0 | P20: 42969 | R20: =+VLOOKUP(A20,'[1]Requete_INFOTITREMINIER OK'!$A$1:$M$117,13,0) -> 0 | S20: =N20=R20 -> TRUE
A21: BOYA SA | B21: 011843 MIM/DMG | C21: DIAMBA SUD | D21: Permis de recherche | E21: KEDOUGOU | F21: Or | G21: SARAYA | H21: SARAYA | I21: 42102 | J21: 42165 | L21: 71.32 | M21: 0 | N21: 18.02 | O21: 0 | P21: 44391 | R21: =+VLOOKUP(A21,'[1]Requete_INFOTITREMINIER OK'!$A$1:$M$117,13,0) -> 18.02 | S21: =N21=R21 -> TRUE
A22: BOYA SA | B22: 011842/MIM/DMG | C22: DIAMBA NORD | D22: Permis de recherche | E22: KEDOUGOU | F22: Or | G22: SARAYA | H22: SARAYA | I22: 42102 | J22: 42165 | L22: 241.8 | M22: 0 | N22: 80.7 | O22: 0 | P22: 43625 | R22: =+VLOOKUP(A22,'[1]Requete_INFOTITREMINIER OK'!$A$1:$M$117,13,0) -> 18.02 | S22: =N22=R22 -> FALSE
A23: CAYOR PHOSPHATE MINING | B23: 036584 | C23: UTM WGS 84 ZONE 28N | D23: Permis de recherche | E23: LOUGA | F23: Phosphate | G23: NDANDE/ THILOM FALL/ NGOURANE | H23: LOUGA | I23: 41425 | J23: 44741 | L23: 637.48 | R23: =+VLOOKUP(A23,'[1]Requete_INFOTITREMINIER OK'!$A$1:$M$117,13,0) -> 0 | S23: =N23=R23 -> TRUE
A24: CHALLENGER NORD-SUD INTERNATIONAL INC | B24: 025475 | C24: NIAKHENE | D24: Permis de recherche | E24: DIOURBEL | F24: Phosphate de chaux | G24: DIOURBEL | H24: DIOURBEL | I24: 44099 | J24: 44132 | L24: 498 | M24: 0 | N24: 0 | O24: 0 | P24: 45592 | R24: =+VLOOKUP(A24,'[1]Requete_INFOTITREMINIER OK'!$A$1:$M$117,13,0) -> 0 | S24: =N24=R24 -> TRUE
A25: CHALLENGER NORD-SUD INTERNATIONAL INC | B25: A07102/MIM/DMG | C25: Coki | D25: Permis de recherche | E25: LOUGA | F25: Phosphate de chaux | G25: COKI | H25: LOUGA | I25: 42474 | J25: 42506 | L25: 4396 | M25: 0 | N25: 1101 | O25: 0 | P25: 44692 | R25: =+VLOOKUP(A25,'[1]Requete_INFOTITREMINIER OK'!$A$1:$M$117,13,0) -> 0 | S25: =N25=R25 -> FALSE
A26: CHESSER | B26: 006873873 | C26: Bondola | D26: Permis de recherche | E26: KEDOUGOU | F26: Or | G26: Bembou | H26: Kedougou | I26: 44606 | J26: 44623 | L26: 207.17 | M26: 0 | N26: 0 | O26: 0 | R26: =+VLOOKUP(A26,'[1]Requete_INFOTITREMINIER OK'!$A$1:$M$117,13,0) -> #N/A | S26: =N26=R26 -> #N/A
A27: CHESSER | B27: 006873873 | C27: Morichou | D27: Permis de recherche | E27: KEDOUGOU | F27: Or | G27: Sadatou | H27: Kedougou | I27: 44606 | J27: 44623 | L27: 207.17 | M27: 0 | N27: 0 | O27: 0 | R27: =+VLOOKUP(A27,'[1]Requete_INFOTITREMINIER OK'!$A$1:$M$117,13,0) -> #N/A | S27: =N27=R27 -> #N/A
A28: CIMENTS DE L' AFRIQUE SA | B28: 005494 | C28: POUT | D28: Permis d’exploitation | E28: THIES | F28: Calcaire | G28: KEUR MOUSSA | H28: THIES | I28: 42479 | J28: 44279 | L28: 2.77 | M28: 2.77 | N28: 0 | O28: 0 | P28: 46104 | R28: =+VLOOKUP(A28,'[1]Requete_INFOTITREMINIER OK'!$A$1:$M$117,13,0) -> 0 | S28: =N28=R28 -> TRUE
A29: CIMENTS DU SAHEL | B29: 2-N°2000-106 du 22 février 2000 | C29: Argile et latérite Tchiky | D29: Concession minière | E29: THIES | F29: Argile | G29: DIASS | H29: MBOUR | I29: 36574 | J29: 36578 | L29: 2 | M29: 0.3 | N29: 0 | O29: 0.05 | P29: 45710 | R29: =+VLOOKUP(A29,'[1]Requete_INFOTITREMINIER OK'!$A$1:$M$117,13,0) -> 0 | S29: =N29=R29 -> TRUE
A30: CIMENTS DU SAHEL | B30: 3-2015-639 du 15 mai 2015 | C30: Bandia-Kirène | D30: Concession minière | E30: THIES | F30: Calcaire | G30: BANDIA | H30: THIES | I30: 36574 | J30: 42139 | L30: 5.86 | M30: 0 | N30: 0 | O30: 0 | P30: 51271 | R30: =+VLOOKUP(A30,'[1]Requete_INFOTITREMINIER OK'!$A$1:$M$117,13,0) -> 0 | S30: =N30=R30 -> TRUE
A31: COMPAGNIE GENERALE D'EXPLOITATION DE CARRIERE | B31: 007541/MMITPME | C31: BANDIA | D31: Carrière | E31: THIES | F31: Calcaire | G31: BANDIA | H31: THIES | J31: 40032 | L31: 0.05 | M31: 0.05 | P31: 46431 | R31: =+VLOOKUP(A31,'[1]Requete_INFOTITREMINIER OK'!$A$1:$M$117,13,0) -> 0 | S31: =N31=R31 -> TRUE
A32: COMPAGNIE GENERALE D'EXPLOITATION DE CARRIERE | B32: 008569/MEMIMEFP | C32: BANDIA | D32: Carrière | E32: THIES | F32: Calcaire | G32: BANDIA | H32: THIES | J32: 35384 | L32: 0.075 | M32: 0.065 | N32: 0.01 | P32: 46431 | R32: =+VLOOKUP(A32,'[1]Requete_INFOTITREMINIER OK'!$A$1:$M$117,13,0) -> 0 | S32: =N32=R32 -> FALSE
A33: COMPAGNIE GENERALE D'EXPLOITATION DE CARRIERE | B33: 010284 | C33: DIACK | D33: Carrière | E33: THIES | F33: Basalte | G33: N'GOUDIANE | H33: THIES | J33: 43986 | L33: 0.0275 | P33: 45811 | R33: =+VLOOKUP(A33,'[1]Requete_INFOTITREMINIER OK'!$A$1:$M$117,13,0) -> 0 | S33: =N33=R33 -> TRUE
A34: COMPAGNIE GENERALE D'EXPLOITATION DE CARRIERE | B34: 6283/MIM/DMG | C34: DIACK | D34: Carrière | E34: THIES | F34: Basalte | G34: N'GOUDIANE | H34: THIES | J34: 42478 | L34: 0.41 | P34: 46432 | R34: =+VLOOKUP(A34,'[1]Requete_INFOTITREMINIER OK'!$A$1:$M$117,13,0) -> 0 | S34: =N34=R34 -> TRUE
A35: COMPAGNIE GENERALE D'EXPLOITATION DE CARRIERE | B35: 07540/MIMTPME/DMG | C35: DIACK | D35: Carrière | E35: THIES | F35: Basalte | G35: N'GOUDIANE | H35: THIES | J35: 40032 | L35: 0.15 | P35: 46460 | R35: =+VLOOKUP(A35,'[1]Requete_INFOTITREMINIER OK'!$A$1:$M$117,13,0) -> 0 | S35: =N35=R35 -> TRUE
A36: COMPAGNIE GENERALE D'EXPLOITATION DE CARRIERE | B36: 04252/MIMTPME/DMG | C36: DIACK | D36: Carrière | E36: THIES | F36: Basalte | G36: N'GOUDIANE | H36: THIES | J36: 39902 | L36: 0.05 | P36: 46460 | R36: =+VLOOKUP(A36,'[1]Requete_INFOTITREMINIER OK'!$A$1:$M$117,13,0) -> 0 | S36: =N36=R36 -> TRUE
A37: COMPAGNIE GENERALE D'EXPLOITATION DE CARRIERE | B37: 001557/MMG/CAB/CT1 | C37: DIACK | D37: Carrière | E37: THIES | F37: Basalte | G37: N'GOUDIANE | H37: THIES | J37: 43493 | L37: 0.15 | P37: 45318 | R37: =+VLOOKUP(A37,'[1]Requete_INFOTITREMINIER OK'!$A$1:$M$117,13,0) -> 0 | S37: =N37=R37 -> TRUE
A38: COMPAGNIE GENERALE D'EXPLOITATION DE CARRIERE | B38: 0010283 | C38: DIACK | D38: Carrière | E38: THIES | F38: Basalte | G38: N'GOUDIANE | H38: THIES | J38: 43986 | L38: 0.015 | P38: 45811 | R38: =+VLOOKUP(A38,'[1]Requete_INFOTITREMINIER OK'!$A$1:$M$117,13,0) -> 0 | S38: =N38=R38 -> TRUE
A39: CONSULTING BUSINESS AGENCY | B39: A025607/MMG/DMG | C39: MADINA TOUBAKOTA | D39: Permis de recherche | E39: KEDOUGOU | F39: Or | G39: BEMBOU | H39: SARAYA | I39: 43737 | J39: 43780 | L39: 252 | M39: 0 | N39: 0 | O39: 0 | P39: 45240 | R39: =+VLOOKUP(A39,'[1]Requete_INFOTITREMINIER OK'!$A$1:$M$117,13,0) -> #N/A | S39: =N39=R39 -> #N/A
A40: CSE GRANULATS | B40: 008633MMG/DMG | C40: DIACK | D40: Carrière | E40: THIES | F40: Basalte | G40: N’GOUNDIANE | H40: THIES | J40: 43219 | L40: 0.092 | M40: 0.092 | N40: 0 | O40: 0 | P40: 401768 | R40: =+VLOOKUP(A40,'[1]Requete_INFOTITREMINIER OK'!$A$1:$M$117,13,0) -> 0 | S40: =N40=R40 -> TRUE
A41: CSE GRANULATS | B41: 033738 | C41: MANSADALA | D41: Carrière | E41: TAMBACOUNDA | F41: Basalte | G41: DIALACOTO | H41: TAMBACOUNDA | L41: 0.5 | M41: 0.5 | N41: 0 | O41: 0 | P41: 44489 | R41: =+VLOOKUP(A41,'[1]Requete_INFOTITREMINIER OK'!$A$1:$M$117,13,0) -> 0 | S41: =N41=R41 -> TRUE
A42: DALEMA | B42: 012394 | C42: dalema | D42: Permis de recherche | E42: KEDOUGOU | F42: Or | G42: SARAYA | H42: SARAYA | L42: 298 | R42: =+VLOOKUP(A42,'[1]Requete_INFOTITREMINIER OK'!$A$1:$M$117,13,0) -> #N/A | S42: =N42=R42 -> #N/A
A43: DAMASH MINERALS LTD | B43: 19005 | C43: KOLDA | D43: Permis de recherche | E43: KOLDA | F43: Phosphate de chaux | G43: MEDINA EL HADJI | H43: KOLDA | I43: 40737 | J43: 41613 | L43: 2645 | M43: 0 | N43: 2520 | O43: 0 | P43: 45145 | R43: =+VLOOKUP(A43,'[1]Requete_INFOTITREMINIER OK'!$A$1:$M$117,13,0) -> 2520 | S43: =N43=R43 -> TRUE
A44: DANGOTE CEMENT SENEGAL | B44: 2008-1431 | C44: POUT | D44: Concession minière | E44: THIES | F44: Calcaire | G44: POUT | H44: THIES | I44: 39794 | J44: 39794 | L44: 10.07 | N44: 0 | O44: 0 | P44: 48924 | R44: =+VLOOKUP(A44,'[1]Requete_INFOTITREMINIER OK'!$A$1:$M$117,13,0) -> 0 | S44: =N44=R44 -> TRUE
A45: DANGOTE CEMENT SENEGAL | B45: 2015-368 | C45: TCHIKY | D45: Concession minière | E45: THIES | F45: latérite, argile | G45: TCHIKY | H45: THIES | L45: 3.59 | R45: =+VLOOKUP(A45,'[1]Requete_INFOTITREMINIER OK'!$A$1:$M$117,13,0) -> 0 | S45: =N45=R45 -> TRUE
A46: DIYAN EXPLOITATION MINIERE SUARL | B46: 026689/MMG/DMG | C46: ICS Darou Khoudoss Mboro | D46: Carrière | E46: THIES | F46: Silex | G46: DAROU KHOUDOSS | H46: TIVAOUANE | J46: 43448 | L46: 0 | P46: 45274 | R46: =+VLOOKUP(A46,'[1]Requete_INFOTITREMINIER OK'!$A$1:$M$117,13,0) -> 0 | S46: =N46=R46 -> TRUE
A47: ENTREPRISE MAPATHE NDIOUCK SA | B47: 100MMITPME/DMG | C47: GABOU | D47: Petite Mine | E47: TAMBACOUNDA | F47: Grès | G47: GABOU | H47: BAKEL | J47: 40112 | L47: 5.11 | M47: 5.11 | N47: 0 | P47: 45195 | R47: =+VLOOKUP(A47,'[1]Requete_INFOTITREMINIER OK'!$A$1:$M$117,13,0) -> 0 | S47: =N47=R47 -> TRUE
A48: ENTREPRISE MAPATHE NDIOUCK SA | B48: 20736 | C48: ICS | D48: Petite Mine | E48: THIES | F48: Silex | G48: Mboro | H48: TIVAOUANE | J48: 43349 | L48: 0.73 | P48: 44809 | R48: =+VLOOKUP(A48,'[1]Requete_INFOTITREMINIER OK'!$A$1:$M$117,13,0) -> 0 | S48: =N48=R48 -> TRUE
A49: ENTREPRISE OUSMANE SOW | C49: Carrière d'entreprise Ousmane SOW | D49: Carrière | E49: THIES | F49: Grès | G49: DIASS | H49: MBOUR | L49: 0.04 | M49: 0 | N49: 0 | O49: 0 | P49: 401768 | R49: =+VLOOKUP(A49,'[1]Requete_INFOTITREMINIER OK'!$A$1:$M$117,13,0) -> 0 | S49: =N49=R49 -> TRUE
A50: G.H MINING | B50: 006243/MMG/DMG | C50: Sud Kéniéba & Madina Foulbé | D50: Petite mine | E50: TAMBACOUNDA | F50: Manganése | G50: MADINA FOULBE | H50: BAKEL | I50: 40914 | J50: 40940 | L50: 5 | M50: 0.02 | N50: 0 | O50: 1.87 | P50: 44593 | R50: =+VLOOKUP(A50,'[1]Requete_INFOTITREMINIER OK'!$A$1:$M$117,13,0) -> 0 | S50: =N50=R50 -> TRUE
A51: GAZAL CARRIERES SUARL | B51: 6101/MIMTPME/DMG | C51: BANDIA | D51: Carrière | E51: THIES | F51: Calcaire | G51: BANDIA | H51: THIES | J51: 44882 | L51: 0.51 | M51: 0.34 | R51: =+VLOOKUP(A51,'[1]Requete_INFOTITREMINIER OK'!$A$1:$M$117,13,0) -> 0 | S51: =N51=R51 -> TRUE
A52: GECAMINES | B52: 001331/MMG/DMG | C52: DIACK | D52: Carrière | E52: THIES | F52: Basalte | G52: N'GOUDIANE | H52: THIES | J52: 43573 | L52: 0.11 | P52: 45314 | R52: =+VLOOKUP(A52,'[1]Requete_INFOTITREMINIER OK'!$A$1:$M$117,13,0) -> 0 | S52: =N52=R52 -> TRUE
A53: GECAMINES | B53: 001332 | C53: DIACK | D53: Carrière | E53: THIES | F53: Basalte | G53: N'GOUDIANE | H53: THIES | J53: 44225 | L53: 0.105 | P53: 46050 | R53: =+VLOOKUP(A53,'[1]Requete_INFOTITREMINIER OK'!$A$1:$M$117,13,0) -> 0 | S53: =N53=R53 -> TRUE
A54: GECAMINES | B54: 08847/MIM/DMG | C54: DIACK | D54: Carrière | E54: THIES | F54: Basalte | G54: N'GOUDIANE | H54: THIES | J54: 42881 | L54: 0.14 | P54: 46629 | R54: =+VLOOKUP(A54,'[1]Requete_INFOTITREMINIER OK'!$A$1:$M$117,13,0) -> 0 | S54: =N54=R54 -> TRUE
A55: GECAMINES | B55: 026694/MMG/DMG | C55: BANDIA | D55: Carrière | E55: THIES | F55: Calcaire | G55: BANDIA | H55: THIES | J55: 43448 | L55: 0.11 | P55: 45273 | R55: =+VLOOKUP(A55,'[1]Requete_INFOTITREMINIER OK'!$A$1:$M$117,13,0) -> 0 | S55: =N55=R55 -> TRUE
A56: GECAMINES | B56: 03044/MEM/DMG | C56: BANDIA | D56: Carrière | E56: THIES | F56: Calcaire | G56: BANDIA | H56: THIES | J56: 38525 | L56: 1.29 | P56: 45248 | R56: =+VLOOKUP(A56,'[1]Requete_INFOTITREMINIER OK'!$A$1:$M$117,13,0) -> 0 | S56: =N56=R56 -> TRUE
A57: GECAMINES | B57: 0032820 | C57: GECAMINES BANDIA | D57: Carrière | E57: THIES | F57: Calcaire | G57: BANDIA | H57: THIES | J57: 44476 | L57: 1.722 | M57: 0.35 | N57: 0 | O57: 0 | P57: 46302 | R57: =+VLOOKUP(A57,'[1]Requete_INFOTITREMINIER OK'!$A$1:$M$117,13,0) -> 0 | S57: =N57=R57 -> TRUE
A58: GECAMINES | B58: A09098 | C58: GECAMINE DIACK | D58: Carrière | E58: THIES | F58: Basalte | G58: N’GOUNDIANE | H58: THIES | J58: 40057 | L58: 0.59 | M58: 0.0129 | N58: 0 | O58: 0 | P58: 41883 | R58: =+VLOOKUP(A58,'[1]Requete_INFOTITREMINIER OK'!$A$1:$M$117,13,0) -> 0 | S58: =N58=R58 -> TRUE
A59: GLOBAL IMMO SENEGAL SARL | B59: 013588 | C59: ICS | D59: Carrière | E59: THIES | F59: Silex | G59: DAROU KHOUDOSS | H59: TIVAOUANE | I59: 43273 | J59: 43273 | L59: 1 | M59: 0 | N59: 0 | O59: 0 | P59: 45107 | R59: =+VLOOKUP(A59,'[1]Requete_INFOTITREMINIER OK'!$A$1:$M$117,13,0) -> 0 | S59: =N59=R59 -> TRUE
A60: G-PHOS S.A.U | B60: 12950 | C60: Niakhène | D60: Permis de recherche | E60: THIES | F60: Phosphate de chaux | G60: TIVAOUANE | H60: TIVAOUANE | I60: 42145 | J60: 42179 | L60: 636 | M60: 0 | N60: 0 | O60: 0 | P60: 401768 | R60: =+VLOOKUP(A60,'[1]Requete_INFOTITREMINIER OK'!$A$1:$M$117,13,0) -> 0 | S60: =N60=R60 -> TRUE
A61: GRANDE COTE OPERATIONS | B61: 1326 | C61: Grande Côte | D61: Concession minière | E61: THIES | F61: Ilménite, zircon, rutile, leucoxène | G61: DAROU KHOUDOSS | H61: TIVAOUANE | I61: 38239 | J61: 38249 | L61: 445 | M61: 2.2 | N61: 0 | O61: 2 | P61: 401768 | R61: =+VLOOKUP(A61,'[1]Requete_INFOTITREMINIER OK'!$A$1:$M$117,13,0) -> 0 | S61: =N61=R61 -> TRUE
A62: GROUPEMENT D'ENTREPRISE SINTRAM HOUAR | B62: 004068MMI/DMG | C62: Carrière de basalte de Diack | D62: Carrière | E62: THIES | F62: Basalte | G62: N’GOUNDIANE | H62: THIES | I62: 39267 | J62: 39391 | L62: 0.04 | M62: 0 | N62: 0.005 | O62: 0 | P62: 44714 | R62: =+VLOOKUP(A62,'[1]Requete_INFOTITREMINIER OK'!$A$1:$M$117,13,0) -> 0.005 | S62: =N62=R62 -> TRUE
A63: HOLDING ATLANTQUE MINING PETROLUM-SA | B63: 025476 | C63: AINOUMANE | D63: Permis de recherche | E63: DIOURBEL | F63: Phosphate de chaux | G63: DINGUIRAYE | H63: BAMBEY | I63: 44099 | J63: 44132 | L63: 588 | M63: 0 | N63: 0 | O63: 0 | P63: 45592 | R63: =+VLOOKUP(A63,'[1]Requete_INFOTITREMINIER OK'!$A$1:$M$117,13,0) -> 0 | S63: =N63=R63 -> TRUE
A64: IAMGOLD BOTO S.A | B64: 2020-981 | C64: Boto | D64: Permis d’exploitation | E64: KEDOUGOU | F64: Or | G64: MEDINA BAFFE | H64: SARAYA | I64: 38215 | J64: 43815 | L64: 148 | M64: 0 | N64: 0 | O64: 0 | P64: 51120 | R64: =+VLOOKUP(A64,'[1]Requete_INFOTITREMINIER OK'!$A$1:$M$117,13,0) -> 0 | S64: =N64=R64 -> TRUE
A65: INCA SARL | B65: 10660 | C65: bandia | D65: Carrière | E65: THIES | F65: Calcaire | G65: BANDIA | H65: MBOUR | I65: 43019 | J65: 42054 | L65: 0.2 | M65: 0 | N65: 0 | O65: 0 | P65: 43880 | R65: =+VLOOKUP(A65,'[1]Requete_INFOTITREMINIER OK'!$A$1:$M$117,13,0) -> 0 | S65: =N65=R65 -> TRUE
A66: INDUSTRIES CHIMIQUES DU SENEGAL | B66: D1999-1021 | C66: TOBENE SUD | D66: Concession minière | E66: THIES | F66: Phosphate de chaux | G66: PIRE GOUREY | H66: TIVAOUANE | I66: 39561 | J66: 36452 | L66: 18.441 | M66: 0 | N66: 0 | P66: 401768 | R66: =+VLOOKUP(A66,'[1]Requete_INFOTITREMINIER OK'!$A$1:$M$117,13,0) -> 0 | S66: =N66=R66 -> TRUE
A67: INDUSTRIES CHIMIQUES DU SENEGAL | B67: D1999-1020 | C67: TOBENE NORD | D67: Concession minière | E67: THIES | F67: Phosphate de chaux | G67: DAROU KHOUDOSS | H67: TIVAOUANE | I67: 39561 | J67: 36452 | L67: 173 | M67: 7 | N67: 0 | P67: 401768 | R67: =+VLOOKUP(A67,'[1]Requete_INFOTITREMINIER OK'!$A$1:$M$117,13,0) -> 0 | S67: =N67=R67 -> TRUE
A68: INTERNATIONAL MINING COMPANY (IMC) | B68: 020031/MIM/DMG | C68: DOUTA | D68: Permis de recherche | E68: KEDOUGOU | F68: Or | G68: KHOSSANTO | H68: SARAYA | I68: 40128 | J68: 40128 | L68: 103 | M68: 0 | N68: 45 | O68: 0 | P68: 44144 | R68: =+VLOOKUP(A68,'[1]Requete_INFOTITREMINIER OK'!$A$1:$M$117,13,0) -> 45 | S68: =N68=R68 -> TRUE
A69: KANEL RESOURCES | B69: 015098 | C69: Sud Kanel | D69: Permis de recherche | E69: MATAM | F69: Phosphate de chaux | G69: OGO | H69: MATAM | I69: 42147 | J69: 42233 | L69: 3029.76 | M69: 0 | N69: 757 | O69: 0 | P69: 44424 | R69: =+VLOOKUP(A69,'[1]Requete_INFOTITREMINIER OK'!$A$1:$M$117,13,0) -> 757 | S69: =N69=R69 -> TRUE
A70: KUTLU GABANE HOLDING S.A | B70: 024218 | C70: Ngoudiane-EGCCBN | D70: Carrière | E70: THIES | F70: Basalte | G70: N’GOUNDIANE | H70: THIES | I70: 43742 | J70: 43797 | L70: 0.06 | M70: 0.0634 | N70: 0 | O70: 0 | P70: 401768 | R70: =+VLOOKUP(A70,'[1]Requete_INFOTITREMINIER OK'!$A$1:$M$117,13,0) -> 0 | S70: =N70=R70 -> TRUE
A71: LES CARRIERES CTG SARL | B71: 019235 | C71: CARRIERE DE CALCAIRE DE KEUR LAT DIOP FALL | D71: Carrière | E71: THIES | F71: Calcaire | G71: MONT- ROLLAND | H71: TIVAOUANE | J71: 44348 | L71: 1.74 | M71: 0 | N71: 0 | O71: 0 | P71: 45808 | R71: =+VLOOKUP(A71,'[1]Requete_INFOTITREMINIER OK'!$A$1:$M$117,13,0) -> 0 | S71: =N71=R71 -> TRUE
A72: Makabingui Gold Operations S.A | B72: 20181904 | C72: Sambarabougou | D72: Permis d’exploitation | E72: KEDOUGOU | F72: Or | G72: MISSIRAH SIRIMANA | H72: SARAYA | I72: 42702 | J72: 43382 | L72: 121.83 | M72: 0 | N72: 102 | O72: 0 | P72: 401768 | R72: =+VLOOKUP(A72,'[1]Requete_INFOTITREMINIER OK'!$A$1:$M$117,13,0) -> 102 | S72: =N72=R72 -> TRUE
A73: MASSAWA JERSEY LIMITED | B73: 0070/MMG | C73: Kanoumba | D73: Permis de recherche | E73: KEDOUGOU | F73: Or | G73: SABODALA | H73: SARAYA | J73: 43886 | L73: 286 | M73: 0 | N73: 0 | O73: 0 | P73: 401768 | R73: =+VLOOKUP(A73,'[1]Requete_INFOTITREMINIER OK'!$A$1:$M$117,13,0) -> 0 | S73: =N73=R73 -> TRUE
A74: NEW ENERGY INVESTMENT SARL | B74: 05FEV2019002204 | C74: Kéniékoto | D74: Permis de recherche | E74: KEDOUGOU | F74: Or | G74: SARAYA | H74: SARAYA | I74: 43413 | J74: 43501 | L74: 110 | M74: 0 | N74: 0 | O74: 0 | P74: 44962 | R74: =+VLOOKUP(A74,'[1]Requete_INFOTITREMINIER OK'!$A$1:$M$117,13,0) -> 0 | S74: =N74=R74 -> TRUE
A75: NEW ENERGY INVESTMENT SARL | B75: 09MAI2018009739 | C75: Ylimalo | D75: Permis de recherche | E75: KEDOUGOU | F75: Lithium | G75: SARAYA | H75: SARAYA | I75: 43196 | J75: 43229 | L75: 368 | M75: 0 | N75: 0 | O75: 0 | P75: 44690 | R75: =+VLOOKUP(A75,'[1]Requete_INFOTITREMINIER OK'!$A$1:$M$117,13,0) -> 0 | S75: =N75=R75 -> TRUE
A76: NIAMAYA GOLD SARL | B76: 011650 | C76: NIAMAYA | D76: Permis de recherche | E76: KEDOUGOU | F76: Or | G76: KHOSSANTO | H76: SARAYA | I76: 41470 | J76: 44012 | L76: 57 | M76: 0 | N76: 14 | O76: 0 | P76: 45472 | R76: =+VLOOKUP(A76,'[1]Requete_INFOTITREMINIER OK'!$A$1:$M$117,13,0) -> 14 | S76: =N76=R76 -> TRUE
A77: PETOWAL MINING COMPANY (PMC) SA | B77: 2016-995 | C77: MAKO | D77: Concession minière | E77: KEDOUGOU | F77: Or | G77: TOMBORONKOTO | H77: KEDOUGOU | I77: 38980 | J77: 42565 | L77: 87.5 | M77: 87.5 | P77: 48043 | R77: =+VLOOKUP(A77,'[1]Requete_INFOTITREMINIER OK'!$A$1:$M$117,13,0) -> 0 | S77: =N77=R77 -> TRUE
A78: PROCHIMAT SA | B78: 966720 | C78: POUT | D78: Concession minière | E78: THIES | F78: Attapulgite | G78: POUT | H78: THIES | J78: 35296 | L78: 0.36 | M78: 0 | N78: 0 | O78: 0 | P78: 401768 | R78: =+VLOOKUP(A78,'[1]Requete_INFOTITREMINIER OK'!$A$1:$M$117,13,0) -> 0 | S78: =N78=R78 -> TRUE
A79: PROCHIMAT SA | B79: 96536 | C79: MBODIENE | D79: Concession minière | E79: THIES | F79: Attapulgite | G79: MALICOUNDA | H79: MBOUR | J79: 35242 | L79: 0.45 | M79: 0 | N79: 0 | O79: 0 | P79: 401768 | R79: =+VLOOKUP(A79,'[1]Requete_INFOTITREMINIER OK'!$A$1:$M$117,13,0) -> 0 | S79: =N79=R79 -> TRUE
A80: PROCHIMAT SA | B80: 007930 | C80: NIANING | D80: Concession minière | E80: THIES | F80: Attapulgite | G80: MALICOUNDA | H80: MBOUR | J80: 28864 | L80: 1.45 | M80: 0.01 | N80: 0 | O80: 0.1 | P80: 56257 | R80: =+VLOOKUP(A80,'[1]Requete_INFOTITREMINIER OK'!$A$1:$M$117,13,0) -> 0 | S80: =N80=R80 -> TRUE
A81: ROYAL SENEGAL MINES ET EQUIPEMENT | B81: 00365/MMG/DMG | C81: BANDIA | D81: Carrière | E81: THIES | F81: Calcaire | G81: BANDIA | H81: THIES | J81: 43474 | L81: 0.42 | M81: 0.42 | P81: 45299 | R81: =+VLOOKUP(A81,'[1]Requete_INFOTITREMINIER OK'!$A$1:$M$117,13,0) -> 0 | S81: =N81=R81 -> TRUE
A82: SABODALA GOLD OPERATIONS | B82: 2015-1136 | C82: SABODALA | D82: Concession minière | E82: KEDOUGOU | F82: Or | G82: SABODALA | H82: SARAYA | I82: 42101 | J82: 42214 | L82: 291.8 | M82: 291.8 | O82: 0.69 | P82: 51345 | R82: =+VLOOKUP(A82,'[1]Requete_INFOTITREMINIER OK'!$A$1:$M$117,13,0) -> 0 | S82: =N82=R82 -> TRUE
A83: SABODALA MINING COMPANY | B83: 008707/MMG/DMG | C83: BRANSAN | D83: Permis de recherche | E83: KEDOUGOU | F83: Or | G83: SABODALA | H83: SARAYA | I83: 43161 | J83: 43210 | L83: 337.3 | M83: 0 | N83: 0 | O83: 0 | P83: 44670 | R83: =+VLOOKUP(A83,'[1]Requete_INFOTITREMINIER OK'!$A$1:$M$117,13,0) -> 0 | S83: =N83=R83 -> TRUE
A84: SENEGAL MINES | B84: 15M | C84: MBODIENE | D84: Concession minière | E84: THIES | F84: Attapulgite | G84: N’GUENIENE | H84: MBOUR | I84: 35941 | J84: 36574 | L84: 2.18 | M84: 0.198 | N84: 2.16 | O84: 0.098 | P84: 401768 | R84: =+VLOOKUP(A84,'[1]Requete_INFOTITREMINIER OK'!$A$1:$M$117,13,0) -> 2.16 | S84: =N84=R84 -> TRUE
A85: SEN-HMC SUARL | B85: 000363MMG/DMG | C85: Sud Saint louis | D85: Petite mine | E85: SAINT-LOUIS | F85: Minéraux Lourds | G85: LEONA | H85: LOUGA | I85: 40931 | J85: 40935 | L85: 4.55 | M85: 0.156 | N85: 2.57 | O85: 0 | P85: 401768 | R85: =+VLOOKUP(A85,'[1]Requete_INFOTITREMINIER OK'!$A$1:$M$117,13,0) -> #N/A | S85: =N85=R85 -> #N/A
A86: SEN-HMC SUARL | B86: 000363MMG/DMG | C86: KEBEMER | D86: Permis de recherche | E86: LOUGA | F86: Phosphates | G86: THIOLOME FALL | H86: LOUGA | I86: 41327 | J86: 41465 | L86: 898.5 | M86: 0 | N86: 545.1 | O86: 0 | P86: 44741 | R86: =+VLOOKUP(A86,'[1]Requete_INFOTITREMINIER OK'!$A$1:$M$117,13,0) -> #N/A | S86: =N86=R86 -> #N/A
A87: SEPHOS SENEGAL SA | B87: 10357MMITPME/DMG | C87: LAM LAM | D87: Petite mine | E87: THIES | F87: Phosphate de chaux | G87: PAMBAL | H87: TIVAOUANE | I87: 40126 | J87: 40126 | L87: 5 | M87: 0 | N87: 0 | O87: 0 | P87: 401768 | R87: =+VLOOKUP(A87,'[1]Requete_INFOTITREMINIER OK'!$A$1:$M$117,13,0) -> 0 | S87: =N87=R87 -> TRUE
A88: SERIGNE SALIOU MBACKE SUARL | B88: 00489/MMG/DMG | C88: SANSAMBA | D88: Petite mine | E88: KEDOUGOU | F88: Or | G88: SARAYA | H88: SARAYA | I88: 43115 | J88: 40935 | L88: 5 | M88: 5 | N88: 0 | O88: 0 | P88: 401768 | R88: =+VLOOKUP(A88,'[1]Requete_INFOTITREMINIER OK'!$A$1:$M$117,13,0) -> #N/A | S88: =N88=R88 -> #N/A
A89: SOCABEG MINING | B89: 013957 | C89: Ndindy | D89: Permis de recherche | E89: DIOURBEL | F89: Phosphate de chaux | G89: N’DINDY | H89: DIOURBEL | I89: 42368 | J89: 42429 | L89: 872 | M89: 0 | N89: 381 | O89: 0 | P89: 44619 | R89: =+VLOOKUP(A89,'[1]Requete_INFOTITREMINIER OK'!$A$1:$M$117,13,0) -> 381 | S89: =N89=R89 -> TRUE
A90: SOCIETE DE CONCASSAGE ET DU BETON (SOCOBE) | B90: 10862 | C90: INDUSTRIES CHIMIQUES DU SENEGAL (ICS) | D90: Carrière | E90: THIES | F90: Silex | G90: M’BORO | H90: TIVAOUANE | J90: 43196 | L90: 0 | M90: 0 | N90: 0 | O90: 0 | P90: 401768 | R90: =+VLOOKUP(A90,'[1]Requete_INFOTITREMINIER OK'!$A$1:$M$117,13,0) -> 0 | S90: =N90=R90 -> TRUE
A91: SOCIETE DE MANUFACTURE DE PRODUCTION INDUSTRIELLE DU SENEGAL (SOMAPIS) | B91: 007526/DMG/MMG | C91: ICS Darou Khoudoss | D91: Carrière | E91: THIES | F91: Silex | G91: DAROU KHOUDOSS | H91: TIVAOUANE | J91: 43195 | L91: 0 | M91: 0 | N91: 0 | O91: 0 | P91: 401768 | R91: =+VLOOKUP(A91,'[1]Requete_INFOTITREMINIER OK'!$A$1:$M$117,13,0) -> #N/A | S91: =N91=R91 -> #N/A
A92: SOCIETE MINIERE DE LA VALLEE DU FLEUVE SENEGAL –SOMIVA | B92: 2011770 | C92: Ndendory | D92: Concession minière | E92: MATAM | F92: Phosphate de chaux | G92: NDENDORY | H92: KANEL | I92: 39722 | J92: 40702 | L92: 661 | M92: 10 | N92: 0 | O92: 0 | R92: =+VLOOKUP(A92,'[1]Requete_INFOTITREMINIER OK'!$A$1:$M$117,13,0) -> 0 | S92: =N92=R92 -> TRUE
A93: SOCIETE SENEGALAISE DE NEGOCE INTERNATIONALE (SNEPAC) SARL | B93: 15099MIM/DMG | C93: BANTACCO | D93: Permis de recherche | E93: KEDOUGOU | F93: Or | G93: BEMBOU | H93: SARAYA | I93: 42955 | J93: 42969 | L93: 113.2 | M93: 0 | N93: 28.3 | O93: 0 | P93: 44430 | R93: =+VLOOKUP(A93,'[1]Requete_INFOTITREMINIER OK'!$A$1:$M$117,13,0) -> 28.3 | S93: =N93=R93 -> TRUE
A94: SOCIETE SENEGALAISE DES PHOSPHATES DE THIES (SSPT) | B94: D1985-411 | C94: ALLOU KAGNE | D94: Concession minière | E94: THIES | F94: Attapulgite | G94: POUT | H94: THIES | I94: 35943 | J94: 35807 | L94: 13.48 | M94: 0.4 | N94: 0 | O94: 0.2 | P94: 44937 | R94: =+VLOOKUP(A94,'[1]Requete_INFOTITREMINIER OK'!$A$1:$M$117,13,0) -> 0 | S94: =N94=R94 -> TRUE
A95: SOCIETE SENEGALAISE DES PHOSPHATES DE THIES (SSPT) | B95: D1985-409 | C95: MBODIENE | D95: Concession minière | E95: THIES | F95: Attapulgite | H95: THIES | J95: 31156 | L95: 1.18 | M95: 0.4 | N95: 0 | P95: 44937 | R95: =+VLOOKUP(A95,'[1]Requete_INFOTITREMINIER OK'!$A$1:$M$117,13,0) -> 0 | S95: =N95=R95 -> TRUE
A96: SOCIETE SENEGALAISE DES PHOSPHATES DE THIES (SSPT) | B96: D1985-413 | C96: SEBIKHOTANE | D96: Concession minière | E96: THIES | F96: Attapulgite | H96: THIES | J96: 31156 | L96: 3.29 | M96: 0.4 | N96: 0 | P96: 44937 | R96: =+VLOOKUP(A96,'[1]Requete_INFOTITREMINIER OK'!$A$1:$M$117,13,0) -> 0 | S96: =N96=R96 -> TRUE
A97: SOCIETE SENEGALAISE DES PHOSPHATES DE THIES (SSPT) | B97: D1985-399 | C97: WARRANG | D97: Concession minière | E97: THIES | F97: Attapulgite | H97: THIES | J97: 31156 | L97: 1.3 | M97: 0.4 | N97: 0 | P97: 44937 | R97: =+VLOOKUP(A97,'[1]Requete_INFOTITREMINIER OK'!$A$1:$M$117,13,0) -> 0 | S97: =N97=R97 -> TRUE
A98: SOCOCIM INDUSTRIES | B98: D2006-359 | C98: BARGNY | D98: Concession minière | E98: DAKAR | F98: Marno calcaires | G98: RUFISQUE | H98: RUFISQUE | I98: 38751 | J98: 38826 | L98: 4.61 | M98: 1.99 | P98: 47957 | R98: =+VLOOKUP(A98,'[1]Requete_INFOTITREMINIER OK'!$A$1:$M$117,13,0) -> 0 | S98: =N98=R98 -> TRUE
A99: SOCOCIM INDUSTRIES | B99: D2006-361 | C99: POUT | D99: Concession minière | E99: THIES | F99: Calcaire | G99: THIES | H99: THIES | I99: 38751 | J99: 38826 | L99: 4.1 | P99: 47957 | R99: =+VLOOKUP(A99,'[1]Requete_INFOTITREMINIER OK'!$A$1:$M$117,13,0) -> 0 | S99: =N99=R99 -> TRUE
A100: SOCOCIM INDUSTRIES | B100: 017372/MMG/CAB/CTI | C100: DIACK | D100: Carrière | E100: THIES | F100: latérite | G100: NGOUNDIANE | H100: THIES | L100: 0.3 | R100: =+VLOOKUP(A100,'[1]Requete_INFOTITREMINIER OK'!$A$1:$M$117,13,0) -> 0 | S100: =N100=R100 -> TRUE
...

Sheet INFOTITRE
A2: Répartition des titres miniers par région en 2022 | O2: Étiquettes de lignes | P2: Nombre de entreprise_id
A3: Étiquettes de lignes | B3: Nombre de entreprise_id | C3: Nombre de entreprise_id2 | E3: Étiquettes de lignes | F3: Nombre de entreprise_id | O3: 2SBCI | P3: 1
A4: THIES | B4: 66 | C4: 0.54545455 | E4: THIES | F4: =B4 -> 66 | O4: AFRIGEM SL | P4: 2
A5: KEDOUGOU | B5: 34 | C5: 0.28099174 | E5: KEDOUGOU | F5: =B5 -> 34 | O5: AFRIGOLD SARL | P5: 1
A6: TAMBACOUNDA | B6: 7 | C6: 0.05785124 | E6: TAMBACOUNDA | F6: =B6 -> 7 | O6: AGEM SENEGAL EXPLORATION SUARL | P6: 2
A7: DIOURBEL | B7: 5 | C7: 0.041322314 | E7: DIOURBEL | F7: =B7 -> 5 | O7: AGROMINE | P7: 2
A8: MATAM | B8: 3 | C8: 0.024793388 | E8: MATAM | F8: =B8 -> 3 | O8: ALBINA SENEGAL SARL | P8: 1
A9: LOUGA | B9: 3 | C9: 0.024793388 | E9: LOUGA | F9: =B9 -> 3 | O9: AMAFRIQUE SENEGAL | P9: 1
A10: SAINT-LOUIS | B10: 1 | C10: 0.0082644628 | E10: SAINT-LOUIS | F10: =B10 -> 1 | O10: ARDIMINES SARL | P10: 1
A11: KOLDA | B11: 1 | C11: 0.0082644628 | E11: KOLDA | F11: =B11 -> 1 | O11: ATIC SARL | P11: 1
A12: DAKAR | B12: 1 | C12: 0.0082644628 | E12: DAKAR | F12: =B12 -> 1 | O12: BAMBADJI SA | P12: 1
A13: Total général | B13: 121 | C13: 1 | E13: Total général | F13: =SUM(F4:F12) -> 121 | O13: BAMBUK MINERALS SARL | P13: 2
O14: BB FIRST COMMODITY HOLDING LIMITED | P14: 1
O15: BHAIRAVA AGRICOLE SARL | P15: 1
A16: Répartition des titres miniers selon le type par région en 2022 | O16: BMCC SA | P16: 1
A17: Nombre de nm_nature | B17: Étiquettes de colonnes | O17: BOSFOR SARL | P17: 1
A18: Étiquettes de lignes | B18: Carrière | C18: Concession minière | D18: Permis d’exploitation | E18: Permis de recherche | F18: Petite Mine | G18: Total général | O18: BOYA SA | P18: 2
A19: DAKAR | C19: 1 | G19: 1 | O19: CAYOR PHOSPHATE MINING | P19: 1
A20: DIOURBEL | D20: 1 | E20: 4 | G20: 5 | O20: CHALLENGER NORD-SUD INTERNATIONAL INC | P20: 2
A21: KEDOUGOU | C21: 3 | D21: 3 | E21: 27 | F21: 1 | G21: 34 | O21: CHESSER | P21: 2
A22: KOLDA | E22: 1 | G22: 1 | O22: CIMENTS DE L' AFRIQUE SA | P22: 1
A23: LOUGA | E23: 3 | G23: 3 | O23: CIMENTS DU SAHEL | P23: 2
A24: MATAM | C24: 1 | E24: 2 | G24: 3 | O24: COMPAGNIE GENERALE D'EXPLOITATION DE CARRIERE | P24: 8
A25: SAINT-LOUIS | F25: 1 | G25: 1 | O25: CONSULTING BUSINESS AGENCY | P25: 1
A26: TAMBACOUNDA | B26: 3 | E26: 2 | F26: 2 | G26: 7 | O26: CSE GRANULATS | P26: 2
A27: THIES | B27: 44 | C27: 18 | D27: 1 | E27: 1 | F27: 2 | G27: 66 | O27: DALEMA | P27: 1
A28: Total général | B28: 47 | C28: 23 | D28: 5 | E28: 40 | F28: 6 | G28: 121 | O28: DAMASH MINERALS LTD | P28: 1
O29: DANGOTE CEMENT SENEGAL | P29: 2
E30: =E21/E28 -> 0.675 | O30: DIYAN EXPLOITATION MINIERE SUARL | P30: 1
A31: Répartition des titres miniers par type en 2022 | O31: ENTREPRISE MAPATHE NDIOUCK SA | P31: 2
A32: Étiquettes de lignes | B32: Nombre de nm_nature | C32: Nombre de nm_nature2 | O32: ENTREPRISE OUSMANE SOW | P32: 1
A33: Carrière | B33: 47 | C33: 0.38842975 | O33: G.H MINING | P33: 1
A34: Permis de recherche | B34: 40 | C34: 0.33057851 | O34: GAZAL CARRIERES SUARL | P34: 1
A35: Concession minière | B35: 23 | C35: 0.19008264 | O35: GECAMINES | P35: 7
A36: Petite Mine | B36: 6 | C36: 0.049586777 | O36: GLOBAL IMMO SENEGAL SARL | P36: 1
A37: Permis d’exploitation | B37: 5 | C37: 0.041322314 | O37: G-PHOS S.A.U | P37: 1
A38: Total général | B38: 121 | C38: 1 | O38: GRANDE COTE OPERATIONS | P38: 1
O39: GROUPEMENT D'ENTREPRISE SINTRAM HOUAR | P39: 1
A40: Répartition des titres miniers par type en 2022 | O40: HOLDING ATLANTQUE MINING PETROLUM-SA | P40: 1
A41: Nature | B41: Nombre | C41: % | O41: IAMGOLD BOTO S.A | P41: 1
A42: Carrière | B42: 46 | C42: 0.38333333 | O42: INCA SARL | P42: 1
A43: Permis de recherche | B43: 40 | C43: 0.33333333 | O43: INDUSTRIES CHIMIQUES DU SENEGAL | P43: 2
A44: Concession minière | B44: 23 | C44: 0.19166667 | O44: INTERNATIONAL MINING COMPANY (IMC) | P44: 1
A45: Petite Mine | B45: 6 | C45: 0.05 | O45: KANEL RESOURCES | P45: 1
A46: Permis d’exploitation | B46: 5 | C46: 0.041666667 | O46: KUTLU GABANE HOLDING S.A | P46: 1
A47: TOTAL | B47: 120 | C47: 1 | O47: LES CARRIERES CTG SARL | P47: 1
O48: Makabingui Gold Operations S.A | P48: 1
O49: MASSAWA JERSEY LIMITED | P49: 1
A50: Répartition des surfaces octroyées et rendues (km²) par type de titre en 2022 | O50: NEW ENERGY INVESTMENT SARL | P50: 2
A51: Étiquettes de lignes | B51: Somme de superficie_octroye | C51: Somme de superficie_octroye2 | D51: Somme de superficie_rendue | E51: Somme de superficie_rendue2 | O51: NIAMAYA GOLD SARL | P51: 1
A52: Carrière | B52: 16.646495 | C52: 0.00068370234 | D52: 0.015 | E52: 2.2870647e-06 | O52: PETOWAL MINING COMPANY (PMC) SA | P52: 1
A53: Concession minière | B53: 1858.48 | C53: 0.076331211 | D53: 2.16 | E53: 0.00032933732 | O53: PROCHIMAT SA | P53: 3
A54: Permis d’exploitation | B54: 386.6 | C54: 0.015878377 | D54: 102 | E54: 0.01555204 | O54: ROYAL SENEGAL MINES ET EQUIPEMENT | P54: 1
A55: Permis de recherche | B55: 22060.46 | C55: 0.9060639 | D55: 6451.88 | E55: 0.98372448 | O55: SABODALA GOLD OPERATIONS | P55: 1
A56: Petite Mine | B56: 25.39 | C56: 0.0010428143 | D56: 2.57 | E56: 0.00039185043 | O56: SABODALA MINING COMPANY | P56: 1
A57: Total général | B57: 24347.576 | C57: 1 | D57: 6558.625 | E57: 1 | O57: SENEGAL MINES | P57: 1
O58: SEN-HMC SUARL | P58: 2
H59: 23140 | O59: SEPHOS SENEGAL SA | P59: 1
H60: 21266 | O60: SERIGNE SALIOU MBACKE SUARL | P60: 1
A61: Répartition des surfaces octroyées et rendues (km²) par région en 2022 | H61: REGION | I61: Superficie octroyée | K61: Superficie rendue | O61: SOCABEG MINING | P61: 1
A62: Étiquettes de lignes | B62: Somme de superficie_octroye | C62: Somme de superficie_octroye2 | D62: Somme de superficie_rendue | E62: Somme de superficie_rendue2 | I62: Km² | J62: % | K62: Km² | L62: % | O62: SOCIETE DE CONCASSAGE ET DU BETON (SOCOBE) | P62: 1
A63: DAKAR | B63: 4.61 | C63: 0.00018934123 | E63: 0 | H63: DAKAR | I63: =B63 -> 4.61 | J63: =C63 -> 0.00018934123 | K63: =D63 -> 0 | L63: =E63 -> 0 | O63: SOCIETE DE MANUFACTURE DE PRODUCTION INDUSTRIELLE DU SENEGAL (SOMAPIS) | P63: 1
A64: DIOURBEL | B64: 2600 | C64: 0.10678681 | D64: 381 | E64: 0.058091444 | H64: DIOURBEL | I64: =B64 -> 2600 | J64: =C64 -> 0.10678681 | K64: =D64 -> 381 | L64: =E64 -> 0.058091444 | O64: SOCIETE MINIERE DE LA VALLEE DU FLEUVE SENEGAL –SOMIVA | P64: 1
A65: KEDOUGOU | B65: 6194.85 | C65: 0.25443395 | D65: 783.78 | E65: 0.11950371 | H65: KEDOUGOU | I65: =B65 -> 6194.85 | J65: =C65 -> 0.25443395 | K65: =D65 -> 783.78 | L65: =E65 -> 0.11950371 | O65: SOCIETE SENEGALAISE DE NEGOCE INTERNATIONALE (SNEPAC) SARL | P65: 1
A66: KOLDA | B66: 2645 | C66: 0.10863504 | D66: 2520 | E66: 0.38422688 | H66: KOLDA | I66: =B66 -> 2645 | J66: =C66 -> 0.10863504 | K66: =D66 -> 2520 | L66: =E66 -> 0.38422688 | O66: SOCIETE SENEGALAISE DES PHOSPHATES DE THIES (SSPT) | P66: 4
A67: LOUGA | B67: 5931.98 | C67: 0.24363739 | D67: 1646.1 | E67: 0.25098248 | H67: LOUGA | I67: =B67 -> 5931.98 | J67: =C67 -> 0.24363739 | K67: =D67 -> 1646.1 | L67: =E67 -> 0.25098248 | O67: SOCOCIM INDUSTRIES | P67: 12
A68: MATAM | B68: 5280.76 | C68: 0.21689058 | D68: 1158 | E68: 0.1765614 | H68: MATAM | I68: =B68 -> 5280.76 | J68: =C68 -> 0.21689058 | K68: =D68 -> 1158 | L68: =E68 -> 0.1765614 | O68: SODEMINES | P68: 2
A69: SAINT-LOUIS | B69: 4.55 | C69: 0.00018687692 | D69: 2.57 | E69: 0.00039185043 | H69: SAINT-LOUIS | I69: =B69 -> 4.55 | J69: =C69 -> 0.00018687692 | K69: =D69 -> 2.57 | L69: =E69 -> 0.00039185043 | O69: SODEVCO | P69: 1
A70: TAMBACOUNDA | B70: 333.86 | C70: 0.013712248 | D70: 65 | E70: 0.0099106139 | H70: TAMBACOUNDA | I70: =B70 -> 333.86 | J70: =C70 -> 0.013712248 | K70: =D70 -> 65 | L70: =E70 -> 0.0099106139 | O70: SONKO ET FILS SARL | P70: 1
A71: THIES | B71: 1351.9665 | C71: 0.055527765 | D71: 2.175 | E71: 0.00033162439 | H71: THIES | I71: =B71 -> 1351.9665 | J71: =C71 -> 0.055527765 | K71: =D71 -> 2.175 | L71: =E71 -> 0.00033162439 | O71: SORED MINES SA | P71: 1
A72: Total général | B72: 24347.576 | C72: 1 | D72: 6558.625 | E72: 1 | H72: Total | I72: =SUM(I63:I71) -> 24347.576 | J72: =SUM(J63:J71) -> 1 | K72: =SUM(K63:K71) -> 6558.625 | L72: =SUM(L63:L71) -> 1 | O72: STRATEX-EMC.SA | P72: 1
O73: SWAMI MINES SA | P73: 1
O74: TALIX-MINES | P74: 1
O75: TANOR SAS | P75: 1
A76: Répartition des titres miniers selon le type par région en 2022 | O76: TRIYANGS INTERNATIONAL MINING GROUP SA | P76: 2
A77: REGION | B77: Carrière | C77: Concession minière | D77: Permis d’exploitation | E77: Permis de recherche | F77: Petite Mine | G77: Total | O77: VAPROM AFRICA SA | P77: 1
A78: DAKAR | B78: 0 | C78: 1 | D78: 0 | E78: 0 | F78: 0 | G78: 1 | O78: CARRIERES ET SABLES | P78: 1
A79: DIOURBEL | B79: 0 | C79: 0 | D79: 1 | E79: 4 | F79: 0 | G79: 5 | O79: Total général | P79: 121
A80: KEDOUGOU | B80: 0 | C80: 3 | D80: 3 | E80: 27 | F80: 1 | G80: 34
A81: KOLDA | B81: 0 | C81: 0 | D81: 0 | E81: 1 | F81: 0 | G81: 1
A82: LOUGA | B82: 0 | C82: 0 | D82: 0 | E82: 3 | F82: 0 | G82: 3
A83: MATAM | B83: 0 | C83: 1 | D83: 0 | E83: 2 | F83: 0 | G83: 3
A84: SAINT-LOUIS | B84: 0 | C84: 0 | D84: 0 | E84: 0 | F84: 1 | G84: 1
A85: TAMBACOUNDA | B85: 3 | C85: 0 | D85: 0 | E85: 2 | F85: 2 | G85: 7
A86: THIES | B86: 44 | C86: 18 | D86: 1 | E86: 1 | F86: 2 | G86: 66
A87: Total | B87: 47 | C87: 23 | D87: 5 | E87: 40 | F87: 6 | G87: 121
B89: =B78/B$87 -> 0 | C89: =C78/C$87 -> 0.043478261 | D89: =D78/D$87 -> 0 | E89: =E78/E$87 -> 0 | F89: =F78/F$87 -> 0 | G89: =G78/G$87 -> 0.0082644628
B90: =B79/B$87 -> 0 | C90: =C79/C$87 -> 0 | D90: =D79/D$87 -> 0.2 | E90: =E79/E$87 -> 0.1 | F90: =F79/F$87 -> 0 | G90: =G79/G$87 -> 0.041322314
B91: =B80/B$87 -> 0 | C91: =C80/C$87 -> 0.13043478 | D91: =D80/D$87 -> 0.6 | E91: =E80/E$87 -> 0.675 | F91: =F80/F$87 -> 0.16666667 | G91: =G80/G$87 -> 0.28099174
B92: =B81/B$87 -> 0 | C92: =C81/C$87 -> 0 | D92: =D81/D$87 -> 0 | E92: =E81/E$87 -> 0.025 | F92: =F81/F$87 -> 0 | G92: =G81/G$87 -> 0.0082644628
B93: =B82/B$87 -> 0 | C93: =C82/C$87 -> 0 | D93: =D82/D$87 -> 0 | E93: =E82/E$87 -> 0.075 | F93: =F82/F$87 -> 0 | G93: =G82/G$87 -> 0.024793388
B94: =B83/B$87 -> 0 | C94: =C83/C$87 -> 0.043478261 | D94: =D83/D$87 -> 0 | E94: =E83/E$87 -> 0.05 | F94: =F83/F$87 -> 0 | G94: =G83/G$87 -> 0.024793388
B95: =B84/B$87 -> 0 | C95: =C84/C$87 -> 0 | D95: =D84/D$87 -> 0 | E95: =E84/E$87 -> 0 | F95: =F84/F$87 -> 0.16666667 | G95: =G84/G$87 -> 0.0082644628
B96: =B85/B$87 -> 0.063829787 | C96: =C85/C$87 -> 0 | D96: =D85/D$87 -> 0 | E96: =E85/E$87 -> 0.05 | F96: =F85/F$87 -> 0.33333333 | G96: =G85/G$87 -> 0.05785124
B97: =B86/B$87 -> 0.93617021 | C97: =C86/C$87 -> 0.7826087 | D97: =D86/D$87 -> 0.2 | E97: =E86/E$87 -> 0.025 | F97: =F86/F$87 -> 0.33333333 | G97: =G86/G$87 -> 0.54545455

Sheet Requete_SONDAGE OK
A1: formulaire_id | B1: entreprise_id | C1: num_titre_minier | D1: nm_nature | E1: sondage_desc | F1: grille_maille_desc | G1: metrage | H1: intervalle | I1: intersection
A2: 1677 | B2: 2SBCI | C2: ………. | D2: Carrière | E2: RAB | F2: 89mm | G2: 17 | H2: 3
B3: AGEM SENEGAL EXPLORATION SUARL | D3: Permis de recherche | E3: RC | G3: 3000
B4: AGROMINE | D4: Permis de recherche | E4: Carotté | G4: 240
B5: ARDIMINES SARL | D5: Permis de recherche | E5: RAB
B6: BAMBADJI SA | D6: Permis de recherche | E6: Carotté | G6: 6122
B7: BAMBADJI SA | D7: Permis de recherche | E7: RC | G7: 16439
B8: BAMBADJI SA | D8: Permis de recherche | E8: Aircore | G8: 2764
B9: BAMBADJI SA | D9: Permis de recherche | E9: Tarrière | G9: 3114
B10: BAMBUK MINERALS SARL | D10: Permis de recherche | E10: RC | G10: =27+30+42+42+47+44+43+40+11+17+32+38+42+42+40+36+36+20+70+72*3+64+76*4+66*2+45+36+48+35+36*3+24+40+33*2+30*4+72+33 -> 2042
B11: BAMBUK MINERALS SARL | D11: Permis de recherche | E11: Tarrière | G11: =9+6+4+12+11+5+4+9+14+18+5+5+8+7+20+10+5 -> 152
B12: BHAIRAVA AGRICOLE SARL | D12: Permis de recherche | E12: Tarrière | G12: 330
B13: BOYA SA | D13: Permis de recherche | E13: RC | G13: 9413
B14: BOYA SA | D14: Permis de recherche | E14: Carotté | G14: 7807
A15: 1580 | B15: CSE GRANULATS | C15: 008633/MMG/DGM | D15: Carrière | E15: Carotté | G15: 21 | H15: 0-0 | I15: 0
A16: 1580 | B16: CSE GRANULATS | C16: 008633/MMG/DGM | D16: Carrière | E16: Destructif | G16: 18 | H16: 0-0 | I16: 0
B17: DAMASH MINERALS LTD | D17: Permis de recherche | E17: RC | G17: 510
B18: DAMASH MINERALS LTD | D18: Permis de recherche | E18: Carotté | G18: 335
B19: HOLDING ATLANTQUE MINING PETROLUM-SA | D19: Permis de recherche | E19: Carotté | G19: 415
B20: HOLDING ATLANTQUE MINING PETROLUM-SA | D20: Permis de recherche | E20: Destructif | G20: 1717
A21: 1395 | B21: INDUSTRIES CHIMIQUES DU SENEGAL | C21: 99 1020 | D21: Concession minière | E21: Carotté | F21: 250*250m | G21: 6111 | H21: 0-0 | I21: 7
B22: INTERNATIONAL MINING COMPANY (IMC) | D22: Permis de recherche | E22: RC | G22: 26898
B23: MASSAWA JERSEY LIMITED | D23: Permis de recherche | E23: RC | G23: 1496
A24: 1400 | B24: PETOWAL MINING COMPANY (PMC) SA | C24: 2016-995 | D24: Concession minière | E24: RC | F24: 10*10 | G24: 25251 | H24: 24 | I24: 0
B25: SABODALA GOLD OPERATIONS | D25: Concession minière | E25: RC | G25: 150659
B26: SABODALA MINING COMPANY | D26: Permis de recherche | E26: RC | G26: 8674
A27: 1460 | B27: SENEGAL MINES | C27: 15M | D27: Concession minière | E27: Carotté | F27: 200 | G27: 30 | H27: 15m | I27: 850000
A28: 1545 | B28: SEN-HMC SUARL | C28: 000363MMG/DMG | D28: Petite mine | E28: Tarrière | F28: 50m*50m | G28: 118 | H28: 0-0 | I28: 0
A29: 1590 | B29: SEPHOS SENEGAL SA | C29: 10357/MMI/PME/DMG | D29: Petite mine | E29: Carotté | F29: 25*25 | G29: 6155 | H29: 0-0 | I29: 0
A30: 1605 | B30: SERIGNE SALIOU MBACKE SUARL | C30: 00489/MMG/DMG | D30: Petite mine | E30: RAB | G30: 6524 | H30: 0-864 | I30: 246
B31: SOCABEG MINING | D31: Permis de recherche | E31: Carotté | G31: 167
B32: SOCABEG MINING | D32: Permis de recherche | E32: Destructif | G32: 681
B33: SOCIETE SENEGALAISE DE NEGOCE INTERNATIONALE (SNEPAC) SARL | D33: Permis de recherche | E33: RC | G33: 4914 | H33: 25 | I33: 3.72
B34: SOCIETE SENEGALAISE DE NEGOCE INTERNATIONALE (SNEPAC) SARL | D34: Permis de recherche | E34: Tarrière | G34: 3193 | H34: 35 | I34: 1.2
B35: SONKO ET FILS SARL | D35: Permis de recherche | E35: Tarrière | G35: =6+12+6+3+6 -> 33
A36: 1680 | B36: SORED-MINES SA | C36: 2007-1327 | D36: Concession minière | E36: RC | G36: 1986 | H36: 0-0 | I36: 0
B37: STRATEX-EMC.SA | D37: Permis de recherche | E37: Tarrière | G37: 8953
G38: =SUM(G2:G37) -> 306299

Sheet SONDAGE
A2: Répartition des entreprises ayant fait des sondages selon le type en 2022
A3: Étiquettes de lignes | B3: Nombre de sondage_desc | C3: Somme de metrage | D3: Somme de metrage2 | G3: Étiquettes de lignes | H3: Nombre de sondage_desc | I3: Nombre de sondage_desc2 | K3: TYPE DE SONDAGE | L3: Nombre | M3: % | N3: METRAGE | O3: %
A4: Aircore | B4: 1 | C4: 2764 | D4: 0.0090238623 | G4: Aircore | H4: 1 | I4: 0.027777778 | K4: RC | L4: 12 | M4: 0.33333333 | N4: 6524 | O4: 0.021299449
A5: Carotté | B5: 10 | C5: 27403 | D5: 0.089464869 | G5: Carotté | H5: 10 | I5: 0.27777778 | K5: Carotté | L5: 10 | M5: 0.27777778 | N5: 27403 | O5: 0.089464869
A6: Destructif | B6: 3 | C6: 2416 | D6: 0.0078877176 | G6: Destructif | H6: 3 | I6: 0.083333333 | K6: Tarrière | L6: 7 | M6: 0.19444444 | N6: 251282 | O6: 0.82038139
A7: RAB | B7: 3 | C7: 6541 | D7: 0.021354951 | G7: RAB | H7: 3 | I7: 0.083333333 | K7: Destructif | L7: 3 | M7: 0.083333333 | N7: 2416 | O7: 0.0078877176
A8: RC | B8: 12 | C8: 251282 | D8: 0.82038139 | G8: RC | H8: 12 | I8: 0.33333333 | K8: RAB | L8: 3 | M8: 0.083333333 | N8: 17 | O8: 5.5501324e-05
A9: Tarrière | B9: 7 | C9: 15893 | D9: 0.051887208 | G9: Tarrière | H9: 7 | I9: 0.19444444 | K9: Aircore | L9: 1 | M9: 0.027777778 | N9: 2764 | O9: 0.0090238623
A10: Total général | B10: 36 | C10: 306299 | D10: 1 | G10: Total général | H10: 36 | I10: 1
A15: Répartition des linéaires de sondage par nature du titre minier 2022
A16: Étiquettes de lignes | B16: Nombre de nm_nature
A17: Permis de recherche | B17: 25
A18: Concession minière | B18: 5
A19: Petite mine | B19: 3
A20: Carrière | B20: 3
A21: Total général | B21: 36
A25: Nombre de nm_nature | B25: Étiquettes de colonnes
A26: Étiquettes de lignes | B26: Carrière | C26: Concession minière | D26: Permis de recherche | E26: Petite mine | F26: Total général
A27: Aircore | D27: 1 | F27: 1
A28: Carotté | B28: 1 | C28: 2 | D28: 6 | E28: 1 | F28: 10
A29: Destructif | B29: 1 | D29: 2 | F29: 3
A30: RAB | B30: 1 | D30: 1 | E30: 1 | F30: 3
A31: RC | C31: 3 | D31: 9 | F31: 12
A32: Tarrière | D32: 6 | E32: 1 | F32: 7
A33: Total général | B33: 3 | C33: 5 | D33: 25 | E33: 3 | F33: 36

Sheet Requete_PRODUCTION_TRANSFOR OK
A1: entreprise_id | B1: Région | C1: produit_desc_ok | D1: qte_prd_vendu_pays | E1: qte_prd_vendu_etrger | F1: qte_prd_immobilise | G1: qte_stock_ouverture | H1: qte_prd_stock_cloture | I1: val_prd_vendu_pays | J1: val_prd_vendu_etrger | K1: val_prd_immobilise | L1: val_prd_stock_ouverture | M1: val_prd_stock_cloture | N1: PRODUCTION EN QUANTITE | O1: PRODUCTION EN VALEUR | Q1: Prix pays | R1: Prix etgr | S1: prix stck ouv | T1: Prix stock Cltur
A2: 2SBCI | B2: =VLOOKUP(A2,'Requete_INFOTITREMINIER OK'!$A$1:$P$122,5,0) -> THIES | C2: Calcaire | D2: 85030 | E2: 0 | F2: 0 | G2: 0 | H2: 0 | I2: 306017.57 | J2: 0 | K2: 0 | L2: 0 | M2: 0 | N2: =+D2+E2+H2-G2 -> 85030 | O2: =+I2+J2+M2-L2 -> 306017.57 | P2: =O2/N2 -> 3.5989365
A3: AFRIGOLD SARL | B3: KEDOUGOU | C3: Or | D3: 0.04847 | E3: 0 | F3: 0 | G3: 0 | H3: 0 | I3: 1614476 | J3: 0 | K3: 0 | L3: 0 | M3: 0 | N3: =+D3+E3+H3-G3 -> 0.04847 | O3: =+I3+J3+M3-L3 -> 1614476 | Q3: =I3/D3 -> 33308768 | R3: =J3/E3 -> #DIV/0! | S3: =L3/G3 -> #DIV/0! | T3: =M3/H3 -> #DIV/0!
A4: ALBINA SENEGAL SARL | B4: THIES | C4: Calcaire | D4: 95809.5 | E4: 0 | F4: 0 | G4: 0 | H4: 0 | I4: 205720.2 | J4: 0 | K4: 0 | L4: 0 | M4: 0 | N4: =+D4+E4+H4-G4 -> 95809.5 | O4: =+I4+J4+M4-L4 -> 205720.2 | P4: =O4/N4 -> 2.1471796 | Q4: =I4/D4 -> 2.1471796 | R4: =J4/E4 -> #DIV/0! | S4: =L4/G4 -> #DIV/0! | T4: =M4/H4 -> #DIV/0!
A5: ATIC SARL | B5: THIES | C5: Silex | D5: 44624 | E5: 0 | F5: 0 | G5: 0 | H5: 0 | I5: 334686 | J5: 0 | K5: 0 | L5: 0 | M5: 0 | N5: =+D5+E5+H5-G5 -> 44624 | O5: =+I5+J5+M5-L5 -> 334686 | P5: =+O5/N5 -> 7.5001345 | Q5: =I5/D5 -> 7.5001345 | R5: =J5/E5 -> #DIV/0! | S5: =L5/G5 -> #DIV/0! | T5: =M5/H5 -> #DIV/0!
A6: BMCC SA | B6: DIOURBEL | C6: Phosphates | D6: 2595 | E6: 49105 | F6: 0 | G6: 549 | H6: 26601 | I6: 149252 | J6: 2483353 | K6: 0 | L6: 13445 | M6: 1346446 | N6: =+D6+E6+H6-G6 -> 77752 | O6: =+I6+J6+M6-L6 -> 3965606 | P6: =+O6/N6 -> 51.003267 | Q6: =I6/D6 -> 57.515222 | R6: =J6/E6 -> 50.572304 | S6: =L6/G6 -> 24.489982 | T6: =M6/H6 -> 50.616368
A7: BOSFOR SARL | B7: THIES | C7: Calcaire | D7: 724174 | E7: 0 | F7: =400457+131471+206999 -> 738927 | G7: =23874+4533 -> 28407 | H7: =10228+7951+24981 -> 43160 | I7: 1954151 | J7: 0 | K7: =240274+723090+931495 -> 1894859 | L7: 145413 | M7: 153082 | N7: =+D7+E7+H7-G7 -> 738927 | O7: =+I7+J7+M7-L7 -> 1961820 | P7: =O7/N7 -> 2.6549578 | Q7: =I7/D7 -> 2.6984551 | R7: =J7/E7 -> #DIV/0! | S7: =L7/G7 -> 5.1189144 | T7: =M7/H7 -> 3.5468489
A8: CIMENTS DU SAHEL | B8: THIES | C8: Ciment | D8: 2401500 | E8: 1112412 | F8: 23334 | G8: 982 | H8: 36378 | I8: 112613674 | J8: 51335300 | K8: 1116653 | L8: 32467 | M8: 1565025 | N8: =+D8+E8+H8-G8 -> 3549308 | O8: =+I8+J8+M8-L8 -> 165481532 | P8: =O8/N8 -> 46.623604 | Q8: =I8/D8 -> 46.893056 | R8: =J8/E8 -> 46.14774 | S8: =L8/G8 -> 33.062118 | T8: =M8/H8 -> 43.021194
A9: COMPAGNIE GENERALE D'EXPLOITATION DE CARRIERE | B9: THIES | C9: Basalte | D9: 2224570 | E9: 14394 | F9: 0 | G9: =L9/7.2 -> 539755.42 | H9: =M9/7.2 -> 543569.31 | I9: 16061313 | J9: 107161 | K9: 0 | L9: 3886239 | M9: 3913699 | N9: =+D9+E9+H9-G9 -> 2242777.9 | O9: =+I9+J9+M9-L9 -> 16195934 | P9: =+O9/N9 -> 7.2213722 | Q9: =I9/D9 -> 7.219963 | R9: =J9/E9 -> 7.4448381 | S9: =L9/G9 -> 7.2 | T9: =M9/H9 -> 7.2
A10: COMPAGNIE GENERALE D'EXPLOITATION DE CARRIERE | B10: THIES | C10: Calcaire | D10: =I10/4.5 -> 49375.204 | I10: =16418122.419-O9 -> 222188.42 | N10: =+D10+E10+H10-G10 -> 49375.204 | O10: =+I10+J10+M10-L10 -> 222188.42 | P10: =O10/N10 -> 4.5 | Q10: =I10/D10 -> 4.5 | R10: =J10/E10 -> #DIV/0! | S10: =L10/G10 -> #DIV/0! | T10: =M10/H10 -> #DIV/0!
A11: CSE GRANULATS | B11: THIES | C11: Basalte | D11: 1236580.2 | E11: 47949.86 | F11: 1412149 | G11: 78819 | H11: 61383 | I11: 8611048.7 | J11: 390487.02 | K11: 55066154 | L11: 634703.08 | M11: 436646.16 | N11: =+D11+E11+H11-G11 -> 1267094.1 | O11: =+I11+J11+M11-L11 -> 8803478.8 | P11: =+O11/N11 -> 6.9477706 | Q11: =I11/D11 -> 6.9635991 | R11: =J11/E11 -> 8.143653 | S11: =L11/G11 -> 8.052666 | T11: =M11/H11 -> 7.1134705
A12: DANGOTE CEMENT SENEGAL | B12: THIES | C12: Ciment | D12: 842075 | E12: 208646 | F12: 0 | G12: 6073 | H12: 27266 | I12: 39627967 | J12: 8959179 | K12: 0 | L12: 184722 | M12: 1063760 | N12: =+D12+E12+H12-G12 -> 1071914 | O12: =+I12+J12+M12-L12 -> 49466184 | P12: =O12/N12 -> 46.14753 | Q12: =I12/D12 -> 47.059902 | R12: =J12/E12 -> 42.939615 | S12: =L12/G12 -> 30.416927 | T12: =M12/H12 -> 39.014157
A13: DIYAN EXPLOITATION MINIERE SUARL | B13: THIES | C13: Silex | N13: =+D13+E13+H13-G13 -> 0 | O13: =+I13+J13+M13-L13 -> 0 | Q13: =I13/D13 -> #DIV/0! | R13: =J13/E13 -> #DIV/0! | S13: =L13/G13 -> #DIV/0! | T13: =M13/H13 -> #DIV/0!
A14: ENTREPRISE MAPATHE NDIOUCK SA | B14: THIES | C14: Silex | D14: 45433 | G14: 1935 | I14: 403499.92 | L14: 17185.137 | N14: =+D14+E14+H14-G14 -> 43498 | O14: =+I14+J14+M14-L14 -> 386314.78 | P14: =+O14/N14 -> 8.8812079 | Q14: =I14/D14 -> 8.8812079 | R14: =J14/E14 -> #DIV/0! | S14: =L14/G14 -> 8.8812078 | T14: =M14/H14 -> #DIV/0!
A15: ENTREPRISE MAPATHE NDIOUCK SA | B15: TAMBACOUNDA | C15: Grès | D15: 62201 | I15: 477353.11 | N15: =+D15+E15+H15-G15 -> 62201 | O15: =+I15+J15+M15-L15 -> 477353.11 | P15: =+O15/N15 -> 7.6743639 | Q15: =I15/D15 -> 7.6743639 | R15: =J15/E15 -> #DIV/0! | S15: =L15/G15 -> #DIV/0! | T15: =M15/H15 -> #DIV/0!
A16: ENTREPRISE OUSMANE SOW | B16: THIES | C16: Grès | D16: =9765+7845 -> 17610 | I16: =54922.81+44127.9 -> 99050.71 | N16: =+D16+E16+H16-G16 -> 17610 | O16: =+I16+J16+M16-L16 -> 99050.71 | P16: =+O16/N16 -> 5.6246854 | Q16: =I16/D16 -> 5.6246854 | R16: =J16/E16 -> #DIV/0! | S16: =L16/G16 -> #DIV/0! | T16: =M16/H16 -> #DIV/0!
A17: ENTREPRISE OUSMANE SOW | B17: THIES | C17: Latérite | N17: =+D17+E17+H17-G17 -> 0 | O17: =+I17+J17+M17-L17 -> 0 | Q17: =I17/D17 -> #DIV/0! | R17: =J17/E17 -> #DIV/0! | S17: =L17/G17 -> #DIV/0! | T17: =M17/H17 -> #DIV/0!
A18: G.H MINING | B18: TAMBACOUNDA | C18: Manganèse | D18: 0 | E18: 31093.338 | F18: 0 | G18: 1300 | H18: 6297.512 | I18: 0 | J18: 1263388 | K18: 0 | L18: 0 | M18: 0 | N18: =+D18+E18+H18-G18 -> 36090.85 | O18: =+I18+J18+M18-L18 -> 1263388 | Q18: =I18/D18 -> #DIV/0! | R18: =J18/E18 -> 40.632112 | S18: =L18/G18 -> 0 | T18: =M18/H18 -> 0
A19: GAZAL CARRIERES | B19: THIES | C19: Calcaire | D19: 117568 | E19: 0 | F19: 0 | G19: 0 | H19: 0 | I19: 534400 | J19: 0 | K19: 0 | L19: 0 | M19: 0 | N19: =+D19+E19+H19-G19 -> 117568 | O19: =+I19+J19+M19-L19 -> 534400 | P19: =O19/N19 -> 4.5454545 | Q19: =I19/D19 -> 4.5454545 | R19: =J19/E19 -> #DIV/0! | S19: =L19/G19 -> #DIV/0! | T19: =M19/H19 -> #DIV/0!
A20: GECAMINES | B20: THIES | C20: Calcaire | D20: =110593+6694+153506+258+178082+106396 -> 555529 | F20: 0 | G20: 0 | H20: 0 | I20: =657483+37673+134004+1480+707190+858211 -> 2396041 | K20: 0 | N20: =+D20+E20+H20-G20 -> 555529 | O20: =+I20+J20+M20-L20 -> 2396041 | Q20: =I20/D20 -> 4.31308 | R20: =J20/E20 -> #DIV/0! | S20: =L20/G20 -> #DIV/0! | T20: =M20/H20 -> #DIV/0!
A21: GECAMINES | B21: THIES | C21: Basalte | D21: 2306764 | E21: 93421 | F21: 0 | G21: 0 | H21: 0 | I21: 17227606 | J21: 736942 | K21: 0 | L21: 3677029 | M21: 3043077 | N21: =+D21+E21+H21-G21 -> 2400185 | O21: =+I21+J21+M21-L21 -> 17330596 | P21: =+O21/N21 -> 7.2205251 | Q21: =I21/D21 -> 7.4683002 | R21: =J21/E21 -> 7.8883977 | S21: =L21/G21 -> #DIV/0! | T21: =M21/H21 -> #DIV/0!
A22: GLOBAL IMMO SENEGAL SARL | B22: THIES | C22: Silex | D22: 292997 | I22: 2137633.4 | N22: =+D22+E22+H22-G22 -> 292997 | O22: =+I22+J22+M22-L22 -> 2137633.4 | P22: =+O22/N22 -> 7.2957519 | Q22: =I22/D22 -> 7.2957519 | R22: =J22/E22 -> #DIV/0! | S22: =L22/G22 -> #DIV/0! | T22: =M22/H22 -> #DIV/0!
A23: GRANDE COTE OPERATIONS | B23: THIES | C23: Ilménite | D23: 0 | E23: 526747 | F23: 0 | G23: =29059+2426+0 -> 31485 | H23: =865+1633 -> 2498 | I23: 0 | J23: 109536232 | K23: 0 | L23: 2176655 | M23: 217218 | N23: =+D23+E23+H23-G23 -> 497760 | O23: =+I23+J23+M23-L23 -> 107576795 | Q23: =I23/D23 -> #DIV/0! | R23: =J23/E23 -> 207.94847 | S23: =L23/G23 -> 69.133079 | T23: =M23/H23 -> 86.956765
A24: GRANDE COTE OPERATIONS | B24: THIES | C24: Zircon | D24: =0 -> 0 | E24: 90745 | F24: 0 | G24: 8549 | H24: 1869 | I24: 0 | J24: 88151983 | K24: 0 | L24: 1516900 | M24: 334527 | N24: =+D24+E24+H24-G24 -> 84065 | O24: =+I24+J24+M24-L24 -> 86969610 | P24: =O24/N24 -> 1034.552 | Q24: =I24/D24 -> #DIV/0! | R24: =J24/E24 -> 971.42524 | S24: =L24/G24 -> 177.43596 | T24: =M24/H24 -> 178.98716
A25: GRANDE COTE OPERATIONS | B25: THIES | C25: Rutile | D25: 0 | E25: 4160 | F25: 0 | G25: 34 | H25: 77 | I25: 0 | J25: 5290813 | K25: 0 | L25: 12483 | M25: 35816 | N25: =+D25+E25+H25-G25 -> 4203 | O25: =+I25+J25+M25-L25 -> 5314146 | Q25: =I25/D25 -> #DIV/0! | R25: =J25/E25 -> 1271.83 | S25: =L25/G25 -> 367.14706 | T25: =M25/H25 -> 465.14286
A26: GRANDE COTE OPERATIONS | B26: THIES | C26: Leucoxene | D26: 0 | E26: 6340 | F26: 0 | G26: 75 | H26: 19 | I26: 0 | J26: 5532815 | K26: 0 | L26: 19731 | M26: 6682 | N26: =+D26+E26+H26-G26 -> 6284 | O26: =+I26+J26+M26-L26 -> 5519766 | Q26: =I26/D26 -> #DIV/0! | R26: =J26/E26 -> 872.68375 | S26: =L26/G26 -> 263.08 | T26: =M26/H26 -> 351.68421
A27: GROUPEMENT D'ENTREPRISE SINTRAM HOUAR | B27: THIES | C27: Basalte | D27: 53521 | E27: 0 | F27: 0 | G27: 0 | H27: 0 | I27: 182334 | J27: 0 | K27: 0 | L27: 0 | M27: 0 | N27: =+D27+E27+H27-G27 -> 53521 | O27: =+I27+J27+M27-L27 -> 182334 | P27: =+O27/N27 -> 3.4067749 | Q27: =I27/D27 -> 3.4067749 | R27: =J27/E27 -> #DIV/0! | S27: =L27/G27 -> #DIV/0! | T27: =M27/H27 -> #DIV/0!
A28: INCA SARL | B28: THIES | C28: Calcaire | N28: =+D28+E28+H28-G28 -> 0 | O28: =+I28+J28+M28-L28 -> 0 | P28: =O28/N28 -> #DIV/0! | R28: =J28/E28 -> #DIV/0! | S28: =L28/G28 -> #DIV/0! | T28: =M28/H28 -> #DIV/0!
A29: INDUSTRIES CHIMIQUES DU SENEGAL | B29: THIES | C29: Phosphates | D29: 0 | E29: 0 | F29: 0 | G29: 180608 | H29: 33590 | I29: 0 | J29: 0 | K29: 0 | L29: 4946108 | M29: 1053777 | N29: =G29-H29 -> 147018 | O29: =L29-M29 -> 3892331 | P29: =+O29/N29 -> 26.4752 | Q29: =I29/D29 -> #DIV/0! | R29: =J29/E29 -> #DIV/0! | S29: =L29/G29 -> 27.385874 | T29: =M29/H29 -> 31.371748
A30: INDUSTRIES CHIMIQUES DU SENEGAL | B30: THIES | C30: Acide phosphorique | D30: 7 | E30: 558410 | F30: 0 | G30: 56345 | H30: 43178 | I30: 6289 | J30: 533842674 | K30: 0 | L30: 16652848 | M30: 18650398 | N30: =+D30+E30+H30-G30 -> 545250 | O30: =+I30+J30+M30-L30 -> 535846513 | P30: =+O30/N30 -> 982.75381 | Q30: =I30/D30 -> 898.42857 | R30: =J30/E30 -> 956.00486 | S30: =L30/G30 -> 295.55148 | T30: =M30/H30 -> 431.94215
A31: INDUSTRIES CHIMIQUES DU SENEGAL | B31: THIES | C31: Engrais | D31: 76545 | E31: 12318 | F31: 0 | G31: 31084 | H31: 25222 | I31: 27574026 | J31: 3328965 | K31: 0 | L31: 7024386 | M31: 6142778 | N31: =+D31+E31+H31-G31 -> 83001 | O31: =+I31+J31+M31-L31 -> 30021383 | P31: =+O31/N31 -> 361.69905 | Q31: =I31/D31 -> 360.23288 | R31: =J31/E31 -> 270.25207 | S31: =L31/G31 -> 225.98076 | T31: =M31/H31 -> 243.54841
A32: KUTLU GABANE HOLDING S.A | B32: THIES | C32: Basalte | D32: 117925.4 | E32: 0 | F32: 0 | G32: 0 | H32: 0 | I32: 963311.8 | J32: 0 | K32: 0 | L32: 0 | M32: 0 | N32: =+D32+E32+H32-G32 -> 117925.4 | O32: =+I32+J32+M32-L32 -> 963311.8 | P32: =+O32/N32 -> 8.1688237 | Q32: =I32/D32 -> 8.1688237 | R32: =J32/E32 -> #DIV/0! | S32: =L32/G32 -> #DIV/0! | T32: =M32/H32 -> #DIV/0!
A33: PETOWAL MINING COMPANY (PMC) SA | B33: KEDOUGOU | C33: Argent | E33: 0.35442419 | J33: 152394.41 | N33: =+D33+E33+H33-G33 -> 0.35442419 | O33: =+I33+J33+M33-L33 -> 152394.41 | Q33: =I33/D33 -> #DIV/0! | R33: =J33/E33 -> 429977.45 | S33: =L33/G33 -> #DIV/0! | T33: =M33/H33 -> #DIV/0!
A34: PETOWAL MINING COMPANY (PMC) SA | B34: KEDOUGOU | C34: Or | D34: 0 | E34: 4.0319337 | F34: 0 | G34: 0.13974758 | H34: 0.12304505 | I34: 0 | J34: 147862816 | K34: 0 | L34: 2874527 | M34: 2730952 | N34: =+D34+E34+H34-G34 -> 4.0152312 | O34: =+I34+J34+M34-L34 -> 147719241 | Q34: =I34/D34 -> #DIV/0! | R34: =J34/E34 -> 36672928 | S34: =L34/G34 -> 20569423 | T34: =M34/H34 -> 22194733
A35: PROCHIMAT SA | B35: THIES | C35: Attapulgite | D35: 1775 | E35: 9235 | G35: 309 | H35: 240 | I35: 129907 | J35: =575697.785+43946.217 -> 619644 | L35: 2096.228 | M35: 34922.894 | N35: =+D35+E35+H35-G35 -> 10941 | O35: =+I35+J35+M35-L35 -> 782377.67 | Q35: =I35/D35 -> 73.187042 | R35: =J35/E35 -> 67.097347 | S35: =L35/G35 -> 6.7839094 | T35: =M35/H35 -> 145.51206
A36: ROYAL SENEGAL MINES ET EQUIPEMENTS | B36: THIES | C36: Calcaire | D36: 57288 | E36: 0 | F36: 0 | G36: 0 | H36: 0 | I36: 260400 | J36: 0 | K36: 0 | L36: 0 | M36: 0 | N36: =+D36+E36+H36-G36 -> 57288 | O36: =+I36+J36+M36-L36 -> 260400 | P36: =O36/N36 -> 4.5454545 | Q36: =I36/D36 -> 4.5454545 | R36: =J36/E36 -> #DIV/0! | S36: =L36/G36 -> #DIV/0! | T36: =M36/H36 -> #DIV/0!
A37: SABODALA GOLD OPERATIONS | B37: KEDOUGOU | C37: Or | D37: 0.25 | E37: 10.64 | F37: 0 | G37: 0.3 | H37: 0.27 | I37: 9028238 | J37: 383558467 | K37: 0 | L37: 1055660 | M37: 2080075 | N37: =+D37+E37+H37-G37 -> 10.86 | O37: =+I37+J37+M37-L37 -> 393611120 | Q37: =I37/D37 -> 36112952 | R37: =J37/E37 -> 36048728 | S37: =L37/G37 -> 3518866.7 | T37: =M37/H37 -> 7703981.5
A38: SABODALA GOLD OPERATIONS | B38: KEDOUGOU | C38: Argent | D38: 0 | E38: 0.85 | F38: 0 | G38: 0 | H38: 0 | I38: 0 | J38: 374908 | K38: 0 | L38: 0 | M38: 0 | N38: =+D38+E38+H38-G38 -> 0.85 | O38: =+I38+J38+M38-L38 -> 374908 | Q38: =I38/D38 -> #DIV/0! | R38: =J38/E38 -> 441068.24 | S38: =L38/G38 -> #DIV/0! | T38: =M38/H38 -> #DIV/0!
A39: SENEGAL MINES | B39: THIES | C39: Hormite | D39: 0 | E39: 20360 | G39: =4599+386 -> 4985 | H39: =1020+386 -> 1406 | I39: 0 | J39: 1335507 | L39: =204952+26315 -> 231267 | M39: =55097+30902 -> 85999 | N39: =+D39+E39+H39-G39 -> 16781 | O39: =+I39+J39+M39-L39 -> 1190239 | R39: =J39/E39 -> 65.594646 | S39: =L39/G39 -> 46.392578 | T39: =M39/H39 -> 61.165718
A40: SENEGAL MINES | B40: THIES | C40: Attapulgite | D40: 80.14 | E40: 9150 | G40: 335 | H40: 694 | I40: 6345 | J40: 430330 | L40: 60416 | M40: 18195 | N40: =+D40+E40+H40-G40 -> 9589.14 | O40: =+I40+J40+M40-L40 -> 394454 | Q40: =I40/D40 -> 79.173946 | R40: =J40/E40 -> 47.030601 | S40: =L40/G40 -> 180.34627 | T40: =M40/H40 -> 26.217579
A41: SEN-HMC SUARL | B41: SAINT-LOUIS | C41: Minéraux lourds | D41: 0 | E41: 9099 | F41: 0 | G41: 0 | H41: 0 | I41: 0 | J41: 2225609 | K41: 0 | L41: 0 | M41: 0 | N41: =+D41+E41+H41-G41 -> 9099 | O41: =+I41+J41+M41-L41 -> 2225609 | P41: =O41/N41 -> 244.5993 | Q41: =I41/D41 -> #DIV/0! | R41: =J41/E41 -> 244.5993 | S41: =L41/G41 -> #DIV/0! | T41: =M41/H41 -> #DIV/0!
A42: SEPHOS SENEGAL SA | B42: THIES | C42: Phosphates | D42: 3336 | E42: 48907 | F42: 0 | G42: 11363 | H42: 28472 | I42: 171436 | J42: 6751500.6 | K42: 0 | L42: 484143 | M42: 2489351 | N42: =+D42+E42+H42-G42 -> 69352 | O42: =+I42+J42+M42-L42 -> 8928144.6 | P42: =+O42/N42 -> 128.73666 | Q42: =I42/D42 -> 51.389688 | R42: =J42/E42 -> 138.04773 | S42: =L42/G42 -> 42.60697 | T42: =M42/H42 -> 87.431547
A43: SERIGNE SALIOU MBACKE SUARL | B43: KEDOUGOU | C43: Or | D43: 0.023 | E43: 0 | F43: 0 | G43: 0 | H43: 0 | I43: 460000 | J43: 0 | K43: 0 | L43: 0 | M43: 0 | N43: =+D43+E43+H43-G43 -> 0.023 | O43: =+I43+J43+M43-L43 -> 460000 | Q43: =I43/D43 -> 20000000 | R43: =J43/E43 -> #DIV/0! | S43: =L43/G43 -> #DIV/0! | T43: =M43/H43 -> #DIV/0!
A44: SOCIETE DE CONCASSAGE ET DU BETON (SOCOBE) | B44: THIES | C44: Silex | D44: 126962 | G44: 133333 | H44: 222979 | I44: 941421 | L44: 315537 | M44: 614319 | N44: =+D44+E44+H44-G44 -> 216608 | O44: =+I44+J44+M44-L44 -> 1240203 | P44: =+O44/N44 -> 5.7255642 | Q44: =I44/D44 -> 7.4149824 | R44: =J44/E44 -> #DIV/0! | S44: =L44/G44 -> 2.3665334 | T44: =M44/H44 -> 2.7550532
A45: SOCIETE DE MANUFACTURE DE PRODUCTION INDUSTRIELLE DU SENEGAL (SOMAPIS) | B45: THIES | C45: Silex | N45: =+D45+E45+H45-G45 -> 0 | O45: =+I45+J45+M45-L45 -> 0 | Q45: =I45/D45 -> #DIV/0! | R45: =J45/E45 -> #DIV/0! | S45: =L45/G45 -> #DIV/0! | T45: =M45/H45 -> #DIV/0!
A46: SOCIETE MINIERE DE LA VALLEE DU FLEUVE SENEGAL – SOMIVA | B46: MATAM | C46: Phosphates | D46: 182602 | E46: 366954 | F46: 0 | G46: 699456 | H46: 944240 | I46: 15367232 | J46: 41075747 | K46: 0 | L46: 21455426 | M46: 21864808 | N46: =+D46+E46+H46-G46 -> 794340 | O46: =+I46+J46+M46-L46 -> 56852361 | P46: =+O46/N46 -> 71.571822 | Q46: =I46/D46 -> 84.156975 | R46: =J46/E46 -> 111.93705 | S46: =L46/G46 -> 30.674447 | T46: =M46/H46 -> 23.155986
A47: SOCIETE SENEGALAISE DES PHOSPHATES DE THIES | B47: THIES | C47: Attapulgite | D47: 4228 | E47: 140727.69 | F47: 144955.69 | G47: 9285.33 | H47: 9359 | I47: 220537 | J47: 3353828 | K47: 3564774 | L47: 120726 | M47: 71466 | N47: =+D47+E47+H47-G47 -> 145029.36 | O47: =+I47+J47+M47-L47 -> 3525105 | Q47: =I47/D47 -> 52.161069 | R47: =J47/E47 -> 23.83204 | S47: =L47/G47 -> 13.0018 | T47: =M47/H47 -> 7.6360722
A48: SOCOCIM INDUSTRIES | B48: DAKAR | C48: Ciment | D48: =3192851.27 -> 3192851.3 | E48: 181550.87 | F48: 0 | G48: 13976 | H48: 10269 | I48: 151849279 | J48: 8241341 | K48: 0 | L48: 606173 | M48: 487189 | N48: =+D48+E48+H48-G48 -> 3370695.1 | O48: =+I48+J48+M48-L48 -> 159971636 | P48: =O48/N48 -> 47.459539 | Q48: =I48/D48 -> 47.559146 | R48: =J48/E48 -> 45.394115 | S48: =L48/G48 -> 43.372424 | T48: =M48/H48 -> 47.442692
A49: SOCOCIM INDUSTRIES | B49: DAKAR | C49: Clinker | D49: 0 | E49: 13645.85 | F49: 0 | G49: 2026.3 | H49: 10399.61 | I49: 0 | J49: 504795 | K49: 0 | L49: 52936 | M49: 384708 | N49: =+D49+E49+H49-G49 -> 22019.16 | O49: =+I49+J49+M49-L49 -> 836567 | Q49: =I49/D49 -> #DIV/0! | R49: =J49/E49 -> 36.992566 | S49: =L49/G49 -> 26.124463 | T49: =M49/H49 -> 36.992541
A50: SODEVCO | B50: THIES | C50: Calcaire | D50: 60940 | E50: 0 | F50: 0 | G50: 0 | H50: 0 | I50: 277000 | J50: 0 | K50: 0 | L50: 0 | M50: 0 | N50: =+D50+E50+H50-G50 -> 60940 | O50: =+I50+J50+M50-L50 -> 277000 | P50: =O50/N50 -> 4.5454545 | Q50: =I50/D50 -> 4.5454545 | R50: =J50/E50 -> #DIV/0! | S50: =L50/G50 -> #DIV/0! | T50: =M50/H50 -> #DIV/0!
A51: SORED MINES SA | B51: KEDOUGOU | C51: Or | D51: 0 | E51: 0 | F51: 0 | G51: 0 | N51: =+D51+E51+H51-G51 -> 0 | O51: =+I51+J51+M51-L51 -> 0 | Q51: =I51/D51 -> #DIV/0! | R51: =J51/E51 -> #DIV/0! | S51: =L51/G51 -> #DIV/0! | T51: =M51/H51 -> #DIV/0!
A52: SWAMI MINES SA | B52: THIES | C52: Silex | D52: 166196.61 | E52: 0 | F52: 0 | G52: 0 | H52: 0 | I52: 1321444.7 | N52: =+D52+E52+H52-G52 -> 166196.61 | O52: =+I52+J52+M52-L52 -> 1321444.7 | P52: =+O52/N52 -> 7.9510929 | Q52: =I52/D52 -> 7.9510929 | R52: =J52/E52 -> #DIV/0! | S52: =L52/G52 -> #DIV/0! | T52: =M52/H52 -> #DIV/0!
A53: TALIX-MINES | B53: THIES | C53: Basalte | D53: =31758+16787+54572+152026+8030+60 -> 263233 | E53: 8030 | I53: 2313840 | J53: =1622+9245+1540+6738+54555 -> 73700 | N53: =+D53+E53+H53-G53 -> 271263 | O53: =+I53+J53+M53-L53 -> 2387540 | P53: =+O53/N53 -> 8.801569 | Q53: =I53/D53 -> 8.7900833 | R53: =J53/E53 -> 9.1780822 | S53: =L53/G53 -> #DIV/0! | T53: =M53/H53 -> #DIV/0!
A54: TANOR SAS | B54: THIES | C54: Silex | D54: 120770 | E54: 0 | F54: 0 | G54: 0 | H54: 14.7 | I54: 716405 | J54: 0 | K54: 0 | L54: 0 | M54: 87200 | N54: =+D54+E54+H54-G54 -> 120784.7 | O54: =+I54+J54+M54-L54 -> 803605 | P54: =+O54/N54 -> 6.6532019 | Q54: =I54/D54 -> 5.9319781 | R54: =J54/E54 -> #DIV/0! | S54: =L54/G54 -> #DIV/0! | T54: =M54/H54 -> 5931.9728
A55: CARRIERES ET SABLES | B55: THIES | C55: Calcaire | D55: 46944 | E55: 0 | G55: 0 | H55: 0 | I55: 371976 | J55: 0 | L55: 0 | M55: 0 | N55: =+D55+E55+H55-G55 -> 46944 | O55: =+I55+J55+M55-L55 -> 371976 | P55: =+O55/N55 -> 7.9238241
A56: VAPROM AFRICA SA | B56: THIES | C56: Calcaire | D56: 609343 | E56: 0 | F56: 0 | G56: 0 | H56: 0 | I56: 609343 | J56: 0 | K56: 0 | L56: 0 | M56: 0 | N56: =+D56+E56+H56-G56 -> 609343 | O56: =+I56+J56+M56-L56 -> 609343 | P56: =(I56+J56)/(D56+E56) -> 1 | Q56: =I56/D56 -> 1 | R56: =J56/E56 -> #DIV/0! | S56: =L56/G56 -> #DIV/0! | T56: =M56/H56 -> #DIV/0!
D58: =SUBTOTAL(9,D2:D56) -> 16188983 | E58: =SUBTOTAL(9,E2:E56) -> 3563416.5 | F58: =SUBTOTAL(9,F2:F56) -> 2319365.7 | G58: =SUBTOTAL(9,G2:G56) -> 1841069.5 | H58: =SUBTOTAL(9,H2:H56) -> 2079181.5 | I58: =SUBTOTAL(9,I2:I56) -> 4.1774684e+08 | J58: =SUBTOTAL(9,J2:J56) -> 1.4075199e+09 | K58: =SUBTOTAL(9,K2:K56) -> 61642440 | ... O58: =SUBTOTAL(9,O2:O56) -> 1.8337643e+09 | P58: =O58/N58 -> 90.402032
F59: =SUM(F2:F2) -> 0 | K59: =SUM(K2:K2) -> 0
D60: =I11/D11 -> 6.9635991 | E60: =J11/E11 -> 8.143653 | L60: =L46/G46 -> 30.674447
D63: pays | E63: etger | F63: =SUM(F60:F62) -> 0
D64: 26062 | E64: 1641
D65: 41522 | E65: 1062
D66: 16095 | E66: 346
D67: 116107 | E67: 4356
D68: 5523
D69: 120
D70: =SUBTOTAL(9,D64:D69) -> 205429 | E70: =SUBTOTAL(9,E64:E69) -> 7405

Sheet PRODUCTION
A3: Étiquettes de lignes | B3: Somme de PRODUCTION EN QUANTITE | E3: Étiquettes de lignes | F3: Somme de qte_brute | K3: Substance | L3: 2019 | M3: 2020 | N3: 2021 | O3: 2020/ 2021
A4: Argent | B4: 1.2044242 | E4: Argile | F4: 556799 | K4: Argent | L4: 0.5 | M4: 1 | N4: 1.3 | O4: 31,8%
A5: Attapulgite | B5: 165559.5 | E5: Calcaire | F5: 5193843 | K5: Argile | L5: 433483 | M5: 418052 | N5: 670650 | O5: 60,4%
A6: Basalte | B6: 6352766.3 | E6: Latérite | F6: 224778 | K6: Attapulgite | L6: 197673 | M6: 201919 | N6: 193438 | O6: -4,2%
A7: Calcaire | B7: 2416753.7 | E7: Marne | F7: 1990935 | K7: Basalte | L7: 3613673 | M7: 3700409 | N7: 5415020 | O7: 46,3%
A8: Grès | B8: 79811 | E8: Phosphate de chaux | F8: 1771000 | K8: Calcaire | L8: 5944543 | M8: 6558606 | N8: 7471837 | O8: 13,9%
A9: Hormite | B9: 16781 | E9: Total général | F9: 9737355 | K9: Grès | N9: 86431
A10: Ilménite | B10: 497760 | K10: Hormite | L10: 11213 | M10: 29603 | N10: 18988 | O10: -35,9%
A11: Latérite | B11: 0 | K11: Ilménite | L11: 492282 | M11: 521440 | N11: 543062 | O11: 4,1%
A12: Leucoxene | B12: 6284 | F12: 5193843 | K12: Latérite | L12: 139552 | M12: 260571 | N12: 293165 | O12: 12,5%
A13: Manganèse | B13: 36090.85 | K13: Leucoxène | L13: 6515 | M13: 5501 | N13: 6985 | O13: 27,0%
A14: Minéraux lourds | B14: 9099 | K14: Manganèse | L14: 4368 | M14: 15376 | N14: 9236 | O14: -39,9%
A15: Or | B15: 14.946701 | F15: =+F12/B29 -> 0.68244885 | K15: Marne | L15: 1617455 | M15: 1845762 | N15: 1965915 | O15: 6,5%
A16: Phosphates | B16: 1088462 | K16: Minéraux lourds | M16: 682 | N16: 1812 | O16: 165,7%
A17: Rutile | B17: 4203 | K17: Or | L17: 13 | M17: 12.4 | N17: 16.2 | O17: 35,0%
A18: Silex | B18: 884708.31 | K18: Phosphates | L18: 2295975 | M18: 2230504 | N18: 2500344 | O18: 12,1%
A19: Zircon | B19: 84065 | K19: Rutile | L19: 3614 | M19: 4044 | N19: 4431 | O19: 9,6%
A20: Total général | B20: 11642360 | K20: Silex | L20: 98355 | M20: 297611 | N20: 888095 | O20: 298,4%
K21: Zircon | L21: 80721 | M21: 84376 | N21: 90706 | O21: 7,5%
L22: =SUM(L17:L21) -> 2478678 | M22: =SUM(M17:M21) -> 2616547.4 | N22: =SUM(N17:N21) -> 3483592.2 | O22: =SUM(O17:O21) -> 0
A24: Production par substance (en tonnes) 2022
A25: Argent | B25: =+B4 -> 1.2044242 | E25: Substance | F25: 2019 | G25: 2020 | H25: 2021 | I25: 2022
A26: Argile | B26: =+F4 -> 556799 | E26: Argent | F26: 0.5 | G26: 1 | H26: 1.3 | I26: =+B25 -> 1.2044242 | J26: =+I26/H26-1 -> -0.073519853
A27: Attapulgite | B27: =+B5 -> 165559.5 | E27: Argile | F27: 433483 | G27: 418052 | H27: 670650 | I27: =+B26 -> 556799 | J27: =+I27/H27-1 -> -0.16976217
A28: Basalte | B28: =+B6 -> 6352766.3 | E28: Attapulgite | F28: 197673 | G28: 201919 | H28: 193438 | I28: =+B27 -> 165559.5 | J28: =+I28/H28-1 -> -0.14412111
A29: Calcaire | B29: =+B7+F5 -> 7610596.7 | E29: Basalte | F29: 3613673 | G29: 3700409 | H29: 5415020 | I29: =+B28 -> 6352766.3 | J29: =+I29/H29-1 -> 0.17317505
A30: Grès | B30: =+B8 -> 79811 | E30: Calcaire | F30: 5944543 | G30: 6558606 | H30: 7471837 | I30: =+B29 -> 7610596.7 | J30: =+I30/H30-1 -> 0.018571029
A31: Hormite | B31: =+B9 -> 16781 | E31: Grès | H31: 86431 | I31: =+B30 -> 79811 | J31: =+I31/H31-1 -> -0.076592889
A32: Ilménite | B32: =+B10 -> 497760 | E32: Hormite | F32: 11213 | G32: 29603 | H32: 18988 | I32: =+B31 -> 16781 | J32: =+I32/H32-1 -> -0.1162313
A33: Latérite | B33: =+B11+F6 -> 224778 | E33: Ilménite | F33: 492282 | G33: 521440 | H33: 543062 | I33: =+B32 -> 497760 | J33: =+I33/H33-1 -> -0.083419573
A34: Leucoxène | B34: =+B12 -> 6284 | E34: Latérite | F34: 139552 | G34: 260571 | H34: 293165 | I34: =+B33 -> 224778 | J34: =+I34/H34-1 -> -0.23327137
A35: Manganèse | B35: =+B13 -> 36090.85 | E35: Leucoxène | F35: 6515 | G35: 5501 | H35: 6985 | I35: =+B34 -> 6284 | J35: =+I35/H35-1 -> -0.10035791
A36: Marne | B36: =+F7 -> 1990935 | E36: Manganèse | F36: 4368 | G36: 15376 | H36: 9236 | I36: =+B35 -> 36090.85 | J36: =+I36/H36-1 -> 2.9076278
A37: Minéraux lourds | B37: =+B14 -> 9099 | E37: Marne | F37: 1617455 | G37: 1845762 | H37: 1965915 | I37: =+B36 -> 1990935 | J37: =+I37/H37-1 -> 0.012726898
A38: Or | B38: =+B15 -> 14.946701 | E38: Minéraux lourds | G38: 682 | H38: 1812 | I38: =+B37 -> 9099 | J38: =+I38/H38-1 -> 4.0215232
A39: Phosphates | B39: =+B16+F8 -> 2859462 | E39: Or | F39: 13 | G39: 12.4 | H39: 16.2 | I39: =+B38 -> 14.946701 | J39: =+I39/H39-1 -> -0.077364122
A40: Rutile | B40: =+B17 -> 4203 | E40: Phosphates | F40: 2295975 | G40: 2230504 | H40: 2500344 | I40: =+B39 -> 2859462 | J40: =+I40/H40-1 -> 0.14362744
A41: Silex | B41: =+B18 -> 884708.31 | E41: Rutile | F41: 3614 | G41: 4044 | H41: 4431 | I41: =+B40 -> 4203 | J41: =+I41/H41-1 -> -0.051455653
A42: Zircon | B42: =+B19 -> 84065 | E42: Silex | F42: 98355 | G42: 297611 | H42: 888095 | I42: =+B41 -> 884708.31 | J42: =+I42/H42-1 -> -0.0038134321
B43: =SUM(B25:B42) -> 21379715 | E43: Zircon | F43: 80721 | G43: 84376 | H43: 90706 | I43: =+B42 -> 84065 | J43: =+I43/H43-1 -> -0.073214561
A46: Production en valeur par substance (en milliards)
A47: Étiquettes de lignes | B47: Somme de PRODUCTION EN VALEUR | E47: Étiquettes de lignes | F47: Somme de Cout de production/qte | G47: Somme de cout_production
A48: Argent | B48: 527302.41 | E48: Argile | F48: 5.7897244 | G48: 1710855
A49: Attapulgite | B49: 4701936.7 | E49: Calcaire | F49: 5.9118996 | G49: 10322170
A50: Basalte | B50: 45863195 | E50: Latérite | F50: 8.9644752 | G50: 727038
A51: Calcaire | B51: 7144906.2 | E51: Marne | F51: 2.1949998 | G51: 4370102
A52: Grès | B52: 576403.82 | E52: Phosphate de chaux | F52: 31.84281 | G52: 56393616
A53: Hormite | B53: 1190239 | E53: Total général | F53: 54.703909 | G53: 73523781
A54: Ilménite | B54: 107576795
A55: Latérite | B55: 0
A56: Leucoxene | B56: 5519766
A57: Manganèse | B57: 1263388
A58: Minéraux lourds | B58: 2225609
A59: Or | B59: 543404837
A60: Phosphates | B60: 73638443
A61: Rutile | B61: 5314146
A62: Silex | B62: 6223886.9
A63: Zircon | B63: 86969610
A64: Total général | B64: 8.9214046e+08
A66: Production en valeur par substance (en milliers FCFA)
A67: Substance | B67: 2022 | E67: SUBSTANCES | F67: 2019 | G67: 2020 | H67: 2021 | I67: 2022 | J67: STRUCTURE 2022 (%) | K67: 2021/2022 (%)
A68: Argent | B68: =+B48 -> 527302.41 | E68: Argent | F68: 0.2 | G68: 0.4 | H68: 0.6 | I68: =B68/1000000 -> 0.52730241 | J68: =I68/$I$86 -> 0.0005460515 | K68: =I68/H68-1 -> -0.12116265 | L68: =I68-[2]PRODUCTION!I68 -> 0
A69: Argile | B69: =G48 -> 1710855 | E69: Argile | F69: 1.4 | G69: 1.3 | H69: 1.9 | I69: =B69/1000000 -> 1.710855 | J69: =I69/$I$86 -> 0.0017716872 | K69: =I69/H69-1 -> -0.09955 | L69: =I69-[2]PRODUCTION!I69 -> 0
A70: Attapulgite | B70: =B49 -> 4701936.7 | E70: Attapulgite | F70: 8.1 | G70: 9.4 | H70: 8.4 | I70: =B70/1000000 -> 4.7019367 | J70: =I70/$I$86 -> 0.0048691216 | K70: =I70/H70-1 -> -0.44024563 | L70: =I70-[2]PRODUCTION!I70 -> 0
A71: Basalte | B71: =B50 -> 45863195 | E71: Basalte | F71: 29.2 | G71: 28.2 | H71: 41.6 | I71: =B71/1000000 -> 45.863195 | J71: =I71/$I$86 -> 0.047493935 | K71: =I71/H71-1 -> 0.10248064 | L71: =I71-[2]PRODUCTION!I71 -> 2.38754
A72: Calcaire | B72: =B51+G49 -> 17467076 | E72: Calcaire | F72: 15.5 | G72: 15.9 | H72: 15 | I72: =B72/1000000 -> 17.467076 | J72: =I72/$I$86 -> 0.018088146 | K72: =I72/H72-1 -> 0.16447175 | L72: =I72-[2]PRODUCTION!I72 -> 0.371976
A73: Grès | B73: =B52 -> 576403.82 | E73: Grès | F73: 0.6 | G73: 0.1 | H73: 0.6 | I73: =B73/1000000 -> 0.57640382 | J73: =I73/$I$86 -> 0.00059689879 | K73: =I73/H73-1 -> -0.03932697 | L73: =I73-[2]PRODUCTION!I73 -> 0.57640382
A74: Hormite | B74: =B53 -> 1190239 | E74: Hormite | F74: 0.7 | G74: 1.1 | H74: 0.3 | I74: =B74/1000000 -> 1.190239 | J74: =I74/$I$86 -> 0.0012325599 | K74: =I74/H74-1 -> 2.9674633 | L74: =I74-[2]PRODUCTION!I74 -> 0
A75: Ilménite | B75: =B54 -> 107576795 | E75: Ilménite | F75: 49.6 | G75: 58.8 | H75: 77.4 | I75: =B75/1000000 -> 107.5768 | J75: =I75/$I$86 -> 0.11140186 | K75: =I75/H75-1 -> 0.38988107 | L75: =I75-[2]PRODUCTION!I75 -> 0
A76: Latérite | B76: =G50 -> 727038 | E76: Latérite | F76: 0.4 | G76: 0.5 | H76: 1.4 | I76: =B76/1000000 -> 0.727038 | J76: =I76/$I$86 -> 0.00075288901 | K76: =I76/H76-1 -> -0.48068714 | L76: =I76-[2]PRODUCTION!I76 -> 0
A77: Leucoxène | B77: =B56 -> 5519766 | E77: Leucoxène | F77: 2.6 | G77: 2.3 | H77: 3.6 | I77: =B77/1000000 -> 5.519766 | J77: =I77/$I$86 -> 0.0057160302 | K77: =I77/H77-1 -> 0.53326833 | L77: =I77-[2]PRODUCTION!I77 -> 0
A78: Manganèse | B78: =B57 -> 1263388 | E78: Manganèse | F78: 0.5 | G78: 0.4 | H78: 0.5 | I78: =B78/1000000 -> 1.263388 | J78: =I78/$I$86 -> 0.0013083098 | K78: =I78/H78-1 -> 1.526776 | L78: =I78-[2]PRODUCTION!I78 -> 0
A79: Marne | B79: =G51 -> 4370102 | E79: Marne | F79: 3.6 | G79: 4.1 | H79: 4.3 | I79: =B79/1000000 -> 4.370102 | J79: =I79/$I$86 -> 0.0045254881 | K79: =I79/H79-1 -> 0.016302791 | L79: =I79-[2]PRODUCTION!I79 -> 0
A80: Minéraux lourds | B80: =B58 -> 2225609 | E80: Minéraux lourds | F80: 0.1 | G80: 0.2 | H80: 0.03 | I80: =B80/1000000 -> 2.225609 | J80: =I80/$I$86 -> 0.0023047441 | K80: =I80/H80-1 -> 73.186967 | L80: =I80-[2]PRODUCTION!I80 -> 0
A81: Or | B81: =B59 -> 543404837 | E81: Or | F81: 339.6 | G81: 387.7 | H81: 512.4 | I81: =B81/1000000 -> 543.40484 | J81: =I81/$I$86 -> 0.56272648 | K81: =I81/H81-1 -> 0.06050905 | L81: =I81-[2]PRODUCTION!I81 -> 0
A82: Phosphates | B82: =B60+G52 -> 1.3003206e+08 | E82: Phosphates | F82: 85 | G82: 66.2 | H82: 79.5 | I82: =B82/1000000 -> 130.03206 | J82: =I82/$I$86 -> 0.13465556 | K82: =I82/H82-1 -> 0.63562338 | L82: =I82-[2]PRODUCTION!I82 -> 0
A83: Rutile | B83: =B61 -> 5314146 | E83: Rutile | F83: 2.4 | G83: 2.8 | H83: 3.6 | I83: =B83/1000000 -> 5.314146 | J83: =I83/$I$86 -> 0.0055030991 | K83: =I83/H83-1 -> 0.47615167 | L83: =I83-[2]PRODUCTION!I83 -> 0
A84: Silex | B84: =B62 -> 6223886.9 | E84: Silex | F84: 0.9 | G84: 2 | H84: 5.3 | I84: =B84/1000000 -> 6.2238869 | J84: =I84/$I$86 -> 0.0064451873 | K84: =I84/H84-1 -> 0.17431828 | L84: =I84-[2]PRODUCTION!I84 -> 0.38631478
A85: Zircon | B85: =B63 -> 86969610 | E85: Zircon | F85: 58.4 | G85: 50.2 | H85: 62 | I85: =B85/1000000 -> 86.96961 | J85: =I85/$I$86 -> 0.090061955 | K85: =I85/H85-1 -> 0.40273565 | L85: =I85-[2]PRODUCTION!I85 -> 0
A86: TOTAL | B86: =SUM(B68:B85) -> 9.6566424e+08 | C86: =B86+C155 -> 1.9072881e+09 | E86: TOTAL | F86: 598.1 | G86: 631.4 | H86: 816.1 | I86: =B86/1000000 -> 965.66424 | J86: =I86/$I$86 -> 1 | K86: =I86/H86-1 -> 0.18326706 | L86: =I86-[2]PRODUCTION!I86 -> 3.7222346
C87: 961.9
C88: 816.1
A89: produit_desc_ok | B89: (Plusieurs éléments) | C89: =C87/C88-1 -> 0.17865458
A90: Répartition de la production minière par région en 2022
A91: Étiquettes de lignes | B91: Somme de PRODUCTION EN VALEUR | E91: Étiquettes de lignes | F91: Somme de cout_production
A92: DIOURBEL | B92: 3965606 | E92: DAKAR | F92: 6747790
A93: KEDOUGOU | B93: 5.4393214e+08 | E93: THIES | F93: 66775991 | I93: Silex | J93: 98355 | K93: 297611 | L93: 888095 | M93: 841210.31
A94: MATAM | B94: 56852361 | E94: Total général | F94: 73523781 | I94: Silex | J94: 0.9 | K94: 2 | L94: 2.6 | M94: 5.8375721
A95: SAINT-LOUIS | B95: 2225609 | J95: =J94/J93 -> 9.1505262e-06 | K95: =K94/K93 -> 6.7201817e-06 | L95: =L94/L93 -> 2.9276147e-06 | M95: =M94/M93 -> 6.9394919e-06
A96: TAMBACOUNDA | B96: 1740741.1
A97: THIES | B97: 2.8342401e+08
A98: Total général | B98: 8.9214046e+08
A103: Région | B103: Production en valeur (en milliers FCFA) | C103: % | D103: Région | E103: Production en valeur (en milliers FCFA) | F103: %
A104: DAKAR | B104: =F92 -> 6747790 | C104: =B104/$B$111 -> 0.0069877186 | D104: AUTRES REGIONS | E104: =+B111-E105-E106 -> 71532107 | F104: =1-F105-F106 -> 0.074075547
A105: DIOURBEL | B105: =B92 -> 3965606 | C105: =B105/$B$111 -> 0.0041066095 | D105: KEDOUGOU | E105: =+B106 -> 5.4393214e+08 | F105: =+C106 -> 0.56327253
A106: KEDOUGOU | B106: =B93 -> 5.4393214e+08 | C106: =B106/$B$111 -> 0.56327253 | D106: THIES | E106: =+B110 -> 3.502e+08 | F106: =+C110 -> 0.36265193
A107: MATAM | B107: =B94 -> 56852361 | C107: =B107/$B$111 -> 0.058873839 | E107: =SUM(E104:E106) -> 9.6566424e+08 | F107: =SUM(F104:F106) -> 1
A108: SAINT-LOUIS | B108: =B95 -> 2225609 | C108: =B108/$B$111 -> 0.0023047441
A109: TAMBACOUNDA | B109: =B96 -> 1740741.1 | C109: =B109/$B$111 -> 0.001802636
A110: THIES | B110: =B97+F93 -> 3.502e+08 | C110: =B110/$B$111 -> 0.36265193
...

Sheet Requete_PRODUCTIONELECTRICIT OK
A1: entreprise_id | B1: electrc_propr_consommtn | C1: qte_electrc_autoconsom | D1: estimatn_autoconsommtn | E1: vendu_electrc_ind | F1: qte_electrc_vendu | G1: solaire_ind | H1: fuel_ind | I1: fuel_qte | J1: fuel_unite_mesr | K1: diesel_ind | L1: diesel_qte | M1: diesel_unite_mesr | N1: charbon_ind | O1: charbon_qte | P1: charbon_unite_mesr | Q1: gaz_nat_ind | R1: gaz_nat_qte | S1: gaz_nat_unite_mesr | T1: autre_source | U1: autre_ind | V1: autre_qte | W1: autre_unite_mesr | X1: autre_unite_mesr_desc | Y1: Prix Implicite
A2: BOSFOR SARL | B2: 1 | C2: 2329600 | D2: 262000 | E2: 2 | F2: 0 | G2: 2 | H2: 2 | I2: 0 | J2: 1 | K2: 1 | L2: 400000 | M2: 1 | N2: 2 | O2: 0 | P2: 1 | Q2: 2 | R2: 0 | S2: 1 | U2: 2 | V2: 0 | W2: 1 | Y2: =D2/C2 -> 0.11246566
A3: INDUSTRIES CHIMIQUES DU SENEGAL | B3: 1 | C3: 265237763 | D3: 7172899 | E3: 1 | F3: 15554000 | G3: 2 | H3: 1 | I3: 787 | J3: 2 | K3: 1 | L3: 26623457 | M3: 2 | N3: 1 | O3: 151162 | P3: 1 | Q3: 2 | R3: 0 | S3: 1 | U3: 2 | V3: 0 | W3: 1 | Y3: =D3/C3 -> 0.02704328
A4: CIMENTS DU SAHEL | B4: 1 | C4: 226156533 | D4: 27100412 | E4: 2 | F4: 0 | G4: 2 | H4: 1 | I4: 26706426 | J4: 1 | K4: 1 | L4: 32938142 | M4: 1 | N4: 2 | O4: 0 | P4: 1 | Q4: 2 | R4: 0 | S4: 1 | U4: 2 | V4: 0 | W4: 1 | Y4: =D4/C4 -> 0.11983033
A5: GRANDE COTE OPERATIONS | B5: 3 | C5: 134248000 | D5: 15033200 | E5: 2 | F5: 0 | G5: 2 | H5: 2 | I5: 0 | J5: 1 | K5: 2 | L5: 0 | M5: 1 | N5: 2 | O5: 0 | P5: 1 | Q5: 2 | R5: 0 | S5: 1 | U5: 2 | V5: 0 | W5: 1 | Y5: =D5/C5 -> 0.11198081
A6: SORED-MINES SA | B6: 1 | C6: 8885368 | D6: =+C6*0.11 -> 977390.48 | E6: 2 | F6: 0 | G6: 2 | H6: 2 | I6: 0 | J6: 1 | K6: 1 | L6: 2221342 | M6: 1 | N6: 2 | O6: 0 | P6: 1 | Q6: 2 | R6: 0 | S6: 1 | U6: 2 | V6: 0 | W6: 1 | Y6: =D6/C6 -> 0.11
A7: SABODALA GOLD OPERATIONS | C7: 143556211 | D7: 14341000 | E7: 2 | F7: 0 | G7: 2 | H7: 2 | I7: 0 | J7: 1 | K7: 2 | L7: 0 | M7: 1 | N7: 2 | O7: 0 | P7: 1 | Q7: 2 | R7: 0 | S7: 1 | U7: 2 | V7: 0 | W7: 1 | Y7: =D7/C7 -> 0.099898151
A8: DANGOTE CEMENT SENEGAL | B8: 1 | C8: 100528139 | D8: 11359680 | E8: 2 | F8: 0 | G8: 1 | H8: 2 | I8: 0 | J8: 1 | K8: 1 | L8: 721980 | M8: 1 | N8: 1 | O8: 72783 | P8: 1 | Q8: 2 | R8: 0 | S8: 1 | U8: 2 | V8: 0 | W8: 1 | Y8: =D8/C8 -> 0.113
A9: PETOWAL MINING COMPANY (PMC) SA | B9: 1 | C9: 83628875 | D9: 9455753 | E9: 2 | F9: 0 | G9: 2 | H9: 2 | I9: 0 | J9: 1 | K9: 1 | L9: 21486676 | M9: 1 | N9: 2 | O9: 0 | P9: 1 | Q9: 2 | R9: 0 | S9: 1 | U9: 2 | V9: 0 | W9: 1 | Y9: =D9/C9 -> 0.11306804
A10: GECAMINES | B10: 1 | C10: 4375380 | D10: 809445 | E10: 2 | F10: 0 | G10: 2 | H10: 2 | I10: 0 | J10: 1 | K10: 1 | L10: 1458460 | M10: 1 | N10: 2 | O10: 0 | P10: 1 | Q10: 2 | R10: 0 | S10: 1 | U10: 2 | V10: 0 | W10: 1 | Y10: =D10/C10 -> 0.18499993
A12: Carrières | C12: =(C10+C2)/1000 -> 6704.98 | D12: =(D10+D2)/1000 -> 1071.445 | L12: =D12/$D$15 -> 0.026210292
A13: Minéraux lourds | C13: =C5/1000 -> 134248 | D13: =D5/1000 -> 15033.2 | L13: =D13/$D$15 -> 0.36775062
A14: Or | C14: =(C6+C7+C9)/1000 -> 236070.45 | D14: =(D6+D7+D9)/1000 -> 24774.143 | L14: =D14/$D$15 -> 0.60603908
A15: TOTAL | C15: =SUM(C12:C14) -> 377023.43 | D15: =SUM(D12:D14) -> 40878.788 | L15: =D15/$D$15 -> 1
C16: =C15/1000 -> 377.02343
C17: 352.2 | D17: =C16/C17-1 -> 0.070481073
A19: Type d'activité | B19: Electricité produite en quantité (MWH) | C19: Electricité produite en valeur | D19: Pourcentage par type d'activité
C20: ( en million FCFA)
A21: Carrière | B21: 4 345 | C21: 809.4 | D21: =+C21/$C$24 -> 0.019800022
A22: Minéraux lourds | B22: 134 248 | C22: 15033.2 | D22: =+C22/$C$24 -> 0.36775103
A23: Or | B23: 236 074,5 | C23: 25036.143 | D23: =+C23/$C$24 -> 0.61244895
A24: TOTAL | C24: =SUM(C21:C23) -> 40878.743

Sheet Requete_PRODUCTION CIMICS ok
A1: entreprise_id | B1: Région | C1: substance_desc | D1: qte_brute | E1: cout_production | F1: qte_transforme | G1: Cout de production/qte
A2: CIMENTS DU SAHEL | B2: THIES | C2: Argile | D2: 400578 | E2: 1321908 | F2: 400578 | G2: =+E2/D2 -> 3.3000015
A3: DANGOTE CEMENT SENEGAL | B3: THIES | C3: Argile | D3: 156221 | E3: 388947 | F3: 168001 | G3: =+E3/D3 -> 2.4897229
A4: CIMENTS DU SAHEL | B4: THIES | C4: Calcaire | D4: 2902226 | E4: 6094674 | F4: 2902226 | G4: =+E4/D4 -> 2.0999998
A5: DANGOTE CEMENT SENEGAL | B5: THIES | C5: Calcaire | D5: 1388347 | E5: 2244819 | F5: 1388347 | G5: =+E5/D5 -> 1.6169005
A6: CIMENTS DU SAHEL | B6: THIES | C6: Latérite | D6: 82473 | E6: 247419 | F6: 82473 | G6: =+E6/D6 -> 3
A7: DANGOTE CEMENT SENEGAL | B7: THIES | C7: Latérite | D7: 40864 | E7: 84608 | F7: 40864 | G7: =+E7/D7 -> 2.0704777
A8: INDUSTRIES CHIMIQUES DU SENEGAL | B8: THIES | C8: Phosphate de chaux | D8: 1771000 | E8: 56393616 | F8: 1987798 | G8: =+E8/D8 -> 31.84281
A9: SOCOCIM INDUSTRIES | B9: DAKAR | C9: Marne | D9: 1990935 | E9: 4370102 | F9: 1990935 | G9: =+E9/D9 -> 2.1949998
A10: SOCOCIM INDUSTRIES | B10: DAKAR | C10: Calcaire | D10: =140987+762283 -> 903270 | E10: 1982677 | F10: =140987+762283 -> 903270 | G10: =+E10/D10 -> 2.1949993
A11: SOCOCIM INDUSTRIES | B11: DAKAR | C11: Latérite | D11: 101441 | E11: 395011 | F11: =101441 -> 101441 | G11: =+E11/D11 -> 3.8939975
D12: =+SUBTOTAL(9,D2:D11) -> 9737355 | E12: =+SUBTOTAL(9,E2:E11) -> 73523781 | F12: =+SUBTOTAL(9,F2:F11) -> 9965933
D13: =SUBTOTAL(9,D2:D12) -> 9737355
C14: Charges/tonnes
C15: CA/Tonnes
B16: CA/Tonnes | C16: QUANTITE | D16: VALEUR | E16: CA/Qte
B17: Ciment | C17: =+'Requete_PRODUCTION_TRANSFOR OK'!N48 -> 3370695.1 | D17: ='Requete_PRODUCTION_TRANSFOR OK'!O48 -> 159971636 | E17: =D17/C17 -> 47.459539
B18: Clincker | C18: =+'Requete_PRODUCTION_TRANSFOR OK'!N49 -> 22019.16 | D18: ='Requete_PRODUCTION_TRANSFOR OK'!O49 -> 836567 | E18: =D18/C18 -> 37.992685
D19: =SUBTOTAL(9,D17:D18) -> 160808203
B20: Charges/tonnes | D20: =D17*0.01 -> 1599716.4
B21: ='Charge rectifiées OK T'!BU53 -> 1.6378472e+08 | C21: =D19-B21 -> -2976517.1 | D21: =D19*0.01 -> 1608082
D24: 7610596.7

Sheet Requete_exportationdetail OK
A1: entreprise_id | B1: produit_desc | C1: exportation_id | D1: produit_id | E1: pays_id | F1: Pays | G1: qte_vendu_pays | H1: val_produit | K1: produit_desc | L1: (Plusieurs éléments)
A2: BMCC SA | B2: Phosphates | C2: 418 | D2: 11 | E2: 81 | F2: Inde | G2: 23001 | H2: 1023137
A3: BMCC SA | B3: Phosphates | C3: 419 | D3: 11 | E3: 81 | F3: Inde | G3: 26105 | H3: 1460215 | K3: Étiquettes de lignes | L3: Somme de qte_vendu_pays | M3: Somme de val_produit | P3: Étiquettes de lignes | Q3: Somme de qte_vendu_pays | R3: Somme de val_produit
A4: CIMENTS DU SAHEL | B4: Ciment | C4: 373 | D4: 46 | E4: 31 | F4: Burkina Faso | G4: 400 | H4: 18200 | K4: Emirat Arabe Unis | L4: 528.89 | M4: 295007440 | P4: Acide phosphorique | Q4: 558410.08 | R4: 533842674
A5: CIMENTS DU SAHEL | B5: Ciment | C5: 374 | D5: 46 | E5: 68 | F5: Gambie | G5: 485904 | H5: 21800120 | K5: France | L5: 529590.76 | M5: 163306124 | P5: Argent | Q5: 0.85 | R5: 374907
A6: CIMENTS DU SAHEL | B6: Ciment | C6: 375 | D6: 46 | E6: 74 | F6: Guinée | G6: 110 | H6: 4785 | K6: Australie | L6: 684.03193 | M6: 148742351 | P6: Attapulgite | Q6: 161515.8 | R6: 4422520
A7: CIMENTS DU SAHEL | B7: Ciment | C7: 376 | D7: 46 | E7: 75 | F7: Guinée-Bissau | G7: 2930 | H7: 134463 | K7: Suisse | L7: 148212.33 | M7: 94910043 | P7: Basalte | Q7: 47949.86 | R7: 390487.02
A8: CIMENTS DU SAHEL | B8: Ciment | C8: 377 | D8: 46 | E8: 111 | F8: Mali | G8: 586238 | H8: 27805009 | K8: Liban | L8: 182942 | M8: 21366392 | P8: Ciment | Q8: 1502608.9 | R8: 68535819
A9: CIMENTS DU SAHEL | B9: Ciment | C9: 378 | D9: 46 | E9: 116 | F9: Mauritanie | G9: 36830 | H9: 1572723 | K9: Norvège | L9: 101873 | M9: 17675149 | P9: Clinker | Q9: 13645.85 | R9: 504795
A10: CSE GRANULATS | B10: Basalte | C10: 417 | D10: 37 | E10: 68 | F10: Gambie | G10: 47949.86 | H10: 390487.02 | K10: Maurice | L10: 0.27 | M10: 9648371 | P10: Engrais | Q10: 12318 | R10: 3328965
A11: DANGOTE CEMENT SENEGAL | B11: Ciment | C11: 415 | D11: 46 | E11: 31 | F11: Burkina Faso | G11: 3396 | H11: 130813 | K11: Chine | L11: 49007.888 | M11: 8487014.9 | P11: Ilménite | Q11: 526747 | R11: 109536229
A12: DANGOTE CEMENT SENEGAL | B12: Ciment | C12: 412 | D12: 46 | E12: 68 | F12: Gambie | G12: 65923 | H12: 2585006 | K12: États-Unis | L12: 31246 | M12: 8049524 | P12: Leucoxene | Q12: 6340 | R12: 5532814
A13: DANGOTE CEMENT SENEGAL | B13: Ciment | C13: 413 | D13: 46 | E13: 75 | F13: Guinée-Bissau | G13: 13462 | H13: 532510 | K13: Espagne | L13: 8360 | M13: 6660472 | P13: Manganèse | Q13: 31093.338 | R13: 1263388
A14: DANGOTE CEMENT SENEGAL | B14: Ciment | C14: 414 | D14: 46 | E14: 111 | F14: Mali | G14: 125865 | H14: 5710850 | K14: Belgique | L14: 29318.253 | M14: 3764950 | P14: Minéraux lourds | Q14: 9097.55 | R14: 2225608.9
A15: G.H MINING | B15: Manganèse | C15: 403 | D15: 8 | E15: 39 | F15: Chine | G15: 31093.338 | H15: 1263388 | K15: Panamá | L15: 40461 | M15: 3434732 | P15: Or | Q15: 14.671934 | R15: 531398667
A16: GRANDE COTE OPERATIONS | B16: Leucoxene | F16: Afrique du Sud | G16: 100 | H16: 76434 | K16: Inde | L16: 49424 | M16: 2876373 | P16: Phosphates | Q16: 464970 | R16: 47999622
A17: GRANDE COTE OPERATIONS | B17: Zircon | C17: 385 | D17: 18 | E17: 5 | F17: Allemagne | G17: 66 | H17: 82182 | K17: Allemagne | L17: 1784 | M17: 2231046 | P17: Rutile | Q17: 4160 | R17: 5290812
A18: GRANDE COTE OPERATIONS | B18: Zircon | F18: Allemagne | G18: 1678 | H18: 2119199 | K18: Pays-Bas | L18: 35791.962 | M18: 1858458 | P18: Zircon | Q18: 90613 | R18: 87993881
A19: GRANDE COTE OPERATIONS | B19: Leucoxene | F19: Allemagne | G19: 40 | H19: 29665 | K19: Japon | L19: 1379 | M19: 1638316 | P19: Total général | Q19: 3429484.9 | R19: 1.4026412e+09
A20: GRANDE COTE OPERATIONS | B20: Zircon | C20: 390 | D20: 18 | F20: Angleterre | G20: 160 | H20: 205256 | K20: Royaume-Uni | L20: 63922.825 | M20: 1436607
A21: GRANDE COTE OPERATIONS | B21: Rutile | F21: Angleterre | G21: 100 | H21: 131315 | K21: Corée du Sud | L21: 1020 | M21: 955701 | P21: SUBSTANCES | Q21: 2021 | S21: 2022
A22: GRANDE COTE OPERATIONS | B22: Leucoxene | F22: Angleterre | G22: 120 | H22: 87598 | K22: Italie | L22: 661 | M22: 805311 | Q22: Quantite | R22: Valeur (Milliers FCFA) | S22: Quantite | T22: Valeur (Milliers FCFA)
A23: GRANDE COTE OPERATIONS | B23: Zircon | C23: 386 | D23: 18 | E23: 12 | F23: Australie | G23: 680 | H23: 879535 | K23: Salvador | L23: 5500 | M23: 785469 | P23: Acide phosphorique | Q23: 497897 | R23: 291874254 | S23: =+VLOOKUP(P23,$P$4:$R$18,2,0) -> 558410.08 | T23: =+VLOOKUP(P23,$P$4:$R$18,3,0) -> 533842674
A24: GRANDE COTE OPERATIONS | B24: Zircon | F24: Brésil | G24: 140 | H24: 176061 | K24: Turquie | L24: 595 | M24: 738090 | P24: Argent | Q24: 1.3179 | R24: 582754 | S24: =+VLOOKUP(P24,$P$4:$R$18,2,0) -> 0.85 | T24: =+VLOOKUP(P24,$P$4:$R$18,3,0) -> 374907
A25: GRANDE COTE OPERATIONS | B25: Zircon | C25: 383 | D25: 18 | E25: 39 | F25: Chine | G25: 1553 | H25: 1972278 | K25: Mali | L25: 8816 | M25: 594500 | P25: Attapulgite | Q25: 182379.62 | R25: 8082682.2 | S25: =+VLOOKUP(P25,$P$4:$R$18,2,0) -> 161515.8 | T25: =+VLOOKUP(P25,$P$4:$R$18,3,0) -> 4422520
A26: GRANDE COTE OPERATIONS | B26: Zircon | F26: Chine | G26: 368 | H26: 436921 | K26: Angleterre | L26: 380 | M26: 424169 | P26: Basalte | Q26: 36437 | R26: 364715.65 | S26: =+VLOOKUP(P26,$P$4:$R$18,2,0) -> 47949.86 | T26: =+VLOOKUP(P26,$P$4:$R$18,3,0) -> 390487.02
A27: GRANDE COTE OPERATIONS | B27: Rutile | F27: Chine | G27: 80 | H27: 96661 | K27: Gambie | L27: 47949.86 | M27: 390487.02 | P27: Ciment | Q27: 1793708.3 | R27: 71599992 | S27: =+VLOOKUP(P27,$P$4:$R$18,2,0) -> 1502608.9 | T27: =+VLOOKUP(P27,$P$4:$R$18,3,0) -> 68535819
A28: GRANDE COTE OPERATIONS | B28: Leucoxene | F28: Chine | G28: 400 | H28: 303853 | K28: Lituanie | L28: 2690 | M28: 317593 | P28: Clinker | Q28: 341082.58 | R28: 8910597 | S28: =+VLOOKUP(P28,$P$4:$R$18,2,0) -> 13645.85 | T28: =+VLOOKUP(P28,$P$4:$R$18,3,0) -> 504795
A29: GRANDE COTE OPERATIONS | B29: Zircon | F29: Chine | G29: 6416 | H29: 2188305 | K29: Brésil | L29: 140 | M29: 176061 | P29: Engrais | Q29: 255148 | R29: 30336436 | S29: =+VLOOKUP(P29,$P$4:$R$18,2,0) -> 12318 | T29: =+VLOOKUP(P29,$P$4:$R$18,3,0) -> 3328965
A30: GRANDE COTE OPERATIONS | B30: Rutile | F30: Corée du Sud | G30: 580 | H30: 634237 | K30: Afrique du Sud | L30: 100 | M30: 76434 | P30: Hormite | Q30: 15363.21 | R30: 134354.48 | S30: 0 | T30: 0
A31: GRANDE COTE OPERATIONS | B31: Leucoxene | F31: Corée du Sud | G31: 400 | H31: 298442 | K31: Taiwan | L31: 60 | M31: 66222 | P31: Ilménite | Q31: 556405.92 | R31: 78636154 | S31: =+VLOOKUP(P31,$P$4:$R$18,2,0) -> 526747 | T31: =+VLOOKUP(P31,$P$4:$R$18,3,0) -> 109536229
A32: GRANDE COTE OPERATIONS | B32: Ilménite | F32: Corée du Sud | G32: 40 | H32: 23022 | K32: Cote d'ivore | L32: 64 | M32: 5536 | P32: Leucoxene | Q32: 6960 | R32: 3595901 | S32: =+VLOOKUP(P32,$P$4:$R$18,2,0) -> 6340 | T32: =+VLOOKUP(P32,$P$4:$R$18,3,0) -> 5532814
A33: GRANDE COTE OPERATIONS | B33: Rutile | F33: Emirat Arabe Unis | G33: 60 | H33: 63698 | K33: Total général | L33: 1342502.1 | M33: 7.9642894e+08 | P33: Manganèse | Q33: 9396 | R33: 518248 | S33: =+VLOOKUP(P33,$P$4:$R$18,2,0) -> 31093.338 | T33: =+VLOOKUP(P33,$P$4:$R$18,3,0) -> 1263388
A34: GRANDE COTE OPERATIONS | B34: Rutile | F34: Emirat Arabe Unis | G34: 20 | H34: 26978 | P34: Minéraux lourds | Q34: 0 | R34: 0 | S34: =+VLOOKUP(P34,$P$4:$R$18,2,0) -> 9097.55 | T34: =+VLOOKUP(P34,$P$4:$R$18,3,0) -> 2225608.9
A35: GRANDE COTE OPERATIONS | B35: Leucoxene | F35: Emirat Arabe Unis | G35: 440 | H35: 341151 | P35: Or | Q35: 15.8735 | R35: 505067362 | S35: =+VLOOKUP(P35,$P$4:$R$18,2,0) -> 14.671934 | T35: =+VLOOKUP(P35,$P$4:$R$18,3,0) -> 531398667
A36: GRANDE COTE OPERATIONS | B36: Zircon | C36: 382 | D36: 18 | E36: 60 | F36: Espagne | G36: 1763 | H36: 2159428 | P36: Phosphates | Q36: 562863 | R36: 23565975 | S36: =+VLOOKUP(P36,$P$4:$R$18,2,0) -> 464970 | T36: =+VLOOKUP(P36,$P$4:$R$18,3,0) -> 47999622
A37: GRANDE COTE OPERATIONS | B37: Zircon | F37: Espagne | G37: 3591 | H37: 4215746 | P37: Rutile | Q37: 4462 | R37: 3629678 | S37: =+VLOOKUP(P37,$P$4:$R$18,2,0) -> 4160 | T37: =+VLOOKUP(P37,$P$4:$R$18,3,0) -> 5290812
A38: GRANDE COTE OPERATIONS | B38: Rutile | F38: Espagne | G38: 60 | H38: 64976 | P38: Zircon | Q38: 90198.732 | R38: 61742607 | S38: =+VLOOKUP(P38,$P$4:$R$18,2,0) -> 90613 | T38: =+VLOOKUP(P38,$P$4:$R$18,3,0) -> 87993881
A39: GRANDE COTE OPERATIONS | B39: Zircon | C39: 381 | D39: 18 | E39: 62 | F39: États-Unis | G39: 2241 | H39: 2673377 | P39: TOTAL | Q39: =SUM(Q23:Q38) -> 4352318.6 | R39: =SUM(R23:R38) -> 1.0886417e+09 | S39: =SUM(S23:S38) -> 3429484.9 | T39: =SUM(T23:T38) -> 1.4026412e+09
A40: GRANDE COTE OPERATIONS | B40: Ilménite | C40: 394 | D40: 22 | E40: 62 | F40: États-Unis | G40: 29005 | H40: 5376147
A41: GRANDE COTE OPERATIONS | B41: Zircon | C41: 391 | D41: 18 | E41: 66 | F41: France | G41: 26783 | H41: 37837012
A42: GRANDE COTE OPERATIONS | B42: Zircon | F42: France | G42: 16915 | H42: 22797650
A43: GRANDE COTE OPERATIONS | B43: Rutile | F43: France | G43: 2840 | H43: 3827195
A44: GRANDE COTE OPERATIONS | B44: Leucoxene | F44: France | G44: 4540 | H44: 4153250
A45: GRANDE COTE OPERATIONS | B45: Zircon | F45: France | G45: 25033 | H45: 6221776
A46: GRANDE COTE OPERATIONS | B46: Ilménite | C46: 392 | D46: 22 | E46: 66 | F46: France | G46: 255142 | H46: 55201748
A47: GRANDE COTE OPERATIONS | B47: Ilménite | F47: France | G47: 105551 | H47: 23782278
A48: GRANDE COTE OPERATIONS | B48: Ilménite | F48: France | G48: 35216 | H48: 7578110
A49: GRANDE COTE OPERATIONS | B49: Zircon | F49: Inde | G49: 64 | H49: 79007
A50: GRANDE COTE OPERATIONS | B50: Zircon | F50: Inde | G50: 234 | H50: 298525
A51: GRANDE COTE OPERATIONS | B51: Rutile | F51: Inde | G51: 20 | H51: 15489
A52: GRANDE COTE OPERATIONS | B52: Zircon | C52: 388 | D52: 18 | E52: 88 | F52: Italie | G52: 661 | H52: 805311
A53: GRANDE COTE OPERATIONS | B53: Zircon | F53: Japon | G53: 899 | H53: 1151481
A54: GRANDE COTE OPERATIONS | B54: Zircon | F54: Japon | G54: 120 | H54: 149568
A55: GRANDE COTE OPERATIONS | B55: Rutile | F55: Japon | G55: 240 | H55: 237529
A56: GRANDE COTE OPERATIONS | B56: Leucoxene | F56: Japon | G56: 120 | H56: 99738
A57: GRANDE COTE OPERATIONS | B57: Zircon | F57: Norvège | G57: 80 | H57: 100225
A58: GRANDE COTE OPERATIONS | B58: Ilménite | C58: 393 | D58: 22 | E58: 131 | F58: Norvège | G58: 101793 | H58: 17574924
A59: GRANDE COTE OPERATIONS | B59: Zircon | C59: 387 | D59: 18 | E59: 142 | F59: Pays-Bas | G59: 110 | H59: 137807
A60: GRANDE COTE OPERATIONS | B60: Zircon | F60: Pays-Bas | G60: 463 | H60: 569141
A61: GRANDE COTE OPERATIONS | B61: Rutile | F61: Pays-Bas | G61: 100 | H61: 126512
A62: GRANDE COTE OPERATIONS | B62: Leucoxene | F62: Pays-Bas | G62: 180 | H62: 142683
A63: GRANDE COTE OPERATIONS | B63: Rutile | F63: Taiwan | G63: 60 | H63: 66222
A64: GRANDE COTE OPERATIONS | B64: Zircon | C64: 389 | D64: 18 | E64: 186 | F64: Turquie | G64: 595 | H64: 738090
A65: INDUSTRIES CHIMIQUES DU SENEGAL | B65: Engrais | C65: 363 | D65: 47 | E65: 31 | F65: Burkina Faso | G65: 47 | H65: 6063
A66: INDUSTRIES CHIMIQUES DU SENEGAL | B66: Engrais | C66: 364 | D66: 47 | E66: 68 | F66: Gambie | G66: 2455 | H66: 795369
A67: INDUSTRIES CHIMIQUES DU SENEGAL | B67: Engrais | C67: 365 | D67: 47 | E67: 74 | F67: Guinée | G67: 990 | H67: 379656
A68: INDUSTRIES CHIMIQUES DU SENEGAL | B68: Acide phosphorique | C68: 367 | D68: 45 | E68: 81 | F68: Inde | G68: 558410.08 | H68: 533842674
A69: INDUSTRIES CHIMIQUES DU SENEGAL | B69: Engrais | C69: 366 | D69: 47 | E69: 111 | F69: Mali | G69: 8826 | H69: 2147877
A70: PETOWAL MINING COMPANY (PMC) SA | B70: Or | C70: 416 | D70: 1 | E70: 12 | F70: Australie | G70: 4.0319337 | H70: 147862816
A71: PROCHIMAT SA | B71: Attapulgite | F71: France | G71: 9235 | H71: 632832
A72: PROCHIMAT SA | B72: Attapulgite | F72: Cote d'ivore | G72: 64 | H72: 5536
A73: SABODALA GOLD OPERATIONS | B73: Or | C73: 397 | D73: 1 | E73: 57 | F73: Emirat Arabe Unis | G73: 8.18 | H73: 294263827
A74: SABODALA GOLD OPERATIONS | B74: Argent | C74: 400 | D74: 2 | E74: 57 | F74: Emirat Arabe Unis | G74: 0.71 | H74: 311786
A75: SABODALA GOLD OPERATIONS | B75: Or | C75: 398 | D75: 1 | E75: 115 | F75: Maurice | G75: 0.27 | H75: 9648371
A76: SABODALA GOLD OPERATIONS | B76: Or | C76: 399 | D76: 1 | E76: 172 | F76: Suisse | G76: 2.19 | H76: 79623653 | L76: Étiquettes de lignes | M76: Somme de qte_vendu_pays | N76: Somme de val_produit | R76: Étiquettes de lignes
A77: SABODALA GOLD OPERATIONS | B77: Argent | C77: 401 | D77: 2 | E77: 172 | F77: Suisse | G77: 0.14 | H77: 63121 | K77: =R105 -> DIOURBEL | L77: BMCC SA | M77: 49106 | N77: 2483352 | R77: 2SBCI
A78: SENEGAL MINES | B78: Attapulgite | C78: 370 | D78: 17 | E78: 19 | F78: Belgique | G78: 5019.253 | H78: 190957 | I78: =H78/G78 -> 38.044904 | L78: Phosphates | M78: 49106 | N78: 2483352 | R78: THIES
A79: SENEGAL MINES | B79: Attapulgite | C79: 372 | D79: 17 | E79: 142 | F79: Pays-Bas | G79: 2594.272 | H79: 99543 | I79: =H79/G79 -> 38.370302 | K79: =R120 -> THIES | L79: CIMENTS DU SAHEL | M79: 1112412 | N79: 51335300 | R79: AFRIGEM SL
A80: SENEGAL MINES | B80: Attapulgite | C80: 371 | D80: 17 | E80: 149 | F80: Royaume-Uni | G80: 3875.575 | H80: 139823 | I80: =H80/G80 -> 36.078001 | L80: Ciment | M80: 1112412 | N80: 51335300 | R80: KEDOUGOU
A81: SEN-HMC SUARL | B81: Minéraux lourds | F81: Chine | G81: 9097.55 | H81: 2225608.9 | J81: =R126 -> TAMBACOUNDA | K81: =R118 -> THIES | L81: CSE GRANULATS | M81: 47949.86 | N81: 390487.02 | R81: AFRIGOLD SARL
A82: SEPHOS SENEGAL SA | B82: Phosphates | C82: 407 | D82: 11 | E82: 60 | F82: Espagne | G82: 2946 | H82: 220322 | L82: Basalte | M82: 47949.86 | N82: 390487.02 | R82: KEDOUGOU
A83: SEPHOS SENEGAL SA | B83: Phosphates | C83: 408 | D83: 11 | E83: 139 | F83: Panamá | G83: 40461 | H83: 3434732 | K83: =R133 -> THIES | L83: DANGOTE CEMENT SENEGAL | M83: 208646 | N83: 8959179 | R83: AGEM SENEGAL EXPLORATION SUARL
A84: SEPHOS SENEGAL SA | B84: Phosphates | C84: 406 | D84: 11 | E84: 157 | F84: Salvador | G84: 5500 | H84: 785469 | L84: Ciment | M84: 208646 | N84: 8959179 | R84: KEDOUGOU
A85: SOCIETE MINIERE DE LA VALLEE DU FLEUVE SENEGAL –SOMIVA | B85: Phosphates | C85: 421 | D85: 9 | E85: 19 | F85: Belgique | G85: 24299 | H85: 3573993 | K85: =R142 -> TAMBACOUNDA | L85: G.H MINING | M85: 31093.338 | N85: 1263388 | R85: AGROMINE
A86: SOCIETE MINIERE DE LA VALLEE DU FLEUVE SENEGAL –SOMIVA | B86: Phosphates | C86: 423 | D86: 9 | E86: 100 | F86: Liban | G86: 182942 | H86: 21366392 | L86: Manganèse | M86: 31093.338 | N86: 1263388 | R86: DIOURBEL
A87: SOCIETE MINIERE DE LA VALLEE DU FLEUVE SENEGAL –SOMIVA | B87: Phosphates | C87: 422 | D87: 9 | E87: 104 | F87: Lituanie | G87: 2690 | H87: 317593 | K87: =R154 -> THIES | L87: GRANDE COTE OPERATIONS | M87: 627860 | N87: 208353736 | R87: THIES
A88: SOCIETE MINIERE DE LA VALLEE DU FLEUVE SENEGAL –SOMIVA | B88: Phosphates | C88: 424 | D88: 9 | E88: 111 | F88: Mali | G88: 8816 | H88: 594500 | L88: Ilménite | M88: 526747 | N88: 109536229 | R88: ALBINA SENEGAL SARL
A89: SOCIETE MINIERE DE LA VALLEE DU FLEUVE SENEGAL –SOMIVA | B89: Phosphates | C89: 420 | D89: 9 | E89: 172 | F89: Suisse | G89: 148210 | H89: 15223269 | L89: Leucoxene | M89: 6340 | N89: 5532814 | R89: THIES
A90: SOCIETE SENEGALAISE DES PHOSPHATES DE THIES | B90: Attapulgite | C90: 409 | D90: 17 | E90: 66 | F90: France | G90: 48335.76 | H90: 1274273 | L90: Rutile | M90: 4160 | N90: 5290812 | R90: AMAFRIQUE SENEGAL
A91: SOCIETE SENEGALAISE DES PHOSPHATES DE THIES | B91: Attapulgite | C91: 411 | D91: 17 | E91: 142 | F91: Pays-Bas | G91: 32344.69 | H91: 782772 | L91: Zircon | M91: 90613 | N91: 87993881 | R91: MATAM
A92: SOCIETE SENEGALAISE DES PHOSPHATES DE THIES | B92: Attapulgite | C92: 410 | D92: 17 | E92: 149 | F92: Royaume-Uni | G92: 60047.25 | H92: 1296784 | K92: =R162 -> THIES | L92: INDUSTRIES CHIMIQUES DU SENEGAL | M92: 570728.08 | N92: 537171639 | R92: ARDIMINES SARL
A93: SOCOCIM INDUSTRIES | B93: Ciment | F93: Gambie | G93: 44459.73 | H93: 1994599 | L93: Acide phosphorique | M93: 558410.08 | N93: 533842674 | R93: KEDOUGOU
A94: SOCOCIM INDUSTRIES | B94: Ciment | F94: Guinée | G94: 1462 | H94: 69090 | L94: Engrais | M94: 12318 | N94: 3328965 | R94: ATIC SARL
A95: SOCOCIM INDUSTRIES | B95: Ciment | F95: Guinée-Bissau | G95: 533 | H95: 34820 | K95: =R182 -> THIES | L95: PROCHIMAT SA | M95: 9299 | N95: 638368 | R95: THIES
A96: SOCOCIM INDUSTRIES | B96: Clinker | F96: Mali | G96: 13645.85 | H96: 504795 | L96: Attapulgite | M96: 9299 | N96: 638368 | R96: BAMBADJI SA
A97: SOCOCIM INDUSTRIES | B97: Ciment | F97: Mali | G97: 132611.99 | H97: 6031024 | K97: =R190 -> THIES | L97: SENEGAL MINES | M97: 11489.1 | N97: 430323 | R97: KEDOUGOU
A98: SOCOCIM INDUSTRIES | B98: Ciment | F98: Mauritanie | G98: 2484.15 | H98: 111807 | L98: Attapulgite | M98: 11489.1 | N98: 430323 | R98: BAMBUK MINERALS SARL
G99: =SUM(G2:G98) -> 3429484.9 | H99: =SUM(H2:H98) -> 1.4026412e+09 | J99: =R193 -> SAINT-LOUIS | K99: =R192 -> LOUGA | L99: SEN-HMC SUARL | M99: 9097.55 | N99: 2225608.9 | R99: KEDOUGOU
L100: Minéraux lourds | M100: 9097.55 | N100: 2225608.9 | R100: BB FIRST COMMODITY HOLDING LIMITED
...

Sheet EXPORTATION
A3: Étiquettes de lignes | B3: Somme de qte_vendu_pays | C3: Somme de val_produit
A4: Argent | B4: 0.85 | C4: 374907
A5: Attapulgite | B5: 161515.8 | C5: 4422520 | F5: Or | G5: 531398667
A6: Basalte | B6: 47949.86 | C6: 390487.02 | F6: Ilménite | G6: 109536229
A7: Ilménite | B7: 526747 | C7: 109536229 | F7: Zircon | G7: 87993881
A8: Leucoxene | B8: 6340 | C8: 5532814 | F8: Phosphates | G8: 47999622
A9: Manganèse | B9: 31093.338 | C9: 1263388 | F9: Leucoxene | G9: 5532814
A10: Minéraux lourds | B10: 9097.55 | C10: 2225608.9 | F10: Rutile | G10: 5290812
A11: Or | B11: 14.671934 | C11: 531398667 | F11: Attapulgite | G11: 4422520
A12: Phosphates | B12: 464970 | C12: 47999622 | F12: Minéraux lourds | G12: 2225608.9
A13: Rutile | B13: 4160 | C13: 5290812 | F13: Manganèse | G13: 1263388
A14: Zircon | B14: 90613 | C14: 87993881 | F14: Basalte | G14: 390487.02
A15: Total général | B15: 1342502.1 | C15: 7.9642894e+08 | D15: 685.9 | F15: Argent | G15: 374907
B16: 1464483 | D16: =796.4/D15-1 -> 0.1611022
B17: =+B15/B16-1 -> -0.083292828
A19: Répartition des exportations par substance en 2022 (en valeur)
A20: SUBSTANCES | B20: MONTANT (milliers FCFA) | C20: %
A21: Or | B21: =VLOOKUP(A21,$A$4:$C$14,3,0) -> 531398667 | C21: =+B21/$B$32 -> 0.66722672 | D21: =+A21 -> Or | E21: =+C21 -> 0.66722672
A22: Ilménite | B22: =VLOOKUP(A22,$A$4:$C$14,3,0) -> 109536229 | C22: =+B22/$B$32 -> 0.13753422 | D22: Ilménite, Rutile et Leucoxène | E22: =+C22+C26+C25 -> 0.15112441
A23: Zircon | B23: =VLOOKUP(A23,$A$4:$C$14,3,0) -> 87993881 | C23: =+B23/$B$32 -> 0.11048554 | D23: =+A23 -> Zircon | E23: =+C23 -> 0.11048554
A24: Phosphates | B24: =VLOOKUP(A24,$A$4:$C$14,3,0) -> 47999622 | C24: =+B24/$B$32 -> 0.060268556 | D24: =+A24 -> Phosphates | E24: =+C24 -> 0.060268556
A25: Leucoxene | B25: =VLOOKUP(A25,$A$4:$C$14,3,0) -> 5532814 | C25: =+B25/$B$32 -> 0.0069470279 | D25: Autres produits | E25: =1-SUM(E21:E24) -> 0.010894771
A26: Rutile | B26: =VLOOKUP(A26,$A$4:$C$14,3,0) -> 5290812 | C26: =+B26/$B$32 -> 0.006643169
A27: Attapulgite | B27: =VLOOKUP(A27,$A$4:$C$14,3,0) -> 4422520 | C27: =+B27/$B$32 -> 0.0055529374
A28: Minéraux lourds | B28: =VLOOKUP(A28,$A$4:$C$14,3,0) -> 2225608.9 | C28: =+B28/$B$32 -> 0.0027944852
A29: Manganèse | B29: =VLOOKUP(A29,$A$4:$C$14,3,0) -> 1263388 | C29: =+B29/$B$32 -> 0.001586316
A30: Basalte | B30: =VLOOKUP(A30,$A$4:$C$14,3,0) -> 390487.02 | C30: =+B30/$B$32 -> 0.00049029738
A31: Argent | B31: =VLOOKUP(A31,$A$4:$C$14,3,0) -> 374907 | C31: =+B31/$B$32 -> 0.00047073503
A32: TOTAL | B32: =SUM(B21:B31) -> 7.9642894e+08 | C32: =+B32/$B$32 -> 1
A34: produit_desc | B34: (Plusieurs éléments)
A35: Répartition des exportations des produits miniers par pays en 2022
A36: Étiquettes de lignes | B36: Somme de qte_vendu_pays | C36: Somme de val_produit | D36: Somme de val_produit2
A37: Emirat Arabe Unis | B37: 528.89 | C37: 295007440 | D37: 0.37041276
A38: France | B38: 529590.76 | C38: 163306124 | D38: 0.20504795
A39: Australie | B39: 684.03193 | C39: 148742351 | D39: 0.18676161
A40: Suisse | B40: 148212.33 | C40: 94910043 | D40: 0.11916951
A41: Liban | B41: 182942 | C41: 21366392 | D41: 0.026827744
A42: Norvège | B42: 101873 | C42: 17675149 | D42: 0.022193002
A43: Maurice | B43: 0.27 | C43: 9648371 | D43: 0.012114541
A44: Chine | B44: 49007.888 | C44: 8487014.9 | D44: 0.010656337
A45: États-Unis | B45: 31246 | C45: 8049524 | D45: 0.010107021
A46: Espagne | B46: 8360 | C46: 6660472 | D46: 0.0083629207
A47: Belgique | B47: 29318.253 | C47: 3764950 | D47: 0.0047272893
A48: Panamá | B48: 40461 | C48: 3434732 | D48: 0.004312666
... A66: Total général | B66: 1342502.1 | C66: 7.9642894e+08 | D66: 1
A69: Répartition des exportations des produits par pays en 2022 (en milliers FCFA)
A70: PAYS | B70: VALEUR VENDUE | C70: %
A71: Emirat Arabe Unis | B71: =+C37 -> 295007440 | C71: =+B71/$B$76 -> 0.37041276
A72: France | B72: =+C38 -> 163306124 | C72: =+B72/$B$76 -> 0.20504795
A73: Australie | B73: =+C39 -> 148742351 | C73: =+B73/$B$76 -> 0.18676161
A74: Suisse | B74: =+C40 -> 94910043 | C74: =+B74/$B$76 -> 0.11916951
A75: Autres pays | B75: =SUM(C41:C65) -> 94462978 | C75: =+B75/$B$76 -> 0.11860817
A76: TOTAL | B76: =SUM(B71:B75) -> 7.9642894e+08 | C76: =SUM(C71:C75) -> 1
B77: =B76=C66 -> TRUE
A81: Étiquettes de lignes | B81: Somme de val_produit | E81: Étiquettes de lignes | F81: Somme de qte_vendu_pays | G81: Somme de val_produit
A82: Or | B82: 531398667 | E82: Acide phosphorique | F82: 558410.08 | G82: 533842674
A83: Australie | B83: 147862816 | E83: Ciment | F83: 1502608.9 | G83: 68535819
A84: Emirat Arabe Unis | B84: 294263827 | E84: Clinker | F84: 13645.85 | G84: 504795
A85: Maurice | B85: 9648371 | E85: Engrais | F85: 12318 | G85: 3328965
A86: Suisse | B86: 79623653 | E86: Total général | F86: 2086982.8 | G86: 606212253
A87: Ilménite | B87: 109536229
A88: Corée du Sud | B88: 23022
A89: États-Unis | B89: 5376147
A90: France | B90: 86562136 | E90: Étiquettes de lignes | F90: Somme de qte_vendu_pays | G90: Somme de val_produit
A91: Norvège | B91: 17574924 | E91: Engrais | F91: 12318 | G91: 3328965
A92: Zircon | B92: 87993881 | E92: Mali | F92: 8826 | G92: 2147877
A93: Allemagne | B93: 2201381 | E93: Gambie | F93: 2455 | G93: 795369
A94: Angleterre | B94: 205256 | E94: Guinée | F94: 990 | G94: 379656
A95: Australie | B95: 879535 | E95: Burkina Faso | F95: 47 | G95: 6063
A96: Brésil | B96: 176061 | E96: Clinker | F96: 13645.85 | G96: 504795
A97: Chine | B97: 4597504 | E97: Mali | F97: 13645.85 | G97: 504795
A98: Espagne | B98: 6375174 | E98: Acide phosphorique | F98: 558410.08 | G98: 533842674
A99: États-Unis | B99: 2673377 | E99: Inde | F99: 558410.08 | G99: 533842674
A100: France | B100: 66856438 | E100: Ciment | F100: 1502608.9 | G100: 68535819
A101: Inde | B101: 377532 | E101: Mali | F101: 844714.99 | G101: 39546883
A102: Italie | B102: 805311 | E102: Gambie | F102: 596286.73 | G102: 26379725
... A107: Phosphates | B107: 47999622 | E107: Total général | F107: 2086982.8 | G107: 606212253
A108: Belgique | B108: 3573993
A109: Espagne | B109: 220322
A110: Inde | B110: 2483352
A111: Liban | B111: 21366392
A112: Lituanie | B112: 317593
A113: Mali | B113: 594500
A114: Panamá | B114: 3434732
A115: Salvador | B115: 785469
A116: Suisse | B116: 15223269
A117: Leucoxene | B117: 5532814
A118: Afrique du Sud | B118: 76434
A119: Allemagne | B119: 29665
... A153: Total général | B153: 7.9642894e+08
A156: REPARTITION DES PRODUITS MINIERS PAR PAYS D’EXPORTATIONS
A157: Or | B157: =+B82 -> 531398667 | C157: Phosphates | D157: =+B107 -> 47999622
A158: Australie | B158: =+B83 -> 147862816 | C158: Belgique | D158: =+B108 -> 3573993
A159: Emirat Arabe Unis | B159: =+B84 -> 294263827 | C159: Espagne | D159: =+B109 -> 220322
A160: Maurice | B160: =+B85 -> 9648371 | C160: Inde | D160: =+B110 -> 2483352
A161: Suisse | B161: =+B86 -> 79623653 | C161: Liban | D161: =+B111 -> 21366392
A162: Ilménite | B162: =+B87 -> 109536229 | C162: Lituanie | D162: =+B112 -> 317593
A163: Corée du Sud | B163: =+B88 -> 23022 | C163: Mali | D163: =+B113 -> 594500
A164: États-Unis | B164: =+B89 -> 5376147 | C164: Panamá | D164: =+B114 -> 3434732
A165: France | B165: =+B90 -> 86562136 | C165: Salvador | D165: =+B115 -> 785469
...

Sheet Charge rectifiées OK
A1: entreprise_id | B1: AFRIGEM SL | C1: AFRIGOLD SARL | D1: AGEM SENEGAL EXPLORATION SUARL | E1: AGROMINE | F1: ALBINA SENEGAL SARL | G1: AMAFRIQUE SENEGAL | H1: ARDIMINES SARL | I1: ATIC SARL | J1: BAMBUK MINERALS SARL | K1: BHAIRAVA AGRICOLE SARL | L1: BOSFOR SARL | M1: BOYA SA | N1: CAYOR PHOSPHATE MINING SAU | O1: CHALLENGER NORD-SUD INTERNATIONAL INC | P1: CHESSER | Q1: CIMENTS DU SAHEL | R1: COMPAGNIE GENERALE D'EXPLOITATION DE CARRIERE | S1: CSE GRANULATS | T1: DALEMA | U1: DAMASH MINERALS LTD | V1: DANGOTE CEMENT SENEGAL | W1: G.H MINING | X1: BMCC SA | Y1: GECAMINES | Z1: G-PHOS S.A | AA1: GLOBAL IMMO SENEGAL SARL | AB1: GRANDE COTE OPERATIONS | AC1: GROUPEMENT D'ENTREPRISE SINTRAM HOUAR | AD1: HOLDING ATLANTQUE MINING PETROLUM-SA | AE1: IAMGOLD BOTO S.A | AF1: INDUSTRIES CHIMIQUES DU SENEGAL | AG1: INTERNATIONAL MINING COMPANY (IMC) | AH1: KANEL RESOURCES | AI1: KUTLU GABANE HOLDING S.A | AJ1: LES CARRIERES CTG SARL | AK1: MASSAWA JERSEY LIMITED | AL1: NIAMAYA GOLD SARL | AM1: PETOWAL MINING COMPANY (PMC) SA | AN1: PROCHIMAT | AO1: SABODALA GOLD OPERATIONS | AP1: SABODALA MINING COMPANY SARL | AQ1: SENEGAL MINES | AR1: SEN-HMC SUARL | AS1: SEPHOS SENEGAL SA | AT1: SERIGNE SALIOU MBACKE SUARL | AU1: SOCABEG MINING | AV1: SOCIETE DE CONCASSAGE ET DU BETON | AW1: 2SBCI | AX1: SOCIETE MINIERE DE LA VALLEE DU FLEUVE SENEGAL –SOMIVA | AY1: SOCIETE SENEGALAISE DE NEGOCE INTERNATIONALE (SNEPAC) SARL | AZ1: SOCIETE SENEGALAISE DES PHOSPHATES DE THIES (SSPT) | BA1: SOCOCIM INDUSTRIES | BB1: SODEMINES | BC1: SONKO ET FILS SARL | BD1: SORED-MINES SA | BE1: STRATEX-EMC SA | BF1: SWAMI MINES SA | BG1: TALIX-MINES | BH1: TANOR SAS | BI1: VAPROM AFRICA SA | BJ1: Makabingui Gold Operations S.A | BK1: ENTREPRISE MAPATHE NDIOUCK SA | BL1: CONSULTING BUSINESS AGENCY | BM1: DIYAN EXPLOITATION MINIERE SUARL | BN1: ENTREPRISE OUSMANE SOW | BO1: NEW ENERGY INVESTMENT SARL | BP1: SOCIETE DE MANUFACTURE DE PRODUCTION INDUSTRIELLE DU SENEGAL (SOMAPIS) | BQ1: TRIYANGS INTERNATIONAL MINING GROUP SA
A2: nbr_fourn_loc | B2: 0 | C2: 60 | D2: 108 | E2: 7 | F2: 0 | G2: 0 | H2: 3 | I2: 0 | J2: 8 | K2: 4 | L2: 11 | M2: 0 | N2: 0 | O2: 0 | P2: 3 | Q2: 243 | R2: 112 | S2: 0 | U2: 1 | V2: 270 | W2: 77 | X2: 0 | Y2: 250 | Z2: 19 | AB2: 0 | AC2: 13 | AD2: 0 | AE2: 162 | AF2: 738 | AG2: 0 | AH2: 0 | AI2: 687 | AJ2: 0 | AK2: 0 | AL2: 5 | AM2: 0 | AO2: 267 | AP2: 10 | AQ2: 0 | AR2: 13 | AS2: 109 | AT2: 6 | AU2: 0 | AV2: 75 | AW2: 2 | AX2: 106 | AY2: 43 | BA2: 605 | BB2: 0 | BD2: 0 | BE2: 0 | BG2: 0 | BH2: 52 | BI2: 0
A3: ttl_paye_fourn_loc | B3: 0 | C3: 695697 | D3: 1386313 | E3: 96890 | F3: 0 | G3: 0 | H3: 1101008 | I3: 0 | J3: 0 | L3: 1040074 | N3: 0 | O3: 0 | P3: 11999 | Q3: 66460438 | R3: 195000 | S3: 0 | T3: 287967 | U3: 0 | V3: 24276063 | W3: 0 | X3: 0 | Y3: 13110174 | Z3: 219614 | AB3: 0 | AC3: 285445 | AD3: 0 | AE3: 5690891 | AF3: 0 | AG3: 0 | AH3: 0 | AI3: 863089098 | AJ3: 0 | AK3: 0 | AL3: 51558720 | AM3: 0 | AO3: 174891063 | AP3: 352821 | AQ3: 0 | AR3: 927073 | AS3: 3090505 | AT3: 329000000 | AU3: 0 | AV3: 0 | AW3: 0 | AX3: 0 | AY3: 135985 | BB3: 0 | BD3: 0 | BE3: 0 | BG3: 0 | BI3: 0
A4: pct_paye_fourn_loc | B4: 0 | C4: 95 | D4: 83 | E4: 100 | F4: 0 | G4: 0 | H4: 0 | I4: 0 | J4: 90 | L4: 73 | N4: 0 | O4: 0 | P4: 0 | Q4: 0 | R4: 75 | S4: 0 | T4: 95 | U4: 25 | V4: 0 | W4: 100 | X4: 0 | Y4: 83 | Z4: =Z3/($Z$3+$Z$6) -> 0.32140955 | AB4: 0 | AC4: 100 | AD4: 0 | AE4: 63 | AF4: 24 | AG4: 0 | AH4: 0 | AI4: 0 | AJ4: 0 | AK4: 0 | AL4: 0 | AM4: 0 | AO4: 76 | AP4: 99 | AQ4: 0 | AR4: 0 | AS4: 0 | AT4: 0 | AU4: 0 | AV4: 0 | AW4: 0 | AX4: 0 | AY4: 97 | BA4: 113801181 | BB4: 0 | BC4: 90 | BD4: 0 | BE4: 0 | BG4: 0 | BH4: 67 | BI4: 0
A5: nbr_fourn_etrg | B5: 0 | C5: 2 | D5: 9 | E5: 0 | F5: 0 | G5: 0 | H5: 1 | I5: 1 | J5: 2 | L5: 2 | M5: 0 | N5: 0 | O5: 0 | P5: 0 | Q5: 146 | R5: 15 | S5: 0 | T5: 1 | U5: 0 | V5: 92 | W5: 0 | X5: 0 | Y5: 49 | Z5: 6 | AB5: 0 | AC5: 0 | AD5: 0 | AE5: 29 | AF5: 432 | AG5: 0 | AH5: 0 | AI5: 0 | AJ5: 0 | AK5: 0 | AL5: 2 | AM5: 0 | AO5: 244 | AP5: 1 | AQ5: 0 | AR5: 1 | AS5: 8 | AT5: 0 | AU5: 0 | AV5: 0 | AW5: 1 | AX5: 33 | AY5: 3 | BA5: 209 | BB5: 0 | BD5: 0 | BE5: 0 | BG5: 0 | BH5: 6 | BI5: 0
A6: ttl_pay_fourn_etrg | B6: 0 | C6: 32805 | D6: 280323 | E6: 0 | F6: 0 | G6: 0 | H6: 400000 | I6: 60000 | J6: 0 | L6: 386847 | N6: 0 | O6: 0 | P6: 0 | Q6: 150359299 | R6: 49000 | S6: 0 | T6: 0 | U6: 0 | V6: 26717258 | W6: 0 | X6: 0 | Y6: 1769824 | Z6: 463670 | AB6: 0 | AC6: 0 | AD6: 0 | AE6: 3248075 | AF6: 0 | AG6: 0 | AH6: 0 | AI6: 0 | AJ6: 0 | AK6: 0 | AL6: 26434989 | AM6: 0 | AO6: 56052595 | AP6: 4845 | AQ6: 0 | AR6: 13119 | AS6: 525272 | AT6: 0 | AU6: 0 | AV6: 0 | AW6: 0 | AX6: 0 | AY6: 31778 | BA6: 77637503 | BB6: 0 | BD6: 0 | BE6: 0 | BG6: 0 | BI6: 0
A7: pct_pay_fourn_etrg | B7: 0 | C7: 5 | D7: 17 | E7: 0 | F7: 0 | G7: 0 | H7: 0 | I7: 100 | J7: 10 | L7: 27 | N7: 0 | O7: 0 | P7: 0 | Q7: 0 | R7: 25 | S7: 0 | T7: 0 | U7: 0 | V7: 0 | W7: 0 | X7: 0 | Y7: 7 | Z7: =Z6/($Z$3+$Z$6) -> 0.67859045 | AB7: 0 | AC7: 0 | AD7: 0 | AE7: 36 | AF7: 76 | AG7: 0 | AH7: 0 | AI7: 0 | AJ7: 0 | AK7: 0 | AL7: 0 | AM7: 0 | AO7: 24 | AP7: 1 | AQ7: 0 | AR7: 0 | AS7: 0 | AT7: 0 | AU7: 0 | AV7: 0 | AW7: 0 | AX7: 0 | AY7: 3 | BB7: 0 | BC7: 10 | BD7: 0 | BE7: 0 | BG7: 0 | BH7: 23 | BI7: 0
A8: F1 ACHATS RECALCULES | B8: =B10+B11+SUM(B21:B29) -> 39277 | C8: =C10+C11+SUM(C21:C29) -> 1435824 | D8: =D10+D11+SUM(D21:D29) -> 165567 | E8: =E10+E11+SUM(E21:E29) -> 35302 | F8: =F10+F11+SUM(F21:F29) -> 147282 | G8: =G10+G11+SUM(G21:G29) -> 0 | H8: =H10+H11+SUM(H21:H29) -> 74110 | I8: =I10+I11+SUM(I21:I29) -> 121200 | J8: =J10+J11+SUM(J21:J29) -> 46899 | K8: =+K9 -> 2518 | L8: =L10+L11+SUM(L21:L29) -> 1094958 | M8: 1964414 | N8: =N10+N11+SUM(N21:N29) -> 1001 | O8: =O10+O11+SUM(O21:O29) -> 6881.32 | P8: =P10+P11+SUM(P21:P29) -> 5791 | Q8: =Q10+Q11+SUM(Q21:Q29) -> 95711292 | R8: =R10+R11+SUM(R21:R29) -> 7231304.7 | S8: =S10+S11+SUM(S21:S29) -> 6133228 | T8: =T10+T11+SUM(T21:T29) -> 57427 | U8: =U10+U11+SUM(U21:U29) -> 22013 | ... BH8: =BH10+BH11+SUM(BH21:BH29) -> 666649 | BI8: =BI9 -> 330968 | BJ8: =BJ10+BJ11+SUM(BJ21:BJ29) -> 169228.56 | BK8: =BK10+BK11+SUM(BK21:BK29) -> 0 | BL8: =BL10+BL11+SUM(BL21:BL29) -> 0 | BM8: =BM10+BM11+SUM(BM21:BM29) -> 0 | BN8: =BN10+BN11+SUM(BN21:BN29) -> 0 | BO8: =BO10+BO11+SUM(BO21:BO29) -> 0 | BP8: =BP10+BP11+SUM(BP21:BP29) -> 0 | BQ8: =BQ10+BQ11+SUM(BQ21:BQ29) -> 0
A9: F1 ACHATS | B9: =+B27 -> 39277 | C9: 0 | D9: 165567 | E9: =11300+6792 -> 18092 | F9: =F8 -> 147282 | G9: 0 | H9: =H12+H21+H26+H28 -> 74110 | I9: =+I12+I28+I29 -> 121200 | J9: =+J16+J25+J26 -> 46899 | K9: 2518 | L9: 201840 | M9: 0 | N9: 1001 | O9: 6881.32 | P9: 0 | Q9: =Q10+Q11+Q21+Q22+Q23+Q24+Q25+Q26+Q27+Q28+Q29 -> 95711292 | R9: =R10+R11+R23+R25+R26+R27+R29+R24 -> 7231304.7 | S9: 6133228 | T9: 57427 | U9: 0 | V9: 39486954 | W9: 825248 | X9: 2027516 | Y9: =Y8 -> 3325679 | Z9: =+Z25+Z26+Z27 -> 207384 | AA9: 425969.18 | AB9: 24061009 | AC9: 224737 | AD9: 2462.277 | AE9: =AE8 -> 349152 | AF9: =AF10+AF11+AF22+AF23+AF25+AF27+AF29 -> 172148520 | AG9: 127567.05 | AH9: 0 | AI9: 383378.68 | AJ9: 0 | AK9: 0 | AL9: 0 | AM9: =AM8 -> 28973479 | AN9: =AN8 -> 248263.9 | AO9: 68569569 | AP9: 45928 | AQ9: =AQ11+SUM(AQ21:AQ29) -> 507384 | AR9: =AR11+SUM(AR21:AR29) -> 195386 | AS9: 1360318 | AT9: =AT10+AT12+AT21+AT22+AT25+AT26+AT27+AT28 -> 95651.867 | AU9: 44200.929 | AV9: =AV10+AV11+AV21+AV22+AV23+AV25+AV26+AV27+AV29 -> 780773 | AX9: 11892294 | AY9: 82857 | AZ9: =AZ8 -> 602490.84 | BA9: =BA11+BA10+SUM(BA21:BA23) -> 119510891 | BB9: =BB8 -> 34680 | BC9: 347 | BD9: 1678237 | BE9: 26830 | BF9: 375425 | BG9: =BG8 -> 675098 | BH9: =BH10+BH12+SUM(BH21:BH29) -> 666649 | BI9: 330968 | BJ9: 169503.38
A10: matier_consmbl | B10: 0 | C10: 10377 | D10: 0 | E10: 0 | F10: 0 | G10: 0 | H10: 0 | I10: 0 | J10: 0 | L10: 201840 | M10: 0 | N10: 0 | O10: 0 | P10: 0 | Q10: 6602432 | R10: 1893399.1 | S10: 2240932 | T10: 0 | U10: 3514 | V10: 6908752 | W10: 0 | X10: 0 | Y10: 0 | Z10: 0 | AA10: 125451 | AB10: 631936 | AC10: 0 | AD10: 0 | AE10: 20675 | AF10: 125925416 | AG10: 0 | AH10: 0 | AI10: 5645.875 | AJ10: 0 | AK10: 0 | AL10: 0 | AM10: 9176655 | AN10: 165058 | AO10: 34000619 | AP10: 0 | AQ10: 0 | AR10: 0 | AS10: 4318 | AT10: 26315 | AU10: 0 | AV10: 317692 | AX10: 1530145 | AY10: 9455 | AZ10: 71607.974 | BA10: 69919486 | BB10: 13100 | BC10: 0 | BD10: 730365 | BE10: 0 | BF10: 2574.525 | BG10: 0 | BH10: 12658 | BI10: 0
A11: matier_combustbl RECALCULEE | B11: =SUM(B13:B20) -> 0 | C11: =SUM(C13:C20) -> 453686 | D11: =SUM(D13:D20) -> 0 | E11: =SUM(E13:E20) -> 14300 | F11: =SUM(F13:F20) -> 95174 | G11: =SUM(G13:G20) -> 0 | H11: =SUM(H13:H20) -> 33 | I11: =SUM(I14:I20) -> 43200 | J11: =SUM(J13:J20) -> 16468 | K11: =SUM(K13:K20) -> 0 | L11: =SUM(L13:L20) -> 820343 | M11: 0 | N11: =SUM(N13:N20) -> 0 | O11: =SUM(O13:O20) -> 0 | P11: =SUM(P13:P20) -> 131 | Q11: =SUM(Q13:Q20) -> 75199228 | R11: =SUM(R13:R20) -> 2211495 | S11: =SUM(S13:S20) -> 2548052 | T11: =SUM(T13:T20) -> 57427 | U11: =SUM(U13:U20) -> 5650 | ... BQ11: =SUM(BQ13:BQ20) -> 0
A12: matier_combustbl | B12: 0 | C12: =+SUM(C13:C20) -> 453686 | D12: 0 | E12: =SUM(E13:E20) -> 14300 | F12: =F15 -> 95174 | G12: 0 | H12: =H16 -> 33 | I12: =SUM(I13:I20) -> 43200 | J12: =+J16 -> 16468 | L12: 820343 | M12: 163111 | N12: 0 | O12: 0 | P12: 0 | Q12: 75199228 | R12: 0 | S12: 0 | T12: 57427 | U12: 5650 | V12: 23715528 | W12: 0 | X12: =X17+X18+X22+X23+X25+X26+X27+X29 -> 2027776 | Y12: 0 | Z12: 0 | AA12: 215146.83 | AB12: 0 | AC12: 102967 | AD12: 0 | AE12: 281706 | AF12: 191791 | AG12: 127567.05 | AH12: 0 | AI12: 14747.926 | AJ12: 0 | AK12: 0 | AL12: 0 | AM12: 16720084 | AO12: 0 | AP12: 0 | AQ12: 0 | AR12: 151721 | AS12: =AS11 -> 584108 | AT12: 29846.215 | AU12: 0 | AV12: 0 | AX12: =AX14+AX18+AX20 -> 1530145 | AY12: 34215 | BA12: 35459444 | BB12: 0 | BC12: 33 | BD12: 0 | BE12: 0 | BF12: 292803.87 | BG12: 0 | BH12: =SUM(BH13:BH20) -> 444429 | BI12: 0 | BJ12: 274
A13: gaz_industriel | B13: 0 | C13: 0 | D13: 0 | E13: 0 | F13: 0 | G13: 0 | H13: 0 | I13: 0 | J13: 0 | L13: 588 | M13: 0 | N13: 0 | O13: 0 | P13: 0 | Q13: 0 | R13: 0 | S13: 0 | T13: 0 | U13: 0 | V13: 0 | W13: 0 | X13: 0 | Y13: 0 | Z13: 0 | AB13: 0 | AC13: 0 | AD13: 0 | AE13: 0 | AF13: 0 | AG13: 0 | AH13: 0 | AI13: 0 | AJ13: 0 | AK13: 0 | AL13: 0 | AM13: 0 | AO13: 44927 | AP13: 0 | AQ13: 0 | AR13: 0 | AS13: 0 | AT13: 950 | AU13: 0 | AV13: 0 | AX13: 0 | AY13: 0 | BB13: 0 | BC13: 0 | BD13: 0 | BE13: 0 | BG13: 0 | BH13: 5667 | BI13: 0
A14: gaz_naturel | B14: 0 | C14: 0 | D14: 0 | E14: 0 | F14: 0 | G14: 0 | H14: 0 | I14: 0 | J14: 0 | L14: 0 | M14: 0 | N14: 0 | O14: 0 | P14: 0 | Q14: 0 | R14: 0 | S14: 0 | T14: 0 | U14: 0 | V14: 0 | W14: 0 | X14: 0 | Y14: 0 | Z14: 0 | AB14: 0 | AC14: 0 | AD14: 0 | AE14: 0 | AF14: 0 | AG14: 0 | AH14: 0 | AI14: 59 | AJ14: 0 | AK14: 0 | AL14: 0 | AM14: 0 | AO14: 0 | AP14: 0 | AQ14: 0 | AR14: 0 | AS14: 0 | AT14: 0 | AU14: 0 | AV14: 0 | AX14: 9197 | AY14: 0 | BB14: 0 | BC14: 0 | BD14: 0 | BE14: 0 | BG14: 0 | BH14: 0 | BI14: 0
A15: essence | B15: 0 | C15: 0 | D15: 0 | E15: =2400+3500 -> 5900 | F15: 95174 | G15: 0 | H15: 0 | I15: 0 | J15: 0 | L15: 0 | M15: 0 | N15: 0 | O15: 0 | P15: 0 | Q15: 0 | R15: 0 | T15: =S9-S8 -> 0 | U15: 5650 | V15: 0 | W15: 0 | X15: 0 | Y15: 0 | Z15: 0 | AB15: 289 | AC15: 0 | AD15: 0 | AE15: 0 | AF15: 0 | AG15: 0 | AH15: 0 | AI15: 4896.308 | AJ15: 0 | AK15: 0 | AL15: 0 | AM15: 0 | AO15: 0 | AP15: 0 | AQ15: 0 | AR15: 0 | AS15: 0 | AT15: 9815.24 | AU15: 0 | AV15: 0 | AX15: 0 | AY15: 0 | BB15: 0 | BC15: 0 | BD15: 0 | BE15: 0 | BG15: 6.1631257 | BH15: 0 | BI15: 0
A16: gas_oil | B16: 0 | C16: 453426 | D16: 0 | E16: =600+7800 -> 8400 | F16: 0 | G16: 0 | H16: 33 | I16: 43200 | J16: 16468 | L16: 814080 | M16: 0 | N16: 0 | O16: 0 | P16: 0 | Q16: 12614951 | R16: 2109355.7 | S16: 2367347 | T16: 57427 | U16: 0 | V16: 2361104 | W16: 0 | X16: 0 | Y16: 2160746 | Z16: 0 | AA16: 215146.83 | AB16: 14565589 | AC16: 89165 | AD16: 0 | AE16: 261031 | AF16: 10249603 | AG16: 127567.05 | AH16: 0 | AI16: 3985.115 | AJ16: 0 | AK16: 1401 | AL16: 0 | AM16: 0 | AO16: 13357307 | AP16: 45928 | AQ16: 154606 | AR16: 0 | AS16: 581039 | AT16: 15560 | AU16: 400 | AV16: 0 | AX16: 0 | AY16: 34215 | BB16: 4000 | BC16: 33 | BD16: 0 | BE16: 0 | BG16: 268683.52 | BH16: 348236 | BI16: 0 | BJ16: 113376.08
A17: fuel_oil | B17: 0 | C17: 0 | D17: 0 | E17: 0 | F17: 0 | G17: 0 | H17: 0 | I17: 0 | J17: 0 | L17: 0 | M17: 0 | N17: 0 | O17: 0 | P17: 131 | Q17: 10993827 | R17: 0 | S17: 0 | T17: 0 | U17: 0 | V17: 0 | W17: 0 | X17: 1743942 | Y17: 420764 | Z17: 0 | AB17: 0 | AC17: 0 | AD17: 0 | AE17: 0 | AF17: 39192 | AG17: 0 | AH17: 0 | AI17: 0 | AJ17: 0 | AK17: 0 | AL17: 0 | AM17: 16720084 | AO17: 13099935 | AP17: 0 | AQ17: 0 | AR17: 151721 | AS17: 0 | AT17: 0 | AU17: 0 | AV17: 269910 | AX17: 0 | AY17: 0 | BA17: 1091362 | BB17: 0 | BC17: 0 | BD17: 0 | BE17: 0 | BG17: 16776.028 | BH17: 0 | BI17: 0
A18: huile_lubrif | B18: 0 | C18: 260 | D18: 0 | E18: 0 | F18: 0 | G18: 0 | H18: 0 | I18: 0 | J18: 0 | L18: 5675 | M18: 0 | N18: 0 | O18: 0 | P18: 0 | Q18: 382524 | R18: 34413.37 | S18: 180705 | T18: 0 | U18: 0 | V18: 0 | W18: 0 | X18: 19192 | Y18: 188214 | Z18: 0 | AB18: 599568 | AC18: 13046 | AD18: 0 | AE18: 0 | AF18: 0 | AG18: 0 | AH18: 0 | AI18: 5807.503 | AJ18: 0 | AK18: 0 | AL18: 0 | AM18: 65341 | AO18: 1887454 | AP18: 0 | AQ18: 16677 | AS18: 0 | AT18: 3520.975 | AU18: 0 | AV18: 1680 | AX18: 118148 | AY18: 0 | BB18: 1580 | BC18: 0 | BD18: 0 | BE18: 0 | BG18: 0 | BH18: 15349 | BI18: 0
A19: charbon | B19: 0 | C19: 0 | D19: 0 | E19: 0 | F19: 0 | G19: 0 | H19: 0 | I19: 0 | J19: 0 | L19: 0 | M19: 0 | N19: 0 | O19: 0 | P19: 0 | Q19: 51159937 | R19: 0 | S19: 0 | T19: 0 | U19: 0 | V19: 21354425 | W19: 0 | X19: 0 | Y19: 0 | Z19: 0 | AB19: 0 | AC19: 0 | AD19: 0 | AE19: 0 | AF19: 16424365 | AG19: 0 | AH19: 0 | AI19: 0 | AJ19: 0 | AK19: 0 | AL19: 0 | AM19: 0 | AO19: 0 | AP19: 0 | AQ19: 0 | AR19: 0 | AS19: 0 | AT19: 0 | AU19: 0 | AV19: 0 | AX19: 0 | AY19: 0 | BA19: 23238259 | BB19: 0 | BC19: 0 | BD19: 0 | BE19: 0 | BG19: 0 | BH19: 0 | BI19: 0
A20: autre_combustbl | B20: 0 | C20: 0 | D20: 0 | E20: 0 | F20: 0 | G20: 0 | H20: 0 | I20: 0 | J20: 0 | L20: 0 | M20: 0 | N20: 0 | O20: 0 | P20: 0 | Q20: 47989 | R20: 67725.933 | S20: 0 | T20: 0 | U20: 0 | V20: 0 | W20: 0 | X20: 0 | Y20: 0 | Z20: 0 | AB20: 0 | AC20: 756 | AD20: 0 | AE20: 0 | AG20: 0 | AH20: 0 | AI20: 0 | AJ20: 0 | AK20: 0 | AL20: 0 | AM20: 0 | AO20: 0 | AP20: 0 | AQ20: 160865 | AR20: 3530 | AS20: 3069 | AT20: 0 | AU20: 197 | AV20: 0 | AX20: 1402800 | AY20: 0 | BA20: 11169823 | BB20: 0 | BC20: 0 | BD20: 0 | BE20: 0 | BG20: 380924.82 | BH20: 75177 | BI20: 0
A21: fourn_bureau_infmtq | B21: 0 | C21: 4250 | D21: 4319 | E21: =752+9000 -> 9752 | F21: 0 | G21: 0 | H21: 70838 | I21: 0 | J21: 0 | L21: 0 | M21: 0 | N21: 0 | O21: 1926.77 | P21: 0 | Q21: 135940 | R21: 0 | S21: 14002 | T21: 0 | U21: 1642 | V21: 8535130 | W21: 0 | X21: 0 | Y21: 0 | Z21: 0 | AB21: 16576 | AC21: 300 | AD21: 386.41 | AE21: 0 | AF21: 0 | AG21: 0 | AH21: 0 | AI21: 0 | AJ21: 0 | AK21: 0 | AL21: 0 | AM21: 147284 | AO21: 127499 | AP21: 0 | AQ21: 0 | AR21: 13 | AS21: 0 | AT21: 200 | AU21: 569 | AV21: 707 | AX21: 1402800 | AY21: 1667 | BA21: 63545 | BB21: 2500 | BC21: 0 | BD21: 0 | BE21: 0 | BF21: 933.22 | BG21: 334.34957 | BH21: 7535 | BI21: 0 | BJ21: 66
A22: eau | B22: 0 | C22: 242 | D22: 897 | E22: =140+700 -> 840 | F22: 0 | G22: 0 | H22: 0 | I22: 0 | J22: 0 | L22: 0 | M22: 497 | N22: 35 | O22: 825.758 | P22: 0 | Q22: 3987 | R22: 0 | S22: 441 | T22: 0 | U22: 1110 | V22: 53553 | W22: 8 | X22: 36823 | Y22: 4364 | Z22: 0 | AA22: 725 | AB22: 33275 | AC22: 0 | AD22: 269.19 | AE22: 563 | AF22: 400608 | AG22: 0 | AH22: 0 | AI22: 146.25 | AJ22: 0 | AK22: 0 | AL22: 0 | AM22: 4102 | AN22: 414.8 | AO22: 1642 | AP22: 0 | AQ22: 4209 | AR22: 5329 | AS22: 6838 | AT22: 3540 | AU22: 0 | AV22: 4229 | AX22: 1562 | AY22: 1026 | AZ22: 6780.6 | BA22: 375925 | BB22: 7500 | BC22: 0 | BD22: 56 | BE22: 84 | BG22: 208.51909 | BH22: 45 | BI22: 0 | BJ22: 591.813
A23: electricite | B23: 0 | C23: 26929 | D23: 6050 | E23: =1400+3800 -> 5200 | F23: 0 | G23: 0 | H23: 0 | I23: 0 | J23: 0 | L23: 0 | M23: 3933 | N23: 40 | O23: 1582.704 | P23: 0 | Q23: 13435 | R23: 827071.09 | S23: 139841 | T23: 0 | U23: 3765 | V23: 13232 | W23: 0 | X23: 10294 | Y23: 249788 | Z23: 0 | AA23: 137116 | AB23: 0 | AC23: 1350 | AD23: 631.285 | AE23: 11361 | AF23: 2257540 | AG23: 0 | AH23: 0 | AI23: 530.3 | AJ23: 0 | AK23: 0 | AL23: 0 | AM23: 4719 | AN23: 13011.6 | AO23: 13599 | AP23: 0 | AQ23: 131790 | AR23: 210 | AS23: 12823 | AT23: 0 | AU23: 0 | AV23: 150803 | AX23: 268269 | AY23: 1440 | AZ23: 159964.97 | BA23: 13652491 | BB23: 1200 | BC23: 0 | BD23: 599 | BE23: 105 | BF23: 201879.46 | BG23: 452.47614 | BH23: 135530 | BI23: 0 | BJ23: 1023.348
A24: autre_energ | B24: 0 | D24: 111946 | E24: 0 | F24: 0 | G24: 0 | H24: 0 | I24: 0 | J24: 0 | L24: 0 | M24: 0 | N24: 0 | O24: 577.876 | P24: 0 | Q24: 136844 | R24: 11853 | S24: 2018 | T24: 0 | U24: 0 | V24: 71313 | W24: 177330 | X24: 0 | Y24: 76046 | Z24: 0 | AB24: 0 | AC24: 0 | AD24: 192.7 | AE24: 3755 | AF24: 0 | AG24: 0 | AH24: 0 | AI24: 206209.88 | AJ24: 0 | AK24: 0 | AL24: 0 | AM24: 0 | AN24: 4049.5 | AO24: 0 | AP24: 0 | AQ24: 17861 | AR24: 13882 | AS24: 15913 | AT24: 0 | AU24: 0 | AV24: 0 | AX24: 5903271.8 | AY24: 0 | AZ24: 171902.26 | BB24: 0 | BC24: 0 | BD24: 856772 | BE24: 20894 | BF24: 3137.47 | BG24: 0 | BH24: 0 | BI24: 0
A25: fourn_bureau_nonstockbl | B25: 0 | C25: 0 | D25: 15697 | E25: 210 | F25: 39 | G25: 0 | H25: 0 | I25: 0 | J25: 359 | L25: 493 | M25: 8888 | N25: 25 | O25: 385.508 | P25: 0 | Q25: 12160 | R25: 32856 | S25: 0 | T25: 0 | U25: 0 | V25: 32490 | W25: 0 | X25: 101616 | Y25: 0 | Z25: 255 | AA25: 2981.166 | AB25: 461 | AC25: 0 | AD25: 108.5 | AE25: 6285 | AF25: 144419 | AG25: 0 | AH25: 0 | AI25: 1649.422 | AJ25: 0 | AK25: 0 | AL25: 0 | AM25: 0 | AN25: 1034.5 | AO25: 1115363 | AP25: 0 | AQ25: 11478 | AR25: 678 | AS25: 9598 | AT25: 2850 | AU25: 0 | AV25: 5250 | AX25: 41987 | AY25: 0 | AZ25: 22341.004 | BB25: 800 | BC25: 5 | BD25: 4372 | BE25: 82 | BG25: 252.68815 | BH25: 520 | BI25: 0
A26: achat_materl_outilg | B26: 0 | C26: 0 | E26: 0 | F26: 0 | G26: 0 | H26: 3135 | I26: 0 | J26: 30072 | L26: 5940 | M26: 33728 | N26: 901 | O26: 550.506 | P26: 0 | Q26: 234607 | R26: 33919.526 | S26: 29621 | T26: 0 | U26: 2200 | V26: 100759 | W26: 43919 | X26: 26627 | Y26: 122718 | Z26: 171463 | AA26: 24050.966 | AB26: 2646352 | AC26: 114679 | AD26: 231.8 | AE26: 25517 | AF26: 0 | AG26: 0 | AH26: 0 | AI26: 8676.548 | AJ26: 0 | AK26: 0 | AL26: 0 | AM26: 1515691 | AO26: 784111 | AP26: 0 | AQ26: 6792 | AR26: 1478 | AS26: 2303 | AT26: 1225 | AU26: 709.898 | AV26: 20874 | AX26: 220500 | AY26: 3039 | BB26: 4000 | BC26: 246 | BD26: 67567 | BE26: 5665 | BF26: 108791.67 | BG26: 7297.6544 | BH26: 21472 | BI26: 0 | BJ26: 43163
A27: achat_etud_servc | B27: 39277 | C27: 900240 | D27: 8028 | E27: 0 | F27: 52037 | G27: 0 | H27: 0 | I27: 0 | J27: 0 | L27: 64637 | M27: 229490 | N27: 0 | O27: 344.066 | P27: 500 | Q27: 128625 | R27: 2205027 | S27: 0 | T27: 0 | U27: 4132 | V27: 55037 | W27: 35866 | X27: 89029 | Y27: 0 | Z27: 35666 | AA27: 35309.689 | AB27: 2361337 | AC27: 0 | AD27: 473.72 | AE27: 0 | AF27: 12536467 | AG27: 0 | AH27: 0 | AI27: 5371.657 | AJ27: 0 | AK27: 0 | AL27: 0 | AM27: 1296777 | AN27: 23093.1 | AO27: 556808 | AP27: 0 | AQ27: 1250 | AR27: 17192 | AS27: 3660 | AT27: 7380 | AU27: 42324.131 | AV27: 5667 | AX27: 639645 | AY27: 31500 | AZ27: 247 | BB27: 0 | BC27: 53 | BD27: 676 | BE27: 0 | BF27: 58108.604 | BG27: 27.734065 | BH27: 11578 | BI27: 0
A28: achat_materl_equip | B28: 0 | C28: 40100 | D28: 18630 | E28: 0 | F28: 32 | G28: 0 | H28: 104 | I28: 60000 | L28: 1705 | M28: 1520594 | N28: 0 | O28: 0 | P28: 0 | Q28: 8893 | R28: 0 | S28: 1158321 | T28: 0 | U28: 0 | W28: 567037 | X28: 0 | Y28: 28373 | Z28: 0 | AB28: 2780992 | AC28: 0 | AD28: 0 | AE28: 19965 | AG28: 0 | AH28: 0 | AI28: 139101.57 | AJ28: 0 | AK28: 0 | AL28: 0 | AM28: 42826 | AO28: 1193832 | AP28: 0 | AQ28: 1856 | AR28: 0 | AS28: 124228 | AT28: 24295.652 | AU28: 0 | AV28: 0 | AX28: 176283 | AY28: 515 | BB28: 0 | BC28: 10 | BD28: 15983 | BE28: 0 | BG28: 134.04798 | BH28: 23687 | BI28: 0 | BJ28: 139
A29: autre_achat | B29: 0 | C29: 0 | D29: 0 | E29: =1500+3500 -> 5000 | F29: 0 | G29: 0 | H29: 0 | I29: 18000 | L29: 0 | M29: 4173 | N29: 0 | O29: 688.132 | P29: 5160 | Q29: 13235141 | R29: 15684 | S29: 0 | T29: 0 | U29: 0 | V29: 1159 | W29: 1089 | X29: 253 | Y29: 74666 | Z29: 0 | AA29: 10639.539 | AB29: 424634 | AC29: 5442 | AD29: 168.672 | AE29: 0 | AF29: 4170910 | AG29: 0 | AH29: 0 | AI29: 1299.25 | AJ29: 0 | AK29: 0 | AL29: 0 | AN29: 41602.4 | AO29: 2386473 | AP29: 0 | AQ29: 0 | AR29: 1353 | AS29: 175336 | AT29: 0 | AU29: 0 | AV29: 3961 | AX29: 177686 | AY29: 0 | AZ29: 169647.04 | BB29: 0 | BC29: 0 | BD29: 1847 | BE29: 0 | BG29: 0 | BH29: 9195 | BI29: 0 | BJ29: 10869.319
A30: F2 TRANSPORTS RECALCULES | B30: =B32+B33 -> 0 | C30: =C32+C33 -> 33414 | D30: =D32+D33 -> 61651 | E30: =E32+E33 -> 32340 | F30: =F32+F33 -> 0 | G30: =G32+G33 -> 0 | H30: =H32+H33 -> 0 | I30: =I32+I33 -> 7500 | J30: =J32+J33 -> 0 | K30: =+K31 -> 2264 | L30: =L32+L33 -> 8474 | M30: 107561 | N30: =N32+N33 -> 0 | O30: =O32+O33 -> 8476.706 | P30: =P32+P33 -> 1032 | Q30: =Q32+Q33 -> 482701 | R30: =R32+R33 -> 1624036 | S30: =S32+S33 -> 136661 | T30: =T32+T33 -> 0 | U30: =U32+U33 -> 0 | ... BQ30: =BQ32+BQ33 -> 0
A31: F2 TRANSPORTS | C31: =+SUM(C32:C33) -> 33414 | D31: =D32+D33 -> 61651 | E31: =E32 -> 32340 | I31: =I32+I33 -> 7500 | K31: 2264 | L31: =L30 -> 8474 | M31: 0 | O31: =O32 -> 8476.706 | Q31: =Q32 -> 482701 | R31: =R32+R33 -> 1624036 | S31: =S32+S33 -> 136661 | V31: =V32 -> 240429 | W31: =W32+W33 -> 9927 | X31: =X32 -> 1109412 | Y31: =Y32+Y33 -> 5588917 | Z31: =Z32 -> 5140 | AA31: 20842.859 | AB31: =AB32+AB33 -> 4064697 | AD31: 1154.335 | AE31: =AE32+AE33 -> 146272 | AF31: 44154306 | AG31: =AG33 -> 7149.555 | AH31: =AH33 -> 150 | AI31: 37859.894 | AM31: =AM32+AM33 -> 1938920 | AN31: 20851 | AO31: =+AO32+AO33 -> 1733591 | AP31: 1246 | AQ31: 124038 | AR31: =AR32+AR33 -> 546211 | AS31: 268481 | AT31: =AT32+AT33 -> 2050 | AU31: =AU32+AU33 -> 122 | AV31: =AV32 -> 5961 | AX31: 11522786 | AY31: =AY32+AY33 -> 2683 | AZ31: =AZ32+AZ33 -> 669263.68 | BA31: 1340085 | BD31: 391675 | BE31: 155 | BF31: 140.13 | BG31: 1211 | BH31: 52051 | BJ31: 24100.933
A32: transprt_marchnds | B32: 0 | C32: 40 | D32: 61472 | E32: 32340 | F32: 0 | G32: 0 | H32: 0 | I32: 1200 | J32: 0 | L32: 4237 | M32: 8690 | N32: 0 | O32: 8476.706 | P32: 1032 | Q32: 482701 | R32: 1504078 | S32: 135751 | T32: 0 | U32: 0 | V32: 240429 | W32: 9196 | X32: 1109412 | Y32: 5521917 | Z32: 5140 | AB32: 3391775 | AC32: 0 | AE32: 3179 | AF32: 42895750 | AG32: 0 | AI32: 37859.894 | AJ32: 0 | AK32: 0 | AL32: 0 | AM32: 1050628 | AN32: =60+19493 -> 19553 | AO32: 1093199 | AP32: 1246 | AQ32: 124038 | AR32: 537211 | AS32: 255773 | AT32: 1900 | AU32: 122 | AV32: 5961 | AW32: 0 | AX32: 11465244 | AY32: 2656 | AZ32: 617859.68 | BA32: 1085925 | BB32: 0 | BC32: 0 | BD32: 368635 | BE32: 155 | BH32: 30901 | BI32: 0
A33: transprt_persnl | B33: 0 | C33: 33374 | D33: 179 | E33: 0 | F33: 0 | G33: 0 | H33: 0 | I33: 6300 | J33: 0 | L33: 4237 | M33: 98871 | N33: 0 | O33: 0 | P33: 0 | Q33: 0 | R33: 119958 | S33: 910 | T33: 0 | U33: 0 | V33: 0 | W33: 731 | X33: 0 | Y33: 67000 | Z33: 0 | AA33: 20842.859 | AB33: 672922 | AC33: 0 | AD33: =AD31 -> 1154.335 | AE33: 143093 | AF33: 1258656 | AG33: 7149.555 | AH33: 150 | AJ33: 15000 | AK33: 0 | AL33: 0 | AM33: 888292 | AN33: 1298.6 | AO33: 640392 | AP33: 0 | AQ33: 0 | AR33: 9000 | AS33: 12708 | AT33: 150 | AW33: 0 | AX33: 57543 | AY33: 27 | AZ33: 51404 | BA33: 254161 | BB33: 0 | BC33: 0 | BD33: 23041 | BE33: 0 | BF33: 140 | BG33: 1211 | BH33: 21150 | BI33: 0 | BJ33: 24100.933
A34: F3 SERVICES EXTERIEURS RECALCULES | B34: =SUM(B36:B50) -> 437222 | C34: =SUM(C36:C50) -> 326118 | D34: =SUM(D36:D50) -> 400447 | E34: =SUM(E36:E50) -> 90040 | F34: =SUM(F36:F50) -> 3093 | G34: =SUM(G36:G50) -> 8206 | H34: =SUM(H36:H50) -> 6760 | I34: =SUM(I36:I50) -> 0 | J34: =SUM(J36:J50) -> 469723 | K34: =+K35 -> 7032 | L34: =SUM(L36:L50) -> 128626 | M34: 505926 | N34: =SUM(N36:N50) -> 2230 | O34: =SUM(O36:O50) -> 12792.146 | P34: =SUM(P36:P50) -> 6708 | Q34: =SUM(Q36:Q50) -> 9078504 | R34: =SUM(R36:R50) -> 1561082.7 | S34: =SUM(S36:S50) -> 3560407 | T34: =SUM(T36:T50) -> 5449 | U34: =SUM(U36:U50) -> 64954 | ... BH34: =SUM(BH36:BH50) -> 716057 | BI34: =BI35 -> 161069 | BJ34: =SUM(BJ36:BJ50) -> 870715.67 | BK34: =SUM(BK36:BK50) -> 0 | BL34: =SUM(BL36:BL50) -> 0 | BM34: =SUM(BM36:BM50) -> 0 | BN34: =SUM(BN36:BN50) -> 0 | BO34: =SUM(BO36:BO50) -> 0 | BP34: =SUM(BP36:BP50) -> 0 | BQ34: =SUM(BQ36:BQ50) -> 0
A35: F3 SERVICES EXTERIEURS | B35: =+SUM(B36:B50) -> 437222 | C35: =+SUM(C36:C50) -> 326118 | D35: 400446 | E35: =54000+36040 -> 90040 | F35: =F37+F39+F40 -> 3093 | G35: =G37+G49 -> 8206 | H35: =H36+H37+H40+H41+H43+H45+H47 -> 6760 | I35: 0 | K35: 7032 | L35: 128626 | M35: 0 | N35: 2230 | O35: 12792.146 | P35: 0 | Q35: 9078504 | R35: =R37+R39+R40+R41+R43+R44+R46+R47+R48 -> 1561082.7 | S35: 3560407 | T35: 5449 | U35: 64954 | V35: =V37+V39+V40+V41+V42+V43+V45+V46+V47+V48+V49+V50 -> 6010747 | W35: =W37+W39+W44+W45+W47+W49 -> 292015 | X35: 4603901 | Y35: =Y34 -> 3158085 | Z35: =+Z37+Z39+Z40+Z41+Z45+Z47+Z48+Z50 -> 248478 | AA35: 606892.39 | AB35: =AB34 -> 36167602 | AC35: 42823 | AD35: 104688.85 | AE35: 3552340 | AF35: 37398422 | AG35: 109422.37 | AH35: =AH36+AH37+AH41+AH43+AH44+AH45+AH47 -> 136360 | AI35: 48449.778 | AJ35: 0 | AK35: 0 | AL35: =AL37+AL45+AL47 -> 67062.36 | AM35: =+SUM(AM36:AM50) -> 60944197 | AN35: 49298.4 | AO35: 36856370 | AP35: 176747 | AQ35: =+SUM(AQ36:AQ50) -> 432741 | AR35: 405336 | AS35: =AS36+AS39+AS40+AS41+AS42+AS43+AS45+AS47+AS48+AS49 -> 1213261 | AT35: 12188.72 | AU35: 27304.983 | AV35: 92390 | AX35: =AX36+AX37+AX39+AX40+AX41+AX42+AX43+AX45+AX46+AX47+AX49+AX50 -> 4798263.4 | AY35: 98500 | AZ35: =SUM(AZ36:AZ50) -> 1878796 | BA35: 24372437 | BB35: =BB34 -> 33933 | BC35: =SUM(BC36:BC50) -> 39999 | BD35: 1785365 | BE35: 717289 | BF35: =+SUM(BF36:BF50) -> 206710.55 | BG35: 189507 | BH35: 716057 | BI35: 161069 | BJ35: 870715.67
A36: soustraitc_generl | B36: 377615 | C36: 11191 | D36: 21745 | E36: =E35 -> 90040 | F36: 0 | G36: 0 | H36: 2156 | I36: 0 | J36: =252173+53278 -> 305451 | L36: 0 | M36: 0 | N36: 0 | O36: 0 | P36: 0 | Q36: 0 | R36: 0 | S36: 0 | T36: 0 | U36: 0 | V36: 0 | W36: 0 | X36: 896807 | Y36: 0 | Z36: 0 | AB36: 1598136 | AC36: 24713 | AD36: 0 | AE36: 1239507 | AF36: 0 | AG36: 109422.37 | AH36: 83166 | AI36: 0 | AJ36: 0 | AK36: 0 | AL36: 0 | AM36: 55015094 | AO36: 15601887 | AP36: 0 | AQ36: 0 | AR36: 359780 | AS36: 444305 | AT36: 8800 | AU36: 0 | AV36: 0 | AX36: 1446772 | AY36: 32500 | AZ36: 678111.61 | BA36: 5472913 | BB36: 0 | BC36: 34084 | BD36: 0 | BE36: 696227 | BF36: 84726.066 | BG36: 4114.1952 | BH36: 116549 | BI36: 0
A37: loctn_charg_lctv | B37: 43200 | C37: 3900 | D37: 69111 | F37: 2735 | G37: 1680 | H37: 4090 | I37: 0 | J37: =4090+4090 -> 8180 | L37: 2333 | M37: 44584 | N37: 585 | O37: 1459.2 | P37: 0 | Q37: 3527682 | R37: 27441.48 | S37: 2975383 | T37: 0 | U37: 0 | V37: 150497 | W37: 10375 | X37: 1417523 | Y37: 863424 | Z37: 4610 | AB37: 3926994 | AC37: 3140 | AD37: 6177.6 | AE37: 117862 | AF37: 4040392 | AG37: 0 | AH37: 600 | AI37: 19457.2 | AJ37: 0 | AK37: 0 | AL37: 20680.526 | AM37: 88233 | AO37: 1108460 | AP37: 0 | AQ37: 128958 | AR37: 9493 | AT37: 2050 | AU37: 1200 | AV37: 6947 | AX37: 775349 | AY37: 15640 | AZ37: 155327.54 | BA37: 9254569 | BB37: 6000 | BC37: 4090 | BD37: 7135 | BE37: 3605 | BF37: 34941.203 | BG37: 75456.075 | BH37: 12155 | BI37: 0 | BJ37: 56795.2
A38: redvanc_creditbail | B38: 0 | C38: 0 | D38: 0 | E38: 0 | F38: 0 | G38: 0 | H38: 0 | I38: 0 | J38: 0 | L38: 0 | M38: 0 | N38: 0 | O38: 0 | P38: 0 | Q38: 0 | R38: 0 | S38: 106792 | T38: 0 | U38: 0 | V38: 0 | W38: 0 | X38: 0 | Y38: 0 | Z38: 0 | AB38: 0 | AC38: 0 | AD38: 0 | AE38: 0 | AF38: 0 | AG38: 0 | AH38: 0 | AI38: 0 | AJ38: 0 | AK38: 0 | AL38: 0 | AM38: 0 | AO38: 0 | AP38: 0 | AQ38: 0 | AR38: 0 | AT38: 0 | AU38: 0 | AV38: 0 | AX38: 0 | AY38: 0 | BB38: 0 | BD38: 0 | BE38: 0 | BG38: 75595.747 | BH38: 0 | BI38: 0
A39: entretn_repar_maint | B39: 15836 | C39: 220831 | D39: 21497 | E39: 0 | F39: 286 | G39: 0 | H39: 0 | I39: 0 | J39: 1310 | L39: 793 | M39: 48710 | N39: 0 | O39: 1162 | P39: 0 | Q39: 3529351 | R39: 851652.55 | S39: 181060 | T39: 5449 | U39: 0 | V39: 1456036 | W39: 60237 | X39: 980847 | Y39: 132263 | Z39: 468 | AA39: 572774.9 | AB39: 385267 | AC39: 1470 | AD39: 549.028 | AE39: 17216 | AF39: 14292468 | AG39: 0 | AH39: 0 | AI39: 6053.4 | AJ39: 0 | AK39: 0 | AL39: 0 | AM39: 10939 | AN39: 25616.5 | AO39: 1949929 | AP39: 0 | AQ39: 133921 | AR39: 7977 | AS39: 7084 | AT39: 883.72 | AU39: 2184.961 | AV39: 46595 | AX39: 1355836 | AY39: 6039 | AZ39: 34345.214 | BA39: 401949 | BB39: 5007 | BC39: 1310 | BD39: 181083 | BE39: 0 | BF39: 4596.501 | BG39: 22542.505 | BH39: 421700 | BI39: 0 | BJ39: 23794.83
A40: prime_assur | B40: 0 | C40: 226 | D40: 45263 | E40: 0 | F40: 72 | G40: 0 | H40: 85 | I40: 0 | J40: 426 | L40: 0 | M40: 6979 | N40: 0 | O40: 0 | P40: 0 | Q40: 1206753 | R40: 231196.2 | S40: 6670 | T40: 0 | U40: 0 | V40: 410450 | W40: 0 | X40: 7886 | Y40: 63498 | Z40: 117 | AA40: 2465.677 | AB40: 2339086 | AC40: 0 | AD40: 604.732 | AE40: 44086 | AF40: 4408310 | AG40: 0 | AH40: 0 | AI40: 6813.099 | AJ40: 0 | AK40: 0 | AL40: 0 | AM40: 587949 | AN40: 632 | AO40: 1347878 | AP40: 0 | AQ40: 35692 | AR40: 1285 | AS40: 28287 | AT40: 0 | AU40: 268.084 | AV40: 1098 | AX40: 231474 | AY40: 293 | AZ40: 37450.711 | BA40: 515711 | BB40: 0 | BC40: 86 | BD40: 11432 | BE40: 0 | BF40: 3380.181 | BG40: 12684.092 | BH40: 22309 | BI40: 0 | BJ40: 7263.392
A41: etud_rech_doc | B41: 0 | C41: 0 | D41: 0 | E41: 0 | F41: 0 | G41: 0 | H41: 16 | I41: 0 | J41: 162 | L41: 0 | M41: 45 | N41: 0 | O41: 0 | P41: 0 | Q41: 1613 | R41: 2550 | S41: 0 | T41: 0 | U41: 64954 | V41: 1420 | W41: 0 | X41: 23194 | Y41: 0 | Z41: 95 | AB41: 0 | AC41: 0 | AD41: 94488.086 | AE41: 0 | AF41: 81 | AG41: 0 | AH41: 29478 | AI41: 0 | AJ41: 1000 | AK41: 0 | AL41: 0 | AM41: 40 | AN41: 4600 | AO41: 271 | AP41: 0 | AQ41: 2222 | AR41: 106 | AS41: 2910 | AT41: 455 | AU41: 0 | AV41: 0 | AX41: 22777 | AY41: 2999 | AZ41: 50 | BA41: 6127.2 | BB41: 10340 | BC41: 16 | BD41: 472675 | BE41: 0 | BG41: 2482.6379 | BH41: 240 | BI41: 0
A42: pub_publictn | B42: 0 | C42: 20 | D42: 0 | E42: 0 | F42: 0 | G42: 0 | H42: 0 | I42: 0 | J42: 0 | L42: 0 | M42: 2957 | N42: 0 | O42: 0 | P42: 0 | Q42: 15979 | R42: 0 | S42: 0 | T42: 0 | U42: 0 | V42: 151707 | W42: 0 | X42: 18154 | Y42: 998 | Z42: 0 | AA42: 1688.582 | AB42: 117560 | AC42: 0 | AD42: 20 | AE42: 44086 | AF42: 37188 | AG42: 0 | AI42: 0 | AJ42: 0 | AK42: 0 | AL42: 0 | AM42: 46947 | AO42: 127215 | AP42: 0 | AQ42: 12257 | AR42: 0 | AS42: 8363 | AT42: 0 | AU42: 0 | AX42: 75789 | AY42: 0 | AZ42: 3355.405 | BA42: 744094 | BB42: 0 | BC42: 0 | BD42: 0 | BE42: 0 | BG42: 95.161389 | BH42: 1075 | BI42: 0
A43: frais_telecom | B43: 0 | C43: 1534 | D43: 67291 | E43: 0 | F43: 0 | G43: 0 | H43: 12 | I43: 0 | J43: =12+12 -> 24 | L43: 773 | M43: 29629 | N43: 0 | O43: 1151.293 | P43: 0 | Q43: 41981 | R43: 51639.837 | S43: 41532 | T43: 0 | U43: 0 | V43: 135269 | W43: 0 | X43: 22483 | Y43: 94849 | Z43: 0 | AA43: 11216.812 | AB43: 693979 | AC43: 456 | AD43: 255.8 | AE43: 33683 | AF43: 330833 | AG43: 0 | AH43: 120 | AI43: 785.1 | AJ43: 0 | AK43: 0 | AL43: 0 | AM43: 134664 | AN43: 2238.7 | AO43: 241087 | AP43: 0 | AQ43: 5111 | AR43: 196 | AS43: 9329 | AT43: 0 | AU43: 0 | AV43: 184 | AX43: 19692 | AY43: 1126 | AZ43: 25877.977 | BA43: 259681 | BB43: 3086 | BC43: 12 | BD43: 2300 | BE43: 115 | BG43: 0 | BH43: 1900 | BI43: 0 | BJ43: 2693.25
A44: autre_service | B44: 0 | C44: 0 | D44: 3296 | E44: 0 | F44: 0 | G44: 0 | H44: 0 | I44: 0 | J44: 0 | L44: 7500 | M44: 28809 | N44: 10 | O44: 4093.487 | P44: 0 | Q44: 0 | R44: 327305.55 | S44: 0 | T44: 0 | U44: 0 | V44: 0 | W44: 1697 | X44: 0 | Y44: 2500 | Z44: 0 | AB44: 12182 | AC44: 0 | AD44: 0 | AE44: 0 | AF44: 0 | AG44: 0 | AH44: 10685 | AI44: 74.6 | AJ44: 0 | AK44: 0 | AL44: 0 | AM44: 133626 | AO44: 0 | AP44: 0 | AQ44: 0 | AR44: 67 | AS44: 0 | AT44: 0 | AU44: 0 | AV44: 0 | AX44: 633074 | AY44: 0 | BB44: 3200 | BC44: 0 | BD44: 0 | BE44: 16468 | BG44: 0 | BH44: 1313 | BI44: 0 | BJ44: 659533.65
A45: remuneratn_conseil | B45: 0 | C45: 13110 | D45: 112558 | E45: 0 | F45: 0 | G45: 0 | H45: 40 | I45: 0 | J45: 200 | L45: 18389 | M45: 51339 | N45: 1203 | O45: 0 | P45: 0 | Q45: 447885 | R45: 0 | S45: 8968 | T45: 0 | U45: 0 | V45: 892639 | W45: 6500 | X45: 745061 | Y45: 1343825 | Z45: 168335 | AA45: 6627.19 | AB45: 9505807 | AC45: 696 | AD45: 0 | AE45: 1884669 | AF45: 11996909 | AG45: 0 | AH45: 12000 | AI45: 13970.787 | AJ45: 0 | AK45: 0 | AL45: 46176.184 | AM45: 2503326 | AN45: 10612.3 | AO45: 2936396 | AP45: 0 | AQ45: 91269 | AR45: 470435 | AS45: 379220 | AT45: 0 | AU45: 0 | AV45: 6963 | AX45: 419769 | AY45: 32463 | AZ45: 849504.01 | BA45: 3598885.9 | BB45: 5000 | BC45: 40 | BD45: 26003 | BE45: 874 | BF45: 4847.456 | BG45: 51636.565 | BH45: 33746 | BI45: 0
A46: frais_formtn_persnl | B46: 0 | C46: 0 | D46: 1641 | E46: 0 | F46: 0 | G46: 0 | H46: 0 | I46: 0 | J46: 0 | L46: 0 | M46: 1700 | N46: 0 | O46: 0 | P46: 0 | Q46: 45 | R46: 10344.667 | S46: 6526 | T46: 0 | U46: 0 | V46: 30035 | W46: 0 | X46: 0 | Y46: 19173 | Z46: 0 | AB46: 72907 | AC46: 0 | AD46: 0 | AE46: 5445 | AF46: 7375 | AG46: 0 | AI46: 0 | AJ46: 0 | AK46: 0 | AL46: 0 | AM46: 46016 | AO46: 258027 | AP46: 0 | AQ46: 0 | AR46: 850 | AS46: 0 | AT46: 0 | AU46: 0 | AV46: 106 | AX46: 1500 | AY46: 3000 | BA46: 163532 | BB46: 0 | BC46: 0 | BD46: 0 | BE46: 0 | BG46: 0 | BH46: 0 | BI46: 0
A47: frais bancaire | B47: 571 | C47: 2154 | D47: 5898 | E47: 0 | F47: 0 | G47: 0 | H47: 361 | I47: 0 | J47: 1961 | L47: 4858 | M47: 5274 | N47: 0 | O47: 1317.905 | P47: 0 | Q47: 65983 | R47: 55064.007 | S47: 19918 | T47: 0 | U47: 0 | V47: 543437 | W47: 1423 | X47: 44069 | Y47: 74776 | Z47: 7099 | AB47: 85339 | AC47: 0 | AD47: 198.203 | AE47: 63487 | AF47: 377550 | AG47: 0 | AH47: 311 | AI47: 0 | AJ47: 0 | AK47: 0 | AL47: 205.65 | AM47: 298201 | AN47: 1155.4 | AO47: 1521621 | AP47: 0 | AQ47: 5061 | AR47: 2495 | AS47: 9470 | AT47: 0 | AU47: 54.52 | AV47: 1070 | AX47: 89281 | AY47: 1811 | AZ47: 34532.246 | BA47: 810866 | BB47: 0 | BC47: 361 | BD47: 3115 | BE47: 0 | BF47: 5740.577 | BG47: 15366.262 | BH47: 15511 | BI47: 0 | BJ47: 25811.881
A48: redvanc_brevt_licn | B48: 0 | C48: 48434 | D48: 19324 | E48: 0 | F48: 0 | G48: 0 | H48: 0 | I48: 0 | J48: 2326 | L48: 73800 | M48: 28755 | N48: 0 | O48: 0 | P48: 0 | Q48: 12349 | R48: 3888.445 | S48: 743 | T48: 0 | U48: 0 | V48: 13598 | W48: 0 | X48: 18632 | Y48: 0 | Z48: 64388 | AB48: 16483697 | AC48: 0 | AD48: 0 | AE48: 24091 | AF48: 1300000 | AG48: 0 | AH48: 0 | AI48: 0 | AJ48: 0 | AK48: 0 | AL48: 0 | AM48: 462726 | AO48: 176809 | AP48: 0 | AQ48: 0 | AR48: 0 | AS48: 4275 | AT48: 0 | AU48: 0 | AV48: 0 | AX48: 1446.772 | AY48: 0 | AZ48: 30544.997 | BA48: 277999 | BB48: 0 | BC48: 0 | BD48: 0 | BE48: 0 | BF48: 68315.566 | BG48: 0 | BH48: 0 | BI48: 0
A49: remuneratn_pers_ext | B49: 0 | C49: 1638 | D49: 0 | E49: 0 | F49: 0 | G49: 6526 | H49: 0 | I49: 0 | J49: 141585 | L49: 11971 | M49: 0 | N49: 432 | O49: 2400 | P49: 0 | Q49: 0 | R49: 0 | S49: 141929 | T49: 0 | U49: 0 | V49: 2209793 | W49: 211783 | X49: 0 | Y49: 14400 | Z49: 0 | AB49: 0 | AC49: 8895 | AD49: 0 | AE49: 52563 | AG49: 0 | AH49: 0 | AI49: 0 | AJ49: 0 | AK49: 0 | AM49: 477997 | AO49: 11478628 | AP49: 0 | AQ49: 0 | AR49: 29546 | AS49: 320018 | AT49: 0 | AU49: 10904.028 | AV49: 16434 | AX49: 157355.24 | AY49: 0 | BA49: 2685714 | BB49: 0 | BC49: 0 | BD49: 999724 | BE49: 0 | BG49: 0 | BH49: 71717 | BI49: 0 | BJ49: 92144.172
A50: autre_charg_ext | B50: 0 | C50: =24718-C49 -> 23080 | D50: 32823 | E50: 0 | F50: 0 | G50: 0 | H50: 0 | I50: 0 | J50: 8098 | L50: 8209 | M50: 257145 | N50: 0 | O50: 1208.261 | P50: 6708 | Q50: 228883 | R50: 0 | S50: 70886 | T50: 0 | U50: 0 | V50: 15866 | W50: 0 | X50: 429241 | Y50: 548379 | Z50: 3366 | AA50: 12119.231 | AB50: 946648 | AC50: 3453 | AD50: 2395.4 | AE50: 25054 | AF50: 607316 | AG50: 0 | AH50: 0 | AI50: 1295.592 | AJ50: 0 | AK50: 0 | AL50: 0 | AM50: 1138439 | AN50: 4443 | AO50: 108162 | AP50: 0 | AQ50: 18250 | AR50: 9248 | AS50: 0 | AT50: 0 | AU50: 12693.39 | AV50: 12993 | AX50: 202669.17 | AY50: 2629 | AZ50: =5094+24602.322 -> 29696.322 | BA50: 260661 | BB50: 1300 | BC50: 0 | BD50: 81898 | BE50: 0 | BF50: 163 | BG50: 10534.519 | BH50: 17842 | BI50: 0 | BJ50: 2679.3
A51: F4 IMPOTS ET TAXES RECALCULES | B51: =SUM(B53:B60) -> 3640 | C51: =SUM(C53:C60) -> 70700 | D51: =SUM(D53:D60) -> 3420 | E51: =SUM(E53:E60) -> 4760 | F51: =SUM(F53:F60) -> 15981 | G51: =SUM(G53:G60) -> 7751 | H51: =SUM(H53:H60) -> 62978 | I51: =SUM(I53:I60) -> 40142 | ... L51: =SUM(L53:L60) -> 26614 | M51: 28327 | N51: =SUM(N53:N60) -> 21526 | O51: =SUM(O53:O60) -> 2490 | P51: =SUM(P53:P60) -> 0 | Q51: =SUM(Q53:Q60) -> 2767922 | R51: =SUM(R53:R60) -> 901454.45 | S51: =SUM(S53:S60) -> 588135 | T51: =SUM(T53:T60) -> 0 | U51: =SUM(U53:U60) -> 0 | ... AF51: =SUM(AF53:AF60) -> 10000 | AG51: =AG52 -> 19253.849 | AH51: =SUM(AH53:AH60) -> 24919 | AI51: =SUM(AI53:AI60) -> 205027.66 | AJ51: =SUM(AJ53:AJ60) -> 8700 | AK51: =SUM(AK53:AK60) -> 19812 | AL51: =SUM(AL53:AL60) -> 8870.225 | AM51: =SUM(AM53:AM60) -> 8102403 | AN51: =SUM(AN53:AN60) -> 41223.9 | AO51: =SUM(AO53:AO60) -> 37867096 | ... BH51: =SUM(BH53:BH60) -> 71227 | BI51: =BI52 -> 8847 | BJ51: =SUM(BJ53:BJ60) -> 206185.58 | BK51: =SUM(BK53:BK60) -> 0 | BL51: =SUM(BL53:BL60) -> 0 | BM51: =SUM(BM53:BM60) -> 0 | BN51: =SUM(BN53:BN60) -> 0 | BO51: =SUM(BO53:BO60) -> 0 | BP51: =SUM(BP53:BP60) -> 0 | BQ51: =SUM(BQ53:BQ60) -> 0
A52: F4 IMPOTS ET TAXES | B52: =+B53 -> 3640 | C52: =SUM(C53:C60) -> 70700 | D52: 3420 | E52: =E56 -> 4760 | F52: =F53+F56+F57 -> 15981 | G52: =G56 -> 7751 | H52: =H56 -> 62978 | I52: =SUM(I53:I60) -> 40142 | J52: 0 | K52: 720 | L52: 26614 | M52: 0 | N52: =+N53+N55+N56+N58 -> 21526 | O52: 2490 | P52: 0 | Q52: 2767922 | R52: =R53+R54+R56+R58+R59 -> 901454.45 | S52: 588135 | U52: 0 | V52: 135265 | W52: 92875 | X52: 255012 | Y52: 1273874 | Z52: 33 | AA52: 98142.476 | AB52: =AB53+AB57+AB59+AB60 -> 10600725 | AC52: 10427 | AD52: =AD55+AD56 -> 5440 | AE52: 50208 | AF52: 10000 | AG52: 19253.849 | AH52: 24919 | AI52: =AI53+AI59 -> 205027.66 | AJ52: 0 | AK52: 19382 | AL52: =AL53+AL54+AL56+AL58 -> 8870.225 | AM52: 8102404 | AN52: 41224 | AO52: 37867096 | AP52: 0 | AQ52: 55793 | AR52: 192627 | AS52: =AS56+AS57+AS58+AS59+AS60 -> 283090 | AT52: 47000 | AU52: 10818.9 | AV52: 22589 | AX52: =AX53+AX54+AX56+AX57+AX58+AX59+AX60 -> 1620995 | AY52: 9406 | AZ52: =AZ53+AZ59+AZ60 -> 96948.343 | BA52: =BA53+BA58+BA59 -> 2861754 | BB52: 0 | BC52: =+BC56 -> 29148 | BD52: 3077 | BE52: 2437 | BF52: =SUM(BF53:BF60) -> 4377.426 | BG52: 140801 | BH52: 71227 | BI52: 8847 | BJ52: 206185.58
A53: impot_tax_entreprs | B53: 3640 | D53: 2698 | E53: 0 | F53: 3167 | G53: 0 | H53: 0 | I53: 500 | J53: 0 | L53: 6873 | M53: 25273 | N53: 10763 | O53: 0 | P53: 0 | Q53: 0 | R53: 860672.83 | S53: 75155 | T53: 0 | U53: 0 | V53: 67869 | W53: 2500 | X53: 125215 | Y53: 327704 | Z53: 0 | AA53: 97538.408 | AB53: 256492 | AC53: 3134 | AD53: 0 | AE53: 13177 | AF53: 0 | AG53: 0 | AH53: 11287 | AI53: 139716.07 | AJ53: 0 | AK53: 0 | AL53: 521.053 | AM53: 626817 | AN53: 238 | AO53: 1028380 | AP53: 0 | AQ53: 25741 | AR53: =AR52-SUM(AR55:AR60) -> 2611 | AS53: 0 | AT53: 22000 | AU53: 0 | AV53: 2129 | AX53: 96489 | AY53: 5509 | AZ53: 74097.4 | BA53: 2445818 | BB53: 0 | BC53: 0 | BD53: 0 | BE53: 0 | BF53: 2795.699 | BG53: 0 | BH53: 9010 | BI53: 0 | BJ53: 40371
A54: impot_tax_indirect | B54: 0 | C54: 0 | D54: 0 | E54: 0 | F54: 0 | G54: 0 | H54: 0 | I54: 0 | J54: 0 | L54: 0 | M54: 2623 | N54: 0 | O54: 0 | P54: 0 | Q54: 0 | R54: 22669.872 | S54: 42847 | T54: 0 | U54: 0 | V54: 0 | W54: 6879 | X54: 40 | Y54: 17697 | Z54: 0 | AB54: 0 | AC54: 0 | AD54: 0 | AE54: 30 | AF54: 0 | AG54: 0 | AI54: 0 | AJ54: 0 | AK54: 0 | AL54: 7955.172 | AM54: 7358225 | AO54: 1312230 | AP54: 0 | AQ54: 5605 | AR54: 0 | AS54: 0 | AT54: 0 | AU54: 0 | AV54: 213 | AX54: 64402 | AY54: 700 | BB54: 0 | BC54: 0 | BD54: 0 | BE54: 0 | BG54: 0 | BH54: 1601 | BI54: 0 | BJ54: 50464.581
A55: droit_entre | B55: 0 | C55: 0 | D55: 0 | E55: 0 | F55: 0 | G55: 0 | H55: 0 | I55: 1500 | J55: 0 | L55: 0 | M55: 431 | N55: 2500 | O55: 0 | P55: 0 | Q55: 0 | R55: 0 | S55: 1000 | T55: 0 | U55: 0 | V55: 0 | W55: 0 | X55: 0 | Y55: 10000 | Z55: 0 | AB55: 0 | AC55: 0 | AD55: 2500 | AE55: 0 | AF55: 0 | AG55: 0 | AI55: 0 | AJ55: 0 | AK55: 0 | AL55: 0 | AM55: 117361 | AN55: 222 | AO55: 0 | AP55: 0 | AQ55: 0 | AR55: 2500 | AS55: 0 | AT55: 25000 | AU55: 0 | AX55: 0 | AY55: 2500 | BB55: 6000 | BC55: 0 | BD55: 0 | BE55: 0 | BG55: 0 | BH55: 0 | BI55: 0 | BJ55: 10000
A56: tax_superficiaire | B56: 0 | C56: 19673 | D56: 415 | E56: =2835+1925 -> 4760 | F56: 2528 | G56: 7751 | H56: 62978 | I56: 19000 | J56: =174+1906 -> 2080 | K56: 720 | L56: 0 | M56: 0 | N56: 7927 | O56: 2490 | P56: 0 | Q56: 0 | R56: 12235.02 | S56: 362264 | U56: 0 | V56: 0 | W56: 0 | X56: 0 | Y56: 3209 | Z56: 0 | AB56: 0 | AC56: 7293 | AD56: 2940 | AE56: 37000 | AF56: 0 | AG56: 0 | AH56: 13632 | AI56: 0 | AJ56: 8700 | AK56: 1430 | AL56: 344 | AM56: 0 | AO56: 81430 | AP56: 0 | AQ56: 24386 | AR56: 22750 | AS56: 25000 | AT56: 0 | AU56: 10818.9 | AV56: 0 | AX56: 176283 | AY56: 0 | BB56: 3375 | BC56: 29148 | BD56: 0 | BE56: 0 | BF56: 0 | BG56: 1000 | BH56: 0 | BI56: 0 | BJ56: 30350
A57: redvanc_miniere | B57: 0 | C57: 48434 | D57: 0 | E57: 0 | F57: 10286 | G57: 0 | H57: 0 | I57: 19142 | J57: 0 | L57: 9625 | M57: 0 | N57: 0 | O57: 0 | P57: 0 | Q57: 262851 | R57: 0 | S57: 70196 | T57: 0 | U57: 0 | V57: 0 | W57: 22533 | X57: 0 | Y57: 796150 | Z57: 0 | AB57: 10301250 | AC57: 0 | AD57: 0 | AE57: 0 | AF57: 0 | AG57: 0 | AH57: 0 | AI57: 0 | AK57: 0 | AL57: 0 | AM57: 0 | AO57: 19594799 | AP57: 0 | AQ57: 0 | AR57: 97267 | AS57: 230598 | AT57: 0 | AV57: 19630 | AX57: 177686 | AY57: 554 | BB57: 0 | BC57: 0 | BD57: 0 | BE57: 2363 | BG57: 136124.99 | BH57: 60352 | BI57: 0 | BJ57: 75000
A58: droit_enregistrmt | B58: 0 | C58: 8 | D58: 0 | E58: 0 | F58: 0 | G58: 0 | H58: 0 | I58: 0 | J58: 0 | L58: 6123 | M58: 0 | N58: 336 | O58: 0 | P58: 0 | Q58: 2943 | R58: 1572.768 | S58: 3200 | T58: 0 | U58: 0 | V58: 399 | W58: 20 | X58: 117419 | Y58: 11138 | Z58: 33 | AA58: 604.068 | AB58: 0 | AC58: 0 | AD58: 0 | AE58: 0 | AF58: 0 | AG58: 0 | AH58: 0 | AI58: 0 | AJ58: 0 | AK58: 0 | AL58: 50 | AM58: 0 | AO58: 180210 | AP58: 0 | AQ58: 60 | AR58: 0 | AS58: 4317 | AT58: 0 | AU58: 0 | AV58: 230 | AX58: 3994 | AY58: 143 | BA58: 2529 | BB58: 0 | BC58: 0 | BD58: 0 | BE58: 74 | BF58: 1581.727 | BG58: 3676.0052 | BH58: 243 | BI58: 0
A59: penalit_amend_fiscl | B59: 0 | C59: 2585 | D59: 0 | E59: 0 | F59: 0 | G59: 0 | H59: 0 | I59: 0 | J59: 0 | L59: 2088 | M59: 0 | N59: 0 | O59: 0 | P59: 0 | Q59: 2500000 | R59: 4303.965 | S59: 880 | T59: 0 | U59: 0 | V59: 2188 | W59: 60000 | X59: 0 | Y59: 12276 | Z59: 0 | AB59: 33692 | AC59: 0 | AD59: 0 | AE59: 0 | AF59: 10000 | AG59: 0 | AH59: 0 | AI59: 65311.594 | AJ59: 0 | AK59: 0 | AL59: 0 | AM59: 0 | AN59: 3286.4 | AO59: 14039438 | AP59: 0 | AQ59: 0 | AR59: 743 | AS59: 2973 | AT59: 0 | AU59: 0 | AV59: 0 | AX59: 50042 | AY59: 0 | AZ59: 15000 | BA59: 413407 | BB59: 0 | BC59: 0 | BD59: 3000 | BE59: 0 | BG59: 0 | BH59: 21 | BI59: 0
A60: autre_droit_imp | B60: 0 | C60: 0 | D60: =D52-(D53+D56) -> 307 | E60: 0 | F60: 0 | G60: 0 | H60: 0 | I60: 0 | J60: 0 | L60: 1905 | M60: 0 | N60: 0 | O60: 0 | P60: 0 | Q60: 2128 | R60: 0 | S60: 32593 | T60: 0 | U60: 0 | V60: 64809 | W60: 944 | X60: 12337 | Y60: 95700 | Z60: 0 | AB60: 9291 | AC60: 0 | AD60: 0 | AE60: 0 | AF60: 0 | AG60: 0 | AH60: 0 | AI60: 0 | AJ60: 0 | AK60: 18382 | AL60: 0 | AM60: 0 | AN60: 37477.5 | AO60: 1630609 | AP60: 0 | AQ60: 0 | AR60: 66756 | AS60: 20202 | AT60: 0 | AU60: 0 | AV60: 600 | AX60: =1620995-568896 -> 1052099 | AY60: 0 | AZ60: 7850.943 | BB60: 0 | BC60: 0 | BD60: 77 | BE60: 0 | BG60: 0 | BH60: 0 | BI60: 0
A61: F5 CHARGES DE PERSONNEL RECALCULEES | B61: =SUM(B63:B68) -> 72144 | C61: =SUM(C63:C68) -> 97937 | D61: =SUM(D63:D68) -> 1343358 | E61: =SUM(E63:E68) -> 224700 | F61: =SUM(F63:F68) -> 42881.804 | G61: =SUM(G63:G68) -> 39310 | H61: =SUM(H63:H68) -> 28421 | I61: =SUM(I63:I68) -> 156000 | J61: =SUM(J63:J68) -> 480782 | K61: =+K62 -> 15490 | L61: =SUM(L63:L68) -> 241855 | M61: 862591 | N61: =SUM(N63:N68) -> 0 | O61: =SUM(O63:O68) -> 7800 | P61: =SUM(P63:P68) -> 8313 | Q61: =SUM(Q63:Q68) -> 8721540 | R61: =SUM(R63:R68) -> 2297980.5 | S61: =SUM(S63:S68) -> 1476420 | T61: =SUM(T63:T68) -> 44545 | U61: =SUM(U63:U68) -> 0 | ... AF61: =SUM(AF63:AF68) -> 23662306 | AG61: =AG62 -> 135056.22 | AH61: =SUM(AH63:AH68) -> 42278 | AI61: =SUM(AI63:AI68) -> 205264.9 | AJ61: =SUM(AJ63:AJ68) -> 68400 | AK61: =SUM(AK63:AK68) -> 0 | AL61: =SUM(AL63:AL68) -> 8524 | AM61: =SUM(AM63:AM68) -> 8724230 | AN61: =SUM(AN63:AN68) -> 207998.6 | AO61: =SUM(AO63:AO68) -> 23119805 | ... BH61: =SUM(BH63:BH68) -> 177187 | BI61: =BI62 -> 84143 | BJ61: =SUM(BJ63:BJ68) -> 1112883 | BK61: =SUM(BK63:BK68) -> 0 | BL61: =SUM(BL63:BL68) -> 0 | BM61: =SUM(BM63:BM68) -> 0 | BN61: =SUM(BN63:BN68) -> 0 | BO61: =SUM(BO63:BO68) -> 0 | BP61: =SUM(BP63:BP68) -> 0 | BQ61: =SUM(BQ63:BQ68) -> 0
A62: F5 CHARGES DE PERSONNEL | B62: =+SUM(B63:B68) -> 72144 | C62: =SUM(C63:C68) -> 97937 | D62: 1343359 | E62: =E63 -> 224700 | F62: =F63+F65+F67 -> 42881.804 | G62: =G63+G67 -> 39310 | H62: =H63+H66+H67 -> 28421 | I62: =SUM(I63:I68) -> 156000 | J62: =+J63+J67 -> 472866 | K62: 15490 | L62: =L61 -> 241855 | M62: 0 | N62: 0 | O62: 7800 | P62: =P63 -> 8313 | Q62: 8721540 | R62: =R63+R64+R65+R66+R67 -> 2297980.5 | S62: 1476420 | T62: 44545 | U62: 0 | V62: =V63+V64+V67+V68 -> 4992446 | W62: =W63+W65+W66+W67+W68 -> 8999 | X62: 190367 | Y62: =Y63+Y64+Y65+Y67+Y68 -> 2028866 | Z62: 0 | AA62: 283582.32 | AB62: 23686593 | AC62: 112808 | AD62: 31680 | AE62: 1086098 | AF62: 23662306 | AG62: 135056.22 | AH62: 42278 | AI62: 205264.9 | AJ62: 68400 | AK62: 0 | AL62: =AL63 -> 8524 | AM62: 8929380 | AO62: 23137805 | AP62: 228242 | AQ62: 522322 | AR62: =SUM(AR63:AR68) -> 82619 | AS62: 74725 | AT62: =AT63+AT68 -> 18650 | AU62: 97224.996 | AV62: 175935 | AW62: 0 | AX62: 2490525 | AY62: 125302 | AZ62: =SUM(AZ63:AZ68) -> 771443.94 | BA62: 9712391 | BB62: =BB63+BB65 -> 84920 | BC62: =+SUM(BC63:BC68) -> 7249 | BD62: 288648 | BE62: 0 | BF62: =SUM(BF63:BF68) -> 137263.44 | BG62: 306882 | BH62: 177188 | BI62: 84143 | BJ62: 1112883
A63: salair_direct_nat | B63: 68845 | C63: 78387 | D63: 527688 | E63: =166200+58500 -> 224700 | F63: 27168.804 | G63: 37755 | H63: 27000 | I63: 108000 | J63: 340528 | L63: 133722 | M63: 436635 | N63: 0 | O63: 6000 | P63: 8313 | Q63: 7994326 | R63: 1857912.5 | S63: 1171571 | T63: 44545 | U63: 0 | V63: 3580371 | W63: 6000 | X63: 183631 | Y63: 1387613 | Z63: 0 | AA63: 220493.12 | AB63: 11333990 | AC63: 40979 | AD63: =AD62 -> 31680 | AE63: 526287 | AF63: 12977720 | AG63: 0 | AH63: 41078 | AI63: 183934.09 | AJ63: 68400 | AK63: 0 | AL63: 8524 | AM63: 3570244 | AN63: 183227.6 | AO63: 18910354 | AP63: 0 | AQ63: 354200 | AR63: 74579 | AS63: 372343 | AT63: 18250 | AU63: 97224.996 | AV63: 157510 | AX63: 1300805.9 | AY63: 63982 | AZ63: 434528.57 | BA63: 6760510 | BB63: 79920 | BC63: 2664 | BD63: 160312 | BE63: 0 | BF63: 95872.412 | BG63: 251417 | BH63: 141855 | BI63: 0 | BJ63: 822751.09
A64: salair_direct_nonnat | B64: 0 | C64: 0 | D64: 577905 | E64: 0 | F64: 0 | G64: 0 | H64: 0 | I64: 30000 | J64: 0 | L64: 74969 | M64: 371043 | N64: 0 | O64: 0 | P64: 0 | R64: 116900.68 | S64: 0 | T64: 0 | U64: 0 | V64: 1023283 | W64: 0 | X64: 0 | Y64: 141546 | Z64: 0 | AB64: 8109127 | AC64: 63473 | AD64: 0 | AE64: 316633 | AF64: 3892679 | AG64: 0 | AH64: 0 | AI64: 0 | AJ64: 0 | AK64: 0 | AL64: 0 | AM64: 4888151 | AO64: 468455 | AP64: 0 | AQ64: 32187 | AR64: 0 | AS64: 0 | AU64: 0 | AV64: 0 | AX64: 444702.72 | AY64: 49308 | AZ64: 209895.85 | BA64: 380197 | BB64: 0 | BC64: 0 | BD64: 99032 | BE64: 0 | BF64: 38982.196 | BG64: 0 | BH64: 14139 | BI64: 0
A65: Indemnt_forfait_pers | B65: 2746 | C65: 7987 | D65: 57421 | E65: 0 | F65: 8153 | G65: 0 | H65: 0 | I65: 0 | J65: 3227 | L65: 10278 | M65: 13819 | N65: 0 | O65: 0 | P65: 0 | Q65: 117784 | R65: 116594.37 | S65: 156600 | T65: 0 | U65: 0 | V65: 0 | W65: 124 | X65: 0 | Y65: 274777 | Z65: 0 | AA65: 38587.809 | AB65: 2698230 | AC65: 0 | AD65: 0 | AE65: 57151 | AF65: 2602738 | AG65: 0 | AH65: 1200 | AI65: 0 | AJ65: 0 | AK65: 0 | AL65: 0 | AM65: 0 | AN65: 8503 | AO65: 0 | AP65: 0 | AQ65: 17161 | AR65: 0 | AS65: 16919 | AT65: 0 | AU65: 0 | AV65: 0 | AX65: 46932 | AY65: 1498 | AZ65: 18385.773 | BB65: 5000 | BC65: 0 | BD65: 250 | BE65: 0 | BF65: 1060.107 | BG65: 0 | BH65: 7947 | BI65: 0 | BJ65: 140
A66: avantage_nature | B66: 0 | C66: 0 | D66: 8200 | E66: 0 | F66: 0 | G66: 0 | H66: 40 | I66: 18000 | J66: =40+4649 -> 4689 | L66: 0 | M66: 3431 | N66: 0 | O66: 0 | P66: 0 | Q66: 39915 | R66: 24636.996 | S66: 0 | T66: 0 | U66: 0 | V66: 0 | W66: 175 | X66: 0 | Y66: 0 | Z66: 0 | AB66: 1545246 | AC66: 0 | AD66: 0 | AE66: 6600 | AF66: 0 | AG66: 0 | AI66: 0 | AJ66: 0 | AK66: 0 | AL66: 0 | AM66: 10223 | AO66: 2518364 | AP66: 0 | AQ66: 0 | AR66: 0 | AS66: 0 | AT66: 0 | AU66: 0 | AV66: 0 | AX66: 393497 | AY66: 4161 | BB66: 0 | BC66: 40 | BD66: 0 | BE66: 0 | BG66: 0 | BI66: 0 | BJ66: 225943.93
A67: charg_social | B67: 470 | C67: 6230 | D67: 24915 | E67: 0 | F67: 7560 | G67: 1555 | H67: 1381 | I67: 0 | J67: 132338 | L67: 22886 | M67: 27775 | N67: 0 | O67: 1800 | P67: 0 | Q67: 501621 | R67: 181935.94 | S67: 130339 | T67: 0 | U67: 0 | V67: 230091 | W67: 272 | X67: 5670 | Y67: 176261 | Z67: 0 | AA67: 22274.34 | AB67: 0 | AC67: 7730 | AD67: 0 | AE67: 25648 | AF67: 1006771 | AG67: 0 | AH67: 0 | AI67: 21330.811 | AJ67: 0 | AK67: 0 | AL67: 0 | AM67: 148602 | AN67: 16268 | AO67: 1080898 | AP67: 0 | AQ67: 41811 | AR67: 6849 | AS67: 4131 | AT67: 0 | AU67: 0 | AV67: 17101 | AX67: 118903 | AY67: 5809 | AZ67: 45328.945 | BA67: 555830 | BB67: 0 | BC67: 905 | BD67: 18373 | BE67: 0 | BF67: 949.324 | BG67: 30170.04 | BH67: 13246 | BI67: 0 | BJ67: 42163.196
A68: autre_charg_social | B68: 83 | C68: 5333 | D68: 147229 | E68: 0 | F68: 0 | G68: 0 | I68: 0 | J68: 0 | L68: 0 | M68: 9888 | N68: 0 | O68: 0 | P68: 0 | Q68: 67894 | R68: 0 | S68: 17910 | T68: 0 | U68: 0 | V68: 158701 | W68: 2428 | X68: 1065 | Y68: 48669 | Z68: 0 | AA68: 2227.049 | AB68: 0 | AC68: 626 | AD68: 0 | AE68: 153779 | AF68: 3182398 | AG68: 0 | AH68: 0 | AI68: 0 | AJ68: 0 | AK68: 0 | AL68: 0 | AM68: 107010 | AO68: 141734 | AP68: 0 | AQ68: 76963 | AR68: 1191 | AS68: 2191 | AT68: 400 | AU68: 0 | AV68: 1325 | AX68: 28327.98 | AY68: 544 | AZ68: 63304.805 | BA68: 2015855 | BB68: 0 | BC68: 3640 | BD68: 10681 | BE68: 0 | BF68: 399.4 | BG68: 25294.96 | BH68: 0 | BI68: 0 | BJ68: 21884.802
A69: F6 FRAIS FINANCIERS | B69: 16785 | C69: 65932 | D69: 267 | E69: 0 | F69: 0 | G69: 0 | H69: 0 | I69: 0 | J69: 0 | K69: 4280 | L69: 10575 | M69: 3323 | N69: 0 | O69: 0 | P69: 0 | Q69: 17552812 | R69: 202321.91 | S69: 23157 | T69: 0 | U69: 0 | V69: 9196819 | W69: 7 | X69: 468544 | Y69: 634303 | Z69: 106222 | AA69: 27702.922 | AB69: 22105386 | AC69: 0 | AD69: 0 | AE69: 300108 | AF69: 5106640 | AG69: 0 | AH69: 0 | AI69: 216.343 | AJ69: 0 | AK69: 0 | AL69: 36983 | AM69: 248280 | AN69: 1446 | AO69: 5464 | AP69: 0 | AQ69: 149314 | AR69: 36073 | AS69: 78832 | AT69: 0 | AU69: 332.993 | AV69: 0 | AX69: 1839931 | AY69: 821 | AZ69: 36639.607 | BA69: 3016282 | BB69: 4000 | BC69: 0 | BD69: 1349 | BE69: 0 | BG69: 115193 | BH69: 20388 | BI69: 823 | BJ69: 757499.04
A70: F7 AUTRES CHARGES | B70: 0 | C70: 0 | D70: 35963 | E70: 0 | F70: 0 | G70: 0 | H70: 3640 | I70: 0 | J70: =3640+3640 -> 7280 | L70: 382395 | M70: 104242 | N70: 0 | O70: 0 | P70: 0 | Q70: 1835858 | R70: 19074.494 | S70: 69509 | U70: 0 | V70: 144117 | W70: 2702 | X70: 190774 | Y70: 429100 | Z70: 48340 | AA70: 12247.488 | AB70: 12280334 | AC70: 0 | AD70: 0 | AE70: 784944 | AF70: 31416453 | AG70: 13476.001 | AH70: 6727 | AI70: 1203.443 | AJ70: 0 | AK70: 0 | AL70: 0 | AM70: 1069051 | AN70: 0 | AO70: 20621787 | AP70: 36820 | AQ70: 434722 | AR70: 27639 | AS70: 43755 | AT70: 1500 | AU70: 0 | AV70: 0 | AX70: 6339552.2 | AY70: 0 | AZ70: 23453.336 | BA70: 393294 | BB70: 15728 | BC70: 3640 | BD70: 36598 | BE70: 62619 | BG70: 2218 | BH70: 11471 | BI70: 0 | BJ70: 503
A71: F8 IMPOTS SUR LE RESULTAT | B71: 0 | C71: 5000 | D71: 0 | E71: 0 | F71: 261 | G71: 0 | H71: 0 | I71: 500 | J71: 0 | L71: 8296 | M71: 0 | N71: 0 | P71: 0 | Q71: 0 | R71: 623022.9 | S71: 397462 | T71: 0 | U71: 0 | V71: 0 | W71: 5000 | X71: 0 | Y71: 1041386 | AA71: 35145.984 | AB71: 0 | AC71: 0 | AD71: 0 | AE71: 0 | AF71: 0 | AG71: 0 | AH71: 0 | AI71: 16841.416 | AJ71: 0 | AK71: 0 | AM71: 0 | AN71: 4252 | AO71: 55929961 | AP71: 0 | AQ71: 5000 | AR71: 94930 | AS71: 0 | AT71: 0 | AU71: 0 | AV71: 0 | AX71: 0 | AY71: 0 | AZ71: 319089.85 | BA71: 2497319 | BB71: 0 | BC71: 0 | BD71: 0 | BE71: 0 | BF71: 7706.268 | BG71: 19896 | BH71: 500 | BI71: 3412
A72: TOTAL CHARGES | B72: 569068 | C72: 2049354 | D72: =D73 -> 2010673 | E72: =E73 -> 387142 | F72: =F73 -> 209498.8 | G72: =G73 -> 55267 | H72: 175909 | I72: 325342 | J72: =311803+666196 -> 977999 | K72: 32304 | L72: =L73 -> 1901793 | M72: 3585592 | N72: 13994 | O72: =O73 -> 38440.172 | P72: 21844 | Q72: =Q73 -> 136150629 | R72: =R73 -> 14460278 | S72: =S73 -> 12384979 | T72: 107421 | U72: 0 | V72: =V73 -> 60206777 | W72: =W73 -> 1236775 | X72: =X73 -> 8845780 | Y72: =Y73 -> 17480210 | Z72: 455117 | AA72: 1635976.6 | AB72: =AB73 -> 132966346 | AC72: 390795 | AD72: =AD73 -> 145425.46 | AE72: =AE73 -> 6268530 | AF72: =AF73 -> 313896747 | AG72: 411925.04 | AH72: =AH73 -> 210434 | AI72: =AI73 -> 898242.11 | AJ72: =AJ73 -> 93100 | AK72: 21214 | AL72: =AL73 -> 121439.59 | AM72: =+AM73 -> 110000560 | AN72: =AN73 -> 573333.9 | AO72: =+AO73 -> 244703643 | AP72: 488983 | AQ72: =AQ73 -> 2231313 | AR72: =AR73 -> 2066963 | AS72: =AS73 -> 3222128 | AT72: 177040.59 | AU72: =AU73 -> 180003.9 | AV72: =AV73 -> 1077862 | AX72: =AX73 -> 40981512 | AY72: 199892 | AZ72: =AZ73 -> 4398125.6 | BA72: =BA73 -> 1.6378472e+08 | BB72: =BB73 -> 182636 | BC72: 80383 | BD72: 4184949 | BE72: 809330 | BF72: 731623 | BG72: =BG73 -> 1531806.8 | BH72: 1706346 | BI72: 589262 | BJ72: 3141115.8
A73: TOTAL CHARGES RECALCULE | B73: =B8+B30+B34+B51+B61+B69+B70+B71 -> 569068 | C73: =C8+C30+C34+C51+C61+C69+C70+C71 -> 2034925 | D73: =D8+D30+D34+D51+D61+D69+D70+D71 -> 2010673 | E73: =E8+E30+E34+E51+E61+E69+E70+E71 -> 387142 | F73: =F8+F30+F34+F51+F61+F69+F70+F71 -> 209498.8 | G73: =G8+G30+G34+G51+G61+G69+G70+G71 -> 55267 | H73: =H8+H30+H34+H51+H61+H69+H70+H71 -> 175909 | I73: =I8+I30+I34+I51+I61+I69+I70+I71 -> 325342 | ... BQ73: =BQ8+BQ30+BQ34+BQ51+BQ61+BQ69+BQ70+BQ71 -> 0
A74: ECART TOTAL | B74: =+B73-B72 -> 0 | C74: =+C73-C72 -> -14429 | D74: =+D73-D72 -> 0 | E74: =+E73-E72 -> 0 | F74: =+F73-F72 -> 0 | G74: =+G73-G72 -> 0 | H74: =+H73-H72 -> 0 | I74: =+I73-I72 -> 0 | ... BQ74: =+BQ73-BQ72 -> 0
A75: PROXI FOURNISSEUR | B75: =+B8+B30+B34+B69+B70 -> 493284 | C75: =+C8+C30+C34+C69+C70 -> 1861288 | D75: =+D8+D30+D34+D69+D70 -> 663895 | E75: =+E8+E30+E34+E69+E70 -> 157682 | F75: =+F8+F30+F34+F69+F70 -> 150375 | G75: =+G8+G30+G34+G69+G70 -> 8206 | H75: =+H8+H30+H34+H69+H70 -> 84510 | I75: =+I8+I30+I34+I69+I70 -> 128700 | ... BQ75: =+BQ8+BQ30+BQ34+BQ69+BQ70 -> 0
AB76: =208-132 -> 76
T77: -57427

Sheet Charge rectifiées OK T
A1: entreprise_id | B1: nbr_fourn_loc | C1: ttl_paye_fourn_loc | D1: pct_paye_fourn_loc | E1: nbr_fourn_etrg | F1: ttl_pay_fourn_etrg | G1: pct_pay_fourn_etrg | H1: nn_nature | I1: F1 ACHATS RECALCULES | J1: F1 ACHATS | K1: matier_consmbl | L1: matier_combustbl RECALCULEE | M1: matier_combustbl | N1: gaz_industriel | O1: gaz_naturel | P1: essence | Q1: gas_oil | R1: fuel_oil | S1: huile_lubrif | T1: charbon | U1: autre_combustbl | V1: fourn_bureau_infmtq | W1: eau | X1: electricite | Y1: autre_energ | Z1: fourn_bureau_nonstockbl | AA1: achat_materl_outilg | AB1: achat_etud_servc | AC1: achat_materl_equip | AD1: autre_achat | AE1: F2 TRANSPORTS RECALCULES | AF1: F2 TRANSPORTS | AG1: transprt_marchnds | AH1: transprt_persnl | AI1: F3 SERVICES EXTERIEURS RECALCULES | AJ1: F3 SERVICES EXTERIEURS | AK1: soustraitc_generl | AL1: loctn_charg_lctv | AM1: redvanc_creditbail | AN1: entretn_repar_maint | AO1: prime_assur | AP1: etud_rech_doc | AQ1: pub_publictn | AR1: frais_telecom | AS1: autre_service | AT1: remuneratn_conseil | AU1: frais_formtn_persnl | AV1: frais bancaire | AW1: redvanc_brevt_licn | AX1: remuneratn_pers_ext | AY1: autre_charg_ext | AZ1: F4 IMPOTS ET TAXES RECALCULES | BA1: F4 IMPOTS ET TAXES | BB1: impot_tax_entreprs | BC1: impot_tax_indirect | BD1: droit_entre | BE1: tax_superficiaire | BF1: redvanc_miniere | BG1: droit_enregistrmt | BH1: penalit_amend_fiscl | BI1: autre_droit_imp | BJ1: F5 CHARGES DE PERSONNEL RECALCULEES | BK1: F5 CHARGES DE PERSONNEL | BL1: salair_direct_nat | BM1: salair_direct_nonnat | BN1: Indemnt_forfait_pers | BO1: avantage_nature | BP1: charg_social | BQ1: autre_charg_social | BR1: F6 FRAIS FINANCIERS | BS1: F7 AUTRES CHARGES | BT1: F8 IMPOTS SUR LE RESULTAT | BU1: TOTAL CHARGES | BV1: TOTAL CHARGES RECALCULE | BW1: ECART TOTAL | BX1: PROXI FOURNISSEUR | BZ1: kk
A2: AFRIGEM SL | B2: 0 | C2: 0 | D2: 0 | E2: 0 | F2: 0 | G2: 0 | H2: Permis de recherche | I2: =K2+L2+SUM(V2:AD2) -> 39277 | J2: =+AB2 -> 39277 | K2: 0 | L2: =SUM(N2:U2) -> 0 | M2: 0 | N2: 0 | O2: 0 | P2: 0 | Q2: 0 | R2: 0 | S2: 0 | T2: 0 | U2: 0 | V2: 0 | W2: 0 | X2: 0 | Y2: 0 | Z2: 0 | AA2: 0 | AB2: 39277 | AC2: 0 | AD2: 0 | AE2: =AG2+AH2 -> 0 | AG2: 0 | AH2: 0 | AI2: =SUM(AK2:AY2) -> 437222 | AJ2: =+SUM(AK2:AY2) -> 437222 | AK2: 377615 | AL2: 43200 | AM2: 0 | AN2: 15836 | AO2: 0 | AP2: 0 | AQ2: 0 | AR2: 0 | AS2: 0 | AT2: 0 | AU2: 0 | AV2: 571 | AW2: 0 | AX2: 0 | AY2: 0 | AZ2: =SUM(BB2:BI2) -> 3640 | BA2: =+BB2 -> 3640 | BB2: 3640 | BC2: 0 | BD2: 0 | BE2: 0 | BF2: 0 | BG2: 0 | BH2: 0 | BI2: 0 | BJ2: =SUM(BL2:BQ2) -> 72144 | BK2: =+SUM(BL2:BQ2) -> 72144 | BL2: 68845 | BM2: 0 | BN2: 2746 | BO2: 0 | BP2: 470 | BQ2: 83 | BR2: 16785 | BS2: 0 | BT2: 0 | BU2: 569068 | BV2: =I2+AE2+AI2+AZ2+BJ2+BR2+BS2+BT2 -> 569068 | BW2: =+BV2-BU2 -> 0 | BX2: =+I2+AE2+AI2+BR2+BS2 -> 493284 | BZ2: =L2=M2 -> TRUE
A3: AFRIGOLD SARL | B3: 60 | C3: 695697 | D3: 95 | E3: 2 | F3: 32805 | G3: 5 | H3: Permis d’exploitation | I3: =K3+L3+SUM(V3:AD3) -> 1435824 | J3: 1435824 | K3: 10377 | L3: =SUM(N3:U3) -> 453686 | M3: =+SUM(N3:U3) -> 453686 | N3: 0 | O3: 0 | P3: 0 | Q3: 453426 | R3: 0 | S3: 260 | T3: 0 | U3: 0 | V3: 4250 | W3: 242 | X3: 26929 | Z3: 0 | AA3: 0 | AB3: 900240 | AC3: 40100 | AD3: 0 | AE3: =AG3+AH3 -> 33414 | AF3: =+SUM(AG3:AH3) -> 33414 | AG3: 40 | AH3: 33374 | AI3: =SUM(AK3:AY3) -> 326118 | AJ3: =+SUM(AK3:AY3) -> 326118 | AK3: 11191 | AL3: 3900 | AM3: 0 | AN3: 220831 | AO3: 226 | AP3: 0 | AQ3: 20 | AR3: 1534 | AS3: 0 | AT3: 13110 | AU3: 0 | AV3: 2154 | AW3: 48434 | AX3: 1638 | AY3: =24718-AX3 -> 23080 | AZ3: =SUM(BB3:BI3) -> 70700 | BA3: =SUM(BB3:BI3) -> 70700 | BC3: 0 | BD3: 0 | BE3: 19673 | BF3: 48434 | BG3: 8 | BH3: 2585 | BI3: 0 | BJ3: =SUM(BL3:BQ3) -> 97937 | BK3: =SUM(BL3:BQ3) -> 97937 | BL3: 78387 | BM3: 0 | BN3: 7987 | BO3: 0 | BP3: 6230 | BQ3: 5333 | BR3: 65932 | BS3: 0 | BT3: 5000 | BU3: 2034925 | BV3: =I3+AE3+AI3+AZ3+BJ3+BR3+BS3+BT3 -> 2034925 | BW3: =+BV3-BU3 -> 0 | BX3: =+I3+AE3+AI3+BR3+BS3 -> 1861288 | BZ3: =L3=M3 -> TRUE
A4: AGEM SENEGAL EXPLORATION SUARL | B4: 108 | C4: 1386313 | D4: 83 | E4: 9 | F4: 280323 | G4: 17 | H4: Permis de recherche | I4: =K4+L4+SUM(V4:AD4) -> 165567 | J4: 165567 | K4: 0 | L4: =SUM(N4:U4) -> 0 | M4: 0 | N4: 0 | O4: 0 | P4: 0 | Q4: 0 | R4: 0 | S4: 0 | T4: 0 | U4: 0 | V4: 4319 | W4: 897 | X4: 6050 | Y4: 111946 | Z4: 15697 | AB4: 8028 | AC4: 18630 | AD4: 0 | AE4: =AG4+AH4 -> 61651 | AF4: =AG4+AH4 -> 61651 | AG4: 61472 | AH4: 179 | AI4: =SUM(AK4:AY4) -> 400447 | AJ4: 400447 | AK4: 21745 | AL4: 69111 | AM4: 0 | AN4: 21497 | AO4: 45263 | AP4: 0 | AQ4: 0 | AR4: 67291 | AS4: 3296 | AT4: 112558 | AU4: 1641 | AV4: 5898 | AW4: 19324 | AX4: 0 | AY4: 32823 | AZ4: =SUM(BB4:BI4) -> 3420 | BA4: 3420 | BB4: 2698 | BC4: 0 | BD4: 0 | BE4: 415 | BF4: 0 | BG4: 0 | BH4: 0 | BI4: =BA4-(BB4+BE4) -> 307 | BJ4: =SUM(BL4:BQ4) -> 1343358 | BK4: 1343358 | BL4: 527688 | BM4: 577905 | BN4: 57421 | BO4: 8200 | BP4: 24915 | BQ4: 147229 | BR4: 267 | BS4: 35963 | BT4: 0 | BU4: =BV4 -> 2010673 | BV4: =I4+AE4+AI4+AZ4+BJ4+BR4+BS4+BT4 -> 2010673 | BW4: =+BV4-BU4 -> 0 | BX4: =+I4+AE4+AI4+BR4+BS4 -> 663895 | BZ4: =L4=M4 -> TRUE
A5: AGROMINE | B5: 7 | C5: 96890 | D5: 100 | E5: 0 | F5: 0 | G5: 0 | H5: Permis de recherche | I5: =K5+L5+SUM(V5:AD5) -> 35302 | J5: 35302 | K5: 0 | L5: =SUM(N5:U5) -> 14300 | M5: =SUM(N5:U5) -> 14300 | N5: 0 | O5: 0 | P5: =2400+3500 -> 5900 | Q5: =600+7800 -> 8400 | R5: 0 | S5: 0 | T5: 0 | U5: 0 | V5: =752+9000 -> 9752 | W5: =140+700 -> 840 | X5: =1400+3800 -> 5200 | Y5: 0 | Z5: 210 | AA5: 0 | AB5: 0 | AC5: 0 | AD5: =1500+3500 -> 5000 | AE5: =AG5+AH5 -> 32340 | AF5: =AG5 -> 32340 | AG5: 32340 | AH5: 0 | AI5: =SUM(AK5:AY5) -> 90040 | AJ5: =54000+36040 -> 90040 | AK5: =AJ5 -> 90040 | AM5: 0 | AN5: 0 | AO5: 0 | AP5: 0 | AQ5: 0 | AR5: 0 | AS5: 0 | AT5: 0 | AU5: 0 | AV5: 0 | AW5: 0 | AX5: 0 | AY5: 0 | AZ5: =SUM(BB5:BI5) -> 4760 | BA5: =BE5 -> 4760 | BB5: 0 | BC5: 0 | BD5: 0 | BE5: =2835+1925 -> 4760 | BF5: 0 | BG5: 0 | BH5: 0 | BI5: 0 | BJ5: =SUM(BL5:BQ5) -> 224700 | BK5: =BL5 -> 224700 | BL5: =166200+58500 -> 224700 | BM5: 0 | BN5: 0 | BO5: 0 | BP5: 0 | BQ5: 0 | BR5: 0 | BS5: 0 | BT5: 0 | BU5: =BV5 -> 387142 | BV5: =I5+AE5+AI5+AZ5+BJ5+BR5+BS5+BT5 -> 387142 | BW5: =+BV5-BU5 -> 0 | BX5: =+I5+AE5+AI5+BR5+BS5 -> 157682 | BZ5: =L5=M5 -> TRUE
A6: ALBINA SENEGAL SARL | B6: 0 | C6: 0 | D6: 0 | E6: 0 | F6: 0 | G6: 0 | H6: Carrière | I6: =K6+L6+SUM(V6:AD6) -> 147282 | J6: =I6 -> 147282 | K6: 0 | L6: =SUM(N6:U6) -> 95174 | M6: =P6 -> 95174 | N6: 0 | O6: 0 | P6: 95174 | Q6: 0 | R6: 0 | S6: 0 | T6: 0 | U6: 0 | V6: 0 | W6: 0 | X6: 0 | Y6: 0 | Z6: 39 | AA6: 0 | AB6: 52037 | AC6: 32 | AD6: 0 | AE6: =AG6+AH6 -> 0 | AG6: 0 | AH6: 0 | AI6: =SUM(AK6:AY6) -> 3093 | AJ6: =AL6+AN6+AO6 -> 3093 | AK6: 0 | AL6: 2735 | AM6: 0 | AN6: 286 | AO6: 72 | AP6: 0 | AQ6: 0 | AR6: 0 | AS6: 0 | AT6: 0 | AU6: 0 | AV6: 0 | AW6: 0 | AX6: 0 | AY6: 0 | AZ6: =SUM(BB6:BI6) -> 15981 | BA6: 15981 | BB6: 3167 | BC6: 0 | BD6: 0 | BE6: 2528 | BF6: 10286 | BG6: 0 | BH6: 0 | BI6: 0 | BJ6: =SUM(BL6:BQ6) -> 42881.804 | BK6: =BL6+BN6+BP6 -> 42881.804 | BL6: 27168.804 | BM6: 0 | BN6: 8153 | BO6: 0 | BP6: 7560 | BQ6: 0 | BR6: 0 | BS6: 0 | BT6: 261 | BU6: =BV6 -> 209498.8 | BV6: =I6+AE6+AI6+AZ6+BJ6+BR6+BS6+BT6 -> 209498.8 | BW6: =+BV6-BU6 -> 0 | BX6: =+I6+AE6+AI6+BR6+BS6 -> 150375 | BZ6: =L6=M6 -> TRUE
A7: AMAFRIQUE SENEGAL | B7: 0 | C7: 0 | D7: 0 | E7: 0 | F7: 0 | G7: 0 | H7: Permis de recherche | I7: =K7+L7+SUM(V7:AD7) -> 0 | J7: 0 | K7: 0 | L7: =SUM(N7:U7) -> 0 | M7: 0 | N7: 0 | O7: 0 | P7: 0 | Q7: 0 | R7: 0 | S7: 0 | T7: 0 | U7: 0 | V7: 0 | W7: 0 | X7: 0 | Y7: 0 | Z7: 0 | AA7: 0 | AB7: 0 | AC7: 0 | AD7: 0 | AE7: =AG7+AH7 -> 0 | AG7: 0 | AH7: 0 | AI7: =SUM(AK7:AY7) -> 8206 | AJ7: =AL7+AX7 -> 8206 | AK7: 0 | AL7: 1680 | AM7: 0 | AN7: 0 | AO7: 0 | AP7: 0 | AQ7: 0 | AR7: 0 | AS7: 0 | AT7: 0 | AU7: 0 | AV7: 0 | AW7: 0 | AX7: 6526 | AY7: 0 | AZ7: =SUM(BB7:BI7) -> 7751 | BA7: =BE7 -> 7751 | BB7: 0 | BC7: 0 | BD7: 0 | BE7: 7751 | BF7: 0 | BG7: 0 | BH7: 0 | BI7: 0 | BJ7: =SUM(BL7:BQ7) -> 39310 | BK7: =BL7+BP7 -> 39310 | BL7: 37755 | BM7: 0 | BN7: 0 | BO7: 0 | BP7: 1555 | BQ7: 0 | BR7: 0 | BS7: 0 | BT7: 0 | BU7: =BV7 -> 55267 | BV7: =I7+AE7+AI7+AZ7+BJ7+BR7+BS7+BT7 -> 55267 | BW7: =+BV7-BU7 -> 0 | BX7: =+I7+AE7+AI7+BR7+BS7 -> 8206 | BZ7: =L7=M7 -> TRUE
A8: ARDIMINES SARL | B8: 3 | C8: 1101008 | D8: 0 | E8: 1 | F8: 400000 | G8: 0 | H8: Permis de recherche | I8: =K8+L8+SUM(V8:AD8) -> 74110 | J8: =M8+V8+AA8+AC8 -> 74110 | K8: 0 | L8: =SUM(N8:U8) -> 33 | M8: =Q8 -> 33 | N8: 0 | O8: 0 | P8: 0 | Q8: 33 | R8: 0 | S8: 0 | T8: 0 | U8: 0 | V8: 70838 | W8: 0 | X8: 0 | Y8: 0 | Z8: 0 | AA8: 3135 | AB8: 0 | AC8: 104 | AD8: 0 | AE8: =AG8+AH8 -> 0 | AG8: 0 | AH8: 0 | AI8: =SUM(AK8:AY8) -> 6760 | AJ8: =AK8+AL8+AO8+AP8+AR8+AT8+AV8 -> 6760 | AK8: 2156 | AL8: 4090 | AM8: 0 | AN8: 0 | AO8: 85 | AP8: 16 | AQ8: 0 | AR8: 12 | AS8: 0 | AT8: 40 | AU8: 0 | AV8: 361 | AW8: 0 | AX8: 0 | AY8: 0 | AZ8: =SUM(BB8:BI8) -> 62978 | BA8: =BE8 -> 62978 | BB8: 0 | BC8: 0 | BD8: 0 | BE8: 62978 | BF8: 0 | BG8: 0 | BH8: 0 | BI8: 0 | BJ8: =SUM(BL8:BQ8) -> 28421 | BK8: =BL8+BO8+BP8 -> 28421 | BL8: 27000 | BM8: 0 | BN8: 0 | BO8: 40 | BP8: 1381 | BR8: 0 | BS8: 3640 | BT8: 0 | BU8: 175909 | BV8: =I8+AE8+AI8+AZ8+BJ8+BR8+BS8+BT8 -> 175909 | BW8: =+BV8-BU8 -> 0 | BX8: =+I8+AE8+AI8+BR8+BS8 -> 84510 | BZ8: =L8=M8 -> TRUE
A9: ATIC SARL | B9: 0 | C9: 0 | D9: 0 | E9: 1 | F9: 60000 | G9: 100 | H9: Carrière | I9: =K9+L9+SUM(V9:AD9) -> 121200 | J9: =+M9+AC9+AD9 -> 121200 | K9: 0 | L9: =SUM(N9:U9) -> 43200 | M9: =SUM(N9:U9) -> 43200 | N9: 0 | O9: 0 | P9: 0 | Q9: 43200 | R9: 0 | S9: 0 | T9: 0 | U9: 0 | V9: 0 | W9: 0 | X9: 0 | Y9: 0 | Z9: 0 | AA9: 0 | AB9: 0 | AC9: 60000 | AD9: 18000 | AE9: =AG9+AH9 -> 7500 | AF9: =AG9+AH9 -> 7500 | AG9: 1200 | AH9: 6300 | AI9: =SUM(AK9:AY9) -> 0 | AJ9: 0 | AK9: 0 | AL9: 0 | AM9: 0 | AN9: 0 | AO9: 0 | AP9: 0 | AQ9: 0 | AR9: 0 | AS9: 0 | AT9: 0 | AU9: 0 | AV9: 0 | AW9: 0 | AX9: 0 | AY9: 0 | AZ9: =SUM(BB9:BI9) -> 40142 | BA9: =SUM(BB9:BI9) -> 40142 | BB9: 500 | BC9: 0 | BD9: 1500 | BE9: 19000 | BF9: 19142 | BG9: 0 | BH9: 0 | BI9: 0 | BJ9: =SUM(BL9:BQ9) -> 156000 | BK9: =SUM(BL9:BQ9) -> 156000 | BL9: 108000 | BM9: 30000 | BN9: 0 | BO9: 18000 | BP9: 0 | BQ9: 0 | BR9: 0 | BS9: 0 | BT9: 500 | BU9: 325342 | BV9: =I9+AE9+AI9+AZ9+BJ9+BR9+BS9+BT9 -> 325342 | BW9: =+BV9-BU9 -> 0 | BX9: =+I9+AE9+AI9+BR9+BS9 -> 128700 | BZ9: =L9=M9 -> TRUE
A10: BAMBUK MINERALS SARL | B10: 8 | C10: 0 | D10: 90 | E10: 2 | F10: 0 | G10: 10 | H10: Permis de recherche | I10: =K10+L10+SUM(V10:AD10) -> 56045 | J10: 56045 | K10: 0 | L10: =SUM(N10:U10) -> 16337 | M10: =+Q10 -> 16337 | N10: 0 | O10: 0 | P10: 0 | Q10: =1657+14680 -> 16337 | R10: 0 | S10: 0 | T10: 0 | U10: 0 | V10: =58+266 -> 324 | W10: =16+300+8637 -> 8953 | X10: 0 | Y10: 0 | Z10: 359 | AA10: 30072 | AB10: 0 | AE10: =AG10+AH10 -> 0 | AG10: 0 | AH10: 0 | AI10: =SUM(AK10:AY10) -> 464008 | AJ10: 464008 | AK10: =53278 -> 53278 | AL10: =4090+4090 -> 8180 | AM10: 0 | AN10: 0 | AO10: =85+85 -> 170 | AP10: 247945 | AQ10: 0 | AR10: =12+12 -> 24 | AS10: 361 | AT10: =40+40 -> 80 | AU10: 0 | AV10: 1961 | AW10: 2326 | AX10: 141585 | AY10: 8098 | AZ10: =SUM(BB10:BI10) -> 2080 | BA10: 2080 | BB10: 0 | BC10: 0 | BD10: 0 | BE10: =174+1906 -> 2080 | BF10: 0 | BG10: 0 | BH10: 0 | BI10: 0 | BJ10: =SUM(BL10:BQ10) -> 1061424 | BK10: 1061424 | BL10: =445181+28968 -> 474149 | BM10: =426222+20799 -> 447021 | BN10: 3227 | BO10: =40+4649 -> 4689 | BP10: 132338 | BQ10: 0 | BR10: 0 | BS10: =3640+3640 -> 7280 | BT10: 0 | BU10: 1590837 | BV10: =I10+AE10+AI10+AZ10+BJ10+BR10+BS10+BT10 -> 1590837 | BW10: =+BV10-BU10 -> 0 | BX10: =+I10+AE10+AI10+BR10+BS10 -> 527333 | BZ10: =L10=M10 -> TRUE
A11: BHAIRAVA AGRICOLE SARL | B11: 4 | H11: Permis de recherche | I11: =K11+L11+SUM(V11:AD11) -> 2518 | J11: 2518 | K11: 2518 | L11: =SUM(N11:U11) -> 0 | AE11: =+AF11 -> 2264 | AF11: 2264 | AI11: =+AJ11 -> 7032 | AJ11: 7032 | AZ11: =SUM(BB11:BI11) -> 720 | BA11: 720 | BE11: 720 | BJ11: =+BK11 -> 15490 | BK11: 15490 | BR11: 4280 | BU11: 32304 | BV11: =I11+AE11+AI11+AZ11+BJ11+BR11+BS11+BT11 -> 32304 | BW11: =+BV11-BU11 -> 0 | BX11: =+I11+AE11+AI11+BR11+BS11 -> 16094 | BZ11: =L11=M11 -> TRUE
A12: BOSFOR SARL | B12: 11 | C12: 1040074 | D12: 73 | E12: 2 | F12: 386847 | G12: 27 | H12: Carrière | I12: =K12+L12+SUM(V12:AD12) -> 1094958 | J12: 1094958 | K12: 201840 | L12: =SUM(N12:U12) -> 820343 | M12: 820343 | N12: 588 | O12: 0 | P12: 0 | Q12: 814080 | R12: 0 | S12: 5675 | T12: 0 | U12: 0 | V12: 0 | W12: 0 | X12: 0 | Y12: 0 | Z12: 493 | AA12: 5940 | AB12: 64637 | AC12: 1705 | AD12: 0 | AE12: =AG12+AH12 -> 8474 | AF12: =AE12 -> 8474 | AG12: 4237 | AH12: 4237 | AI12: =SUM(AK12:AY12) -> 128626 | AJ12: 128626 | AK12: 0 | AL12: 2333 | AM12: 0 | AN12: 793 | AO12: 0 | AP12: 0 | AQ12: 0 | AR12: 773 | AS12: 7500 | AT12: 18389 | AU12: 0 | AV12: 4858 | AW12: 73800 | AX12: 11971 | AY12: 8209 | AZ12: =SUM(BB12:BI12) -> 26614 | BA12: 26614 | BB12: 6873 | BC12: 0 | BD12: 0 | BE12: 0 | BF12: 9625 | BG12: 6123 | BH12: 2088 | BI12: 1905 | BJ12: =SUM(BL12:BQ12) -> 241855 | BK12: =BJ12 -> 241855 | BL12: 133722 | BM12: 74969 | BN12: 10278 | BO12: 0 | BP12: 22886 | BQ12: 0 | BR12: 10575 | BS12: 382395 | BT12: 8296 | BU12: =BV12 -> 1901793 | BV12: =I12+AE12+AI12+AZ12+BJ12+BR12+BS12+BT12 -> 1901793 | BW12: =+BV12-BU12 -> 0 | BX12: =+I12+AE12+AI12+BR12+BS12 -> 1625028 | BZ12: =L12=M12 -> TRUE
A13: BOYA SA | B13: 0 | E13: 0 | H13: Permis de recherche | I13: =K13+L13+SUM(V13:AD13) -> 1964414 | J13: 1964414 | K13: 0 | L13: =SUM(N13:U13) -> 163111 | M13: 163111 | N13: 130488.8 | O13: 32622.2 | P13: 0 | Q13: 0 | R13: 0 | S13: 0 | T13: 0 | U13: 0 | V13: 0 | W13: 497 | X13: 3933 | Y13: 0 | Z13: 8888 | AA13: 33728 | AB13: 229490 | AC13: 1520594 | AD13: 4173 | AE13: 107561 | AF13: 107561 | AG13: 8690 | AH13: 98871 | AI13: 505926 | AJ13: 505926 | AK13: 0 | AL13: 44584 | AM13: 0 | AN13: 48710 | AO13: 6979 | AP13: 45 | AQ13: 2957 | AR13: 29629 | AS13: 28809 | AT13: 51339 | AU13: 1700 | AV13: 5274 | AW13: 28755 | AX13: 0 | AY13: 257145 | AZ13: 28327 | BA13: 28327 | BB13: 25273 | BC13: 2623 | BD13: 431 | BE13: 0 | BF13: 0 | BG13: 0 | BH13: 0 | BI13: 0 | BJ13: 862591 | BK13: 862591 | BL13: 436635 | BM13: 371043 | BN13: 13819 | BO13: 3431 | BP13: 27775 | BQ13: 9888 | BR13: 3323 | BS13: 104242 | BT13: 0 | BU13: 3576384 | BV13: =I13+AE13+AI13+AZ13+BJ13+BR13+BS13+BT13 -> 3576384 | BW13: =+BV13-BU13 -> 0 | BX13: =+I13+AE13+AI13+BR13+BS13 -> 2685466 | BZ13: =L13=M13 -> TRUE
A14: CAYOR PHOSPHATE MINING SAU | B14: 0 | C14: 0 | D14: 0 | E14: 0 | F14: 0 | G14: 0 | H14: Permis de recherche | I14: =K14+L14+SUM(V14:AD14) -> 1001 | J14: 1001 | K14: 0 | L14: =SUM(N14:U14) -> 0 | M14: 0 | N14: 0 | O14: 0 | P14: 0 | Q14: 0 | R14: 0 | S14: 0 | T14: 0 | U14: 0 | V14: 0 | W14: 35 | X14: 40 | Y14: 0 | Z14: 25 | AA14: 901 | AB14: 0 | AC14: 0 | AD14: 0 | AE14: =AG14+AH14 -> 0 | AG14: 0 | AH14: 0 | AI14: =SUM(AK14:AY14) -> 2230 | AJ14: 2230 | AK14: 0 | AL14: 585 | AM14: 0 | AN14: 0 | AO14: 0 | AP14: 0 | AQ14: 0 | AR14: 0 | AS14: 10 | AT14: 1203 | AU14: 0 | AV14: 0 | AW14: 0 | AX14: 432 | AY14: 0 | AZ14: =SUM(BB14:BI14) -> 21526 | BA14: =+BB14+BD14+BE14+BG14 -> 21526 | BB14: 10763 | BC14: 0 | BD14: 2500 | BE14: 7927 | BF14: 0 | BG14: 336 | BH14: 0 | BI14: 0 | BJ14: =SUM(BL14:BQ14) -> 0 | BK14: 0 | BL14: 0 | BM14: 0 | BN14: 0 | BO14: 0 | BP14: 0 | BQ14: 0 | BR14: 0 | BS14: 0 | BT14: 0 | BU14: 24757 | BV14: =I14+AE14+AI14+AZ14+BJ14+BR14+BS14+BT14 -> 24757 | BW14: =+BV14-BU14 -> 0 | BX14: =+I14+AE14+AI14+BR14+BS14 -> 3231 | BZ14: =L14=M14 -> TRUE
A15: CHALLENGER NORD-SUD INTERNATIONAL INC | B15: 0 | C15: 0 | D15: 0 | E15: 0 | F15: 0 | G15: 0 | H15: Permis de recherche | I15: =K15+L15+SUM(V15:AD15) -> 6881.32 | J15: 6881.32 | K15: 0 | L15: =SUM(N15:U15) -> 0 | M15: 0 | N15: 0 | O15: 0 | P15: 0 | Q15: 0 | R15: 0 | S15: 0 | T15: 0 | U15: 0 | V15: 1926.77 | W15: 825.758 | X15: 1582.704 | Y15: 577.876 | Z15: 385.508 | AA15: 550.506 | AB15: 344.066 | AC15: 0 | AD15: 688.132 | AE15: =AG15+AH15 -> 8476.706 | AF15: =AG15 -> 8476.706 | AG15: 8476.706 | AH15: 0 | AI15: =SUM(AK15:AY15) -> 12792.146 | AJ15: 12792.146 | AK15: 0 | AL15: 1459.2 | AM15: 0 | AN15: 1162 | AO15: 0 | AP15: 0 | AQ15: 0 | AR15: 1151.293 | AS15: 4093.487 | AT15: 0 | AU15: 0 | AV15: 1317.905 | AW15: 0 | AX15: 2400 | AY15: 1208.261 | AZ15: =SUM(BB15:BI15) -> 2490 | BA15: 2490 | BB15: 0 | BC15: 0 | BD15: 0 | BE15: 2490 | BF15: 0 | BG15: 0 | BH15: 0 | BI15: 0 | BJ15: =SUM(BL15:BQ15) -> 7800 | BK15: 7800 | BL15: 6000 | BM15: 0 | BN15: 0 | BO15: 0 | BP15: 1800 | BQ15: 0 | BR15: 0 | BS15: 0 | BU15: =BV15 -> 38440.172 | BV15: =I15+AE15+AI15+AZ15+BJ15+BR15+BS15+BT15 -> 38440.172 | BW15: =+BV15-BU15 -> 0 | BX15: =+I15+AE15+AI15+BR15+BS15 -> 28150.172 | BZ15: =L15=M15 -> TRUE
A16: CHESSER | B16: 3 | C16: 11999 | D16: 0 | E16: 0 | F16: 0 | G16: 0 | H16: Permis de recherche | I16: =K16+L16+SUM(V16:AD16) -> 5791 | J16: 5791 | K16: 0 | L16: =SUM(N16:U16) -> 131 | M16: 131 | N16: 0 | O16: 0 | P16: 0 | Q16: 0 | R16: 131 | S16: 0 | T16: 0 | U16: 0 | V16: 0 | W16: 0 | X16: 0 | Y16: 0 | Z16: 0 | AA16: 0 | AB16: 500 | AC16: 0 | AD16: 5160 | AE16: =AG16+AH16 -> 1032 | AF16: 1032 | AG16: 1032 | AH16: 0 | AI16: =SUM(AK16:AY16) -> 6708 | AJ16: 6708 | AK16: 0 | AL16: 0 | AM16: 0 | AN16: 0 | AO16: 0 | AP16: 0 | AQ16: 0 | AR16: 0 | AS16: 0 | AT16: 0 | AU16: 0 | AV16: 0 | AW16: 0 | AX16: 0 | AY16: 6708 | AZ16: =SUM(BB16:BI16) -> 0 | BA16: 0 | BB16: 0 | BC16: 0 | BD16: 0 | BE16: 0 | BF16: 0 | BG16: 0 | BH16: 0 | BI16: 0 | BJ16: =SUM(BL16:BQ16) -> 8313 | BK16: =BL16 -> 8313 | BL16: 8313 | BM16: 0 | BN16: 0 | BO16: 0 | BP16: 0 | BQ16: 0 | BR16: 0 | BS16: 0 | BT16: 0 | BU16: 21844 | BV16: =I16+AE16+AI16+AZ16+BJ16+BR16+BS16+BT16 -> 21844 | BW16: =+BV16-BU16 -> 0 | BX16: =+I16+AE16+AI16+BR16+BS16 -> 13531 | BZ16: =L16=M16 -> TRUE
A17: CIMENTS DU SAHEL | B17: 243 | C17: 66460438 | D17: 0 | E17: 146 | F17: 150359299 | G17: 0 | H17: Concession minière | I17: =K17+L17+SUM(V17:AD17) -> 95711292 | J17: =K17+L17+V17+W17+X17+Y17+Z17+AA17+AB17+AC17+AD17 -> 95711292 | K17: 6602432 | L17: =SUM(N17:U17) -> 75199228 | M17: 75199228 | N17: 0 | O17: 0 | P17: 0 | Q17: 12614951 | R17: 10993827 | S17: 382524 | T17: 51159937 | U17: 47989 | V17: 135940 | W17: 3987 | X17: 13435 | Y17: 136844 | Z17: 12160 | AA17: 234607 | AB17: 128625 | AC17: 8893 | AD17: 13235141 | AE17: =AG17+AH17 -> 482701 | AF17: =AG17 -> 482701 | AG17: 482701 | AH17: 0 | AI17: =SUM(AK17:AY17) -> 9078504 | AJ17: 9078504 | AK17: 0 | AL17: 3527682 | AM17: 0 | AN17: 3529351 | AO17: 1206753 | AP17: 1613 | AQ17: 15979 | AR17: 41981 | AS17: 0 | AT17: 447885 | AU17: 45 | AV17: 65983 | AW17: 12349 | AX17: 0 | AY17: 228883 | AZ17: =SUM(BB17:BI17) -> 2767922 | BA17: 2767922 | BB17: 0 | BC17: 0 | BD17: 0 | BE17: 0 | BF17: 262851 | BG17: 2943 | BH17: 2500000 | BI17: 2128 | BJ17: =SUM(BL17:BQ17) -> 8721540 | BK17: 8721540 | BL17: 7994326 | BN17: 117784 | BO17: 39915 | BP17: 501621 | BQ17: 67894 | BR17: 17552812 | BS17: 1835858 | BT17: 0 | BU17: =BV17 -> 136150629 | BV17: =I17+AE17+AI17+AZ17+BJ17+BR17+BS17+BT17 -> 136150629 | BW17: =+BV17-BU17 -> 0 | BX17: =+I17+AE17+AI17+BR17+BS17 -> 124661167 | BZ17: =L17=M17 -> TRUE
A18: COMPAGNIE GENERALE D'EXPLOITATION DE CARRIERE | B18: 112 | C18: 195000 | D18: 75 | E18: 15 | F18: 49000 | G18: 25 | H18: Carrière | I18: =K18+L18+SUM(V18:AD18) -> 7231304.7 | J18: =K18+L18+X18+Z18+AA18+AB18+AD18+Y18 -> 7231304.7 | K18: 1893399.1 | L18: =SUM(N18:U18) -> 2211495 | M18: 2211495 | N18: 0 | O18: 0 | P18: 0 | Q18: 2109355.7 | R18: 0 | S18: 34413.37 | T18: 0 | U18: 67725.933 | V18: 0 | W18: 0 | X18: 827071.09 | Y18: 11853 | Z18: 32856 | AA18: 33919.526 | AB18: 2205027 | AC18: 0 | AD18: 15684 | AE18: =AG18+AH18 -> 1624036 | AF18: =AG18+AH18 -> 1624036 | AG18: 1504078 | AH18: 119958 | AI18: =SUM(AK18:AY18) -> 1561082.7 | AJ18: =AL18+AN18+AO18+AP18+AR18+AS18+AU18+AV18+AW18 -> 1561082.7 | AK18: 0 | AL18: 27441.48 | AM18: 0 | AN18: 851652.55 | AO18: 231196.2 | AP18: 2550 | AQ18: 0 | AR18: 51639.837 | AS18: 327305.55 | AT18: 0 | AU18: 10344.667 | AV18: 55064.007 | AW18: 3888.445 | AX18: 0 | AY18: 0 | AZ18: =SUM(BB18:BI18) -> 901454.45 | BA18: =BB18+BC18+BE18+BG18+BH18 -> 901454.45 | BB18: 860672.83 | BC18: 22669.872 | BD18: 0 | BE18: 12235.02 | BF18: 0 | BG18: 1572.768 | BH18: 4303.965 | BI18: 0 | BJ18: =SUM(BL18:BQ18) -> 2297980.5 | BK18: =BL18+BM18+BN18+BO18+BP18 -> 2297980.5 | BL18: 1857912.5 | BM18: 116900.68 | BN18: 116594.37 | BO18: 24636.996 | BP18: 181935.94 | BQ18: 0 | BR18: 202321.91 | BS18: 19074.494 | BT18: 623022.9 | BU18: =BV18 -> 14460278 | BV18: =I18+AE18+AI18+AZ18+BJ18+BR18+BS18+BT18 -> 14460278 | BW18: =+BV18-BU18 -> 0 | BX18: =+I18+AE18+AI18+BR18+BS18 -> 10637820 | BZ18: =L18=M18 -> TRUE
A19: CSE GRANULATS | B19: 0 | C19: 0 | D19: 0 | E19: 0 | F19: 0 | G19: 0 | H19: Carrière | I19: =K19+L19+SUM(V19:AD19) -> 6133228 | J19: 6133228 | K19: 2240932 | L19: =SUM(N19:U19) -> 2548052 | M19: 2548052 | N19: 0 | O19: 0 | Q19: 2367347 | R19: 0 | S19: 180705 | T19: 0 | U19: 0 | V19: 14002 | W19: 441 | X19: 139841 | Y19: 2018 | Z19: 0 | AA19: 29621 | AB19: 0 | AC19: 1158321 | AD19: 0 | AE19: =AG19+AH19 -> 136661 | AF19: =AG19+AH19 -> 136661 | AG19: 135751 | AH19: 910 | AI19: =SUM(AK19:AY19) -> 3560407 | AJ19: 3560407 | AK19: 0 | AL19: 2975383 | AM19: 106792 | AN19: 181060 | AO19: 6670 | AP19: 0 | AQ19: 0 | AR19: 41532 | AS19: 0 | AT19: 8968 | AU19: 6526 | AV19: 19918 | AW19: 743 | AX19: 141929 | AY19: 70886 | AZ19: =SUM(BB19:BI19) -> 588135 | BA19: 588135 | BB19: 75155 | BC19: 42847 | BD19: 1000 | BE19: 362264 | BF19: 70196 | BG19: 3200 | BH19: 880 | BI19: 32593 | BJ19: =SUM(BL19:BQ19) -> 1476420 | BK19: 1476420 | BL19: 1171571 | BM19: 0 | BN19: 156600 | BO19: 0 | BP19: 130339 | BQ19: 17910 | BR19: 23157 | BS19: 69509 | BT19: 397462 | BU19: =BV19 -> 12384979 | BV19: =I19+AE19+AI19+AZ19+BJ19+BR19+BS19+BT19 -> 12384979 | BW19: =+BV19-BU19 -> 0 | BX19: =+I19+AE19+AI19+BR19+BS19 -> 9922962 | BZ19: =L19=M19 -> TRUE
A20: DALEMA | C20: 287967 | D20: 95 | E20: 1 | F20: 0 | G20: 0 | H20: Permis de recherche | I20: =K20+L20+SUM(V20:AD20) -> 57427 | J20: 57427 | K20: 0 | L20: =SUM(N20:U20) -> 57427 | M20: 57427 | N20: 0 | O20: 0 | P20: =J19-I19 -> 0 | Q20: 57427 | R20: 0 | S20: 0 | T20: 0 | U20: 0 | V20: 0 | W20: 0 | X20: 0 | Y20: 0 | Z20: 0 | AA20: 0 | AB20: 0 | AC20: 0 | AD20: 0 | AE20: =AG20+AH20 -> 0 | AG20: 0 | AH20: 0 | AI20: =SUM(AK20:AY20) -> 5449 | AJ20: 5449 | AK20: 0 | AL20: 0 | AM20: 0 | AN20: 5449 | AO20: 0 | AP20: 0 | AQ20: 0 | AR20: 0 | AS20: 0 | AT20: 0 | AU20: 0 | AV20: 0 | AW20: 0 | AX20: 0 | AY20: 0 | AZ20: =SUM(BB20:BI20) -> 0 | BA20: 0 | BB20: 0 | BC20: 0 | BD20: 0 | BF20: 0 | BG20: 0 | BH20: 0 | BI20: 0 | BJ20: =SUM(BL20:BQ20) -> 44545 | BK20: 44545 | BL20: 44545 | BM20: 0 | BN20: 0 | BO20: 0 | BP20: 0 | BQ20: 0 | BR20: 0 | BT20: 0 | BU20: 107421 | BV20: =I20+AE20+AI20+AZ20+BJ20+BR20+BS20+BT20 -> 107421 | BW20: =+BV20-BU20 -> 0 | BX20: =+I20+AE20+AI20+BR20+BS20 -> 62876 | BZ20: =L20=M20 -> TRUE
A21: DAMASH MINERALS LTD | B21: 1 | C21: 0 | D21: 25 | E21: 0 | F21: 0 | G21: 0 | H21: Permis de recherche | I21: =K21+L21+SUM(V21:AD21) -> 22013 | J21: 22013 | K21: 3514 | L21: =SUM(N21:U21) -> 5650 | M21: 5650 | N21: 0 | O21: 0 | P21: 5650 | Q21: 0 | R21: 0 | S21: 0 | T21: 0 | U21: 0 | V21: 1642 | W21: 1110 | X21: 3765 | Y21: 0 | Z21: 0 | AA21: 2200 | AB21: 4132 | AC21: 0 | AD21: 0 | AE21: =AG21+AH21 -> 0 | AG21: 0 | AH21: 0 | AI21: =SUM(AK21:AY21) -> 64954 | AJ21: 64954 | AK21: 0 | AL21: 0 | AM21: 0 | AN21: 0 | AO21: 0 | AP21: 64954 | AQ21: 0 | AR21: 0 | AS21: 0 | AT21: 0 | AU21: 0 | AV21: 0 | AW21: 0 | AX21: 0 | AY21: 0 | AZ21: =SUM(BB21:BI21) -> 0 | BA21: 0 | BB21: 0 | BC21: 0 | BD21: 0 | BE21: 0 | BF21: 0 | BG21: 0 | BH21: 0 | BI21: 0 | BJ21: =SUM(BL21:BQ21) -> 0 | BK21: 0 | BL21: 0 | BM21: 0 | BN21: 0 | BO21: 0 | BP21: 0 | BQ21: 0 | BR21: 0 | BS21: 0 | BT21: 0 | BU21: 86967 | BV21: =I21+AE21+AI21+AZ21+BJ21+BR21+BS21+BT21 -> 86967 | BW21: =+BV21-BU21 -> 0 | BX21: =+I21+AE21+AI21+BR21+BS21 -> 86967 | BZ21: =L21=M21 -> TRUE
A22: DANGOTE CEMENT SENEGAL | B22: 270 | C22: 24276063 | D22: 0 | E22: 92 | F22: 26717258 | G22: 0 | H22: Concession minière | I22: =K22+L22+SUM(V22:AD22) -> 39486954 | J22: 39486954 | K22: 6908752 | L22: =SUM(N22:U22) -> 23715529 | M22: 23715529 | N22: 0 | O22: 0 | P22: 0 | Q22: 2361104 | R22: 0 | S22: 0 | T22: 21354425 | U22: 0 | V22: 8535130 | W22: 53553 | X22: 13232 | Y22: 71313 | Z22: 32490 | AA22: 100759 | AB22: 55037 | AD22: 1159 | AE22: =AG22+AH22 -> 240429 | AF22: =AG22 -> 240429 | AG22: 240429 | AH22: 0 | AI22: =SUM(AK22:AY22) -> 6010747 | AJ22: =AL22+AN22+AO22+AP22+AQ22+AR22+AT22+AU22+AV22+AW22+AX22+AY22 -> 6010747 | AK22: 0 | AL22: 150497 | AM22: 0 | AN22: 1456036 | AO22: 410450 | AP22: 1420 | AQ22: 151707 | AR22: 135269 | AS22: 0 | AT22: 892639 | AU22: 30035 | AV22: 543437 | AW22: 13598 | AX22: 2209793 | AY22: 15866 | AZ22: =SUM(BB22:BI22) -> 135265 | BA22: 135265 | BB22: 67869 | BC22: 0 | BD22: 0 | BE22: 0 | BF22: 0 | BG22: 399 | BH22: 2188 | BI22: 64809 | BJ22: =SUM(BL22:BQ22) -> 4992446 | BK22: =BL22+BM22+BP22+BQ22 -> 4992446 | BL22: 3580371 | BM22: 1023283 | BN22: 0 | BO22: 0 | BP22: 230091 | BQ22: 158701 | BR22: 9196819 | BS22: 144117 | BT22: 0 | BU22: =BV22 -> 60206777 | BV22: =I22+AE22+AI22+AZ22+BJ22+BR22+BS22+BT22 -> 60206777 | BW22: =+BV22-BU22 -> 0 | BX22: =+I22+AE22+AI22+BR22+BS22 -> 55079066 | BZ22: =L22=M22 -> TRUE
A23: G.H MINING | B23: 77 | C23: 0 | D23: 100 | E23: 0 | F23: 0 | G23: 0 | H23: Petite mine | I23: =K23+L23+SUM(V23:AD23) -> 825249 | J23: 825249 | K23: 0 | L23: =SUM(N23:U23) -> 0 | M23: 0 | N23: 0 | O23: 0 | P23: 0 | Q23: 0 | R23: 0 | S23: 0 | T23: 0 | U23: 0 | V23: 0 | W23: 8 | X23: 0 | Y23: 177330 | Z23: 0 | AA23: 43919 | AB23: 35866 | AC23: 567037 | AD23: 1089 | AE23: =AG23+AH23 -> 9927 | AF23: =AG23+AH23 -> 9927 | AG23: 9196 | AH23: 731 | AI23: =SUM(AK23:AY23) -> 292015 | AJ23: =AL23+AN23+AS23+AT23+AV23+AX23 -> 292015 | AK23: 0 | AL23: 10375 | AM23: 0 | AN23: 60237 | AO23: 0 | AP23: 0 | AQ23: 0 | AR23: 0 | AS23: 1697 | AT23: 6500 | AU23: 0 | AV23: 1423 | AW23: 0 | AX23: 211783 | AY23: 0 | AZ23: =SUM(BB23:BI23) -> 92876 | BA23: 92876 | BB23: 2500 | BC23: 6879 | BD23: 0 | BE23: 0 | BF23: 22533 | BG23: 20 | BH23: 60000 | BI23: 944 | BJ23: =SUM(BL23:BQ23) -> 8999 | BK23: =BL23+BN23+BO23+BP23+BQ23 -> 8999 | BL23: 6000 | BM23: 0 | BN23: 124 | BO23: 175 | BP23: 272 | BQ23: 2428 | BR23: 7 | BS23: 2702 | BT23: 5000 | BU23: =BV23 -> 1236775 | BV23: =I23+AE23+AI23+AZ23+BJ23+BR23+BS23+BT23 -> 1236775 | BW23: =+BV23-BU23 -> 0 | BX23: =+I23+AE23+AI23+BR23+BS23 -> 1129900 | BZ23: =L23=M23 -> TRUE
A24: BMCC SA | B24: 0 | C24: 0 | D24: 0 | E24: 0 | F24: 0 | G24: 0 | H24: Permis d’exploitation | I24: =K24+L24+SUM(V24:AD24) -> 2027776 | J24: 2027776 | K24: 0 | L24: =SUM(N24:U24) -> 1763134 | M24: 1763134 | N24: 0 | O24: 0 | P24: 0 | Q24: 0 | R24: 1743942 | S24: 19192 | T24: 0 | U24: 0 | V24: 0 | W24: 36823 | X24: 10294 | Y24: 0 | Z24: 101616 | AA24: 26627 | AB24: 89029 | AC24: 0 | AD24: 253 | AE24: =AG24+AH24 -> 1109412 | AF24: 1109412 | AG24: 1109412 | AH24: 0 | AI24: =SUM(AK24:AY24) -> 4603897 | AJ24: 4603897 | AK24: 896807 | AL24: 1417523 | AM24: 0 | AN24: 980847 | AO24: 7886 | AP24: 23194 | AQ24: 18154 | AR24: 22483 | AS24: 0 | AT24: 745061 | AU24: 0 | AV24: 44069 | AW24: 18632 | AX24: 0 | AY24: 429241 | AZ24: =SUM(BB24:BI24) -> 255011 | BA24: 255011 | BB24: 125215 | BC24: 40 | BD24: 0 | BE24: 0 | BF24: 0 | BG24: 117419 | BH24: 0 | BI24: 12337 | BJ24: =SUM(BL24:BQ24) -> 190366 | BK24: 190366 | BL24: 183631 | BM24: 0 | BN24: 0 | BO24: 0 | BP24: 5670 | BQ24: 1065 | BR24: 468544 | BS24: 190774 | BT24: 0 | BU24: =BV24 -> 8845780 | BV24: =I24+AE24+AI24+AZ24+BJ24+BR24+BS24+BT24 -> 8845780 | BW24: =+BV24-BU24 -> 0 | BX24: =+I24+AE24+AI24+BR24+BS24 -> 8400403 | BZ24: =L24=M24 -> TRUE
A25: GECAMINES | B25: 250 | C25: 13110174 | D25: 83 | E25: 49 | F25: 1769824 | G25: 7 | H25: Carrière | I25: =K25+L25+SUM(V25:AD25) -> 3325679 | J25: =I25 -> 3325679 | K25: 0 | L25: =SUM(N25:U25) -> 2769724 | M25: 2769724 | N25: 0 | O25: 0 | P25: 0 | Q25: 2160746 | R25: 420764 | S25: 188214 | T25: 0 | U25: 0 | V25: 0 | W25: 4364 | X25: 249788 | Y25: 76046 | Z25: 0 | AA25: 122718 | AB25: 0 | AC25: 28373 | AD25: 74666 | AE25: =AG25+AH25 -> 5588917 | AF25: =AG25+AH25 -> 5588917 | AG25: 5521917 | AH25: 67000 | AI25: =SUM(AK25:AY25) -> 3158085 | AJ25: =AI25 -> 3158085 | AK25: 0 | AL25: 863424 | AM25: 0 | AN25: 132263 | AO25: 63498 | AP25: 0 | AQ25: 998 | AR25: 94849 | AS25: 2500 | AT25: 1343825 | AU25: 19173 | AV25: 74776 | AW25: 0 | AX25: 14400 | AY25: 548379 | AZ25: =SUM(BB25:BI25) -> 1273874 | BA25: 1273874 | BB25: 327704 | BC25: 17697 | BD25: 10000 | BE25: 3209 | BF25: 796150 | BG25: 11138 | BH25: 12276 | BI25: 95700 | BJ25: =SUM(BL25:BQ25) -> 2028866 | BK25: =BL25+BM25+BN25+BP25+BQ25 -> 2028866 | BL25: 1387613 | BM25: 141546 | BN25: 274777 | BO25: 0 | BP25: 176261 | BQ25: 48669 | BR25: 634303 | BS25: 429100 | BT25: 1041386 | BU25: =BV25 -> 17480210 | BV25: =I25+AE25+AI25+AZ25+BJ25+BR25+BS25+BT25 -> 17480210 | BW25: =+BV25-BU25 -> 0 | BX25: =+I25+AE25+AI25+BR25+BS25 -> 13136084 | BZ25: =L25=M25 -> TRUE
A26: G-PHOS S.A | B26: 19 | C26: 219614 | D26: =C26/($C$26+$F$26) -> 0.32140955 | E26: 6 | F26: 463670 | G26: =F26/($C$26+$F$26) -> 0.67859045 | H26: Permis d’exploitation | I26: =K26+L26+SUM(V26:AD26) -> 207384 | J26: =+Z26+AA26+AB26 -> 207384 | K26: 0 | L26: =SUM(N26:U26) -> 0 | M26: 0 | N26: 0 | O26: 0 | P26: 0 | Q26: 0 | R26: 0 | S26: 0 | T26: 0 | U26: 0 | V26: 0 | W26: 0 | X26: 0 | Y26: 0 | Z26: 255 | AA26: 171463 | AB26: 35666 | AC26: 0 | AD26: 0 | AE26: =AG26+AH26 -> 5140 | AF26: =AG26 -> 5140 | AG26: 5140 | AH26: 0 | AI26: =SUM(AK26:AY26) -> 248478 | AJ26: =+AL26+AN26+AO26+AP26+AT26+AV26+AW26+AY26 -> 248478 | AK26: 0 | AL26: 4610 | AM26: 0 | AN26: 468 | AO26: 117 | AP26: 95 | AQ26: 0 | AR26: 0 | AS26: 0 | AT26: 168335 | AU26: 0 | AV26: 7099 | AW26: 64388 | AX26: 0 | AY26: 3366 | AZ26: =SUM(BB26:BI26) -> 33 | BA26: 33 | BB26: 0 | BC26: 0 | BD26: 0 | BE26: 0 | BF26: 0 | BG26: 33 | BH26: 0 | BI26: 0 | BJ26: =SUM(BL26:BQ26) -> 0 | BK26: 0 | BL26: 0 | BM26: 0 | BN26: 0 | BO26: 0 | BP26: 0 | BQ26: 0 | BR26: 106222 | BS26: 48340 | BU26: 615597 | BV26: =I26+AE26+AI26+AZ26+BJ26+BR26+BS26+BT26 -> 615597 | BW26: =+BV26-BU26 -> 0 | BX26: =+I26+AE26+AI26+BR26+BS26 -> 615564 | BZ26: =L26=M26 -> TRUE
A27: GLOBAL IMMO SENEGAL SARL | H27: Carrière | I27: =K27+L27+SUM(V27:AD27) -> 551420.19 | J27: 551420.19 | K27: 125451 | L27: =SUM(N27:U27) -> 215146.83 | M27: 215146.83 | Q27: 215146.83 | W27: 725 | X27: 137116 | Z27: 2981.166 | AA27: 24050.966 | AB27: 35309.689 | AD27: 10639.539 | AE27: =AG27+AH27 -> 20842.859 | AF27: 20842.859 | AH27: 20842.859 | AI27: =SUM(AK27:AY27) -> 606892.39 | AJ27: 606892.39 | AN27: 572774.9 | AO27: 2465.677 | AQ27: 1688.582 | AR27: 11216.812 | AT27: 6627.19 | AY27: 12119.231 | AZ27: =SUM(BB27:BI27) -> 98142.476 | BA27: 98142.476 | BB27: 97538.408 | BG27: 604.068 | BJ27: =SUM(BL27:BQ27) -> 283582.32 | BK27: 283582.32 | BL27: 220493.12 | BN27: 38587.809 | BP27: 22274.34 | BQ27: 2227.049 | BR27: 27702.922 | BS27: 12247.488 | BT27: 35145.984 | BU27: 1635976.6 | BV27: =I27+AE27+AI27+AZ27+BJ27+BR27+BS27+BT27 -> 1635976.6 | BW27: =+BV27-BU27 -> 0 | BX27: =+I27+AE27+AI27+BR27+BS27 -> 1219105.8 | BZ27: =L27=M27 -> TRUE
A28: GRANDE COTE OPERATIONS | B28: 0 | C28: 0 | D28: 0 | E28: 0 | F28: 0 | G28: 0 | H28: Concession minière | I28: =K28+L28+SUM(V28:AD28) -> 24061009 | J28: 24061009 | K28: 631936 | L28: =SUM(N28:U28) -> 15165446 | M28: 15165446 | N28: 0 | O28: 0 | P28: 289 | Q28: 14565589 | R28: 0 | S28: 599568 | T28: 0 | U28: 0 | V28: 16576 | W28: 33275 | X28: 0 | Y28: 0 | Z28: 461 | AA28: 2646352 | AB28: 2361337 | AC28: 2780992 | AD28: 424634 | AE28: =AG28+AH28 -> 4064697 | AF28: =AG28+AH28 -> 4064697 | AG28: 3391775 | AH28: 672922 | AI28: =SUM(AK28:AY28) -> 36167602 | AJ28: =AI28 -> 36167602 | AK28: 1598136 | AL28: 3926994 | AM28: 0 | AN28: 385267 | AO28: 2339086 | AP28: 0 | AQ28: 117560 | AR28: 693979 | AS28: 12182 | AT28: 9505807 | AU28: 72907 | AV28: 85339 | AW28: 16483697 | AX28: 0 | AY28: 946648 | AZ28: =SUM(BB28:BI28) -> 10600725 | BA28: =BB28+BF28+BH28+BI28 -> 10600725 | BB28: 256492 | BC28: 0 | BD28: 0 | BE28: 0 | BF28: 10301250 | BG28: 0 | BH28: 33692 | BI28: 9291 | BJ28: =SUM(BL28:BQ28) -> 23686593 | BK28: 23686593 | BL28: 11333990 | BM28: 8109127 | BN28: 2698230 | BO28: 1545246 | BP28: 0 | BQ28: 0 | BR28: 22105386 | BS28: 12280334 | BT28: 0 | BU28: =BV28 -> 132966346 | BV28: =I28+AE28+AI28+AZ28+BJ28+BR28+BS28+BT28 -> 132966346 | BW28: =+BV28-BU28 -> 0 | BX28: =+I28+AE28+AI28+BR28+BS28 -> 98679028 | BZ28: =L28=M28 -> TRUE
A29: GROUPEMENT D'ENTREPRISE SINTRAM HOUAR | B29: 13 | C29: 285445 | D29: 100 | E29: 0 | F29: 0 | G29: 0 | H29: Carrière | I29: =K29+L29+SUM(V29:AD29) -> 224738 | J29: 224738 | K29: 0 | L29: =SUM(N29:U29) -> 102967 | M29: 102967 | N29: 0 | O29: 0 | P29: 0 | Q29: 89165 | R29: 0 | S29: 13046 | T29: 0 | U29: 756 | V29: 300 | W29: 0 | X29: 1350 | Y29: 0 | Z29: 0 | AA29: 114679 | AB29: 0 | AC29: 0 | AD29: 5442 | AE29: =AG29+AH29 -> 0 | AG29: 0 | AH29: 0 | AI29: =SUM(AK29:AY29) -> 42823 | AJ29: 42823 | AK29: 24713 | AL29: 3140 | AM29: 0 | AN29: 1470 | AO29: 0 | AP29: 0 | AQ29: 0 | AR29: 456 | AS29: 0 | AT29: 696 | AU29: 0 | AV29: 0 | AW29: 0 | AX29: 8895 | AY29: 3453 | AZ29: =SUM(BB29:BI29) -> 10427 | BA29: 10427 | BB29: 3134 | BC29: 0 | BD29: 0 | BE29: 7293 | BF29: 0 | BG29: 0 | BH29: 0 | BI29: 0 | BJ29: =SUM(BL29:BQ29) -> 112808 | BK29: 112808 | BL29: 40979 | BM29: 63473 | BN29: 0 | BO29: 0 | BP29: 7730 | BQ29: 626 | BR29: 0 | BS29: 0 | BT29: 0 | BU29: 390796 | BV29: =I29+AE29+AI29+AZ29+BJ29+BR29+BS29+BT29 -> 390796 | BW29: =+BV29-BU29 -> 0 | BX29: =+I29+AE29+AI29+BR29+BS29 -> 267561 | BZ29: =L29=M29 -> TRUE
