Workbook
Name \a: #N/A
Name \Convergence: 1000000
Name \i: #REF!
Name \IterationCount: 0
Name \PM: #REF!
Name \r: #REF!
Name \W: #REF!
Name \WorstStream: " "
Name _____________Inv27: #REF!
Name ____________Inv27: #REF!
Name ___________Inv27: #REF!
Name __________Inv27: #REF!
Name _________Inv27: #REF!
Name ________ABN1: #REF!
Name ________ADN1: #REF!
Name ________AIN1: #REF!
Name ________AJN1: #REF!
Name ________AZN1: #REF!
Name ________BCN1: #REF!
Name ________BDN1: #REF!
Name ________BEN1: #REF!
Name ________BFN1: #REF!
Name ________BHN1: #REF!
Name ________BIN1: #REF!
Name ________BJN1: #REF!
Name ________BKN1: #REF!
Name ________BSN1: #REF!
Name ________BUN1: #REF!
Name ________DAN1: #REF!
Name ________DCN1: #REF!
Name ________DGN1: #REF!
Name ________DIN1: #REF!
Name ________DJN1: #REF!
Name ________DKN1: #REF!
Name ________DLN1: #REF!
Name ________DMN1: #REF!
Name ________DNN1: #REF!
Name ________DPN1: #REF!
Name ________DTN1: #REF!
Name ________DVN1: #REF!
Name ________Inv27: #REF!
Name ________SAN1: #REF!
Name ________SCN1: #REF!
Name ________SLN1: #REF!
Name ________SQN1: #REF!
Name ________SRN1: #REF!
Name ________TFN1: #REF!
Name ________TQN1: #REF!
Name ________TTN1: #REF!
Name ________UAN1: #REF!
Name ________UCN1: #REF!
Name ________UEN1: #REF!
Name ________ULN1: #REF!
Name ________UNN1: #REF!
Name _______ABN1: #REF!
Name _______ADN1: #REF!
Name _______AIN1: #REF!
Name _______AJN1: #REF!
Name _______AZN1: #REF!
Name _______BCN1: #REF!

Sheet Page de garde
A1: DA
B5: REPUBLIQUE | I5: DU SENEGAL
B7: MINISTERE | I7: DES FINANCES ET DU BUDGET
B9: DIRECTION | I9: DIRECTION GENERALE DES IMPÔTS ET DES DOMAINES
B17: CENTRE DE DEPOT : Direction des Grandes Entreprises
A23: ETATS FINANCIERS NORMALISES
A24: SYSTÈME COMPTABLE (SYSCOHADA)
B27: EXERCICE CLOS LE : | M27: 45657
A30: DESIGNATION DE L'ENTREPRISE
C35: DENOMINATION SOCIALE : | L35: Sabodala Gold Operations S.A
C36: (ou nom et prénoms de l'exploitant)
C41: SIGLE USUEL : | H41: SGO
C46: ADRESSE COMPLETE : | J46: Route du Méridien Président, Immeuble 2k Plaza
C51: N° D'IDENTIFICATION FISCALE : | N51: 002850023
C55: SYSTEME NORMAL
C59: Documents déposés | V59: Réservé à la Direction Générale des Impôts
C62: Fiche d'identification et renseignements divers | S62: X | V62: Date de dépôt
C64: Bilan | S64: X
C66: Compte de résultat | S66: X | V66: Nom de l'agent de DGI ayant réceptionné le dépôt
C68: Tableau des flux de trésorerie | S68: X
C70: Notes annexes | S70: X | V70: Signature de l'agent et cachet du service
C72: Nombre de pages déposées par exemplaire
C73: Nombre d'exemplaires déposés | R73: 5

Sheet Fiche de renseignement R1
A1: Fiche R1
I4: Dénomination sociale de l’entreprise | J4: =+'Page de garde'!L35 -> Sabodala Gold Operations S.A
I7: Adresse de l'entreprise | J7: ='Page de garde'!J46 -> Route du Méridien Président, Immeuble 2k Plaza | AC7: Sigle usuel | AD7: =+'Page de garde'!H41 -> SGO
I10: N° d'identification fiscale | J10: ='Page de garde'!N51 -> 002850023 | U10: Exercice clos le | V10: =+'Page de garde'!M27 -> 45657 | AG10: Durée (en mois) | AH10: 12
B13: ZA | E13: EXERCICE COMPTABLE | W13: DU | Y13: 45292 | AF13: AU | AH13: 45657
B16: ZB | E16: DATE D'ARRETE EFFECTIF DES COMPTES | U16: =+V10 -> 45657
B20: ZC | E20: EXERCICE PRECEDENT CLOS LE | Q20: 45657 | AK20: DUREE EXERCICE PRECEDENT EN MOIS : | AL20: 12
B24: ZD | F24: SN | I24: SNDKR-2008-B1711 | W24: 002850023
F25: Greffe | I25: N° registre du Commerce | W25: N° répertoire des entreprises
B28: ZE | G28: 20950 | S28: 28457 | AE28: 006 002 Extraction d’autres
G29: N° de caisse sociale | S29: N° Code employeur | AE29: Code activité principale
B32: ZF | D32: =+J4 -> Sabodala Gold Operations S.A | AE32: =+AD7 -> SGO
D33: Désignation de l'entreprise | AE33: Sigle
B36: ZG | G36: 33 864 25 25 | Q36: 33 864 25 26 | Y36: 221 | AA36: 38385 Dakar Yoff | AE36: Dakar
G37: N° de téléphone | Q37: Télécopie | Y37: Code | AA37: Boîte postale | AE37: Ville
B40: ZH | D40: Route du Méridien Pdt - Immeuble 2K Plaza
D41: Adresse géographique complète (Immeuble, rue, quartier, ville, pays)
B44: ZI | D44: Industries extractives
D45: Désignation précise de l'activité principale exercée par l'entreprise
D48: Malick SOURANG - Responsable Financier
D49: Nom, adresse et qualité de personne à contacter en cas de demande d'informations complémentaires
D52: Malick SOURANG - Responsable Financier
D53: Nom du professionnel salarié de l'entreprise ou Nom, adresse et téléphone du cabinet comptable ou du professionnel INSCRIT A L'ORDRE NATIONAL DES EXPERTS COMPTABLES ET DES COMPTABLES AGREES ayant établi les états financiers.
D56: ERSNT & YOUNG - Commissaire aux comptes
D57: Noms et adresses du ou des commissaires au comptes
E64: Non assujettie | K64: Non (refus) | O64: Oui avec réserves | S64: X | T64: Oui sans réserves | Z64: Non assujettie | AF64: X | AG64: Non | AL64: Oui
C66: Etats financiers certifiés (cocher la case) | X66: Etats financiers approuvés par l'Assemblée Générale (cocher la case)
D69: Abdoul Aziz SY | T69: Domiciliations bancaires
D70: Nom du signataire des états financiers | T70: Banque | AD70: Numéro de compte
T71: SG PARIS CC USD | AD71: FR7630003033920302029993378
D72: Directeur Général | T72: SG PARIS CC EUR | AD72: FR7630003033920302029993378
D73: Qualité du signataire des états financiers | T73: SGBS DAKAR | AD73: SN011 01005 005001566924 66
T74: BICIS DAKAR | AD74: SN010 01528 000581200010 85
D75: 45777 | T75: CBAO DAKAR | AD75: SN012 01203 036184218501 85
D76: Date de signature | T76: CITIBANK | AD76: SN141 01001 000100180001 35
T77: SGBS DAKAR | AD77: SN011 01005 005000578086 29
T78: CITIBANK | AD78: SN141 01001 000100180025 60
T79: CITIBANK | AD79: SN141 01001 000100189001 01
D83: Signature

Sheet Activités de l'entreprise R2
A1: Fiche R2
B4: Désignation de l'entreprise : | C4: ='Fiche de renseignement R1'!$J$4 -> Sabodala Gold Operations S.A
B5: Adresse de l'entreprise :
B6: ='Fiche de renseignement R1'!J7 -> Route du Méridien Président, Immeuble 2k Plaza | L6: Sigle usuel : | M6: ='Fiche de renseignement R1'!AD7 -> SGO
B7: N° d'identification : | L7: Exercice clos le :
B8: =+'Fiche de renseignement R1'!J10 -> 002850023 | K8: ='Fiche de renseignement R1'!V10 -> 45657 | M8: Durée (en mois) | N8: ='Fiche de renseignement R1'!AH10 -> 12
A10: FICHE D'IDENTIFICATION ET RENSEIGNEMENTS DIVERS 2
L12: Contrôle de l'entreprise (cocher la case)
A14: ZK | B14: Forme juridique (1) | F14: 0 | G14: 1 | K14: ZQ | L14: Entreprise sous contrôle public
A16: ZL | B16: Régime fiscal (1) | F16: 1 | K16: ZR | L16: Entreprise sous contrôle privé national
A18: ZM | B18: Pays du siège social (1) | F18: 0 | G18: 7 | K18: ZS | L18: Entreprise sous contrôle privé étranger | Q18: X
A20: ZN | B20: Nbre d'établissements dans le pays | F20: 0 | G20: 1
A22: ZO | B22: Nbre d'établissements hors du pays | F22: 0 | G22: 0
B23: pour lesquels une comptabilité distincte est tenue
A25: ZP | B25: 1ère année exercice dans le pays | E25: 2 | F25: 0 | G25: 0 | H25: 8
A28: ACTIVITE DE L'ENTREPRISE
B30: DESIGNATION DE L'ACTIVITE (2) | C30: Code nomenclature d'activité (1) | K30: Valeur Ajoutée (VA) HT | M30: % activité dans le CA HT ou la VA
B33: Exploitation minière | F33: 6 | G33: 0 | H33: 0 | I33: 2 | L33: 3.3716269e+11 | M33: 1
M36: =+L36/$L$59 -> 0
M39: =+L39/$L$59 -> 0
M42: =+L42/$L$59 -> 0
M45: =+L45/$L$59 -> 0
M48: =+L48/$L$59 -> 0
M51: =+L51/$L$59 -> 0
M54: =+L54/$L$59 -> 0
B57: Divers
I59: TOTAL | L59: =SUM(L32:L56) -> 3.3716269e+11 | M59: =SUM(M32:M57) -> 1
B62: (1) Se réréfer aux tables des codes
B63: (2) Lister de manière précise les activités dans l'ordre décroissant du CAHT, ou de la valeur ajoutée (V.A.)
B64: (3) Rayer la mention inutile (utiliser de préférence la V.A.)

Sheet Dirigeants R3
A1: Fiche R3
A3: Désignation de l'entreprise | B3: ='Fiche de renseignement R1'!$J$4 -> Sabodala Gold Operations S.A
A4: Adresse de l'entreprise | B4: ='Activités de l''entreprise R2'!B6 -> Route du Méridien Président, Immeuble 2k Plaza | D4: Sigle usuel | E4: ='Activités de l''entreprise R2'!M6 -> SGO
A5: N° d'identification fiscale | B5: ='Activités de l''entreprise R2'!B8 -> 002850023 | C5: Exercice clos le | D5: ='Activités de l''entreprise R2'!K8 -> 45657 | E5: Durée (en mois) | F5: ='Activités de l''entreprise R2'!N8 -> 12
A7: FICHE D'IDENTIFICATION ET RENSEIGNEMENTS DIVERS 3
A9: DIRIGEANTS (1)
A11: Nom | B11: Prénoms | C11: Qualité | D11: N° d'identification fiscale | E11: Adressse (BP, ville, pays)
A12: SY | B12: ABDOUL AZIZ | C12: Directeur Général | E12: Dakar - Sénégal
A27: (1) Dirigeants = Président Directeur Général, Directeur Général, Adminsitrateur Général, Gérant, Autres.
A29: MEMBRES DU CONSEIL D'ADMINISTRATION
A31: Nom | B31: Prénoms | C31: Qualité | E31: Adressse (BP, ville, pays)
A32: Sabodala Gold Mauritius Limited représentée par : Abdoul Aziz SY | C32: Administrateur | E32: 6 CIO Kross Border Trust Services Limited St Louis Business Centre, Cnr Desroches & S. Louis Streets, Port Louis, Ile Maurice
A33: Etat du Sénégal représenté par Monsieur Moctar Kettani DOUCOURE | C33: Administrateur | E33: s/c Ministère des Finances et du Budget, Dakar, Sénégal
A34: TOURE | B34: Elhadj Ngagne Demba | C34: Administrateur | E34: s/c de la Société des Mines du Sénégal
A35: GASSAMA | B35: IBRAHIMA | C35: Administrateur | E35: s/c Ministère des Mines et de la Géologie - Pôle Urbain de Diamniadio, Dakar, Sénégal
A36: NDIAYE | B36: Mamadou Diagna | C36: Administrateur | E36: Immeuble Atlantis, Plateau, Dakar, Sénégal
A37: SY | B37: Abdoul Aziz | C37: Administrateur | E37: Villa AD34, Sicap Keur Gorgui, BP 25670, Dakar, Sénégal
A38: BERNASCONI | B38: Pascal | C38: Administrateur, Président du CA | E38: Abidjan, Côte d'Ivoire
A39: MANJENGWA | B39: Lawrence | C39: Administrateur | E39: Zimbabwé
A40: KOFFI | B40: Céline Aka | C40: Administrateur | E40: Cote d'Ivoire
A41: MBODJI | B41: Ibrahima | C41: Administrateur | E41: Dakar - Sénégal
A42: SANFO | B42: Zakaria | C42: Administrateur | E42: Dakar - Sénégal

Sheet Tableau des Notes R4
A1: FICHE R4
A2: Désignation entité : | B2: =+'Fiche de renseignement R1'!$J$4 -> Sabodala Gold Operations S.A | D2: Excercice clos le : | E2: =+'Fiche de renseignement R1'!$V$10 -> 45657
D3: Durée en mois : | E3: =+'Fiche de renseignement R1'!$AH$10 -> 12
A4: Numéro d'identification : | B4: =+'Fiche de renseignement R1'!$J$10 -> 002850023
A6: FICHE RECAPITULATIVE DES NOTES ANNEXES PRESENTEES
A8: NOTES | B8: INTITULES | C8: A | D8: N/A
A9: NOTE 1 | B9: DETTES GARANTIES PAR DES SURETES REELLES | C9: x
A10: NOTE 2 | B10: INFORMATIONS OBLIGATOIRES | C10: x
A11: NOTE 3A | B11: IMMOBILISATION BRUTE | C11: x
A12: NOTE 3B | B12: BIENS PRIS EN LOCATION ACQUISITION | C12: x
A13: NOTE 3C | B13: IMMOBILISATIONS : AMORTISSEMENTS | C13: x
A14: NOTE 3D | B14: IMMOBILISATIONS : PLUS-VALUES ET MOINS VALUES DE CESSION | C14: x
A15: NOTE 3E | B15: INFORMATIONS SUR LES REEVALUATIONS EFFECTUEES PAR L'ENTITE | D15: x
A16: NOTE 3F | B16: TABLEAU D'ETALEMENT DES CHARGES IMMOBILISEES | D16: x
A17: NOTE 4 | B17: IMMOBILISATIONS FINANCIERES | C17: x
A18: NOTE 5 | B18: ACTIF CIRCULANT HAO | D18: x
A19: NOTE 6 | B19: STOCKS ET ENCOURS | C19: x
A20: NOTE 7 | B20: CLIENTS PRODUITS A RECEVOIR | C20: x
A21: NOTE 8 | B21: AUTRES CREANCES | C21: x
A22: NOTE 9 | B22: TITRES DE PLACEMENT | D22: x
A23: NOTE 10 | B23: VALEURS A ENCAISSER | C23: x
A24: NOTE 11 | B24: DISPONIBILITES | C24: x
A25: NOTE 12 | B25: ECARTS DE CONVERSION | C25: x
A26: NOTE 13 | B26: CAPITAL : VALEUR NOMINALE DES ACTIONS OU PARTS | C26: x
A27: NOTE 14 | B27: PRIMES ET RESERVES | C27: x
A28: NOTE 15A | B28: SUBVENTIONS ET PROVISIONS REGLEMENTEES | D28: x
A29: NOTE 15B | B29: AUTRES FONDS PROPRES | D29: x
A30: NOTE 16A | B30: DETTES FINANCIERES ET RESSOURCES ASSIMILEES | C30: x
A31: NOTE 16B | B31: ENGAGEMENTS DE RETRAITE ET AVANTAGES ASSIMILES (METHODE ACTURIELLE) | D31: x
A32: NOTE 16B bis | B32: ENGAGEMENTS DE RETRAITE ET AVANTAGES ASSIMILES (METHODE ACTURIELLE) | D32: x
A33: NOTE 16C | B33: ACTIFS ET PASSIFS EVENTUELS | D33: x
A34: NOTE 17 | B34: FOURNISSEURS D'EXPLOITATION | C34: x
A35: NOTE 18 | B35: DETTES FISCALES ET SOCIALES | C35: x
A36: NOTE 19 | B36: AUTRES DETTES ET PROVISIONS POUR RISQUES A COURT TERME | C36: x
A37: NOTE 20 | B37: BANQUES, CREDIT D'ESCOMPTE ET TRESORERIE | C37: x
A38: NOTE 21 | B38: CHIFFRE D'AFFAIRES ET AUTRES PRODUITS | C38: x
A39: NOTE 22 | B39: ACHATS | C39: x
A40: NOTE 23 | B40: TRANSPORTS | C40: x
A41: NOTE 24 | B41: SERVICES EXTERIEURS | C41: x
A42: NOTE 25 | B42: IMPOTS ET TAXES | C42: x
A43: NOTE 26 | B43: AUTRES CHARGES | C43: x
A44: NOTE 27A | B44: CHARGES DE PERSONNEL | C44: x
A45: NOTE 27B | B45: EFFECTIFS, MASSE SALARIALE ET PERSONNEL EXTERIEUR | C45: x
... A47: NOTE 29 | B47: CHARGES ET REVENUS FINANCIERS | C47: x
A48: NOTE 30 | B48: AUTRES CHARGES ET PRODUITS HAO | D48: x
A49: NOTE 31 | B49: REPARTITION DU RESULTAT ET AUTRES ELEMENTS CARACTERISTIQUES DES CINQ DERNIERES ANNEES | C49: x
A50: NOTE 32 | B50: PRODUCTION DE L'EXERCICE | C50: x
A51: NOTE 33 | B51: ACHATS DESTINES A LA PRODUCTION | D51: X
A52: NOTE 34 | B52: FICHE DE SYNTHESE DES PRINCIPAUX INDICATEURS FINANCIERS | C52: x
A53: NOTE 35 | B53: LISTE DES INFORMATIONS SOCIALES, ENVIRONNEMENTALES ET SOCIALES A FOURNIR | C53: x
A54: NOTE 36 | B54: TABLES DES CODES | C54: x

Sheet BILAN PAYSAGE
A1: BILAN PAYSAGE
A3: Désignation entité : | D3: =+'Tableau des Notes R4'!B2 -> Sabodala Gold Operations S.A | I3: Excercice clos le : | J3: =+'Fiche de renseignement R1'!$V$10 -> 45657
I4: Durée en mois : | J4: =+'Fiche de renseignement R1'!$AH$10 -> 12
A5: Numéro d'identification : | D5: =+'Fiche de renseignement R1'!$J$10 -> 002850023
A7: REF | B7: ACTIF | C7: Note | E7: Exercice au 31/12/N | G7: Exercice au 31/12/N-1 | H7: REF | I7: PASSIF | J7: Note | K7: Exercice au 31/12/N | L7: Exercice au 31/12/N-1
D8: Brut | E8: Amorts et Dépréc. | F8: Net | G8: Net | K8: Net | L8: Net
A9: AD | B9: IMMOBILISATIONS INCORPORELLES | C9: 3 | D9: 5.948758e+11 | E9: 3.4595603e+11 | F9: 2.4891977e+11 | G9: 2.8127399e+11 | H9: CA | I9: CAPITAL | J9: 13 | K9: 10500000 | L9: 10500000
A10: AE | B10: Frais de développement et de prospection | D10: 5.5825964e+11 | E10: 3.4391615e+11 | F10: 2.1434349e+11 | G10: 2.5711648e+11 | H10: CB | I10: Apporteurs capital non appelé | J10: 13 | K10: 0 | L10: 0
A11: AF | B11: Brevets, licences, logiciels et droits similaires | D11: 2.1875373e+09 | E11: 2.0398808e+09 | F11: 1.4765655e+08 | G11: 1.7882297e+08 | H11: CD | I11: Primes liées au capital social | J11: 14 | K11: 50704413696 | L11: 50704413696
A12: AG | B12: Fonds commercial et droit au bail | D12: 0 | E12: 0 | F12: 0 | G12: 0 | H12: CE | I12: Ecarts de réévaluation | J12: 3e | K12: 0 | L12: 0
A13: AH | B13: Autres immobilisations incorporelles | D13: 3.4428619e+10 | E13: 0 | F13: 3.4428619e+10 | G13: 2.397869e+10 | H13: CF | I13: Réserves indisponibles | J13: 14 | K13: 2100000 | L13: 2000000
A14: AI | B14: IMMOBILISATIONS CORPORELLES | C14: 3 | D14: 5.1222627e+11 | E14: 2.1067302e+11 | F14: 3.0155326e+11 | G14: 2.4705803e+11 | H14: CG | I14: Réserves libres | J14: 14 | K14: 0 | L14: 0
A15: AJ | B15: Terrains (1) (1) dont placement en net ………../………… | D15: 0 | E15: 0 | F15: 0 | H15: CH | I15: Report à nouveau (+ ou -) | J15: 14 | K15: 4.2060701e+11 | L15: 348511721438
A16: AK | B16: Bâtiments (1) dont placement en net ………../………… | D16: 4.5086893e+10 | E16: 2.5813226e+10 | F16: 1.9273667e+10 | G16: 1.3954137e+10 | H16: CJ | I16: Résutat net de l'exercice (bénéfice + ou perte -) | K16: 57851662541 | L16: 1.3709634e+11
A17: AL | B17: Aménagements, agencements et installations | D17: 3.1715697e+11 | E17: 1.2433049e+11 | F17: 1.9282648e+11 | G17: 1.859635e+11 | H17: CL | I17: Subventions d'investissement | J17: 15 | K17: 0 | L17: 0
A18: AM | B18: Matériel, mobilier et actifs biologiques | D18: 1.4333245e+11 | E18: 5.5154109e+10 | F18: 8.8178344e+10 | G18: 3.5474848e+10 | H18: CM | I18: Provisions réglementées et fonds assimilés | J18: 15 | K18: 0 | L18: 0
A19: AN | B19: Matériel de transport | D19: 6.3593049e+09 | E19: 5.3751946e+09 | F19: 9.8411035e+08 | G19: 1.3637898e+09 | H19: CP | I19: TOTAL CAPITAUX PROPRES ET RESSOURCES ASSIMILEES | K19: 5.2917569e+11 | L19: 5.3632498e+11
A20: AP | B20: Avances & acomptes versés sur immobilisations | C20: 3 | D20: 2.9065658e+08 | E20: 0 | F20: 2.9065658e+08 | G20: 1.0301753e+10 | H20: DA | I20: Emprunts et dettes financières diverses | J20: 16 | K20: 4.1732566e+10 | L20: 3.9946905e+10
A21: AQ | B21: IMMOBILISATIONS FINANCIERES | C21: 4 | D21: 407226428 | E21: 0 | F21: 407226428 | G21: 431226428 | H21: DB | I21: Dettes de location acquisition | J21: 16 | K21: 6.0241819e+08 | L21: 5.6499704e+08
A22: AR | B22: Titres de participation | D22: 0 | E22: 0 | F22: 0 | G22: 0 | H22: DC | I22: Provisions pour risques et charges | J22: 16 | K22: 3.7765366e+10 | L22: 3.3349151e+10
A23: AS | B23: Autres immobilisations financières | D23: 407226428 | E23: 0 | F23: 407226428 | G23: 431226428 | H23: DD | I23: TOTAL DETTES FINANCIERES ET RESSOURCES ASSIMILEES | K23: 8.010035e+10 | L23: 7.3861053e+10
A24: AZ | B24: TOTAL ACTIF IMMOBILISE | D24: 1.1075093e+12 | E24: 5.5662905e+11 | F24: 5.5088025e+11 | G24: 5.2876325e+11 | H24: DF | I24: TOTAL RESSOURCES STABLES | K24: 6.0927604e+11 | L24: 6.1018603e+11
A25: BA | B25: ACTIF CIRCULANT H.A.O. | C25: 5 | D25: 0 | E25: 0 | F25: 0 | G25: 0 | H25: DH | I25: Dettes circulantes HAO | J25: 5 | K25: 0 | L25: 0
A26: BB | B26: STOCKS ET ENCOURS | C26: 6 | D26: 1.5771953e+11 | E26: 9.6629245e+09 | F26: 1.4805661e+11 | G26: 1.1986613e+11 | H26: DI | I26: Clients, avances reçues | J26: 7 | K26: 0 | L26: 0
A27: BG | B27: CREANCES ET EMPLOIS ASSIMILES | D27: 4.6729739e+10 | E27: 0 | F27: 4.6729739e+10 | G27: 6.639748e+10 | H27: DJ | I27: Fournisseurs d'exploitation | J27: 17 | K27: 4.5625346e+10 | L27: 4.4185646e+10
A28: BH | B28: Fournisseurs, avances versées | C28: 17 | D28: 3.6960548e+09 | E28: 0 | F28: 3.6960548e+09 | G28: 4.5610626e+09 | H28: DK | I28: Dettes fiscales et sociales | J28: 18 | K28: 3.8694253e+10 | L28: 7.2919235e+10
A29: BI | B29: Clients | C29: 7 | D29: 2.2384217e+08 | E29: 0 | F29: 2.2384217e+08 | G29: 4.4494604e+09 | H29: DM | I29: Autres dettes | J29: 19 | K29: 6.8376294e+10 | L29: 4.3101673e+10
A30: BJ | B30: Autres créances | C30: 8 | D30: 4.2809842e+10 | E30: 0 | F30: 4.2809842e+10 | G30: 5.7386957e+10 | H30: DN | I30: Provisions pour risques à court terme | J30: 19 | K30: 4.9123551e+09 | L30: 3.5306801e+09
A31: BK | B31: TOTAL ACTIF CIRCULANT | D31: 2.0444927e+11 | E31: 9.6629245e+09 | F31: 1.9478635e+11 | G31: 1.8626361e+11 | H31: DP | I31: TOTAL PASSIF CIRCULANT | K31: 1.5760825e+11 | L31: 1.6373723e+11
A32: BQ | B32: Titres de placement | C32: 9 | D32: 0 | E32: 0 | F32: 0 | G32: 0 | K32: 0 | L32: 0
A33: BR | B33: Valeurs à encaisser | C33: 10 | D33: 1729831521 | E33: 0 | F33: 1729831521 | G33: 945599580 | H33: DQ | I33: Banques, crédits d'escompte | J33: 20 | K33: 0 | L33: 0
A34: BS | B34: Banques, chèques postaux, caisse et assimilés | C34: 11 | D34: 1.9217116e+10 | E34: 0 | F34: 1.9217116e+10 | G34: 5.4227066e+10 | H34: DR | I34: Banques, établissements financiers et crédits de trésorerie | J34: 20 | K34: 8000000000 | L34: 154577
A35: BT | B35: TOTAL TRESORERIE - ACTIF | D35: 2.0946947e+10 | E35: 0 | F35: 2.0946947e+10 | G35: 5.5172666e+10 | H35: DT | I35: TOTAL TRESORERIE - PASSIF | K35: 8000000000 | L35: 154577
A36: BU | B36: Ecarts de conversion - Actif | C36: 12 | D36: 8.2707414e+09 | E36: 0 | F36: 8.2707414e+09 | G36: 4.6132099e+09 | H36: DV | I36: Ecarts de conversion - Passif | J36: 12 | K36: 0 | L36: 8.8931858e+08
A37: BZ | B37: TOTAL GENERAL | D37: 1.3411763e+12 | E37: 5.6629197e+11 | F37: 774884286268 | G37: 7.7481274e+11 | H37: DZ | I37: TOTAL GENERAL | K37: 774884286268 | L37: 7.7481274e+11

Sheet COMPTE DE RESULTAT
A1: COMPTE DE RESULTAT
A3: Désignation entité :Sabodala Gold Operations S.A | D3: Excercice clos le : | E3: =+'Fiche de renseignement R1'!$V$10 -> 45657
D4: Durée en mois : | E4: =+'Fiche de renseignement R1'!$AH$10 -> 12
A5: Numéro d'identification : | B5: =+'Fiche de renseignement R1'!$J$10 -> 002850023
A7: REF | B7: LIBELLES | D7: NOTE | E7: 31/12/N | F7: 31/12/N-1
A8: TA | B8: Ventes de marchandises A | C8: + | D8: 21 | E8: 0 | F8: 0
A9: RA | B9: Achats de marchandises | C9: - | D9: 22 | E9: 0 | F9: 0
A10: RB | B10: Variation de stocks de marchandises | C10: -/+ | D10: 6 | E10: 0 | F10: 0
A11: XA | B11: MARGE BRUTE SUR MARCHANDISES (somme TA à RB) | E11: 0 | F11: 0
A12: TB | B12: Ventes de produits fabriqués B | C12: + | D12: 21 | E12: 3.3716269e+11 | F12: 3.5407533e+11
A13: TC | B13: Travaux, services vendus C | C13: + | D13: 21 | E13: 0 | F13: 0
A14: TD | B14: Produits accessoires D | C14: + | D14: 21 | E14: 0 | F14: 0
A15: XB | B15: CHIFFRE D'AFFAIRES (A + B + C + D) | E15: 337162693235 | F15: 3.5407533e+11
A16: TE | B16: Production stockée (ou destockage) | C16: -/+ | D16: 6 | E16: 1.7407545e+10 | F16: 2.6055476e+10
A17: TF | B17: Production immobilisée | D17: 21 | E17: 0 | F17: 0
A18: TG | B18: Subventions d'exploitation | D18: 21 | E18: 0 | F18: 0
A19: TH | B19: Autres produits | C19: + | D19: 21 | E19: 9.7362148e+09 | F19: 2.444924e+10
A20: TI | B20: Transferts de charges d'exploitation | C20: + | D20: 12 | E20: 2.0101757e+10 | F20: 2.0280953e+10
A21: RC | B21: Achats de matières premières et fournitures liées | C21: - | D21: 22 | E21: 0 | F21: 0
A22: RD | B22: Variation de stocks de stocks de matières premières et fournitures liées | C22: -/+ | D22: 6 | E22: 0 | F22: 0
A23: RE | B23: Autres achats | C23: - | D23: 22 | E23: -9.8270284e+10 | F23: -7.136424e+10
A24: RF | B24: Variation de stocks d'autres approvisionnements | C24: -/+ | D24: 6 | E24: 1.0999104e+10 | F24: 1.2174809e+09
A25: RG | B25: Transports | C25: - | D25: 23 | E25: -2.5246668e+09 | F25: -1.8888878e+09
A26: RH | B26: Services extérieurs | C26: - | D26: 24 | E26: -2.8766951e+10 | F26: -2.5755498e+10
A27: RI | B27: Impôts et taxes | C27: - | D27: 25 | E27: -2.315184e+10 | F27: -44009458558
A28: RJ | B28: Autres charges | C28: - | D28: 26 | E28: -1.1879175e+10 | F28: -1.1186585e+10
A29: XC | B29: VALEUR AJOUTEE (XB + RA + RB) + (somme TE à RJ) | E29: 2.308144e+11 | F29: 2.7187381e+11
A30: RK | B30: Charges de personnel | C30: - | D30: 27 | E30: -5.1202887e+10 | F30: -3.6700823e+10
A31: XD | B31: EXCEDENT BRUT D'EXPLOITATION (XC + RK) | E31: 1.7961151e+11 | F31: 2.3517299e+11
A32: TJ | B32: Reprises d'amortissements, provisions et dépréciations | C32: + | D32: 28 | E32: 1.7207649e+09 | F32: 1.0232607e+09
A33: RL | B33: Dotations aux amortissements, aux provisions et dépréciations | C33: - | D33: 3C & 28 | E33: -9.7413143e+10 | F33: -6.1139751e+10
A34: XE | B34: RESULTAT D'EXPLOITATION (XD + TJ + RL) | E34: 8.3919133e+10 | F34: 1.750565e+11
A35: TK | B35: Revenus financiers et assimilés | C35: + | D35: 29 | E35: 0 | F35: 0
A36: TL | B36: Reprises de provisions et dépréciations financières | C36: + | D36: 28 | E36: 3.5406524e+09 | F36: 1.3394153e+10
A37: TM | B37: Tranferts de charges financières | C37: + | D37: 12 | E37: 0 | F37: 0
A38: RM | B38: Frais financiers et charges assimilées | C38: - | D38: 29 | E38: -3.4265364e+09 | F38: -1.5562051e+09
A39: RN | B39: Dotations aux provisions et aux dépréciations financières | C39: - | D39: 3C & 28 | E39: -4.5016509e+09 | F39: -1.6223677e+09
A40: XF | B40: RESULTAT FINANCIER (somme TK à RN) | E40: -4.3875349e+09 | F40: 1.021558e+10
A41: XG | B41: RESULTAT DES ACTIVITES ORDINAIRES (XE + XF) | E41: 7.9531598e+10 | F41: 1.8527208e+11
A42: TN | B42: Produits des cessions d'immobilisations | C42: + | D42: 3D | E42: 0 | F42: 0
A43: TO | B43: Autres produits H.A.O. | C43: + | D43: 30 | E43: 0 | F43: 0
A44: RO | B44: Valeurs comptables des cessions d'immobilisations | C44: - | D44: 3D | E44: -8.8101416e+08 | F44: -3.9878994e+08
A45: RP | B45: Autres charges H.A.O. | C45: - | D45: 30 | E45: 0
A46: XH | B46: RESULTAT HORS ACTIVITES ORDINAIRES (somme TN à RP) | E46: -8.8101416e+08 | F46: -3.9878994e+08
A47: RQ | B47: Participation des travailleurs | C47: - | D47: 30 | E47: 0 | F47: 0
A48: RS | B48: Impôts sur le résultat | C48: - | E48: -2.0798922e+10 | F48: -47776945172
A49: XI | B49: RESULTAT NET (XG + XH + RQ + RS) | E49: 57851662541 | F49: 1.3709634e+11

Sheet FLUX DE TRESORERIE
A1: FLUX DE TRESORERIE
A3: Désignation entité :Sabodala Gold Operations S.A | D3: Excercice clos le : | E3: =+'Fiche de renseignement R1'!$V$10 -> 45657
D4: Durée en mois : | E4: =+'Fiche de renseignement R1'!$AH$10 -> 12
A5: Numéro d'identification : | B5: =+'Fiche de renseignement R1'!$J$10 -> 002850023
A7: REF | B7: LIBELLES | D7: NOTE | E7: 31/12/N | F7: 31/12/N-1
A8: ZA | B8: Trésorerie nette au 1er janvier (Trésorerie actif N-1 - Trésorerie passif N-1) | C8: A | E8: 5.5172511e+10 | F8: 5.7322902e+10
B9: Flux de trésorerie provenant des activités opérationnelles
A10: FA | B10: Capacité d'Autofinancement Globale (CAFG) | E10: 1.5538605e+11 | F10: 1.8583984e+11
A11: FB | B11: - Variation d'actif circulant HAO (1) | E11: 0 | F11: 0
A12: FC | B12: - Variation des stocks | E12: -2.8190477e+10 | F12: -2.4811423e+10
A13: FD | B13: - Variation des créances | E13: 1.9667741e+10 | F13: -1.9999458e+10
A14: FE | B14: + Variation du passif circulant (1) | E14: -2.8515051e+10 | F14: -1.1381167e+09
B15: Variation du BF lié aux activités opérationnelles (FB + FC + FD + FE) : …………………………………………….. | E15: =SUM(E11:E14) -> -3.7037787e+10 | F15: -4.5948998e+10
A16: ZB | B16: Flux de trésorerie provenant des activités opérationnelles (somme FA à FE) | C16: B | E16: 1.1834827e+11 | F16: 1.3989084e+11
B17: Flux de trésorerie provenant des activités d'investissement
A18: FF | B18: - Décaissements liés aux acquisitions d'immobilisations incorporelles | E18: -3.3600447e+10 | F18: -4.4383364e+10
A19: FG | B19: - Décaissements liés aux acquisitions d'immobilisations corporelles | E19: -8.1927164e+10 | F19: -1.1158633e+11
A20: FH | B20: - Décaissements liés aux acquisitions d'immobilisations financières | E20: 0 | F20: -53831204
A21: FI | B21: + Encaissements liés aux cessions d'immobilisations incorporelles et corporelles | E21: 0 | F21: 0
A22: FJ | B22: + Encaissements liés aux cessions d'immobilisations financières | E22: 24000000 | F22: 0
A23: ZC | B23: Flux de trésorerie provenant des activités d'investissement (somme FF à FJ) | C23: C | E23: -1.1550361e+11 | F23: -1.5602352e+11
B24: Flux de trésorerie provenant du financement par les capitaux propres
A25: FK | B25: + Augmentations de capital par apports nouveaux | E25: 0
A26: FL | B26: + Subventions d'investissements reçues | E26: 0 | F26: 0
A27: FM | B27: - Prélèvements sur le capital | E27: 0 | F27: 0
A28: FN | B28: - Dividendes versés | E28: -44387621281 | F28: -2.6462868e+10
A29: ZD | B29: Flux de trésorerie provenant des capitaux propres (somme FK à FN) | C29: D | E29: -44387621281 | F29: -2.6462868e+10
B30: Flux de trésorerie provenant du financement par les capitaux étrangers
A31: FO | B31: + Emprunts | E31: 0 | F31: 4.0445163e+10
A32: FP | B32: + Autres dettes financières | E32: 2.4174025e+09 | F32: 0
A33: FQ | B33: - Remboursements des emprunts et autres dettes financières | E33: -3100000000
A34: ZE | B34: Flux de trésorerie provenant des capitaux étrangers (somme FO à FQ) | C34: E | E34: -6.8259753e+08 | F34: 4.0445163e+10
A35: ZF | B35: Flux de trésorerie provenant des activités de financement (D + E) | C35: F | E35: -4.5070219e+10 | F35: 1.3982295e+10
A36: ZG | B36: VARIATION DE LA TRESORERIE NETTE DE LA PERIODE (B + C + F) | C36: G | E36: -4.2225564e+10 | F36: -2.1503907e+09
A37: ZH | B37: Trésorerie nette au 31 décembre (G + A) Contrôle : Trésorerie actif N - Trésorerie passif N | C37: H | E37: 1.2946947e+10 | F37: 5.5172511e+10
B38: Contrôle

Sheet Note 1
A1: NOTE 1 : DETTES GARANTIES PAR DES SURETES REELLES
A3: Désignation entité : | D3: Excercice clos le : | E3: =+'Fiche de renseignement R1'!$V$10 -> 45657
A4: =+'Fiche de renseignement R1'!$J$4 -> Sabodala Gold Operations S.A | D4: Durée en mois : | E4: =+'Fiche de renseignement R1'!$AH$10 -> 12
A5: Numéro d'identification : | B5: =+'Fiche de renseignement R1'!$J$10 -> 002850023
A7: LIBELLES | B7: Note | C7: Montant brut | D7: SURETES REELLES
D8: Hypothèques | E8: Nantissements | F8: Gages
F9: Autres
A10: Dettes financières et ressources assimilées :
A11: Emprunts obligataires convertibles
A12: Autres emprunts obligataires
A13: Emprunts et dettes des établissements de crédit
A14: Autres dettes financières
A15: SOUS TOTAL (1) | C15: =SUM(C11:C14) -> 0 | D15: =SUM(D11:D14) -> 0 | E15: =SUM(E11:E14) -> 0 | F15: =SUM(F11:F14) -> 0
A17: Dettes de location-acquisition :
A18: Dettes de crédit-bail immobilier
A19: Dettes de crédit-bail mobilier
A20: Dettes sur contrats de location-vente
A21: Dettes sur contrats de location-acquisition
A22: SOUS TOTAL (2) | C22: =SUM(C18:C21) -> 0 | D22: =SUM(D18:D21) -> 0 | E22: =SUM(E18:E21) -> 0 | F22: =SUM(F18:F21) -> 0
A24: Dettes du passif circulant :
A25: Fournisseurs et comptes rattachés
A26: Clients
A27: Personnel
A28: Sécurité sociale et organismes sociaux
A29: Etat
A30: Organismes internationaux
A31: Associés et groupe
A32: Créditeurs divers
A33: SOUS TOTAL (3) | C33: =SUM(C25:C32) -> 0 | D33: =SUM(D25:D32) -> 0 | E33: =SUM(E25:E32) -> 0 | F33: =SUM(F25:F32) -> 0
A34: TOTAL (1) + (2) + (3) | C34: =+C15+C22+C33 -> 0 | D34: =+D15+D22+D33 -> 0 | E34: =+E15+E22+E33 -> 0 | F34: =+F15+F22+F33 -> 0
A35: ENGAGEMENTS FINANCIERS | E35: Engagements donnés | F35: Engagements reçus
A36: Engagements consentis à des entités liées
A37: Primes de remboursement non échus
A38: Avals, cautions, garanties
A39: Hypothèques, nantissements, gages, autres
A40: Effets escomptés non échus
A41: Créances commerciales et professionnelles cédées
A42: Abandons de créances conditionnels
A43: TOTAL | E43: =SUM(E36:E42) -> 0 | F43: =SUM(F36:F42) -> 0
A44: Commentaire :
A45: Ligne de crédit spot auprès de citibank pour 45 000 000 USD

Sheet Note 2
A1: NOTE 2 : INFORMATIONS OBLIGATOIRES
A3: Désignation entité : | C3: Excercice clos le : | D3: =+'Note 1'!E3 -> 45657
A4: =+'Note 1'!A4 -> Sabodala Gold Operations S.A | C4: Durée en mois : | D4: =+'Note 1'!E4 -> 12
A5: Numéro d'identification : | B5: =+'Note 1'!B5 -> 002850023
A7: A - DECLARATION DE CONFORMITE AU SYSCOHADA
A8: Les états financiers sont établis en conformité avec le Système comptable OHADA et l'Acte uniforme relatif au droit comptable et à l'information financière.
A9: B - REGLES ET METHODES COMPTABLES
A10: L’entreprise tient sa comptabilité suivant les prescriptions du système comptable OHADA, adaptées à l’activité de Sabodala gold Operations S.A. (« SGO »). Le système normal est appliqué. La comptabilité est tenue de façon chronologique sur un système informatique permettant d’éditer le Grand-Livre, la Balance Générale. Les pièces comptables sont numérotées. Les principes de prudence, de transparence, d’importance significative, d’intangibilité du bilan, du coût historique, de la continuité d’exploitation, de la permanence des méthodes, ainsi que de la spécialisation des exercices sont respectés. La comptabilité est tenue en anglais et en US dollars, en raison de l’utilisation depuis le 1er octobre 2011 du système d’information intégré Pronto. Ce dernier est spécifique au secteur minier. Une balance et un Grand Livre en Francs CFA sont préparés. Les opérations en monnaies étrangères effectuées par SGO sont comptabilisées en appliquant le cours de change en vigueur à la date de l’opération. Lorsque le règlement survient durant l’exercice au cours duquel l’opération a été conclue, la différence de change entre le montant enregistré initialement et le montant effectif du règlement constitue un gain ou une perte entrant dans la formation du résultat de l’exercice. A la date de clôture, les éléments en monnaies étrangères (fournisseurs d’exploitation et d’investissement, clients, dépôts en devises, …) sont évalués en utilisant le cours de change du jour de la transaction. La perte de change latente en résultant est prise en compte dans la détermination du résultat de l’exercice par le biais des provisions pour Risques et Charges. Les gains de change latents ne sont pas enregistrés dans le compte de résultat.
A11: C - DEROGATION AUX POSTULATS ET CONVENTIONS COMPTABLES
A12: Respect de tous les postulats et conventions comptables sans aucune dérogation
A13: D - INFORMATIONS COMPLEMENTAIRES RELATIVES AU BILAN, AU COMPTE DE RESULTAT ET AU TABLEAU DES FLUX DE TRESORERIE
A14: • Distribution de dividendes Sur décision de l’Assemblée Générale réunit à la date du 27 juin 2024, approuvant la proposition du Conseil d’Administration, un montant de FCFA 65 milliards du bénéfice réalisé de l’exercice 2023 a été distribué en dividendes aux actionnaires. • Mise en service de la nouvelle usine de traitement du minerai réfractaire (STP/BIOX) En avril 2024, la société a lancé la production au sein de sa nouvelle usine dédiée au traitement du minerai réfractaire, dénommée STP (Sulfide Treatment Process), basée sur la technologie BIOX (bio-oxydation). Ce projet stratégique d'un cout d'environ 290 millions de Dollars US a été mis en œuvre dans le but d’améliorer significativement le taux de récupération des minerais réfractaires, qui représentaient une part importante des réserves de l’entreprise mais dont le traitement demeurait peu efficient avec l’ancienne usine CIL. La nouvelle unité vient ainsi compléter les capacités existantes et renforcer la performance globale de l’outil industriel. Dotée d’une capacité annuelle de traitement de 1 200 000 de tonnes, l’usine BIOX marque une étape clé dans l’optimisation de l’exploitation des ressources minières de la société.

Sheet Note 3A
A1: NOTE 3A : IMMOBILISATION BRUTE
A3: Désignation entité : | E3: Excercice clos le : | F3: ='Note 1'!E3 -> 45657
A4: Sabodala Gold Operations S.A | E4: Durée en mois : | F4: 12
A5: Numéro d'identification : | B5: 002850023
A7: SITUATIONS ET MOUVEMENTS | B7: Montant brut à l'ouverture de l'exercice | C7: Acquisitions Apports Créations | D7: Virements de poste à poste | E7: Suite à une réévaluation pratiquée au cours de l'exercice | F7: Cessions Scissions Hors service | G7: Virements de poste à poste | H7: Montant brut à la clôture de l'exercice
A10: IMMOBILISATIONS INCORPORELLES | B10: =SUM(B11:B14) -> 5.6873242e+11 | C10: =SUM(C11:C14) -> 3.3600447e+10 | D10: =SUM(D11:D14) -> 2.3353161e+10 | E10: =SUM(E11:E14) -> 0 | F10: =SUM(F11:F14) -> -5.3165345e+08 | G10: =SUM(G11:G14) -> -3.0278576e+10 | H10: =SUM(H11:H14) -> 5.948758e+11
A11: Frais de développement et de prospection | B11: 5.425858e+11 | C11: 1.6780475e+10 | D11: 1.1123262e+10 | G11: -1.2229899e+10 | H11: =SUM(B11:G11) -> 5.5825964e+11
A12: Brevets, licences, logiciels et droits similaires | B12: 2.167926e+09 | C12: 19611269 | H12: =SUM(B12:G12) -> 2.1875373e+09
A13: Fonds commercial et droit au bail
A14: Autres immobilisations incorporelles | B14: 2.397869e+10 | C14: 1.6800361e+10 | D14: 1.2229899e+10 | F14: -5.3165345e+08 | G14: -1.8048678e+10 | H14: =SUM(B14:G14) -> 3.4428619e+10
A15: IMMOBILISATIONS CORPORELLES | B15: =SUM(B16:B22) -> 4.4053869e+11 | C15: =SUM(C16:C22) -> 8.2585601e+10 | D15: =SUM(D16:D22) -> 7.419232e+10 | F15: =SUM(F16:F22) -> -2.8415843e+10 | G15: =SUM(G16:G22) -> -5.6965152e+10 | H15: =SUM(H16:H22) -> 5.1193562e+11
A16: Terrains hors immeuble de placement
A17: Terrains immeuble de placement
A18: Bâtiments hors immeuble de placement | B18: 3.6103518e+10 | C18: 1.1278017e+09 | D18: 7.8555735e+09 | H18: =SUM(B18:G18) -> 4.5086893e+10
A19: Bâtiments immeuble de placement
A20: Aménagements, agencements et installations | B20: 2.9679388e+11 | C20: 5.6574242e+10 | D20: 1.0301753e+10 | F20: -3.2665852e+09 | G20: -4.3246327e+10 | H20: =SUM(B20:G20) -> 3.1715697e+11
A21: Matériel, mobilier et actifs biologiques | B21: 9.8497144e+10 | C21: 1.074863e+10 | D21: 5.6034994e+10 | F21: -2.1948315e+10 | H21: =SUM(B21:G21) -> 1.4333245e+11
A22: Matériel de transport | B22: 9.1441464e+09 | C22: 1.4134928e+10 | F22: -3.2009435e+09 | G22: -1.3718825e+10 | H22: =SUM(B22:G22) -> 6.3593049e+09
A23: AVANCES ET ACOMPTES VERSES SUR IMMOBILISATIONS | B23: =SUM(B24:B25) -> 1.0301753e+10 | C23: =SUM(C24:C25) -> 290656582 | D23: =SUM(D24:D25) -> -1.0301753e+10 | E23: =SUM(E24:E25) -> 0 | F23: =SUM(F24:F25) -> 0 | G23: =SUM(G24:G25) -> 0 | H23: =SUM(H24:H25) -> 290656582
A24: Immobilisations incorporelles
A25: Immoblisations corporelles | B25: 1.0301753e+10 | C25: 290656582 | D25: -1.0301753e+10 | H25: =SUM(B25:G25) -> 290656582
A26: IMMOBILISATIONS FINANCIERES | B26: =SUM(B27:B28) -> 431226428 | C26: =SUM(C27:C28) -> 0 | D26: =SUM(D27:D28) -> 0 | E26: =SUM(E27:E28) -> 0 | F26: =SUM(F27:F28) -> -24000000 | G26: =SUM(G27:G28) -> 0 | H26: =SUM(H27:H28) -> 407226428
A27: Titres de placement
A28: Autres immobilisations financières | B28: 431226428 | F28: -24000000 | H28: =SUM(B28:G28) -> 407226428
A29: TOTAL GENERAL | B29: =B26+B23+B15+B10 -> 1.0200041e+12 | C29: =C26+C23+C15+C10 -> 1.1647671e+11 | D29: =D26+D23+D15+D10 -> 8.7243728e+10 | E29: =E26+E23+E15+E10 -> 0 | F29: =F26+F23+F15+F10 -> -2.8971497e+10 | G29: =G26+G23+G15+G10 -> -8.7243728e+10 | H29: =H26+H23+H15+H10 -> 1.1075093e+12
A30: Commentaire :
A31: Immobilisations incorporelles Les immobilisations incorporelles sont principalement constituées des frais de prospection et des coûts de recherche et développement liés à l’exploration minière. Elles sont évaluées au coût historique et amorties en fonction de l’estimation de la production attendue. Immobilisations corporelles Également évaluées au coût historique, les immobilisations corporelles comprennent plusieurs catégories d’actifs. La Société applique la méthode d’amortissement linéaire pour le mobilier de bureau, les véhicules et les équipements mobiles. Les autres immobilisations corporelles sont amorties sur la base de la production. Bâtiments : ils englobent principalement les bureaux administratifs et le village permanent destiné à l’hébergement du personnel. Installations et agencements : ils incluent essentiellement l’usine de traitement, y compris les travaux liés à son extension. Matériel : cette catégorie regroupe les installations et équipements techniques nécessaires aux opérations. Principales acquisitions de l'exercice : Coûts de décapage : +16 831 M FCFA, correspondant aux travaux dans les fosses de Massawa Nord, Kiesta (mise en exploitation en cours d'année), Massawa Centre, Bambaraya, Niakafiri, ainsi qu’une capitalisation marginale à Sabodala. Frais de recherche et développement : +16 780 M FCFA.Logiciels : +19,6 M FCFA.Autres immobilisations incorporelles : +16 800 M FCFA, correspondant à un reclassement de coûts d’exploration en cours vers la rubrique "Autres immobilisations en cours".Bâtiments : +8 983 M FCFA.Agencements, aménagements et installations : +20 363 M FCFA, comprenant : La poursuite et l’achèvement en avril 2024 (date de démarrage de la production) des travaux de construction et d’installation de la nouvelle usine BIOX (traitement de l’or réfractaire). Un montant initial de 43 425 M FCFA, précédemment enregistré dans la rubrique "Bâtiment", a été reclassé comme suit : infrastructures (+1 926 M FCFA), équipements (+39 816 M FCFA), mobiliers et autres matériels (+973 M FCFA). Le projet d'installation du système solaire est en cours : les nouvelles dépenses liées à sa mise en œuvre, ainsi que d'autres coûts rattachés à l'usine BIOX, s’élèvent à 27 689 M FCFA. Le montant de l’actif de démantèlement a été réévalué à la hausse pour un total de +949 M FCFA.Matériel, mobilier et actifs biologiques : +44 835 M FCFA. Matériel roulant : -2 785 M FCFA (sorties nettes). Les sorties d’immobilisations s’élèvent à 28 947 M FCFA en valeur brute. Le détail de ces mouvements figure dans la Note 3D des états financiers.

Sheet Note 3B
A1: NOTE 3B : BIENS PRIS EN LOCATION ACQUISITION
A3: Désignation entité : | G3: Excercice clos le : | H3: ='Note 1'!E3 -> 45657
A4: Sabodala Gold Operations S.A | G4: Durée en mois : | H4: 12
A5: Numéro d'identification : | B5: 002850023
A7: SITUATIONS ET MOUVEMENTS | B7: NATURE DU CONTRAT (I; M; A) | C7: A | D7: AUGMENTATIONS B | G7: DIMINUTIONS C | I7: D = A +B - C
C8: Montant brut à l'ouverture de l'exercice | D8: Acquisitions Apports Créations | E8: Virements de poste à poste | F8: Suite à une réévaluation pratiquée au cours de l'exercice | G8: Cessions Scissions Hors service | H8: Virements de poste à poste | I8: Montant brut à l'ouverture de l'exercice
B9: [1]
A10: Brevets, licences, logiciels et droits similaires
A11: Fonds commercial et droit au bail
A12: Autres immobilisations incorporelles
A13: SOUS TOTAL : IMMOBILISATIONS INCORPORELLES
A14: Terrains
A15: Bâtiments
A16: Aménagements, agencements et installations
A17: Matériel, mobilier et actifs biologiques | B17: M | C17: 1.7291333e+10 | G17: -8.077149e+09 | I17: 9.2141843e+09
A18: Matériel de transport
A19: SOUS TOTAL : IMMOBILISATIONS CORPORELLES | C19: 1.7291333e+10 | G19: -8.077149e+09 | I19: 9.2141843e+09
A21: TOTAL GENERAL | C21: 1.7291333e+10 | G21: -8.077149e+09 | I21: 9.2141843e+09
A22: [1] I : crédit-bail immobilier; M : crédit-bail mobilier; A : autres contrats (dédoubler le poste si montants significatifs)
A23: Commentaire :
A24: Contrat de location financement avec option d’achat signé en Novembre 2008 entre SGMC, Société Générale Branche de Londres et SGO pour l’utilisation de biens d’équipements industriels sur le site de Sabodala.

Sheet Note 3C
A1: NOTE 3C : IMMOBILISATIONS (AMORTISSEMENTS)
A3: Désignation entité : | D3: Excercice clos le : | E3: ='Note 1'!E3 -> 45657
A4: Sabodala Gold Operations S.A | D4: Durée en mois : | E4: 12
A5: Numéro d'identification : | B5: 002850023
A7: SITUATIONS ET MOUVEMENTS | B7: A | C7: B | D7: C | E7: D = A +B - C
B8: Amortissements cumulés à l'ouverture de l'exercice | C8: Augmentations : Dotations de l'exercice | D8: Diminutions : Amortissements relatifs aux éléments sortis de l'actif | E8: Cumul des amortissements à la clôture de l'exercice
A10: Frais de développement et de prospection | B10: 2.8546932e+11 | C10: 5.8446828e+10 | E10: 3.4391615e+11
A11: Brevets, licences, logiciels et droits similaires | B11: 1.9891031e+09 | C11: 50777693 | E11: 2.0398808e+09
A12: Fonds commercial et droit au bail
A13: Autres immobilisations incorporelles
A14: SOUS TOTAL : IMMOBILISATIONS INCORPORELLES | B14: 2.8745843e+11 | C14: 5.8497605e+10 | D14: 0 | E14: 3.4595603e+11
A15: Terrains hors immeuble de placement
A16: Terrains immeuble de placement
A17: Bâtiments hors immeuble de placement | B17: 2.214938e+10 | C17: 3.6638455e+09 | E17: 2.5813226e+10
A18: Bâtiments immeuble de placement
A19: Aménagements, agencements et installations | B19: 1.1083038e+11 | C19: 1.6521435e+10 | D19: -3.0213288e+09 | E19: 1.2433049e+11
A20: Matériel, mobilier et actifs biologiques | B20: 6.3022296e+10 | C20: 1.4038748e+10 | D20: -2.1906935e+10 | E20: 5.5154109e+10
A21: Matériel de transport | B21: 7.7803566e+09 | C21: 7.3305659e+08 | D21: -3.1382186e+09 | E21: 5.3751946e+09
A22: SOUS TOTAL : IMMOBILISATIONS CORPORELLES | B22: 2.0378241e+11 | C22: 3.4957085e+10 | D22: -2.8066483e+10 | E22: 2.1067302e+11
A24: TOTAL GENERAL | B24: 4.9124084e+11 | C24: 9.3454691e+10 | D24: -2.8066483e+10 | E24: 5.5662905e+11
A25: Commentaire :
A26: Les immobilisations incorporelles de SGO sont constituées principalement des frais de prospection minière et des coûts de Recherche et Développement dans le cadre de l’exploration minière. Elles sont évaluées au coût historique et font l’objet d’un amortissement en fonction de l’estimation de la production. Les immobilisations corporelles sont également évaluées au coût historique. La Société utilise la méthode de l’amortissement linéaire pour le mobilier de bureau, les véhicules et les équipements mobiles. Les autres immobilisations corporelles sont amorties en fonction de l’estimation de la production.
A27: Les taux d'amortissement pratiqués sont les suivants : Installations et aménagements : 3 à 5 ans Matériel et outillage : 4 ans Matériel de transport : 3 à 5 ans Mobilier, matériel de bureau : 3 à 5 ans Il y a eu une hausse des dotations de l'exercice en relation avec l'entrée en production de Niakafiri Est - kiesta - BIOX. Les amortissements des couts de décapage s'élévent à 29 224 M FCFA dont 28 737 relatifs au Pit de Sabodala dont les reserves sont presques épuisées, 125 M FCFA à celui de BAMBARAYA et Kiesta pour 362 M FCFA

Sheet Note 3D
A1: NOTE 3D : IMMOBILISATIONS (PLUS-VALUES ET MOINS VALUES DE CESSION)
A3: Désignation entité : | D3: Excercice clos le : | E3: ='Note 1'!E3 -> 45657
A4: Sabodala Gold Operations S.A | D4: Durée en mois : | E4: 12
A5: Numéro d'identification : | B5: 002850023
B7: MONTANT BRUT | C7: AMORTISSEMENTS | D7: VALEUR COMPTABLE NETTE | E7: PRIX DE CESSION | F7: PLUS VALUE OU MOINS VALUE
C8: PRATIQUES
B9: A | C9: B | D9: C = A - B | E9: D | F9: E = D - C
A10: Frais de développement et de prospection
A11: Brevets, licences, logiciels et droits similaires
A12: Fonds commercial et droit au bail
A13: Autres immobilisations incorporelles | B13: 5.3165345e+08 | D13: 5.3165345e+08 | F13: -5.3165345e+08
A14: SOUS TOTAL : IMMOBILISATIONS INCORPORELLES | B14: 5.3165345e+08 | D14: 5.3165345e+08 | F14: -5.3165345e+08
A15: Terrains
A16: Bâtiments
A17: Aménagements, agencements et installations | B17: 3.2665852e+09 | C17: -3.0213288e+09 | D17: 2.4525646e+08 | F17: -2.4525646e+08
A18: Matériel, mobilier et actifs biologiques | B18: 2.1948315e+10 | C18: -2.1906935e+10 | D18: 41379351 | F18: -41379351
A19: Matériel de transport | B19: 3.2009435e+09 | C19: -3.1382186e+09 | D19: 62724901 | F19: -62724901
A20: SOUS TOTAL : IMMOBILISATIONS CORPORELLES | B20: 2.8415843e+10 | C20: -2.8066483e+10 | D20: 3.4936071e+08 | F20: -3.4936071e+08
A21: Titres de participation
A22: Autres immobilisations financières
A23: SOUS TOTAL : IMMOBILISATIONS FINANCIERES
A25: TOTAL GENERAL | B25: 2.8947497e+10 | C25: -2.8066483e+10 | D25: 8.8101416e+08 | F25: -8.8101416e+08
A26: Commentaire :
A27: La sortie d'actif pour un montant XOF de 349M correspond a des installations pour 3 266 M, des materiels et mobiliers actifs pour 21 948M et des materiels de transport pour 3 220M en valeurs brutes.
A28: La sortie de 531M correspond à des Couts d'exploration (en cours) dont les zones d'interventions sont abandonnées 410M FCFA (Mining Lease ) et 121M FCFA Soukhoto East

Sheet Note 3E
A1: NOTE 3E : INFORMATIONS SUR LES REEVALUATIONS EFFECTUEES PAR L'ENTITE
A3: Désignation entité : | C3: Excercice clos le : | D3: =+'Note 1'!E3 -> 45657
A4: =+'Note 1'!A4 -> Sabodala Gold Operations S.A | C4: Durée en mois : | D4: =+'Note 1'!E4 -> 12
A5: Numéro d'identification : | B5: =+'Note 1'!B5 -> 002850023
A7: Nature et date des réévaluations :
A13: Eléments réévalués par postes du bilan | B13: Montants coûts historiques | C13: Amortissements supplémentaires
A22: Méthode de réévaluation utilisée :
A24: Traitement fiscal de l'écart de réévaluation
A25: et des amortissements supplémentaires :
A27: Montant de l'écart incorporé au capital :

Sheet Note 4
A1: NOTE 4 : IMMOBILISATIONS FINANCIERES
A3: Désignation entité : | E3: Excercice clos le : | F3: =+'Note 1'!E3 -> 45657
E4: Durée en mois : | F4: =+'Note 1'!E4 -> 12
A5: Numéro d'identification : | B5: =+'Note 1'!B5 -> 002850023
A7: SITUATIONS ET MOUVEMENTS | B7: ANNEE N | C7: ANNEE N-1 | D7: Variation en % | E7: Créances à un an au plus | F7: Créances à plus d'un an et à deux ans au plus | G7: Créances à plus de deux ans
A9: Titres de participation
A10: Prêts et créances
A11: Prêt au personnel
A12: Créances sur l'Etat
A13: Titres immobilisés
A14: Dépôts et cautionnements | B14: 407226428 | C14: 431226428 | D14: =(B14-C14)/C14 -> -0.055655216 | G14: 407226428
A15: Intérêts courus
A16: TOTAL BRUT | B16: 407226428 | C16: 431226428 | D16: -0.055655216 | G16: 407226428
A17: Dépréciations titres de participation
A18: Dépréciations autres immobilisations
A19: TOTAL NET DE DEPRECIATION
A21: Liste des filiales et participations :
A23: Dénomination sociale | B23: Localisation (ville/pays) | C23: Valeur d'acquisition | E23: % détenu | F23: Montant des capitaux propres filiale | G23: Résultat dernier exercice filiale
A32: Commentaire :
A33: Provision pour réhabilitation des sites miniers versée auprès de la Caisse de Dépots et Consignations (CDC) pour un montant XOF 326 millions. Dépôts et cautionnement auprès des fournisseurs pour un montant XOF de 81 millions.

Sheet Note 5
A1: NOTE 5 : ACTIF CIRCULANT HAO
A3: Désignation entité : | E3: Excercice clos le : | F3: =+'Note 1'!E3 -> 45657
E4: Durée en mois : | F4: =+'Note 1'!E4 -> 12
A5: Numéro d'identification : | B5: =+'Note 1'!B5 -> 002850023
A6: ACTIF CIRCULANT HAO | P6: ACTIF CIRCULANT HAO | X6: ACTIF CIRCULANT HAO | AF6: ACTIF CIRCULANT HAO | AN6: ACTIF CIRCULANT HAO | AV6: ACTIF CIRCULANT HAO | BD6: ACTIF CIRCULANT HAO | BL6: ACTIF CIRCULANT HAO | BT6: ACTIF CIRCULANT HAO | CB6: ACTIF CIRCULANT HAO | CJ6: ACTIF CIRCULANT HAO | CR6: ACTIF CIRCULANT HAO | CZ6: ACTIF CIRCULANT HAO | DH6: ACTIF CIRCULANT HAO | DP6: ACTIF CIRCULANT HAO | DX6: ACTIF CIRCULANT HAO | EF6: ACTIF CIRCULANT HAO | EN6: ACTIF CIRCULANT HAO | EV6: ACTIF CIRCULANT HAO | FD6: ACTIF CIRCULANT HAO | FL6: ACTIF CIRCULANT HAO | FT6: ACTIF CIRCULANT HAO | GB6: ACTIF CIRCULANT HAO | GJ6: ACTIF CIRCULANT HAO | GR6: ACTIF CIRCULANT HAO | GZ6: ACTIF CIRCULANT HAO | HH6: ACTIF CIRCULANT HAO | HP6: ACTIF CIRCULANT HAO | HX6: ACTIF CIRCULANT HAO | IF6: ACTIF CIRCULANT HAO | IN6: ACTIF CIRCULANT HAO | IV6: ACTIF CIRCULANT HAO | JD6: ACTIF CIRCULANT HAO | JL6: ACTIF CIRCULANT HAO | JT6: ACTIF CIRCULANT HAO | KB6: ACTIF CIRCULANT HAO | KJ6: ACTIF CIRCULANT HAO | KR6: ACTIF CIRCULANT HAO | KZ6: ACTIF CIRCULANT HAO | LH6: ACTIF CIRCULANT HAO | LP6: ACTIF CIRCULANT HAO | LX6: ACTIF CIRCULANT HAO | MF6: ACTIF CIRCULANT HAO | MN6: ACTIF CIRCULANT HAO | MV6: ACTIF CIRCULANT HAO | ND6: ACTIF CIRCULANT HAO | NL6: ACTIF CIRCULANT HAO | NT6: ACTIF CIRCULANT HAO | OB6: ACTIF CIRCULANT HAO | OJ6: ACTIF CIRCULANT HAO | OR6: ACTIF CIRCULANT HAO | OZ6: ACTIF CIRCULANT HAO | PH6: ACTIF CIRCULANT HAO | PP6: ACTIF CIRCULANT HAO | PX6: ACTIF CIRCULANT HAO | QF6: ACTIF CIRCULANT HAO | QN6: ACTIF CIRCULANT HAO | QV6: ACTIF CIRCULANT HAO | RD6: ACTIF CIRCULANT HAO | RL6: ACTIF CIRCULANT HAO | RT6: ACTIF CIRCULANT HAO | SB6: ACTIF CIRCULANT HAO | SJ6: ACTIF CIRCULANT HAO | SR6: ACTIF CIRCULANT HAO | SZ6: ACTIF CIRCULANT HAO | TH6: ACTIF CIRCULANT HAO | TP6: ACTIF CIRCULANT HAO | TX6: ACTIF CIRCULANT HAO | UF6: ACTIF CIRCULANT HAO | UN6: ACTIF CIRCULANT HAO | UV6: ACTIF CIRCULANT HAO | VD6: ACTIF CIRCULANT HAO | VL6: ACTIF CIRCULANT HAO | VT6: ACTIF CIRCULANT HAO | WB6: ACTIF CIRCULANT HAO | WJ6: ACTIF CIRCULANT HAO | WR6: ACTIF CIRCULANT HAO | WZ6: ACTIF CIRCULANT HAO | XH6: ACTIF CIRCULANT HAO | XP6: ACTIF CIRCULANT HAO | XX6: ACTIF CIRCULANT HAO | YF6: ACTIF CIRCULANT HAO | YN6: ACTIF CIRCULANT HAO | YV6: ACTIF CIRCULANT HAO | ZD6: ACTIF CIRCULANT HAO | ZL6: ACTIF CIRCULANT HAO | ZT6: ACTIF CIRCULANT HAO | AAB6: ACTIF CIRCULANT HAO | AAJ6: ACTIF CIRCULANT HAO | AAR6: ACTIF CIRCULANT HAO | AAZ6: ACTIF CIRCULANT HAO | ABH6: ACTIF CIRCULANT HAO | ABP6: ACTIF CIRCULANT HAO | ABX6: ACTIF CIRCULANT HAO | ACF6: ACTIF CIRCULANT HAO | ACN6: ACTIF CIRCULANT HAO | ACV6: ACTIF CIRCULANT HAO | ADD6: ACTIF CIRCULANT HAO | ADL6: ACTIF CIRCULANT HAO | ADT6: ACTIF CIRCULANT HAO | AEB6: ACTIF CIRCULANT HAO | AEJ6: ACTIF CIRCULANT HAO | AER6: ACTIF CIRCULANT HAO | AEZ6: ACTIF CIRCULANT HAO | AFH6: ACTIF CIRCULANT HAO | AFP6: ACTIF CIRCULANT HAO | AFX6: ACTIF CIRCULANT HAO | AGF6: ACTIF CIRCULANT HAO | AGN6: ACTIF CIRCULANT HAO | AGV6: ACTIF CIRCULANT HAO | AHD6: ACTIF CIRCULANT HAO | AHL6: ACTIF CIRCULANT HAO | AHT6: ACTIF CIRCULANT HAO | AIB6: ACTIF CIRCULANT HAO | AIJ6: ACTIF CIRCULANT HAO | AIR6: ACTIF CIRCULANT HAO | AIZ6: ACTIF CIRCULANT HAO | AJH6: ACTIF CIRCULANT HAO | AJP6: ACTIF CIRCULANT HAO | AJX6: ACTIF CIRCULANT HAO | AKF6: ACTIF CIRCULANT HAO | AKN6: ACTIF CIRCULANT HAO | AKV6: ACTIF CIRCULANT HAO | ALD6: ACTIF CIRCULANT HAO | ALL6: ACTIF CIRCULANT HAO | ALT6: ACTIF CIRCULANT HAO | AMB6: ACTIF CIRCULANT HAO | AMJ6: ACTIF CIRCULANT HAO | AMR6: ACTIF CIRCULANT HAO | AMZ6: ACTIF CIRCULANT HAO | ANH6: ACTIF CIRCULANT HAO | ANP6: ACTIF CIRCULANT HAO | ANX6: ACTIF CIRCULANT HAO | AOF6: ACTIF CIRCULANT HAO | AON6: ACTIF CIRCULANT HAO | AOV6: ACTIF CIRCULANT HAO | APD6: ACTIF CIRCULANT HAO | APL6: ACTIF CIRCULANT HAO | APT6: ACTIF CIRCULANT HAO | AQB6: ACTIF CIRCULANT HAO | AQJ6: ACTIF CIRCULANT HAO | AQR6: ACTIF CIRCULANT HAO | AQZ6: ACTIF CIRCULANT HAO | ARH6: ACTIF CIRCULANT HAO | ARP6: ACTIF CIRCULANT HAO | ARX6: ACTIF CIRCULANT HAO | ASF6: ACTIF CIRCULANT HAO | ASN6: ACTIF CIRCULANT HAO | ASV6: ACTIF CIRCULANT HAO | ATD6: ACTIF CIRCULANT HAO | ATL6: ACTIF CIRCULANT HAO | ATT6: ACTIF CIRCULANT HAO | AUB6: ACTIF CIRCULANT HAO | AUJ6: ACTIF CIRCULANT HAO | AUR6: ACTIF CIRCULANT HAO | AUZ6: ACTIF CIRCULANT HAO | AVH6: ACTIF CIRCULANT HAO | AVP6: ACTIF CIRCULANT HAO | AVX6: ACTIF CIRCULANT HAO | AWF6: ACTIF CIRCULANT HAO | AWN6: ACTIF CIRCULANT HAO | AWV6: ACTIF CIRCULANT HAO | AXD6: ACTIF CIRCULANT HAO | AXL6: ACTIF CIRCULANT HAO | AXT6: ACTIF CIRCULANT HAO | AYB6: ACTIF CIRCULANT HAO | AYJ6: ACTIF CIRCULANT HAO | AYR6: ACTIF CIRCULANT HAO | AYZ6: ACTIF CIRCULANT HAO | AZH6: ACTIF CIRCULANT HAO | AZP6: ACTIF CIRCULANT HAO | AZX6: ACTIF CIRCULANT HAO | BAF6: ACTIF CIRCULANT HAO | BAN6: ACTIF CIRCULANT HAO | BAV6: ACTIF CIRCULANT HAO | BBD6: ACTIF CIRCULANT HAO | BBL6: ACTIF CIRCULANT HAO | BBT6: ACTIF CIRCULANT HAO | BCB6: ACTIF CIRCULANT HAO | BCJ6: ACTIF CIRCULANT HAO | BCR6: ACTIF CIRCULANT HAO | BCZ6: ACTIF CIRCULANT HAO | BDH6: ACTIF CIRCULANT HAO | BDP6: ACTIF CIRCULANT HAO | BDX6: ACTIF CIRCULANT HAO | BEF6: ACTIF CIRCULANT HAO | BEN6: ACTIF CIRCULANT HAO | BEV6: ACTIF CIRCULANT HAO | BFD6: ACTIF CIRCULANT HAO | BFL6: ACTIF CIRCULANT HAO | BFT6: ACTIF CIRCULANT HAO | BGB6: ACTIF CIRCULANT HAO | BGJ6: ACTIF CIRCULANT HAO | BGR6: ACTIF CIRCULANT HAO | BGZ6: ACTIF CIRCULANT HAO | BHH6: ACTIF CIRCULANT HAO | BHP6: ACTIF CIRCULANT HAO | BHX6: ACTIF CIRCULANT HAO | BIF6: ACTIF CIRCULANT HAO | BIN6: ACTIF CIRCULANT HAO | BIV6: ACTIF CIRCULANT HAO | BJD6: ACTIF CIRCULANT HAO | BJL6: ACTIF CIRCULANT HAO | BJT6: ACTIF CIRCULANT HAO | BKB6: ACTIF CIRCULANT HAO | BKJ6: ACTIF CIRCULANT HAO | BKR6: ACTIF CIRCULANT HAO | BKZ6: ACTIF CIRCULANT HAO | BLH6: ACTIF CIRCULANT HAO | BLP6: ACTIF CIRCULANT HAO | BLX6: ACTIF CIRCULANT HAO | BMF6: ACTIF CIRCULANT HAO | BMN6: ACTIF CIRCULANT HAO | BMV6: ACTIF CIRCULANT HAO | BND6: ACTIF CIRCULANT HAO | BNL6: ACTIF CIRCULANT HAO | BNT6: ACTIF CIRCULANT HAO | BOB6: ACTIF CIRCULANT HAO | BOJ6: ACTIF CIRCULANT HAO | BOR6: ACTIF CIRCULANT HAO | BOZ6: ACTIF CIRCULANT HAO | BPH6: ACTIF CIRCULANT HAO | BPP6: ACTIF CIRCULANT HAO | BPX6: ACTIF CIRCULANT HAO | BQF6: ACTIF CIRCULANT HAO | BQN6: ACTIF CIRCULANT HAO | BQV6: ACTIF CIRCULANT HAO | BRD6: ACTIF CIRCULANT HAO | BRL6: ACTIF CIRCULANT HAO | BRT6: ACTIF CIRCULANT HAO | BSB6: ACTIF CIRCULANT HAO | BSJ6: ACTIF CIRCULANT HAO | BSR6: ACTIF CIRCULANT HAO | BSZ6: ACTIF CIRCULANT HAO | BTH6: ACTIF CIRCULANT HAO | BTP6: ACTIF CIRCULANT HAO | BTX6: ACTIF CIRCULANT HAO | BUF6: ACTIF CIRCULANT HAO | BUN6: ACTIF CIRCULANT HAO | BUV6: ACTIF CIRCULANT HAO | BVD6: ACTIF CIRCULANT HAO | BVL6: ACTIF CIRCULANT HAO | BVT6: ACTIF CIRCULANT HAO | BWB6: ACTIF CIRCULANT HAO | BWJ6: ACTIF CIRCULANT HAO | BWR6: ACTIF CIRCULANT HAO | BWZ6: ACTIF CIRCULANT HAO | BXH6: ACTIF CIRCULANT HAO | BXP6: ACTIF CIRCULANT HAO | BXX6: ACTIF CIRCULANT HAO | BYF6: ACTIF CIRCULANT HAO | BYN6: ACTIF CIRCULANT HAO | BYV6: ACTIF CIRCULANT HAO | BZD6: ACTIF CIRCULANT HAO | BZL6: ACTIF CIRCULANT HAO | BZT6: ACTIF CIRCULANT HAO | CAB6: ACTIF CIRCULANT HAO | CAJ6: ACTIF CIRCULANT HAO | CAR6: ACTIF CIRCULANT HAO | CAZ6: ACTIF CIRCULANT HAO | CBH6: ACTIF CIRCULANT HAO | CBP6: ACTIF CIRCULANT HAO | CBX6: ACTIF CIRCULANT HAO | CCF6: ACTIF CIRCULANT HAO | CCN6: ACTIF CIRCULANT HAO | CCV6: ACTIF CIRCULANT HAO | CDD6: ACTIF CIRCULANT HAO | CDL6: ACTIF CIRCULANT HAO | CDT6: ACTIF CIRCULANT HAO | CEB6: ACTIF CIRCULANT HAO | CEJ6: ACTIF CIRCULANT HAO | CER6: ACTIF CIRCULANT HAO | CEZ6: ACTIF CIRCULANT HAO | CFH6: ACTIF CIRCULANT HAO | CFP6: ACTIF CIRCULANT HAO | CFX6: ACTIF CIRCULANT HAO | CGF6: ACTIF CIRCULANT HAO | CGN6: ACTIF CIRCULANT HAO | CGV6: ACTIF CIRCULANT HAO | CHD6: ACTIF CIRCULANT HAO | CHL6: ACTIF CIRCULANT HAO | CHT6: ACTIF CIRCULANT HAO | CIB6: ACTIF CIRCULANT HAO | CIJ6: ACTIF CIRCULANT HAO | CIR6: ACTIF CIRCULANT HAO | CIZ6: ACTIF CIRCULANT HAO | CJH6: ACTIF CIRCULANT HAO | CJP6: ACTIF CIRCULANT HAO | CJX6: ACTIF CIRCULANT HAO | CKF6: ACTIF CIRCULANT HAO | CKN6: ACTIF CIRCULANT HAO | CKV6: ACTIF CIRCULANT HAO | CLD6: ACTIF CIRCULANT HAO | CLL6: ACTIF CIRCULANT HAO | CLT6: ACTIF CIRCULANT HAO | CMB6: ACTIF CIRCULANT HAO | CMJ6: ACTIF CIRCULANT HAO | CMR6: ACTIF CIRCULANT HAO | CMZ6: ACTIF CIRCULANT HAO | CNH6: ACTIF CIRCULANT HAO | CNP6: ACTIF CIRCULANT HAO | CNX6: ACTIF CIRCULANT HAO | COF6: ACTIF CIRCULANT HAO | CON6: ACTIF CIRCULANT HAO | COV6: ACTIF CIRCULANT HAO | CPD6: ACTIF CIRCULANT HAO | CPL6: ACTIF CIRCULANT HAO | CPT6: ACTIF CIRCULANT HAO | CQB6: ACTIF CIRCULANT HAO | CQJ6: ACTIF CIRCULANT HAO | CQR6: ACTIF CIRCULANT HAO | CQZ6: ACTIF CIRCULANT HAO | CRH6: ACTIF CIRCULANT HAO | CRP6: ACTIF CIRCULANT HAO | CRX6: ACTIF CIRCULANT HAO | CSF6: ACTIF CIRCULANT HAO | CSN6: ACTIF CIRCULANT HAO | CSV6: ACTIF CIRCULANT HAO | CTD6: ACTIF CIRCULANT HAO | CTL6: ACTIF CIRCULANT HAO | CTT6: ACTIF CIRCULANT HAO | CUB6: ACTIF CIRCULANT HAO | CUJ6: ACTIF CIRCULANT HAO | CUR6: ACTIF CIRCULANT HAO | CUZ6: ACTIF CIRCULANT HAO | CVH6: ACTIF CIRCULANT HAO | CVP6: ACTIF CIRCULANT HAO | CVX6: ACTIF CIRCULANT HAO | CWF6: ACTIF CIRCULANT HAO | CWN6: ACTIF CIRCULANT HAO | CWV6: ACTIF CIRCULANT HAO | CXD6: ACTIF CIRCULANT HAO | CXL6: ACTIF CIRCULANT HAO | CXT6: ACTIF CIRCULANT HAO | CYB6: ACTIF CIRCULANT HAO | CYJ6: ACTIF CIRCULANT HAO | CYR6: ACTIF CIRCULANT HAO | CYZ6: ACTIF CIRCULANT HAO | CZH6: ACTIF CIRCULANT HAO | CZP6: ACTIF CIRCULANT HAO | CZX6: ACTIF CIRCULANT HAO | DAF6: ACTIF CIRCULANT HAO | DAN6: ACTIF CIRCULANT HAO | DAV6: ACTIF CIRCULANT HAO | DBD6: ACTIF CIRCULANT HAO | DBL6: ACTIF CIRCULANT HAO | DBT6: ACTIF CIRCULANT HAO | DCB6: ACTIF CIRCULANT HAO | DCJ6: ACTIF CIRCULANT HAO | DCR6: ACTIF CIRCULANT HAO | DCZ6: ACTIF CIRCULANT HAO | DDH6: ACTIF CIRCULANT HAO | DDP6: ACTIF CIRCULANT HAO | DDX6: ACTIF CIRCULANT HAO | DEF6: ACTIF CIRCULANT HAO | DEN6: ACTIF CIRCULANT HAO | DEV6: ACTIF CIRCULANT HAO | DFD6: ACTIF CIRCULANT HAO | DFL6: ACTIF CIRCULANT HAO | DFT6: ACTIF CIRCULANT HAO | DGB6: ACTIF CIRCULANT HAO | DGJ6: ACTIF CIRCULANT HAO | DGR6: ACTIF CIRCULANT HAO | DGZ6: ACTIF CIRCULANT HAO | DHH6: ACTIF CIRCULANT HAO | DHP6: ACTIF CIRCULANT HAO | DHX6: ACTIF CIRCULANT HAO | DIF6: ACTIF CIRCULANT HAO | DIN6: ACTIF CIRCULANT HAO | DIV6: ACTIF CIRCULANT HAO | DJD6: ACTIF CIRCULANT HAO | DJL6: ACTIF CIRCULANT HAO | DJT6: ACTIF CIRCULANT HAO | DKB6: ACTIF CIRCULANT HAO | DKJ6: ACTIF CIRCULANT HAO | DKR6: ACTIF CIRCULANT HAO | DKZ6: ACTIF CIRCULANT HAO | DLH6: ACTIF CIRCULANT HAO | DLP6: ACTIF CIRCULANT HAO | DLX6: ACTIF CIRCULANT HAO | DMF6: ACTIF CIRCULANT HAO | DMN6: ACTIF CIRCULANT HAO | DMV6: ACTIF CIRCULANT HAO | DND6: ACTIF CIRCULANT HAO | DNL6: ACTIF CIRCULANT HAO | DNT6: ACTIF CIRCULANT HAO | DOB6: ACTIF CIRCULANT HAO | DOJ6: ACTIF CIRCULANT HAO | DOR6: ACTIF CIRCULANT HAO | DOZ6: ACTIF CIRCULANT HAO | DPH6: ACTIF CIRCULANT HAO | DPP6: ACTIF CIRCULANT HAO | DPX6: ACTIF CIRCULANT HAO | DQF6: ACTIF CIRCULANT HAO | DQN6: ACTIF CIRCULANT HAO | DQV6: ACTIF CIRCULANT HAO | DRD6: ACTIF CIRCULANT HAO | DRL6: ACTIF CIRCULANT HAO | DRT6: ACTIF CIRCULANT HAO | DSB6: ACTIF CIRCULANT HAO | DSJ6: ACTIF CIRCULANT HAO | DSR6: ACTIF CIRCULANT HAO | DSZ6: ACTIF CIRCULANT HAO | DTH6: ACTIF CIRCULANT HAO | DTP6: ACTIF CIRCULANT HAO | DTX6: ACTIF CIRCULANT HAO | DUF6: ACTIF CIRCULANT HAO | DUN6: ACTIF CIRCULANT HAO | DUV6: ACTIF CIRCULANT HAO | DVD6: ACTIF CIRCULANT HAO | DVL6: ACTIF CIRCULANT HAO | DVT6: ACTIF CIRCULANT HAO | DWB6: ACTIF CIRCULANT HAO | DWJ6: ACTIF CIRCULANT HAO | DWR6: ACTIF CIRCULANT HAO | DWZ6: ACTIF CIRCULANT HAO | DXH6: ACTIF CIRCULANT HAO | DXP6: ACTIF CIRCULANT HAO | DXX6: ACTIF CIRCULANT HAO | DYF6: ACTIF CIRCULANT HAO | DYN6: ACTIF CIRCULANT HAO | DYV6: ACTIF CIRCULANT HAO | DZD6: ACTIF CIRCULANT HAO | DZL6: ACTIF CIRCULANT HAO | DZT6: ACTIF CIRCULANT HAO | EAB6: ACTIF CIRCULANT HAO | EAJ6: ACTIF CIRCULANT HAO | EAR6: ACTIF CIRCULANT HAO | EAZ6: ACTIF CIRCULANT HAO | EBH6: ACTIF CIRCULANT HAO | EBP6: ACTIF CIRCULANT HAO | EBX6: ACTIF CIRCULANT HAO | ECF6: ACTIF CIRCULANT HAO | ECN6: ACTIF CIRCULANT HAO | ECV6: ACTIF CIRCULANT HAO | EDD6: ACTIF CIRCULANT HAO | EDL6: ACTIF CIRCULANT HAO | EDT6: ACTIF CIRCULANT HAO | EEB6: ACTIF CIRCULANT HAO | EEJ6: ACTIF CIRCULANT HAO | EER6: ACTIF CIRCULANT HAO | EEZ6: ACTIF CIRCULANT HAO | EFH6: ACTIF CIRCULANT HAO | EFP6: ACTIF CIRCULANT HAO | EFX6: ACTIF CIRCULANT HAO | EGF6: ACTIF CIRCULANT HAO | EGN6: ACTIF CIRCULANT HAO | EGV6: ACTIF CIRCULANT HAO | EHD6: ACTIF CIRCULANT HAO | EHL6: ACTIF CIRCULANT HAO | EHT6: ACTIF CIRCULANT HAO | EIB6: ACTIF CIRCULANT HAO | EIJ6: ACTIF CIRCULANT HAO | EIR6: ACTIF CIRCULANT HAO | EIZ6: ACTIF CIRCULANT HAO | EJH6: ACTIF CIRCULANT HAO | EJP6: ACTIF CIRCULANT HAO | EJX6: ACTIF CIRCULANT HAO | EKF6: ACTIF CIRCULANT HAO | EKN6: ACTIF CIRCULANT HAO | EKV6: ACTIF CIRCULANT HAO | ELD6: ACTIF CIRCULANT HAO | ELL6: ACTIF CIRCULANT HAO | ELT6: ACTIF CIRCULANT HAO | EMB6: ACTIF CIRCULANT HAO | EMJ6: ACTIF CIRCULANT HAO | EMR6: ACTIF CIRCULANT HAO | EMZ6: ACTIF CIRCULANT HAO | ENH6: ACTIF CIRCULANT HAO | ENP6: ACTIF CIRCULANT HAO | ENX6: ACTIF CIRCULANT HAO | EOF6: ACTIF CIRCULANT HAO | EON6: ACTIF CIRCULANT HAO | EOV6: ACTIF CIRCULANT HAO | EPD6: ACTIF CIRCULANT HAO | EPL6: ACTIF CIRCULANT HAO | EPT6: ACTIF CIRCULANT HAO | EQB6: ACTIF CIRCULANT HAO | EQJ6: ACTIF CIRCULANT HAO | EQR6: ACTIF CIRCULANT HAO | EQZ6: ACTIF CIRCULANT HAO | ERH6: ACTIF CIRCULANT HAO | ERP6: ACTIF CIRCULANT HAO | ERX6: ACTIF CIRCULANT HAO | ESF6: ACTIF CIRCULANT HAO | ESN6: ACTIF CIRCULANT HAO | ESV6: ACTIF CIRCULANT HAO | ETD6: ACTIF CIRCULANT HAO | ETL6: ACTIF CIRCULANT HAO | ETT6: ACTIF CIRCULANT HAO | EUB6: ACTIF CIRCULANT HAO | EUJ6: ACTIF CIRCULANT HAO | EUR6: ACTIF CIRCULANT HAO | EUZ6: ACTIF CIRCULANT HAO | EVH6: ACTIF CIRCULANT HAO | EVP6: ACTIF CIRCULANT HAO | EVX6: ACTIF CIRCULANT HAO | EWF6: ACTIF CIRCULANT HAO | EWN6: ACTIF CIRCULANT HAO | EWV6: ACTIF CIRCULANT HAO | EXD6: ACTIF CIRCULANT HAO | EXL6: ACTIF CIRCULANT HAO | EXT6: ACTIF CIRCULANT HAO | EYB6: ACTIF CIRCULANT HAO | EYJ6: ACTIF CIRCULANT HAO | EYR6: ACTIF CIRCULANT HAO | EYZ6: ACTIF CIRCULANT HAO | EZH6: ACTIF CIRCULANT HAO | EZP6: ACTIF CIRCULANT HAO | EZX6: ACTIF CIRCULANT HAO | FAF6: ACTIF CIRCULANT HAO | FAN6: ACTIF CIRCULANT HAO | FAV6: ACTIF CIRCULANT HAO | FBD6: ACTIF CIRCULANT HAO | FBL6: ACTIF CIRCULANT HAO | FBT6: ACTIF CIRCULANT HAO | FCB6: ACTIF CIRCULANT HAO | FCJ6: ACTIF CIRCULANT HAO | FCR6: ACTIF CIRCULANT HAO | FCZ6: ACTIF CIRCULANT HAO | FDH6: ACTIF CIRCULANT HAO | FDP6: ACTIF CIRCULANT HAO | FDX6: ACTIF CIRCULANT HAO | FEF6: ACTIF CIRCULANT HAO | FEN6: ACTIF CIRCULANT HAO | FEV6: ACTIF CIRCULANT HAO | FFD6: ACTIF CIRCULANT HAO | FFL6: ACTIF CIRCULANT HAO | FFT6: ACTIF CIRCULANT HAO | FGB6: ACTIF CIRCULANT HAO | FGJ6: ACTIF CIRCULANT HAO | FGR6: ACTIF CIRCULANT HAO | FGZ6: ACTIF CIRCULANT HAO | FHH6: ACTIF CIRCULANT HAO | FHP6: ACTIF CIRCULANT HAO | FHX6: ACTIF CIRCULANT HAO | FIF6: ACTIF CIRCULANT HAO | FIN6: ACTIF CIRCULANT HAO | FIV6: ACTIF CIRCULANT HAO | FJD6: ACTIF CIRCULANT HAO | FJL6: ACTIF CIRCULANT HAO | FJT6: ACTIF CIRCULANT HAO | FKB6: ACTIF CIRCULANT HAO | FKJ6: ACTIF CIRCULANT HAO | FKR6: ACTIF CIRCULANT HAO | FKZ6: ACTIF CIRCULANT HAO | FLH6: ACTIF CIRCULANT HAO | FLP6: ACTIF CIRCULANT HAO | FLX6: ACTIF CIRCULANT HAO | FMF6: ACTIF CIRCULANT HAO | FMN6: ACTIF CIRCULANT HAO | FMV6: ACTIF CIRCULANT HAO | FND6: ACTIF CIRCULANT HAO | FNL6: ACTIF CIRCULANT HAO | FNT6: ACTIF CIRCULANT HAO | FOB6: ACTIF CIRCULANT HAO | FOJ6: ACTIF CIRCULANT HAO | FOR6: ACTIF CIRCULANT HAO | FOZ6: ACTIF CIRCULANT HAO | FPH6: ACTIF CIRCULANT HAO | FPP6: ACTIF CIRCULANT HAO | FPX6: ACTIF CIRCULANT HAO | FQF6: ACTIF CIRCULANT HAO | FQN6: ACTIF CIRCULANT HAO | FQV6: ACTIF CIRCULANT HAO | FRD6: ACTIF CIRCULANT HAO | FRL6: ACTIF CIRCULANT HAO | FRT6: ACTIF CIRCULANT HAO | FSB6: ACTIF CIRCULANT HAO | FSJ6: ACTIF CIRCULANT HAO | FSR6: ACTIF CIRCULANT HAO | FSZ6: ACTIF CIRCULANT HAO | FTH6: ACTIF CIRCULANT HAO | FTP6: ACTIF CIRCULANT HAO | FTX6: ACTIF CIRCULANT HAO | FUF6: ACTIF CIRCULANT HAO | FUN6: ACTIF CIRCULANT HAO | FUV6: ACTIF CIRCULANT HAO | FVD6: ACTIF CIRCULANT HAO | FVL6: ACTIF CIRCULANT HAO | FVT6: ACTIF CIRCULANT HAO | FWB6: ACTIF CIRCULANT HAO | FWJ6: ACTIF CIRCULANT HAO | FWR6: ACTIF CIRCULANT HAO | FWZ6: ACTIF CIRCULANT HAO | FXH6: ACTIF CIRCULANT HAO | FXP6: ACTIF CIRCULANT HAO | FXX6: ACTIF CIRCULANT HAO | FYF6: ACTIF CIRCULANT HAO | FYN6: ACTIF CIRCULANT HAO | FYV6: ACTIF CIRCULANT HAO | FZD6: ACTIF CIRCULANT HAO | FZL6: ACTIF CIRCULANT HAO | FZT6: ACTIF CIRCULANT HAO | GAB6: ACTIF CIRCULANT HAO | GAJ6: ACTIF CIRCULANT HAO | GAR6: ACTIF CIRCULANT HAO | GAZ6: ACTIF CIRCULANT HAO | GBH6: ACTIF CIRCULANT HAO | GBP6: ACTIF CIRCULANT HAO | GBX6: ACTIF CIRCULANT HAO | GCF6: ACTIF CIRCULANT HAO | GCN6: ACTIF CIRCULANT HAO | GCV6: ACTIF CIRCULANT HAO | GDD6: ACTIF CIRCULANT HAO | GDL6: ACTIF CIRCULANT HAO | GDT6: ACTIF CIRCULANT HAO | GEB6: ACTIF CIRCULANT HAO | GEJ6: ACTIF CIRCULANT HAO | GER6: ACTIF CIRCULANT HAO | GEZ6: ACTIF CIRCULANT HAO | GFH6: ACTIF CIRCULANT HAO | GFP6: ACTIF CIRCULANT HAO | GFX6: ACTIF CIRCULANT HAO | GGF6: ACTIF CIRCULANT HAO | GGN6: ACTIF CIRCULANT HAO | GGV6: ACTIF CIRCULANT HAO | GHD6: ACTIF CIRCULANT HAO | GHL6: ACTIF CIRCULANT HAO | GHT6: ACTIF CIRCULANT HAO | GIB6: ACTIF CIRCULANT HAO | GIJ6: ACTIF CIRCULANT HAO | GIR6: ACTIF CIRCULANT HAO | GIZ6: ACTIF CIRCULANT HAO | GJH6: ACTIF CIRCULANT HAO | GJP6: ACTIF CIRCULANT HAO | GJX6: ACTIF CIRCULANT HAO | GKF6: ACTIF CIRCULANT HAO | GKN6: ACTIF CIRCULANT HAO | GKV6: ACTIF CIRCULANT HAO | GLD6: ACTIF CIRCULANT HAO | GLL6: ACTIF CIRCULANT HAO | GLT6: ACTIF CIRCULANT HAO | GMB6: ACTIF CIRCULANT HAO | GMJ6: ACTIF CIRCULANT HAO | GMR6: ACTIF CIRCULANT HAO | GMZ6: ACTIF CIRCULANT HAO | GNH6: ACTIF CIRCULANT HAO | GNP6: ACTIF CIRCULANT HAO | GNX6: ACTIF CIRCULANT HAO | GOF6: ACTIF CIRCULANT HAO | GON6: ACTIF CIRCULANT HAO | GOV6: ACTIF CIRCULANT HAO | GPD6: ACTIF CIRCULANT HAO | GPL6: ACTIF CIRCULANT HAO | GPT6: ACTIF CIRCULANT HAO | GQB6: ACTIF CIRCULANT HAO | GQJ6: ACTIF CIRCULANT HAO | GQR6: ACTIF CIRCULANT HAO | GQZ6: ACTIF CIRCULANT HAO | GRH6: ACTIF CIRCULANT HAO | GRP6: ACTIF CIRCULANT HAO | GRX6: ACTIF CIRCULANT HAO | GSF6: ACTIF CIRCULANT HAO | GSN6: ACTIF CIRCULANT HAO | GSV6: ACTIF CIRCULANT HAO | GTD6: ACTIF CIRCULANT HAO | GTL6: ACTIF CIRCULANT HAO | GTT6: ACTIF CIRCULANT HAO | GUB6: ACTIF CIRCULANT HAO | GUJ6: ACTIF CIRCULANT HAO | GUR6: ACTIF CIRCULANT HAO | GUZ6: ACTIF CIRCULANT HAO | GVH6: ACTIF CIRCULANT HAO | GVP6: ACTIF CIRCULANT HAO | GVX6: ACTIF CIRCULANT HAO | GWF6: ACTIF CIRCULANT HAO | GWN6: ACTIF CIRCULANT HAO | GWV6: ACTIF CIRCULANT HAO | GXD6: ACTIF CIRCULANT HAO | GXL6: ACTIF CIRCULANT HAO | GXT6: ACTIF CIRCULANT HAO | GYB6: ACTIF CIRCULANT HAO | GYJ6: ACTIF CIRCULANT HAO | GYR6: ACTIF CIRCULANT HAO | GYZ6: ACTIF CIRCULANT HAO | GZH6: ACTIF CIRCULANT HAO | GZP6: ACTIF CIRCULANT HAO | GZX6: ACTIF CIRCULANT HAO | HAF6: ACTIF CIRCULANT HAO | HAN6: ACTIF CIRCULANT HAO | HAV6: ACTIF CIRCULANT HAO | HBD6: ACTIF CIRCULANT HAO | HBL6: ACTIF CIRCULANT HAO | HBT6: ACTIF CIRCULANT HAO | HCB6: ACTIF CIRCULANT HAO | HCJ6: ACTIF CIRCULANT HAO | HCR6: ACTIF CIRCULANT HAO | HCZ6: ACTIF CIRCULANT HAO | HDH6: ACTIF CIRCULANT HAO | HDP6: ACTIF CIRCULANT HAO | HDX6: ACTIF CIRCULANT HAO | HEF6: ACTIF CIRCULANT HAO | HEN6: ACTIF CIRCULANT HAO | HEV6: ACTIF CIRCULANT HAO | HFD6: ACTIF CIRCULANT HAO | HFL6: ACTIF CIRCULANT HAO | HFT6: ACTIF CIRCULANT HAO | HGB6: ACTIF CIRCULANT HAO | HGJ6: ACTIF CIRCULANT HAO | HGR6: ACTIF CIRCULANT HAO | HGZ6: ACTIF CIRCULANT HAO | HHH6: ACTIF CIRCULANT HAO | HHP6: ACTIF CIRCULANT HAO | HHX6: ACTIF CIRCULANT HAO | HIF6: ACTIF CIRCULANT HAO | HIN6: ACTIF CIRCULANT HAO | HIV6: ACTIF CIRCULANT HAO | HJD6: ACTIF CIRCULANT HAO | HJL6: ACTIF CIRCULANT HAO | HJT6: ACTIF CIRCULANT HAO | HKB6: ACTIF CIRCULANT HAO | HKJ6: ACTIF CIRCULANT HAO | HKR6: ACTIF CIRCULANT HAO | HKZ6: ACTIF CIRCULANT HAO | HLH6: ACTIF CIRCULANT HAO | HLP6: ACTIF CIRCULANT HAO | HLX6: ACTIF CIRCULANT HAO | HMF6: ACTIF CIRCULANT HAO | HMN6: ACTIF CIRCULANT HAO | HMV6: ACTIF CIRCULANT HAO | HND6: ACTIF CIRCULANT HAO | HNL6: ACTIF CIRCULANT HAO | HNT6: ACTIF CIRCULANT HAO | HOB6: ACTIF CIRCULANT HAO | HOJ6: ACTIF CIRCULANT HAO | HOR6: ACTIF CIRCULANT HAO | HOZ6: ACTIF CIRCULANT HAO | HPH6: ACTIF CIRCULANT HAO | HPP6: ACTIF CIRCULANT HAO | HPX6: ACTIF CIRCULANT HAO | HQF6: ACTIF CIRCULANT HAO | HQN6: ACTIF CIRCULANT HAO | HQV6: ACTIF CIRCULANT HAO | HRD6: ACTIF CIRCULANT HAO | HRL6: ACTIF CIRCULANT HAO | HRT6: ACTIF CIRCULANT HAO | HSB6: ACTIF CIRCULANT HAO | HSJ6: ACTIF CIRCULANT HAO | HSR6: ACTIF CIRCULANT HAO | HSZ6: ACTIF CIRCULANT HAO | HTH6: ACTIF CIRCULANT HAO | HTP6: ACTIF CIRCULANT HAO | HTX6: ACTIF CIRCULANT HAO | HUF6: ACTIF CIRCULANT HAO | HUN6: ACTIF CIRCULANT HAO | HUV6: ACTIF CIRCULANT HAO | HVD6: ACTIF CIRCULANT HAO | HVL6: ACTIF CIRCULANT HAO | HVT6: ACTIF CIRCULANT HAO | HWB6: ACTIF CIRCULANT HAO | HWJ6: ACTIF CIRCULANT HAO | HWR6: ACTIF CIRCULANT HAO | HWZ6: ACTIF CIRCULANT HAO | HXH6: ACTIF CIRCULANT HAO | HXP6: ACTIF CIRCULANT HAO | HXX6: ACTIF CIRCULANT HAO | HYF6: ACTIF CIRCULANT HAO | HYN6: ACTIF CIRCULANT HAO | HYV6: ACTIF CIRCULANT HAO | HZD6: ACTIF CIRCULANT HAO | HZL6: ACTIF CIRCULANT HAO | HZT6: ACTIF CIRCULANT HAO | IAB6: ACTIF CIRCULANT HAO | IAJ6: ACTIF CIRCULANT HAO | IAR6: ACTIF CIRCULANT HAO | IAZ6: ACTIF CIRCULANT HAO | IBH6: ACTIF CIRCULANT HAO | IBP6: ACTIF CIRCULANT HAO | IBX6: ACTIF CIRCULANT HAO | ICF6: ACTIF CIRCULANT HAO | ICN6: ACTIF CIRCULANT HAO | ICV6: ACTIF CIRCULANT HAO | IDD6: ACTIF CIRCULANT HAO | IDL6: ACTIF CIRCULANT HAO | IDT6: ACTIF CIRCULANT HAO | IEB6: ACTIF CIRCULANT HAO | IEJ6: ACTIF CIRCULANT HAO | IER6: ACTIF CIRCULANT HAO | IEZ6: ACTIF CIRCULANT HAO | IFH6: ACTIF CIRCULANT HAO | IFP6: ACTIF CIRCULANT HAO | IFX6: ACTIF CIRCULANT HAO | IGF6: ACTIF CIRCULANT HAO | IGN6: ACTIF CIRCULANT HAO | IGV6: ACTIF CIRCULANT HAO | IHD6: ACTIF CIRCULANT HAO | IHL6: ACTIF CIRCULANT HAO | IHT6: ACTIF CIRCULANT HAO | IIB6: ACTIF CIRCULANT HAO | IIJ6: ACTIF CIRCULANT HAO | IIR6: ACTIF CIRCULANT HAO | IIZ6: ACTIF CIRCULANT HAO | IJH6: ACTIF CIRCULANT HAO | IJP6: ACTIF CIRCULANT HAO | IJX6: ACTIF CIRCULANT HAO | IKF6: ACTIF CIRCULANT HAO | IKN6: ACTIF CIRCULANT HAO | IKV6: ACTIF CIRCULANT HAO | ILD6: ACTIF CIRCULANT HAO | ILL6: ACTIF CIRCULANT HAO | ILT6: ACTIF CIRCULANT HAO | IMB6: ACTIF CIRCULANT HAO | IMJ6: ACTIF CIRCULANT HAO | IMR6: ACTIF CIRCULANT HAO | IMZ6: ACTIF CIRCULANT HAO | INH6: ACTIF CIRCULANT HAO | INP6: ACTIF CIRCULANT HAO | INX6: ACTIF CIRCULANT HAO | IOF6: ACTIF CIRCULANT HAO | ION6: ACTIF CIRCULANT HAO | IOV6: ACTIF CIRCULANT HAO | IPD6: ACTIF CIRCULANT HAO | IPL6: ACTIF CIRCULANT HAO | IPT6: ACTIF CIRCULANT HAO | IQB6: ACTIF CIRCULANT HAO | IQJ6: ACTIF CIRCULANT HAO | IQR6: ACTIF CIRCULANT HAO | IQZ6: ACTIF CIRCULANT HAO | IRH6: ACTIF CIRCULANT HAO | IRP6: ACTIF CIRCULANT HAO | IRX6: ACTIF CIRCULANT HAO | ISF6: ACTIF CIRCULANT HAO | ISN6: ACTIF CIRCULANT HAO | ISV6: ACTIF CIRCULANT HAO | ITD6: ACTIF CIRCULANT HAO | ITL6: ACTIF CIRCULANT HAO | ITT6: ACTIF CIRCULANT HAO | IUB6: ACTIF CIRCULANT HAO | IUJ6: ACTIF CIRCULANT HAO | IUR6: ACTIF CIRCULANT HAO | IUZ6: ACTIF CIRCULANT HAO | IVH6: ACTIF CIRCULANT HAO | IVP6: ACTIF CIRCULANT HAO | IVX6: ACTIF CIRCULANT HAO | IWF6: ACTIF CIRCULANT HAO | IWN6: ACTIF CIRCULANT HAO | IWV6: ACTIF CIRCULANT HAO | IXD6: ACTIF CIRCULANT HAO | IXL6: ACTIF CIRCULANT HAO | IXT6: ACTIF CIRCULANT HAO | IYB6: ACTIF CIRCULANT HAO | IYJ6: ACTIF CIRCULANT HAO | IYR6: ACTIF CIRCULANT HAO | IYZ6: ACTIF CIRCULANT HAO | IZH6: ACTIF CIRCULANT HAO | IZP6: ACTIF CIRCULANT HAO | IZX6: ACTIF CIRCULANT HAO | JAF6: ACTIF CIRCULANT HAO | JAN6: ACTIF CIRCULANT HAO | JAV6: ACTIF CIRCULANT HAO | JBD6: ACTIF CIRCULANT HAO | JBL6: ACTIF CIRCULANT HAO | JBT6: ACTIF CIRCULANT HAO | JCB6: ACTIF CIRCULANT HAO | JCJ6: ACTIF CIRCULANT HAO | JCR6: ACTIF CIRCULANT HAO | JCZ6: ACTIF CIRCULANT HAO | JDH6: ACTIF CIRCULANT HAO | JDP6: ACTIF CIRCULANT HAO | JDX6: ACTIF CIRCULANT HAO | JEF6: ACTIF CIRCULANT HAO | JEN6: ACTIF CIRCULANT HAO | JEV6: ACTIF CIRCULANT HAO | JFD6: ACTIF CIRCULANT HAO | JFL6: ACTIF CIRCULANT HAO | JFT6: ACTIF CIRCULANT HAO | JGB6: ACTIF CIRCULANT HAO | JGJ6: ACTIF CIRCULANT HAO | JGR6: ACTIF CIRCULANT HAO | JGZ6: ACTIF CIRCULANT HAO | JHH6: ACTIF CIRCULANT HAO | JHP6: ACTIF CIRCULANT HAO | JHX6: ACTIF CIRCULANT HAO | JIF6: ACTIF CIRCULANT HAO | JIN6: ACTIF CIRCULANT HAO | JIV6: ACTIF CIRCULANT HAO | JJD6: ACTIF CIRCULANT HAO | JJL6: ACTIF CIRCULANT HAO | JJT6: ACTIF CIRCULANT HAO | JKB6: ACTIF CIRCULANT HAO | JKJ6: ACTIF CIRCULANT HAO | JKR6: ACTIF CIRCULANT HAO | JKZ6: ACTIF CIRCULANT HAO | JLH6: ACTIF CIRCULANT HAO | JLP6: ACTIF CIRCULANT HAO | JLX6: ACTIF CIRCULANT HAO | JMF6: ACTIF CIRCULANT HAO | JMN6: ACTIF CIRCULANT HAO | JMV6: ACTIF CIRCULANT HAO | JND6: ACTIF CIRCULANT HAO | JNL6: ACTIF CIRCULANT HAO | JNT6: ACTIF CIRCULANT HAO | JOB6: ACTIF CIRCULANT HAO | JOJ6: ACTIF CIRCULANT HAO | JOR6: ACTIF CIRCULANT HAO | JOZ6: ACTIF CIRCULANT HAO | JPH6: ACTIF CIRCULANT HAO | JPP6: ACTIF CIRCULANT HAO | JPX6: ACTIF CIRCULANT HAO | JQF6: ACTIF CIRCULANT HAO | JQN6: ACTIF CIRCULANT HAO | JQV6: ACTIF CIRCULANT HAO | JRD6: ACTIF CIRCULANT HAO | JRL6: ACTIF CIRCULANT HAO | JRT6: ACTIF CIRCULANT HAO | JSB6: ACTIF CIRCULANT HAO | JSJ6: ACTIF CIRCULANT HAO | JSR6: ACTIF CIRCULANT HAO | JSZ6: ACTIF CIRCULANT HAO | JTH6: ACTIF CIRCULANT HAO | JTP6: ACTIF CIRCULANT HAO | JTX6: ACTIF CIRCULANT HAO | JUF6: ACTIF CIRCULANT HAO | JUN6: ACTIF CIRCULANT HAO | JUV6: ACTIF CIRCULANT HAO | JVD6: ACTIF CIRCULANT HAO | JVL6: ACTIF CIRCULANT HAO | JVT6: ACTIF CIRCULANT HAO | JWB6: ACTIF CIRCULANT HAO | JWJ6: ACTIF CIRCULANT HAO | JWR6: ACTIF CIRCULANT HAO | JWZ6: ACTIF CIRCULANT HAO | JXH6: ACTIF CIRCULANT HAO | JXP6: ACTIF CIRCULANT HAO | JXX6: ACTIF CIRCULANT HAO | JYF6: ACTIF CIRCULANT HAO | JYN6: ACTIF CIRCULANT HAO | JYV6: ACTIF CIRCULANT HAO | JZD6: ACTIF CIRCULANT HAO | JZL6: ACTIF CIRCULANT HAO | JZT6: ACTIF CIRCULANT HAO | KAB6: ACTIF CIRCULANT HAO | KAJ6: ACTIF CIRCULANT HAO | KAR6: ACTIF CIRCULANT HAO | KAZ6: ACTIF CIRCULANT HAO | KBH6: ACTIF CIRCULANT HAO | KBP6: ACTIF CIRCULANT HAO | KBX6: ACTIF CIRCULANT HAO | KCF6: ACTIF CIRCULANT HAO | KCN6: ACTIF CIRCULANT HAO | KCV6: ACTIF CIRCULANT HAO | KDD6: ACTIF CIRCULANT HAO | KDL6: ACTIF CIRCULANT HAO | KDT6: ACTIF CIRCULANT HAO | KEB6: ACTIF CIRCULANT HAO | KEJ6: ACTIF CIRCULANT HAO | KER6: ACTIF CIRCULANT HAO | KEZ6: ACTIF CIRCULANT HAO | KFH6: ACTIF CIRCULANT HAO | KFP6: ACTIF CIRCULANT HAO | KFX6: ACTIF CIRCULANT HAO | KGF6: ACTIF CIRCULANT HAO | KGN6: ACTIF CIRCULANT HAO | KGV6: ACTIF CIRCULANT HAO | KHD6: ACTIF CIRCULANT HAO | KHL6: ACTIF CIRCULANT HAO | KHT6: ACTIF CIRCULANT HAO | KIB6: ACTIF CIRCULANT HAO | KIJ6: ACTIF CIRCULANT HAO | KIR6: ACTIF CIRCULANT HAO | KIZ6: ACTIF CIRCULANT HAO | KJH6: ACTIF CIRCULANT HAO | KJP6: ACTIF CIRCULANT HAO | KJX6: ACTIF CIRCULANT HAO | KKF6: ACTIF CIRCULANT HAO | KKN6: ACTIF CIRCULANT HAO | KKV6: ACTIF CIRCULANT HAO | KLD6: ACTIF CIRCULANT HAO | KLL6: ACTIF CIRCULANT HAO | KLT6: ACTIF CIRCULANT HAO | KMB6: ACTIF CIRCULANT HAO | KMJ6: ACTIF CIRCULANT HAO | KMR6: ACTIF CIRCULANT HAO | KMZ6: ACTIF CIRCULANT HAO | KNH6: ACTIF CIRCULANT HAO | KNP6: ACTIF CIRCULANT HAO | KNX6: ACTIF CIRCULANT HAO | KOF6: ACTIF CIRCULANT HAO | KON6: ACTIF CIRCULANT HAO | KOV6: ACTIF CIRCULANT HAO | KPD6: ACTIF CIRCULANT HAO | KPL6: ACTIF CIRCULANT HAO | KPT6: ACTIF CIRCULANT HAO | KQB6: ACTIF CIRCULANT HAO | KQJ6: ACTIF CIRCULANT HAO | KQR6: ACTIF CIRCULANT HAO | KQZ6: ACTIF CIRCULANT HAO | KRH6: ACTIF CIRCULANT HAO | KRP6: ACTIF CIRCULANT HAO | KRX6: ACTIF CIRCULANT HAO | KSF6: ACTIF CIRCULANT HAO | KSN6: ACTIF CIRCULANT HAO | KSV6: ACTIF CIRCULANT HAO | KTD6: ACTIF CIRCULANT HAO | KTL6: ACTIF CIRCULANT HAO | KTT6: ACTIF CIRCULANT HAO | KUB6: ACTIF CIRCULANT HAO | KUJ6: ACTIF CIRCULANT HAO | KUR6: ACTIF CIRCULANT HAO | KUZ6: ACTIF CIRCULANT HAO | KVH6: ACTIF CIRCULANT HAO | KVP6: ACTIF CIRCULANT HAO | KVX6: ACTIF CIRCULANT HAO | KWF6: ACTIF CIRCULANT HAO | KWN6: ACTIF CIRCULANT HAO | KWV6: ACTIF CIRCULANT HAO | KXD6: ACTIF CIRCULANT HAO | KXL6: ACTIF CIRCULANT HAO | KXT6: ACTIF CIRCULANT HAO | KYB6: ACTIF CIRCULANT HAO | KYJ6: ACTIF CIRCULANT HAO | KYR6: ACTIF CIRCULANT HAO | KYZ6: ACTIF CIRCULANT HAO | KZH6: ACTIF CIRCULANT HAO | KZP6: ACTIF CIRCULANT HAO | KZX6: ACTIF CIRCULANT HAO | LAF6: ACTIF CIRCULANT HAO | LAN6: ACTIF CIRCULANT HAO | LAV6: ACTIF CIRCULANT HAO | LBD6: ACTIF CIRCULANT HAO | LBL6: ACTIF CIRCULANT HAO | LBT6: ACTIF CIRCULANT HAO | LCB6: ACTIF CIRCULANT HAO | LCJ6: ACTIF CIRCULANT HAO | LCR6: ACTIF CIRCULANT HAO | LCZ6: ACTIF CIRCULANT HAO | LDH6: ACTIF CIRCULANT HAO | LDP6: ACTIF CIRCULANT HAO | LDX6: ACTIF CIRCULANT HAO | LEF6: ACTIF CIRCULANT HAO | LEN6: ACTIF CIRCULANT HAO | LEV6: ACTIF CIRCULANT HAO | LFD6: ACTIF CIRCULANT HAO | LFL6: ACTIF CIRCULANT HAO | LFT6: ACTIF CIRCULANT HAO | LGB6: ACTIF CIRCULANT HAO | LGJ6: ACTIF CIRCULANT HAO | LGR6: ACTIF CIRCULANT HAO | LGZ6: ACTIF CIRCULANT HAO | LHH6: ACTIF CIRCULANT HAO | LHP6: ACTIF CIRCULANT HAO | LHX6: ACTIF CIRCULANT HAO | LIF6: ACTIF CIRCULANT HAO | LIN6: ACTIF CIRCULANT HAO | LIV6: ACTIF CIRCULANT HAO | LJD6: ACTIF CIRCULANT HAO | LJL6: ACTIF CIRCULANT HAO | LJT6: ACTIF CIRCULANT HAO | LKB6: ACTIF CIRCULANT HAO | LKJ6: ACTIF CIRCULANT HAO | LKR6: ACTIF CIRCULANT HAO | LKZ6: ACTIF CIRCULANT HAO | LLH6: ACTIF CIRCULANT HAO | LLP6: ACTIF CIRCULANT HAO | LLX6: ACTIF CIRCULANT HAO | LMF6: ACTIF CIRCULANT HAO | LMN6: ACTIF CIRCULANT HAO | LMV6: ACTIF CIRCULANT HAO | LND6: ACTIF CIRCULANT HAO | LNL6: ACTIF CIRCULANT HAO | LNT6: ACTIF CIRCULANT HAO | LOB6: ACTIF CIRCULANT HAO | LOJ6: ACTIF CIRCULANT HAO | LOR6: ACTIF CIRCULANT HAO | LOZ6: ACTIF CIRCULANT HAO | LPH6: ACTIF CIRCULANT HAO | LPP6: ACTIF CIRCULANT HAO | LPX6: ACTIF CIRCULANT HAO | LQF6: ACTIF CIRCULANT HAO | LQN6: ACTIF CIRCULANT HAO | LQV6: ACTIF CIRCULANT HAO | LRD6: ACTIF CIRCULANT HAO | LRL6: ACTIF CIRCULANT HAO | LRT6: ACTIF CIRCULANT HAO | LSB6: ACTIF CIRCULANT HAO | LSJ6: ACTIF CIRCULANT HAO | LSR6: ACTIF CIRCULANT HAO | LSZ6: ACTIF CIRCULANT HAO | LTH6: ACTIF CIRCULANT HAO | LTP6: ACTIF CIRCULANT HAO | LTX6: ACTIF CIRCULANT HAO | LUF6: ACTIF CIRCULANT HAO | LUN6: ACTIF CIRCULANT HAO | LUV6: ACTIF CIRCULANT HAO | LVD6: ACTIF CIRCULANT HAO | LVL6: ACTIF CIRCULANT HAO | LVT6: ACTIF CIRCULANT HAO | LWB6: ACTIF CIRCULANT HAO | LWJ6: ACTIF CIRCULANT HAO | LWR6: ACTIF CIRCULANT HAO | LWZ6: ACTIF CIRCULANT HAO | LXH6: ACTIF CIRCULANT HAO | LXP6: ACTIF CIRCULANT HAO | LXX6: ACTIF CIRCULANT HAO | LYF6: ACTIF CIRCULANT HAO | LYN6: ACTIF CIRCULANT HAO | LYV6: ACTIF CIRCULANT HAO | LZD6: ACTIF CIRCULANT HAO | LZL6: ACTIF CIRCULANT HAO | LZT6: ACTIF CIRCULANT HAO | MAB6: ACTIF CIRCULANT HAO | MAJ6: ACTIF CIRCULANT HAO | MAR6: ACTIF CIRCULANT HAO | MAZ6: ACTIF CIRCULANT HAO | MBH6: ACTIF CIRCULANT HAO | MBP6: ACTIF CIRCULANT HAO | MBX6: ACTIF CIRCULANT HAO | MCF6: ACTIF CIRCULANT HAO | MCN6: ACTIF CIRCULANT HAO | MCV6: ACTIF CIRCULANT HAO | MDD6: ACTIF CIRCULANT HAO | MDL6: ACTIF CIRCULANT HAO | MDT6: ACTIF CIRCULANT HAO | MEB6: ACTIF CIRCULANT HAO | MEJ6: ACTIF CIRCULANT HAO | MER6: ACTIF CIRCULANT HAO | MEZ6: ACTIF CIRCULANT HAO | MFH6: ACTIF CIRCULANT HAO | MFP6: ACTIF CIRCULANT HAO | MFX6: ACTIF CIRCULANT HAO | MGF6: ACTIF CIRCULANT HAO | MGN6: ACTIF CIRCULANT HAO | MGV6: ACTIF CIRCULANT HAO | MHD6: ACTIF CIRCULANT HAO | MHL6: ACTIF CIRCULANT HAO | MHT6: ACTIF CIRCULANT HAO | MIB6: ACTIF CIRCULANT HAO | MIJ6: ACTIF CIRCULANT HAO | MIR6: ACTIF CIRCULANT HAO | MIZ6: ACTIF CIRCULANT HAO | MJH6: ACTIF CIRCULANT HAO | MJP6: ACTIF CIRCULANT HAO | MJX6: ACTIF CIRCULANT HAO | MKF6: ACTIF CIRCULANT HAO | MKN6: ACTIF CIRCULANT HAO | MKV6: ACTIF CIRCULANT HAO | MLD6: ACTIF CIRCULANT HAO | MLL6: ACTIF CIRCULANT HAO | MLT6: ACTIF CIRCULANT HAO | MMB6: ACTIF CIRCULANT HAO | MMJ6: ACTIF CIRCULANT HAO | MMR6: ACTIF CIRCULANT HAO | MMZ6: ACTIF CIRCULANT HAO | MNH6: ACTIF CIRCULANT HAO | MNP6: ACTIF CIRCULANT HAO | MNX6: ACTIF CIRCULANT HAO | MOF6: ACTIF CIRCULANT HAO | MON6: ACTIF CIRCULANT HAO | MOV6: ACTIF CIRCULANT HAO | MPD6: ACTIF CIRCULANT HAO | MPL6: ACTIF CIRCULANT HAO | MPT6: ACTIF CIRCULANT HAO | MQB6: ACTIF CIRCULANT HAO | MQJ6: ACTIF CIRCULANT HAO | MQR6: ACTIF CIRCULANT HAO | MQZ6: ACTIF CIRCULANT HAO | MRH6: ACTIF CIRCULANT HAO | MRP6: ACTIF CIRCULANT HAO | MRX6: ACTIF CIRCULANT HAO | MSF6: ACTIF CIRCULANT HAO | MSN6: ACTIF CIRCULANT HAO | MSV6: ACTIF CIRCULANT HAO | MTD6: ACTIF CIRCULANT HAO | MTL6: ACTIF CIRCULANT HAO | MTT6: ACTIF CIRCULANT HAO | MUB6: ACTIF CIRCULANT HAO | MUJ6: ACTIF CIRCULANT HAO | MUR6: ACTIF CIRCULANT HAO | MUZ6: ACTIF CIRCULANT HAO | MVH6: ACTIF CIRCULANT HAO | MVP6: ACTIF CIRCULANT HAO | MVX6: ACTIF CIRCULANT HAO | MWF6: ACTIF CIRCULANT HAO | MWN6: ACTIF CIRCULANT HAO | MWV6: ACTIF CIRCULANT HAO | MXD6: ACTIF CIRCULANT HAO | MXL6: ACTIF CIRCULANT HAO | MXT6: ACTIF CIRCULANT HAO | MYB6: ACTIF CIRCULANT HAO | MYJ6: ACTIF CIRCULANT HAO | MYR6: ACTIF CIRCULANT HAO | MYZ6: ACTIF CIRCULANT HAO | MZH6: ACTIF CIRCULANT HAO | MZP6: ACTIF CIRCULANT HAO | MZX6: ACTIF CIRCULANT HAO | NAF6: ACTIF CIRCULANT HAO | NAN6: ACTIF CIRCULANT HAO | NAV6: ACTIF CIRCULANT HAO | NBD6: ACTIF CIRCULANT HAO | NBL6: ACTIF CIRCULANT HAO | NBT6: ACTIF CIRCULANT HAO | NCB6: ACTIF CIRCULANT HAO | NCJ6: ACTIF CIRCULANT HAO | NCR6: ACTIF CIRCULANT HAO | NCZ6: ACTIF CIRCULANT HAO | NDH6: ACTIF CIRCULANT HAO | NDP6: ACTIF CIRCULANT HAO | NDX6: ACTIF CIRCULANT HAO | NEF6: ACTIF CIRCULANT HAO | NEN6: ACTIF CIRCULANT HAO | NEV6: ACTIF CIRCULANT HAO | NFD6: ACTIF CIRCULANT HAO | NFL6: ACTIF CIRCULANT HAO | NFT6: ACTIF CIRCULANT HAO | NGB6: ACTIF CIRCULANT HAO | NGJ6: ACTIF CIRCULANT HAO | NGR6: ACTIF CIRCULANT HAO | NGZ6: ACTIF CIRCULANT HAO | NHH6: ACTIF CIRCULANT HAO | NHP6: ACTIF CIRCULANT HAO | NHX6: ACTIF CIRCULANT HAO | NIF6: ACTIF CIRCULANT HAO | NIN6: ACTIF CIRCULANT HAO | NIV6: ACTIF CIRCULANT HAO | NJD6: ACTIF CIRCULANT HAO | NJL6: ACTIF CIRCULANT HAO | NJT6: ACTIF CIRCULANT HAO | NKB6: ACTIF CIRCULANT HAO | NKJ6: ACTIF CIRCULANT HAO | NKR6: ACTIF CIRCULANT HAO | NKZ6: ACTIF CIRCULANT HAO | NLH6: ACTIF CIRCULANT HAO | NLP6: ACTIF CIRCULANT HAO | NLX6: ACTIF CIRCULANT HAO | NMF6: ACTIF CIRCULANT HAO | NMN6: ACTIF CIRCULANT HAO | NMV6: ACTIF CIRCULANT HAO | NND6: ACTIF CIRCULANT HAO | NNL6: ACTIF CIRCULANT HAO | NNT6: ACTIF CIRCULANT HAO | NOB6: ACTIF CIRCULANT HAO | NOJ6: ACTIF CIRCULANT HAO | NOR6: ACTIF CIRCULANT HAO | NOZ6: ACTIF CIRCULANT HAO | NPH6: ACTIF CIRCULANT HAO | NPP6: ACTIF CIRCULANT HAO | NPX6: ACTIF CIRCULANT HAO | NQF6: ACTIF CIRCULANT HAO | NQN6: ACTIF CIRCULANT HAO | NQV6: ACTIF CIRCULANT HAO | NRD6: ACTIF CIRCULANT HAO | NRL6: ACTIF CIRCULANT HAO | NRT6: ACTIF CIRCULANT HAO | NSB6: ACTIF CIRCULANT HAO | NSJ6: ACTIF CIRCULANT HAO | NSR6: ACTIF CIRCULANT HAO | NSZ6: ACTIF CIRCULANT HAO | NTH6: ACTIF CIRCULANT HAO | NTP6: ACTIF CIRCULANT HAO | NTX6: ACTIF CIRCULANT HAO | NUF6: ACTIF CIRCULANT HAO | NUN6: ACTIF CIRCULANT HAO | NUV6: ACTIF CIRCULANT HAO | NVD6: ACTIF CIRCULANT HAO | NVL6: ACTIF CIRCULANT HAO | NVT6: ACTIF CIRCULANT HAO | NWB6: ACTIF CIRCULANT HAO | NWJ6: ACTIF CIRCULANT HAO | NWR6: ACTIF CIRCULANT HAO | NWZ6: ACTIF CIRCULANT HAO | NXH6: ACTIF CIRCULANT HAO | NXP6: ACTIF CIRCULANT HAO | NXX6: ACTIF CIRCULANT HAO | NYF6: ACTIF CIRCULANT HAO | NYN6: ACTIF CIRCULANT HAO | NYV6: ACTIF CIRCULANT HAO | NZD6: ACTIF CIRCULANT HAO | NZL6: ACTIF CIRCULANT HAO | NZT6: ACTIF CIRCULANT HAO | OAB6: ACTIF CIRCULANT HAO | OAJ6: ACTIF CIRCULANT HAO | OAR6: ACTIF CIRCULANT HAO | OAZ6: ACTIF CIRCULANT HAO | OBH6: ACTIF CIRCULANT HAO | OBP6: ACTIF CIRCULANT HAO | OBX6: ACTIF CIRCULANT HAO | OCF6: ACTIF CIRCULANT HAO | OCN6: ACTIF CIRCULANT HAO | OCV6: ACTIF CIRCULANT HAO | ODD6: ACTIF CIRCULANT HAO | ODL6: ACTIF CIRCULANT HAO | ODT6: ACTIF CIRCULANT HAO | OEB6: ACTIF CIRCULANT HAO | OEJ6: ACTIF CIRCULANT HAO | OER6: ACTIF CIRCULANT HAO | OEZ6: ACTIF CIRCULANT HAO | OFH6: ACTIF CIRCULANT HAO | OFP6: ACTIF CIRCULANT HAO | OFX6: ACTIF CIRCULANT HAO | OGF6: ACTIF CIRCULANT HAO | OGN6: ACTIF CIRCULANT HAO | OGV6: ACTIF CIRCULANT HAO | OHD6: ACTIF CIRCULANT HAO | OHL6: ACTIF CIRCULANT HAO | OHT6: ACTIF CIRCULANT HAO | OIB6: ACTIF CIRCULANT HAO | OIJ6: ACTIF CIRCULANT HAO | OIR6: ACTIF CIRCULANT HAO | OIZ6: ACTIF CIRCULANT HAO | OJH6: ACTIF CIRCULANT HAO | OJP6: ACTIF CIRCULANT HAO | OJX6: ACTIF CIRCULANT HAO | OKF6: ACTIF CIRCULANT HAO | OKN6: ACTIF CIRCULANT HAO | OKV6: ACTIF CIRCULANT HAO | OLD6: ACTIF CIRCULANT HAO | OLL6: ACTIF CIRCULANT HAO | OLT6: ACTIF CIRCULANT HAO | OMB6: ACTIF CIRCULANT HAO | OMJ6: ACTIF CIRCULANT HAO | OMR6: ACTIF CIRCULANT HAO | OMZ6: ACTIF CIRCULANT HAO | ONH6: ACTIF CIRCULANT HAO | ONP6: ACTIF CIRCULANT HAO | ONX6: ACTIF CIRCULANT HAO | OOF6: ACTIF CIRCULANT HAO | OON6: ACTIF CIRCULANT HAO | OOV6: ACTIF CIRCULANT HAO | OPD6: ACTIF CIRCULANT HAO | OPL6: ACTIF CIRCULANT HAO | OPT6: ACTIF CIRCULANT HAO | OQB6: ACTIF CIRCULANT HAO | OQJ6: ACTIF CIRCULANT HAO | OQR6: ACTIF CIRCULANT HAO | OQZ6: ACTIF CIRCULANT HAO | ORH6: ACTIF CIRCULANT HAO | ORP6: ACTIF CIRCULANT HAO | ORX6: ACTIF CIRCULANT HAO | OSF6: ACTIF CIRCULANT HAO | OSN6: ACTIF CIRCULANT HAO | OSV6: ACTIF CIRCULANT HAO | OTD6: ACTIF CIRCULANT HAO | OTL6: ACTIF CIRCULANT HAO | OTT6: ACTIF CIRCULANT HAO | OUB6: ACTIF CIRCULANT HAO | OUJ6: ACTIF CIRCULANT HAO | OUR6: ACTIF CIRCULANT HAO | OUZ6: ACTIF CIRCULANT HAO | OVH6: ACTIF CIRCULANT HAO | OVP6: ACTIF CIRCULANT HAO | OVX6: ACTIF CIRCULANT HAO | OWF6: ACTIF CIRCULANT HAO | OWN6: ACTIF CIRCULANT HAO | OWV6: ACTIF CIRCULANT HAO | OXD6: ACTIF CIRCULANT HAO | OXL6: ACTIF CIRCULANT HAO | OXT6: ACTIF CIRCULANT HAO | OYB6: ACTIF CIRCULANT HAO | OYJ6: ACTIF CIRCULANT HAO | OYR6: ACTIF CIRCULANT HAO | OYZ6: ACTIF CIRCULANT HAO | OZH6: ACTIF CIRCULANT HAO | OZP6: ACTIF CIRCULANT HAO | OZX6: ACTIF CIRCULANT HAO | PAF6: ACTIF CIRCULANT HAO | PAN6: ACTIF CIRCULANT HAO | PAV6: ACTIF CIRCULANT HAO | PBD6: ACTIF CIRCULANT HAO | PBL6: ACTIF CIRCULANT HAO | PBT6: ACTIF CIRCULANT HAO | PCB6: ACTIF CIRCULANT HAO | PCJ6: ACTIF CIRCULANT HAO | PCR6: ACTIF CIRCULANT HAO | PCZ6: ACTIF CIRCULANT HAO | PDH6: ACTIF CIRCULANT HAO | PDP6: ACTIF CIRCULANT HAO | PDX6: ACTIF CIRCULANT HAO | PEF6: ACTIF CIRCULANT HAO | PEN6: ACTIF CIRCULANT HAO | PEV6: ACTIF CIRCULANT HAO | PFD6: ACTIF CIRCULANT HAO | PFL6: ACTIF CIRCULANT HAO | PFT6: ACTIF CIRCULANT HAO | PGB6: ACTIF CIRCULANT HAO | PGJ6: ACTIF CIRCULANT HAO | PGR6: ACTIF CIRCULANT HAO | PGZ6: ACTIF CIRCULANT HAO | PHH6: ACTIF CIRCULANT HAO | PHP6: ACTIF CIRCULANT HAO | PHX6: ACTIF CIRCULANT HAO | PIF6: ACTIF CIRCULANT HAO | PIN6: ACTIF CIRCULANT HAO | PIV6: ACTIF CIRCULANT HAO | PJD6: ACTIF CIRCULANT HAO | PJL6: ACTIF CIRCULANT HAO | PJT6: ACTIF CIRCULANT HAO | PKB6: ACTIF CIRCULANT HAO | PKJ6: ACTIF CIRCULANT HAO | PKR6: ACTIF CIRCULANT HAO | PKZ6: ACTIF CIRCULANT HAO | PLH6: ACTIF CIRCULANT HAO | PLP6: ACTIF CIRCULANT HAO | PLX6: ACTIF CIRCULANT HAO | PMF6: ACTIF CIRCULANT HAO | PMN6: ACTIF CIRCULANT HAO | PMV6: ACTIF CIRCULANT HAO | PND6: ACTIF CIRCULANT HAO | PNL6: ACTIF CIRCULANT HAO | PNT6: ACTIF CIRCULANT HAO | POB6: ACTIF CIRCULANT HAO | POJ6: ACTIF CIRCULANT HAO | POR6: ACTIF CIRCULANT HAO | POZ6: ACTIF CIRCULANT HAO | PPH6: ACTIF CIRCULANT HAO | PPP6: ACTIF CIRCULANT HAO | PPX6: ACTIF CIRCULANT HAO | PQF6: ACTIF CIRCULANT HAO | PQN6: ACTIF CIRCULANT HAO | PQV6: ACTIF CIRCULANT HAO | PRD6: ACTIF CIRCULANT HAO | PRL6: ACTIF CIRCULANT HAO | PRT6: ACTIF CIRCULANT HAO | PSB6: ACTIF CIRCULANT HAO | PSJ6: ACTIF CIRCULANT HAO | PSR6: ACTIF CIRCULANT HAO | PSZ6: ACTIF CIRCULANT HAO | PTH6: ACTIF CIRCULANT HAO | PTP6: ACTIF CIRCULANT HAO | PTX6: ACTIF CIRCULANT HAO | PUF6: ACTIF CIRCULANT HAO | PUN6: ACTIF CIRCULANT HAO | PUV6: ACTIF CIRCULANT HAO | PVD6: ACTIF CIRCULANT HAO | PVL6: ACTIF CIRCULANT HAO | PVT6: ACTIF CIRCULANT HAO | PWB6: ACTIF CIRCULANT HAO | PWJ6: ACTIF CIRCULANT HAO | PWR6: ACTIF CIRCULANT HAO | PWZ6: ACTIF CIRCULANT HAO | PXH6: ACTIF CIRCULANT HAO | PXP6: ACTIF CIRCULANT HAO | PXX6: ACTIF CIRCULANT HAO | PYF6: ACTIF CIRCULANT HAO | PYN6: ACTIF CIRCULANT HAO | PYV6: ACTIF CIRCULANT HAO | PZD6: ACTIF CIRCULANT HAO | PZL6: ACTIF CIRCULANT HAO | PZT6: ACTIF CIRCULANT HAO | QAB6: ACTIF CIRCULANT HAO | QAJ6: ACTIF CIRCULANT HAO | QAR6: ACTIF CIRCULANT HAO | QAZ6: ACTIF CIRCULANT HAO | QBH6: ACTIF CIRCULANT HAO | QBP6: ACTIF CIRCULANT HAO | QBX6: ACTIF CIRCULANT HAO | QCF6: ACTIF CIRCULANT HAO | QCN6: ACTIF CIRCULANT HAO | QCV6: ACTIF CIRCULANT HAO | QDD6: ACTIF CIRCULANT HAO | QDL6: ACTIF CIRCULANT HAO | QDT6: ACTIF CIRCULANT HAO | QEB6: ACTIF CIRCULANT HAO | QEJ6: ACTIF CIRCULANT HAO | QER6: ACTIF CIRCULANT HAO | QEZ6: ACTIF CIRCULANT HAO | QFH6: ACTIF CIRCULANT HAO | QFP6: ACTIF CIRCULANT HAO | QFX6: ACTIF CIRCULANT HAO | QGF6: ACTIF CIRCULANT HAO | QGN6: ACTIF CIRCULANT HAO | QGV6: ACTIF CIRCULANT HAO | QHD6: ACTIF CIRCULANT HAO | QHL6: ACTIF CIRCULANT HAO | QHT6: ACTIF CIRCULANT HAO | QIB6: ACTIF CIRCULANT HAO | QIJ6: ACTIF CIRCULANT HAO | QIR6: ACTIF CIRCULANT HAO | QIZ6: ACTIF CIRCULANT HAO | QJH6: ACTIF CIRCULANT HAO | QJP6: ACTIF CIRCULANT HAO | QJX6: ACTIF CIRCULANT HAO | QKF6: ACTIF CIRCULANT HAO | QKN6: ACTIF CIRCULANT HAO | QKV6: ACTIF CIRCULANT HAO | QLD6: ACTIF CIRCULANT HAO | QLL6: ACTIF CIRCULANT HAO | QLT6: ACTIF CIRCULANT HAO | QMB6: ACTIF CIRCULANT HAO | QMJ6: ACTIF CIRCULANT HAO | QMR6: ACTIF CIRCULANT HAO | QMZ6: ACTIF CIRCULANT HAO | QNH6: ACTIF CIRCULANT HAO | QNP6: ACTIF CIRCULANT HAO | QNX6: ACTIF CIRCULANT HAO | QOF6: ACTIF CIRCULANT HAO | QON6: ACTIF CIRCULANT HAO | QOV6: ACTIF CIRCULANT HAO | QPD6: ACTIF CIRCULANT HAO | QPL6: ACTIF CIRCULANT HAO | QPT6: ACTIF CIRCULANT HAO | QQB6: ACTIF CIRCULANT HAO | QQJ6: ACTIF CIRCULANT HAO | QQR6: ACTIF CIRCULANT HAO | QQZ6: ACTIF CIRCULANT HAO | QRH6: ACTIF CIRCULANT HAO | QRP6: ACTIF CIRCULANT HAO | QRX6: ACTIF CIRCULANT HAO | QSF6: ACTIF CIRCULANT HAO | QSN6: ACTIF CIRCULANT HAO | QSV6: ACTIF CIRCULANT HAO | QTD6: ACTIF CIRCULANT HAO | QTL6: ACTIF CIRCULANT HAO | QTT6: ACTIF CIRCULANT HAO | QUB6: ACTIF CIRCULANT HAO | QUJ6: ACTIF CIRCULANT HAO | QUR6: ACTIF CIRCULANT HAO | QUZ6: ACTIF CIRCULANT HAO | QVH6: ACTIF CIRCULANT HAO | QVP6: ACTIF CIRCULANT HAO | QVX6: ACTIF CIRCULANT HAO | QWF6: ACTIF CIRCULANT HAO | QWN6: ACTIF CIRCULANT HAO | QWV6: ACTIF CIRCULANT HAO | QXD6: ACTIF CIRCULANT HAO | QXL6: ACTIF CIRCULANT HAO | QXT6: ACTIF CIRCULANT HAO | QYB6: ACTIF CIRCULANT HAO | QYJ6: ACTIF CIRCULANT HAO | QYR6: ACTIF CIRCULANT HAO | QYZ6: ACTIF CIRCULANT HAO | QZH6: ACTIF CIRCULANT HAO | QZP6: ACTIF CIRCULANT HAO | QZX6: ACTIF CIRCULANT HAO | RAF6: ACTIF CIRCULANT HAO | RAN6: ACTIF CIRCULANT HAO | RAV6: ACTIF CIRCULANT HAO | RBD6: ACTIF CIRCULANT HAO | RBL6: ACTIF CIRCULANT HAO | RBT6: ACTIF CIRCULANT HAO | RCB6: ACTIF CIRCULANT HAO | RCJ6: ACTIF CIRCULANT HAO | RCR6: ACTIF CIRCULANT HAO | RCZ6: ACTIF CIRCULANT HAO | RDH6: ACTIF CIRCULANT HAO | RDP6: ACTIF CIRCULANT HAO | RDX6: ACTIF CIRCULANT HAO | REF6: ACTIF CIRCULANT HAO | REN6: ACTIF CIRCULANT HAO | REV6: ACTIF CIRCULANT HAO | RFD6: ACTIF CIRCULANT HAO | RFL6: ACTIF CIRCULANT HAO | RFT6: ACTIF CIRCULANT HAO | RGB6: ACTIF CIRCULANT HAO | RGJ6: ACTIF CIRCULANT HAO | RGR6: ACTIF CIRCULANT HAO | RGZ6: ACTIF CIRCULANT HAO | RHH6: ACTIF CIRCULANT HAO | RHP6: ACTIF CIRCULANT HAO | RHX6: ACTIF CIRCULANT HAO | RIF6: ACTIF CIRCULANT HAO | RIN6: ACTIF CIRCULANT HAO | RIV6: ACTIF CIRCULANT HAO | RJD6: ACTIF CIRCULANT HAO | RJL6: ACTIF CIRCULANT HAO | RJT6: ACTIF CIRCULANT HAO | RKB6: ACTIF CIRCULANT HAO | RKJ6: ACTIF CIRCULANT HAO | RKR6: ACTIF CIRCULANT HAO | RKZ6: ACTIF CIRCULANT HAO | RLH6: ACTIF CIRCULANT HAO | RLP6: ACTIF CIRCULANT HAO | RLX6: ACTIF CIRCULANT HAO | RMF6: ACTIF CIRCULANT HAO | RMN6: ACTIF CIRCULANT HAO | RMV6: ACTIF CIRCULANT HAO | RND6: ACTIF CIRCULANT HAO | RNL6: ACTIF CIRCULANT HAO | RNT6: ACTIF CIRCULANT HAO | ROB6: ACTIF CIRCULANT HAO | ROJ6: ACTIF CIRCULANT HAO | ROR6: ACTIF CIRCULANT HAO | ROZ6: ACTIF CIRCULANT HAO | RPH6: ACTIF CIRCULANT HAO | RPP6: ACTIF CIRCULANT HAO | RPX6: ACTIF CIRCULANT HAO | RQF6: ACTIF CIRCULANT HAO | RQN6: ACTIF CIRCULANT HAO | RQV6: ACTIF CIRCULANT HAO | RRD6: ACTIF CIRCULANT HAO | RRL6: ACTIF CIRCULANT HAO | RRT6: ACTIF CIRCULANT HAO | RSB6: ACTIF CIRCULANT HAO | RSJ6: ACTIF CIRCULANT HAO | RSR6: ACTIF CIRCULANT HAO | RSZ6: ACTIF CIRCULANT HAO | RTH6: ACTIF CIRCULANT HAO | RTP6: ACTIF CIRCULANT HAO | RTX6: ACTIF CIRCULANT HAO | RUF6: ACTIF CIRCULANT HAO | RUN6: ACTIF CIRCULANT HAO | RUV6: ACTIF CIRCULANT HAO | RVD6: ACTIF CIRCULANT HAO | RVL6: ACTIF CIRCULANT HAO | RVT6: ACTIF CIRCULANT HAO | RWB6: ACTIF CIRCULANT HAO | RWJ6: ACTIF CIRCULANT HAO | RWR6: ACTIF CIRCULANT HAO | RWZ6: ACTIF CIRCULANT HAO | RXH6: ACTIF CIRCULANT HAO | RXP6: ACTIF CIRCULANT HAO | RXX6: ACTIF CIRCULANT HAO | RYF6: ACTIF CIRCULANT HAO | RYN6: ACTIF CIRCULANT HAO | RYV6: ACTIF CIRCULANT HAO | RZD6: ACTIF CIRCULANT HAO | RZL6: ACTIF CIRCULANT HAO | RZT6: ACTIF CIRCULANT HAO | SAB6: ACTIF CIRCULANT HAO | SAJ6: ACTIF CIRCULANT HAO | SAR6: ACTIF CIRCULANT HAO | SAZ6: ACTIF CIRCULANT HAO | SBH6: ACTIF CIRCULANT HAO | SBP6: ACTIF CIRCULANT HAO | SBX6: ACTIF CIRCULANT HAO | SCF6: ACTIF CIRCULANT HAO | SCN6: ACTIF CIRCULANT HAO | SCV6: ACTIF CIRCULANT HAO | SDD6: ACTIF CIRCULANT HAO | SDL6: ACTIF CIRCULANT HAO | SDT6: ACTIF CIRCULANT HAO | SEB6: ACTIF CIRCULANT HAO | SEJ6: ACTIF CIRCULANT HAO | SER6: ACTIF CIRCULANT HAO | SEZ6: ACTIF CIRCULANT HAO | SFH6: ACTIF CIRCULANT HAO | SFP6: ACTIF CIRCULANT HAO | SFX6: ACTIF CIRCULANT HAO | SGF6: ACTIF CIRCULANT HAO | SGN6: ACTIF CIRCULANT HAO | SGV6: ACTIF CIRCULANT HAO | SHD6: ACTIF CIRCULANT HAO | SHL6: ACTIF CIRCULANT HAO | SHT6: ACTIF CIRCULANT HAO | SIB6: ACTIF CIRCULANT HAO | SIJ6: ACTIF CIRCULANT HAO | SIR6: ACTIF CIRCULANT HAO | SIZ6: ACTIF CIRCULANT HAO | SJH6: ACTIF CIRCULANT HAO | SJP6: ACTIF CIRCULANT HAO | SJX6: ACTIF CIRCULANT HAO | SKF6: ACTIF CIRCULANT HAO | SKN6: ACTIF CIRCULANT HAO | SKV6: ACTIF CIRCULANT HAO | SLD6: ACTIF CIRCULANT HAO | SLL6: ACTIF CIRCULANT HAO | SLT6: ACTIF CIRCULANT HAO | SMB6: ACTIF CIRCULANT HAO | SMJ6: ACTIF CIRCULANT HAO | SMR6: ACTIF CIRCULANT HAO | SMZ6: ACTIF CIRCULANT HAO | SNH6: ACTIF CIRCULANT HAO | SNP6: ACTIF CIRCULANT HAO | SNX6: ACTIF CIRCULANT HAO | SOF6: ACTIF CIRCULANT HAO | SON6: ACTIF CIRCULANT HAO | SOV6: ACTIF CIRCULANT HAO | SPD6: ACTIF CIRCULANT HAO | SPL6: ACTIF CIRCULANT HAO | SPT6: ACTIF CIRCULANT HAO | SQB6: ACTIF CIRCULANT HAO | SQJ6: ACTIF CIRCULANT HAO | SQR6: ACTIF CIRCULANT HAO | SQZ6: ACTIF CIRCULANT HAO | SRH6: ACTIF CIRCULANT HAO | SRP6: ACTIF CIRCULANT HAO | SRX6: ACTIF CIRCULANT HAO | SSF6: ACTIF CIRCULANT HAO | SSN6: ACTIF CIRCULANT HAO | SSV6: ACTIF CIRCULANT HAO | STD6: ACTIF CIRCULANT HAO | STL6: ACTIF CIRCULANT HAO | STT6: ACTIF CIRCULANT HAO | SUB6: ACTIF CIRCULANT HAO | SUJ6: ACTIF CIRCULANT HAO | SUR6: ACTIF CIRCULANT HAO | SUZ6: ACTIF CIRCULANT HAO | SVH6: ACTIF CIRCULANT HAO | SVP6: ACTIF CIRCULANT HAO | SVX6: ACTIF CIRCULANT HAO | SWF6: ACTIF CIRCULANT HAO | SWN6: ACTIF CIRCULANT HAO | SWV6: ACTIF CIRCULANT HAO | SXD6: ACTIF CIRCULANT HAO | SXL6: ACTIF CIRCULANT HAO | SXT6: ACTIF CIRCULANT HAO | SYB6: ACTIF CIRCULANT HAO | SYJ6: ACTIF CIRCULANT HAO | SYR6: ACTIF CIRCULANT HAO | SYZ6: ACTIF CIRCULANT HAO | SZH6: ACTIF CIRCULANT HAO | SZP6: ACTIF CIRCULANT HAO | SZX6: ACTIF CIRCULANT HAO | TAF6: ACTIF CIRCULANT HAO | TAN6: ACTIF CIRCULANT HAO | TAV6: ACTIF CIRCULANT HAO | TBD6: ACTIF CIRCULANT HAO | TBL6: ACTIF CIRCULANT HAO | TBT6: ACTIF CIRCULANT HAO | TCB6: ACTIF CIRCULANT HAO | TCJ6: ACTIF CIRCULANT HAO | TCR6: ACTIF CIRCULANT HAO | TCZ6: ACTIF CIRCULANT HAO | TDH6: ACTIF CIRCULANT HAO | TDP6: ACTIF CIRCULANT HAO | TDX6: ACTIF CIRCULANT HAO | TEF6: ACTIF CIRCULANT HAO | TEN6: ACTIF CIRCULANT HAO | TEV6: ACTIF CIRCULANT HAO | TFD6: ACTIF CIRCULANT HAO | TFL6: ACTIF CIRCULANT HAO | TFT6: ACTIF CIRCULANT HAO | TGB6: ACTIF CIRCULANT HAO | TGJ6: ACTIF CIRCULANT HAO | TGR6: ACTIF CIRCULANT HAO | TGZ6: ACTIF CIRCULANT HAO | THH6: ACTIF CIRCULANT HAO | THP6: ACTIF CIRCULANT HAO | THX6: ACTIF CIRCULANT HAO | TIF6: ACTIF CIRCULANT HAO | TIN6: ACTIF CIRCULANT HAO | TIV6: ACTIF CIRCULANT HAO | TJD6: ACTIF CIRCULANT HAO | TJL6: ACTIF CIRCULANT HAO | TJT6: ACTIF CIRCULANT HAO | TKB6: ACTIF CIRCULANT HAO | TKJ6: ACTIF CIRCULANT HAO | TKR6: ACTIF CIRCULANT HAO | TKZ6: ACTIF CIRCULANT HAO | TLH6: ACTIF CIRCULANT HAO | TLP6: ACTIF CIRCULANT HAO | TLX6: ACTIF CIRCULANT HAO | TMF6: ACTIF CIRCULANT HAO | TMN6: ACTIF CIRCULANT HAO | TMV6: ACTIF CIRCULANT HAO | TND6: ACTIF CIRCULANT HAO | TNL6: ACTIF CIRCULANT HAO | TNT6: ACTIF CIRCULANT HAO | TOB6: ACTIF CIRCULANT HAO | TOJ6: ACTIF CIRCULANT HAO | TOR6: ACTIF CIRCULANT HAO | TOZ6: ACTIF CIRCULANT HAO | TPH6: ACTIF CIRCULANT HAO | TPP6: ACTIF CIRCULANT HAO | TPX6: ACTIF CIRCULANT HAO | TQF6: ACTIF CIRCULANT HAO | TQN6: ACTIF CIRCULANT HAO | TQV6: ACTIF CIRCULANT HAO | TRD6: ACTIF CIRCULANT HAO | TRL6: ACTIF CIRCULANT HAO | TRT6: ACTIF CIRCULANT HAO | TSB6: ACTIF CIRCULANT HAO | TSJ6: ACTIF CIRCULANT HAO | TSR6: ACTIF CIRCULANT HAO | TSZ6: ACTIF CIRCULANT HAO | TTH6: ACTIF CIRCULANT HAO | TTP6: ACTIF CIRCULANT HAO | TTX6: ACTIF CIRCULANT HAO | TUF6: ACTIF CIRCULANT HAO | TUN6: ACTIF CIRCULANT HAO | TUV6: ACTIF CIRCULANT HAO | TVD6: ACTIF CIRCULANT HAO | TVL6: ACTIF CIRCULANT HAO | TVT6: ACTIF CIRCULANT HAO | TWB6: ACTIF CIRCULANT HAO | TWJ6: ACTIF CIRCULANT HAO | TWR6: ACTIF CIRCULANT HAO | TWZ6: ACTIF CIRCULANT HAO | TXH6: ACTIF CIRCULANT HAO | TXP6: ACTIF CIRCULANT HAO | TXX6: ACTIF CIRCULANT HAO | TYF6: ACTIF CIRCULANT HAO | TYN6: ACTIF CIRCULANT HAO | TYV6: ACTIF CIRCULANT HAO | TZD6: ACTIF CIRCULANT HAO | TZL6: ACTIF CIRCULANT HAO | TZT6: ACTIF CIRCULANT HAO | UAB6: ACTIF CIRCULANT HAO | UAJ6: ACTIF CIRCULANT HAO | UAR6: ACTIF CIRCULANT HAO | UAZ6: ACTIF CIRCULANT HAO | UBH6: ACTIF CIRCULANT HAO | UBP6: ACTIF CIRCULANT HAO | UBX6: ACTIF CIRCULANT HAO | UCF6: ACTIF CIRCULANT HAO | UCN6: ACTIF CIRCULANT HAO | UCV6: ACTIF CIRCULANT HAO | UDD6: ACTIF CIRCULANT HAO | UDL6: ACTIF CIRCULANT HAO | UDT6: ACTIF CIRCULANT HAO | UEB6: ACTIF CIRCULANT HAO | UEJ6: ACTIF CIRCULANT HAO | UER6: ACTIF CIRCULANT HAO | UEZ6: ACTIF CIRCULANT HAO | UFH6: ACTIF CIRCULANT HAO | UFP6: ACTIF CIRCULANT HAO | UFX6: ACTIF CIRCULANT HAO | UGF6: ACTIF CIRCULANT HAO | UGN6: ACTIF CIRCULANT HAO | UGV6: ACTIF CIRCULANT HAO | UHD6: ACTIF CIRCULANT HAO | UHL6: ACTIF CIRCULANT HAO | UHT6: ACTIF CIRCULANT HAO | UIB6: ACTIF CIRCULANT HAO | UIJ6: ACTIF CIRCULANT HAO | UIR6: ACTIF CIRCULANT HAO | UIZ6: ACTIF CIRCULANT HAO | UJH6: ACTIF CIRCULANT HAO | UJP6: ACTIF CIRCULANT HAO | UJX6: ACTIF CIRCULANT HAO | UKF6: ACTIF CIRCULANT HAO | UKN6: ACTIF CIRCULANT HAO | UKV6: ACTIF CIRCULANT HAO | ULD6: ACTIF CIRCULANT HAO | ULL6: ACTIF CIRCULANT HAO | ULT6: ACTIF CIRCULANT HAO | UMB6: ACTIF CIRCULANT HAO | UMJ6: ACTIF CIRCULANT HAO | UMR6: ACTIF CIRCULANT HAO | UMZ6: ACTIF CIRCULANT HAO | UNH6: ACTIF CIRCULANT HAO | UNP6: ACTIF CIRCULANT HAO | UNX6: ACTIF CIRCULANT HAO | UOF6: ACTIF CIRCULANT HAO | UON6: ACTIF CIRCULANT HAO | UOV6: ACTIF CIRCULANT HAO | UPD6: ACTIF CIRCULANT HAO | UPL6: ACTIF CIRCULANT HAO | UPT6: ACTIF CIRCULANT HAO | UQB6: ACTIF CIRCULANT HAO | UQJ6: ACTIF CIRCULANT HAO | UQR6: ACTIF CIRCULANT HAO | UQZ6: ACTIF CIRCULANT HAO | URH6: ACTIF CIRCULANT HAO | URP6: ACTIF CIRCULANT HAO | URX6: ACTIF CIRCULANT HAO | USF6: ACTIF CIRCULANT HAO | USN6: ACTIF CIRCULANT HAO | USV6: ACTIF CIRCULANT HAO | UTD6: ACTIF CIRCULANT HAO | UTL6: ACTIF CIRCULANT HAO | UTT6: ACTIF CIRCULANT HAO | UUB6: ACTIF CIRCULANT HAO | UUJ6: ACTIF CIRCULANT HAO | UUR6: ACTIF CIRCULANT HAO | UUZ6: ACTIF CIRCULANT HAO | UVH6: ACTIF CIRCULANT HAO | UVP6: ACTIF CIRCULANT HAO | UVX6: ACTIF CIRCULANT HAO | UWF6: ACTIF CIRCULANT HAO | UWN6: ACTIF CIRCULANT HAO | UWV6: ACTIF CIRCULANT HAO | UXD6: ACTIF CIRCULANT HAO | UXL6: ACTIF CIRCULANT HAO | UXT6: ACTIF CIRCULANT HAO | UYB6: ACTIF CIRCULANT HAO | UYJ6: ACTIF CIRCULANT HAO | UYR6: ACTIF CIRCULANT HAO | UYZ6: ACTIF CIRCULANT HAO | UZH6: ACTIF CIRCULANT HAO | UZP6: ACTIF CIRCULANT HAO | UZX6: ACTIF CIRCULANT HAO | VAF6: ACTIF CIRCULANT HAO | VAN6: ACTIF CIRCULANT HAO | VAV6: ACTIF CIRCULANT HAO | VBD6: ACTIF CIRCULANT HAO | VBL6: ACTIF CIRCULANT HAO | VBT6: ACTIF CIRCULANT HAO | VCB6: ACTIF CIRCULANT HAO | VCJ6: ACTIF CIRCULANT HAO | VCR6: ACTIF CIRCULANT HAO | VCZ6: ACTIF CIRCULANT HAO | VDH6: ACTIF CIRCULANT HAO | VDP6: ACTIF CIRCULANT HAO | VDX6: ACTIF CIRCULANT HAO | VEF6: ACTIF CIRCULANT HAO | VEN6: ACTIF CIRCULANT HAO | VEV6: ACTIF CIRCULANT HAO | VFD6: ACTIF CIRCULANT HAO | VFL6: ACTIF CIRCULANT HAO | VFT6: ACTIF CIRCULANT HAO | VGB6: ACTIF CIRCULANT HAO | VGJ6: ACTIF CIRCULANT HAO | VGR6: ACTIF CIRCULANT HAO | VGZ6: ACTIF CIRCULANT HAO | VHH6: ACTIF CIRCULANT HAO | VHP6: ACTIF CIRCULANT HAO | VHX6: ACTIF CIRCULANT HAO | VIF6: ACTIF CIRCULANT HAO | VIN6: ACTIF CIRCULANT HAO | VIV6: ACTIF CIRCULANT HAO | VJD6: ACTIF CIRCULANT HAO | VJL6: ACTIF CIRCULANT HAO | VJT6: ACTIF CIRCULANT HAO | VKB6: ACTIF CIRCULANT HAO | VKJ6: ACTIF CIRCULANT HAO | VKR6: ACTIF CIRCULANT HAO | VKZ6: ACTIF CIRCULANT HAO | VLH6: ACTIF CIRCULANT HAO | VLP6: ACTIF CIRCULANT HAO | VLX6: ACTIF CIRCULANT HAO | VMF6: ACTIF CIRCULANT HAO | VMN6: ACTIF CIRCULANT HAO | VMV6: ACTIF CIRCULANT HAO | VND6: ACTIF CIRCULANT HAO | VNL6: ACTIF CIRCULANT HAO | VNT6: ACTIF CIRCULANT HAO | VOB6: ACTIF CIRCULANT HAO | VOJ6: ACTIF CIRCULANT HAO | VOR6: ACTIF CIRCULANT HAO | VOZ6: ACTIF CIRCULANT HAO | VPH6: ACTIF CIRCULANT HAO | VPP6: ACTIF CIRCULANT HAO | VPX6: ACTIF CIRCULANT HAO | VQF6: ACTIF CIRCULANT HAO | VQN6: ACTIF CIRCULANT HAO | VQV6: ACTIF CIRCULANT HAO | VRD6: ACTIF CIRCULANT HAO | VRL6: ACTIF CIRCULANT HAO | VRT6: ACTIF CIRCULANT HAO | VSB6: ACTIF CIRCULANT HAO | VSJ6: ACTIF CIRCULANT HAO | VSR6: ACTIF CIRCULANT HAO | VSZ6: ACTIF CIRCULANT HAO | VTH6: ACTIF CIRCULANT HAO | VTP6: ACTIF CIRCULANT HAO | VTX6: ACTIF CIRCULANT HAO | VUF6: ACTIF CIRCULANT HAO | VUN6: ACTIF CIRCULANT HAO | VUV6: ACTIF CIRCULANT HAO | VVD6: ACTIF CIRCULANT HAO | VVL6: ACTIF CIRCULANT HAO | VVT6: ACTIF CIRCULANT HAO | VWB6: ACTIF CIRCULANT HAO | VWJ6: ACTIF CIRCULANT HAO | VWR6: ACTIF CIRCULANT HAO | VWZ6: ACTIF CIRCULANT HAO | VXH6: ACTIF CIRCULANT HAO | VXP6: ACTIF CIRCULANT HAO | VXX6: ACTIF CIRCULANT HAO | VYF6: ACTIF CIRCULANT HAO | VYN6: ACTIF CIRCULANT HAO | VYV6: ACTIF CIRCULANT HAO | VZD6: ACTIF CIRCULANT HAO | VZL6: ACTIF CIRCULANT HAO | VZT6: ACTIF CIRCULANT HAO | WAB6: ACTIF CIRCULANT HAO | WAJ6: ACTIF CIRCULANT HAO | WAR6: ACTIF CIRCULANT HAO | WAZ6: ACTIF CIRCULANT HAO | WBH6: ACTIF CIRCULANT HAO | WBP6: ACTIF CIRCULANT HAO | WBX6: ACTIF CIRCULANT HAO | WCF6: ACTIF CIRCULANT HAO | WCN6: ACTIF CIRCULANT HAO | WCV6: ACTIF CIRCULANT HAO | WDD6: ACTIF CIRCULANT HAO | WDL6: ACTIF CIRCULANT HAO | WDT6: ACTIF CIRCULANT HAO | WEB6: ACTIF CIRCULANT HAO | WEJ6: ACTIF CIRCULANT HAO | WER6: ACTIF CIRCULANT HAO | WEZ6: ACTIF CIRCULANT HAO | WFH6: ACTIF CIRCULANT HAO | WFP6: ACTIF CIRCULANT HAO | WFX6: ACTIF CIRCULANT HAO | WGF6: ACTIF CIRCULANT HAO | WGN6: ACTIF CIRCULANT HAO | WGV6: ACTIF CIRCULANT HAO | WHD6: ACTIF CIRCULANT HAO | WHL6: ACTIF CIRCULANT HAO | WHT6: ACTIF CIRCULANT HAO | WIB6: ACTIF CIRCULANT HAO | WIJ6: ACTIF CIRCULANT HAO | WIR6: ACTIF CIRCULANT HAO | WIZ6: ACTIF CIRCULANT HAO | WJH6: ACTIF CIRCULANT HAO | WJP6: ACTIF CIRCULANT HAO | WJX6: ACTIF CIRCULANT HAO | WKF6: ACTIF CIRCULANT HAO | WKN6: ACTIF CIRCULANT HAO | WKV6: ACTIF CIRCULANT HAO | WLD6: ACTIF CIRCULANT HAO | WLL6: ACTIF CIRCULANT HAO | WLT6: ACTIF CIRCULANT HAO | WMB6: ACTIF CIRCULANT HAO | WMJ6: ACTIF CIRCULANT HAO | WMR6: ACTIF CIRCULANT HAO | WMZ6: ACTIF CIRCULANT HAO | WNH6: ACTIF CIRCULANT HAO | WNP6: ACTIF CIRCULANT HAO | WNX6: ACTIF CIRCULANT HAO | WOF6: ACTIF CIRCULANT HAO | WON6: ACTIF CIRCULANT HAO | WOV6: ACTIF CIRCULANT HAO | WPD6: ACTIF CIRCULANT HAO | WPL6: ACTIF CIRCULANT HAO | WPT6: ACTIF CIRCULANT HAO | WQB6: ACTIF CIRCULANT HAO | WQJ6: ACTIF CIRCULANT HAO | WQR6: ACTIF CIRCULANT HAO | WQZ6: ACTIF CIRCULANT HAO | WRH6: ACTIF CIRCULANT HAO | WRP6: ACTIF CIRCULANT HAO | WRX6: ACTIF CIRCULANT HAO | WSF6: ACTIF CIRCULANT HAO | WSN6: ACTIF CIRCULANT HAO | WSV6: ACTIF CIRCULANT HAO | WTD6: ACTIF CIRCULANT HAO | WTL6: ACTIF CIRCULANT HAO | WTT6: ACTIF CIRCULANT HAO | WUB6: ACTIF CIRCULANT HAO | WUJ6: ACTIF CIRCULANT HAO | WUR6: ACTIF CIRCULANT HAO | WUZ6: ACTIF CIRCULANT HAO | WVH6: ACTIF CIRCULANT HAO | WVP6: ACTIF CIRCULANT HAO | WVX6: ACTIF CIRCULANT HAO | WWF6: ACTIF CIRCULANT HAO | WWN6: ACTIF CIRCULANT HAO | WWV6: ACTIF CIRCULANT HAO | WXD6: ACTIF CIRCULANT HAO | WXL6: ACTIF CIRCULANT HAO | WXT6: ACTIF CIRCULANT HAO | WYB6: ACTIF CIRCULANT HAO | WYJ6: ACTIF CIRCULANT HAO | WYR6: ACTIF CIRCULANT HAO | WYZ6: ACTIF CIRCULANT HAO | WZH6: ACTIF CIRCULANT HAO | WZP6: ACTIF CIRCULANT HAO | WZX6: ACTIF CIRCULANT HAO | XAF6: ACTIF CIRCULANT HAO | XAN6: ACTIF CIRCULANT HAO | XAV6: ACTIF CIRCULANT HAO | XBD6: ACTIF CIRCULANT HAO | XBL6: ACTIF CIRCULANT HAO | XBT6: ACTIF CIRCULANT HAO | XCB6: ACTIF CIRCULANT HAO | XCJ6: ACTIF CIRCULANT HAO | XCR6: ACTIF CIRCULANT HAO | XCZ6: ACTIF CIRCULANT HAO | XDH6: ACTIF CIRCULANT HAO | XDP6: ACTIF CIRCULANT HAO | XDX6: ACTIF CIRCULANT HAO | XEF6: ACTIF CIRCULANT HAO | XEN6: ACTIF CIRCULANT HAO | XEV6: ACTIF CIRCULANT HAO
A8: LIBELLES | B8: ANNEE N | C8: ANNEE N-1 | D8: Variation en %
A10: Créances sur cessions d'immobilisations
A11: Autres créances hors activités ordinaires
A12: TOTAL BRUT
A13: Dépréciations des créances HAO
A14: TOTAL NET DE DEPRECIATION
A15: Commentaire :
A16: · Commenter touter variation significative
A17: · Dépréciation : indiquer les évènements et les circonstances qui ont motivé
A18: la dépréciation ou la reprise
A20: DETTES CIRCULANTES HAO
A22: LIBELLES | B22: ANNEE N | D22: ANNEE N-1 | F22: VARIATION EN %
A24: Fournisseurs d'investissements
A25: Fournisseurs d'investissements effets à payer
A26: Versements restant à effectuer sur titres de participation et titres immobilisés non libérés
A27: Autres dettes hors activités ordinaires
A28: TOTAL
A29: Commentaire :
A30: · Indiquer la date de cession et la nature de l'immobilisation achétée et/ou cédée
A31: · Expliquer toute variation significative

Sheet Note 6
A1: NOTE 6 : STOCKS ET ENCOURS(1)
A3: Désignation entité : | C3: Excercice clos le : | D3: =+'Note 1'!E3 -> 45657
A4: =+'Note 1'!A4 -> Sabodala Gold Operations S.A | C4: Durée en mois : | D4: =+'Note 1'!E4 -> 12
A5: Numéro d'identification : | B5: =+'Note 1'!B5 -> 002850023
A7: LIBELLES | B7: ANNEE N | C7: ANNEE N-1 | D7: VARIATION EN %
A9: Marchandises
A10: Matières premières et fournitures liées
A11: Autres approvisionnements | B11: 3.1149011e+10 | C11: 2.2131527e+10 | D11: 0.40744972
A12: Produits en cours | B12: 5.7428941e+09 | C12: 2.7401716e+09 | D12: 1.0958155
A13: Services en cours
A14: Produits finis | B14: 2.6597853e+09 | C14: 1.6907999e+09 | D14: 0.57309287
A15: Produits intermédiaires | B15: 1.1302033e+11 | C15: 9.9584492e+10 | D15: 0.13491897
A16: Stocks en cours de route, en consignation ou en dépôt | B16: 5.1475143e+09 | C16: 3.1658945e+09 | D16: 0.62592729
A17: TOTAL BRUT STOCKS ET EN COURS | B17: 1.5771953e+11 | C17: 1.2931289e+11 | D17: 0.21369434
A18: Dépréciations des stocks | B18: 9662924522 | C18: 9.4467527e+09 | D18: 0.022883185
A20: Total net de dépréciation | B20: 1.4805661e+11 | C20: 1.1986613e+11 | D20: 0.23518301
A21: (1) : Les stocks HAO seront inscrits dans l'actif circulant HAO que lorsque leur montant total est significatif
A22: (supérieur à 5% du total de l'actif circulant)
A23: Commentaire :
A24: L’or en cours de production et le minerai sont mesurés physiquement ou estimés et évalués au montant le plus faible entre leur coût C et leur valeur nette de réalisation. Le coût C représente le coût moyen pondéré des stocks de minerai et d’or. Celui-ci est constitué des coûts directs de production, ainsi que de l'allocation d’une part des coûts indirects de production fixes et variables. Ces derniers comprennent la dotation aux amortissements des immobilisations utilisées dans le processus de production, ainsi que les dotations aux amortissements de coûts de décapage différés. Les autres stocks, constitués des stocks d’approvisionnement (essentiellement pièces détachées, Divers consommables et produits chimiques), ont été inscrits en comptabilité sur la base de leur valeur d’inventaire. La méthode comptable utilisée est l'inventaire permanent et les sorties sont évaluées au cout unitaire moyen pondéré (CUMP). La provision pour stocks obsolètes à fin 2023 de FCFA 9.446 M a été reconduite et compléter par une nouvelle provision de FCFA 216 millions comptabilisée au 31.12.2024 suite à une revue détaillée. Le stock de minerai a connu une hausse de +13% au 31-12-2024 comparé au stock à la même période l'exercice précédent. Le stock d'or (Produits destinés à la vente) a augmenté de +57% à fin Décembre 2024 . Ce qui entraine une augmentation des produits en cours de +110% ainsi que les stocks des autres fournitures et consommables de 41%.

Sheet Note 7
A1: NOTE 7 : CLIENTS
A3: Désignation entité : | E3: Excercice clos le : | F3: =+'Note 1'!E3 -> 45657
A4: =+'Note 1'!A4 -> Sabodala Gold Operations S.A | E4: Durée en mois : | F4: =+'Note 1'!E4 -> 12
A5: Numéro d'identification : | B5: =+'Note 1'!B5 -> 002850023
A7: LIBELLES | B7: ANNEE N | C7: ANNEE N-1 | D7: Variation en % | E7: Créances à un an au plus | F7: Créances à plus d'un an et à deux ans au plus | G7: Créances à plus de deux ans
A9: Clients (hors réserves de propriété Groupe) | B9: 23110053 | C9: 4.3422323e+09 | D9: -0.99467784 | E9: 23110053
A10: Clients effets à recevoir (hors réserves de propriété Groupe)
A11: Clients effets à recevoir avec réserves de propriété
A12: Clients et effets à recevoir Groupe
A13: Créances sur cession d'immobilisations
A14: Clients effets escomptés et non échus
A15: Créances litigieuses ou douteuses
A16: Clients produits à recevoir | B16: 2.0073212e+08 | C16: 1.0722816e+08 | D16: 0.87200942 | E16: 2.0073212e+08
A17: TOTAL BRUT CLIENTS | B17: 2.2384217e+08 | C17: 4.4494604e+09 | D17: -0.94969229 | E17: 2.2384217e+08
A18: Dépréciations des comptes clients
A19: TOTAL NET DE DEPRECIATION | B19: 2.2384217e+08 | C19: 4.4494604e+09 | D19: -0.94969229 | E19: 2.2384217e+08
A20: Clients, avances reçues hors groupe
A21: Clients, avances reçues groupe
A22: Autres clients créditeurs
A23: TOTAL CLIENTS CREDITEURS
A24: Commentaire :
A25: Les créances sont évaluées à leur valeur nominale. En raison du contrat commercial liant SGO à son client principal, les créances ne sont pas provisionnées. Les créances en devises ont été réévaluées au cours de change de clôture. Les exportations sont effectuées au cours spot de l’once d’or coté sur le marché London Bullion Market Association (« LBMA ») de Londres. Cette méthode a été approuvée par la Direction des Mines et de la Géologie.
A26: Le solde du compte client au 31.12.2024 est constitué par les creances non encore reglees des clients locaux et etrangers
A27: Le compte Clients produits à recevoir est consituté des refacturation de charges.

Sheet Note 8
A1: NOTE 8 : AUTRES CREANCES
A3: Désignation entité : | E3: Excercice clos le : | F3: =+'Note 1'!E3 -> 45657
A4: =+'Note 1'!A4 -> Sabodala Gold Operations S.A | E4: Durée en mois : | F4: =+'Note 1'!E4 -> 12
A5: Numéro d'identification : | B5: =+'Note 1'!B5 -> 002850023
A7: LIBELLES | B7: ANNEE N | C7: ANNEE N- | D7: Variation en % | E7: Créances à un an au plus | F7: Créances à plus d'un an et à deux ans au plus | G7: Créances à plus de deux ans
A9: Personnel | B9: 1.1416819e+08 | C9: 63402814 | D9: 0.80068014 | E9: 1.1416819e+08
A10: Organismes sociaux | B10: 2.4233711e+08 | C10: 23085514 | D10: 9.4973666 | E10: 2.4233711e+08
A11: Etat et collectivités publiques | B11: 1.6795845e+10 | C11: 3.1593541e+10 | D11: -0.46837725 | E11: 1.6795845e+10
A12: Organismes internationaux
A13: Apporteurs, associés et Groupe | B13: 2.446278e+10 | C13: 2.4507565e+10 | D13: -0.0018273985 | E13: 2.446278e+10
A14: Compte transitoire ajustement spécial lié à la révision du SYSCOHADA
A15: Autres débiteurs divers | B15: 1.1947117e+09 | C15: 1.1993629e+09 | D15: -0.0038780796 | E15: 1.1947117e+09
A16: Comptes permanents non bloqués des établissements et des succursales
A17: Comptes de liaison charges et produits
A18: Comptes de liaison des sociétés en participation
A19: TOTAL BRUT AUTRES CREANCES | B19: 4.2809842e+10 | C19: 5.7386957e+10 | D19: -0.25401443 | E19: 4.2809842e+10
A20: Dépréciations des autres créances
A21: TOTAL NET DE DEPRECIATION | B21: 4.2809842e+10 | C21: 5.7386957e+10 | D21: -0.25401443 | E21: 4.2809842e+10
A22: Commentaire :
A23: Ce poste a connu une variation globale à la baisse de -25% soit FCFA - 14 577 M qui s'explique comme suit : - Etat et collectivités publiques : FCFA +14 798 M relatif aux Crédits de TVA - Personnel, Acomptes sur salaires locaux : FCFA +58 M - Personnel, avances su frais de déplacement : FCFA -7 M - Apporteurs, Associés Groupe: FCFA -45 M, dû principalement au compte courant débiteur SMC - Charges constatées d'avance : FCFA - 5M

Sheet Note 8A
A1: NOTE 8 A: TABLEAU D'ETALEMENT DES CHARGES IMMOBILISEES
A3: Désignation entité : | E3: Excercice clos le : | F3: =+'Note 1'!E3 -> 45657
A4: =+'Note 1'!A4 -> Sabodala Gold Operations S.A | E4: Durée en mois : | F4: =+'Note 1'!E4 -> 12
A5: Numéro d'identification : | B5: =+'Note 1'!B5 -> 002850023
A7: LIBELLES | B7: Frais d'établissement | D7: Charges à répartir sur plusiers exercices | F7: Primes de remboursement des obligations
A9: Montant global à étaler au 1er janvier 2018
A10: Durée d'étalement retenue
B11: Comptes | C11: Montants | D11: Comptes | E11: Montants | F11: Comptes | G11: Montants
A12: Exercice 2018 | B12: 60… | D12: 60… | F12: 6714
B13: 61… | D13: 61…
B14: 62… | D14: 62…
B15: 63… | D15: 63…
B16: … | D16: …
A17: Total exercice 2018
A18: Total exercice 2019
A19: Total exercice 2020
A20: Total exercice 2021
A21: Total exercice 2022
A22: TOTAL GENERAL

Sheet Note 9
A1: NOTE 9 : TITRES DE PLACEMENT
A3: Désignation entité : | C3: Excercice clos le :
A4: =+'Note 1'!A4 -> Sabodala Gold Operations S.A | C4: Durée en mois :
A5: Numéro d'identification :
A7: LIBELLES | B7: ANNEE N | C7: ANNEE N-1 | D7: VARIATION EN %
A9: Titres de trésor et bons de caisse à court terme
A10: Actions
A11: Obligations
A12: Bons de souscription
A13: Titres négociables hors régions
A14: Intérêts courus
A15: Autres valeurs assimilées
A16: TOTAL BRUT TITRES
A17: Dépréciations des titres
A19: TOTAL NET DE DEPRECIATION
A20: Commentaire :
A21: · Justifier toutes variations significatives
... A25: · Indiquer les évènements et les circonstances qui ont conduit à la dépréciation et à la reprise

Sheet Note 10
A1: NOTE 10 : VALEURS A ENCAISSER
A3: Désignation entité : | C3: Excercice clos le : | D3: =+'Note 1'!E3 -> 45657
A4: =+'Note 1'!A4 -> Sabodala Gold Operations S.A | C4: Durée en mois : | D4: =+'Note 1'!E4 -> 12
A5: Numéro d'identification : | B5: =+'Note 1'!B5 -> 002850023
A7: LIBELLES | B7: ANNEE N | C7: ANNEE N-1 | D7: VARIATION EN %
A9: Effets à encaisser
A10: Effets à l'encaissement
A11: Chèques à encaisser
A12: Chèques à l'encaissement
A13: Cartes de crédit à encaisser
A14: Autres valeurs à encaisser | B14: 1729831521 | C14: 945599580 | D14: 0.82934887
A15: TOTAL BRUT VALEURS A ENCAISSER | B15: 1729831521 | C15: 945599580 | D15: 0.82934887
A16: Dépréciations des valeurs à encaisser
A18: TOTAL NET DE DEPRECIATION | B18: 1729831521 | C18: 945599580 | D18: 0.82934887
A19: Commentaire :
A20: Il s'agit de Certificat de détaxes en portefeuille, non encore utilisés au 31.12.2024. Ce poste a connu une hausse de 83% soit un montant XOF de 784millions.

Sheet Note 11
A1: NOTE 11 : DISPONIBILITES
A3: Désignation entité : | C3: Excercice clos le : | D3: =+'Note 1'!E3 -> 45657
A4: =+'Note 1'!A4 -> Sabodala Gold Operations S.A | C4: Durée en mois : | D4: =+'Note 1'!E4 -> 12
A5: Numéro d'identification : | B5: =+'Note 1'!B5 -> 002850023
A7: LIBELLES | B7: ANNEE N | C7: ANNEE N-1 | D7: VARIATION EN %
A9: Banques locales | B9: 1.9209787e+10 | C9: 5.3491742e+10 | D9: -0.64088313
A10: Banques autres états région
A11: Banques, dépôt à terme | B11: 0 | C11: 700000000 | D11: -1
A12: Autres banques | B12: 0 | C12: 21804961 | D12: -1
A13: Banques, intérêts courus
A14: Chèques postaux
A15: Autres établissements financiers
A16: Etablissements financiers intérêts courus
A17: Instruments de trésorerie
A18: Caisse | B18: 7328837.7 | C18: 13518935 | D18: -0.45788351
A19: Casse électronique mobile
A20: Régies d'avances et virements accréditifs
A21: TOTAL BRUT DISPONIBILITES | B21: 1.9217116e+10 | C21: 5.4227066e+10 | D21: -0.64561764
A22: Dépréciations
A24: TOTAL NET DE DEPRECIATIONS | B24: 1.9217116e+10 | C24: 5.4227066e+10 | D24: -0.64561764
A25: Commentaire :
A26: Les rapprochements bancaires ainsi que les inventaires des caisses et des instruments de monnaie électronique ont été effectués au 31.12.2024 Les avoirs en banques ont baissé de F CFA 35 000 milliards (65%) au 31-12-2024 La trésorerie a évolué comme suit :
A27: Trésorerie au 01 janvier 2024 : 54 227 M
A28: Flux provenant des activités opérationnelles : +118 348 M
A29: Flux provenant des activités d'investissement : -115 504 M
A30: Flux provenant des activités de financement : - 45 070 M
A31: Trésorerie au 31 décembre 2024 : 19 217 M
A32: Flux de trésorerie provenant des activités opérationnelles : La masse positive de FCFA 118 milliards est essentiellement expliquée par la capacité d’autofinancement globale à hauteur de FCFA 155 milliards, la hausse des stocks de FCFA 28 milliards, la hausse des créances de FCFA 20 milliards, compensées par la variation du passif circulant de FCFA -1,6 milliards.
A33: Flux de trésorerie provenant des activités d'investissement : FCFA -116 milliards : Les décaissements sont essentiellement constitués d’une part par des frais de recherche et de développement à hauteur de FCFA 33 milliards et d’autre part par des capitalisations de dépenses en Immobilisations Corporelles pour FCFA 81 milliards.
A34: Flux de trésorerie provenant des activités de financement : FCFA -45 milliards : Les décaissements sont constitués par une distribution de dividendes à hauteur de 44 milliards FCFA et l'acompte 3,1 Milliards FCFA, de l'emprunt EGC dont le solde au 31 décembe 2024 est de 38 043 milliards FCFA.

Sheet Note 12
A1: NOTE 12 : ECARTS DE CONVERSION
A3: Désignation entité : | E3: Excercice clos le : | F3: =+'Note 1'!E3 -> 45657
A4: =+'Note 1'!A4 -> Sabodala Gold Operations S.A | E4: Durée en mois : | F4: =+'Note 1'!E4 -> 12
A5: Numéro d'identification : | B5: =+'Note 1'!B5 -> 002850023
A7: LIBELLES | B7: Devises | C7: Montant en devises | E7: Cours UML année acquisition | F7: Cours UML 31/12 | G7: Variation en valeur absolue
A9: Ecarts de conversion actif : Détailler les créances et dettes concernées | G9: 8.2707414e+09
A10: I/C SGML TAF | B10: USD | C10: -23880405 | E10: 496.38759 | F10: 633.58887 | G10: -4.2048736e+09
A11: Bonus s/Réserves additionnelles | B11: USD | C11: -2344883.2 | E11: 499 | F11: 633.58887 | G11: -3.1652632e+08
A12: Fournisseurs | B12: USD | C12: -18986470 | F12: 633.58887 | G12: -2.4204791e+08
A13: SGML | B13: USD | C13: -3665781.4 | E13: 531.91 | F13: 633.58887 | G13: -2.9011947e+08
A14: Fond social | B14: USD | C14: -7162404.8 | E14: 451 | F14: 633.58887 | G14: -1.2471731e+09
A15: I/C ECG | B15: USD | C15: -60044779 | E15: 600.78 | F15: 633.58887 | G15: -1.970001e+09
A16: Ecarts de conversion passif : Détailler les créances et dettes concernées
A18: Commentaire :
A19: Les opérations en monnaies étrangères effectuées par SGO sont comptabilisées en appliquant le cours de change en vigueur à la date de l’opération. Lorsque le règlement survient durant l’exercice au cours duquel l’opération a été conclue, la différence de change entre le montant enregistré initialement et le montant effectif du règlement constitue un gain ou une perte entrant dans la formation du résultat de l’exercice. A la date de clôture, les éléments en monnaies étrangères (fournisseurs d’exploitation et d’investissement, clients, dépôts en devises, …) sont évalués en utilisant le cours de change du jour de la transaction. La perte de change latente en résultant est prise en compte dans la détermination du résultat de l’exercice par le biais des provisions pour Risques et Charges. Les gains de change latents ne sont pas enregistrés dans le compte de résultat. La société a décidé d'intégrer dans une position globale de change toutes ses opérations traitées avec l'étranger, non encore dénouées à l'inventaire en opérant une compensation entre les pertes probables et les gains latents pour les dettes et créances à long terme, de même que les dettes et créances à court terme, suivant les dispositions de l'article 57.4 de l'Acte Uniforme.
A23: TRANSFERTS DE CHARGES
A25: LIBELLES | B25: ANNEE N | D25: ANNEE N-1 | F25: VARIATION EN %
A27: Transferts de charges d'exploitation : Détailler la nature des charges transférées | B27: 2.0101757e+10 | D27: 2.0280953e+10 | F27: -0.0088356454
A30: Transferts de charges financières : Détailler la nature des charges transférées
A33: TOTAL | B33: 2.0101757e+10 | D33: 2.0280953e+10 | F33: -0.0088356454
A35: Commentaire :
A36: Les transferts de charges d'exploitation sont constitués principalement de coûts de décapage des fosses, et des refacturations de depenses pour respectivement 16 831 M et 3 271 M soit une baisse de -1% par rapport a l'annee 2023.

Sheet Note 13
A1: NOTE 13 : CAPITAL
A3: Désignation entité : | E3: Excercice clos le : | F3: =+'Note 1'!E3 -> 45657
A4: =+'Note 1'!A4 -> Sabodala Gold Operations S.A | E4: Durée en mois : | F4: =+'Note 1'!E4 -> 12
A5: Numéro d'identification : | B5: =+'Note 1'!B5 -> 002850023
E7: Valeur nominale des actions ou parts : | G7: 10000
A8: NOMS ET PRENOMS | B8: Nationalité | C8: Nature des actions ou parts (ordinaires ou préférences) | E8: Nombre | F8: Montant total | G8: Cessions ou remboursements en cours d'exercice
A10: République du Sénégal | B10: SEN | C10: Ordinaires | E10: 105 | F10: 1050000 | G10: 0
A11: Sabodala Gold (Mauritius) Ltd. | B11: ANG | C11: Ordinaires | E11: 900 | F11: 9000000 | G11: 0
A12: Massawa Jersey Limited | B12: JER | C12: Ordinaires | E12: 45 | F12: 450000 | G12: 0
A18: Apporteurs, capital non appelé
E19: TOTAL | F19: 10500000
A20: Commentaire :
A21: Pas d'évolution en 2024.

Sheet Note 14
A1: NOTE 14 : PRIMES ET RESERVES
A3: Désignation entité : | E3: Excercice clos le : | F3: =+'Note 1'!E3 -> 45657
A4: =+'Note 1'!A4 -> Sabodala Gold Operations S.A | E4: Durée en mois : | F4: =+'Note 1'!E4 -> 12
A5: Numéro d'identification : | B5: =+'Note 1'!B5 -> 002850023
A7: LIBELLES | B7: ANNEE N | D7: ANNEE N-1 | F7: VARIATION EN VALEUR ABSOLUE
A9: Prime d'apport
A10: Primes d'émission
A11: Prime de fusion | B11: 50704413696 | D11: 50704413696 | F11: 0
A12: Primes de conversion
A13: Autres primes
A14: TOTAL PRIMES | B14: 50704413696 | D14: 50704413696 | F14: 0
A16: Réserves légales | B16: 2100000 | D16: 2000000 | F16: 100000
A17: Réserves statutaires
A18: Réserves de plus-values nettes à long terme
A19: Réserves d'attribution gratuite d'actions au personnel salarié et aux dirigeants
A20: Autres réserves réglementées
A21: TOTAL RESERVES INDISPONIBLES | C21: 2100000 | E21: 2000000 | F21: 100000
A23: Réserves libres
A25: Report à nouveau | B25: 420607011591 | D25: 348511721438 | F25: 72095290153
A27: Commentaire :
A28: La variation du Report à Nouveau est constitué de l'affectation du bénéfice de l'exercice 2023 diminué du montant de FCFA 65 milliards de dividendes à distribuer.

Sheet Note 15A
A1: NOTE 15A : SUBVENTIONS ET PROVISIONS REGLEMENTEES
A3: Désignation entité : | E3: Excercice clos le : | F3: =+'Note 1'!E3 -> 45657
A4: =+'Note 1'!A4 -> Sabodala Gold Operations S.A | E4: Durée en mois : | F4: =+'Note 1'!E4 -> 12
A5: Numéro d'identification : | B5: =+'Note 1'!B5 -> 002850023
A7: LIBELLES | B7: NOTE | C7: ANNEE N | D7: ANNEE N-1 | E7: Variation en valeur absolue | F7: Variation en % | G7: Régime fiscal | H7: Échéances
A9: Etat
A10: Régions
A11: Départements
A12: Communes et collectivités publiques décentralisées
A13: Entités publiques ou mixtes
A14: Entités et organismes privés
A15: Organismes internationaux
A16: Autres
A17: TOTAL SUBVENTIONS
A19: Amortissements dérogatoires
A20: Plus-values de cession à réinvestir
A21: Provision spéciale de réévaluation | B21: 3E
A22: Provisions réglementées relatives aux immobilisations
A23: Provisions réglementées relatives aux stocks
A24: Provisions pour investissement
A25: Autres provisions et fonds réglementés
A26: TOTAL PROVISIONS REGLEMENTEES
A28: TOTAL SUBVENTIONS ET PROVISIONS REGLEMENTEES
A30: Commentaire :
A31: Indiquer pour la subvention la date d'octroi, la nature, les obligations éventuelles.
A32: Pour les provisions réglementées, indiquer le texte de référence, les obligations.
A33: Commenter toute variation significative.

Sheet Note 15B
A1: NOTE 15B : AUTRES FONDS PROPRES(1)
A3: Désignation entité : | E3: Excercice clos le : | F3: =+'Note 1'!E3 -> 45657
A4: =+'Note 1'!A4 -> Sabodala Gold Operations S.A | E4: Durée en mois : | F4: =+'Note 1'!E4 -> 12
A5: Numéro d'identification : | B5: =+'Note 1'!B5 -> 002850023
A7: LIBELLES | B7: NOTE | C7: ANNEE N | D7: ANNEE N-1 | E7: Variation en valeur absolue | F7: Variation en % | G7: Échéances
A9: Titres participatifs
A10: Avances conditionnées
A11: Titres subordonnés à durée indéterminée (TSDI)
A12: Obligations remboursables en actions (ORA)
A13: Autres
A14: TOTAL AUTRES FONDS PROPRES
A16: (1) : Le cas échéant, une rubrique "Autres fonds propres" (montant des émissions de titres participatifs,
A17: avances conditionnées,…) sur une ligne séparée est intercalée entre les rubriques
A18: "TOTAL CAPTAUX PROPRES ET RESSOURCES ASSIMILEES" et "EMPRUNTS ET DETTES FINANCIERES" si le
A19: montant des autres fonds propres est significatif.
A21: Commentaire :
A22: · Justifier l'inscription de ces dettes dans une rubrique spécifique du passif du bilan "autres fonds
... A25: · Commenter toute variation significative

Sheet Note 16A
A1: NOTE 16A : DETTES FINANCIERES ET RESSOURCES ASSIMILEES
A3: Désignation entité : | E3: Excercice clos le : | F3: =+'Note 1'!E3 -> 45657
A4: =+'Note 1'!A4 -> Sabodala Gold Operations S.A | D4: Durée en mois : | F4: =+'Note 1'!E4 -> 12
A5: Numéro d'identification : | B5: =+'Note 1'!B5 -> 002850023
A7: LIBELLES | B7: ANNEE N | C7: ANNEE N-1 | D7: Variation en valeur absolue | E7: Variation en % | F7: Dettes à un an au plus | G7: Dettes à plus d'un an et à deux ans au plus | H7: Dettes à plus de deux ans
A9: Emprunts obligataires
A10: Emprunts et dettes auprès des établissements de crédit
A11: Avances reçues de l'Etat
A12: Avances reçues et comptes courants bloqués | B12: -41732566474 | C12: -39946904604 | D12: -1785661870 | E12: 0.044700882 | H12: -41732566474
A13: Dépôts et cautionnements reçus
A14: Intérêts courus
A15: Avances assorties de conditions particulières
A16: Autres emprunts et dettes
A17: Dettes liées à des participations
A18: Comptes permanents bloqués des établissements et succursales
A19: TOTAL EMPRUNTS ET DETTES FINANCIERES | B19: -41732566474 | C19: -39946904604 | D19: -1785661870 | E19: 0.044700882 | H19: -41732566474
A21: Crédit bail immobilier
A22: Crédit bail mobilier | B22: -602418195 | C22: -564997042 | D22: -37421153 | E22: 0.066232476 | H22: -602418195
A23: Location vente
A24: Intérêts courus
A25: Autres dettes de location acquisition
A26: TOTAL DETTES DE LOCATION ACQUISITION | B26: -602418195 | C26: -564997042 | D26: -37421153 | E26: 0.066232476 | H26: -602418195
A28: Provisions pour litiges | B28: -6.4053834e+08 | C28: 0 | D28: -6.4053834e+08 | E28: 1
A29: Provisions pour garantie donnés aux clients
A30: Provisions pour pertes sur marchés à achèvement futur
A31: Provisions pour pertes de change | B31: -3358386287 | C31: -1.0825298e+09 | D31: -2.2758565e+09 | E31: 2.10235
A32: Provisions pour impôts
A33: Provisions pour pensions et obligations assimilées | B33: -6411874286 | C33: -4814725426 | D33: -1597148860 | E33: 0.33172169
A34: Actif du régime de retraite
A35: Provisions pour restructuration
A36: Provisions pour amendes et pénalités
A37: Provisions de propre assureur
A38: Provisions pour démantèlement et remise en état | B38: -22816546745 | C38: -23398984422 | D38: 582437677 | E38: -0.024891579
A39: Provisions de droits à déduction
A40: Autres provisions | B40: -4538019960 | C40: -4052911713 | D40: -485108247 | E40: 0.11969376
A41: TOTAL PROVISIONS POUR RISQUES ET CHARGES | B41: -3.7765366e+10 | C41: -3.3349151e+10 | D41: -4.4162143e+09 | E41: 0.13242359
A43: Commentaire :
A44: Les variations significatives ci-après ont été notés pour ce poste : .FCFA +1 786 M correspondant au prêt interco ECG et de la provision d'intèrêts courus. Le montant de la facilité est de 300 000 000 USD sur 7 ans; . FCFA +2 275 M représente l'ajustement de la provision pour pertes latentes de change à long terme relative à la réévaluation des dettes et créances aux cours de devises à la clôture de l'exercice ; . FCFA +1 597 M correspond à l'ajustement de la provision retraite lié à l'augmentation de l'effectif du personnel en 2024 (évaluation interne, pas de convention avec une compagnie d'assurance retraite) ; . FCFA -582 représente l'ajustement de la provision pour réhabilitation ; . FCFA +485 M correspond à la variation de la provision pour Fonds social . FCFA +640 M représentant le contentieux entre les ex-employés et SGO concernant le rappel des paiements des heures supplémentaires.

Sheet Note 16B
A1: NOTE 16B : ENGAGEMENTS DE RETRAITE ET AVANTAGES ASSIMILES (METHODE ACTUARIELLE)
A3: Désignation entité : | D3: Excercice clos le : | E3: =+'Note 1'!E3 -> 45657
A4: =+'Note 1'!A4 -> Sabodala Gold Operations S.A | D4: Durée en mois : | E4: =+'Note 1'!E4 -> 12
A5: Numéro d'identification : | B5: =+'Note 1'!B5 -> 002850023
A7: HYPOTHESES ACTUARIELLES
A8: LIBELLES | B8: ANNEE N | D8: ANNEE N-1
A9: Taux d'augmentation des salaires
A10: Taux d'actualisation
A11: Taux d'inflation
A12: Probabilité d'être présent dans l'entité à la date de départ à la retraite (expérience passée)
A13: Probabilité d'être en vie à l'âge de départ à la retraite (table de mortalité)
A14: Taux de rendement effectif des actifs du régime
A16: Commentaire :
A17: · Commenter les variations d'hypothèses actuarielles utilisées pour le calcul des
A18: engagements de retraite et avantages assimilés.
A21: VARIATION DE LA VALEUR DE L'ENGAGEMENT DE RETRAITE AU COURS DE L'EXERCICE
A22: LIBELLES | B22: ANNEE N | D22: ANNEE N-1
A23: OBLIGATION AU TITRE DES ENGAGEMENTS DE RETRAITE A L'OUVERTURE
A24: Coût des services rendus au cours de l'exercice
A25: Coût financier
A26: Pertes actuarielles / (gain)
A27: Prestations payées au cours de l'exercice
A28: Coût des services passés
A29: OBLIGATION AU TITRE DES ENGAGEMENTS DE RETRAITE A LA CLÔTURE
A31: Commentaire :
A32: · indiquer le montant de la charge par nature comptabilisée au cours de l'exercice.
A35: ANALYSES DE SENSIBILITE DES HYPOTHESES ACTUARIELLES
A36: LIBELLES | C36: ANNEE N | E36: ANNEE N-1
C37: Augmentation | D37: Diminution | E37: Augmentation | F37: Diminution
A38: Taux d'actualisation (variation de …%)
A39: Taux de progression des salaires (variation de …%)
A40: Taux de départ du personnel (variation de …%)
A42: Commentaire :
A43: · Indiquer l'impact des variations obtenues sur le montant des engagements de retraite.

Sheet Note 16B bis
A1: NOTE 16B bis : ENGAGEMENTS DE RETRAITE ET AVANTAGES ASSIMILES
A3: Désignation entité : | C3: Excercice clos le : | D3: =+'Note 1'!E3 -> 45657
A4: =+'Note 1'!A4 -> Sabodala Gold Operations S.A | C4: Durée en mois :
A5: Numéro d'identification : | D5: =+'Note 1'!E4 -> 12
B6: =+'Note 1'!B5 -> 002850023
A8: ACTIF/PASSIF NET COMPTABILISE AU TITRE DES REGIMES FINANCES
A9: LIBELLES | B9: ANNEE N | C9: ANNEE N-1
A10: Valeur actuelle de l'obligation résultant de régimes financés
A11: Valeur actuelle des actifs affectés aux plans de retraite
A12: Excédent / Déficit de régime
A14: Commentaire :
A15: · indiquer le montant comptabilisé au passif (ou actif) à la clôture de l'exercice.
A18: VALEUR ACTUELLE DES ACTIFS DU REGIME
A19: LIBELLES | B19: ANNEE N | D19: ANNEE N-1
B20: Rendement attendu | C20: Juste valeur des actifs | D20: Rendement attendu | E20: Juste valeur des actifs
A21: Actions
A22: Obligations
A23: Autres
A24: TOTAL
A26: Commentaire :
A27: · Expliquer comment les taux de rendement par catégorie d'actifs et global ont été déterminés.
A28: · Indiquer le montant des rendements réels des actifs affectés aux plans en N et N-1.

Sheet Note 16C
A1: NOTE 16C : ACTIFS ET PASSIFS EVENTUELS
A3: Désignation entité : | C3: Excercice clos le : | D3: =+'Note 1'!E3 -> 45657
A4: =+'Note 1'!A4 -> Sabodala Gold Operations S.A | C4: Durée en mois : | D4: =+'Note 1'!E4 -> 12
A5: Numéro d'identification : | B5: =+'Note 1'!B5 -> 002850023
A8: LIBELLES | C8: ANNEE N | D8: ANNEE N-1
A9: Actif éventuel
A10: Litiges
A11: …………………………..
A12: …………………………..
A13: Passif éventuel
A14: Litiges
A15: …………………………..
A16: …………………………..
A18: Commentaire :
A19: · Décrire les principales caractéristiques des actifs / passifs éventuels, l'horizon de temps auquel
A20: les encaissements / décaissements sont attendus et les éventuels remboursements à percevoir.

Sheet Note 17
A1: NOTE 17 : FOURNISSEURS D'EXPLOITATION
A3: Désignation entité : | E3: Excercice clos le : | F3: =+'Note 1'!E3 -> 45657
A4: =+'Note 1'!A4 -> Sabodala Gold Operations S.A | E4: Durée en mois : | F4: =+'Note 1'!E4 -> 12
A5: Numéro d'identification : | B5: =+'Note 1'!B5 -> 002850023
A7: LIBELLES | B7: ANNEE N | C7: ANNEE N-1 | D7: Variation en % | E7: Dettes à un an au plus | F7: Dettes à plus d'un an et à deux ans au plus | G7: Dettes à plus de deux ans
A9: Fournisseurs dettes en compte (hors groupe) | B9: -3.4847678e+10 | C9: -3.5242009e+10 | D9: -0.011189245 | E9: -3.4847678e+10
A10: Fournisseurs effets à payer (hors groupe)
A11: Fournisseurs, dettes et effets à payer (groupe)
A12: Fournisseurs, factures non parvenues (hors groupe) | B12: -1.0777668e+10 | C12: -8.9436372e+09 | D12: 0.20506544 | E12: -1.0777668e+10
A13: Fournisseurs, factures non parvenues (groupe)
A14: TOTAL FOURNISSEURS | B14: -4.5625346e+10 | C14: -4.4185646e+10 | D14: 0.032582966 | E14: -4.5625346e+10
A16: Fournisseurs, avances et acomptes (hors groupe) | B16: 3.6960548e+09 | C16: 4.5610626e+09 | D16: -0.18965051 | E16: 3.6960548e+09
A17: Fournisseurs, avances et acomptes (groupe)
A18: Autres fournisseurs débiteurs
A19: TOTAL FOURNISSEURS DEBITEURS | B19: 3.6960548e+09 | C19: 4.5610626e+09 | D19: -0.18965051 | E19: 3.6960548e+09
A21: Commentaire :
A22: Les délais de paiement obtenus auprès de nos fournisseurs varient entre 15 jours et 135 jours. La majorité des fournisseurs est payée à 30 jours. Cependant, quelques uns d'entre eux sont payés d'avance partiellement ou parfois intégralement, dû à la spécificité de leurs produits. Le solde des comptes Fournisseurs locaux au 31.12.2024 a connu une augmentation de FCFA 4 945 M comparé au solde au 31.12.2023. De meme , le solde des comptes Fournisseurs Etrangers et le solde des factures fournisseurs a recevoir ont connu une hausse de respectivement FCFA 5 340 M et FCFA 1 834 M.

Sheet Note 18
A1: NOTE 18 : DETTES FISCALES ET SOCIALES
A3: Désignation entité : | F3: Excercice clos le : | G3: =+'Note 1'!E3 -> 45657
A4: =+'Note 1'!A4 -> Sabodala Gold Operations S.A | F4: Durée en mois : | G4: =+'Note 1'!E4 -> 12
A5: Numéro d'identification : | B5: =+'Note 1'!B5 -> 002850023
A7: LIBELLES | B7: ANNEE N | C7: ANNEE N-1 | D7: Variation en valeur absolue | E7: Variation en % | F7: Dettes à un an au plus | G7: Dettes à plus d'un an et à deux ans au plus | H7: Dettes à plus de deux ans
A9: Personnel congés à payer | B9: -1.3923847e+09 | D9: -1.3923847e+09 | F9: -1.3923847e+09
A10: Personnel rémunérations dues | B10: -19324458 | C10: -6023304 | D10: -13301154 | E10: 2.208282 | F10: -19324458
A11: Autres personnel | B11: -2.376765e+09 | C11: -7.9066882e+08 | D11: -1.5860962e+09 | E11: 2.0060184 | F11: -2.376765e+09
A12: Caisse de sécurité sociale | B12: -1.0283612e+08 | C12: -96200225 | D12: -6635890.6 | E12: 0.06897999 | F12: -1.0283612e+08
A13: Caisse de retraite | D13: 0
A14: Autres organismes sociaux | D14: 0
A15: TOTAL DETTES SOCIALES | B15: -3.8913102e+09 | C15: -8.9289235e+08 | D15: -2.9984179e+09 | E15: 3.3580956 | F15: -3.8913102e+09
A17: Etat, impôts sur les bénéfices | B17: -2.0798922e+10 | C17: -46107479550 | D17: 2.5308558e+10 | E17: -0.54890352 | F17: -2.0798922e+10
A18: Etat, impôts et taxes | B18: -3.295992e+09 | C18: -4195613915 | D18: 8.9962195e+08 | E18: -0.21441962 | F18: -3.295992e+09
A19: Etat, TVA | B19: -2.245411e+08 | C19: -6.7610484e+08 | D19: 4.5156374e+08 | E19: -0.66789012 | F19: -2.245411e+08
A20: Etat, impôts retenus à la source | B20: -7.8261786e+08 | C20: -6.181197e+08 | D20: -1.6449816e+08 | E20: 0.26612671 | F20: -7.8261786e+08
A21: Autres dettes Etat | B21: -9.7008699e+09 | C21: -2.0429024e+10 | D21: 1.0728155e+10 | E21: -0.52514277 | F21: -9.7008699e+09
A22: TOTAL DETTES FISCALES | B22: -3.4802943e+10 | C22: -7.2026342e+10 | D22: 3.72234e+10 | E22: -0.51680258 | F22: -3.4802943e+10
A24: TOTAL DETTES SOCIALES ET FISCALES | B24: -3.8694253e+10 | C24: -7.2919235e+10 | D24: 3.4224982e+10 | E24: -0.47155071 | F24: -3.8694253e+10
A26: Commentaire :
A27: Une augmentation globale de +47% de ce poste qui s'explique par l'effet combiné de : . Importante augmentation des dettes sociales de FCFA +2 998 M principalement liée aux charges à payer dont le reliquat de 40% des heures supplementaires, . baisse de l'IS de FCFA -25 309 M due à la baisse du bénéfice réalisé, aux deductions et reintegrations pour la determination du resultat fiscal, . variation a la baisse des impôts et taxes de FCFA -900 M,due prinipalement a la CFCE de 2022 a 2024 a payer de +2 315 M,la patentede 2024 deja payee pour un montant de -2 345 M, . baisse de la TVA pour compte et de la TVA collectée de FCFA -451 M, . hausse des Impôts retenus à la source de FCFA +164 M, . baisse des Autres Dettes fiscales de FCFA -10 728 M en raison des paiements de la retenue IRVM sur dividendes +3 000M et à l'amende douanière + 8 000M.

Sheet Note 19
A1: NOTE 19 : AUTRES DETTES ET PROVISIONS POUR RISQUES A COURT TERME
A3: Désignation entité : | F3: Excercice clos le : | G3: =+'Note 1'!E3 -> 45657
A4: =+'Note 1'!A4 -> Sabodala Gold Operations S.A | F4: Durée en mois : | G4: =+'Note 1'!E4 -> 12
A5: Numéro d'identification : | B5: =+'Note 1'!B5 -> 002850023
A7: LIBELLES | B7: ANNEE N | C7: ANNEE N-1 | D7: Variation en valeur absolue | E7: Variation en % | F7: Dettes à un an au plus | G7: Dettes à plus d'un an et à deux ans au plus | H7: Dettes à plus de deux ans
A9: Organismes internationaux
A11: Apporteurs, opérations sur le capital
A12: Associés, compte courant | B12: -1.6850538e+10 | C12: -1.5748327e+10 | D12: -1.1022118e+09 | E12: 0.069989137 | F12: -1.6850538e+10
A13: Associés, dividendes à payer | B13: -5.0613329e+10 | C13: -27000000000 | D13: -2.3613329e+10 | E13: 0.87456774 | F13: -5.0613329e+10
A14: Groupe, comptes courants
A15: Autres dettes associés | B15: -9.1242683e+08 | C15: -3.5334659e+08 | D15: -3.5334659e+08 | E15: 1.5822432 | F15: -9.1242683e+08
A16: TOTAL DETTES ASSOCIES | B16: -6.8376294e+10 | C16: -4.3101673e+10 | D16: -2.376417e+08 | E16: 0.58639536 | F16: -6.8376294e+10
A18: Créditeurs divers
A19: Obligataires
A20: Rémunérations d'administrateurs
A21: Compte du factor
A22: Versements restant à effectuer sur titres de placements non libérés
A23: Compte transitoire ajustement spécial lié à la révision du SYSCOHADA
A24: Autres créditeurs divers
A25: TOTAL CREDITEURS DIVERS
A27: Comptes permanents non bloqués des établissements et des succursales
A28: Comptes de liaison charges et produits
A29: Comptes de liaison des sociétés en participation
A30: TOTAL COMPTES DE LIAISON
A32: TOTAL AUTRES DETTES | B32: -6.8376294e+10 | C32: -4.3101673e+10 | D32: -2.5274621e+10 | E32: 0.58639536 | F32: -6.8376294e+10
A34: Provisions pour risques à court terme (voir note 28) | B34: -4.9123551e+09 | C34: -3.5306801e+09 | D34: -1.381675e+09 | E34: 0.39133395 | F34: -4.9123551e+09
A36: Commentaire :
A37: Le poste "Associés, comptes courants" enregistre les montants dus à l'actionnaire SGML qui ont connu une hausse legere de FCFA + 1 102 M.
A38: Reliquat dividendes 2023 SGML de FCFA 26 337M à payer
A39: La ligne "Provisions pour risques à court terme" concerne la Provision pour pertes latentes de change pour FCFA 4 912 M

Sheet Note 20
A1: NOTE 20 : BANQUES, CREDIT D'ESCOMPTE ET TRESORERIE
A3: Désignation entité : | C3: Excercice clos le : | D3: =+'Note 1'!E3 -> 45657
A4: =+'Note 1'!A4 -> Sabodala Gold Operations S.A | C4: Durée en mois : | D4: =+'Note 1'!E4 -> 12
A5: Numéro d'identification : | B5: =+'Note 1'!B5 -> 002850023
A7: LIBELLES | B7: ANNEE N | C7: ANNEE N-1 | D7: VARIATION EN %
A9: Escomptes de crédit de campagne
A10: Escomptes de crédit ordinaires
A11: TOTAL BANQUES, CREDITS D'ESCOMPTE ET DE TRESORERIE
A13: Banques locales | B13: -8000000000 | C13: 154577 | D13: -51755.142
A14: Banques autres états régions
A15: Autres banques
A16: Banques intérêts courus
A17: Crédits de trésorerie
A18: TOTAL BANQUES, CREDITS DE TRESORERIE | B18: -8000000000 | C18: 154577 | D18: -51755.142
A20: TOTAL GENERAL | B20: -8000000000 | C20: 154577 | D20: -51755.142
A22: Ce poste est créditeur en raison du credit de tresorerie a court terme obtenu de la banque locale Ecobank.

Sheet Note 21
A1: NOTE 21 : CHIFFRE D'AFFAIRES ET AUTRES PRODUITS
A3: Désignation entité : | C3: Excercice clos le : | D3: =+'Note 1'!E3 -> 45657
A4: =+'Note 1'!A4 -> Sabodala Gold Operations S.A | C4: Durée en mois : | D4: =+'Note 1'!E4 -> 12
A5: Numéro d'identification : | B5: =+'Note 1'!B5 -> 002850023
A7: LIBELLES | B7: ANNEE N | C7: ANNEE N-1 | D7: VARIATION EN %
A9: Ventes dans la région
A10: Ventes hors région
A11: Ventes Groupe
A12: Ventes sur internet
A13: TOTAL VENTES MARCHANDISES
A14: Ventes dans l'Etat partie | B14: 11805992800 | C14: 9494006760 | D14: 0.24352058
A15: Ventes dans la région
A16: Ventes hors région | B16: 325356700435 | C16: 3.4458132e+11 | D16: -0.055791248
A17: Ventes Groupe
A18: Ventes sur internet
A19: TOTAL VENTES DE PRODUITS FABRIQUES | B19: 337162693235 | C19: 3.5407533e+11 | D19: -0.047765643
A20: Ventes dans l'Etat partie
A21: Ventes dans la région
A22: Ventes hors région
A23: Ventes Groupe
A24: Ventes sur internet
A25: TOTAL VENTES DE TRAVAUX ET SERVICES VENDUS
A27: Produits accessoires
A30: TOTAL CHIFFRE D'AFFAIRES | B30: 337162693235 | C30: 3.5407533e+11 | D30: -0.098956953
A32: Production immobilisée
A33: Subventions d'exploitation
A34: Autres produits | B34: 9.7362148e+09 | C34: 2.444924e+10 | D34: -0.60177842
A35: TOTAL AUTRES PRODUITS | B35: 9.7362148e+09 | C35: 2.444924e+10 | D35: -0.60177842
A37: TOTAL | B37: 3.4689891e+11 | C37: 3.7852457e+11 | D37: -0.083549823
A39: Commentaire :
A40: . La production de l’exercice 2024 a totalisé 229k onces en baisse de 28% par rapport à l’année 2022 (294k onces), ce qui se traduit par une baisse en valeur des ventes d'or passant de FCFA 354 milliards en 2023 à FCFA 337 milliards au 31-12-2024 (soit -5%) . La baisse des "Autres Produits" de FCFA -14 713 M s’explique par les variations suivantes : - le paiement de l’amende fiscale de FCFA -14 000M (Importante provision qui était reprise en 2023) - des produits divers de FCFA +630M - des autres produits de FCFA +359M soit 7% - reprise provision sur risques à CT comptes Etat de FCFA -401M

Sheet Note 22
A1: NOTE 22 : ACHATS
A3: Désignation entité : | C3: Excercice clos le : | D3: =+'Note 1'!E3 -> 45657
A4: =+'Note 1'!A4 -> Sabodala Gold Operations S.A | C4: Durée en mois : | D4: =+'Note 1'!E4 -> 12
A5: Numéro d'identification : | B5: =+'Note 1'!B5 -> 002850023
A7: LIBELLES | B7: ANNEE N | C7: ANNEE N-1 | D7: VARIATION EN %
A9: Achats dans la région
A10: Achats hors région
A11: Achats Groupe
A12: TOTAL ACHATS DE MARCHANDISES
A14: Achats dans la région
A15: Achats hors région
A16: Achats Groupe
A17: TOTAL ACHATS MATIERES PREMIERES ET FOURNITURES LEES
A19: Matières consommables | B19: -2.0520595e+10 | C19: -7691554227 | D19: 1.6679387
A20: Matières combustibles | B20: -2.0678348e+10 | C20: -14796514390 | D20: 0.3975148
A21: Produits d'entretien | B21: -5.1644765e+08 | C21: -437991655 | D21: 0.17912668
A22: Fournitures d'atelier, d'usine et de magasin | B22: -2.6604533e+10 | C22: -23788931669 | D22: 0.11835762
A23: Eau
A24: Electricité | B24: -18344564 | C24: -18615410 | D24: -0.01454958
A25: Autres énergies | B25: -2.007035e+10 | C25: -17816774236 | D25: 0.12648621
A26: Fournitures d'entretien
A27: Fourniture de bureau | B27: -1.9448766e+09 | C27: -1476491524 | D27: 0.31722845
A28: Petit matériel et outillages | B28: -9.6049525e+08 | C28: -725786591 | D28: 0.53691293
A29: Achats d'études, prestations de services, de travaux matériels et équipements | B29: -6.9449366e+09 | C29: -4435987847 | D29: 0.53065367
A30: Achats d'emballages
A31: Frais sur achats | B31: -11357177 | C31: -175592478 | D31: -0.93532083
A32: Remises rabais, remises et ristournes
A33: TOTAL AUTRES ACHATS | B33: -9.8270284e+10 | C33: -71364240027 | D33: 0.37702418
A35: Commentaire :
A36: Variation Autres achats : + 26 906 M, soit +38% par rapport à 2023.
A37: . Matières consommables : FCFA +12 829 M dont : Achats consommables- stock en transit de 3 274 M et des achats de consommables refactures aux partenaires pour 5 575 M
A38: . Fournitures d'atelier, d'usine et de magasin FCFA + 2 815 M
A39: . Autres énergies : FCFA + 2 254 M (Gasoil lourd)
A40: . Fournitures de bureau : FCFA +468 M
A41: . Achats d'études, prestations de services, de travaux matériel et équipements : FCFA +2 354 M
A42: . Petit materiel et outillage : FCFA +390 M
A43: . Matieres combustibles : FCFA +5 881 M

Sheet Note 23
A1: NOTE 23 : TRANSPORTS
A3: Désignation entité : | C3: Excercice clos le : | D3: =+'Note 1'!E3 -> 45657
A4: =+'Note 1'!A4 -> Sabodala Gold Operations S.A | C4: Durée en mois : | D4: =+'Note 1'!E4 -> 12
A5: Numéro d'identification : | B5: =+'Note 1'!B5 -> 002850023
A7: LIBELLES | B7: ANNEE N | C7: ANNEE N-1 | D7: VARIATION EN %
A9: Transports sur ventes
A10: Transports pour le compte de tiers
A11: Transports du personnel | B11: -8.7708182e+08 | C11: -675588920 | D11: 0.29899212
A12: Transports de plis | B12: -18412503 | C12: -16344734 | D12: 0.12650977
A13: Autres transports | B13: -1.6291725e+09 | C13: -1196954117 | D13: 0.36109855
A14: TOTAL | B14: -2.5246668e+09 | C14: -1888887771 | D14: 0.33685534
A16: Commentaire :
A17: Ce poste a connu une hausse de +34% soit FCFA +636M liée à l'augmentation des effectifs du personnel.

Sheet Note 24
A1: NOTE 24 : SERVICES EXTERIEURS
A3: Désignation entité : | C3: Excercice clos le : | D3: =+'Note 1'!E3 -> 45657
A4: =+'Note 1'!A4 -> Sabodala Gold Operations S.A | C4: Durée en mois : | D4: =+'Note 1'!E4 -> 12
A5: Numéro d'identification : | B5: =+'Note 1'!B5 -> 002850023
A7: LIBELLES | B7: ANNEE N | C7: ANNEE N-1 | D7: VARIATION EN %
A9: Sous-traitance générale | B9: -1.8972656e+10 | C9: -17061280095 | D9: 0.11203007
A10: Locations et charges locatives | B10: -1.2497731e+09 | C10: -1211667088 | D10: 0.031449269
A11: Redevances de location acquisition
A12: Entretien, réparations et maintenance | B12: -1.5513923e+09 | C12: -1862112689 | D12: -0.16686445
A13: Primes d'assurance | B13: -1.6762672e+09 | C13: -1405741921 | D13: 0.19244308
A14: Etudes, recherches et documentation
A15: Publicité, publications, relations publiques | B15: -71952767 | C15: -75536995 | D15: -0.047449969
A16: Frais de télécommunications | B16: -2.7191972e+08 | C16: -294508466 | D16: -0.076699828
A17: Frais bancaires | B17: -9.4901365e+08 | C17: -701676000 | D17: 0.35249553
A18: Rémunérations d'intermédiaires et de conseils | B18: -3.1303285e+09 | C18: -2574884118 | D18: 0.21571627
A19: Frais de formation du personnel | B19: -3.4587209e+08 | C19: -239023516 | D19: 0.44702119
A20: Redevances pour brevets, licences, logiciels, concession et droits similaires | B20: -4.2185031e+08 | C20: -240802355 | D20: 0.75185294
A21: Cotisations
A22: Autres charges externes | B22: -1.2592475e+08 | C22: -88264488 | D22: 0.42667518
A24: TOTAL | B24: -2.8766951e+10 | C24: -25755497732 | D24: 0.11692467
A26: Commentaire :
A27: Une hausse de ce poste de FCFA + 3 011 M soit 12% a été constatée, principalement due à la varation des différentes rubriques ci-après :
A28: . augmentation de 11% des coûts de sous-traitance soit FCFA +1 911 M
A29: . Augmentation de 19% de la Prime d'assurance soit FCFA +271 M
A30: . Augmentation des redevances de 75% soit FCFA +181 M
A31: . Augmentation des autres charges externes de 43% soit FCFA +38 M
A32: . Frais bancaires , hausse de 35% soit FCFA +247M

Sheet Note 25
A1: NOTE 25 : IMPOTS ET TAXES
A3: Désignation entité : | C3: Excercice clos le : | D3: =+'Note 1'!E3 -> 45657
A4: =+'Note 1'!A4 -> Sabodala Gold Operations S.A | C4: Durée en mois : | D4: =+'Note 1'!E4 -> 12
A5: Numéro d'identification : | B5: =+'Note 1'!B5 -> 002850023
A7: LIBELLES | B7: ANNEE N | C7: ANNEE N-1 | D7: VARIATION EN %
A9: Impôts et taxes directs | B9: -2.23954e+10 | C9: -2.4129057e+10 | D9: -0.071849346
A10: Impôts et taxes indirects | B10: -41367306 | C10: -18293217 | D10: 1.2613467
A11: Droits d'enregistrement
A12: Pénalités et amendes fiscales | B12: -250595994 | C12: -16040056020 | D12: -0.98437686
A13: Autres impôts et taxes | B13: -4.6447674e+08 | C13: -3822052464 | D13: -0.87847452
A15: TOTAL | B15: -2.315184e+10 | C15: -4.4009459e+10 | D15: -0.47393491
A17: Commentaire :
A18: Importante baisse de -47% soit FCFA -20 858 M dont :
A19: .Paiement du Redressement Contribution Patentes 2023 : +FCFA 2 831M
A20: . Paiement Pénalités et amendes fiscales 2023 : FCFA +16 000 M dont amendes fiscales FCFA 8 040M et amendes douaniéres FCFA 8 000M
A21: . Autres impots et taxes : baisse de -3 424 M. dont IRVM (129M)

Sheet Note 26
A1: NOTE 26 : AUTRES CHARGES
A3: Désignation entité : | C3: Excercice clos le : | D3: =+'Note 1'!E3 -> 45657
A4: =+'Note 1'!A4 -> Sabodala Gold Operations S.A | C4: Durée en mois : | D4: =+'Note 1'!E4 -> 12
A5: Numéro d'identification : | B5: =+'Note 1'!B5 -> 002850023
A7: LIBELLES | B7: ANNEE N | C7: ANNEE N-1 | D7: VARIATION EN %
A9: Pertes sur créances clients
A10: Pertes sur autres débiteurs | B10: -2.2082968e+09 | C10: -1.620459e+09 | D10: 0.36276011
A11: Quote-part de résultat sur opérations faites en commun
A12: Valeur nette comptable des cessions courantes d'immobilisations
A13: Indemnités de fonction et autres rémunérations d'administrateurs | B13: -38234915 | C13: -38491185 | D13: -0.0066578935
A14: Dons et mécénat | B14: -4.5041162e+09 | C14: -3535420998 | D14: 0.27399714
A15: Autres charges diverses
A16: Charges pour provisions et provisons pour risques à court terme d'exploitation (voir note 28) | B16: -5.1285269e+09 | C16: -5.9922143e+09 | D16: -0.14413493
A18: TOTAL | B18: -1.1879175e+10 | C18: -1.1186585e+10 | D18: 0.061912499
A20: Commentaire :
A21: Variation du poste Autres charges : FCFA +693 M soit +6%, liée principalement à :
A22: . Pertes de change réalisées : baisse de FCFA +588 M, liées aux variations du cours des devises
A23: . Dons et mécénat : FCFA +968 M
A24: . Charges pour dépréciations et provisions pour risques à court terme : FCFA -864 M : - variation à la hausse de la provision pour pertes latentes de change FCFA +1 381 M - variation à la hausse de la provision pour dépréciations des stocks de FCFA +216 M

Sheet Note 27A
A1: NOTE 27A : CHARGES DE PERSONNEL
A3: Désignation entité : | C3: Excercice clos le : | D3: =+'Note 1'!E3 -> 45657
A4: =+'Note 1'!A4 -> Sabodala Gold Operations S.A | C4: Durée en mois : | D4: =+'Note 1'!E4 -> 12
A5: Numéro d'identification : | B5: =+'Note 1'!B5 -> 002850023
A7: LIBELLES | B7: ANNEE N | C7: ANNEE N-1 | D7: VARIATION EN %
A9: Rémunérations directes versées au personnel | B9: -3.0611362e+10 | C9: -2.1530849e+10 | D9: 0.42174433
A10: Indemnités forfaitaires versées au personnel | B10: -2.7691871e+09 | C10: -2516329900 | D10: 0.10048653
A11: Charges sociales | B11: -1168758019 | C11: -1312068251 | D11: -0.10922468
A12: Rémunérations et charges sociales de l'exploitant individuel
A13: Rémunération transférée de personnel extérieur | B13: -16568307065 | C13: -1.1200784e+10 | D13: 0.47920954
A14: Autres charges sociales | B14: -85271906 | C14: -140791546 | D14: -0.3943393
A16: TOTAL | B16: -5.1202887e+10 | C16: -3.6700823e+10 | D16: 0.39514274
A18: Commentaire :
A19: La variation à la hausse de ce poste, d’un montant de +14 502 millions FCFA, soit une augmentation de 40 % par rapport à l’exercice précédent, s’explique principalement par les facteurs ci-après : - la revalorisation annuelle des salaires, intervenue dans le cadre des ajustements contractuels et conventionnels ; - l’augmentation des effectifs, notamment en lien avec la montée en puissance des opérations de la nouvelle usine BIOX. - par ailleurs, il convient de souligner un paiement exceptionnel d’environ 6 milliards FCFA (dont une provision de 40% à payer en 2025), effectué au titre d’un accord de rappel sur les heures supplémentaires, contribuant significativement à la hausse du poste. En complément, le recours au personnel intérimaire a connu une progression de 48 %, principalement en raison : - des besoins accrus liés au démarrage des activités de l’unité BIOX, nécessitant des compétences spécifiques et un renfort temporaire ; - de l’enregistrement, dans cette même rubrique, des rémunérations des expatriés (dont une provision de bonus de 2,637 milliards F CFA).

Sheet Note 27B
B1: NOTE 27B : EFFECTIFS, MASSE SALARIALE ET PERSONNEL EXTERIEUR
B3: Désignation entité : | K3: Excercice clos le :
B5: Numéro d'identification : | K5: Durée en mois :
B7: EFFECTIF ET MASSE SALARIALE | C7: EFFECTIFS | J7: MASSE SALARIALE
C8: NATIONAUX | E8: AUTRES ETATS DE L'OHADA | G8: HORS OHADA | I8: TOTAL | J8: NATIONAUX | L8: AUTRES ETATS DE L'OHADA | N8: HORS OHADA | P8: TOTAL
C9: M | D9: F | E9: M | F9: F | G9: M | H9: F | J9: M | K9: F | L9: M | M9: F | N9: M | O9: F
A10: YA | B10: 1 - Cadres supérieurs | C10: 104 | D10: 12 | I10: 116 | J10: 5.3204554e+09 | K10: 5.4058998e+08 | P10: 5.8610454e+09
A11: YB | B11: 2 - Techniciens supérieurs et cadres moyens | C11: 137 | D11: 12 | I11: 149 | J11: 5.1256392e+09 | K11: 4.1599863e+08 | P11: 5.5416378e+09
A12: YC | B12: 3 - Techniciens, agents de maîtrise et ouvriers qualifiés | C12: 508 | D12: 32 | I12: 540 | J12: 1.4018282e+10 | K12: 8.1657177e+08 | P12: 1.4834854e+10
A13: YD | B13: 4 - Employés, manœuvres, ouvriers et apprentis | C13: 400 | D13: 60 | I13: 460 | J13: 6.4087519e+09 | K13: 7.3426076e+08 | P13: 7.1430127e+09
A14: YE | B14: TOTAL (1) | C14: 1149 | D14: 116 | I14: 1265 | J14: 3.0873128e+10 | K14: 2.5074211e+09 | P14: 3.338055e+10
I15: 0
A16: YF | B16: Permanents | C16: 1149 | D16: 116 | I16: 1265 | J16: 3.0873128e+10 | K16: 2.5074211e+09 | P16: 3.338055e+10
A17: YG | B17: Saisonniers | I17: 0 | P17: 0
B20: 2. Personnel extérieur | J20: FACTURATION A L'ENTITE
A21: YH | B21: 1 - Cadres supérieurs | G21: 51 | I21: =+SUM(C21:G21) -> 51
A22: YI | B22: 2 - Techniciens supérieurs et cadres moyens | C22: 38 | D22: 4 | H22: 0 | I22: =+SUM(C22:G22) -> 42 | J22: 1.4149347e+10 | K22: 3.37937e+08
A23: YJ | B23: 3 - Techniciens, agents de maîtrise et ouvriers qualifiés | C23: 70 | D23: 14 | I23: =+SUM(C23:G23) -> 84 | J23: 1.0130359e+09 | K23: 2.1302516e+08
A24: YK | B24: 4 - Employés, manœuvres, ouvriers et apprentis | C24: 458 | D24: 50 | I24: =+SUM(C24:G24) -> 508 | J24: 7.9024319e+08 | K24: 64719037
A25: YL | B25: TOTAL (2) | C25: 550 | D25: 71 | G25: 51 | H25: 1 | I25: =+SUM(C25:G25) -> 672 | J25: 1.5952626e+10 | K25: 6.156812e+08
I26: =+SUM(C26:G26) -> 0
A27: YM | B27: Permanents | C27: =C25 -> 550 | D27: =D25 -> 71 | G27: 51 | I27: =+SUM(C27:G27) -> 672 | J27: =+J25 -> 1.5952626e+10 | K27: =+K25 -> 6.156812e+08
A28: YN | B28: Saisonniers
A30: YO | B30: TOTAL (1 + 2) | C30: =C14+C25 -> 1699 | D30: =D14+D25 -> 187 | E30: =E14+E25 -> 0 | F30: =F14+F25 -> 0 | G30: =G14+G25 -> 51 | H30: =H14+H25 -> 1 | I30: =I14+I25 -> 1937 | J30: =+J25+J14 -> 4.6825754e+10 | K30: =+K25+K14 -> 3.1231023e+09
B32: Commentaire :

Sheet Note 28
A1: NOTE 28 : PROVISIONS ET DEPRECIATIONS INSCRITES AU BILAN
A3: Désignation entité : | G3: Excercice clos le : | H3: =+'Note 1'!E3 -> 45657
A4: =+'Note 1'!A4 -> Sabodala Gold Operations S.A | G4: Durée en mois : | H4: =+'Note 1'!E4 -> 12
A5: Numéro d'identification : | B5: =+'Note 1'!B5 -> 002850023
A7: SITUATIONS ET MOUVEMENTS | B7: A | C7: B | F7: C | I7: D = A + B - C
B8: PROVISIONS A L'OUVERTURE DE L'EXERCICE | C8: AUGMENTATIONS : DOTATIONS | F8: DIMINUTIONS : REPRISES | I8: PROVISIONS A LA CLOTURE DE L'EXERCICE
A9: NATURE | C9: D'EXPLOITATION | D9: FINANCIERES | E9: HORS ACTIVITES ORDINAIRES | F9: D'EXPLOITATION | G9: FINANCIERES | H9: HORS ACTIVITES ORDINAIRES
A10: 1. Provisions réglementées | C10: -6.4053834e+08 | I10: -6.4053834e+08
A11: 2. Provisions financières pour risques et charges | B11: -3.3349151e+10 | C11: -4.5354424e+09 | D11: -4.5016509e+09 | F11: 1.7207649e+09 | G11: 3.5406524e+09 | I11: -3.7124827e+10
A12: 3. Dépréciation des immobilisations
A13: TOTAL DOTATIONS | B13: -3.3349151e+10 | C13: -5.1759807e+09 | D13: -4.5016509e+09 | E13: 0 | F13: 1.7207649e+09 | G13: 3.5406524e+09 | H13: 0 | I13: -3.7765366e+10
A15: 4. Dépréciations des stocks | B15: -9.4467527e+09 | C15: -2.1617179e+08 | I15: -9.6629245e+09
A16: 5. Dépréciations actif circulant HAO
A17: 6. Dépréciations fournisseurs
A18: 7. Dépréciations des clients
A19: 8.Dépréciations autres créances
A20: 9. Dépréciations titres de placement
A21: 10. Dépréciations valeurs à encaisser
A22: 11. Dépréciations disponibilité
A23: 12. Dépréciations et provisions pour risques à court terme exploitation
A24: 13. Dépréciations et provisions pour risques à court terme à caractère financier | B24: -3.5306801e+09 | C24: -4.9123551e+09 | F24: 3530680114 | I24: -4.9123551e+09
A25: TOTAL CHARGES POUR DEPRECIATIONS ET PROVISIONS A COURT TERME | B25: -1.2977433e+10 | C25: -5.1285269e+09 | D25: 0 | E25: 0 | F25: 3530680114 | G25: 0 | H25: 0 | I25: -1.457528e+10
A27: TOTAL PROVISIONS ET DEPRECIATIONS | B27: -4.6326584e+10 | C27: -1.0304508e+10 | D27: -4.5016509e+09 | E27: 0 | F27: 5.251445e+09 | G27: 3.5406524e+09 | H27: 0 | I27: -5.2340645e+10
A29: Commentaire :
A30: 2. . Provisions financières pour risques et charges Variation 202 : +FCFA 4 416 composée cmme suit : Prov. pour Retraite FCFA +1597 M Prov. p/Ecarts de change long terme FCFA +2276 M Prov. pour démantèlement –FCFA+949 M Prov. pour Réhabilitation – Dégradation progressive FCFA -1531 M Prov. Fonds social FCFA -485 M
A31: 4. Dépréciation des stocks : +FCFA 216M (ajustement de la provision suite à une revue des stocks)
A32: 13. Dépréciations et provisions pour risques à court terme à caractère financier : +FCFA 1382M correspondant aux Provision écarts de conversion

Sheet Note 29
A1: NOTE 29 : CHARGES ET REVENUS FINANCIERS
A3: Désignation entité : | C3: Excercice clos le : | D3: =+'Note 1'!E3 -> 45657
A4: =+'Note 1'!A4 -> Sabodala Gold Operations S.A | C4: Durée en mois : | D4: =+'Note 1'!E4 -> 12
A5: Numéro d'identification : | B5: =+'Note 1'!B5 -> 002850023
A7: LIBELLES | B7: ANNEE N | C7: ANNEE N-1 | D7: VARIATION EN %
A9: Intérêts des emprunts
A10: Intérêts dans loyers de locations acquisition
A11: Escomptes accordés
A12: Autres intérêts | B12: -3.4265364e+09 | C12: -1556205052 | D12: 1.2018541
A13: Escomptes des effets de commerce
A14: Pertes de change
A15: Pertes sur cessions de titres de placement
A16: Malis provenant d'attribution gratuite d'actions au personnel salarié et aux dirigeants
A17: Pertes sur risques financiers
A18: Charges pour dépréciations et provisons à court terme à caractère financier (voir note 28)
A19: SOUS TOTAL FRAIS FINANCIERS | B19: -3.4265364e+09 | C19: -1556205052 | D19: 1.2018541
A21: Intérêts de prêts et créances diverses
A22: Revenus de participations
A23: Escomptes obtenus
A24: Revenus de placement
A25: Intérêts dans loyers de location-financement
A26: Gains de change
A27: Gains sur cessions de titres de placement
A28: Gains sur risques financiers
A29: Reprises de charges pour dépréciation et provisions à court terme à caractère financier (voir note 28)
A30: SOUS TOTAL REVENUS FINANCIERS
A32: TOTAL | B32: -3.4265364e+09 | C32: -1556205052 | D32: 1.2018541
A34: Commentaire :
A35: Le poste Charges et Revenus Financiers a connu une évolution positive de +1 870M FCFA liée à l'effet combiné de : - des intérêts du prêt ECG pour un montant de FCFA +1 831 M - des intérêts de retard sur créances diverses payés +1M - intérêts bancaires : FCFA +37M

Sheet Note 30
A1: NOTE 30 : AUTRES CHARGES ET PRODUITS HAO
A3: Désignation entité : | C3: Excercice clos le : | D3: =+'Note 1'!E3 -> 45657
A4: =+'Note 1'!A4 -> Sabodala Gold Operations S.A | C4: Durée en mois : | D4: =+'Note 1'!E4 -> 12
A5: Numéro d'identification : | B5: =+'Note 1'!B5 -> 002850023
A7: LIBELLES | B7: ANNEE N | C7: ANNEE N-1 | D7: VARIATION EN %
A9: Charges HAO constatées (1) à détailler
A10: (1) …………………
A11: (1) …………………
A12: Pertes sur créances HAO
A13: Dons et libéralités accordés
A14: Abandons de créances consentis
A15: Charges provisionnées HAO
A16: Dotations hors activités ordinaires
A17: Participation des travailleurs
A18: SOUS TOTAL AUTRES CHARGES HAO
A19: Produits HAO constatés (1) à détailler
A20: (1) …………………
... A33: · Commenter toute variation significative

Sheet Note 31
A1: NOTE 31 : REPARTITION DU RESULTAT ET AUTRES ELEMENTS CARACTERISTIQUES DES CINQ DERNIERS EXERCICES
A3: Désignation entité : | D3: Excercice clos le : | E3: =+'Note 1'!E3 -> 45657
A4: =+'Note 1'!A4 -> Sabodala Gold Operations S.A | D4: Durée en mois : | E4: =+'Note 1'!E4 -> 12
A5: Numéro d'identification : | B5: =+'Note 1'!B5 -> 002850023
A7: EXERCICES CONCERNES (1) | B7: N | C7: N-1 | D7: N-2 | E7: N-3 | F7: N-4
A9: STRUCTURE DU CAPITAL A LA CLOTURE DE L'EXERCICE (2)
A10: Capital social | B10: 10500000 | C10: 10500000 | D10: 10500000 | E10: 10000000 | F10: 10000000
A11: Actions ordinaires | B11: 105 | C11: 105 | D11: 105 | E11: 100 | F11: 100
A12: Actions à dividendes prioritaires (ADP) sans droit de vote | B12: 0 | C12: 0 | D12: 0 | E12: 0 | F12: 0
A13: Actions nouvelles à émettre :
A14: -par conversion d'obligations | B14: 0 | C14: 0 | D14: 0 | E14: 0 | F14: 0
A15: -par exercice de droits de souscription | B15: 0 | C15: 0 | D15: 0 | E15: 0 | F15: 0
A16: OPERATIONS ET RESULTATS DE L'EXERCICE (3) | B16: 0 | C16: 0 | D16: 0 | E16: 0 | F16: 0
A17: Chiffre d'affaires hors taxes | B17: 3.3716269e+11 | C17: 354075329142 | D17: 3.9296161e+11 | E17: 4.5997525e+11 | F17: 247066828376
A18: Résultat des activités ordinaires (RAO) hors dotations et reprises (exploitation et financières) | B18: 1.7618497e+11 | C18: 2.3194732e+11 | D18: 2.528073e+11 | E18: 57404295662 | F18: 69850260170
A19: Participation des travailleurs aux bénéfices | F19: 0
A20: Impôt sur le résultat | B20: 2.0798922e+10 | C20: 4.610748e+10 | D20: 5.6031664e+10 | E20: 10209148562 | F20: 10470001322
A21: Résultat net (4) | B21: 5.7851663e+10 | C21: 1.3709634e+11 | D21: 1.4355631e+11 | E21: 26718633081 | F21: 39562196908
A22: RESULTAT ET DIVIDENDE DISTRIBUES
A23: Résultat distribué (5) | B23: 65000950350 | C23: 30000000000 | D23: 26718633081 | E23: 7912439382
A24: Dividende attribué à chaque action | B24: 61905667 | C24: 28571429 | D24: 25446317 | E24: 7912439.4
A25: PERSONNEL ET POLITIQUE SALARIALE
A26: Effectif moyen des travailleurs au cours de l'exercice (6) | B26: 1265 | C26: 1177 | D26: 1095 | E26: 1122 | F26: 1044
A27: Effectif moyen de personnel extérieur | B27: 672 | C27: 683 | D27: 1157 | E27: 665 | F27: 525
A28: Masse salariale distribuée au cours de l'exercice (7) | B28: 3.338055e+10 | C28: 2.3281051e+10 | D28: 21915173176 | E28: 21416883592 | F28: 13033161392
A29: Avantages sociaux versés au cours de l'exercice (8) {Sécurité sociale, œuvres sociales} | B29: 1.2540299e+09 | C29: 1452859797 | D29: 1209328706 | E29: 6.6880785e+08 | F29: 2968503423
A30: Personnel extérieur facturé à l'entreprise (9) | B30: 16568307065 | C30: 11200784343 | D30: 1.1478628e+10 | E30: 4959321311 | F30: 11147834122
A32: (1) Y compris l'exercice dont les états financiers sont soumis à l'approbation de l'Assemblée | C32: (6) Personnel propre
A33: (2) Indication, en cas de libération partielle du capital, du montant du capital non appelé | C33: (7) Total des comptes 661, 662, 663
A34: (3) Les éléments de cette rubrique sont ceux figurant au compte de résultat | C34: (8) Total des comptes 664, 668
A35: (4) Le résultat, lorsqu'il est négatif, doit être mis entre parenthèses | C35: (9) Compte 667.
A36: (5) L'exercice N correspond au dividende proposé du dernier exercice

Sheet Note 32
A1: NOTE 32 : PRODUCTION DE L'EXERCICE
A3: Désignation entité : | K3: Excercice clos le : | L3: =+'Note 1'!E3 -> 45657
A4: =+'Note 1'!A4 -> Sabodala Gold Operations S.A | K4: Durée en mois : | L4: =+'Note 1'!E4 -> 12
A5: Numéro d'identification : | B5: =+'Note 1'!B5 -> 002850023
A7: DESIGNATION DU PRODUIT | B7: UNITE DE QUANTITE CHOISIE | C7: PRODUCTION VENDUE DANS LE PAYS | E7: PRODUCTION VENDUE DANS LES AUTRES PAYS DE L'OHADA | G7: PRODUCTION VENDUE HORS L'OHADA | I7: PRODUCTION IMMOBILISEE | K7: STOCK OUVERTURE DE L'EXERCICE | M7: STOCK CLOTURE DE L'EXERCICE
C8: Quantité | D8: Valeur | E8: Quantité | F8: Valeur | G8: Quantité | H8: Valeur | I8: Quantité | J8: Valeur | K8: Quantité | L8: Valeur | M8: Quantité | N8: Valeur
A9: Vente d'OR | B9: Once | C9: 8000 | D9: 11805992800 | G9: 221419.25 | H9: 3.2505981e+11 | K9: 3430 | L9: 1.6907999e+09 | M9: 3356 | N9: 2.6597853e+09
A10: Vente d'Argent | B10: Once | G10: 17085.075 | H10: 2.9688727e+08
A23: NON VENTILE
A25: TOTAL | C25: =SUM(C9:C24) -> 8000 | D25: =SUM(D9:D24) -> 11805992800 | E25: =SUM(E9:E24) -> 0 | F25: =SUM(F9:F24) -> 0 | G25: =SUM(G9:G24) -> 238504.33 | H25: =SUM(H9:H24) -> 3.253567e+11 | K25: =SUM(K9:K24) -> 3430 | L25: =SUM(L9:L24) -> 1.6907999e+09 | M25: =SUM(M9:M24) -> 3356 | N25: =SUM(N9:N24) -> 2.6597853e+09
A28: La production de l’exercice 2024 a totalisé 229117 en baisse de 22% par rapport à l’année 2023 (293 680 onces). Les ventes d’or se sont élevées à 221 195 onces, contre 299 342 onces en 2024, soit également une baisse de 24%. liée à la faible teneur moyenne des minerais traités.Une quantité marginale de 17 085 onces d’argent a été vendue en 2023 pour un montant de FCFA 298M.

Sheet Note 33
A1: NOTE 33 : ACHATS DESTINES A LA PRODUCTION
A3: Désignation entité : | G3: Excercice clos le : | H3: =+'Note 1'!E3 -> 45657
A4: =+'Note 1'!A4 -> Sabodala Gold Operations S.A | G4: Durée en mois : | H4: =+'Note 1'!E4 -> 12
A5: Numéro d'identification : | B5: =+'Note 1'!B5 -> 002850023
A7: DESIGNATION DES MATIERES ET PRODUITS | B7: UNITE DE QUANTITE CHOISIE | C7: ACHATS EFFECTUES AU COURS DE L'EXERCICE | I7: VARIATION DES STOCKS
C8: PRODUITS DE L'ETAT | E8: PRODUITS IMPORTES
E9: ACHETES DANS L'ETAT | G9: ACHETES HORS DE L'ETAT
C10: Quantité | D10: Valeur | E10: Quantité | F10: Valeur | G10: Quantité | H10: Valeur | I10: Valeur
B11: Tonne
A25: NON VENTILES
A27: TOTAL

Sheet Note 34
A1: NOTE 34 : FICHE DE SYNTHESE DES PRINCIPAUX INDICATEURS FINANCIERS
A3: Désignation entité : | B3: Excercice clos le : | C3: =+'Note 1'!E3 -> 45657
A4: =+'Note 1'!A4 -> Sabodala Gold Operations S.A | C4: Durée en mois : | D4: =+'Note 1'!E4 -> 12
A5: Numéro d'identification : | B5: =+'Note 1'!B5 -> 002850023
A7: (EN MILLIERS FRANCS) | B7: ANNEE N | C7: ANNEE N-1 | D7: VARIATION EN %
A8: ANALYSE DE L'ACTIVITE
A9: SOLDES INTERMEDIAIRES DE GESTION
A10: CHIFFRE D'AFFAIRES | B10: 3.3716269e+08 | C10: 3.5407533e+08 | D10: -0.047765643
A11: MARGE COMMERCIALE
A12: VALEUR AJOUTEE | B12: 2.308144e+08 | C12: 2.7187381e+08 | D12: -0.15102378
A13: EXCEDENT BRUT D'EXPLOITATION (EBE) | B13: 1.7961151e+08 | C13: 235172986 | D13: -0.2362579
A14: RESULTAT D'EXPLOITATION | B14: 83919133 | C14: 175056496 | D14: -0.52061686
A15: RESULTAT FINANCIER | B15: -4387534.9 | C15: 10215580 | D15: -1.4294945
A16: RESULTAT DES ACTIVITES ORDINAIRES | B16: 79531598 | C16: 185272076 | D16: -0.57073079
A17: RESULTAT HORS ACTIVITES ORDINAIRES | B17: -881014.16 | C17: -398789.94 | D17: 1.2092186
A18: RESULTAT NET | B18: 57851663 | C18: 1.3709634e+08 | D18: -0.57802183
A19: DETERMINATION DE LA CAPACITE D'AUTOFINANCEMENT
A20: EBE | B20: 1.7961151e+08 | C20: 235172986
A21: + Valeurs comptables des cessions courantes d'immobilisation (compte 654)
A22: - Produits ces cessions courantes d'immobilisation (compte 754)
A23: = CAPACITE D'AUTOFINANCEMENT D'EXPLOITATION | B23: 1.7961151e+08 | C23: 2.3350352e+08
A24: + Revenus financiers
A25: + Gains de change
A26: + Transferts de charges financières
A27: + Produits HAO
A28: + Transferts de charges HAO
A29: - Frais financiers | B29: -3426536.4 | C29: -1556205.1
A30: - Pertes de change
A31: - Charges HAO
A32: - Participation
A33: - Impôts sur le résultat | B33: -20798922 | C33: -47529211
A34: = CAPACITE D'AUTOFINANCEMENT GLOBALE (C.A.F.G) | B34: 1.5538605e+08 | C34: 1.8583984e+08 | D34: -0.16387112
A35: - Distributions de dividendes opérées durant l'exercice | B35: -44387621 | C35: -26462868 | D35: 0.6773549
A36: = AUTOFINANCEMENT | B36: 1.1099843e+08 | C36: 1.5937697e+08 | D36: -0.30354785
A37: ANALYSE DE LA RENTABILITE
B38: 0.30985903 | C38: 0.323138 | D38: -0.041093799
B39: 0.10959356 | C39: 0.25550375 | D39: -0.57106869
A40: ANALYSE DE LA STRUCTURE FINANCIERE
A41: Capitaux propres et ressources assimilées | B41: 5.2917569e+08 | C41: 5.3657271e+08 | D41: -0.013785684
A42: + Dettes financières* et autres ressources assimilées (b) | B42: 76741964 | C42: 73276782 | D42: 0.047288954
A43: = Ressources stables | B43: 6.0591765e+08 | C43: 6.0960176e+08 | D43: -0.0060434626
A44: - Actif immobilisé (b) | B44: -5.5088025e+08 | C44: -5.2876325e+08 | D44: 0.041827794
A45: = FONDS DE ROULEMENT (1) | B45: 55037403 | C45: 80838509 | D45: -0.3191685
A46: Actif circulant d'exploitation (b) | B46: 1.9478635e+08 | C46: 1.8626361e+08 | D46: 0.045756314
A47: - Passif circulant d'exploitation (b) | B47: -1.5269589e+08 | C47: -1.6059761e+08 | D47: -0.049201986
A48: = BESOIN DE FINANCEMENT D'EXPLOITATION (2) | B48: 42090456 | C48: 25665998 | D48: 0.63993063
A49: Actif circulant HAO (b)
A50: - Passif circulant HAO (b)
A51: = BESOIN DE FINANCEMENT HAO (3)
A52: BESOIN DE FINANCEMENT GLOBAL (4) = (2) + (3) | B52: 42090456 | C52: 25665998 | D52: 0.63993063
A54: TRESORERIE NETTE (5) = (1) - (4) | B54: 12946948 | C54: 55172511 | D54: -0.76533699
A55: CONTRÔLE : TRESORERIE NETTE = TRESORERIE ACTIF - TRESORERIE PASSIF | B55: 12946947 | C55: 55172511 | D55: -0.76533699
A56: ANALYSE DE LA VARIATION DE LA TRESORERIE
A57: Flux de trésorerie des activités opérationnelles | B57: 1.1834827e+08 | C57: 1.3989084e+08 | D57: -0.15399559
A58: - Flux de trésorerie des activités d'investissement | B58: -1.1550361e+08 | C58: -1.5602352e+08 | D58: -0.25970387
A59: + Flux de trésorerie des activités de financement | B59: -45070219 | C59: 13982295 | D59: -4.2233777
A60: = VARIATION DE LA TRESORERIE NETTE DE LA PERIODE | B60: -42225564 | C60: -2150390.7 | D60: 18.636229
A61: ANALYSE DE LA VARIATION DE L'ENDETTEMENT FINANCIER NET
A62: Endettement financier brut (Dettes financières* + Trésorerie passif) - Trésorerie actif | B62: 26029651 | C62: -41010315 | D62: -1.6347099
A63: = ENDETTEMENT FINANCIER NET | B63: 26029651 | C63: -41010315 | D63: -1.6347099
A64: (a) Résultat d'exploitation après impôt théorique sur le bénéfice.
A65: (b) Les écarts de conversion doivent être éliminés afin de ramener les créances et les dettes concernées à leur valeur initiale.
A66: Dettes financières* = emprunts et dettes financières diverses + dettes de location acquisition.

Sheet Note 35
A1: NOTE 35 : LISTE DES INFORMATIONS SOCIALES, ENVIRONNEMENTALES ET SOCIETALES A FOURNIR
A3: Désignation entité : | B3: Excercice clos le : | C3: =+'Note 1'!E3 -> 45657
A4: =+'Note 1'!A4 -> Sabodala Gold Operations S.A
A5: Numéro d'identification : | B5: Durée en mois : | C5: =+'Note 1'!E4 -> 12
A6: =+'Note 1'!B5 -> 002850023
A8: Note obligatoire pour les entités ayant un effectif de plus de 250 salariés
A9: Liste des informations sociales, environnementales et sociétales à fournir
A10: INFORMATIONS SOCIALES
A11: Emploi : Mettre en œuvre les meilleures pratiques en matière de ressources humaines pour le recrutement, le développement et la gestion de notre main-d'œuvre ; fondant les pratiques d'embauche et d'emploi sur les compétences, l'expérience, les capacités d'apprentissage et les performances sans discrimination fondée sur l'âge, le sexe, l'appartenance ethnique, la nationalité, la politique ou la religion.
A12: Relations sociales : Chez Sabodala Gold Operations, nous avons la ferme conviction que nos employés et tous les membres de notre personnel sont au cœur de nos performances et de notre réussite en tant qu'organisation. Comme notre succès dépend de la qualité et de l'engagement de l'ensemble de notre personnel, nous avons pour objectif d'employer les personnes les plus compétentes et d'entretenir une relation de travail solide, équitable et collaborative avec nos employés et associés ainsi qu'avec nos partenaires commerciaux, nos prestataires et tous ceux qui travaillent directement pour nous et avec nous. A ces fins, nous aspirons à : • Créer un environnement empreint de valeurs telles que le respect, l’attention, l’intégrité, la performance, la collaboration et la communication avec ouverture et transparence ; • Offrir un environnement de travail dépourvu de toutes formes de discrimination et harcèlement ; • Offrir un environnement de travail encourageant la motivation personnelle et la prise d’initiatives ; • Récompenser la régularité des performances professionnelles ; • Prôner l’ouverture et le dialogue sur les questions liées au travail et à l’entreprise ; • Garantir l’égalité des chances en matière de développement personnel, d’évolution de carrière et d’avancement selon les compétences personnelles et performances professionnelles démontrées ; • Offrir à tous des conditions de travail saines et sûres ; • Proposer des mesures d’adaptation personnalisées aux travailleurs handicapés qui en font la demande, dans la mesure du possible, conformément à nos exigences professionnelles et aux normes de santé et de sécurité concernant nos processus d’emploi, nos supports d’information et de communication, nos processus de retour à l’emploi, notre gestion des performances, nos processus de développement et d’évolution professionnels et nos procédures de réaffectation. L’entreprise a la conviction que les problèmes pouvant survenir entre les employés et la direction peuvent être résolus grâce à une communication ouverte et directe entre les deux parties, sans l’intervention d’intermédiaires. Bien que l’implication d’intermédiaires soit encouragée ; l’entreprise respecte le droit des employés à solliciter leur intervention et agira en conséquence. L’entreprise reconnait et respecte l’implication et la relation avec les comités d’entreprise composés d’employés élus, avec lesquels nous sommes pleinement disposés à collaborer dans l’intérêt commun de l’entreprise et des employés.
A13: Santé et sécurité : Sabodala Gold Operations s'est engagée à maintenir un bilan solide en matière de santé et de sécurité avec un signalement efficace des incidents et des mesures correctives rapides. À Sabodala, nous avons un certain nombre de programmes visant à accroître la sensibilisation à la sécurité et la responsabilité. Depuis 2009, il n’y a eu que 12 blessures entraînant une perte de temps (LTI). En 2017, nous avons mis en place un cadre de gestion des conséquences pour évaluer et élever le comportement en matière de sécurité. Le projet Karangué (qui signifie «se protéger» en wolof, la langue locale) a été mis en œuvre pour doter l'ensemble du personnel d'une formation de base en matière de sécurité.
A14: Formation : SGO s'est engagée à : • fournir des compétences et un développement de carrière pour aider les employés à mettre en œuvre leur potentiel et à faire avancer leur carrière; • promouvoir les employés locaux à des postes de responsabilité accrue ; • soutenir le développement local des compétences et de la main d’œuvre minières par le biais de partenariats avec diverses institutions, en fournissant une éducation et une formation aux employés actuels et futurs de l’industrie ; • fournir des opportunités pour le développement de l’emploi des jeunes et l’emploi au sein de l’entreprise et de la communauté.
A15: Égalité de traitement : SGO prône les principes fondamentaux de l'égalité des chances face à l'emploi. Nous nous engageons à traiter chacun avec égalité, respect et dignité et à garantir l'égalité des chances face à l'emploi en prenant pour référence les qualifications professionnelles de chacun. Nul ne pourra être victime de discrimination our de harcèlement pour des raisons de race, de descendance, d'origine, de couleur de peau, de citoynneté, de croyance, d'âge, de statut marital, de handicap ou autres.
A16: INFORMATIONS ENVIRONNEMENTALES
A17: Politique générale en matière environnementale : Sabodala Gold Operations (SGO) SA, filiale de Endeavour Mining Corporation, est une compagnie d’exploitation minière et de production d’or à Sabodala dans la région de Kédougou au Sénégal. SGO s’est engagée à protéger l’environnement tout en participant au développement économique du Sénégal. La Direction de SGO est consciente que ses employés, les communautés environnantes, ainsi que toutes les parties prenantes à ses activités ont le droit d’attendre de sa part une garantie de performances environnementales responsables et durables. L'intégralité de cette politique est présentée aux employés, affichée et disponible en ligne sur le site Internet de la compagnie.
A18: Pollution et gestion des déchets : SGO s'est engagée à assurer une gestion efficace des matières résiduelles par des stratégies de Réduction, de Réutilisation, de Recyclage et d’Elimination appropriées (SGO dispose d'une décharge autorisée et des incinérateurs, recyclage des plastiques, valorisation des huiles usagées, recyclage des batteries...). Conformément à son Plan de Gestion Environnemental & Social (PGES), SGO prend les mesures adéquates pour prévenir la pollution des eaux de surface, des eaux souterraines, du sol et de l’air pour réduire au maximum les impacts négatifs sur la biodiversité.
A19: Utilisation durable des ressources : Installation de bassins de collecte des eaux de pluie pour éviter d'utiliser les eaux souterraines (laissées aux besoins des populations), recyclage des eaux du parc à résidus miniers pour éviter les rejets dans l'environnement, installation d'une usine de traitement des eaux usées. Installations de pépinières pour la production de plants (plus de 25 000 par année) pour la réhabilitation des zones minières. Organisation de campagnes de sensibilisation sur l'efficacité énergétique, organisation d'un concours sur l'efficacité energétique dans les résidences des employés, suivi de l'efficacité énérgétique comme indicateur de performance opérationnelle (usine et véhicules....). Organisation annuelle d'une campagne de prévention et de lutte contre les feux de brousse.
... A25: Sous-traitance et fournisseurs : SGO, étant une société engagée et sociétalement responsable, privilégie le développement des fournisseurs locaux sur les questions liées à l'approvisionnement. Pour cela un réseau de fournisseurs locaux est créé et intensifié de jour en jour. Il s'agit principalement de fournisseurs dans le domaine de la construction métallique, du batiment, de la quincaillerie générale, de l'alimentaire, des services (location de main d'oeuvre, d'engins de BTP etc..). Une mission d'accompagnement est mise sur place pour les accompagner dans l'organisation et la gestion de leur entreprise d'une facon formelle et professionnelle.

Sheet Note 36
A1: NOTE 36 : TABLE DES CODES
A6: 1 - Code forme juridique (1) | E6: 3 - Code pays du siège social
A8: Société Anonyme (SA) à participation publique | C8: 0 | D8: 0 | E8: Pays OHADA (2)
A10: Société Anonyme (SA) | C10: 0 | D10: 1 | E10: Autres pays africains | G10: 2 | H10: 1
A12: Société à Responsabilité Limitée (SARL) | C12: 0 | D12: 2 | E12: France | G12: 2 | H12: 3
A14: Société en Commandite Simple (SCS) | C14: 0 | D14: 3 | E14: Autres pays de l'Union Européenne | G14: 3 | H14: 9
A16: Société en Nom Collectif (SNC) | C16: 0 | D16: 4 | E16: U.S.A. | G16: 4 | H16: 0
A18: Société en Participation (SP) | C18: 0 | D18: 5 | E18: Canada | G18: 4 | H18: 1
A20: Groupement d'Intérêt Économique (GIE) | C20: 0 | D20: 6 | E20: Autres pays américains | G20: 4 | H20: 9
A22: Association | C22: 0 | D22: 7 | E22: Pays asiatiques | G22: 5 | H22: 0
A24: Société par Actions Simplifiée | C24: 0 | D24: 8 | E24: Autres pays | G24: 9 | H24: 9
A26: Autre forme juridique (à préciser) | C26: 0 | D26: 9
A28: 2 - Code régime fiscal
A30: Réel normal | D30: 1
A32: Réel simplifié | D32: 2
A34: Synthétique | D34: 3
A36: Forfait | D36: 4
A39: (1) Remplacer le premier 0 par 1 si l'entité bénéficie d'un agrément prioritaire
A40: (2) Bénin = 01; Burkina = 02; Côte d'Ivoire = 03; Guinée Bissau = 04; Mali = 05; Niger = 06; Sénégal = 07; Togo = 08
A41: Cameroun = 09; Congo = 10; Gabon = 11; République Centrafricaine = 12; Tchad = 13; Comores = 14; Guinée = 15;
A42: Guinée Equatoriale = 16; Congo RDC = 17.

Sheet Codes activités
A1: CODES DES ACTIVITES ECONOMIQUES
A4: Agriculture vivrière | C4: Industries du caoutchouc et des plastiques
A5: 001 001 Culture céréalière | C5: 022 001 Fabrication du caoutchouc naturel
A6: 001 002 Culture de tubercules et plantains | C6: 022 002 Industries du caoutchouc
A7: 001 003 Culture de légumes | C7: 022 003 Fabrication de matières plastiques
A8: 001 004 Culture de condiments | C8: Fabrication d'autres produits minéraux non métalliques et de matériaux
A9: 001 005 Culture de fruits | C9: de construction
A10: 001 006 Culture d'autres produits de l'Agriculture vivrière | C10: 023 001 Industrie du verre
A11: Agriculture industrielle et d'exportation | C11: 023 002 Fabrication de produits minéraux pour la construction
A12: 002 001 Culture de canne à sucre | C12: 023 003 Fabrication d'autres produits minéraux non métalliques
A13: 002 002 Culture d'arachide d'huilerie | C13: Métallurgie et travail des métaux
A14: 002 003 Culture d'arachide de bouche | C14: 024 001 Métallurgie
A15: 002 004 Culture de tabac | C15: 024 002 Travail des métaux
... A85: 021 005 Fabrication d'autres produits chimiques | C85: Correction territoriale
C86: 044 000 Correction territoriale
