Workbook

Sheet Modèle
A1: Nom | B1: Unité | C1: Année 1 | D1: Année 2 | E1: Année 3 | F1: Année 4 | G1: Année 5 | H1: Année 6 | I1: Année 7 | J1: Année 8 | K1: Année 9 | L1: Année 10 | M1: Année 11 | N1: SOMME | O1: VAN
A3: I. PRODUCTION
A4: Production d'or | B4: oz | E4: 250000 | F4: 250000 | G4: 250000 | H4: 250000 | I4: 250000 | J4: 250000 | K4: 250000 | L4: 250000 | N4: =SUM($C4:$M4) -> 2000000
A5: Cours de l'or | B5: USD/oz | E5: 1300 | F5: 1300 | G5: 1300 | H5: 1300 | I5: 1300 | J5: 1300 | K5: 1300 | L5: 1300
A6: Chiffre d'affaires | B6: USD | C6: =C$4*C$5 -> 0 | D6: =D$4*D$5 -> 0 | E6: =E$4*E$5 -> 325000000 | F6: =F$4*F$5 -> 325000000 | G6: =G$4*G$5 -> 325000000 | H6: =H$4*H$5 -> 325000000 | I6: =I$4*I$5 -> 325000000 | J6: =J$4*J$5 -> 325000000 | ... M6: =M$4*M$5 -> 0 | N6: =SUM($C6:$M6) -> 2600000000 | O6: =$C6+NPV(10%,$D6:$M6) -> 1.5762282e+09
A8: II. DEPENSES D'INVESTISSEMENT (CAPEX)
A9: Coûts des construction industrielles | B9: USD | C9: 50000000 | D9: 100000000 | N9: =SUM($C9:$M9) -> 150000000 | O9: =$C9+NPV(10%,$D9:$M9) -> 1.4090909e+08
A10: Coûts des biens d'équipement | B10: USD | D10: 50000000 | E10: 5000000 | F10: 5000000 | G10: 5000000 | H10: 5000000 | I10: 5000000 | J10: 5000000 | K10: 5000000 | L10: 5000000 | N10: =SUM($C10:$M10) -> 90000000 | O10: =$C10+NPV(10%,$D10:$M10) -> 69704210
A11: Coûts de réhabilitation du site | B11: USD | M11: 10000000 | N11: =SUM($C11:$M11) -> 10000000 | O11: =$C11+NPV(10%,$D11:$M11) -> 9090909.1
A12: Total des dépenses d'investissement | B12: USD | C12: =SUM(C$9:C$11) -> 50000000 | D12: =SUM(D$9:D$11) -> 150000000 | E12: =SUM(E$9:E$11) -> 5000000 | F12: =SUM(F$9:F$11) -> 5000000 | G12: =SUM(G$9:G$11) -> 5000000 | H12: =SUM(H$9:H$11) -> 5000000 | I12: =SUM(I$9:I$11) -> 5000000 | J12: =SUM(J$9:J$11) -> 5000000 | ... M12: =SUM(M$9:M$11) -> 10000000 | N12: =SUM($C12:$M12) -> 250000000 | O12: =$C12+NPV(10%,$D12:$M12) -> 2.1446873e+08
A14: III. COÛTS D'EXPLOITATION (OPEX)
A15: Coût moyen d'exploitation | B15: USD/oz | E15: 700 | F15: 700 | G15: 700 | H15: 700 | I15: 700 | J15: 700 | K15: 700 | L15: 700
A16: Total des coûts d'exploitation | B16: USD | C16: =C$4*C$15 -> 0 | D16: =D$4*D$15 -> 0 | E16: =E$4*E$15 -> 175000000 | F16: =F$4*F$15 -> 175000000 | G16: =G$4*G$15 -> 175000000 | H16: =H$4*H$15 -> 175000000 | I16: =I$4*I$15 -> 175000000 | J16: =J$4*J$15 -> 175000000 | ... M16: =M$4*M$15 -> 0 | N16: =SUM($C16:$M16) -> 1400000000 | O16: =$C16+NPV(10%,$D16:$M16) -> 8.4873826e+08
A18: IV. FLUX NETS DE TRESORERIE AVANT IMPÔTS
A19: Flux nets de trésorerie avant impôts | B19: USD | C19: =C$6-C$12-C$16 -> -50000000 | D19: =D$6-D$12-D$16 -> -150000000 | E19: =E$6-E$12-E$16 -> 145000000 | F19: =F$6-F$12-F$16 -> 145000000 | G19: =G$6-G$12-G$16 -> 145000000 | H19: =H$6-H$12-H$16 -> 145000000 | I19: =I$6-I$12-I$16 -> 145000000 | J19: =J$6-J$12-J$16 -> 145000000 | ... M19: =M$6-M$12-M$16 -> -10000000 | N19: =SUM($C19:$M19) -> 950000000 | O19: =$C19+NPV(10%,$D19:$M19) -> 5.130212e+08
A20: Taux de rendement interne avant impôts | B20: % | C20: =IF(ISNUMBER(IRR($C19:C19)),IF(IRR($C19:C19)>0,IRR($C19:C19),""),"") | D20: =IF(ISNUMBER(IRR($C19:D19)),IF(IRR($C19:D19)>0,IRR($C19:D19),""),"") | E20: =IF(ISNUMBER(IRR($C19:E19)),IF(IRR($C19:E19)>0,IRR($C19:E19),""),"") | F20: =IF(ISNUMBER(IRR($C19:F19)),IF(IRR($C19:F19)>0,IRR($C19:F19),""),"") -> 0.23743596 | G20: =IF(ISNUMBER(IRR($C19:G19)),IF(IRR($C19:G19)>0,IRR($C19:G19),""),"") -> 0.43121332 | H20: =IF(ISNUMBER(IRR($C19:H19)),IF(IRR($C19:H19)>0,IRR($C19:H19),""),"") -> 0.52174773 | I20: =IF(ISNUMBER(IRR($C19:I19)),IF(IRR($C19:I19)>0,IRR($C19:I19),""),"") -> 0.5678591 | J20: =IF(ISNUMBER(IRR($C19:J19)),IF(IRR($C19:J19)>0,IRR($C19:J19),""),"") -> 0.59275422 | ... M20: =IF(ISNUMBER(IRR($C19:M19)),IF(IRR($C19:M19)>0,IRR($C19:M19),""),"") -> 0.614484
A22: V. DROITS FIXES
A23: Droits fixes | B23: USD | C23: 100000 | N23: =SUM($C23:$M23) -> 100000 | O23: =$C23+NPV(10%,$D23:$M23) -> 100000
A25: VI. REDEVANCE SUPERFICAIRE
A26: Superficie de la mine | B26: km² | C26: 100 | D26: 100 | E26: 100 | F26: 100 | G26: 100 | H26: 100 | I26: 100 | J26: 100 | K26: 100 | L26: 100 | M26: 100
A27: Montant de la redevance superfiaire | B27: USD/km² | C27: 100 | D27: 100 | E27: 100 | F27: 100 | G27: 100 | H27: 100 | I27: 100 | J27: 100 | K27: 100 | L27: 100 | M27: 100
A28: Redevance superficiaire | B28: USD | C28: =C$26*C$27 -> 10000 | D28: =D$26*D$27 -> 10000 | E28: =E$26*E$27 -> 10000 | F28: =F$26*F$27 -> 10000 | G28: =G$26*G$27 -> 10000 | H28: =H$26*H$27 -> 10000 | I28: =I$26*I$27 -> 10000 | J28: =J$26*J$27 -> 10000 | ... M28: =M$26*M$27 -> 10000 | N28: =SUM($C28:$M28) -> 110000 | O28: =$C28+NPV(10%,$D28:$M28) -> 71445.671
A30: VII. REDEVANCE MINIERE
A31: Taux de la redevance minière | B31: % | C31: =IF(ISNUMBER(C5),IF(C$5<1300,3%,IF(C$5<1500,4%,5%)),"") | D31: =IF(ISNUMBER(D5),IF(D$5<1300,3%,IF(D$5<1500,4%,5%)),"") | E31: =IF(ISNUMBER(E5),IF(E$5<1300,3%,IF(E$5<1500,4%,5%)),"") -> 0.04 | F31: =IF(ISNUMBER(F5),IF(F$5<1300,3%,IF(F$5<1500,4%,5%)),"") -> 0.04 | G31: =IF(ISNUMBER(G5),IF(G$5<1300,3%,IF(G$5<1500,4%,5%)),"") -> 0.04 | H31: =IF(ISNUMBER(H5),IF(H$5<1300,3%,IF(H$5<1500,4%,5%)),"") -> 0.04 | I31: =IF(ISNUMBER(I5),IF(I$5<1300,3%,IF(I$5<1500,4%,5%)),"") -> 0.04 | J31: =IF(ISNUMBER(J5),IF(J$5<1300,3%,IF(J$5<1500,4%,5%)),"") -> 0.04 | ... M31: =IF(ISNUMBER(M5),IF(M$5<1300,3%,IF(M$5<1500,4%,5%)),"")
A32: Redevance minière | B32: USD | C32: =IF(ISNUMBER(C31),C$6*C$31,0) -> 0 | D32: =IF(ISNUMBER(D31),D$6*D$31,0) -> 0 | E32: =IF(ISNUMBER(E31),E$6*E$31,0) -> 13000000 | F32: =IF(ISNUMBER(F31),F$6*F$31,0) -> 13000000 | G32: =IF(ISNUMBER(G31),G$6*G$31,0) -> 13000000 | H32: =IF(ISNUMBER(H31),H$6*H$31,0) -> 13000000 | I32: =IF(ISNUMBER(I31),I$6*I$31,0) -> 13000000 | J32: =IF(ISNUMBER(J31),J$6*J$31,0) -> 13000000 | ... M32: =IF(ISNUMBER(M31),M$6*M$31,0) -> 0 | N32: =SUM($C32:$M32) -> 104000000 | O32: =$C32+NPV(10%,$D32:$M32) -> 63049128
A34: +. LA TAXE SUR LA RENTE
A35: Taux de revalorisation des pertes | B35: % | C35: 0.02 | D35: 0.02 | E35: 0.02 | F35: 0.02 | G35: 0.02 | H35: 0.02 | I35: 0.02 | J35: 0.02 | K35: 0.02 | L35: 0.02 | M35: 0.02
A36: Flux nets de trésorerie revalorisés | B36: USD | C36: =IF(C19<0,C19*(1+C35),C19) -> -51000000 | D36: =IF(D19<0,D19*(1+D35),D19) -> -153000000 | E36: =IF(E19<0,E19*(1+E35),E19) -> 145000000 | F36: =IF(F19<0,F19*(1+F35),F19) -> 145000000 | G36: =IF(G19<0,G19*(1+G35),G19) -> 145000000 | H36: =IF(H19<0,H19*(1+H35),H19) -> 145000000 | I36: =IF(I19<0,I19*(1+I35),I19) -> 145000000 | J36: =IF(J19<0,J19*(1+J35),J19) -> 145000000 | ... M36: =IF(M19<0,M19*(1+M35),M19) -> -10200000 | N36: =SUM($C36:$M36) -> 945800000 | O36: =$C36+NPV(10%,$D36:$M36) -> 5.0921682e+08
A37: Taux de rendement interne | B37: % | C37: =IF(ISNUMBER(IRR($C36:C36)),IF(IRR($C36:C36)>0,IRR($C36:C36),""),"") | D37: =IF(ISNUMBER(IRR($C36:D36)),IF(IRR($C36:D36)>0,IRR($C36:D36),""),"") | E37: =IF(ISNUMBER(IRR($C36:E36)),IF(IRR($C36:E36)>0,IRR($C36:E36),""),"") | F37: =IF(ISNUMBER(IRR($C36:F36)),IF(IRR($C36:F36)>0,IRR($C36:F36),""),"") -> 0.22342633 | G37: =IF(ISNUMBER(IRR($C36:G36)),IF(IRR($C36:G36)>0,IRR($C36:G36),""),"") -> 0.41772238 | H37: =IF(ISNUMBER(IRR($C36:H36)),IF(IRR($C36:H36)>0,IRR($C36:H36),""),"") -> 0.5089236 | I37: =IF(ISNUMBER(IRR($C36:I36)),IF(IRR($C36:I36)>0,IRR($C36:I36),""),"") -> 0.55558431 | J37: =IF(ISNUMBER(IRR($C36:J36)),IF(IRR($C36:J36)>0,IRR($C36:J36),""),"") -> 0.58089254 | ... M37: =IF(ISNUMBER(IRR($C36:M36)),IF(IRR($C36:M36)>0,IRR($C36:M36),""),"") -> 0.60312112
A38: Seuil de déclenchement de la taxe sur la rente | B38: % | C38: 0.15 | D38: 0.15 | E38: 0.15 | F38: 0.15 | G38: 0.15 | H38: 0.15 | I38: 0.15 | J38: 0.15 | K38: 0.15 | L38: 0.15 | M38: 0.15
A39: Report des pertes revalorisées | D39: =IF(C40<0,C40,0) -> -51000000 | E39: =IF(D40<0,D40,0) -> -204000000 | F39: =IF(E40<0,E40,0) -> -59000000 | G39: =IF(F40<0,F40,0) -> 0 | H39: =IF(G40<0,G40,0) -> 0 | I39: =IF(H40<0,H40,0) -> 0 | J39: =IF(I40<0,I40,0) -> 0 | K39: =IF(J40<0,J40,0) -> 0 | ... M39: =IF(L40<0,L40,0) -> 0
A40: Flux nets de trésorerie après report des pertes revalorisées | B40: USD | C40: =C36+C39 -> -51000000 | D40: =D36+D39 -> -204000000 | E40: =E36+E39 -> -59000000 | F40: =F36+F39 -> 86000000 | G40: =G36+G39 -> 145000000 | H40: =H36+H39 -> 145000000 | I40: =I36+I39 -> 145000000 | J40: =J36+J39 -> 145000000 | ... M40: =M36+M39 -> -10200000 | N40: =SUM($C40:$M40) -> 631800000 | O40: =$C40+NPV(10%,$D40:$M40) -> 2.4993057e+08
A41: Taux de la taxe sur la rente | B41: % | C41: 0.2 | D41: 0.2 | E41: 0.2 | F41: 0.2 | G41: 0.2 | H41: 0.2 | I41: 0.2 | J41: 0.2 | K41: 0.2 | L41: 0.2 | M41: 0.2
A42: Taxe sur la rente | B42: USD | C42: =IF(C37<C38,0,IF(C40<0,0,C40*C41)) -> 0 | D42: =IF(D37<D38,0,IF(D40<0,0,D40*D41)) -> 0 | E42: =IF(E37<E38,0,IF(E40<0,0,E40*E41)) -> 0 | F42: =IF(F37<F38,0,IF(F40<0,0,F40*F41)) -> 17200000 | G42: =IF(G37<G38,0,IF(G40<0,0,G40*G41)) -> 29000000 | H42: =IF(H37<H38,0,IF(H40<0,0,H40*H41)) -> 29000000 | I42: =IF(I37<I38,0,IF(I40<0,0,I40*I41)) -> 29000000 | J42: =IF(J37<J38,0,IF(J40<0,0,J40*J41)) -> 29000000 | ... M42: =IF(M37<M38,0,IF(M40<0,0,M40*M41)) -> 0 | N42: =SUM($C42:$M42) -> 191200000 | O42: =$C42+NPV(10%,$D42:$M42) -> 1.078156e+08
A44: VIII. IMPÔT SUR LES SOCIETES (IS)
A45: Bénéfice avant report des pertes | B45: USD | C45: =C$6-C$16-C$23-C$28-C$32-C$42-'Amortissements et Emprunt'!C$25-'Amortissements et Emprunt'!C$119-'Amortissements et Emprunt'!C133-'Amortissements et Emprunt'!C$157 -> -7610000 | D45: =D$6-D$16-D$23-D$28-D$32-D$42-'Amortissements et Emprunt'!D$25-'Amortissements et Emprunt'!D$119-'Amortissements et Emprunt'!D133-'Amortissements et Emprunt'!D$157 -> -44510000 | E45: =E$6-E$16-E$23-E$28-E$32-E$42-'Amortissements et Emprunt'!E$25-'Amortissements et Emprunt'!E$119-'Amortissements et Emprunt'!E133-'Amortissements et Emprunt'!E$157 -> 100490000 | F45: =F$6-F$16-F$23-F$28-F$32-F$42-'Amortissements et Emprunt'!F$25-'Amortissements et Emprunt'!F$119-'Amortissements et Emprunt'!F133-'Amortissements et Emprunt'!F$157 -> 88890000 | G45: =G$6-G$16-G$23-G$28-G$32-G$42-'Amortissements et Emprunt'!G$25-'Amortissements et Emprunt'!G$119-'Amortissements et Emprunt'!G133-'Amortissements et Emprunt'!G$157 -> 80170000 | H45: =H$6-H$16-H$23-H$28-H$32-H$42-'Amortissements et Emprunt'!H$25-'Amortissements et Emprunt'!H$119-'Amortissements et Emprunt'!H133-'Amortissements et Emprunt'!H$157 -> 81630000 | I45: =I$6-I$16-I$23-I$28-I$32-I$42-'Amortissements et Emprunt'!I$25-'Amortissements et Emprunt'!I$119-'Amortissements et Emprunt'!I133-'Amortissements et Emprunt'!I$157 -> 87990000 | J45: =J$6-J$16-J$23-J$28-J$32-J$42-'Amortissements et Emprunt'!J$25-'Amortissements et Emprunt'!J$119-'Amortissements et Emprunt'!J133-'Amortissements et Emprunt'!J$157 -> 87990000 | ... M45: =M$6-M$16-M$23-M$28-M$32-M$42-'Amortissements et Emprunt'!M$25-'Amortissements et Emprunt'!M$119-'Amortissements et Emprunt'!M133-'Amortissements et Emprunt'!M$157 -> -25450000 | N45: =SUM($C45:$M45) -> 624590000 | O45: =$C45+NPV(10%,$D45:$M45) -> 3.701608e+08
A46: Report des pertes | B46: USD | D46: =IF(C47<0,C47,0) -> -7610000 | E46: =IF(D47<0,D47,0) -> -52120000 | F46: =IF(E47<0,E47,0) -> 0 | G46: =IF(F47<0,F47,0) -> 0 | H46: =IF(G47<0,G47,0) -> 0 | I46: =IF(H47<0,H47,0) -> 0 | J46: =IF(I47<0,I47,0) -> 0 | K46: =IF(J47<0,J47,0) -> 0 | ... M46: =IF(L47<0,L47,0) -> 0
A47: Bénéfice fiscal | B47: USD | C47: =C$45+C$46 -> -7610000 | D47: =D$45+D$46 -> -52120000 | E47: =E$45+E$46 -> 48370000 | F47: =F$45+F$46 -> 88890000 | G47: =G$45+G$46 -> 80170000 | H47: =H$45+H$46 -> 81630000 | I47: =I$45+I$46 -> 87990000 | J47: =J$45+J$46 -> 87990000 | ... M47: =M$45+M$46 -> -25450000 | N47: =SUM($C47:$M47) -> 564860000 | O47: =$C47+NPV(10%,$D47:$M47) -> 3.2016824e+08
A48: Taux de l'impôt sur les sociétés | B48: % | C48: 0.3 | D48: 0.3 | E48: 0.3 | F48: 0.3 | G48: 0.3 | H48: 0.3 | I48: 0.3 | J48: 0.3 | K48: 0.3 | L48: 0.3 | M48: 0.3
A49: Impôt sur les sociétés | B49: USD | C49: =IF(C$47>0,C$47*C$48,0) -> 0 | D49: =IF(D$47>0,D$47*D$48,0) -> 0 | E49: =IF(E$47>0,E$47*E$48,0) -> 14511000 | F49: =IF(F$47>0,F$47*F$48,0) -> 26667000 | G49: =IF(G$47>0,G$47*G$48,0) -> 24051000 | H49: =IF(H$47>0,H$47*H$48,0) -> 24489000 | I49: =IF(I$47>0,I$47*I$48,0) -> 26397000 | J49: =IF(J$47>0,J$47*J$48,0) -> 26397000 | ... M49: =IF(M$47>0,M$47*M$48,0) -> 0 | N49: =SUM($C49:$M49) -> 195012000 | O49: =$C49+NPV(10%,$D49:$M49) -> 1.1549164e+08
A51: IX. IMPÔT MINIMUM FORFAITAIRE (IMF)
A52: Montant minimum | B52: USD | C52: 2000 | D52: 2000 | E52: 2000 | F52: 2000 | G52: 2000 | H52: 2000 | I52: 2000 | J52: 2000 | K52: 2000 | L52: 2000 | M52: 2000
A53: Taux de l'impôt minimum forfaitaire | B53: % | C53: 0.01 | D53: 0.01 | E53: 0.01 | F53: 0.01 | G53: 0.01 | H53: 0.01 | I53: 0.01 | J53: 0.01 | K53: 0.01 | L53: 0.01 | M53: 0.01
A54: Impôt minimum forfaitaire | B54: USD | C54: =IF(C$6*C$53>C$52,C$6*C$53,C$52) -> 2000 | D54: =IF(D$6*D$53>D$52,D$6*D$53,D$52) -> 2000 | E54: =IF(E$6*E$53>E$52,E$6*E$53,E$52) -> 3250000 | F54: =IF(F$6*F$53>F$52,F$6*F$53,F$52) -> 3250000 | G54: =IF(G$6*G$53>G$52,G$6*G$53,G$52) -> 3250000 | H54: =IF(H$6*H$53>H$52,H$6*H$53,H$52) -> 3250000 | I54: =IF(I$6*I$53>I$52,I$6*I$53,I$52) -> 3250000 | J54: =IF(J$6*J$53>J$52,J$6*J$53,J$52) -> 3250000 | ... M54: =IF(M$6*M$53>M$52,M$6*M$53,M$52) -> 2000 | N54: =SUM($C54:$M54) -> 26006000 | O54: =$C54+NPV(10%,$D54:$M54) -> 15766871
A56: X. IMPÔT SUR LES SOCIETES (IS) / IMPÔT MINIMUM FORFAITAIRE (IMF)
A57: Impôt sur les sociétés / Impôt minimum forfaitaire | B57: USD | C57: =IF(C$54>C$49,C$54,C$49) -> 2000 | D57: =IF(D$54>D$49,D$54,D$49) -> 2000 | E57: =IF(E$54>E$49,E$54,E$49) -> 14511000 | F57: =IF(F$54>F$49,F$54,F$49) -> 26667000 | G57: =IF(G$54>G$49,G$54,G$49) -> 24051000 | H57: =IF(H$54>H$49,H$54,H$49) -> 24489000 | I57: =IF(I$54>I$49,I$54,I$49) -> 26397000 | J57: =IF(J$54>J$49,J$54,J$49) -> 26397000 | ... M57: =IF(M$54>M$49,M$54,M$49) -> 2000 | N57: =SUM($C57:$M57) -> 195018000 | O57: =$C57+NPV(10%,$D57:$M57) -> 1.1549623e+08
A59: XI. PRELEVEMENTS PUBLICS
A60: Total des prélèvements publics | B60: USD | C60: =C$23+C$28+C$32+C$42+C$57 -> 112000 | D60: =D$23+D$28+D$32+D$42+D$57 -> 12000 | E60: =E$23+E$28+E$32+E$42+E$57 -> 27521000 | F60: =F$23+F$28+F$32+F$42+F$57 -> 56877000 | G60: =G$23+G$28+G$32+G$42+G$57 -> 66061000 | H60: =H$23+H$28+H$32+H$42+H$57 -> 66499000 | I60: =I$23+I$28+I$32+I$42+I$57 -> 68407000 | J60: =J$23+J$28+J$32+J$42+J$57 -> 68407000 | ... M60: =M$23+M$28+M$32+M$42+M$57 -> 12000 | N60: =SUM($C60:$M60) -> 490428000 | O60: =$C60+NPV(10%,$D60:$M60) -> 2.865324e+08
A62: XII. FLUX NETS DE TRESORERIE APRES IMPÔTS
A63: Flux nets de trésorerie après impôts | B63: USD | C63: =C$19-C$60 -> -50112000 | D63: =D$19-D$60 -> -150012000 | E63: =E$19-E$60 -> 117479000 | F63: =F$19-F$60 -> 88123000 | G63: =G$19-G$60 -> 78939000 | H63: =H$19-H$60 -> 78501000 | I63: =I$19-I$60 -> 76593000 | J63: =J$19-J$60 -> 76593000 | ... M63: =M$19-M$60 -> -10012000 | N63: =SUM($C63:$M63) -> 459572000 | O63: =$C63+NPV(10%,$D63:$M63) -> 2.264888e+08
A64: Taux de rendement interne après impôts | B64: % | C64: =IF(ISNUMBER(IRR($C63:C63)),IF(IRR($C63:C63)>0,IRR($C63:C63),""),"") | D64: =IF(ISNUMBER(IRR($C63:D63)),IF(IRR($C63:D63)>0,IRR($C63:D63),""),"") | E64: =IF(ISNUMBER(IRR($C63:E63)),IF(IRR($C63:E63)>0,IRR($C63:E63),""),"") | F64: =IF(ISNUMBER(IRR($C63:F63)),IF(IRR($C63:F63)>0,IRR($C63:F63),""),"") -> 0.016218361 | G64: =IF(ISNUMBER(IRR($C63:G63)),IF(IRR($C63:G63)>0,IRR($C63:G63),""),"") -> 0.18482883 | H64: =IF(ISNUMBER(IRR($C63:H63)),IF(IRR($C63:H63)>0,IRR($C63:H63),""),"") -> 0.27560329 | I64: =IF(ISNUMBER(IRR($C63:I63)),IF(IRR($C63:I63)>0,IRR($C63:I63),""),"") -> 0.32645512 | J64: =IF(ISNUMBER(IRR($C63:J63)),IF(IRR($C63:J63)>0,IRR($C63:J63),""),"") -> 0.35715004 | ... M64: =IF(ISNUMBER(IRR($C63:M63)),IF(IRR($C63:M63)>0,IRR($C63:M63),""),"") -> 0.38765507
A66: XIII. PARTAGE DE LA RENTE MINIERE
A67: Rente minière | B67: USD | N67: =N$19 -> 950000000 | O67: =O$19 -> 5.130212e+08
A68: Part de l'Etat | B68: % | N68: =N$60/N$67 -> 0.51624 | O68: =O$60/O$67 -> 0.55851961
A69: Part de l'investisseur | B69: % | N69: =N$63/N$67 -> 0.48376 | O69: =O$63/O$67 -> 0.44148039

Sheet Amortissements et Emprunt
A1: Nom | B1: Unité | C1: Année 1 | D1: Année 2 | E1: Année 3 | F1: Année 4 | G1: Année 5 | H1: Année 6 | I1: Année 7 | J1: Année 8 | K1: Année 9 | L1: Année 10 | M1: Année 11
A3: Durée restante maximum | B3: Années | C3: 11 | D3: 10 | E3: 9 | F3: 8 | G3: 7 | H3: 6 | I3: 5 | J3: 4 | K3: 3 | L3: 2 | M3: 1
A5: I. AMORTISSEMENTS DES CONSTRUCTIONS INDUSTRIELLES
A6: Durée d'amortissement linéaire | B6: Années | C6: 10
A7: Coefficient d'amortissement dégressif | B7: Coefficient | C7: 1
A9: Immobilisations de l'année A1
A10: Durée restante | B10: Années | C10: =IF($C$6<C$3,$C$6,C$3) -> 10 | D10: =IF(C10=0,0,IF(C10-1<D$3,C10-1,D$3)) -> 9 | E10: =IF(D10=0,0,IF(D10-1<E$3,D10-1,E$3)) -> 8 | F10: =IF(E10=0,0,IF(E10-1<F$3,E10-1,F$3)) -> 7 | G10: =IF(F10=0,0,IF(F10-1<G$3,F10-1,G$3)) -> 6 | H10: =IF(G10=0,0,IF(G10-1<H$3,G10-1,H$3)) -> 5 | I10: =IF(H10=0,0,IF(H10-1<I$3,H10-1,I$3)) -> 4 | J10: =IF(I10=0,0,IF(I10-1<J$3,I10-1,J$3)) -> 3 | K10: =IF(J10=0,0,IF(J10-1<K$3,J10-1,K$3)) -> 2 | ... M10: =IF(L10=0,0,IF(L10-1<M$3,L10-1,M$3)) -> 0
A11: Base amortissable | B11: USD | C11: =Modèle!C$9 -> 50000000 | D11: =C15 -> 45000000 | E11: =D15 -> 40000000 | F11: =E15 -> 35000000 | G11: =F15 -> 30000000 | H11: =G15 -> 25000000 | I11: =H15 -> 20000000 | J11: =I15 -> 15000000 | K11: =J15 -> 10000000 | ... M11: =L15 -> 0
A12: Inverse de la durée restante | B12: % | C12: =IF(C10=0,0,1/C10) -> 0.1 | D12: =IF(D10=0,0,1/D10) -> 0.11111111 | E12: =IF(E10=0,0,1/E10) -> 0.125 | F12: =IF(F10=0,0,1/F10) -> 0.14285714 | G12: =IF(G10=0,0,1/G10) -> 0.16666667 | H12: =IF(H10=0,0,1/H10) -> 0.2 | I12: =IF(I10=0,0,1/I10) -> 0.25 | J12: =IF(J10=0,0,1/J10) -> 0.33333333 | ... M12: =IF(M10=0,0,1/M10) -> 0
A13: Taux dégressif | B13: % | C13: =IF(C10=0,0,IF($C$7*1/$C$6>C12,$C$7*1/$C$6,C12)) -> 0.1 | D13: =IF(D10=0,0,IF($C$7*1/$C$6>D12,$C$7*1/$C$6,D12)) -> 0.11111111 | E13: =IF(E10=0,0,IF($C$7*1/$C$6>E12,$C$7*1/$C$6,E12)) -> 0.125 | F13: =IF(F10=0,0,IF($C$7*1/$C$6>F12,$C$7*1/$C$6,F12)) -> 0.14285714 | G13: =IF(G10=0,0,IF($C$7*1/$C$6>G12,$C$7*1/$C$6,G12)) -> 0.16666667 | H13: =IF(H10=0,0,IF($C$7*1/$C$6>H12,$C$7*1/$C$6,H12)) -> 0.2 | I13: =IF(I10=0,0,IF($C$7*1/$C$6>I12,$C$7*1/$C$6,I12)) -> 0.25 | J13: =IF(J10=0,0,IF($C$7*1/$C$6>J12,$C$7*1/$C$6,J12)) -> 0.33333333 | ... M13: =IF(M10=0,0,IF($C$7*1/$C$6>M12,$C$7*1/$C$6,M12)) -> 0
A14: Charge d'amortissement | B14: USD | C14: =C11*C13 -> 5000000 | D14: =D11*D13 -> 5000000 | E14: =E11*E13 -> 5000000 | F14: =F11*F13 -> 5000000 | G14: =G11*G13 -> 5000000 | H14: =H11*H13 -> 5000000 | I14: =I11*I13 -> 5000000 | J14: =J11*J13 -> 5000000 | ... M14: =M11*M13 -> 0
A15: Amortissement restant | B15: USD | C15: =C11-C14 -> 45000000 | D15: =D11-D14 -> 40000000 | E15: =E11-E14 -> 35000000 | F15: =F11-F14 -> 30000000 | G15: =G11-G14 -> 25000000 | H15: =H11-H14 -> 20000000 | I15: =I11-I14 -> 15000000 | J15: =J11-J14 -> 10000000 | ... M15: =M11-M14 -> 0
A17: Immobilisations de l'année A2
A18: Durée restante | B18: Années | D18: =IF($C$6<D$3,$C$6,D$3) -> 10 | E18: =IF(D18=0,0,IF(D18-1<E$3,D18-1,E$3)) -> 9 | F18: =IF(E18=0,0,IF(E18-1<F$3,E18-1,F$3)) -> 8 | G18: =IF(F18=0,0,IF(F18-1<G$3,F18-1,G$3)) -> 7 | H18: =IF(G18=0,0,IF(G18-1<H$3,G18-1,H$3)) -> 6 | I18: =IF(H18=0,0,IF(H18-1<I$3,H18-1,I$3)) -> 5 | J18: =IF(I18=0,0,IF(I18-1<J$3,I18-1,J$3)) -> 4 | K18: =IF(J18=0,0,IF(J18-1<K$3,J18-1,K$3)) -> 3 | L18: =IF(K18=0,0,IF(K18-1<L$3,K18-1,L$3)) -> 2 | M18: =IF(L18=0,0,IF(L18-1<M$3,L18-1,M$3)) -> 1
A19: Base amortissable | B19: USD | D19: =Modèle!D$9 -> 100000000 | E19: =D23 -> 90000000 | F19: =E23 -> 80000000 | G19: =F23 -> 70000000 | H19: =G23 -> 60000000 | I19: =H23 -> 50000000 | J19: =I23 -> 40000000 | K19: =J23 -> 30000000 | L19: =K23 -> 20000000 | M19: =L23 -> 10000000
A20: Inverse de la durée restante | B20: % | D20: =IF(D18=0,0,1/D18) -> 0.1 | E20: =IF(E18=0,0,1/E18) -> 0.11111111 | F20: =IF(F18=0,0,1/F18) -> 0.125 | G20: =IF(G18=0,0,1/G18) -> 0.14285714 | H20: =IF(H18=0,0,1/H18) -> 0.16666667 | I20: =IF(I18=0,0,1/I18) -> 0.2 | J20: =IF(J18=0,0,1/J18) -> 0.25 | K20: =IF(K18=0,0,1/K18) -> 0.33333333 | ... M20: =IF(M18=0,0,1/M18) -> 1
A21: Taux dégressif | B21: % | D21: =IF(D18=0,0,IF($C$7*1/$C$6>D20,$C$7*1/$C$6,D20)) -> 0.1 | E21: =IF(E18=0,0,IF($C$7*1/$C$6>E20,$C$7*1/$C$6,E20)) -> 0.11111111 | F21: =IF(F18=0,0,IF($C$7*1/$C$6>F20,$C$7*1/$C$6,F20)) -> 0.125 | G21: =IF(G18=0,0,IF($C$7*1/$C$6>G20,$C$7*1/$C$6,G20)) -> 0.14285714 | H21: =IF(H18=0,0,IF($C$7*1/$C$6>H20,$C$7*1/$C$6,H20)) -> 0.16666667 | I21: =IF(I18=0,0,IF($C$7*1/$C$6>I20,$C$7*1/$C$6,I20)) -> 0.2 | J21: =IF(J18=0,0,IF($C$7*1/$C$6>J20,$C$7*1/$C$6,J20)) -> 0.25 | K21: =IF(K18=0,0,IF($C$7*1/$C$6>K20,$C$7*1/$C$6,K20)) -> 0.33333333 | ... M21: =IF(M18=0,0,IF($C$7*1/$C$6>M20,$C$7*1/$C$6,M20)) -> 1
A22: Charge d'amortissement | B22: USD | D22: =D19*D21 -> 10000000 | E22: =E19*E21 -> 10000000 | F22: =F19*F21 -> 10000000 | G22: =G19*G21 -> 10000000 | H22: =H19*H21 -> 10000000 | I22: =I19*I21 -> 10000000 | J22: =J19*J21 -> 10000000 | K22: =K19*K21 -> 10000000 | ... M22: =M19*M21 -> 10000000
A23: Amortissement restant | B23: USD | D23: =D19-D22 -> 90000000 | E23: =E19-E22 -> 80000000 | F23: =F19-F22 -> 70000000 | G23: =G19-G22 -> 60000000 | H23: =H19-H22 -> 50000000 | I23: =I19-I22 -> 40000000 | J23: =J19-J22 -> 30000000 | K23: =K19-K22 -> 20000000 | ... M23: =M19-M22 -> 0
A25: Amortissements des constructions industrielles | B25: USD | C25: =C$14+C$22 -> 5000000 | D25: =D$14+D$22 -> 15000000 | E25: =E$14+E$22 -> 15000000 | F25: =F$14+F$22 -> 15000000 | G25: =G$14+G$22 -> 15000000 | H25: =H$14+H$22 -> 15000000 | I25: =I$14+I$22 -> 15000000 | J25: =J$14+J$22 -> 15000000 | ... M25: =M$14+M$22 -> 10000000
A27: II. AMORTISSEMENTS DES BIENS D'EQUIPEMENT
A28: Durée d'amortissement linéaire | B28: Années | C28: 5
A29: Coefficient d'amortissement dégressif | B29: Coefficient | C29: 2
A31: Immobilisations de l'année A1
A32: Durée restante | B32: Années | C32: =IF($C$28<C$3,$C$28,C$3) -> 5 | D32: =IF(C32=0,0,IF(C32-1<D$3,C32-1,D$3)) -> 4 | E32: =IF(D32=0,0,IF(D32-1<E$3,D32-1,E$3)) -> 3 | F32: =IF(E32=0,0,IF(E32-1<F$3,E32-1,F$3)) -> 2 | G32: =IF(F32=0,0,IF(F32-1<G$3,F32-1,G$3)) -> 1 | H32: =IF(G32=0,0,IF(G32-1<H$3,G32-1,H$3)) -> 0 | I32: =IF(H32=0,0,IF(H32-1<I$3,H32-1,I$3)) -> 0 | J32: =IF(I32=0,0,IF(I32-1<J$3,I32-1,J$3)) -> 0 | K32: =IF(J32=0,0,IF(J32-1<K$3,J32-1,K$3)) -> 0 | ... M32: =IF(L32=0,0,IF(L32-1<M$3,L32-1,M$3)) -> 0
A33: Base amortissable | B33: USD | C33: =Modèle!C$10 -> 0 | D33: =C37 -> 0 | E33: =D37 -> 0 | F33: =E37 -> 0 | G33: =F37 -> 0 | H33: =G37 -> 0 | I33: =H37 -> 0 | J33: =I37 -> 0 | K33: =J37 -> 0 | ... M33: =L37 -> 0
A34: Inverse de la durée restante | B34: % | C34: =IF(C32=0,0,1/C32) -> 0.2 | D34: =IF(D32=0,0,1/D32) -> 0.25 | E34: =IF(E32=0,0,1/E32) -> 0.33333333 | F34: =IF(F32=0,0,1/F32) -> 0.5 | G34: =IF(G32=0,0,1/G32) -> 1 | H34: =IF(H32=0,0,1/H32) -> 0 | I34: =IF(I32=0,0,1/I32) -> 0 | J34: =IF(J32=0,0,1/J32) -> 0 | ... M34: =IF(M32=0,0,1/M32) -> 0
A35: Taux dégressif | B35: % | C35: =IF(C32=0,0,IF($C$29*1/$C$28>C34,$C$29*1/$C$28,C34)) -> 0.4 | D35: =IF(D32=0,0,IF($C$29*1/$C$28>D34,$C$29*1/$C$28,D34)) -> 0.4 | E35: =IF(E32=0,0,IF($C$29*1/$C$28>E34,$C$29*1/$C$28,E34)) -> 0.4 | F35: =IF(F32=0,0,IF($C$29*1/$C$28>F34,$C$29*1/$C$28,F34)) -> 0.5 | G35: =IF(G32=0,0,IF($C$29*1/$C$28>G34,$C$29*1/$C$28,G34)) -> 1 | H35: =IF(H32=0,0,IF($C$29*1/$C$28>H34,$C$29*1/$C$28,H34)) -> 0 | I35: =IF(I32=0,0,IF($C$29*1/$C$28>I34,$C$29*1/$C$28,I34)) -> 0 | J35: =IF(J32=0,0,IF($C$29*1/$C$28>J34,$C$29*1/$C$28,J34)) -> 0 | ... M35: =IF(M32=0,0,IF($C$29*1/$C$28>M34,$C$29*1/$C$28,M34)) -> 0
A36: Charge d'amortissement | B36: USD | C36: =C33*C35 -> 0 | D36: =D33*D35 -> 0 | E36: =E33*E35 -> 0 | F36: =F33*F35 -> 0 | G36: =G33*G35 -> 0 | H36: =H33*H35 -> 0 | I36: =I33*I35 -> 0 | J36: =J33*J35 -> 0 | ... M36: =M33*M35 -> 0
A37: Amortissement restant | B37: USD | C37: =C33-C36 -> 0 | D37: =D33-D36 -> 0 | E37: =E33-E36 -> 0 | F37: =F33-F36 -> 0 | G37: =G33-G36 -> 0 | H37: =H33-H36 -> 0 | I37: =I33-I36 -> 0 | J37: =J33-J36 -> 0 | ... M37: =M33-M36 -> 0
A39: Immobilisations de l'année A2
A40: Durée restante | B40: Années | D40: =IF($C$28<D$3,$C$28,D$3) -> 5 | E40: =IF(D40=0,0,IF(D40-1<E$3,D40-1,E$3)) -> 4 | F40: =IF(E40=0,0,IF(E40-1<F$3,E40-1,F$3)) -> 3 | G40: =IF(F40=0,0,IF(F40-1<G$3,F40-1,G$3)) -> 2 | H40: =IF(G40=0,0,IF(G40-1<H$3,G40-1,H$3)) -> 1 | I40: =IF(H40=0,0,IF(H40-1<I$3,H40-1,I$3)) -> 0 | J40: =IF(I40=0,0,IF(I40-1<J$3,I40-1,J$3)) -> 0 | K40: =IF(J40=0,0,IF(J40-1<K$3,J40-1,K$3)) -> 0 | L40: =IF(K40=0,0,IF(K40-1<L$3,K40-1,L$3)) -> 0 | M40: =IF(L40=0,0,IF(L40-1<M$3,L40-1,M$3)) -> 0
A41: Base amortissable | B41: USD | D41: =Modèle!D$10 -> 50000000 | E41: =D45 -> 30000000 | F41: =E45 -> 18000000 | G41: =F45 -> 10800000 | H41: =G45 -> 5400000 | I41: =H45 -> 0 | J41: =I45 -> 0 | K41: =J45 -> 0 | L41: =K45 -> 0 | M41: =L45 -> 0
A42: Inverse de la durée restante | B42: % | D42: =IF(D40=0,0,1/D40) -> 0.2 | E42: =IF(E40=0,0,1/E40) -> 0.25 | F42: =IF(F40=0,0,1/F40) -> 0.33333333 | G42: =IF(G40=0,0,1/G40) -> 0.5 | H42: =IF(H40=0,0,1/H40) -> 1 | I42: =IF(I40=0,0,1/I40) -> 0 | J42: =IF(J40=0,0,1/J40) -> 0 | K42: =IF(K40=0,0,1/K40) -> 0 | ... M42: =IF(M40=0,0,1/M40) -> 0
A43: Taux dégressif | B43: % | D43: =IF(D40=0,0,IF($C$29*1/$C$28>D42,$C$29*1/$C$28,D42)) -> 0.4 | E43: =IF(E40=0,0,IF($C$29*1/$C$28>E42,$C$29*1/$C$28,E42)) -> 0.4 | F43: =IF(F40=0,0,IF($C$29*1/$C$28>F42,$C$29*1/$C$28,F42)) -> 0.4 | G43: =IF(G40=0,0,IF($C$29*1/$C$28>G42,$C$29*1/$C$28,G42)) -> 0.5 | H43: =IF(H40=0,0,IF($C$29*1/$C$28>H42,$C$29*1/$C$28,H42)) -> 1 | I43: =IF(I40=0,0,IF($C$29*1/$C$28>I42,$C$29*1/$C$28,I42)) -> 0 | J43: =IF(J40=0,0,IF($C$29*1/$C$28>J42,$C$29*1/$C$28,J42)) -> 0 | K43: =IF(K40=0,0,IF($C$29*1/$C$28>K42,$C$29*1/$C$28,K42)) -> 0 | ... M43: =IF(M40=0,0,IF($C$29*1/$C$28>M42,$C$29*1/$C$28,M42)) -> 0
A44: Charge d'amortissement | B44: USD | D44: =D41*D43 -> 20000000 | E44: =E41*E43 -> 12000000 | F44: =F41*F43 -> 7200000 | G44: =G41*G43 -> 5400000 | H44: =H41*H43 -> 5400000 | I44: =I41*I43 -> 0 | J44: =J41*J43 -> 0 | K44: =K41*K43 -> 0 | ... M44: =M41*M43 -> 0
A45: Amortissement restant | B45: USD | D45: =D41-D44 -> 30000000 | E45: =E41-E44 -> 18000000 | F45: =F41-F44 -> 10800000 | G45: =G41-G44 -> 5400000 | H45: =H41-H44 -> 0 | I45: =I41-I44 -> 0 | J45: =J41-J44 -> 0 | K45: =K41-K44 -> 0 | ... M45: =M41-M44 -> 0
A47: Immobilisations de l'année A3
A48: Durée restante | B48: Années | E48: =IF($C$28<E$3,$C$28,E$3) -> 5 | F48: =IF(E48=0,0,IF(E48-1<F$3,E48-1,F$3)) -> 4 | G48: =IF(F48=0,0,IF(F48-1<G$3,F48-1,G$3)) -> 3 | H48: =IF(G48=0,0,IF(G48-1<H$3,G48-1,H$3)) -> 2 | I48: =IF(H48=0,0,IF(H48-1<I$3,H48-1,I$3)) -> 1 | J48: =IF(I48=0,0,IF(I48-1<J$3,I48-1,J$3)) -> 0 | K48: =IF(J48=0,0,IF(J48-1<K$3,J48-1,K$3)) -> 0 | L48: =IF(K48=0,0,IF(K48-1<L$3,K48-1,L$3)) -> 0 | M48: =IF(L48=0,0,IF(L48-1<M$3,L48-1,M$3)) -> 0
A49: Base amortissable | B49: USD | E49: =Modèle!E$10 -> 5000000 | F49: =E53 -> 3000000 | G49: =F53 -> 1800000 | H49: =G53 -> 1080000 | I49: =H53 -> 540000 | J49: =I53 -> 0 | K49: =J53 -> 0 | L49: =K53 -> 0 | M49: =L53 -> 0
A50: Inverse de la durée restante | B50: % | E50: =IF(E48=0,0,1/E48) -> 0.2 | F50: =IF(F48=0,0,1/F48) -> 0.25 | G50: =IF(G48=0,0,1/G48) -> 0.33333333 | H50: =IF(H48=0,0,1/H48) -> 0.5 | I50: =IF(I48=0,0,1/I48) -> 1 | J50: =IF(J48=0,0,1/J48) -> 0 | K50: =IF(K48=0,0,1/K48) -> 0 | L50: =IF(L48=0,0,1/L48) -> 0 | M50: =IF(M48=0,0,1/M48) -> 0
A51: Taux dégressif | B51: % | E51: =IF(E48=0,0,IF($C$29*1/$C$28>E50,$C$29*1/$C$28,E50)) -> 0.4 | F51: =IF(F48=0,0,IF($C$29*1/$C$28>F50,$C$29*1/$C$28,F50)) -> 0.4 | G51: =IF(G48=0,0,IF($C$29*1/$C$28>G50,$C$29*1/$C$28,G50)) -> 0.4 | H51: =IF(H48=0,0,IF($C$29*1/$C$28>H50,$C$29*1/$C$28,H50)) -> 0.5 | I51: =IF(I48=0,0,IF($C$29*1/$C$28>I50,$C$29*1/$C$28,I50)) -> 1 | J51: =IF(J48=0,0,IF($C$29*1/$C$28>J50,$C$29*1/$C$28,J50)) -> 0 | K51: =IF(K48=0,0,IF($C$29*1/$C$28>K50,$C$29*1/$C$28,K50)) -> 0 | L51: =IF(L48=0,0,IF($C$29*1/$C$28>L50,$C$29*1/$C$28,L50)) -> 0 | M51: =IF(M48=0,0,IF($C$29*1/$C$28>M50,$C$29*1/$C$28,M50)) -> 0
A52: Charge d'amortissement | B52: USD | E52: =E49*E51 -> 2000000 | F52: =F49*F51 -> 1200000 | G52: =G49*G51 -> 720000 | H52: =H49*H51 -> 540000 | I52: =I49*I51 -> 540000 | J52: =J49*J51 -> 0 | K52: =K49*K51 -> 0 | L52: =L49*L51 -> 0 | M52: =M49*M51 -> 0
A53: Amortissement restant | B53: USD | E53: =E49-E52 -> 3000000 | F53: =F49-F52 -> 1800000 | G53: =G49-G52 -> 1080000 | H53: =H49-H52 -> 540000 | I53: =I49-I52 -> 0 | J53: =J49-J52 -> 0 | K53: =K49-K52 -> 0 | L53: =L49-L52 -> 0 | M53: =M49-M52 -> 0
A55: Immobilisations de l'année A4
A56: Durée restante | B56: Années | F56: =IF($C$28<F$3,$C$28,F$3) -> 5 | G56: =IF(F56=0,0,IF(F56-1<G$3,F56-1,G$3)) -> 4 | H56: =IF(G56=0,0,IF(G56-1<H$3,G56-1,H$3)) -> 3 | I56: =IF(H56=0,0,IF(H56-1<I$3,H56-1,I$3)) -> 2 | J56: =IF(I56=0,0,IF(I56-1<J$3,I56-1,J$3)) -> 1 | K56: =IF(J56=0,0,IF(J56-1<K$3,J56-1,K$3)) -> 0 | L56: =IF(K56=0,0,IF(K56-1<L$3,K56-1,L$3)) -> 0 | M56: =IF(L56=0,0,IF(L56-1<M$3,L56-1,M$3)) -> 0
A57: Base amortissable | B57: USD | F57: =Modèle!F$10 -> 5000000 | G57: =F61 -> 3000000 | H57: =G61 -> 1800000 | I57: =H61 -> 1080000 | J57: =I61 -> 540000 | K57: =J61 -> 0 | L57: =K61 -> 0 | M57: =L61 -> 0
A58: Inverse de la durée restante | B58: % | F58: =IF(F56=0,0,1/F56) -> 0.2 | G58: =IF(G56=0,0,1/G56) -> 0.25 | H58: =IF(H56=0,0,1/H56) -> 0.33333333 | I58: =IF(I56=0,0,1/I56) -> 0.5 | J58: =IF(J56=0,0,1/J56) -> 1 | K58: =IF(K56=0,0,1/K56) -> 0 | L58: =IF(L56=0,0,1/L56) -> 0 | M58: =IF(M56=0,0,1/M56) -> 0
A59: Taux dégressif | B59: % | F59: =IF(F56=0,0,IF($C$29*1/$C$28>F58,$C$29*1/$C$28,F58)) -> 0.4 | G59: =IF(G56=0,0,IF($C$29*1/$C$28>G58,$C$29*1/$C$28,G58)) -> 0.4 | H59: =IF(H56=0,0,IF($C$29*1/$C$28>H58,$C$29*1/$C$28,H58)) -> 0.4 | I59: =IF(I56=0,0,IF($C$29*1/$C$28>I58,$C$29*1/$C$28,I58)) -> 0.5 | J59: =IF(J56=0,0,IF($C$29*1/$C$28>J58,$C$29*1/$C$28,J58)) -> 1 | K59: =IF(K56=0,0,IF($C$29*1/$C$28>K58,$C$29*1/$C$28,K58)) -> 0 | L59: =IF(L56=0,0,IF($C$29*1/$C$28>L58,$C$29*1/$C$28,L58)) -> 0 | M59: =IF(M56=0,0,IF($C$29*1/$C$28>M58,$C$29*1/$C$28,M58)) -> 0
A60: Charge d'amortissement | B60: USD | F60: =F57*F59 -> 2000000 | G60: =G57*G59 -> 1200000 | H60: =H57*H59 -> 720000 | I60: =I57*I59 -> 540000 | J60: =J57*J59 -> 540000 | K60: =K57*K59 -> 0 | L60: =L57*L59 -> 0 | M60: =M57*M59 -> 0
A61: Amortissement restant | B61: USD | F61: =F57-F60 -> 3000000 | G61: =G57-G60 -> 1800000 | H61: =H57-H60 -> 1080000 | I61: =I57-I60 -> 540000 | J61: =J57-J60 -> 0 | K61: =K57-K60 -> 0 | L61: =L57-L60 -> 0 | M61: =M57-M60 -> 0
A63: Immobilisations de l'année A5
A64: Durée restante | B64: Années | G64: =IF($C$28<G$3,$C$28,G$3) -> 5 | H64: =IF(G64=0,0,IF(G64-1<H$3,G64-1,H$3)) -> 4 | I64: =IF(H64=0,0,IF(H64-1<I$3,H64-1,I$3)) -> 3 | J64: =IF(I64=0,0,IF(I64-1<J$3,I64-1,J$3)) -> 2 | K64: =IF(J64=0,0,IF(J64-1<K$3,J64-1,K$3)) -> 1 | L64: =IF(K64=0,0,IF(K64-1<L$3,K64-1,L$3)) -> 0 | M64: =IF(L64=0,0,IF(L64-1<M$3,L64-1,M$3)) -> 0
A65: Base amortissable | B65: USD | G65: =Modèle!G$10 -> 5000000 | H65: =G69 -> 3000000 | I65: =H69 -> 1800000 | J65: =I69 -> 1080000 | K65: =J69 -> 540000 | L65: =K69 -> 0 | M65: =L69 -> 0
A66: Inverse de la durée restante | B66: % | G66: =IF(G64=0,0,1/G64) -> 0.2 | H66: =IF(H64=0,0,1/H64) -> 0.25 | I66: =IF(I64=0,0,1/I64) -> 0.33333333 | J66: =IF(J64=0,0,1/J64) -> 0.5 | K66: =IF(K64=0,0,1/K64) -> 1 | L66: =IF(L64=0,0,1/L64) -> 0 | M66: =IF(M64=0,0,1/M64) -> 0
A67: Taux dégressif | B67: % | G67: =IF(G64=0,0,IF($C$29*1/$C$28>G66,$C$29*1/$C$28,G66)) -> 0.4 | H67: =IF(H64=0,0,IF($C$29*1/$C$28>H66,$C$29*1/$C$28,H66)) -> 0.4 | I67: =IF(I64=0,0,IF($C$29*1/$C$28>I66,$C$29*1/$C$28,I66)) -> 0.4 | J67: =IF(J64=0,0,IF($C$29*1/$C$28>J66,$C$29*1/$C$28,J66)) -> 0.5 | K67: =IF(K64=0,0,IF($C$29*1/$C$28>K66,$C$29*1/$C$28,K66)) -> 1 | L67: =IF(L64=0,0,IF($C$29*1/$C$28>L66,$C$29*1/$C$28,L66)) -> 0 | M67: =IF(M64=0,0,IF($C$29*1/$C$28>M66,$C$29*1/$C$28,M66)) -> 0
A68: Charge d'amortissement | B68: USD | G68: =G65*G67 -> 2000000 | H68: =H65*H67 -> 1200000 | I68: =I65*I67 -> 720000 | J68: =J65*J67 -> 540000 | K68: =K65*K67 -> 540000 | L68: =L65*L67 -> 0 | M68: =M65*M67 -> 0
A69: Amortissement restant | B69: USD | G69: =G65-G68 -> 3000000 | H69: =H65-H68 -> 1800000 | I69: =I65-I68 -> 1080000 | J69: =J65-J68 -> 540000 | K69: =K65-K68 -> 0 | L69: =L65-L68 -> 0 | M69: =M65-M68 -> 0
A71: Immobilisations de l'année A6
A72: Durée restante | B72: Années | H72: =IF($C$28<H$3,$C$28,H$3) -> 5 | I72: =IF(H72=0,0,IF(H72-1<I$3,H72-1,I$3)) -> 4 | J72: =IF(I72=0,0,IF(I72-1<J$3,I72-1,J$3)) -> 3 | K72: =IF(J72=0,0,IF(J72-1<K$3,J72-1,K$3)) -> 2 | L72: =IF(K72=0,0,IF(K72-1<L$3,K72-1,L$3)) -> 1 | M72: =IF(L72=0,0,IF(L72-1<M$3,L72-1,M$3)) -> 0
A73: Base amortissable | B73: USD | H73: =Modèle!H$10 -> 5000000 | I73: =H77 -> 3000000 | J73: =I77 -> 1800000 | K73: =J77 -> 1080000 | L73: =K77 -> 540000 | M73: =L77 -> 0
A74: Inverse de la durée restante | B74: % | H74: =IF(H72=0,0,1/H72) -> 0.2 | I74: =IF(I72=0,0,1/I72) -> 0.25 | J74: =IF(J72=0,0,1/J72) -> 0.33333333 | K74: =IF(K72=0,0,1/K72) -> 0.5 | L74: =IF(L72=0,0,1/L72) -> 1 | M74: =IF(M72=0,0,1/M72) -> 0
A75: Taux dégressif | B75: % | H75: =IF(H72=0,0,IF($C$29*1/$C$28>H74,$C$29*1/$C$28,H74)) -> 0.4 | I75: =IF(I72=0,0,IF($C$29*1/$C$28>I74,$C$29*1/$C$28,I74)) -> 0.4 | J75: =IF(J72=0,0,IF($C$29*1/$C$28>J74,$C$29*1/$C$28,J74)) -> 0.4 | K75: =IF(K72=0,0,IF($C$29*1/$C$28>K74,$C$29*1/$C$28,K74)) -> 0.5 | L75: =IF(L72=0,0,IF($C$29*1/$C$28>L74,$C$29*1/$C$28,L74)) -> 1 | M75: =IF(M72=0,0,IF($C$29*1/$C$28>M74,$C$29*1/$C$28,M74)) -> 0
A76: Charge d'amortissement | B76: USD | H76: =H73*H75 -> 2000000 | I76: =I73*I75 -> 1200000 | J76: =J73*J75 -> 720000 | K76: =K73*K75 -> 540000 | L76: =L73*L75 -> 540000 | M76: =M73*M75 -> 0
A77: Amortissement restant | B77: USD | H77: =H73-H76 -> 3000000 | I77: =I73-I76 -> 1800000 | J77: =J73-J76 -> 1080000 | K77: =K73-K76 -> 540000 | L77: =L73-L76 -> 0 | M77: =M73-M76 -> 0
A79: Immobilisations de l'année A7
A80: Durée restante | B80: Années | I80: =IF($C$28<I$3,$C$28,I$3) -> 5 | J80: =IF(I80=0,0,IF(I80-1<J$3,I80-1,J$3)) -> 4 | K80: =IF(J80=0,0,IF(J80-1<K$3,J80-1,K$3)) -> 3 | L80: =IF(K80=0,0,IF(K80-1<L$3,K80-1,L$3)) -> 2 | M80: =IF(L80=0,0,IF(L80-1<M$3,L80-1,M$3)) -> 1
A81: Base amortissable | B81: USD | I81: =Modèle!I$10 -> 5000000 | J81: =I85 -> 3000000 | K81: =J85 -> 1800000 | L81: =K85 -> 1080000 | M81: =L85 -> 540000
A82: Inverse de la durée restante | B82: % | I82: =IF(I80=0,0,1/I80) -> 0.2 | J82: =IF(J80=0,0,1/J80) -> 0.25 | K82: =IF(K80=0,0,1/K80) -> 0.33333333 | L82: =IF(L80=0,0,1/L80) -> 0.5 | M82: =IF(M80=0,0,1/M80) -> 1
A83: Taux dégressif | B83: % | I83: =IF(I80=0,0,IF($C$29*1/$C$28>I82,$C$29*1/$C$28,I82)) -> 0.4 | J83: =IF(J80=0,0,IF($C$29*1/$C$28>J82,$C$29*1/$C$28,J82)) -> 0.4 | K83: =IF(K80=0,0,IF($C$29*1/$C$28>K82,$C$29*1/$C$28,K82)) -> 0.4 | L83: =IF(L80=0,0,IF($C$29*1/$C$28>L82,$C$29*1/$C$28,L82)) -> 0.5 | M83: =IF(M80=0,0,IF($C$29*1/$C$28>M82,$C$29*1/$C$28,M82)) -> 1
A84: Charge d'amortissement | B84: USD | I84: =I81*I83 -> 2000000 | J84: =J81*J83 -> 1200000 | K84: =K81*K83 -> 720000 | L84: =L81*L83 -> 540000 | M84: =M81*M83 -> 540000
A85: Amortissement restant | B85: USD | I85: =I81-I84 -> 3000000 | J85: =J81-J84 -> 1800000 | K85: =K81-K84 -> 1080000 | L85: =L81-L84 -> 540000 | M85: =M81-M84 -> 0
A87: Immobilisations de l'année A8
A88: Durée restante | B88: Années | J88: =IF($C$28<J$3,$C$28,J$3) -> 4 | K88: =IF(J88=0,0,IF(J88-1<K$3,J88-1,K$3)) -> 3 | L88: =IF(K88=0,0,IF(K88-1<L$3,K88-1,L$3)) -> 2 | M88: =IF(L88=0,0,IF(L88-1<M$3,L88-1,M$3)) -> 1
A89: Base amortissable | B89: USD | J89: =Modèle!J$10 -> 5000000 | K89: =J93 -> 3000000 | L89: =K93 -> 1800000 | M89: =L93 -> 900000
A90: Inverse de la durée restante | B90: % | J90: =IF(J88=0,0,1/J88) -> 0.25 | K90: =IF(K88=0,0,1/K88) -> 0.33333333 | L90: =IF(L88=0,0,1/L88) -> 0.5 | M90: =IF(M88=0,0,1/M88) -> 1
A91: Taux dégressif | B91: % | J91: =IF(J88=0,0,IF($C$29*1/$C$28>J90,$C$29*1/$C$28,J90)) -> 0.4 | K91: =IF(K88=0,0,IF($C$29*1/$C$28>K90,$C$29*1/$C$28,K90)) -> 0.4 | L91: =IF(L88=0,0,IF($C$29*1/$C$28>L90,$C$29*1/$C$28,L90)) -> 0.5 | M91: =IF(M88=0,0,IF($C$29*1/$C$28>M90,$C$29*1/$C$28,M90)) -> 1
A92: Charge d'amortissement | B92: USD | J92: =J89*J91 -> 2000000 | K92: =K89*K91 -> 1200000 | L92: =L89*L91 -> 900000 | M92: =M89*M91 -> 900000
A93: Amortissement restant | B93: USD | J93: =J89-J92 -> 3000000 | K93: =K89-K92 -> 1800000 | L93: =L89-L92 -> 900000 | M93: =M89-M92 -> 0
A95: Immobilisations de l'année A9
A96: Durée restante | B96: Années | K96: =IF($C$28<K$3,$C$28,K$3) -> 3 | L96: =IF(K96=0,0,IF(K96-1<L$3,K96-1,L$3)) -> 2 | M96: =IF(L96=0,0,IF(L96-1<M$3,L96-1,M$3)) -> 1
A97: Base amortissable | B97: USD | K97: =Modèle!K$10 -> 5000000 | L97: =K101 -> 3000000 | M97: =L101 -> 1500000
A98: Inverse de la durée restante | B98: % | K98: =IF(K96=0,0,1/K96) -> 0.33333333 | L98: =IF(L96=0,0,1/L96) -> 0.5 | M98: =IF(M96=0,0,1/M96) -> 1
A99: Taux dégressif | B99: % | K99: =IF(K96=0,0,IF($C$29*1/$C$28>K98,$C$29*1/$C$28,K98)) -> 0.4 | L99: =IF(L96=0,0,IF($C$29*1/$C$28>L98,$C$29*1/$C$28,L98)) -> 0.5 | M99: =IF(M96=0,0,IF($C$29*1/$C$28>M98,$C$29*1/$C$28,M98)) -> 1
A100: Charge d'amortissement | B100: USD | K100: =K97*K99 -> 2000000 | L100: =L97*L99 -> 1500000 | M100: =M97*M99 -> 1500000
A101: Amortissement restant | B101: USD | K101: =K97-K100 -> 3000000 | L101: =L97-L100 -> 1500000 | M101: =M97-M100 -> 0
A103: Immobilisations de l'année A10
A104: Durée restante | B104: Années | L104: =IF($C$28<L$3,$C$28,L$3) -> 2 | M104: =IF(L104=0,0,IF(L104-1<M$3,L104-1,M$3)) -> 1
A105: Base amortissable | B105: USD | L105: =Modèle!L$10 -> 5000000 | M105: =L109 -> 2500000
A106: Inverse de la durée restante | B106: % | L106: =IF(L104=0,0,1/L104) -> 0.5 | M106: =IF(M104=0,0,1/M104) -> 1
A107: Taux dégressif | B107: % | L107: =IF(L104=0,0,IF($C$29*1/$C$28>L106,$C$29*1/$C$28,L106)) -> 0.5 | M107: =IF(M104=0,0,IF($C$29*1/$C$28>M106,$C$29*1/$C$28,M106)) -> 1
A108: Charge d'amortissement | B108: USD | L108: =L105*L107 -> 2500000 | M108: =M105*M107 -> 2500000
A109: Amortissement restant | B109: USD | L109: =L105-L108 -> 2500000 | M109: =M105-M108 -> 0
A111: Immobilisations de l'année A11
A112: Durée restante | B112: Années | M112: =IF($C$28<M$3,$C$28,M$3) -> 1
A113: Base amortissable | B113: USD | M113: =Modèle!M$10 -> 0
A114: Inverse de la durée restante | B114: % | M114: =IF(M112=0,0,1/M112) -> 1
A115: Taux dégressif | B115: % | M115: =IF(M112=0,0,IF($C$29*1/$C$28>M114,$C$29*1/$C$28,M114)) -> 1
A116: Charge d'amortissement | B116: USD | M116: =M113*M115 -> 0
A117: Amortissement restant | B117: USD | M117: =M113-M116 -> 0
...
