Workbook

Sheet Index
A1: Feuille | B1: Fichier source | C1: Feuille d'origine
A2: 01_02_Rente_min | B2: 02-Rente-miniere.xlsx | C2: Modèle
A3: 02_03_Impots_su | B3: 03-Impots-sur-la-production.xlsx | C3: Modèle
A4: 03_04_Charges_d_1 | B4: 04-Charges-d-amortissement.xlsx | C4: Modèle
A5: 03_04_Charges_d_2 | B5: 04-Charges-d-amortissement.xlsx | C5: Amortissements
A6: 04_05_Charges_f_1 | B6: 05-Charges-financieres (1).xlsx | C6: Modèle
A7: 04_05_Charges_f_2 | B7: 05-Charges-financieres (1).xlsx | C7: Amortissements et Emprunt
A8: 05_05_Charges_f_1 | B8: 05-Charges-financieres.xlsx | C8: Modèle
A9: 05_05_Charges_f_2 | B9: 05-Charges-financieres.xlsx | C9: Amortissements et Emprunt
A10: 06_06_IS_IMF_1 | B10: 06-IS-IMF.xlsx | C10: Modèle
A11: 06_06_IS_IMF_2 | B11: 06-IS-IMF.xlsx | C11: Amortissements et Emprunt
A12: 07_07_TEMI_1 | B12: 07-TEMI.xlsx | C12: Modèle
... A20: 10_10_Illustrat_3 | B20: 10-Illustrations-graphiques.xlsx | C20: Graphiques

Sheet 01_02_Rente_min
A1: Nom | B1: Unité | C1: Année 1 | D1: Année 2 | E1: Année 3 | F1: Année 4 | G1: Année 5 | H1: Année 6 | I1: Année 7 | J1: Année 8 | K1: Année 9 | L1: Année 10 | M1: Année 11 | N1: SOMME | O1: VAN
A3: I. PRODUCTION
A4: Production d'or | B4: oz | E4: 250000 | F4: 250000 | G4: 250000 | H4: 250000 | I4: 250000 | J4: 250000 | K4: 250000 | L4: 250000 | N4: =SUM($C4:$M4)
A5: Cours de l'or | B5: USD/oz | E5: 1300 | F5: 1300 | G5: 1300 | H5: 1300 | I5: 1300 | J5: 1300 | K5: 1300 | L5: 1300
A6: Chiffre d'affaires | B6: USD | C6: =C$4*C$5 | D6: =D$4*D$5 | E6: =E$4*E$5 | F6: =F$4*F$5 | G6: =G$4*G$5 | H6: =H$4*H$5 | I6: =I$4*I$5 | J6: =J$4*J$5 | ... M6: =M$4*M$5 | N6: =SUM($C6:$M6) | O6: =$C6+NPV(10%,$D6:$M6)
A8: II. DEPENSES D'INVESTISSEMENT (CAPEX)
A9: Coûts des construction industrielles | B9: USD | C9: 50000000 | D9: 100000000 | N9: =SUM($C9:$M9) | O9: =$C9+NPV(10%,$D9:$M9)
A10: Coûts des biens d'équipement | B10: USD | D10: 50000000 | E10: 5000000 | F10: 5000000 | G10: 5000000 | H10: 5000000 | I10: 5000000 | J10: 5000000 | K10: 5000000 | L10: 5000000 | N10: =SUM($C10:$M10) | O10: =$C10+NPV(10%,$D10:$M10)
A11: Coûts de réhabilitation du site | B11: USD | M11: 10000000 | N11: =SUM($C11:$M11) | O11: =$C11+NPV(10%,$D11:$M11)
A12: Total des dépenses d'investissement | B12: USD | C12: =SUM(C$9:C$11) | D12: =SUM(D$9:D$11) | E12: =SUM(E$9:E$11) | F12: =SUM(F$9:F$11) | G12: =SUM(G$9:G$11) | H12: =SUM(H$9:H$11) | I12: =SUM(I$9:I$11) | J12: =SUM(J$9:J$11) | ... M12: =SUM(M$9:M$11) | N12: =SUM($C12:$M12) | O12: =$C12+NPV(10%,$D12:$M12)
A14: III. COÛTS D'EXPLOITATION (OPEX)
A15: Coût moyen d'exploitation | B15: USD/oz | E15: 700 | F15: 700 | G15: 700 | H15: 700 | I15: 700 | J15: 700 | K15: 700 | L15: 700
A16: Total des coûts d'exploitation | B16: USD | C16: =C$4*C$15 | D16: =D$4*D$15 | E16: =E$4*E$15 | F16: =F$4*F$15 | G16: =G$4*G$15 | H16: =H$4*H$15 | I16: =I$4*I$15 | J16: =J$4*J$15 | ... M16: =M$4*M$15 | N16: =SUM($C16:$M16) | O16: =$C16+NPV(10%,$D16:$M16)
A18: IV. FLUX NETS DE TRESORERIE AVANT IMPÔTS
A19: Flux nets de trésorerie avant impôts | B19: USD | C19: =C$6-C$12-C$16 | D19: =D$6-D$12-D$16 | E19: =E$6-E$12-E$16 | F19: =F$6-F$12-F$16 | G19: =G$6-G$12-G$16 | H19: =H$6-H$12-H$16 | I19: =I$6-I$12-I$16 | J19: =J$6-J$12-J$16 | ... M19: =M$6-M$12-M$16 | N19: =SUM($C19:$M19) | O19: =$C19+NPV(10%,$D19:$M19)
A20: Taux de rendement interne avant impôts | B20: % | C20: =IF(ISNUMBER(IRR($C19:C19)),IF(IRR($C19:C19)>0,IRR($C19:C19),""),"") | D20: =IF(ISNUMBER(IRR($C19:D19)),IF(IRR($C19:D19)>0,IRR($C19:D19),""),"") | E20: =IF(ISNUMBER(IRR($C19:E19)),IF(IRR($C19:E19)>0,IRR($C19:E19),""),"") | F20: =IF(ISNUMBER(IRR($C19:F19)),IF(IRR($C19:F19)>0,IRR($C19:F19),""),"") | G20: =IF(ISNUMBER(IRR($C19:G19)),IF(IRR($C19:G19)>0,IRR($C19:G19),""),"") | H20: =IF(ISNUMBER(IRR($C19:H19)),IF(IRR($C19:H19)>0,IRR($C19:H19),""),"") | I20: =IF(ISNUMBER(IRR($C19:I19)),IF(IRR($C19:I19)>0,IRR($C19:I19),""),"") | J20: =IF(ISNUMBER(IRR($C19:J19)),IF(IRR($C19:J19)>0,IRR($C19:J19),""),"") | ... M20: =IF(ISNUMBER(IRR($C19:M19)),IF(IRR($C19:M19)>0,IRR($C19:M19),""),"")
A23: V. IMPOT SUR LA PRODUCTION
A24: Droit fixes | B24: USD | C24: 100000
A25: Redevance superficiaire | B25: USD | C25: =100*100 | D25: =100*100 | E25: =100*100 | F25: =100*100 | G25: =100*100 | H25: =100*100 | I25: =100*100 | J25: =100*100 | ... M25: =100*100
A26: Redevance minière | B26: USD | E26: =E6*0.04 | F26: =F6*0.04 | G26: =G6*0.04 | H26: =H6*0.04 | I26: =I6*0.04 | J26: =J6*0.04 | K26: =K6*0.04 | L26: =L6*0.04 | M26: =M6*0.04

Sheet 02_03_Impots_su
A1: Nom | B1: Unité | C1: Année 1 | D1: Année 2 | E1: Année 3 | F1: Année 4 | G1: Année 5 | H1: Année 6 | I1: Année 7 | J1: Année 8 | K1: Année 9 | L1: Année 10 | M1: Année 11 | N1: SOMME | O1: VAN
A3: I. PRODUCTION
A4: Production d'or | B4: oz | E4: 250000 | F4: 250000 | G4: 250000 | H4: 250000 | I4: 250000 | J4: 250000 | K4: 250000 | L4: 250000 | N4: =SUM($C4:$M4)
A5: Cours de l'or | B5: USD/oz | E5: 1300 | F5: 1300 | G5: 1300 | H5: 1300 | I5: 1300 | J5: 1300 | K5: 1300 | L5: 1300
A6: Chiffre d'affaires | B6: USD | C6: =C$4*C$5 | D6: =D$4*D$5 | E6: =E$4*E$5 | F6: =F$4*F$5 | G6: =G$4*G$5 | H6: =H$4*H$5 | I6: =I$4*I$5 | J6: =J$4*J$5 | ... M6: =M$4*M$5 | N6: =SUM($C6:$M6) | O6: =$C6+NPV(10%,$D6:$M6)
A8: II. DEPENSES D'INVESTISSEMENT (CAPEX)
A9: Coûts des construction industrielles | B9: USD | C9: 50000000 | D9: 100000000 | N9: =SUM($C9:$M9) | O9: =$C9+NPV(10%,$D9:$M9)
A10: Coûts des biens d'équipement | B10: USD | D10: 50000000 | E10: 5000000 | F10: 5000000 | G10: 5000000 | H10: 5000000 | I10: 5000000 | J10: 5000000 | K10: 5000000 | L10: 5000000 | N10: =SUM($C10:$M10) | O10: =$C10+NPV(10%,$D10:$M10)
A11: Coûts de réhabilitation du site | B11: USD | M11: 10000000 | N11: =SUM($C11:$M11) | O11: =$C11+NPV(10%,$D11:$M11)
A12: Total des dépenses d'investissement | B12: USD | C12: =SUM(C$9:C$11) | D12: =SUM(D$9:D$11) | E12: =SUM(E$9:E$11) | F12: =SUM(F$9:F$11) | G12: =SUM(G$9:G$11) | H12: =SUM(H$9:H$11) | I12: =SUM(I$9:I$11) | J12: =SUM(J$9:J$11) | ... M12: =SUM(M$9:M$11) | N12: =SUM($C12:$M12) | O12: =$C12+NPV(10%,$D12:$M12)
A14: III. COÛTS D'EXPLOITATION (OPEX)
A15: Coût moyen d'exploitation | B15: USD/oz | E15: 700 | F15: 700 | G15: 700 | H15: 700 | I15: 700 | J15: 700 | K15: 700 | L15: 700
A16: Total des coûts d'exploitation | B16: USD | C16: =C$4*C$15 | D16: =D$4*D$15 | E16: =E$4*E$15 | F16: =F$4*F$15 | G16: =G$4*G$15 | H16: =H$4*H$15 | I16: =I$4*I$15 | J16: =J$4*J$15 | ... M16: =M$4*M$15 | N16: =SUM($C16:$M16) | O16: =$C16+NPV(10%,$D16:$M16)
A18: IV. FLUX NETS DE TRESORERIE AVANT IMPÔTS
A19: Flux nets de trésorerie avant impôts | B19: USD | C19: =C$6-C$12-C$16 | D19: =D$6-D$12-D$16 | E19: =E$6-E$12-E$16 | F19: =F$6-F$12-F$16 | G19: =G$6-G$12-G$16 | H19: =H$6-H$12-H$16 | I19: =I$6-I$12-I$16 | J19: =J$6-J$12-J$16 | ... M19: =M$6-M$12-M$16 | N19: =SUM($C19:$M19) | O19: =$C19+NPV(10%,$D19:$M19)
A20: Taux de rendement interne avant impôts | B20: % | C20: =IF(ISNUMBER(IRR($C19:C19)),IF(IRR($C19:C19)>0,IRR($C19:C19),""),"") | D20: =IF(ISNUMBER(IRR($C19:D19)),IF(IRR($C19:D19)>0,IRR($C19:D19),""),"") | E20: =IF(ISNUMBER(IRR($C19:E19)),IF(IRR($C19:E19)>0,IRR($C19:E19),""),"") | F20: =IF(ISNUMBER(IRR($C19:F19)),IF(IRR($C19:F19)>0,IRR($C19:F19),""),"") | G20: =IF(ISNUMBER(IRR($C19:G19)),IF(IRR($C19:G19)>0,IRR($C19:G19),""),"") | H20: =IF(ISNUMBER(IRR($C19:H19)),IF(IRR($C19:H19)>0,IRR($C19:H19),""),"") | I20: =IF(ISNUMBER(IRR($C19:I19)),IF(IRR($C19:I19)>0,IRR($C19:I19),""),"") | J20: =IF(ISNUMBER(IRR($C19:J19)),IF(IRR($C19:J19)>0,IRR($C19:J19),""),"") | ... M20: =IF(ISNUMBER(IRR($C19:M19)),IF(IRR($C19:M19)>0,IRR($C19:M19),""),"")
A22: V. DROITS FIXES
A23: Droits fixes | B23: USD | C23: 100000 | N23: =SUM($C23:$M23) | O23: =$C23+NPV(10%,$D23:$M23)
A25: VI. REDEVANCE SUPERFICAIRE
A26: Superficie de la mine | B26: km² | C26: 100 | D26: 100 | E26: 100 | F26: 100 | G26: 100 | H26: 100 | I26: 100 | J26: 100 | K26: 100 | L26: 100 | M26: 100
A27: Montant de la redevance superfiaire | B27: USD/km² | C27: 100 | D27: 100 | E27: 100 | F27: 100 | G27: 100 | H27: 100 | I27: 100 | J27: 100 | K27: 100 | L27: 100 | M27: 100
A28: Redevance superficiaire | B28: USD | C28: =C$26*C$27 | D28: =D$26*D$27 | E28: =E$26*E$27 | F28: =F$26*F$27 | G28: =G$26*G$27 | H28: =H$26*H$27 | I28: =I$26*I$27 | J28: =J$26*J$27 | ... M28: =M$26*M$27 | N28: =SUM($C28:$M28) | O28: =$C28+NPV(10%,$D28:$M28)
A30: VII. REDEVANCE MINIERE
A31: Taux de la redevance minière | B31: % | C31: =IF(ISNUMBER(C5),IF(C$5<1300,3%,IF(C$5<1500,4%,5%)),"") | D31: =IF(ISNUMBER(D5),IF(D$5<1300,3%,IF(D$5<1500,4%,5%)),"") | E31: =IF(ISNUMBER(E5),IF(E$5<1300,3%,IF(E$5<1500,4%,5%)),"") | F31: =IF(ISNUMBER(F5),IF(F$5<1300,3%,IF(F$5<1500,4%,5%)),"") | G31: =IF(ISNUMBER(G5),IF(G$5<1300,3%,IF(G$5<1500,4%,5%)),"") | H31: =IF(ISNUMBER(H5),IF(H$5<1300,3%,IF(H$5<1500,4%,5%)),"") | I31: =IF(ISNUMBER(I5),IF(I$5<1300,3%,IF(I$5<1500,4%,5%)),"") | J31: =IF(ISNUMBER(J5),IF(J$5<1300,3%,IF(J$5<1500,4%,5%)),"") | ... M31: =IF(ISNUMBER(M5),IF(M$5<1300,3%,IF(M$5<1500,4%,5%)),"")
A32: Redevance minière | B32: USD | C32: =IF(ISNUMBER(C31),C$6*C$31,0) | D32: =IF(ISNUMBER(D31),D$6*D$31,0) | E32: =IF(ISNUMBER(E31),E$6*E$31,0) | F32: =IF(ISNUMBER(F31),F$6*F$31,0) | G32: =IF(ISNUMBER(G31),G$6*G$31,0) | H32: =IF(ISNUMBER(H31),H$6*H$31,0) | I32: =IF(ISNUMBER(I31),I$6*I$31,0) | J32: =IF(ISNUMBER(J31),J$6*J$31,0) | ... M32: =IF(ISNUMBER(M31),M$6*M$31,0) | N32: =SUM($C32:$M32) | O32: =$C32+NPV(10%,$D32:$M32)

Sheet 03_04_Charges_d_1
A1: Nom | B1: Unité | C1: Année 1 | D1: Année 2 | E1: Année 3 | F1: Année 4 | G1: Année 5 | H1: Année 6 | I1: Année 7 | J1: Année 8 | K1: Année 9 | L1: Année 10 | M1: Année 11 | N1: SOMME | O1: VAN
A3: I. PRODUCTION
A4: Production d'or | B4: oz | E4: 250000 | F4: 250000 | G4: 250000 | H4: 250000 | I4: 250000 | J4: 250000 | K4: 250000 | L4: 250000 | N4: =SUM($C4:$M4)
A5: Cours de l'or | B5: USD/oz | E5: 1300 | F5: 1300 | G5: 1300 | H5: 1300 | I5: 1300 | J5: 1300 | K5: 1300 | L5: 1300
A6: Chiffre d'affaires | B6: USD | C6: =C$4*C$5 | D6: =D$4*D$5 | E6: =E$4*E$5 | F6: =F$4*F$5 | G6: =G$4*G$5 | H6: =H$4*H$5 | I6: =I$4*I$5 | J6: =J$4*J$5 | ... M6: =M$4*M$5 | N6: =SUM($C6:$M6) | O6: =$C6+NPV(10%,$D6:$M6)
A8: II. DEPENSES D'INVESTISSEMENT (CAPEX)
A9: Coûts des construction industrielles | B9: USD | C9: 50000000 | D9: 100000000 | N9: =SUM($C9:$M9) | O9: =$C9+NPV(10%,$D9:$M9)
A10: Coûts des biens d'équipement | B10: USD | D10: 50000000 | E10: 5000000 | F10: 5000000 | G10: 5000000 | H10: 5000000 | I10: 5000000 | J10: 5000000 | K10: 5000000 | L10: 5000000 | N10: =SUM($C10:$M10) | O10: =$C10+NPV(10%,$D10:$M10)
A11: Coûts de réhabilitation du site | B11: USD | M11: 10000000 | N11: =SUM($C11:$M11) | O11: =$C11+NPV(10%,$D11:$M11)
A12: Total des dépenses d'investissement | B12: USD | C12: =SUM(C$9:C$11) | D12: =SUM(D$9:D$11) | E12: =SUM(E$9:E$11) | F12: =SUM(F$9:F$11) | G12: =SUM(G$9:G$11) | H12: =SUM(H$9:H$11) | I12: =SUM(I$9:I$11) | J12: =SUM(J$9:J$11) | ... M12: =SUM(M$9:M$11) | N12: =SUM($C12:$M12) | O12: =$C12+NPV(10%,$D12:$M12)
A14: III. COÛTS D'EXPLOITATION (OPEX)
A15: Coût moyen d'exploitation | B15: USD/oz | E15: 700 | F15: 700 | G15: 700 | H15: 700 | I15: 700 | J15: 700 | K15: 700 | L15: 700
A16: Total des coûts d'exploitation | B16: USD | C16: =C$4*C$15 | D16: =D$4*D$15 | E16: =E$4*E$15 | F16: =F$4*F$15 | G16: =G$4*G$15 | H16: =H$4*H$15 | I16: =I$4*I$15 | J16: =J$4*J$15 | ... M16: =M$4*M$15 | N16: =SUM($C16:$M16) | O16: =$C16+NPV(10%,$D16:$M16)
A18: IV. FLUX NETS DE TRESORERIE AVANT IMPÔTS
A19: Flux nets de trésorerie avant impôts | B19: USD | C19: =C$6-C$12-C$16 | D19: =D$6-D$12-D$16 | E19: =E$6-E$12-E$16 | F19: =F$6-F$12-F$16 | G19: =G$6-G$12-G$16 | H19: =H$6-H$12-H$16 | I19: =I$6-I$12-I$16 | J19: =J$6-J$12-J$16 | ... M19: =M$6-M$12-M$16 | N19: =SUM($C19:$M19) | O19: =$C19+NPV(10%,$D19:$M19)
A20: Taux de rendement interne avant impôts | B20: % | C20: =IF(ISNUMBER(IRR($C19:C19)),IF(IRR($C19:C19)>0,IRR($C19:C19),""),"") | D20: =IF(ISNUMBER(IRR($C19:D19)),IF(IRR($C19:D19)>0,IRR($C19:D19),""),"") | E20: =IF(ISNUMBER(IRR($C19:E19)),IF(IRR($C19:E19)>0,IRR($C19:E19),""),"") | F20: =IF(ISNUMBER(IRR($C19:F19)),IF(IRR($C19:F19)>0,IRR($C19:F19),""),"") | G20: =IF(ISNUMBER(IRR($C19:G19)),IF(IRR($C19:G19)>0,IRR($C19:G19),""),"") | H20: =IF(ISNUMBER(IRR($C19:H19)),IF(IRR($C19:H19)>0,IRR($C19:H19),""),"") | I20: =IF(ISNUMBER(IRR($C19:I19)),IF(IRR($C19:I19)>0,IRR($C19:I19),""),"") | J20: =IF(ISNUMBER(IRR($C19:J19)),IF(IRR($C19:J19)>0,IRR($C19:J19),""),"") | ... M20: =IF(ISNUMBER(IRR($C19:M19)),IF(IRR($C19:M19)>0,IRR($C19:M19),""),"")
A22: V. DROITS FIXES
A23: Droits fixes | B23: USD | C23: 100000 | N23: =SUM($C23:$M23) | O23: =$C23+NPV(10%,$D23:$M23)
A25: VI. REDEVANCE SUPERFICAIRE
A26: Superficie de la mine | B26: km² | C26: 100 | D26: 100 | E26: 100 | F26: 100 | G26: 100 | H26: 100 | I26: 100 | J26: 100 | K26: 100 | L26: 100 | M26: 100
A27: Montant de la redevance superfiaire | B27: USD/km² | C27: 100 | D27: 100 | E27: 100 | F27: 100 | G27: 100 | H27: 100 | I27: 100 | J27: 100 | K27: 100 | L27: 100 | M27: 100
A28: Redevance superficiaire | B28: USD | C28: =C$26*C$27 | D28: =D$26*D$27 | E28: =E$26*E$27 | F28: =F$26*F$27 | G28: =G$26*G$27 | H28: =H$26*H$27 | I28: =I$26*I$27 | J28: =J$26*J$27 | ... M28: =M$26*M$27 | N28: =SUM($C28:$M28) | O28: =$C28+NPV(10%,$D28:$M28)
A30: VII. REDEVANCE MINIERE
A31: Taux de la redevance minière | B31: % | C31: =IF(ISNUMBER(C5),IF(C$5<1300,3%,IF(C$5<1500,4%,5%)),"") | D31: =IF(ISNUMBER(D5),IF(D$5<1300,3%,IF(D$5<1500,4%,5%)),"") | E31: =IF(ISNUMBER(E5),IF(E$5<1300,3%,IF(E$5<1500,4%,5%)),"") | F31: =IF(ISNUMBER(F5),IF(F$5<1300,3%,IF(F$5<1500,4%,5%)),"") | G31: =IF(ISNUMBER(G5),IF(G$5<1300,3%,IF(G$5<1500,4%,5%)),"") | H31: =IF(ISNUMBER(H5),IF(H$5<1300,3%,IF(H$5<1500,4%,5%)),"") | I31: =IF(ISNUMBER(I5),IF(I$5<1300,3%,IF(I$5<1500,4%,5%)),"") | J31: =IF(ISNUMBER(J5),IF(J$5<1300,3%,IF(J$5<1500,4%,5%)),"") | ... M31: =IF(ISNUMBER(M5),IF(M$5<1300,3%,IF(M$5<1500,4%,5%)),"")
A32: Redevance minière | B32: USD | C32: =IF(ISNUMBER(C31),C$6*C$31,0) | D32: =IF(ISNUMBER(D31),D$6*D$31,0) | E32: =IF(ISNUMBER(E31),E$6*E$31,0) | F32: =IF(ISNUMBER(F31),F$6*F$31,0) | G32: =IF(ISNUMBER(G31),G$6*G$31,0) | H32: =IF(ISNUMBER(H31),H$6*H$31,0) | I32: =IF(ISNUMBER(I31),I$6*I$31,0) | J32: =IF(ISNUMBER(J31),J$6*J$31,0) | ... M32: =IF(ISNUMBER(M31),M$6*M$31,0) | N32: =SUM($C32:$M32) | O32: =$C32+NPV(10%,$D32:$M32)

Sheet 03_04_Charges_d_2
A1: Nom | B1: Unité | C1: Année 1 | D1: Année 2 | E1: Année 3 | F1: Année 4 | G1: Année 5 | H1: Année 6 | I1: Année 7 | J1: Année 8 | K1: Année 9 | L1: Année 10 | M1: Année 11
A3: Durée restante maximum | B3: Années | C3: 11 | D3: 10 | E3: 9 | F3: 8 | G3: 7 | H3: 6 | I3: 5 | J3: 4 | K3: 3 | L3: 2 | M3: 1
A5: I. AMORTISSEMENTS DES CONSTRUCTIONS INDUSTRIELLES
A6: Durée d'amortissement linéaire | B6: Années | C6: 10
A7: Coefficient d'amortissement dégressif | B7: Coefficient | C7: 1
A9: Immobilisations de l'année A1
A10: Durée restante | B10: Années | C10: =IF($C$6<C$3,$C$6,C$3) | D10: =IF(C10=0,0,IF(C10-1<D$3,C10-1,D$3)) | E10: =IF(D10=0,0,IF(D10-1<E$3,D10-1,E$3)) | F10: =IF(E10=0,0,IF(E10-1<F$3,E10-1,F$3)) | G10: =IF(F10=0,0,IF(F10-1<G$3,F10-1,G$3)) | H10: =IF(G10=0,0,IF(G10-1<H$3,G10-1,H$3)) | I10: =IF(H10=0,0,IF(H10-1<I$3,H10-1,I$3)) | J10: =IF(I10=0,0,IF(I10-1<J$3,I10-1,J$3)) | K10: =IF(J10=0,0,IF(J10-1<K$3,J10-1,K$3)) | ... M10: =IF(L10=0,0,IF(L10-1<M$3,L10-1,M$3))
A11: Base amortissable | B11: USD | C11: =Modèle!C$9 | D11: =C15 | E11: =D15 | F11: =E15 | G11: =F15 | H11: =G15 | I11: =H15 | J11: =I15 | K11: =J15 | ... M11: =L15
A12: Inverse de la durée restante | B12: % | C12: =IF(C10=0,0,1/C10) | D12: =IF(D10=0,0,1/D10) | E12: =IF(E10=0,0,1/E10) | F12: =IF(F10=0,0,1/F10) | G12: =IF(G10=0,0,1/G10) | H12: =IF(H10=0,0,1/H10) | I12: =IF(I10=0,0,1/I10) | J12: =IF(J10=0,0,1/J10) | ... M12: =IF(M10=0,0,1/M10)
A13: Taux dégressif | B13: % | C13: =IF(C10=0,0,IF($C$7*1/$C$6>C12,$C$7*1/$C$6,C12)) | D13: =IF(D10=0,0,IF($C$7*1/$C$6>D12,$C$7*1/$C$6,D12)) | E13: =IF(E10=0,0,IF($C$7*1/$C$6>E12,$C$7*1/$C$6,E12)) | F13: =IF(F10=0,0,IF($C$7*1/$C$6>F12,$C$7*1/$C$6,F12)) | G13: =IF(G10=0,0,IF($C$7*1/$C$6>G12,$C$7*1/$C$6,G12)) | H13: =IF(H10=0,0,IF($C$7*1/$C$6>H12,$C$7*1/$C$6,H12)) | I13: =IF(I10=0,0,IF($C$7*1/$C$6>I12,$C$7*1/$C$6,I12)) | J13: =IF(J10=0,0,IF($C$7*1/$C$6>J12,$C$7*1/$C$6,J12)) | ... M13: =IF(M10=0,0,IF($C$7*1/$C$6>M12,$C$7*1/$C$6,M12))
A14: Charge d'amortissement | B14: USD | C14: =C11*C13 | D14: =D11*D13 | E14: =E11*E13 | F14: =F11*F13 | G14: =G11*G13 | H14: =H11*H13 | I14: =I11*I13 | J14: =J11*J13 | ... M14: =M11*M13
A15: Amortissement restant | B15: USD | C15: =C11-C14 | D15: =D11-D14 | E15: =E11-E14 | F15: =F11-F14 | G15: =G11-G14 | H15: =H11-H14 | I15: =I11-I14 | J15: =J11-J14 | ... M15: =M11-M14
A17: Immobilisations de l'année A2
A18: Durée restante | B18: Années | D18: =IF($C$6<D$3,$C$6,D$3) | E18: =IF(D18=0,0,IF(D18-1<E$3,D18-1,E$3)) | F18: =IF(E18=0,0,IF(E18-1<F$3,E18-1,F$3)) | G18: =IF(F18=0,0,IF(F18-1<G$3,F18-1,G$3)) | H18: =IF(G18=0,0,IF(G18-1<H$3,G18-1,H$3)) | I18: =IF(H18=0,0,IF(H18-1<I$3,H18-1,I$3)) | J18: =IF(I18=0,0,IF(I18-1<J$3,I18-1,J$3)) | K18: =IF(J18=0,0,IF(J18-1<K$3,J18-1,K$3)) | L18: =IF(K18=0,0,IF(K18-1<L$3,K18-1,L$3)) | M18: =IF(L18=0,0,IF(L18-1<M$3,L18-1,M$3))
A19: Base amortissable | B19: USD | D19: =Modèle!D$9 | E19: =D23 | F19: =E23 | G19: =F23 | H19: =G23 | I19: =H23 | J19: =I23 | K19: =J23 | L19: =K23 | M19: =L23
A20: Inverse de la durée restante | B20: % | D20: =IF(D18=0,0,1/D18) | E20: =IF(E18=0,0,1/E18) | F20: =IF(F18=0,0,1/F18) | G20: =IF(G18=0,0,1/G18) | H20: =IF(H18=0,0,1/H18) | I20: =IF(I18=0,0,1/I18) | J20: =IF(J18=0,0,1/J18) | K20: =IF(K18=0,0,1/K18) | ... M20: =IF(M18=0,0,1/M18)
A21: Taux dégressif | B21: % | D21: =IF(D18=0,0,IF($C$7*1/$C$6>D20,$C$7*1/$C$6,D20)) | E21: =IF(E18=0,0,IF($C$7*1/$C$6>E20,$C$7*1/$C$6,E20)) | F21: =IF(F18=0,0,IF($C$7*1/$C$6>F20,$C$7*1/$C$6,F20)) | G21: =IF(G18=0,0,IF($C$7*1/$C$6>G20,$C$7*1/$C$6,G20)) | H21: =IF(H18=0,0,IF($C$7*1/$C$6>H20,$C$7*1/$C$6,H20)) | I21: =IF(I18=0,0,IF($C$7*1/$C$6>I20,$C$7*1/$C$6,I20)) | J21: =IF(J18=0,0,IF($C$7*1/$C$6>J20,$C$7*1/$C$6,J20)) | K21: =IF(K18=0,0,IF($C$7*1/$C$6>K20,$C$7*1/$C$6,K20)) | ... M21: =IF(M18=0,0,IF($C$7*1/$C$6>M20,$C$7*1/$C$6,M20))
A22: Charge d'amortissement | B22: USD | D22: =D19*D21 | E22: =E19*E21 | F22: =F19*F21 | G22: =G19*G21 | H22: =H19*H21 | I22: =I19*I21 | J22: =J19*J21 | K22: =K19*K21 | ... M22: =M19*M21
A23: Amortissement restant | B23: USD | D23: =D19-D22 | E23: =E19-E22 | F23: =F19-F22 | G23: =G19-G22 | H23: =H19-H22 | I23: =I19-I22 | J23: =J19-J22 | K23: =K19-K22 | ... M23: =M19-M22
A25: Amortissements des constructions industrielles | B25: USD | C25: =C$14+C$22 | D25: =D$14+D$22 | E25: =E$14+E$22 | F25: =F$14+F$22 | G25: =G$14+G$22 | H25: =H$14+H$22 | I25: =I$14+I$22 | J25: =J$14+J$22 | ... M25: =M$14+M$22
A27: II. AMORTISSEMENTS DES BIENS D'EQUIPEMENT
A28: Durée d'amortissement linéaire | B28: Années | C28: 5
A29: Coefficient d'amortissement dégressif | B29: Coefficient | C29: 2
A31: Immobilisations de l'année A1
A32: Durée restante | B32: Années | C32: =IF($C$28<C$3,$C$28,C$3) | D32: =IF(C32=0,0,IF(C32-1<D$3,C32-1,D$3)) | E32: =IF(D32=0,0,IF(D32-1<E$3,D32-1,E$3)) | F32: =IF(E32=0,0,IF(E32-1<F$3,E32-1,F$3)) | G32: =IF(F32=0,0,IF(F32-1<G$3,F32-1,G$3)) | H32: =IF(G32=0,0,IF(G32-1<H$3,G32-1,H$3)) | I32: =IF(H32=0,0,IF(H32-1<I$3,H32-1,I$3)) | J32: =IF(I32=0,0,IF(I32-1<J$3,I32-1,J$3)) | K32: =IF(J32=0,0,IF(J32-1<K$3,J32-1,K$3)) | ... M32: =IF(L32=0,0,IF(L32-1<M$3,L32-1,M$3))
A33: Base amortissable | B33: USD | C33: =Modèle!C$10 | D33: =C37 | E33: =D37 | F33: =E37 | G33: =F37 | H33: =G37 | I33: =H37 | J33: =I37 | K33: =J37 | ... M33: =L37
A34: Inverse de la durée restante | B34: % | C34: =IF(C32=0,0,1/C32) | D34: =IF(D32=0,0,1/D32) | E34: =IF(E32=0,0,1/E32) | F34: =IF(F32=0,0,1/F32) | G34: =IF(G32=0,0,1/G32) | H34: =IF(H32=0,0,1/H32) | I34: =IF(I32=0,0,1/I32) | J34: =IF(J32=0,0,1/J32) | ... M34: =IF(M32=0,0,1/M32)
A35: Taux dégressif | B35: % | C35: =IF(C32=0,0,IF($C$29*1/$C$28>C34,$C$29*1/$C$28,C34)) | D35: =IF(D32=0,0,IF($C$29*1/$C$28>D34,$C$29*1/$C$28,D34)) | E35: =IF(E32=0,0,IF($C$29*1/$C$28>E34,$C$29*1/$C$28,E34)) | F35: =IF(F32=0,0,IF($C$29*1/$C$28>F34,$C$29*1/$C$28,F34)) | G35: =IF(G32=0,0,IF($C$29*1/$C$28>G34,$C$29*1/$C$28,G34)) | H35: =IF(H32=0,0,IF($C$29*1/$C$28>H34,$C$29*1/$C$28,H34)) | I35: =IF(I32=0,0,IF($C$29*1/$C$28>I34,$C$29*1/$C$28,I34)) | J35: =IF(J32=0,0,IF($C$29*1/$C$28>J34,$C$29*1/$C$28,J34)) | ... M35: =IF(M32=0,0,IF($C$29*1/$C$28>M34,$C$29*1/$C$28,M34))
A36: Charge d'amortissement | B36: USD | C36: =C33*C35 | D36: =D33*D35 | E36: =E33*E35 | F36: =F33*F35 | G36: =G33*G35 | H36: =H33*H35 | I36: =I33*I35 | J36: =J33*J35 | ... M36: =M33*M35
A37: Amortissement restant | B37: USD | C37: =C33-C36 | D37: =D33-D36 | E37: =E33-E36 | F37: =F33-F36 | G37: =G33-G36 | H37: =H33-H36 | I37: =I33-I36 | J37: =J33-J36 | ... M37: =M33-M36
A39: Immobilisations de l'année A2
A40: Durée restante | B40: Années | D40: =IF($C$28<D$3,$C$28,D$3) | E40: =IF(D40=0,0,IF(D40-1<E$3,D40-1,E$3)) | F40: =IF(E40=0,0,IF(E40-1<F$3,E40-1,F$3)) | G40: =IF(F40=0,0,IF(F40-1<G$3,F40-1,G$3)) | H40: =IF(G40=0,0,IF(G40-1<H$3,G40-1,H$3)) | I40: =IF(H40=0,0,IF(H40-1<I$3,H40-1,I$3)) | J40: =IF(I40=0,0,IF(I40-1<J$3,I40-1,J$3)) | K40: =IF(J40=0,0,IF(J40-1<K$3,J40-1,K$3)) | L40: =IF(K40=0,0,IF(K40-1<L$3,K40-1,L$3)) | M40: =IF(L40=0,0,IF(L40-1<M$3,L40-1,M$3))
A41: Base amortissable | B41: USD | D41: =Modèle!D$10 | E41: =D45 | F41: =E45 | G41: =F45 | H41: =G45 | I41: =H45 | J41: =I45 | K41: =J45 | L41: =K45 | M41: =L45
A42: Inverse de la durée restante | B42: % | D42: =IF(D40=0,0,1/D40) | E42: =IF(E40=0,0,1/E40) | F42: =IF(F40=0,0,1/F40) | G42: =IF(G40=0,0,1/G40) | H42: =IF(H40=0,0,1/H40) | I42: =IF(I40=0,0,1/I40) | J42: =IF(J40=0,0,1/J40) | K42: =IF(K40=0,0,1/K40) | ... M42: =IF(M40=0,0,1/M40)
A43: Taux dégressif | B43: % | D43: =IF(D40=0,0,IF($C$29*1/$C$28>D42,$C$29*1/$C$28,D42)) | E43: =IF(E40=0,0,IF($C$29*1/$C$28>E42,$C$29*1/$C$28,E42)) | F43: =IF(F40=0,0,IF($C$29*1/$C$28>F42,$C$29*1/$C$28,F42)) | G43: =IF(G40=0,0,IF($C$29*1/$C$28>G42,$C$29*1/$C$28,G42)) | H43: =IF(H40=0,0,IF($C$29*1/$C$28>H42,$C$29*1/$C$28,H42)) | I43: =IF(I40=0,0,IF($C$29*1/$C$28>I42,$C$29*1/$C$28,I42)) | J43: =IF(J40=0,0,IF($C$29*1/$C$28>J42,$C$29*1/$C$28,J42)) | K43: =IF(K40=0,0,IF($C$29*1/$C$28>K42,$C$29*1/$C$28,K42)) | ... M43: =IF(M40=0,0,IF($C$29*1/$C$28>M42,$C$29*1/$C$28,M42))
A44: Charge d'amortissement | B44: USD | D44: =D41*D43 | E44: =E41*E43 | F44: =F41*F43 | G44: =G41*G43 | H44: =H41*H43 | I44: =I41*I43 | J44: =J41*J43 | K44: =K41*K43 | ... M44: =M41*M43
A45: Amortissement restant | B45: USD | D45: =D41-D44 | E45: =E41-E44 | F45: =F41-F44 | G45: =G41-G44 | H45: =H41-H44 | I45: =I41-I44 | J45: =J41-J44 | K45: =K41-K44 | ... M45: =M41-M44
A47: Immobilisations de l'année A3
A48: Durée restante | B48: Années | E48: =IF($C$28<E$3,$C$28,E$3) | F48: =IF(E48=0,0,IF(E48-1<F$3,E48-1,F$3)) | G48: =IF(F48=0,0,IF(F48-1<G$3,F48-1,G$3)) | H48: =IF(G48=0,0,IF(G48-1<H$3,G48-1,H$3)) | I48: =IF(H48=0,0,IF(H48-1<I$3,H48-1,I$3)) | J48: =IF(I48=0,0,IF(I48-1<J$3,I48-1,J$3)) | K48: =IF(J48=0,0,IF(J48-1<K$3,J48-1,K$3)) | L48: =IF(K48=0,0,IF(K48-1<L$3,K48-1,L$3)) | M48: =IF(L48=0,0,IF(L48-1<M$3,L48-1,M$3))
A49: Base amortissable | B49: USD | E49: =Modèle!E$10 | F49: =E53 | G49: =F53 | H49: =G53 | I49: =H53 | J49: =I53 | K49: =J53 | L49: =K53 | M49: =L53
A50: Inverse de la durée restante | B50: % | E50: =IF(E48=0,0,1/E48) | F50: =IF(F48=0,0,1/F48) | G50: =IF(G48=0,0,1/G48) | H50: =IF(H48=0,0,1/H48) | I50: =IF(I48=0,0,1/I48) | J50: =IF(J48=0,0,1/J48) | K50: =IF(K48=0,0,1/K48) | L50: =IF(L48=0,0,1/L48) | M50: =IF(M48=0,0,1/M48)
A51: Taux dégressif | B51: % | E51: =IF(E48=0,0,IF($C$29*1/$C$28>E50,$C$29*1/$C$28,E50)) | F51: =IF(F48=0,0,IF($C$29*1/$C$28>F50,$C$29*1/$C$28,F50)) | G51: =IF(G48=0,0,IF($C$29*1/$C$28>G50,$C$29*1/$C$28,G50)) | H51: =IF(H48=0,0,IF($C$29*1/$C$28>H50,$C$29*1/$C$28,H50)) | I51: =IF(I48=0,0,IF($C$29*1/$C$28>I50,$C$29*1/$C$28,I50)) | J51: =IF(J48=0,0,IF($C$29*1/$C$28>J50,$C$29*1/$C$28,J50)) | K51: =IF(K48=0,0,IF($C$29*1/$C$28>K50,$C$29*1/$C$28,K50)) | L51: =IF(L48=0,0,IF($C$29*1/$C$28>L50,$C$29*1/$C$28,L50)) | M51: =IF(M48=0,0,IF($C$29*1/$C$28>M50,$C$29*1/$C$28,M50))
A52: Charge d'amortissement | B52: USD | E52: =E49*E51 | F52: =F49*F51 | G52: =G49*G51 | H52: =H49*H51 | I52: =I49*I51 | J52: =J49*J51 | K52: =K49*K51 | L52: =L49*L51 | M52: =M49*M51
A53: Amortissement restant | B53: USD | E53: =E49-E52 | F53: =F49-F52 | G53: =G49-G52 | H53: =H49-H52 | I53: =I49-I52 | J53: =J49-J52 | K53: =K49-K52 | L53: =L49-L52 | M53: =M49-M52
A55: Immobilisations de l'année A4
A56: Durée restante | B56: Années | F56: =IF($C$28<F$3,$C$28,F$3) | G56: =IF(F56=0,0,IF(F56-1<G$3,F56-1,G$3)) | H56: =IF(G56=0,0,IF(G56-1<H$3,G56-1,H$3)) | I56: =IF(H56=0,0,IF(H56-1<I$3,H56-1,I$3)) | J56: =IF(I56=0,0,IF(I56-1<J$3,I56-1,J$3)) | K56: =IF(J56=0,0,IF(J56-1<K$3,J56-1,K$3)) | L56: =IF(K56=0,0,IF(K56-1<L$3,K56-1,L$3)) | M56: =IF(L56=0,0,IF(L56-1<M$3,L56-1,M$3))
A57: Base amortissable | B57: USD | F57: =Modèle!F$10 | G57: =F61 | H57: =G61 | I57: =H61 | J57: =I61 | K57: =J61 | L57: =K61 | M57: =L61
A58: Inverse de la durée restante | B58: % | F58: =IF(F56=0,0,1/F56) | G58: =IF(G56=0,0,1/G56) | H58: =IF(H56=0,0,1/H56) | I58: =IF(I56=0,0,1/I56) | J58: =IF(J56=0,0,1/J56) | K58: =IF(K56=0,0,1/K56) | L58: =IF(L56=0,0,1/L56) | M58: =IF(M56=0,0,1/M56)
A59: Taux dégressif | B59: % | F59: =IF(F56=0,0,IF($C$29*1/$C$28>F58,$C$29*1/$C$28,F58)) | G59: =IF(G56=0,0,IF($C$29*1/$C$28>G58,$C$29*1/$C$28,G58)) | H59: =IF(H56=0,0,IF($C$29*1/$C$28>H58,$C$29*1/$C$28,H58)) | I59: =IF(I56=0,0,IF($C$29*1/$C$28>I58,$C$29*1/$C$28,I58)) | J59: =IF(J56=0,0,IF($C$29*1/$C$28>J58,$C$29*1/$C$28,J58)) | K59: =IF(K56=0,0,IF($C$29*1/$C$28>K58,$C$29*1/$C$28,K58)) | L59: =IF(L56=0,0,IF($C$29*1/$C$28>L58,$C$29*1/$C$28,L58)) | M59: =IF(M56=0,0,IF($C$29*1/$C$28>M58,$C$29*1/$C$28,M58))
A60: Charge d'amortissement | B60: USD | F60: =F57*F59 | G60: =G57*G59 | H60: =H57*H59 | I60: =I57*I59 | J60: =J57*J59 | K60: =K57*K59 | L60: =L57*L59 | M60: =M57*M59
A61: Amortissement restant | B61: USD | F61: =F57-F60 | G61: =G57-G60 | H61: =H57-H60 | I61: =I57-I60 | J61: =J57-J60 | K61: =K57-K60 | L61: =L57-L60 | M61: =M57-M60
A63: Immobilisations de l'année A5
A64: Durée restante | B64: Années | G64: =IF($C$28<G$3,$C$28,G$3) | H64: =IF(G64=0,0,IF(G64-1<H$3,G64-1,H$3)) | I64: =IF(H64=0,0,IF(H64-1<I$3,H64-1,I$3)) | J64: =IF(I64=0,0,IF(I64-1<J$3,I64-1,J$3)) | K64: =IF(J64=0,0,IF(J64-1<K$3,J64-1,K$3)) | L64: =IF(K64=0,0,IF(K64-1<L$3,K64-1,L$3)) | M64: =IF(L64=0,0,IF(L64-1<M$3,L64-1,M$3))
A65: Base amortissable | B65: USD | G65: =Modèle!G$10 | H65: =G69 | I65: =H69 | J65: =I69 | K65: =J69 | L65: =K69 | M65: =L69
A66: Inverse de la durée restante | B66: % | G66: =IF(G64=0,0,1/G64) | H66: =IF(H64=0,0,1/H64) | I66: =IF(I64=0,0,1/I64) | J66: =IF(J64=0,0,1/J64) | K66: =IF(K64=0,0,1/K64) | L66: =IF(L64=0,0,1/L64) | M66: =IF(M64=0,0,1/M64)
A67: Taux dégressif | B67: % | G67: =IF(G64=0,0,IF($C$29*1/$C$28>G66,$C$29*1/$C$28,G66)) | H67: =IF(H64=0,0,IF($C$29*1/$C$28>H66,$C$29*1/$C$28,H66)) | I67: =IF(I64=0,0,IF($C$29*1/$C$28>I66,$C$29*1/$C$28,I66)) | J67: =IF(J64=0,0,IF($C$29*1/$C$28>J66,$C$29*1/$C$28,J66)) | K67: =IF(K64=0,0,IF($C$29*1/$C$28>K66,$C$29*1/$C$28,K66)) | L67: =IF(L64=0,0,IF($C$29*1/$C$28>L66,$C$29*1/$C$28,L66)) | M67: =IF(M64=0,0,IF($C$29*1/$C$28>M66,$C$29*1/$C$28,M66))
A68: Charge d'amortissement | B68: USD | G68: =G65*G67 | H68: =H65*H67 | I68: =I65*I67 | J68: =J65*J67 | K68: =K65*K67 | L68: =L65*L67 | M68: =M65*M67
A69: Amortissement restant | B69: USD | G69: =G65-G68 | H69: =H65-H68 | I69: =I65-I68 | J69: =J65-J68 | K69: =K65-K68 | L69: =L65-L68 | M69: =M65-M68
A71: Immobilisations de l'année A6
A72: Durée restante | B72: Années | H72: =IF($C$28<H$3,$C$28,H$3) | I72: =IF(H72=0,0,IF(H72-1<I$3,H72-1,I$3)) | J72: =IF(I72=0,0,IF(I72-1<J$3,I72-1,J$3)) | K72: =IF(J72=0,0,IF(J72-1<K$3,J72-1,K$3)) | L72: =IF(K72=0,0,IF(K72-1<L$3,K72-1,L$3)) | M72: =IF(L72=0,0,IF(L72-1<M$3,L72-1,M$3))
A73: Base amortissable | B73: USD | H73: =Modèle!H$10 | I73: =H77 | J73: =I77 | K73: =J77 | L73: =K77 | M73: =L77
A74: Inverse de la durée restante | B74: % | H74: =IF(H72=0,0,1/H72) | I74: =IF(I72=0,0,1/I72) | J74: =IF(J72=0,0,1/J72) | K74: =IF(K72=0,0,1/K72) | L74: =IF(L72=0,0,1/L72) | M74: =IF(M72=0,0,1/M72)
A75: Taux dégressif | B75: % | H75: =IF(H72=0,0,IF($C$29*1/$C$28>H74,$C$29*1/$C$28,H74)) | I75: =IF(I72=0,0,IF($C$29*1/$C$28>I74,$C$29*1/$C$28,I74)) | J75: =IF(J72=0,0,IF($C$29*1/$C$28>J74,$C$29*1/$C$28,J74)) | K75: =IF(K72=0,0,IF($C$29*1/$C$28>K74,$C$29*1/$C$28,K74)) | L75: =IF(L72=0,0,IF($C$29*1/$C$28>L74,$C$29*1/$C$28,L74)) | M75: =IF(M72=0,0,IF($C$29*1/$C$28>M74,$C$29*1/$C$28,M74))
A76: Charge d'amortissement | B76: USD | H76: =H73*H75 | I76: =I73*I75 | J76: =J73*J75 | K76: =K73*K75 | L76: =L73*L75 | M76: =M73*M75
A77: Amortissement restant | B77: USD | H77: =H73-H76 | I77: =I73-I76 | J77: =J73-J76 | K77: =K73-K76 | L77: =L73-L76 | M77: =M73-M76
A79: Immobilisations de l'année A7
A80: Durée restante | B80: Années | I80: =IF($C$28<I$3,$C$28,I$3) | J80: =IF(I80=0,0,IF(I80-1<J$3,I80-1,J$3)) | K80: =IF(J80=0,0,IF(J80-1<K$3,J80-1,K$3)) | L80: =IF(K80=0,0,IF(K80-1<L$3,K80-1,L$3)) | M80: =IF(L80=0,0,IF(L80-1<M$3,L80-1,M$3))
A81: Base amortissable | B81: USD | I81: =Modèle!I$10 | J81: =I85 | K81: =J85 | L81: =K85 | M81: =L85
A82: Inverse de la durée restante | B82: % | I82: =IF(I80=0,0,1/I80) | J82: =IF(J80=0,0,1/J80) | K82: =IF(K80=0,0,1/K80) | L82: =IF(L80=0,0,1/L80) | M82: =IF(M80=0,0,1/M80)
A83: Taux dégressif | B83: % | I83: =IF(I80=0,0,IF($C$29*1/$C$28>I82,$C$29*1/$C$28,I82)) | J83: =IF(J80=0,0,IF($C$29*1/$C$28>J82,$C$29*1/$C$28,J82)) | K83: =IF(K80=0,0,IF($C$29*1/$C$28>K82,$C$29*1/$C$28,K82)) | L83: =IF(L80=0,0,IF($C$29*1/$C$28>L82,$C$29*1/$C$28,L82)) | M83: =IF(M80=0,0,IF($C$29*1/$C$28>M82,$C$29*1/$C$28,M82))
A84: Charge d'amortissement | B84: USD | I84: =I81*I83 | J84: =J81*J83 | K84: =K81*K83 | L84: =L81*L83 | M84: =M81*M83
A85: Amortissement restant | B85: USD | I85: =I81-I84 | J85: =J81-J84 | K85: =K81-K84 | L85: =L81-L84 | M85: =M81-M84
A87: Immobilisations de l'année A8
A88: Durée restante | B88: Années | J88: =IF($C$28<J$3,$C$28,J$3) | K88: =IF(J88=0,0,IF(J88-1<K$3,J88-1,K$3)) | L88: =IF(K88=0,0,IF(K88-1<L$3,K88-1,L$3)) | M88: =IF(L88=0,0,IF(L88-1<M$3,L88-1,M$3))
A89: Base amortissable | B89: USD | J89: =Modèle!J$10 | K89: =J93 | L89: =K93 | M89: =L93
A90: Inverse de la durée restante | B90: % | J90: =IF(J88=0,0,1/J88) | K90: =IF(K88=0,0,1/K88) | L90: =IF(L88=0,0,1/L88) | M90: =IF(M88=0,0,1/M88)
A91: Taux dégressif | B91: % | J91: =IF(J88=0,0,IF($C$29*1/$C$28>J90,$C$29*1/$C$28,J90)) | K91: =IF(K88=0,0,IF($C$29*1/$C$28>K90,$C$29*1/$C$28,K90)) | L91: =IF(L88=0,0,IF($C$29*1/$C$28>L90,$C$29*1/$C$28,L90)) | M91: =IF(M88=0,0,IF($C$29*1/$C$28>M90,$C$29*1/$C$28,M90))
A92: Charge d'amortissement | B92: USD | J92: =J89*J91 | K92: =K89*K91 | L92: =L89*L91 | M92: =M89*M91
A93: Amortissement restant | B93: USD | J93: =J89-J92 | K93: =K89-K92 | L93: =L89-L92 | M93: =M89-M92
A95: Immobilisations de l'année A9
A96: Durée restante | B96: Années | K96: =IF($C$28<K$3,$C$28,K$3) | L96: =IF(K96=0,0,IF(K96-1<L$3,K96-1,L$3)) | M96: =IF(L96=0,0,IF(L96-1<M$3,L96-1,M$3))
A97: Base amortissable | B97: USD | K97: =Modèle!K$10 | L97: =K101 | M97: =L101
A98: Inverse de la durée restante | B98: % | K98: =IF(K96=0,0,1/K96) | L98: =IF(L96=0,0,1/L96) | M98: =IF(M96=0,0,1/M96)
A99: Taux dégressif | B99: % | K99: =IF(K96=0,0,IF($C$29*1/$C$28>K98,$C$29*1/$C$28,K98)) | L99: =IF(L96=0,0,IF($C$29*1/$C$28>L98,$C$29*1/$C$28,L98)) | M99: =IF(M96=0,0,IF($C$29*1/$C$28>M98,$C$29*1/$C$28,M98))
A100: Charge d'amortissement | B100: USD | K100: =K97*K99 | L100: =L97*L99 | M100: =M97*M99
A101: Amortissement restant | B101: USD | K101: =K97-K100 | L101: =L97-L100 | M101: =M97-M100
A103: Immobilisations de l'année A10
A104: Durée restante | B104: Années | L104: =IF($C$28<L$3,$C$28,L$3) | M104: =IF(L104=0,0,IF(L104-1<M$3,L104-1,M$3))
A105: Base amortissable | B105: USD | L105: =Modèle!L$10 | M105: =L109
A106: Inverse de la durée restante | B106: % | L106: =IF(L104=0,0,1/L104) | M106: =IF(M104=0,0,1/M104)
A107: Taux dégressif | B107: % | L107: =IF(L104=0,0,IF($C$29*1/$C$28>L106,$C$29*1/$C$28,L106)) | M107: =IF(M104=0,0,IF($C$29*1/$C$28>M106,$C$29*1/$C$28,M106))
A108: Charge d'amortissement | B108: USD | L108: =L105*L107 | M108: =M105*M107
A109: Amortissement restant | B109: USD | L109: =L105-L108 | M109: =M105-M108
A111: Immobilisations de l'année A11
A112: Durée restante | B112: Années | M112: =IF($C$28<M$3,$C$28,M$3)
A113: Base amortissable | B113: USD | M113: =Modèle!M$10
A114: Inverse de la durée restante | B114: % | M114: =IF(M112=0,0,1/M112)
A115: Taux dégressif | B115: % | M115: =IF(M112=0,0,IF($C$29*1/$C$28>M114,$C$29*1/$C$28,M114))
A116: Charge d'amortissement | B116: USD | M116: =M113*M115
A117: Amortissement restant | B117: USD | M117: =M113-M116
...

Sheet 04_05_Charges_f_1
A1: Nom | B1: Unité | C1: Année 1 | D1: Année 2 | E1: Année 3 | F1: Année 4 | G1: Année 5 | H1: Année 6 | I1: Année 7 | J1: Année 8 | K1: Année 9 | L1: Année 10 | M1: Année 11 | N1: SOMME | O1: VAN
A3: I. PRODUCTION
A4: Production d'or | B4: oz | E4: 250000 | F4: 250000 | G4: 250000 | H4: 250000 | I4: 250000 | J4: 250000 | K4: 250000 | L4: 250000 | N4: =SUM($C4:$M4)
A5: Cours de l'or | B5: USD/oz | E5: 1300 | F5: 1300 | G5: 1300 | H5: 1300 | I5: 1300 | J5: 1300 | K5: 1300 | L5: 1300
A6: Chiffre d'affaires | B6: USD | C6: =C$4*C$5 | D6: =D$4*D$5 | E6: =E$4*E$5 | F6: =F$4*F$5 | G6: =G$4*G$5 | H6: =H$4*H$5 | I6: =I$4*I$5 | J6: =J$4*J$5 | ... M6: =M$4*M$5 | N6: =SUM($C6:$M6) | O6: =$C6+NPV(10%,$D6:$M6)
A8: II. DEPENSES D'INVESTISSEMENT (CAPEX)
A9: Coûts des construction industrielles | B9: USD | C9: 50000000 | D9: 100000000 | N9: =SUM($C9:$M9) | O9: =$C9+NPV(10%,$D9:$M9)
A10: Coûts des biens d'équipement | B10: USD | D10: 50000000 | E10: 5000000 | F10: 5000000 | G10: 5000000 | H10: 5000000 | I10: 5000000 | J10: 5000000 | K10: 5000000 | L10: 5000000 | N10: =SUM($C10:$M10) | O10: =$C10+NPV(10%,$D10:$M10)
A11: Coûts de réhabilitation du site | B11: USD | M11: 10000000 | N11: =SUM($C11:$M11) | O11: =$C11+NPV(10%,$D11:$M11)
A12: Total des dépenses d'investissement | B12: USD | C12: =SUM(C$9:C$11) | D12: =SUM(D$9:D$11) | E12: =SUM(E$9:E$11) | F12: =SUM(F$9:F$11) | G12: =SUM(G$9:G$11) | H12: =SUM(H$9:H$11) | I12: =SUM(I$9:I$11) | J12: =SUM(J$9:J$11) | ... M12: =SUM(M$9:M$11) | N12: =SUM($C12:$M12) | O12: =$C12+NPV(10%,$D12:$M12)
A14: III. COÛTS D'EXPLOITATION (OPEX)
A15: Coût moyen d'exploitation | B15: USD/oz | E15: 700 | F15: 700 | G15: 700 | H15: 700 | I15: 700 | J15: 700 | K15: 700 | L15: 700
A16: Total des coûts d'exploitation | B16: USD | C16: =C$4*C$15 | D16: =D$4*D$15 | E16: =E$4*E$15 | F16: =F$4*F$15 | G16: =G$4*G$15 | H16: =H$4*H$15 | I16: =I$4*I$15 | J16: =J$4*J$15 | ... M16: =M$4*M$15 | N16: =SUM($C16:$M16) | O16: =$C16+NPV(10%,$D16:$M16)
A18: IV. FLUX NETS DE TRESORERIE AVANT IMPÔTS
A19: Flux nets de trésorerie avant impôts | B19: USD | C19: =C$6-C$12-C$16 | D19: =D$6-D$12-D$16 | E19: =E$6-E$12-E$16 | F19: =F$6-F$12-F$16 | G19: =G$6-G$12-G$16 | H19: =H$6-H$12-H$16 | I19: =I$6-I$12-I$16 | J19: =J$6-J$12-J$16 | ... M19: =M$6-M$12-M$16 | N19: =SUM($C19:$M19) | O19: =$C19+NPV(10%,$D19:$M19)
A20: Taux de rendement interne avant impôts | B20: % | C20: =IF(ISNUMBER(IRR($C19:C19)),IF(IRR($C19:C19)>0,IRR($C19:C19),""),"") | D20: =IF(ISNUMBER(IRR($C19:D19)),IF(IRR($C19:D19)>0,IRR($C19:D19),""),"") | E20: =IF(ISNUMBER(IRR($C19:E19)),IF(IRR($C19:E19)>0,IRR($C19:E19),""),"") | F20: =IF(ISNUMBER(IRR($C19:F19)),IF(IRR($C19:F19)>0,IRR($C19:F19),""),"") | G20: =IF(ISNUMBER(IRR($C19:G19)),IF(IRR($C19:G19)>0,IRR($C19:G19),""),"") | H20: =IF(ISNUMBER(IRR($C19:H19)),IF(IRR($C19:H19)>0,IRR($C19:H19),""),"") | I20: =IF(ISNUMBER(IRR($C19:I19)),IF(IRR($C19:I19)>0,IRR($C19:I19),""),"") | J20: =IF(ISNUMBER(IRR($C19:J19)),IF(IRR($C19:J19)>0,IRR($C19:J19),""),"") | ... M20: =IF(ISNUMBER(IRR($C19:M19)),IF(IRR($C19:M19)>0,IRR($C19:M19),""),"")
A22: V. DROITS FIXES
A23: Droits fixes | B23: USD | C23: 100000 | N23: =SUM($C23:$M23) | O23: =$C23+NPV(10%,$D23:$M23)
A25: VI. REDEVANCE SUPERFICAIRE
A26: Superficie de la mine | B26: km² | C26: 100 | D26: 100 | E26: 100 | F26: 100 | G26: 100 | H26: 100 | I26: 100 | J26: 100 | K26: 100 | L26: 100 | M26: 100
A27: Montant de la redevance superfiaire | B27: USD/km² | C27: 100 | D27: 100 | E27: 100 | F27: 100 | G27: 100 | H27: 100 | I27: 100 | J27: 100 | K27: 100 | L27: 100 | M27: 100
A28: Redevance superficiaire | B28: USD | C28: =C$26*C$27 | D28: =D$26*D$27 | E28: =E$26*E$27 | F28: =F$26*F$27 | G28: =G$26*G$27 | H28: =H$26*H$27 | I28: =I$26*I$27 | J28: =J$26*J$27 | ... M28: =M$26*M$27 | N28: =SUM($C28:$M28) | O28: =$C28+NPV(10%,$D28:$M28)
A30: VII. REDEVANCE MINIERE
A31: Taux de la redevance minière | B31: % | C31: =IF(ISNUMBER(C5),IF(C$5<1300,3%,IF(C$5<1500,4%,5%)),"") | D31: =IF(ISNUMBER(D5),IF(D$5<1300,3%,IF(D$5<1500,4%,5%)),"") | E31: =IF(ISNUMBER(E5),IF(E$5<1300,3%,IF(E$5<1500,4%,5%)),"") | F31: =IF(ISNUMBER(F5),IF(F$5<1300,3%,IF(F$5<1500,4%,5%)),"") | G31: =IF(ISNUMBER(G5),IF(G$5<1300,3%,IF(G$5<1500,4%,5%)),"") | H31: =IF(ISNUMBER(H5),IF(H$5<1300,3%,IF(H$5<1500,4%,5%)),"") | I31: =IF(ISNUMBER(I5),IF(I$5<1300,3%,IF(I$5<1500,4%,5%)),"") | J31: =IF(ISNUMBER(J5),IF(J$5<1300,3%,IF(J$5<1500,4%,5%)),"") | ... M31: =IF(ISNUMBER(M5),IF(M$5<1300,3%,IF(M$5<1500,4%,5%)),"")
A32: Redevance minière | B32: USD | C32: =IF(ISNUMBER(C31),C$6*C$31,0) | D32: =IF(ISNUMBER(D31),D$6*D$31,0) | E32: =IF(ISNUMBER(E31),E$6*E$31,0) | F32: =IF(ISNUMBER(F31),F$6*F$31,0) | G32: =IF(ISNUMBER(G31),G$6*G$31,0) | H32: =IF(ISNUMBER(H31),H$6*H$31,0) | I32: =IF(ISNUMBER(I31),I$6*I$31,0) | J32: =IF(ISNUMBER(J31),J$6*J$31,0) | ... M32: =IF(ISNUMBER(M31),M$6*M$31,0) | N32: =SUM($C32:$M32) | O32: =$C32+NPV(10%,$D32:$M32)

Sheet 04_05_Charges_f_2
A1: Nom | B1: Unité | C1: Année 1 | D1: Année 2 | E1: Année 3 | F1: Année 4 | G1: Année 5 | H1: Année 6 | I1: Année 7 | J1: Année 8 | K1: Année 9 | L1: Année 10 | M1: Année 11
A3: Durée restante maximum | B3: Années | C3: 11 | D3: 10 | E3: 9 | F3: 8 | G3: 7 | H3: 6 | I3: 5 | J3: 4 | K3: 3 | L3: 2 | M3: 1
A5: I. AMORTISSEMENTS DES CONSTRUCTIONS INDUSTRIELLES
A6: Durée d'amortissement linéaire | B6: Années | C6: 10
A7: Coefficient d'amortissement dégressif | B7: Coefficient | C7: 1
A9: Immobilisations de l'année A1
A10: Durée restante | B10: Années | C10: =IF($C$6<C$3,$C$6,C$3) | D10: =IF(C10=0,0,IF(C10-1<D$3,C10-1,D$3)) | E10: =IF(D10=0,0,IF(D10-1<E$3,D10-1,E$3)) | F10: =IF(E10=0,0,IF(E10-1<F$3,E10-1,F$3)) | G10: =IF(F10=0,0,IF(F10-1<G$3,F10-1,G$3)) | H10: =IF(G10=0,0,IF(G10-1<H$3,G10-1,H$3)) | I10: =IF(H10=0,0,IF(H10-1<I$3,H10-1,I$3)) | J10: =IF(I10=0,0,IF(I10-1<J$3,I10-1,J$3)) | K10: =IF(J10=0,0,IF(J10-1<K$3,J10-1,K$3)) | ... M10: =IF(L10=0,0,IF(L10-1<M$3,L10-1,M$3))
A11: Base amortissable | B11: USD | C11: =Modèle!C$9 | D11: =C15 | E11: =D15 | F11: =E15 | G11: =F15 | H11: =G15 | I11: =H15 | J11: =I15 | K11: =J15 | ... M11: =L15
A12: Inverse de la durée restante | B12: % | C12: =IF(C10=0,0,1/C10) | D12: =IF(D10=0,0,1/D10) | E12: =IF(E10=0,0,1/E10) | F12: =IF(F10=0,0,1/F10) | G12: =IF(G10=0,0,1/G10) | H12: =IF(H10=0,0,1/H10) | I12: =IF(I10=0,0,1/I10) | J12: =IF(J10=0,0,1/J10) | ... M12: =IF(M10=0,0,1/M10)
A13: Taux dégressif | B13: % | C13: =IF(C10=0,0,IF($C$7*1/$C$6>C12,$C$7*1/$C$6,C12)) | D13: =IF(D10=0,0,IF($C$7*1/$C$6>D12,$C$7*1/$C$6,D12)) | E13: =IF(E10=0,0,IF($C$7*1/$C$6>E12,$C$7*1/$C$6,E12)) | F13: =IF(F10=0,0,IF($C$7*1/$C$6>F12,$C$7*1/$C$6,F12)) | G13: =IF(G10=0,0,IF($C$7*1/$C$6>G12,$C$7*1/$C$6,G12)) | H13: =IF(H10=0,0,IF($C$7*1/$C$6>H12,$C$7*1/$C$6,H12)) | I13: =IF(I10=0,0,IF($C$7*1/$C$6>I12,$C$7*1/$C$6,I12)) | J13: =IF(J10=0,0,IF($C$7*1/$C$6>J12,$C$7*1/$C$6,J12)) | ... M13: =IF(M10=0,0,IF($C$7*1/$C$6>M12,$C$7*1/$C$6,M12))
A14: Charge d'amortissement | B14: USD | C14: =C11*C13 | D14: =D11*D13 | E14: =E11*E13 | F14: =F11*F13 | G14: =G11*G13 | H14: =H11*H13 | I14: =I11*I13 | J14: =J11*J13 | ... M14: =M11*M13
A15: Amortissement restant | B15: USD | C15: =C11-C14 | D15: =D11-D14 | E15: =E11-E14 | F15: =F11-F14 | G15: =G11-G14 | H15: =H11-H14 | I15: =I11-I14 | J15: =J11-J14 | ... M15: =M11-M14
A17: Immobilisations de l'année A2
A18: Durée restante | B18: Années | D18: =IF($C$6<D$3,$C$6,D$3) | E18: =IF(D18=0,0,IF(D18-1<E$3,D18-1,E$3)) | F18: =IF(E18=0,0,IF(E18-1<F$3,E18-1,F$3)) | G18: =IF(F18=0,0,IF(F18-1<G$3,F18-1,G$3)) | H18: =IF(G18=0,0,IF(G18-1<H$3,G18-1,H$3)) | I18: =IF(H18=0,0,IF(H18-1<I$3,H18-1,I$3)) | J18: =IF(I18=0,0,IF(I18-1<J$3,I18-1,J$3)) | K18: =IF(J18=0,0,IF(J18-1<K$3,J18-1,K$3)) | L18: =IF(K18=0,0,IF(K18-1<L$3,K18-1,L$3)) | M18: =IF(L18=0,0,IF(L18-1<M$3,L18-1,M$3))
A19: Base amortissable | B19: USD | D19: =Modèle!D$9 | E19: =D23 | F19: =E23 | G19: =F23 | H19: =G23 | I19: =H23 | J19: =I23 | K19: =J23 | L19: =K23 | M19: =L23
A20: Inverse de la durée restante | B20: % | D20: =IF(D18=0,0,1/D18) | E20: =IF(E18=0,0,1/E18) | F20: =IF(F18=0,0,1/F18) | G20: =IF(G18=0,0,1/G18) | H20: =IF(H18=0,0,1/H18) | I20: =IF(I18=0,0,1/I18) | J20: =IF(J18=0,0,1/J18) | K20: =IF(K18=0,0,1/K18) | ... M20: =IF(M18=0,0,1/M18)
A21: Taux dégressif | B21: % | D21: =IF(D18=0,0,IF($C$7*1/$C$6>D20,$C$7*1/$C$6,D20)) | E21: =IF(E18=0,0,IF($C$7*1/$C$6>E20,$C$7*1/$C$6,E20)) | F21: =IF(F18=0,0,IF($C$7*1/$C$6>F20,$C$7*1/$C$6,F20)) | G21: =IF(G18=0,0,IF($C$7*1/$C$6>G20,$C$7*1/$C$6,G20)) | H21: =IF(H18=0,0,IF($C$7*1/$C$6>H20,$C$7*1/$C$6,H20)) | I21: =IF(I18=0,0,IF($C$7*1/$C$6>I20,$C$7*1/$C$6,I20)) | J21: =IF(J18=0,0,IF($C$7*1/$C$6>J20,$C$7*1/$C$6,J20)) | K21: =IF(K18=0,0,IF($C$7*1/$C$6>K20,$C$7*1/$C$6,K20)) | ... M21: =IF(M18=0,0,IF($C$7*1/$C$6>M20,$C$7*1/$C$6,M20))
A22: Charge d'amortissement | B22: USD | D22: =D19*D21 | E22: =E19*E21 | F22: =F19*F21 | G22: =G19*G21 | H22: =H19*H21 | I22: =I19*I21 | J22: =J19*J21 | K22: =K19*K21 | ... M22: =M19*M21
A23: Amortissement restant | B23: USD | D23: =D19-D22 | E23: =E19-E22 | F23: =F19-F22 | G23: =G19-G22 | H23: =H19-H22 | I23: =I19-I22 | J23: =J19-J22 | K23: =K19-K22 | ... M23: =M19-M22
A25: Amortissements des constructions industrielles | B25: USD | C25: =C$14+C$22 | D25: =D$14+D$22 | E25: =E$14+E$22 | F25: =F$14+F$22 | G25: =G$14+G$22 | H25: =H$14+H$22 | I25: =I$14+I$22 | J25: =J$14+J$22 | ... M25: =M$14+M$22
A27: II. AMORTISSEMENTS DES BIENS D'EQUIPEMENT
A28: Durée d'amortissement linéaire | B28: Années | C28: 5
A29: Coefficient d'amortissement dégressif | B29: Coefficient | C29: 2
A31: Immobilisations de l'année A1
A32: Durée restante | B32: Années | C32: =IF($C$28<C$3,$C$28,C$3) | D32: =IF(C32=0,0,IF(C32-1<D$3,C32-1,D$3)) | E32: =IF(D32=0,0,IF(D32-1<E$3,D32-1,E$3)) | F32: =IF(E32=0,0,IF(E32-1<F$3,E32-1,F$3)) | G32: =IF(F32=0,0,IF(F32-1<G$3,F32-1,G$3)) | H32: =IF(G32=0,0,IF(G32-1<H$3,G32-1,H$3)) | I32: =IF(H32=0,0,IF(H32-1<I$3,H32-1,I$3)) | J32: =IF(I32=0,0,IF(I32-1<J$3,I32-1,J$3)) | K32: =IF(J32=0,0,IF(J32-1<K$3,J32-1,K$3)) | ... M32: =IF(L32=0,0,IF(L32-1<M$3,L32-1,M$3))
A33: Base amortissable | B33: USD | C33: =Modèle!C$10 | D33: =C37 | E33: =D37 | F33: =E37 | G33: =F37 | H33: =G37 | I33: =H37 | J33: =I37 | K33: =J37 | ... M33: =L37
A34: Inverse de la durée restante | B34: % | C34: =IF(C32=0,0,1/C32) | D34: =IF(D32=0,0,1/D32) | E34: =IF(E32=0,0,1/E32) | F34: =IF(F32=0,0,1/F32) | G34: =IF(G32=0,0,1/G32) | H34: =IF(H32=0,0,1/H32) | I34: =IF(I32=0,0,1/I32) | J34: =IF(J32=0,0,1/J32) | ... M34: =IF(M32=0,0,1/M32)
A35: Taux dégressif | B35: % | C35: =IF(C32=0,0,IF($C$29*1/$C$28>C34,$C$29*1/$C$28,C34)) | D35: =IF(D32=0,0,IF($C$29*1/$C$28>D34,$C$29*1/$C$28,D34)) | E35: =IF(E32=0,0,IF($C$29*1/$C$28>E34,$C$29*1/$C$28,E34)) | F35: =IF(F32=0,0,IF($C$29*1/$C$28>F34,$C$29*1/$C$28,F34)) | G35: =IF(G32=0,0,IF($C$29*1/$C$28>G34,$C$29*1/$C$28,G34)) | H35: =IF(H32=0,0,IF($C$29*1/$C$28>H34,$C$29*1/$C$28,H34)) | I35: =IF(I32=0,0,IF($C$29*1/$C$28>I34,$C$29*1/$C$28,I34)) | J35: =IF(J32=0,0,IF($C$29*1/$C$28>J34,$C$29*1/$C$28,J34)) | ... M35: =IF(M32=0,0,IF($C$29*1/$C$28>M34,$C$29*1/$C$28,M34))
A36: Charge d'amortissement | B36: USD | C36: =C33*C35 | D36: =D33*D35 | E36: =E33*E35 | F36: =F33*F35 | G36: =G33*G35 | H36: =H33*H35 | I36: =I33*I35 | J36: =J33*J35 | ... M36: =M33*M35
A37: Amortissement restant | B37: USD | C37: =C33-C36 | D37: =D33-D36 | E37: =E33-E36 | F37: =F33-F36 | G37: =G33-G36 | H37: =H33-H36 | I37: =I33-I36 | J37: =J33-J36 | ... M37: =M33-M36
A39: Immobilisations de l'année A2
A40: Durée restante | B40: Années | D40: =IF($C$28<D$3,$C$28,D$3) | E40: =IF(D40=0,0,IF(D40-1<E$3,D40-1,E$3)) | F40: =IF(E40=0,0,IF(E40-1<F$3,E40-1,F$3)) | G40: =IF(F40=0,0,IF(F40-1<G$3,F40-1,G$3)) | H40: =IF(G40=0,0,IF(G40-1<H$3,G40-1,H$3)) | I40: =IF(H40=0,0,IF(H40-1<I$3,H40-1,I$3)) | J40: =IF(I40=0,0,IF(I40-1<J$3,I40-1,J$3)) | K40: =IF(J40=0,0,IF(J40-1<K$3,J40-1,K$3)) | L40: =IF(K40=0,0,IF(K40-1<L$3,K40-1,L$3)) | M40: =IF(L40=0,0,IF(L40-1<M$3,L40-1,M$3))
A41: Base amortissable | B41: USD | D41: =Modèle!D$10 | E41: =D45 | F41: =E45 | G41: =F45 | H41: =G45 | I41: =H45 | J41: =I45 | K41: =J45 | L41: =K45 | M41: =L45
A42: Inverse de la durée restante | B42: % | D42: =IF(D40=0,0,1/D40) | E42: =IF(E40=0,0,1/E40) | F42: =IF(F40=0,0,1/F40) | G42: =IF(G40=0,0,1/G40) | H42: =IF(H40=0,0,1/H40) | I42: =IF(I40=0,0,1/I40) | J42: =IF(J40=0,0,1/J40) | K42: =IF(K40=0,0,1/K40) | ... M42: =IF(M40=0,0,1/M40)
A43: Taux dégressif | B43: % | D43: =IF(D40=0,0,IF($C$29*1/$C$28>D42,$C$29*1/$C$28,D42)) | E43: =IF(E40=0,0,IF($C$29*1/$C$28>E42,$C$29*1/$C$28,E42)) | F43: =IF(F40=0,0,IF($C$29*1/$C$28>F42,$C$29*1/$C$28,F42)) | G43: =IF(G40=0,0,IF($C$29*1/$C$28>G42,$C$29*1/$C$28,G42)) | H43: =IF(H40=0,0,IF($C$29*1/$C$28>H42,$C$29*1/$C$28,H42)) | I43: =IF(I40=0,0,IF($C$29*1/$C$28>I42,$C$29*1/$C$28,I42)) | J43: =IF(J40=0,0,IF($C$29*1/$C$28>J42,$C$29*1/$C$28,J42)) | K43: =IF(K40=0,0,IF($C$29*1/$C$28>K42,$C$29*1/$C$28,K42)) | ... M43: =IF(M40=0,0,IF($C$29*1/$C$28>M42,$C$29*1/$C$28,M42))
A44: Charge d'amortissement | B44: USD | D44: =D41*D43 | E44: =E41*E43 | F44: =F41*F43 | G44: =G41*G43 | H44: =H41*H43 | I44: =I41*I43 | J44: =J41*J43 | K44: =K41*K43 | ... M44: =M41*M43
A45: Amortissement restant | B45: USD | D45: =D41-D44 | E45: =E41-E44 | F45: =F41-F44 | G45: =G41-G44 | H45: =H41-H44 | I45: =I41-I44 | J45: =J41-J44 | K45: =K41-K44 | ... M45: =M41-M44
A47: Immobilisations de l'année A3
A48: Durée restante | B48: Années | E48: =IF($C$28<E$3,$C$28,E$3) | F48: =IF(E48=0,0,IF(E48-1<F$3,E48-1,F$3)) | G48: =IF(F48=0,0,IF(F48-1<G$3,F48-1,G$3)) | H48: =IF(G48=0,0,IF(G48-1<H$3,G48-1,H$3)) | I48: =IF(H48=0,0,IF(H48-1<I$3,H48-1,I$3)) | J48: =IF(I48=0,0,IF(I48-1<J$3,I48-1,J$3)) | K48: =IF(J48=0,0,IF(J48-1<K$3,J48-1,K$3)) | L48: =IF(K48=0,0,IF(K48-1<L$3,K48-1,L$3)) | M48: =IF(L48=0,0,IF(L48-1<M$3,L48-1,M$3))
A49: Base amortissable | B49: USD | E49: =Modèle!E$10 | F49: =E53 | G49: =F53 | H49: =G53 | I49: =H53 | J49: =I53 | K49: =J53 | L49: =K53 | M49: =L53
A50: Inverse de la durée restante | B50: % | E50: =IF(E48=0,0,1/E48) | F50: =IF(F48=0,0,1/F48) | G50: =IF(G48=0,0,1/G48) | H50: =IF(H48=0,0,1/H48) | I50: =IF(I48=0,0,1/I48) | J50: =IF(J48=0,0,1/J48) | K50: =IF(K48=0,0,1/K48) | L50: =IF(L48=0,0,1/L48) | M50: =IF(M48=0,0,1/M48)
A51: Taux dégressif | B51: % | E51: =IF(E48=0,0,IF($C$29*1/$C$28>E50,$C$29*1/$C$28,E50)) | F51: =IF(F48=0,0,IF($C$29*1/$C$28>F50,$C$29*1/$C$28,F50)) | G51: =IF(G48=0,0,IF($C$29*1/$C$28>G50,$C$29*1/$C$28,G50)) | H51: =IF(H48=0,0,IF($C$29*1/$C$28>H50,$C$29*1/$C$28,H50)) | I51: =IF(I48=0,0,IF($C$29*1/$C$28>I50,$C$29*1/$C$28,I50)) | J51: =IF(J48=0,0,IF($C$29*1/$C$28>J50,$C$29*1/$C$28,J50)) | K51: =IF(K48=0,0,IF($C$29*1/$C$28>K50,$C$29*1/$C$28,K50)) | L51: =IF(L48=0,0,IF($C$29*1/$C$28>L50,$C$29*1/$C$28,L50)) | M51: =IF(M48=0,0,IF($C$29*1/$C$28>M50,$C$29*1/$C$28,M50))
A52: Charge d'amortissement | B52: USD | E52: =E49*E51 | F52: =F49*F51 | G52: =G49*G51 | H52: =H49*H51 | I52: =I49*I51 | J52: =J49*J51 | K52: =K49*K51 | L52: =L49*L51 | M52: =M49*M51
A53: Amortissement restant | B53: USD | E53: =E49-E52 | F53: =F49-F52 | G53: =G49-G52 | H53: =H49-H52 | I53: =I49-I52 | J53: =J49-J52 | K53: =K49-K52 | L53: =L49-L52 | M53: =M49-M52
A55: Immobilisations de l'année A4
A56: Durée restante | B56: Années | F56: =IF($C$28<F$3,$C$28,F$3) | G56: =IF(F56=0,0,IF(F56-1<G$3,F56-1,G$3)) | H56: =IF(G56=0,0,IF(G56-1<H$3,G56-1,H$3)) | I56: =IF(H56=0,0,IF(H56-1<I$3,H56-1,I$3)) | J56: =IF(I56=0,0,IF(I56-1<J$3,I56-1,J$3)) | K56: =IF(J56=0,0,IF(J56-1<K$3,J56-1,K$3)) | L56: =IF(K56=0,0,IF(K56-1<L$3,K56-1,L$3)) | M56: =IF(L56=0,0,IF(L56-1<M$3,L56-1,M$3))
A57: Base amortissable | B57: USD | F57: =Modèle!F$10 | G57: =F61 | H57: =G61 | I57: =H61 | J57: =I61 | K57: =J61 | L57: =K61 | M57: =L61
A58: Inverse de la durée restante | B58: % | F58: =IF(F56=0,0,1/F56) | G58: =IF(G56=0,0,1/G56) | H58: =IF(H56=0,0,1/H56) | I58: =IF(I56=0,0,1/I56) | J58: =IF(J56=0,0,1/J56) | K58: =IF(K56=0,0,1/K56) | L58: =IF(L56=0,0,1/L56) | M58: =IF(M56=0,0,1/M56)
A59: Taux dégressif | B59: % | F59: =IF(F56=0,0,IF($C$29*1/$C$28>F58,$C$29*1/$C$28,F58)) | G59: =IF(G56=0,0,IF($C$29*1/$C$28>G58,$C$29*1/$C$28,G58)) | H59: =IF(H56=0,0,IF($C$29*1/$C$28>H58,$C$29*1/$C$28,H58)) | I59: =IF(I56=0,0,IF($C$29*1/$C$28>I58,$C$29*1/$C$28,I58)) | J59: =IF(J56=0,0,IF($C$29*1/$C$28>J58,$C$29*1/$C$28,J58)) | K59: =IF(K56=0,0,IF($C$29*1/$C$28>K58,$C$29*1/$C$28,K58)) | L59: =IF(L56=0,0,IF($C$29*1/$C$28>L58,$C$29*1/$C$28,L58)) | M59: =IF(M56=0,0,IF($C$29*1/$C$28>M58,$C$29*1/$C$28,M58))
A60: Charge d'amortissement | B60: USD | F60: =F57*F59 | G60: =G57*G59 | H60: =H57*H59 | I60: =I57*I59 | J60: =J57*J59 | K60: =K57*K59 | L60: =L57*L59 | M60: =M57*M59
A61: Amortissement restant | B61: USD | F61: =F57-F60 | G61: =G57-G60 | H61: =H57-H60 | I61: =I57-I60 | J61: =J57-J60 | K61: =K57-K60 | L61: =L57-L60 | M61: =M57-M60
A63: Immobilisations de l'année A5
A64: Durée restante | B64: Années | G64: =IF($C$28<G$3,$C$28,G$3) | H64: =IF(G64=0,0,IF(G64-1<H$3,G64-1,H$3)) | I64: =IF(H64=0,0,IF(H64-1<I$3,H64-1,I$3)) | J64: =IF(I64=0,0,IF(I64-1<J$3,I64-1,J$3)) | K64: =IF(J64=0,0,IF(J64-1<K$3,J64-1,K$3)) | L64: =IF(K64=0,0,IF(K64-1<L$3,K64-1,L$3)) | M64: =IF(L64=0,0,IF(L64-1<M$3,L64-1,M$3))
A65: Base amortissable | B65: USD | G65: =Modèle!G$10 | H65: =G69 | I65: =H69 | J65: =I69 | K65: =J69 | L65: =K69 | M65: =L69
A66: Inverse de la durée restante | B66: % | G66: =IF(G64=0,0,1/G64) | H66: =IF(H64=0,0,1/H64) | I66: =IF(I64=0,0,1/I64) | J66: =IF(J64=0,0,1/J64) | K66: =IF(K64=0,0,1/K64) | L66: =IF(L64=0,0,1/L64) | M66: =IF(M64=0,0,1/M64)
A67: Taux dégressif | B67: % | G67: =IF(G64=0,0,IF($C$29*1/$C$28>G66,$C$29*1/$C$28,G66)) | H67: =IF(H64=0,0,IF($C$29*1/$C$28>H66,$C$29*1/$C$28,H66)) | I67: =IF(I64=0,0,IF($C$29*1/$C$28>I66,$C$29*1/$C$28,I66)) | J67: =IF(J64=0,0,IF($C$29*1/$C$28>J66,$C$29*1/$C$28,J66)) | K67: =IF(K64=0,0,IF($C$29*1/$C$28>K66,$C$29*1/$C$28,K66)) | L67: =IF(L64=0,0,IF($C$29*1/$C$28>L66,$C$29*1/$C$28,L66)) | M67: =IF(M64=0,0,IF($C$29*1/$C$28>M66,$C$29*1/$C$28,M66))
A68: Charge d'amortissement | B68: USD | G68: =G65*G67 | H68: =H65*H67 | I68: =I65*I67 | J68: =J65*J67 | K68: =K65*K67 | L68: =L65*L67 | M68: =M65*M67
A69: Amortissement restant | B69: USD | G69: =G65-G68 | H69: =H65-H68 | I69: =I65-I68 | J69: =J65-J68 | K69: =K65-K68 | L69: =L65-L68 | M69: =M65-M68
A71: Immobilisations de l'année A6
A72: Durée restante | B72: Années | H72: =IF($C$28<H$3,$C$28,H$3) | I72: =IF(H72=0,0,IF(H72-1<I$3,H72-1,I$3)) | J72: =IF(I72=0,0,IF(I72-1<J$3,I72-1,J$3)) | K72: =IF(J72=0,0,IF(J72-1<K$3,J72-1,K$3)) | L72: =IF(K72=0,0,IF(K72-1<L$3,K72-1,L$3)) | M72: =IF(L72=0,0,IF(L72-1<M$3,L72-1,M$3))
A73: Base amortissable | B73: USD | H73: =Modèle!H$10 | I73: =H77 | J73: =I77 | K73: =J77 | L73: =K77 | M73: =L77
A74: Inverse de la durée restante | B74: % | H74: =IF(H72=0,0,1/H72) | I74: =IF(I72=0,0,1/I72) | J74: =IF(J72=0,0,1/J72) | K74: =IF(K72=0,0,1/K72) | L74: =IF(L72=0,0,1/L72) | M74: =IF(M72=0,0,1/M72)
A75: Taux dégressif | B75: % | H75: =IF(H72=0,0,IF($C$29*1/$C$28>H74,$C$29*1/$C$28,H74)) | I75: =IF(I72=0,0,IF($C$29*1/$C$28>I74,$C$29*1/$C$28,I74)) | J75: =IF(J72=0,0,IF($C$29*1/$C$28>J74,$C$29*1/$C$28,J74)) | K75: =IF(K72=0,0,IF($C$29*1/$C$28>K74,$C$29*1/$C$28,K74)) | L75: =IF(L72=0,0,IF($C$29*1/$C$28>L74,$C$29*1/$C$28,L74)) | M75: =IF(M72=0,0,IF($C$29*1/$C$28>M74,$C$29*1/$C$28,M74))
A76: Charge d'amortissement | B76: USD | H76: =H73*H75 | I76: =I73*I75 | J76: =J73*J75 | K76: =K73*K75 | L76: =L73*L75 | M76: =M73*M75
A77: Amortissement restant | B77: USD | H77: =H73-H76 | I77: =I73-I76 | J77: =J73-J76 | K77: =K73-K76 | L77: =L73-L76 | M77: =M73-M76
A79: Immobilisations de l'année A7
A80: Durée restante | B80: Années | I80: =IF($C$28<I$3,$C$28,I$3) | J80: =IF(I80=0,0,IF(I80-1<J$3,I80-1,J$3)) | K80: =IF(J80=0,0,IF(J80-1<K$3,J80-1,K$3)) | L80: =IF(K80=0,0,IF(K80-1<L$3,K80-1,L$3)) | M80: =IF(L80=0,0,IF(L80-1<M$3,L80-1,M$3))
A81: Base amortissable | B81: USD | I81: =Modèle!I$10 | J81: =I85 | K81: =J85 | L81: =K85 | M81: =L85
A82: Inverse de la durée restante | B82: % | I82: =IF(I80=0,0,1/I80) | J82: =IF(J80=0,0,1/J80) | K82: =IF(K80=0,0,1/K80) | L82: =IF(L80=0,0,1/L80) | M82: =IF(M80=0,0,1/M80)
A83: Taux dégressif | B83: % | I83: =IF(I80=0,0,IF($C$29*1/$C$28>I82,$C$29*1/$C$28,I82)) | J83: =IF(J80=0,0,IF($C$29*1/$C$28>J82,$C$29*1/$C$28,J82)) | K83: =IF(K80=0,0,IF($C$29*1/$C$28>K82,$C$29*1/$C$28,K82)) | L83: =IF(L80=0,0,IF($C$29*1/$C$28>L82,$C$29*1/$C$28,L82)) | M83: =IF(M80=0,0,IF($C$29*1/$C$28>M82,$C$29*1/$C$28,M82))
A84: Charge d'amortissement | B84: USD | I84: =I81*I83 | J84: =J81*J83 | K84: =K81*K83 | L84: =L81*L83 | M84: =M81*M83
A85: Amortissement restant | B85: USD | I85: =I81-I84 | J85: =J81-J84 | K85: =K81-K84 | L85: =L81-L84 | M85: =M81-M84
A87: Immobilisations de l'année A8
A88: Durée restante | B88: Années | J88: =IF($C$28<J$3,$C$28,J$3) | K88: =IF(J88=0,0,IF(J88-1<K$3,J88-1,K$3)) | L88: =IF(K88=0,0,IF(K88-1<L$3,K88-1,L$3)) | M88: =IF(L88=0,0,IF(L88-1<M$3,L88-1,M$3))
A89: Base amortissable | B89: USD | J89: =Modèle!J$10 | K89: =J93 | L89: =K93 | M89: =L93
A90: Inverse de la durée restante | B90: % | J90: =IF(J88=0,0,1/J88) | K90: =IF(K88=0,0,1/K88) | L90: =IF(L88=0,0,1/L88) | M90: =IF(M88=0,0,1/M88)
A91: Taux dégressif | B91: % | J91: =IF(J88=0,0,IF($C$29*1/$C$28>J90,$C$29*1/$C$28,J90)) | K91: =IF(K88=0,0,IF($C$29*1/$C$28>K90,$C$29*1/$C$28,K90)) | L91: =IF(L88=0,0,IF($C$29*1/$C$28>L90,$C$29*1/$C$28,L90)) | M91: =IF(M88=0,0,IF($C$29*1/$C$28>M90,$C$29*1/$C$28,M90))
A92: Charge d'amortissement | B92: USD | J92: =J89*J91 | K92: =K89*K91 | L92: =L89*L91 | M92: =M89*M91
A93: Amortissement restant | B93: USD | J93: =J89-J92 | K93: =K89-K92 | L93: =L89-L92 | M93: =M89-M92
A95: Immobilisations de l'année A9
A96: Durée restante | B96: Années | K96: =IF($C$28<K$3,$C$28,K$3) | L96: =IF(K96=0,0,IF(K96-1<L$3,K96-1,L$3)) | M96: =IF(L96=0,0,IF(L96-1<M$3,L96-1,M$3))
A97: Base amortissable | B97: USD | K97: =Modèle!K$10 | L97: =K101 | M97: =L101
A98: Inverse de la durée restante | B98: % | K98: =IF(K96=0,0,1/K96) | L98: =IF(L96=0,0,1/L96) | M98: =IF(M96=0,0,1/M96)
A99: Taux dégressif | B99: % | K99: =IF(K96=0,0,IF($C$29*1/$C$28>K98,$C$29*1/$C$28,K98)) | L99: =IF(L96=0,0,IF($C$29*1/$C$28>L98,$C$29*1/$C$28,L98)) | M99: =IF(M96=0,0,IF($C$29*1/$C$28>M98,$C$29*1/$C$28,M98))
A100: Charge d'amortissement | B100: USD | K100: =K97*K99 | L100: =L97*L99 | M100: =M97*M99
A101: Amortissement restant | B101: USD | K101: =K97-K100 | L101: =L97-L100 | M101: =M97-M100
A103: Immobilisations de l'année A10
A104: Durée restante | B104: Années | L104: =IF($C$28<L$3,$C$28,L$3) | M104: =IF(L104=0,0,IF(L104-1<M$3,L104-1,M$3))
A105: Base amortissable | B105: USD | L105: =Modèle!L$10 | M105: =L109
A106: Inverse de la durée restante | B106: % | L106: =IF(L104=0,0,1/L104) | M106: =IF(M104=0,0,1/M104)
A107: Taux dégressif | B107: % | L107: =IF(L104=0,0,IF($C$29*1/$C$28>L106,$C$29*1/$C$28,L106)) | M107: =IF(M104=0,0,IF($C$29*1/$C$28>M106,$C$29*1/$C$28,M106))
A108: Charge d'amortissement | B108: USD | L108: =L105*L107 | M108: =M105*M107
A109: Amortissement restant | B109: USD | L109: =L105-L108 | M109: =M105-M108
A111: Immobilisations de l'année A11
A112: Durée restante | B112: Années | M112: =IF($C$28<M$3,$C$28,M$3)
A113: Base amortissable | B113: USD | M113: =Modèle!M$10
A114: Inverse de la durée restante | B114: % | M114: =IF(M112=0,0,1/M112)
A115: Taux dégressif | B115: % | M115: =IF(M112=0,0,IF($C$29*1/$C$28>M114,$C$29*1/$C$28,M114))
A116: Charge d'amortissement | B116: USD | M116: =M113*M115
A117: Amortissement restant | B117: USD | M117: =M113-M116
...

Sheet 05_05_Charges_f_1
A1: Nom | B1: Unité | C1: Année 1 | D1: Année 2 | E1: Année 3 | F1: Année 4 | G1: Année 5 | H1: Année 6 | I1: Année 7 | J1: Année 8 | K1: Année 9 | L1: Année 10 | M1: Année 11 | N1: SOMME | O1: VAN
A3: I. PRODUCTION
A4: Production d'or | B4: oz | E4: 250000 | F4: 250000 | G4: 250000 | H4: 250000 | I4: 250000 | J4: 250000 | K4: 250000 | L4: 250000 | N4: =SUM($C4:$M4)
A5: Cours de l'or | B5: USD/oz | E5: 1300 | F5: 1300 | G5: 1300 | H5: 1300 | I5: 1300 | J5: 1300 | K5: 1300 | L5: 1300
A6: Chiffre d'affaires | B6: USD | C6: =C$4*C$5 | D6: =D$4*D$5 | E6: =E$4*E$5 | F6: =F$4*F$5 | G6: =G$4*G$5 | H6: =H$4*H$5 | I6: =I$4*I$5 | J6: =J$4*J$5 | ... M6: =M$4*M$5 | N6: =SUM($C6:$M6) | O6: =$C6+NPV(10%,$D6:$M6)
A8: II. DEPENSES D'INVESTISSEMENT (CAPEX)
A9: Coûts des construction industrielles | B9: USD | C9: 50000000 | D9: 100000000 | N9: =SUM($C9:$M9) | O9: =$C9+NPV(10%,$D9:$M9)
A10: Coûts des biens d'équipement | B10: USD | D10: 50000000 | E10: 5000000 | F10: 5000000 | G10: 5000000 | H10: 5000000 | I10: 5000000 | J10: 5000000 | K10: 5000000 | L10: 5000000 | N10: =SUM($C10:$M10) | O10: =$C10+NPV(10%,$D10:$M10)
A11: Coûts de réhabilitation du site | B11: USD | M11: 10000000 | N11: =SUM($C11:$M11) | O11: =$C11+NPV(10%,$D11:$M11)
A12: Total des dépenses d'investissement | B12: USD | C12: =SUM(C$9:C$11) | D12: =SUM(D$9:D$11) | E12: =SUM(E$9:E$11) | F12: =SUM(F$9:F$11) | G12: =SUM(G$9:G$11) | H12: =SUM(H$9:H$11) | I12: =SUM(I$9:I$11) | J12: =SUM(J$9:J$11) | ... M12: =SUM(M$9:M$11) | N12: =SUM($C12:$M12) | O12: =$C12+NPV(10%,$D12:$M12)
A14: III. COÛTS D'EXPLOITATION (OPEX)
A15: Coût moyen d'exploitation | B15: USD/oz | E15: 700 | F15: 700 | G15: 700 | H15: 700 | I15: 700 | J15: 700 | K15: 700 | L15: 700
A16: Total des coûts d'exploitation | B16: USD | C16: =C$4*C$15 | D16: =D$4*D$15 | E16: =E$4*E$15 | F16: =F$4*F$15 | G16: =G$4*G$15 | H16: =H$4*H$15 | I16: =I$4*I$15 | J16: =J$4*J$15 | ... M16: =M$4*M$15 | N16: =SUM($C16:$M16) | O16: =$C16+NPV(10%,$D16:$M16)
A18: IV. FLUX NETS DE TRESORERIE AVANT IMPÔTS
A19: Flux nets de trésorerie avant impôts | B19: USD | C19: =C$6-C$12-C$16 | D19: =D$6-D$12-D$16 | E19: =E$6-E$12-E$16 | F19: =F$6-F$12-F$16 | G19: =G$6-G$12-G$16 | H19: =H$6-H$12-H$16 | I19: =I$6-I$12-I$16 | J19: =J$6-J$12-J$16 | ... M19: =M$6-M$12-M$16 | N19: =SUM($C19:$M19) | O19: =$C19+NPV(10%,$D19:$M19)
A20: Taux de rendement interne avant impôts | B20: % | C20: =IF(ISNUMBER(IRR($C19:C19)),IF(IRR($C19:C19)>0,IRR($C19:C19),""),"") | D20: =IF(ISNUMBER(IRR($C19:D19)),IF(IRR($C19:D19)>0,IRR($C19:D19),""),"") | E20: =IF(ISNUMBER(IRR($C19:E19)),IF(IRR($C19:E19)>0,IRR($C19:E19),""),"") | F20: =IF(ISNUMBER(IRR($C19:F19)),IF(IRR($C19:F19)>0,IRR($C19:F19),""),"") | G20: =IF(ISNUMBER(IRR($C19:G19)),IF(IRR($C19:G19)>0,IRR($C19:G19),""),"") | H20: =IF(ISNUMBER(IRR($C19:H19)),IF(IRR($C19:H19)>0,IRR($C19:H19),""),"") | I20: =IF(ISNUMBER(IRR($C19:I19)),IF(IRR($C19:I19)>0,IRR($C19:I19),""),"") | J20: =IF(ISNUMBER(IRR($C19:J19)),IF(IRR($C19:J19)>0,IRR($C19:J19),""),"") | ... M20: =IF(ISNUMBER(IRR($C19:M19)),IF(IRR($C19:M19)>0,IRR($C19:M19),""),"")
A22: V. DROITS FIXES
A23: Droits fixes | B23: USD | C23: 100000 | N23: =SUM($C23:$M23) | O23: =$C23+NPV(10%,$D23:$M23)
A25: VI. REDEVANCE SUPERFICAIRE
A26: Superficie de la mine | B26: km² | C26: 100 | D26: 100 | E26: 100 | F26: 100 | G26: 100 | H26: 100 | I26: 100 | J26: 100 | K26: 100 | L26: 100 | M26: 100
A27: Montant de la redevance superfiaire | B27: USD/km² | C27: 100 | D27: 100 | E27: 100 | F27: 100 | G27: 100 | H27: 100 | I27: 100 | J27: 100 | K27: 100 | L27: 100 | M27: 100
A28: Redevance superficiaire | B28: USD | C28: =C$26*C$27 | D28: =D$26*D$27 | E28: =E$26*E$27 | F28: =F$26*F$27 | G28: =G$26*G$27 | H28: =H$26*H$27 | I28: =I$26*I$27 | J28: =J$26*J$27 | ... M28: =M$26*M$27 | N28: =SUM($C28:$M28) | O28: =$C28+NPV(10%,$D28:$M28)
A30: VII. REDEVANCE MINIERE
A31: Taux de la redevance minière | B31: % | C31: =IF(ISNUMBER(C5),IF(C$5<1300,3%,IF(C$5<1500,4%,5%)),"") | D31: =IF(ISNUMBER(D5),IF(D$5<1300,3%,IF(D$5<1500,4%,5%)),"") | E31: =IF(ISNUMBER(E5),IF(E$5<1300,3%,IF(E$5<1500,4%,5%)),"") | F31: =IF(ISNUMBER(F5),IF(F$5<1300,3%,IF(F$5<1500,4%,5%)),"") | G31: =IF(ISNUMBER(G5),IF(G$5<1300,3%,IF(G$5<1500,4%,5%)),"") | H31: =IF(ISNUMBER(H5),IF(H$5<1300,3%,IF(H$5<1500,4%,5%)),"") | I31: =IF(ISNUMBER(I5),IF(I$5<1300,3%,IF(I$5<1500,4%,5%)),"") | J31: =IF(ISNUMBER(J5),IF(J$5<1300,3%,IF(J$5<1500,4%,5%)),"") | ... M31: =IF(ISNUMBER(M5),IF(M$5<1300,3%,IF(M$5<1500,4%,5%)),"")
A32: Redevance minière | B32: USD | C32: =IF(ISNUMBER(C31),C$6*C$31,0) | D32: =IF(ISNUMBER(D31),D$6*D$31,0) | E32: =IF(ISNUMBER(E31),E$6*E$31,0) | F32: =IF(ISNUMBER(F31),F$6*F$31,0) | G32: =IF(ISNUMBER(G31),G$6*G$31,0) | H32: =IF(ISNUMBER(H31),H$6*H$31,0) | I32: =IF(ISNUMBER(I31),I$6*I$31,0) | J32: =IF(ISNUMBER(J31),J$6*J$31,0) | ... M32: =IF(ISNUMBER(M31),M$6*M$31,0) | N32: =SUM($C32:$M32) | O32: =$C32+NPV(10%,$D32:$M32)

Sheet 05_05_Charges_f_2
A1: Nom | B1: Unité | C1: Année 1 | D1: Année 2 | E1: Année 3 | F1: Année 4 | G1: Année 5 | H1: Année 6 | I1: Année 7 | J1: Année 8 | K1: Année 9 | L1: Année 10 | M1: Année 11
A3: Durée restante maximum | B3: Années | C3: 11 | D3: 10 | E3: 9 | F3: 8 | G3: 7 | H3: 6 | I3: 5 | J3: 4 | K3: 3 | L3: 2 | M3: 1
A5: I. AMORTISSEMENTS DES CONSTRUCTIONS INDUSTRIELLES
A6: Durée d'amortissement linéaire | B6: Années | C6: 10
A7: Coefficient d'amortissement dégressif | B7: Coefficient | C7: 1
A9: Immobilisations de l'année A1
A10: Durée restante | B10: Années | C10: =IF($C$6<C$3,$C$6,C$3) | D10: =IF(C10=0,0,IF(C10-1<D$3,C10-1,D$3)) | E10: =IF(D10=0,0,IF(D10-1<E$3,D10-1,E$3)) | F10: =IF(E10=0,0,IF(E10-1<F$3,E10-1,F$3)) | G10: =IF(F10=0,0,IF(F10-1<G$3,F10-1,G$3)) | H10: =IF(G10=0,0,IF(G10-1<H$3,G10-1,H$3)) | I10: =IF(H10=0,0,IF(H10-1<I$3,H10-1,I$3)) | J10: =IF(I10=0,0,IF(I10-1<J$3,I10-1,J$3)) | K10: =IF(J10=0,0,IF(J10-1<K$3,J10-1,K$3)) | ... M10: =IF(L10=0,0,IF(L10-1<M$3,L10-1,M$3))
A11: Base amortissable | B11: USD | C11: =Modèle!C$9 | D11: =C15 | E11: =D15 | F11: =E15 | G11: =F15 | H11: =G15 | I11: =H15 | J11: =I15 | K11: =J15 | ... M11: =L15
A12: Inverse de la durée restante | B12: % | C12: =IF(C10=0,0,1/C10) | D12: =IF(D10=0,0,1/D10) | E12: =IF(E10=0,0,1/E10) | F12: =IF(F10=0,0,1/F10) | G12: =IF(G10=0,0,1/G10) | H12: =IF(H10=0,0,1/H10) | I12: =IF(I10=0,0,1/I10) | J12: =IF(J10=0,0,1/J10) | ... M12: =IF(M10=0,0,1/M10)
A13: Taux dégressif | B13: % | C13: =IF(C10=0,0,IF($C$7*1/$C$6>C12,$C$7*1/$C$6,C12)) | D13: =IF(D10=0,0,IF($C$7*1/$C$6>D12,$C$7*1/$C$6,D12)) | E13: =IF(E10=0,0,IF($C$7*1/$C$6>E12,$C$7*1/$C$6,E12)) | F13: =IF(F10=0,0,IF($C$7*1/$C$6>F12,$C$7*1/$C$6,F12)) | G13: =IF(G10=0,0,IF($C$7*1/$C$6>G12,$C$7*1/$C$6,G12)) | H13: =IF(H10=0,0,IF($C$7*1/$C$6>H12,$C$7*1/$C$6,H12)) | I13: =IF(I10=0,0,IF($C$7*1/$C$6>I12,$C$7*1/$C$6,I12)) | J13: =IF(J10=0,0,IF($C$7*1/$C$6>J12,$C$7*1/$C$6,J12)) | ... M13: =IF(M10=0,0,IF($C$7*1/$C$6>M12,$C$7*1/$C$6,M12))
A14: Charge d'amortissement | B14: USD | C14: =C11*C13 | D14: =D11*D13 | E14: =E11*E13 | F14: =F11*F13 | G14: =G11*G13 | H14: =H11*H13 | I14: =I11*I13 | J14: =J11*J13 | ... M14: =M11*M13
A15: Amortissement restant | B15: USD | C15: =C11-C14 | D15: =D11-D14 | E15: =E11-E14 | F15: =F11-F14 | G15: =G11-G14 | H15: =H11-H14 | I15: =I11-I14 | J15: =J11-J14 | ... M15: =M11-M14
A17: Immobilisations de l'année A2
A18: Durée restante | B18: Années | D18: =IF($C$6<D$3,$C$6,D$3) | E18: =IF(D18=0,0,IF(D18-1<E$3,D18-1,E$3)) | F18: =IF(E18=0,0,IF(E18-1<F$3,E18-1,F$3)) | G18: =IF(F18=0,0,IF(F18-1<G$3,F18-1,G$3)) | H18: =IF(G18=0,0,IF(G18-1<H$3,G18-1,H$3)) | I18: =IF(H18=0,0,IF(H18-1<I$3,H18-1,I$3)) | J18: =IF(I18=0,0,IF(I18-1<J$3,I18-1,J$3)) | K18: =IF(J18=0,0,IF(J18-1<K$3,J18-1,K$3)) | L18: =IF(K18=0,0,IF(K18-1<L$3,K18-1,L$3)) | M18: =IF(L18=0,0,IF(L18-1<M$3,L18-1,M$3))
A19: Base amortissable | B19: USD | D19: =Modèle!D$9 | E19: =D23 | F19: =E23 | G19: =F23 | H19: =G23 | I19: =H23 | J19: =I23 | K19: =J23 | L19: =K23 | M19: =L23
A20: Inverse de la durée restante | B20: % | D20: =IF(D18=0,0,1/D18) | E20: =IF(E18=0,0,1/E18) | F20: =IF(F18=0,0,1/F18) | G20: =IF(G18=0,0,1/G18) | H20: =IF(H18=0,0,1/H18) | I20: =IF(I18=0,0,1/I18) | J20: =IF(J18=0,0,1/J18) | K20: =IF(K18=0,0,1/K18) | ... M20: =IF(M18=0,0,1/M18)
A21: Taux dégressif | B21: % | D21: =IF(D18=0,0,IF($C$7*1/$C$6>D20,$C$7*1/$C$6,D20)) | E21: =IF(E18=0,0,IF($C$7*1/$C$6>E20,$C$7*1/$C$6,E20)) | F21: =IF(F18=0,0,IF($C$7*1/$C$6>F20,$C$7*1/$C$6,F20)) | G21: =IF(G18=0,0,IF($C$7*1/$C$6>G20,$C$7*1/$C$6,G20)) | H21: =IF(H18=0,0,IF($C$7*1/$C$6>H20,$C$7*1/$C$6,H20)) | I21: =IF(I18=0,0,IF($C$7*1/$C$6>I20,$C$7*1/$C$6,I20)) | J21: =IF(J18=0,0,IF($C$7*1/$C$6>J20,$C$7*1/$C$6,J20)) | K21: =IF(K18=0,0,IF($C$7*1/$C$6>K20,$C$7*1/$C$6,K20)) | ... M21: =IF(M18=0,0,IF($C$7*1/$C$6>M20,$C$7*1/$C$6,M20))
A22: Charge d'amortissement | B22: USD | D22: =D19*D21 | E22: =E19*E21 | F22: =F19*F21 | G22: =G19*G21 | H22: =H19*H21 | I22: =I19*I21 | J22: =J19*J21 | K22: =K19*K21 | ... M22: =M19*M21
A23: Amortissement restant | B23: USD | D23: =D19-D22 | E23: =E19-E22 | F23: =F19-F22 | G23: =G19-G22 | H23: =H19-H22 | I23: =I19-I22 | J23: =J19-J22 | K23: =K19-K22 | ... M23: =M19-M22
A25: Amortissements des constructions industrielles | B25: USD | C25: =C$14+C$22 | D25: =D$14+D$22 | E25: =E$14+E$22 | F25: =F$14+F$22 | G25: =G$14+G$22 | H25: =H$14+H$22 | I25: =I$14+I$22 | J25: =J$14+J$22 | ... M25: =M$14+M$22
A27: II. AMORTISSEMENTS DES BIENS D'EQUIPEMENT
A28: Durée d'amortissement linéaire | B28: Années | C28: 5
A29: Coefficient d'amortissement dégressif | B29: Coefficient | C29: 2
A31: Immobilisations de l'année A1
A32: Durée restante | B32: Années | C32: =IF($C$28<C$3,$C$28,C$3) | D32: =IF(C32=0,0,IF(C32-1<D$3,C32-1,D$3)) | E32: =IF(D32=0,0,IF(D32-1<E$3,D32-1,E$3)) | F32: =IF(E32=0,0,IF(E32-1<F$3,E32-1,F$3)) | G32: =IF(F32=0,0,IF(F32-1<G$3,F32-1,G$3)) | H32: =IF(G32=0,0,IF(G32-1<H$3,G32-1,H$3)) | I32: =IF(H32=0,0,IF(H32-1<I$3,H32-1,I$3)) | J32: =IF(I32=0,0,IF(I32-1<J$3,I32-1,J$3)) | K32: =IF(J32=0,0,IF(J32-1<K$3,J32-1,K$3)) | ... M32: =IF(L32=0,0,IF(L32-1<M$3,L32-1,M$3))
A33: Base amortissable | B33: USD | C33: =Modèle!C$10 | D33: =C37 | E33: =D37 | F33: =E37 | G33: =F37 | H33: =G37 | I33: =H37 | J33: =I37 | K33: =J37 | ... M33: =L37
A34: Inverse de la durée restante | B34: % | C34: =IF(C32=0,0,1/C32) | D34: =IF(D32=0,0,1/D32) | E34: =IF(E32=0,0,1/E32) | F34: =IF(F32=0,0,1/F32) | G34: =IF(G32=0,0,1/G32) | H34: =IF(H32=0,0,1/H32) | I34: =IF(I32=0,0,1/I32) | J34: =IF(J32=0,0,1/J32) | ... M34: =IF(M32=0,0,1/M32)
A35: Taux dégressif | B35: % | C35: =IF(C32=0,0,IF($C$29*1/$C$28>C34,$C$29*1/$C$28,C34)) | D35: =IF(D32=0,0,IF($C$29*1/$C$28>D34,$C$29*1/$C$28,D34)) | E35: =IF(E32=0,0,IF($C$29*1/$C$28>E34,$C$29*1/$C$28,E34)) | F35: =IF(F32=0,0,IF($C$29*1/$C$28>F34,$C$29*1/$C$28,F34)) | G35: =IF(G32=0,0,IF($C$29*1/$C$28>G34,$C$29*1/$C$28,G34)) | H35: =IF(H32=0,0,IF($C$29*1/$C$28>H34,$C$29*1/$C$28,H34)) | I35: =IF(I32=0,0,IF($C$29*1/$C$28>I34,$C$29*1/$C$28,I34)) | J35: =IF(J32=0,0,IF($C$29*1/$C$28>J34,$C$29*1/$C$28,J34)) | ... M35: =IF(M32=0,0,IF($C$29*1/$C$28>M34,$C$29*1/$C$28,M34))
A36: Charge d'amortissement | B36: USD | C36: =C33*C35 | D36: =D33*D35 | E36: =E33*E35 | F36: =F33*F35 | G36: =G33*G35 | H36: =H33*H35 | I36: =I33*I35 | J36: =J33*J35 | ... M36: =M33*M35
A37: Amortissement restant | B37: USD | C37: =C33-C36 | D37: =D33-D36 | E37: =E33-E36 | F37: =F33-F36 | G37: =G33-G36 | H37: =H33-H36 | I37: =I33-I36 | J37: =J33-J36 | ... M37: =M33-M36
A39: Immobilisations de l'année A2
A40: Durée restante | B40: Années | D40: =IF($C$28<D$3,$C$28,D$3) | E40: =IF(D40=0,0,IF(D40-1<E$3,D40-1,E$3)) | F40: =IF(E40=0,0,IF(E40-1<F$3,E40-1,F$3)) | G40: =IF(F40=0,0,IF(F40-1<G$3,F40-1,G$3)) | H40: =IF(G40=0,0,IF(G40-1<H$3,G40-1,H$3)) | I40: =IF(H40=0,0,IF(H40-1<I$3,H40-1,I$3)) | J40: =IF(I40=0,0,IF(I40-1<J$3,I40-1,J$3)) | K40: =IF(J40=0,0,IF(J40-1<K$3,J40-1,K$3)) | L40: =IF(K40=0,0,IF(K40-1<L$3,K40-1,L$3)) | M40: =IF(L40=0,0,IF(L40-1<M$3,L40-1,M$3))
A41: Base amortissable | B41: USD | D41: =Modèle!D$10 | E41: =D45 | F41: =E45 | G41: =F45 | H41: =G45 | I41: =H45 | J41: =I45 | K41: =J45 | L41: =K45 | M41: =L45
A42: Inverse de la durée restante | B42: % | D42: =IF(D40=0,0,1/D40) | E42: =IF(E40=0,0,1/E40) | F42: =IF(F40=0,0,1/F40) | G42: =IF(G40=0,0,1/G40) | H42: =IF(H40=0,0,1/H40) | I42: =IF(I40=0,0,1/I40) | J42: =IF(J40=0,0,1/J40) | K42: =IF(K40=0,0,1/K40) | ... M42: =IF(M40=0,0,1/M40)
A43: Taux dégressif | B43: % | D43: =IF(D40=0,0,IF($C$29*1/$C$28>D42,$C$29*1/$C$28,D42)) | E43: =IF(E40=0,0,IF($C$29*1/$C$28>E42,$C$29*1/$C$28,E42)) | F43: =IF(F40=0,0,IF($C$29*1/$C$28>F42,$C$29*1/$C$28,F42)) | G43: =IF(G40=0,0,IF($C$29*1/$C$28>G42,$C$29*1/$C$28,G42)) | H43: =IF(H40=0,0,IF($C$29*1/$C$28>H42,$C$29*1/$C$28,H42)) | I43: =IF(I40=0,0,IF($C$29*1/$C$28>I42,$C$29*1/$C$28,I42)) | J43: =IF(J40=0,0,IF($C$29*1/$C$28>J42,$C$29*1/$C$28,J42)) | K43: =IF(K40=0,0,IF($C$29*1/$C$28>K42,$C$29*1/$C$28,K42)) | ... M43: =IF(M40=0,0,IF($C$29*1/$C$28>M42,$C$29*1/$C$28,M42))
A44: Charge d'amortissement | B44: USD | D44: =D41*D43 | E44: =E41*E43 | F44: =F41*F43 | G44: =G41*G43 | H44: =H41*H43 | I44: =I41*I43 | J44: =J41*J43 | K44: =K41*K43 | ... M44: =M41*M43
A45: Amortissement restant | B45: USD | D45: =D41-D44 | E45: =E41-E44 | F45: =F41-F44 | G45: =G41-G44 | H45: =H41-H44 | I45: =I41-I44 | J45: =J41-J44 | K45: =K41-K44 | ... M45: =M41-M44
A47: Immobilisations de l'année A3
A48: Durée restante | B48: Années | E48: =IF($C$28<E$3,$C$28,E$3) | F48: =IF(E48=0,0,IF(E48-1<F$3,E48-1,F$3)) | G48: =IF(F48=0,0,IF(F48-1<G$3,F48-1,G$3)) | H48: =IF(G48=0,0,IF(G48-1<H$3,G48-1,H$3)) | I48: =IF(H48=0,0,IF(H48-1<I$3,H48-1,I$3)) | J48: =IF(I48=0,0,IF(I48-1<J$3,I48-1,J$3)) | K48: =IF(J48=0,0,IF(J48-1<K$3,J48-1,K$3)) | L48: =IF(K48=0,0,IF(K48-1<L$3,K48-1,L$3)) | M48: =IF(L48=0,0,IF(L48-1<M$3,L48-1,M$3))
A49: Base amortissable | B49: USD | E49: =Modèle!E$10 | F49: =E53 | G49: =F53 | H49: =G53 | I49: =H53 | J49: =I53 | K49: =J53 | L49: =K53 | M49: =L53
A50: Inverse de la durée restante | B50: % | E50: =IF(E48=0,0,1/E48) | F50: =IF(F48=0,0,1/F48) | G50: =IF(G48=0,0,1/G48) | H50: =IF(H48=0,0,1/H48) | I50: =IF(I48=0,0,1/I48) | J50: =IF(J48=0,0,1/J48) | K50: =IF(K48=0,0,1/K48) | L50: =IF(L48=0,0,1/L48) | M50: =IF(M48=0,0,1/M48)
A51: Taux dégressif | B51: % | E51: =IF(E48=0,0,IF($C$29*1/$C$28>E50,$C$29*1/$C$28,E50)) | F51: =IF(F48=0,0,IF($C$29*1/$C$28>F50,$C$29*1/$C$28,F50)) | G51: =IF(G48=0,0,IF($C$29*1/$C$28>G50,$C$29*1/$C$28,G50)) | H51: =IF(H48=0,0,IF($C$29*1/$C$28>H50,$C$29*1/$C$28,H50)) | I51: =IF(I48=0,0,IF($C$29*1/$C$28>I50,$C$29*1/$C$28,I50)) | J51: =IF(J48=0,0,IF($C$29*1/$C$28>J50,$C$29*1/$C$28,J50)) | K51: =IF(K48=0,0,IF($C$29*1/$C$28>K50,$C$29*1/$C$28,K50)) | L51: =IF(L48=0,0,IF($C$29*1/$C$28>L50,$C$29*1/$C$28,L50)) | M51: =IF(M48=0,0,IF($C$29*1/$C$28>M50,$C$29*1/$C$28,M50))
A52: Charge d'amortissement | B52: USD | E52: =E49*E51 | F52: =F49*F51 | G52: =G49*G51 | H52: =H49*H51 | I52: =I49*I51 | J52: =J49*J51 | K52: =K49*K51 | L52: =L49*L51 | M52: =M49*M51
A53: Amortissement restant | B53: USD | E53: =E49-E52 | F53: =F49-F52 | G53: =G49-G52 | H53: =H49-H52 | I53: =I49-I52 | J53: =J49-J52 | K53: =K49-K52 | L53: =L49-L52 | M53: =M49-M52
A55: Immobilisations de l'année A4
A56: Durée restante | B56: Années | F56: =IF($C$28<F$3,$C$28,F$3) | G56: =IF(F56=0,0,IF(F56-1<G$3,F56-1,G$3)) | H56: =IF(G56=0,0,IF(G56-1<H$3,G56-1,H$3)) | I56: =IF(H56=0,0,IF(H56-1<I$3,H56-1,I$3)) | J56: =IF(I56=0,0,IF(I56-1<J$3,I56-1,J$3)) | K56: =IF(J56=0,0,IF(J56-1<K$3,J56-1,K$3)) | L56: =IF(K56=0,0,IF(K56-1<L$3,K56-1,L$3)) | M56: =IF(L56=0,0,IF(L56-1<M$3,L56-1,M$3))
A57: Base amortissable | B57: USD | F57: =Modèle!F$10 | G57: =F61 | H57: =G61 | I57: =H61 | J57: =I61 | K57: =J61 | L57: =K61 | M57: =L61
A58: Inverse de la durée restante | B58: % | F58: =IF(F56=0,0,1/F56) | G58: =IF(G56=0,0,1/G56) | H58: =IF(H56=0,0,1/H56) | I58: =IF(I56=0,0,1/I56) | J58: =IF(J56=0,0,1/J56) | K58: =IF(K56=0,0,1/K56) | L58: =IF(L56=0,0,1/L56) | M58: =IF(M56=0,0,1/M56)
A59: Taux dégressif | B59: % | F59: =IF(F56=0,0,IF($C$29*1/$C$28>F58,$C$29*1/$C$28,F58)) | G59: =IF(G56=0,0,IF($C$29*1/$C$28>G58,$C$29*1/$C$28,G58)) | H59: =IF(H56=0,0,IF($C$29*1/$C$28>H58,$C$29*1/$C$28,H58)) | I59: =IF(I56=0,0,IF($C$29*1/$C$28>I58,$C$29*1/$C$28,I58)) | J59: =IF(J56=0,0,IF($C$29*1/$C$28>J58,$C$29*1/$C$28,J58)) | K59: =IF(K56=0,0,IF($C$29*1/$C$28>K58,$C$29*1/$C$28,K58)) | L59: =IF(L56=0,0,IF($C$29*1/$C$28>L58,$C$29*1/$C$28,L58)) | M59: =IF(M56=0,0,IF($C$29*1/$C$28>M58,$C$29*1/$C$28,M58))
A60: Charge d'amortissement | B60: USD | F60: =F57*F59 | G60: =G57*G59 | H60: =H57*H59 | I60: =I57*I59 | J60: =J57*J59 | K60: =K57*K59 | L60: =L57*L59 | M60: =M57*M59
A61: Amortissement restant | B61: USD | F61: =F57-F60 | G61: =G57-G60 | H61: =H57-H60 | I61: =I57-I60 | J61: =J57-J60 | K61: =K57-K60 | L61: =L57-L60 | M61: =M57-M60
A63: Immobilisations de l'année A5
A64: Durée restante | B64: Années | G64: =IF($C$28<G$3,$C$28,G$3) | H64: =IF(G64=0,0,IF(G64-1<H$3,G64-1,H$3)) | I64: =IF(H64=0,0,IF(H64-1<I$3,H64-1,I$3)) | J64: =IF(I64=0,0,IF(I64-1<J$3,I64-1,J$3)) | K64: =IF(J64=0,0,IF(J64-1<K$3,J64-1,K$3)) | L64: =IF(K64=0,0,IF(K64-1<L$3,K64-1,L$3)) | M64: =IF(L64=0,0,IF(L64-1<M$3,L64-1,M$3))
A65: Base amortissable | B65: USD | G65: =Modèle!G$10 | H65: =G69 | I65: =H69 | J65: =I69 | K65: =J69 | L65: =K69 | M65: =L69
A66: Inverse de la durée restante | B66: % | G66: =IF(G64=0,0,1/G64) | H66: =IF(H64=0,0,1/H64) | I66: =IF(I64=0,0,1/I64) | J66: =IF(J64=0,0,1/J64) | K66: =IF(K64=0,0,1/K64) | L66: =IF(L64=0,0,1/L64) | M66: =IF(M64=0,0,1/M64)
A67: Taux dégressif | B67: % | G67: =IF(G64=0,0,IF($C$29*1/$C$28>G66,$C$29*1/$C$28,G66)) | H67: =IF(H64=0,0,IF($C$29*1/$C$28>H66,$C$29*1/$C$28,H66)) | I67: =IF(I64=0,0,IF($C$29*1/$C$28>I66,$C$29*1/$C$28,I66)) | J67: =IF(J64=0,0,IF($C$29*1/$C$28>J66,$C$29*1/$C$28,J66)) | K67: =IF(K64=0,0,IF($C$29*1/$C$28>K66,$C$29*1/$C$28,K66)) | L67: =IF(L64=0,0,IF($C$29*1/$C$28>L66,$C$29*1/$C$28,L66)) | M67: =IF(M64=0,0,IF($C$29*1/$C$28>M66,$C$29*1/$C$28,M66))
A68: Charge d'amortissement | B68: USD | G68: =G65*G67 | H68: =H65*H67 | I68: =I65*I67 | J68: =J65*J67 | K68: =K65*K67 | L68: =L65*L67 | M68: =M65*M67
A69: Amortissement restant | B69: USD | G69: =G65-G68 | H69: =H65-H68 | I69: =I65-I68 | J69: =J65-J68 | K69: =K65-K68 | L69: =L65-L68 | M69: =M65-M68
A71: Immobilisations de l'année A6
A72: Durée restante | B72: Années | H72: =IF($C$28<H$3,$C$28,H$3) | I72: =IF(H72=0,0,IF(H72-1<I$3,H72-1,I$3)) | J72: =IF(I72=0,0,IF(I72-1<J$3,I72-1,J$3)) | K72: =IF(J72=0,0,IF(J72-1<K$3,J72-1,K$3)) | L72: =IF(K72=0,0,IF(K72-1<L$3,K72-1,L$3)) | M72: =IF(L72=0,0,IF(L72-1<M$3,L72-1,M$3))
A73: Base amortissable | B73: USD | H73: =Modèle!H$10 | I73: =H77 | J73: =I77 | K73: =J77 | L73: =K77 | M73: =L77
A74: Inverse de la durée restante | B74: % | H74: =IF(H72=0,0,1/H72) | I74: =IF(I72=0,0,1/I72) | J74: =IF(J72=0,0,1/J72) | K74: =IF(K72=0,0,1/K72) | L74: =IF(L72=0,0,1/L72) | M74: =IF(M72=0,0,1/M72)
A75: Taux dégressif | B75: % | H75: =IF(H72=0,0,IF($C$29*1/$C$28>H74,$C$29*1/$C$28,H74)) | I75: =IF(I72=0,0,IF($C$29*1/$C$28>I74,$C$29*1/$C$28,I74)) | J75: =IF(J72=0,0,IF($C$29*1/$C$28>J74,$C$29*1/$C$28,J74)) | K75: =IF(K72=0,0,IF($C$29*1/$C$28>K74,$C$29*1/$C$28,K74)) | L75: =IF(L72=0,0,IF($C$29*1/$C$28>L74,$C$29*1/$C$28,L74)) | M75: =IF(M72=0,0,IF($C$29*1/$C$28>M74,$C$29*1/$C$28,M74))
A76: Charge d'amortissement | B76: USD | H76: =H73*H75 | I76: =I73*I75 | J76: =J73*J75 | K76: =K73*K75 | L76: =L73*L75 | M76: =M73*M75
A77: Amortissement restant | B77: USD | H77: =H73-H76 | I77: =I73-I76 | J77: =J73-J76 | K77: =K73-K76 | L77: =L73-L76 | M77: =M73-M76
A79: Immobilisations de l'année A7
A80: Durée restante | B80: Années | I80: =IF($C$28<I$3,$C$28,I$3) | J80: =IF(I80=0,0,IF(I80-1<J$3,I80-1,J$3)) | K80: =IF(J80=0,0,IF(J80-1<K$3,J80-1,K$3)) | L80: =IF(K80=0,0,IF(K80-1<L$3,K80-1,L$3)) | M80: =IF(L80=0,0,IF(L80-1<M$3,L80-1,M$3))
A81: Base amortissable | B81: USD | I81: =Modèle!I$10 | J81: =I85 | K81: =J85 | L81: =K85 | M81: =L85
A82: Inverse de la durée restante | B82: % | I82: =IF(I80=0,0,1/I80) | J82: =IF(J80=0,0,1/J80) | K82: =IF(K80=0,0,1/K80) | L82: =IF(L80=0,0,1/L80) | M82: =IF(M80=0,0,1/M80)
A83: Taux dégressif | B83: % | I83: =IF(I80=0,0,IF($C$29*1/$C$28>I82,$C$29*1/$C$28,I82)) | J83: =IF(J80=0,0,IF($C$29*1/$C$28>J82,$C$29*1/$C$28,J82)) | K83: =IF(K80=0,0,IF($C$29*1/$C$28>K82,$C$29*1/$C$28,K82)) | L83: =IF(L80=0,0,IF($C$29*1/$C$28>L82,$C$29*1/$C$28,L82)) | M83: =IF(M80=0,0,IF($C$29*1/$C$28>M82,$C$29*1/$C$28,M82))
A84: Charge d'amortissement | B84: USD | I84: =I81*I83 | J84: =J81*J83 | K84: =K81*K83 | L84: =L81*L83 | M84: =M81*M83
A85: Amortissement restant | B85: USD | I85: =I81-I84 | J85: =J81-J84 | K85: =K81-K84 | L85: =L81-L84 | M85: =M81-M84
A87: Immobilisations de l'année A8
A88: Durée restante | B88: Années | J88: =IF($C$28<J$3,$C$28,J$3) | K88: =IF(J88=0,0,IF(J88-1<K$3,J88-1,K$3)) | L88: =IF(K88=0,0,IF(K88-1<L$3,K88-1,L$3)) | M88: =IF(L88=0,0,IF(L88-1<M$3,L88-1,M$3))
A89: Base amortissable | B89: USD | J89: =Modèle!J$10 | K89: =J93 | L89: =K93 | M89: =L93
A90: Inverse de la durée restante | B90: % | J90: =IF(J88=0,0,1/J88) | K90: =IF(K88=0,0,1/K88) | L90: =IF(L88=0,0,1/L88) | M90: =IF(M88=0,0,1/M88)
A91: Taux dégressif | B91: % | J91: =IF(J88=0,0,IF($C$29*1/$C$28>J90,$C$29*1/$C$28,J90)) | K91: =IF(K88=0,0,IF($C$29*1/$C$28>K90,$C$29*1/$C$28,K90)) | L91: =IF(L88=0,0,IF($C$29*1/$C$28>L90,$C$29*1/$C$28,L90)) | M91: =IF(M88=0,0,IF($C$29*1/$C$28>M90,$C$29*1/$C$28,M90))
A92: Charge d'amortissement | B92: USD | J92: =J89*J91 | K92: =K89*K91 | L92: =L89*L91 | M92: =M89*M91
A93: Amortissement restant | B93: USD | J93: =J89-J92 | K93: =K89-K92 | L93: =L89-L92 | M93: =M89-M92
A95: Immobilisations de l'année A9
A96: Durée restante | B96: Années | K96: =IF($C$28<K$3,$C$28,K$3) | L96: =IF(K96=0,0,IF(K96-1<L$3,K96-1,L$3)) | M96: =IF(L96=0,0,IF(L96-1<M$3,L96-1,M$3))
A97: Base amortissable | B97: USD | K97: =Modèle!K$10 | L97: =K101 | M97: =L101
A98: Inverse de la durée restante | B98: % | K98: =IF(K96=0,0,1/K96) | L98: =IF(L96=0,0,1/L96) | M98: =IF(M96=0,0,1/M96)
A99: Taux dégressif | B99: % | K99: =IF(K96=0,0,IF($C$29*1/$C$28>K98,$C$29*1/$C$28,K98)) | L99: =IF(L96=0,0,IF($C$29*1/$C$28>L98,$C$29*1/$C$28,L98)) | M99: =IF(M96=0,0,IF($C$29*1/$C$28>M98,$C$29*1/$C$28,M98))
A100: Charge d'amortissement | B100: USD | K100: =K97*K99 | L100: =L97*L99 | M100: =M97*M99
A101: Amortissement restant | B101: USD | K101: =K97-K100 | L101: =L97-L100 | M101: =M97-M100
A103: Immobilisations de l'année A10
A104: Durée restante | B104: Années | L104: =IF($C$28<L$3,$C$28,L$3) | M104: =IF(L104=0,0,IF(L104-1<M$3,L104-1,M$3))
A105: Base amortissable | B105: USD | L105: =Modèle!L$10 | M105: =L109
A106: Inverse de la durée restante | B106: % | L106: =IF(L104=0,0,1/L104) | M106: =IF(M104=0,0,1/M104)
A107: Taux dégressif | B107: % | L107: =IF(L104=0,0,IF($C$29*1/$C$28>L106,$C$29*1/$C$28,L106)) | M107: =IF(M104=0,0,IF($C$29*1/$C$28>M106,$C$29*1/$C$28,M106))
A108: Charge d'amortissement | B108: USD | L108: =L105*L107 | M108: =M105*M107
A109: Amortissement restant | B109: USD | L109: =L105-L108 | M109: =M105-M108
A111: Immobilisations de l'année A11
A112: Durée restante | B112: Années | M112: =IF($C$28<M$3,$C$28,M$3)
A113: Base amortissable | B113: USD | M113: =Modèle!M$10
A114: Inverse de la durée restante | B114: % | M114: =IF(M112=0,0,1/M112)
A115: Taux dégressif | B115: % | M115: =IF(M112=0,0,IF($C$29*1/$C$28>M114,$C$29*1/$C$28,M114))
A116: Charge d'amortissement | B116: USD | M116: =M113*M115
A117: Amortissement restant | B117: USD | M117: =M113-M116
...

Sheet 06_06_IS_IMF_1
A1: Nom | B1: Unité | C1: Année 1 | D1: Année 2 | E1: Année 3 | F1: Année 4 | G1: Année 5 | H1: Année 6 | I1: Année 7 | J1: Année 8 | K1: Année 9 | L1: Année 10 | M1: Année 11 | N1: SOMME | O1: VAN
A3: I. PRODUCTION
A4: Production d'or | B4: oz | E4: 250000 | F4: 250000 | G4: 250000 | H4: 250000 | I4: 250000 | J4: 250000 | K4: 250000 | L4: 250000 | N4: =SUM($C4:$M4)
A5: Cours de l'or | B5: USD/oz | E5: 1300 | F5: 1300 | G5: 1300 | H5: 1300 | I5: 1300 | J5: 1300 | K5: 1300 | L5: 1300
A6: Chiffre d'affaires | B6: USD | C6: =C$4*C$5 | D6: =D$4*D$5 | E6: =E$4*E$5 | F6: =F$4*F$5 | G6: =G$4*G$5 | H6: =H$4*H$5 | I6: =I$4*I$5 | J6: =J$4*J$5 | ... M6: =M$4*M$5 | N6: =SUM($C6:$M6) | O6: =$C6+NPV(10%,$D6:$M6)
A8: II. DEPENSES D'INVESTISSEMENT (CAPEX)
A9: Coûts des construction industrielles | B9: USD | C9: 50000000 | D9: 100000000 | N9: =SUM($C9:$M9) | O9: =$C9+NPV(10%,$D9:$M9)
A10: Coûts des biens d'équipement | B10: USD | D10: 50000000 | E10: 5000000 | F10: 5000000 | G10: 5000000 | H10: 5000000 | I10: 5000000 | J10: 5000000 | K10: 5000000 | L10: 5000000 | N10: =SUM($C10:$M10) | O10: =$C10+NPV(10%,$D10:$M10)
A11: Coûts de réhabilitation du site | B11: USD | M11: 10000000 | N11: =SUM($C11:$M11) | O11: =$C11+NPV(10%,$D11:$M11)
A12: Total des dépenses d'investissement | B12: USD | C12: =SUM(C$9:C$11) | D12: =SUM(D$9:D$11) | E12: =SUM(E$9:E$11) | F12: =SUM(F$9:F$11) | G12: =SUM(G$9:G$11) | H12: =SUM(H$9:H$11) | I12: =SUM(I$9:I$11) | J12: =SUM(J$9:J$11) | ... M12: =SUM(M$9:M$11) | N12: =SUM($C12:$M12) | O12: =$C12+NPV(10%,$D12:$M12)
A14: III. COÛTS D'EXPLOITATION (OPEX)
A15: Coût moyen d'exploitation | B15: USD/oz | E15: 700 | F15: 700 | G15: 700 | H15: 700 | I15: 700 | J15: 700 | K15: 700 | L15: 700
A16: Total des coûts d'exploitation | B16: USD | C16: =C$4*C$15 | D16: =D$4*D$15 | E16: =E$4*E$15 | F16: =F$4*F$15 | G16: =G$4*G$15 | H16: =H$4*H$15 | I16: =I$4*I$15 | J16: =J$4*J$15 | ... M16: =M$4*M$15 | N16: =SUM($C16:$M16) | O16: =$C16+NPV(10%,$D16:$M16)
A18: IV. FLUX NETS DE TRESORERIE AVANT IMPÔTS
A19: Flux nets de trésorerie avant impôts | B19: USD | C19: =C$6-C$12-C$16 | D19: =D$6-D$12-D$16 | E19: =E$6-E$12-E$16 | F19: =F$6-F$12-F$16 | G19: =G$6-G$12-G$16 | H19: =H$6-H$12-H$16 | I19: =I$6-I$12-I$16 | J19: =J$6-J$12-J$16 | ... M19: =M$6-M$12-M$16 | N19: =SUM($C19:$M19) | O19: =$C19+NPV(10%,$D19:$M19)
A20: Taux de rendement interne avant impôts | B20: % | C20: =IF(ISNUMBER(IRR($C19:C19)),IF(IRR($C19:C19)>0,IRR($C19:C19),""),"") | D20: =IF(ISNUMBER(IRR($C19:D19)),IF(IRR($C19:D19)>0,IRR($C19:D19),""),"") | E20: =IF(ISNUMBER(IRR($C19:E19)),IF(IRR($C19:E19)>0,IRR($C19:E19),""),"") | F20: =IF(ISNUMBER(IRR($C19:F19)),IF(IRR($C19:F19)>0,IRR($C19:F19),""),"") | G20: =IF(ISNUMBER(IRR($C19:G19)),IF(IRR($C19:G19)>0,IRR($C19:G19),""),"") | H20: =IF(ISNUMBER(IRR($C19:H19)),IF(IRR($C19:H19)>0,IRR($C19:H19),""),"") | I20: =IF(ISNUMBER(IRR($C19:I19)),IF(IRR($C19:I19)>0,IRR($C19:I19),""),"") | J20: =IF(ISNUMBER(IRR($C19:J19)),IF(IRR($C19:J19)>0,IRR($C19:J19),""),"") | ... M20: =IF(ISNUMBER(IRR($C19:M19)),IF(IRR($C19:M19)>0,IRR($C19:M19),""),"")
A22: V. DROITS FIXES
A23: Droits fixes | B23: USD | C23: 100000 | N23: =SUM($C23:$M23) | O23: =$C23+NPV(10%,$D23:$M23)
A25: VI. REDEVANCE SUPERFICAIRE
A26: Superficie de la mine | B26: km² | C26: 100 | D26: 100 | E26: 100 | F26: 100 | G26: 100 | H26: 100 | I26: 100 | J26: 100 | K26: 100 | L26: 100 | M26: 100
A27: Montant de la redevance superfiaire | B27: USD/km² | C27: 100 | D27: 100 | E27: 100 | F27: 100 | G27: 100 | H27: 100 | I27: 100 | J27: 100 | K27: 100 | L27: 100 | M27: 100
A28: Redevance superficiaire | B28: USD | C28: =C$26*C$27 | D28: =D$26*D$27 | E28: =E$26*E$27 | F28: =F$26*F$27 | G28: =G$26*G$27 | H28: =H$26*H$27 | I28: =I$26*I$27 | J28: =J$26*J$27 | ... M28: =M$26*M$27 | N28: =SUM($C28:$M28) | O28: =$C28+NPV(10%,$D28:$M28)
A30: VII. REDEVANCE MINIERE
A31: Taux de la redevance minière | B31: % | C31: =IF(ISNUMBER(C5),IF(C$5<1300,3%,IF(C$5<1500,4%,5%)),"") | D31: =IF(ISNUMBER(D5),IF(D$5<1300,3%,IF(D$5<1500,4%,5%)),"") | E31: =IF(ISNUMBER(E5),IF(E$5<1300,3%,IF(E$5<1500,4%,5%)),"") | F31: =IF(ISNUMBER(F5),IF(F$5<1300,3%,IF(F$5<1500,4%,5%)),"") | G31: =IF(ISNUMBER(G5),IF(G$5<1300,3%,IF(G$5<1500,4%,5%)),"") | H31: =IF(ISNUMBER(H5),IF(H$5<1300,3%,IF(H$5<1500,4%,5%)),"") | I31: =IF(ISNUMBER(I5),IF(I$5<1300,3%,IF(I$5<1500,4%,5%)),"") | J31: =IF(ISNUMBER(J5),IF(J$5<1300,3%,IF(J$5<1500,4%,5%)),"") | ... M31: =IF(ISNUMBER(M5),IF(M$5<1300,3%,IF(M$5<1500,4%,5%)),"")
A32: Redevance minière | B32: USD | C32: =IF(ISNUMBER(C31),C$6*C$31,0) | D32: =IF(ISNUMBER(D31),D$6*D$31,0) | E32: =IF(ISNUMBER(E31),E$6*E$31,0) | F32: =IF(ISNUMBER(F31),F$6*F$31,0) | G32: =IF(ISNUMBER(G31),G$6*G$31,0) | H32: =IF(ISNUMBER(H31),H$6*H$31,0) | I32: =IF(ISNUMBER(I31),I$6*I$31,0) | J32: =IF(ISNUMBER(J31),J$6*J$31,0) | ... M32: =IF(ISNUMBER(M31),M$6*M$31,0) | N32: =SUM($C32:$M32) | O32: =$C32+NPV(10%,$D32:$M32)
A34: VIII. IMPÔT SUR LES SOCIETES (IS)
A35: Bénéfice avant report des pertes | B35: USD | C35: =C$6-C$16-C$23-C$28-C$32-'Amortissements et Emprunt'!C$25-'Amortissements et Emprunt'!C$119-'Amortissements et Emprunt'!C133-'Amortissements et Emprunt'!C$157 | D35: =D$6-D$16-D$23-D$28-D$32-'Amortissements et Emprunt'!D$25-'Amortissements et Emprunt'!D$119-'Amortissements et Emprunt'!D133-'Amortissements et Emprunt'!D$157 | E35: =E$6-E$16-E$23-E$28-E$32-'Amortissements et Emprunt'!E$25-'Amortissements et Emprunt'!E$119-'Amortissements et Emprunt'!E133-'Amortissements et Emprunt'!E$157 | F35: =F$6-F$16-F$23-F$28-F$32-'Amortissements et Emprunt'!F$25-'Amortissements et Emprunt'!F$119-'Amortissements et Emprunt'!F133-'Amortissements et Emprunt'!F$157 | G35: =G$6-G$16-G$23-G$28-G$32-'Amortissements et Emprunt'!G$25-'Amortissements et Emprunt'!G$119-'Amortissements et Emprunt'!G133-'Amortissements et Emprunt'!G$157 | H35: =H$6-H$16-H$23-H$28-H$32-'Amortissements et Emprunt'!H$25-'Amortissements et Emprunt'!H$119-'Amortissements et Emprunt'!H133-'Amortissements et Emprunt'!H$157 | I35: =I$6-I$16-I$23-I$28-I$32-'Amortissements et Emprunt'!I$25-'Amortissements et Emprunt'!I$119-'Amortissements et Emprunt'!I133-'Amortissements et Emprunt'!I$157 | J35: =J$6-J$16-J$23-J$28-J$32-'Amortissements et Emprunt'!J$25-'Amortissements et Emprunt'!J$119-'Amortissements et Emprunt'!J133-'Amortissements et Emprunt'!J$157 | ... M35: =M$6-M$16-M$23-M$28-M$32-'Amortissements et Emprunt'!M$25-'Amortissements et Emprunt'!M$119-'Amortissements et Emprunt'!M133-'Amortissements et Emprunt'!M$157 | N35: =SUM($C35:$M35) | O35: =$C35+NPV(10%,$D35:$M35)
A36: Report des pertes | B36: USD | D36: =IF(C37<0,C37,0) | E36: =IF(D37<0,D37,0) | F36: =IF(E37<0,E37,0) | G36: =IF(F37<0,F37,0) | H36: =IF(G37<0,G37,0) | I36: =IF(H37<0,H37,0) | J36: =IF(I37<0,I37,0) | K36: =IF(J37<0,J37,0) | ... M36: =IF(L37<0,L37,0)
A37: Bénéfice fiscal | B37: USD | C37: =C$35+C$36 | D37: =D$35+D$36 | E37: =E$35+E$36 | F37: =F$35+F$36 | G37: =G$35+G$36 | H37: =H$35+H$36 | I37: =I$35+I$36 | J37: =J$35+J$36 | ... M37: =M$35+M$36 | N37: =SUM($C37:$M37) | O37: =$C37+NPV(10%,$D37:$M37)
A38: Taux de l'impôt sur les sociétés | B38: % | C38: 0.3 | D38: 0.3 | E38: 0.3 | F38: 0.3 | G38: 0.3 | H38: 0.3 | I38: 0.3 | J38: 0.3 | K38: 0.3 | L38: 0.3 | M38: 0.3
A39: Impôt sur les sociétés | B39: USD | C39: =IF(C$37>0,C$37*C$38,0) | D39: =IF(D$37>0,D$37*D$38,0) | E39: =IF(E$37>0,E$37*E$38,0) | F39: =IF(F$37>0,F$37*F$38,0) | G39: =IF(G$37>0,G$37*G$38,0) | H39: =IF(H$37>0,H$37*H$38,0) | I39: =IF(I$37>0,I$37*I$38,0) | J39: =IF(J$37>0,J$37*J$38,0) | ... M39: =IF(M$37>0,M$37*M$38,0) | N39: =SUM($C39:$M39) | O39: =$C39+NPV(10%,$D39:$M39)
A41: IX. IMPÔT MINIMUM FORFAITAIRE (IMF)
A42: Montant minimum | B42: USD | C42: 2000 | D42: 2000 | E42: 2000 | F42: 2000 | G42: 2000 | H42: 2000 | I42: 2000 | J42: 2000 | K42: 2000 | L42: 2000 | M42: 2000
A43: Taux de l'impôt minimum forfaitaire | B43: % | C43: 0.01 | D43: 0.01 | E43: 0.01 | F43: 0.01 | G43: 0.01 | H43: 0.01 | I43: 0.01 | J43: 0.01 | K43: 0.01 | L43: 0.01 | M43: 0.01
A44: Impôt minimum forfaitaire | B44: USD | C44: =IF(C$6*C$43>C$42,C$6*C$43,C$42) | D44: =IF(D$6*D$43>D$42,D$6*D$43,D$42) | E44: =IF(E$6*E$43>E$42,E$6*E$43,E$42) | F44: =IF(F$6*F$43>F$42,F$6*F$43,F$42) | G44: =IF(G$6*G$43>G$42,G$6*G$43,G$42) | H44: =IF(H$6*H$43>H$42,H$6*H$43,H$42) | I44: =IF(I$6*I$43>I$42,I$6*I$43,I$42) | J44: =IF(J$6*J$43>J$42,J$6*J$43,J$42) | ... M44: =IF(M$6*M$43>M$42,M$6*M$43,M$42) | N44: =SUM($C44:$M44) | O44: =$C44+NPV(10%,$D44:$M44)
A46: X. IMPÔT SUR LES SOCIETES (IS) / IMPÔT MINIMUM FORFAITAIRE (IMF)
A47: Impôt sur les sociétés / Impôt minimum forfaitaire | B47: USD | C47: =IF(C$44>C$39,C$44,C$39) | D47: =IF(D$44>D$39,D$44,D$39) | E47: =IF(E$44>E$39,E$44,E$39) | F47: =IF(F$44>F$39,F$44,F$39) | G47: =IF(G$44>G$39,G$44,G$39) | H47: =IF(H$44>H$39,H$44,H$39) | I47: =IF(I$44>I$39,I$44,I$39) | J47: =IF(J$44>J$39,J$44,J$39) | ... M47: =IF(M$44>M$39,M$44,M$39) | N47: =SUM($C47:$M47) | O47: =$C47+NPV(10%,$D47:$M47)

Sheet 06_06_IS_IMF_2
A1: Nom | B1: Unité | C1: Année 1 | D1: Année 2 | E1: Année 3 | F1: Année 4 | G1: Année 5 | H1: Année 6 | I1: Année 7 | J1: Année 8 | K1: Année 9 | L1: Année 10 | M1: Année 11
A3: Durée restante maximum | B3: Années | C3: 11 | D3: 10 | E3: 9 | F3: 8 | G3: 7 | H3: 6 | I3: 5 | J3: 4 | K3: 3 | L3: 2 | M3: 1
A5: I. AMORTISSEMENTS DES CONSTRUCTIONS INDUSTRIELLES
A6: Durée d'amortissement linéaire | B6: Années | C6: 10
A7: Coefficient d'amortissement dégressif | B7: Coefficient | C7: 1
A9: Immobilisations de l'année A1
A10: Durée restante | B10: Années | C10: =IF($C$6<C$3,$C$6,C$3) | D10: =IF(C10=0,0,IF(C10-1<D$3,C10-1,D$3)) | E10: =IF(D10=0,0,IF(D10-1<E$3,D10-1,E$3)) | F10: =IF(E10=0,0,IF(E10-1<F$3,E10-1,F$3)) | G10: =IF(F10=0,0,IF(F10-1<G$3,F10-1,G$3)) | H10: =IF(G10=0,0,IF(G10-1<H$3,G10-1,H$3)) | I10: =IF(H10=0,0,IF(H10-1<I$3,H10-1,I$3)) | J10: =IF(I10=0,0,IF(I10-1<J$3,I10-1,J$3)) | K10: =IF(J10=0,0,IF(J10-1<K$3,J10-1,K$3)) | ... M10: =IF(L10=0,0,IF(L10-1<M$3,L10-1,M$3))
A11: Base amortissable | B11: USD | C11: =Modèle!C$9 | D11: =C15 | E11: =D15 | F11: =E15 | G11: =F15 | H11: =G15 | I11: =H15 | J11: =I15 | K11: =J15 | ... M11: =L15
A12: Inverse de la durée restante | B12: % | C12: =IF(C10=0,0,1/C10) | D12: =IF(D10=0,0,1/D10) | E12: =IF(E10=0,0,1/E10) | F12: =IF(F10=0,0,1/F10) | G12: =IF(G10=0,0,1/G10) | H12: =IF(H10=0,0,1/H10) | I12: =IF(I10=0,0,1/I10) | J12: =IF(J10=0,0,1/J10) | ... M12: =IF(M10=0,0,1/M10)
A13: Taux dégressif | B13: % | C13: =IF(C10=0,0,IF($C$7*1/$C$6>C12,$C$7*1/$C$6,C12)) | D13: =IF(D10=0,0,IF($C$7*1/$C$6>D12,$C$7*1/$C$6,D12)) | E13: =IF(E10=0,0,IF($C$7*1/$C$6>E12,$C$7*1/$C$6,E12)) | F13: =IF(F10=0,0,IF($C$7*1/$C$6>F12,$C$7*1/$C$6,F12)) | G13: =IF(G10=0,0,IF($C$7*1/$C$6>G12,$C$7*1/$C$6,G12)) | H13: =IF(H10=0,0,IF($C$7*1/$C$6>H12,$C$7*1/$C$6,H12)) | I13: =IF(I10=0,0,IF($C$7*1/$C$6>I12,$C$7*1/$C$6,I12)) | J13: =IF(J10=0,0,IF($C$7*1/$C$6>J12,$C$7*1/$C$6,J12)) | ... M13: =IF(M10=0,0,IF($C$7*1/$C$6>M12,$C$7*1/$C$6,M12))
A14: Charge d'amortissement | B14: USD | C14: =C11*C13 | D14: =D11*D13 | E14: =E11*E13 | F14: =F11*F13 | G14: =G11*G13 | H14: =H11*H13 | I14: =I11*I13 | J14: =J11*J13 | ... M14: =M11*M13
A15: Amortissement restant | B15: USD | C15: =C11-C14 | D15: =D11-D14 | E15: =E11-E14 | F15: =F11-F14 | G15: =G11-G14 | H15: =H11-H14 | I15: =I11-I14 | J15: =J11-J14 | ... M15: =M11-M14
A17: Immobilisations de l'année A2
A18: Durée restante | B18: Années | D18: =IF($C$6<D$3,$C$6,D$3) | E18: =IF(D18=0,0,IF(D18-1<E$3,D18-1,E$3)) | F18: =IF(E18=0,0,IF(E18-1<F$3,E18-1,F$3)) | G18: =IF(F18=0,0,IF(F18-1<G$3,F18-1,G$3)) | H18: =IF(G18=0,0,IF(G18-1<H$3,G18-1,H$3)) | I18: =IF(H18=0,0,IF(H18-1<I$3,H18-1,I$3)) | J18: =IF(I18=0,0,IF(I18-1<J$3,I18-1,J$3)) | K18: =IF(J18=0,0,IF(J18-1<K$3,J18-1,K$3)) | L18: =IF(K18=0,0,IF(K18-1<L$3,K18-1,L$3)) | M18: =IF(L18=0,0,IF(L18-1<M$3,L18-1,M$3))
A19: Base amortissable | B19: USD | D19: =Modèle!D$9 | E19: =D23 | F19: =E23 | G19: =F23 | H19: =G23 | I19: =H23 | J19: =I23 | K19: =J23 | L19: =K23 | M19: =L23
A20: Inverse de la durée restante | B20: % | D20: =IF(D18=0,0,1/D18) | E20: =IF(E18=0,0,1/E18) | F20: =IF(F18=0,0,1/F18) | G20: =IF(G18=0,0,1/G18) | H20: =IF(H18=0,0,1/H18) | I20: =IF(I18=0,0,1/I18) | J20: =IF(J18=0,0,1/J18) | K20: =IF(K18=0,0,1/K18) | ... M20: =IF(M18=0,0,1/M18)
A21: Taux dégressif | B21: % | D21: =IF(D18=0,0,IF($C$7*1/$C$6>D20,$C$7*1/$C$6,D20)) | E21: =IF(E18=0,0,IF($C$7*1/$C$6>E20,$C$7*1/$C$6,E20)) | F21: =IF(F18=0,0,IF($C$7*1/$C$6>F20,$C$7*1/$C$6,F20)) | G21: =IF(G18=0,0,IF($C$7*1/$C$6>G20,$C$7*1/$C$6,G20)) | H21: =IF(H18=0,0,IF($C$7*1/$C$6>H20,$C$7*1/$C$6,H20)) | I21: =IF(I18=0,0,IF($C$7*1/$C$6>I20,$C$7*1/$C$6,I20)) | J21: =IF(J18=0,0,IF($C$7*1/$C$6>J20,$C$7*1/$C$6,J20)) | K21: =IF(K18=0,0,IF($C$7*1/$C$6>K20,$C$7*1/$C$6,K20)) | ... M21: =IF(M18=0,0,IF($C$7*1/$C$6>M20,$C$7*1/$C$6,M20))
A22: Charge d'amortissement | B22: USD | D22: =D19*D21 | E22: =E19*E21 | F22: =F19*F21 | G22: =G19*G21 | H22: =H19*H21 | I22: =I19*I21 | J22: =J19*J21 | K22: =K19*K21 | ... M22: =M19*M21
A23: Amortissement restant | B23: USD | D23: =D19-D22 | E23: =E19-E22 | F23: =F19-F22 | G23: =G19-G22 | H23: =H19-H22 | I23: =I19-I22 | J23: =J19-J22 | K23: =K19-K22 | ... M23: =M19-M22
A25: Amortissements des constructions industrielles | B25: USD | C25: =C$14+C$22 | D25: =D$14+D$22 | E25: =E$14+E$22 | F25: =F$14+F$22 | G25: =G$14+G$22 | H25: =H$14+H$22 | I25: =I$14+I$22 | J25: =J$14+J$22 | ... M25: =M$14+M$22
A27: II. AMORTISSEMENTS DES BIENS D'EQUIPEMENT
A28: Durée d'amortissement linéaire | B28: Années | C28: 5
A29: Coefficient d'amortissement dégressif | B29: Coefficient | C29: 2
A31: Immobilisations de l'année A1
A32: Durée restante | B32: Années | C32: =IF($C$28<C$3,$C$28,C$3) | D32: =IF(C32=0,0,IF(C32-1<D$3,C32-1,D$3)) | E32: =IF(D32=0,0,IF(D32-1<E$3,D32-1,E$3)) | F32: =IF(E32=0,0,IF(E32-1<F$3,E32-1,F$3)) | G32: =IF(F32=0,0,IF(F32-1<G$3,F32-1,G$3)) | H32: =IF(G32=0,0,IF(G32-1<H$3,G32-1,H$3)) | I32: =IF(H32=0,0,IF(H32-1<I$3,H32-1,I$3)) | J32: =IF(I32=0,0,IF(I32-1<J$3,I32-1,J$3)) | K32: =IF(J32=0,0,IF(J32-1<K$3,J32-1,K$3)) | ... M32: =IF(L32=0,0,IF(L32-1<M$3,L32-1,M$3))
A33: Base amortissable | B33: USD | C33: =Modèle!C$10 | D33: =C37 | E33: =D37 | F33: =E37 | G33: =F37 | H33: =G37 | I33: =H37 | J33: =I37 | K33: =J37 | ... M33: =L37
A34: Inverse de la durée restante | B34: % | C34: =IF(C32=0,0,1/C32) | D34: =IF(D32=0,0,1/D32) | E34: =IF(E32=0,0,1/E32) | F34: =IF(F32=0,0,1/F32) | G34: =IF(G32=0,0,1/G32) | H34: =IF(H32=0,0,1/H32) | I34: =IF(I32=0,0,1/I32) | J34: =IF(J32=0,0,1/J32) | ... M34: =IF(M32=0,0,1/M32)
A35: Taux dégressif | B35: % | C35: =IF(C32=0,0,IF($C$29*1/$C$28>C34,$C$29*1/$C$28,C34)) | D35: =IF(D32=0,0,IF($C$29*1/$C$28>D34,$C$29*1/$C$28,D34)) | E35: =IF(E32=0,0,IF($C$29*1/$C$28>E34,$C$29*1/$C$28,E34)) | F35: =IF(F32=0,0,IF($C$29*1/$C$28>F34,$C$29*1/$C$28,F34)) | G35: =IF(G32=0,0,IF($C$29*1/$C$28>G34,$C$29*1/$C$28,G34)) | H35: =IF(H32=0,0,IF($C$29*1/$C$28>H34,$C$29*1/$C$28,H34)) | I35: =IF(I32=0,0,IF($C$29*1/$C$28>I34,$C$29*1/$C$28,I34)) | J35: =IF(J32=0,0,IF($C$29*1/$C$28>J34,$C$29*1/$C$28,J34)) | ... M35: =IF(M32=0,0,IF($C$29*1/$C$28>M34,$C$29*1/$C$28,M34))
A36: Charge d'amortissement | B36: USD | C36: =C33*C35 | D36: =D33*D35 | E36: =E33*E35 | F36: =F33*F35 | G36: =G33*G35 | H36: =H33*H35 | I36: =I33*I35 | J36: =J33*J35 | ... M36: =M33*M35
A37: Amortissement restant | B37: USD | C37: =C33-C36 | D37: =D33-D36 | E37: =E33-E36 | F37: =F33-F36 | G37: =G33-G36 | H37: =H33-H36 | I37: =I33-I36 | J37: =J33-J36 | ... M37: =M33-M36
A39: Immobilisations de l'année A2
A40: Durée restante | B40: Années | D40: =IF($C$28<D$3,$C$28,D$3) | E40: =IF(D40=0,0,IF(D40-1<E$3,D40-1,E$3)) | F40: =IF(E40=0,0,IF(E40-1<F$3,E40-1,F$3)) | G40: =IF(F40=0,0,IF(F40-1<G$3,F40-1,G$3)) | H40: =IF(G40=0,0,IF(G40-1<H$3,G40-1,H$3)) | I40: =IF(H40=0,0,IF(H40-1<I$3,H40-1,I$3)) | J40: =IF(I40=0,0,IF(I40-1<J$3,I40-1,J$3)) | K40: =IF(J40=0,0,IF(J40-1<K$3,J40-1,K$3)) | L40: =IF(K40=0,0,IF(K40-1<L$3,K40-1,L$3)) | M40: =IF(L40=0,0,IF(L40-1<M$3,L40-1,M$3))
A41: Base amortissable | B41: USD | D41: =Modèle!D$10 | E41: =D45 | F41: =E45 | G41: =F45 | H41: =G45 | I41: =H45 | J41: =I45 | K41: =J45 | L41: =K45 | M41: =L45
A42: Inverse de la durée restante | B42: % | D42: =IF(D40=0,0,1/D40) | E42: =IF(E40=0,0,1/E40) | F42: =IF(F40=0,0,1/F40) | G42: =IF(G40=0,0,1/G40) | H42: =IF(H40=0,0,1/H40) | I42: =IF(I40=0,0,1/I40) | J42: =IF(J40=0,0,1/J40) | K42: =IF(K40=0,0,1/K40) | ... M42: =IF(M40=0,0,1/M40)
A43: Taux dégressif | B43: % | D43: =IF(D40=0,0,IF($C$29*1/$C$28>D42,$C$29*1/$C$28,D42)) | E43: =IF(E40=0,0,IF($C$29*1/$C$28>E42,$C$29*1/$C$28,E42)) | F43: =IF(F40=0,0,IF($C$29*1/$C$28>F42,$C$29*1/$C$28,F42)) | G43: =IF(G40=0,0,IF($C$29*1/$C$28>G42,$C$29*1/$C$28,G42)) | H43: =IF(H40=0,0,IF($C$29*1/$C$28>H42,$C$29*1/$C$28,H42)) | I43: =IF(I40=0,0,IF($C$29*1/$C$28>I42,$C$29*1/$C$28,I42)) | J43: =IF(J40=0,0,IF($C$29*1/$C$28>J42,$C$29*1/$C$28,J42)) | K43: =IF(K40=0,0,IF($C$29*1/$C$28>K42,$C$29*1/$C$28,K42)) | ... M43: =IF(M40=0,0,IF($C$29*1/$C$28>M42,$C$29*1/$C$28,M42))
A44: Charge d'amortissement | B44: USD | D44: =D41*D43 | E44: =E41*E43 | F44: =F41*F43 | G44: =G41*G43 | H44: =H41*H43 | I44: =I41*I43 | J44: =J41*J43 | K44: =K41*K43 | ... M44: =M41*M43
A45: Amortissement restant | B45: USD | D45: =D41-D44 | E45: =E41-E44 | F45: =F41-F44 | G45: =G41-G44 | H45: =H41-H44 | I45: =I41-I44 | J45: =J41-J44 | K45: =K41-K44 | ... M45: =M41-M44
A47: Immobilisations de l'année A3
A48: Durée restante | B48: Années | E48: =IF($C$28<E$3,$C$28,E$3) | F48: =IF(E48=0,0,IF(E48-1<F$3,E48-1,F$3)) | G48: =IF(F48=0,0,IF(F48-1<G$3,F48-1,G$3)) | H48: =IF(G48=0,0,IF(G48-1<H$3,G48-1,H$3)) | I48: =IF(H48=0,0,IF(H48-1<I$3,H48-1,I$3)) | J48: =IF(I48=0,0,IF(I48-1<J$3,I48-1,J$3)) | K48: =IF(J48=0,0,IF(J48-1<K$3,J48-1,K$3)) | L48: =IF(K48=0,0,IF(K48-1<L$3,K48-1,L$3)) | M48: =IF(L48=0,0,IF(L48-1<M$3,L48-1,M$3))
A49: Base amortissable | B49: USD | E49: =Modèle!E$10 | F49: =E53 | G49: =F53 | H49: =G53 | I49: =H53 | J49: =I53 | K49: =J53 | L49: =K53 | M49: =L53
A50: Inverse de la durée restante | B50: % | E50: =IF(E48=0,0,1/E48) | F50: =IF(F48=0,0,1/F48) | G50: =IF(G48=0,0,1/G48) | H50: =IF(H48=0,0,1/H48) | I50: =IF(I48=0,0,1/I48) | J50: =IF(J48=0,0,1/J48) | K50: =IF(K48=0,0,1/K48) | L50: =IF(L48=0,0,1/L48) | M50: =IF(M48=0,0,1/M48)
A51: Taux dégressif | B51: % | E51: =IF(E48=0,0,IF($C$29*1/$C$28>E50,$C$29*1/$C$28,E50)) | F51: =IF(F48=0,0,IF($C$29*1/$C$28>F50,$C$29*1/$C$28,F50)) | G51: =IF(G48=0,0,IF($C$29*1/$C$28>G50,$C$29*1/$C$28,G50)) | H51: =IF(H48=0,0,IF($C$29*1/$C$28>H50,$C$29*1/$C$28,H50)) | I51: =IF(I48=0,0,IF($C$29*1/$C$28>I50,$C$29*1/$C$28,I50)) | J51: =IF(J48=0,0,IF($C$29*1/$C$28>J50,$C$29*1/$C$28,J50)) | K51: =IF(K48=0,0,IF($C$29*1/$C$28>K50,$C$29*1/$C$28,K50)) | L51: =IF(L48=0,0,IF($C$29*1/$C$28>L50,$C$29*1/$C$28,L50)) | M51: =IF(M48=0,0,IF($C$29*1/$C$28>M50,$C$29*1/$C$28,M50))
A52: Charge d'amortissement | B52: USD | E52: =E49*E51 | F52: =F49*F51 | G52: =G49*G51 | H52: =H49*H51 | I52: =I49*I51 | J52: =J49*J51 | K52: =K49*K51 | L52: =L49*L51 | M52: =M49*M51
A53: Amortissement restant | B53: USD | E53: =E49-E52 | F53: =F49-F52 | G53: =G49-G52 | H53: =H49-H52 | I53: =I49-I52 | J53: =J49-J52 | K53: =K49-K52 | L53: =L49-L52 | M53: =M49-M52
A55: Immobilisations de l'année A4
A56: Durée restante | B56: Années | F56: =IF($C$28<F$3,$C$28,F$3) | G56: =IF(F56=0,0,IF(F56-1<G$3,F56-1,G$3)) | H56: =IF(G56=0,0,IF(G56-1<H$3,G56-1,H$3)) | I56: =IF(H56=0,0,IF(H56-1<I$3,H56-1,I$3)) | J56: =IF(I56=0,0,IF(I56-1<J$3,I56-1,J$3)) | K56: =IF(J56=0,0,IF(J56-1<K$3,J56-1,K$3)) | L56: =IF(K56=0,0,IF(K56-1<L$3,K56-1,L$3)) | M56: =IF(L56=0,0,IF(L56-1<M$3,L56-1,M$3))
A57: Base amortissable | B57: USD | F57: =Modèle!F$10 | G57: =F61 | H57: =G61 | I57: =H61 | J57: =I61 | K57: =J61 | L57: =K61 | M57: =L61
A58: Inverse de la durée restante | B58: % | F58: =IF(F56=0,0,1/F56) | G58: =IF(G56=0,0,1/G56) | H58: =IF(H56=0,0,1/H56) | I58: =IF(I56=0,0,1/I56) | J58: =IF(J56=0,0,1/J56) | K58: =IF(K56=0,0,1/K56) | L58: =IF(L56=0,0,1/L56) | M58: =IF(M56=0,0,1/M56)
A59: Taux dégressif | B59: % | F59: =IF(F56=0,0,IF($C$29*1/$C$28>F58,$C$29*1/$C$28,F58)) | G59: =IF(G56=0,0,IF($C$29*1/$C$28>G58,$C$29*1/$C$28,G58)) | H59: =IF(H56=0,0,IF($C$29*1/$C$28>H58,$C$29*1/$C$28,H58)) | I59: =IF(I56=0,0,IF($C$29*1/$C$28>I58,$C$29*1/$C$28,I58)) | J59: =IF(J56=0,0,IF($C$29*1/$C$28>J58,$C$29*1/$C$28,J58)) | K59: =IF(K56=0,0,IF($C$29*1/$C$28>K58,$C$29*1/$C$28,K58)) | L59: =IF(L56=0,0,IF($C$29*1/$C$28>L58,$C$29*1/$C$28,L58)) | M59: =IF(M56=0,0,IF($C$29*1/$C$28>M58,$C$29*1/$C$28,M58))
A60: Charge d'amortissement | B60: USD | F60: =F57*F59 | G60: =G57*G59 | H60: =H57*H59 | I60: =I57*I59 | J60: =J57*J59 | K60: =K57*K59 | L60: =L57*L59 | M60: =M57*M59
A61: Amortissement restant | B61: USD | F61: =F57-F60 | G61: =G57-G60 | H61: =H57-H60 | I61: =I57-I60 | J61: =J57-J60 | K61: =K57-K60 | L61: =L57-L60 | M61: =M57-M60
A63: Immobilisations de l'année A5
A64: Durée restante | B64: Années | G64: =IF($C$28<G$3,$C$28,G$3) | H64: =IF(G64=0,0,IF(G64-1<H$3,G64-1,H$3)) | I64: =IF(H64=0,0,IF(H64-1<I$3,H64-1,I$3)) | J64: =IF(I64=0,0,IF(I64-1<J$3,I64-1,J$3)) | K64: =IF(J64=0,0,IF(J64-1<K$3,J64-1,K$3)) | L64: =IF(K64=0,0,IF(K64-1<L$3,K64-1,L$3)) | M64: =IF(L64=0,0,IF(L64-1<M$3,L64-1,M$3))
A65: Base amortissable | B65: USD | G65: =Modèle!G$10 | H65: =G69 | I65: =H69 | J65: =I69 | K65: =J69 | L65: =K69 | M65: =L69
A66: Inverse de la durée restante | B66: % | G66: =IF(G64=0,0,1/G64) | H66: =IF(H64=0,0,1/H64) | I66: =IF(I64=0,0,1/I64) | J66: =IF(J64=0,0,1/J64) | K66: =IF(K64=0,0,1/K64) | L66: =IF(L64=0,0,1/L64) | M66: =IF(M64=0,0,1/M64)
A67: Taux dégressif | B67: % | G67: =IF(G64=0,0,IF($C$29*1/$C$28>G66,$C$29*1/$C$28,G66)) | H67: =IF(H64=0,0,IF($C$29*1/$C$28>H66,$C$29*1/$C$28,H66)) | I67: =IF(I64=0,0,IF($C$29*1/$C$28>I66,$C$29*1/$C$28,I66)) | J67: =IF(J64=0,0,IF($C$29*1/$C$28>J66,$C$29*1/$C$28,J66)) | K67: =IF(K64=0,0,IF($C$29*1/$C$28>K66,$C$29*1/$C$28,K66)) | L67: =IF(L64=0,0,IF($C$29*1/$C$28>L66,$C$29*1/$C$28,L66)) | M67: =IF(M64=0,0,IF($C$29*1/$C$28>M66,$C$29*1/$C$28,M66))
A68: Charge d'amortissement | B68: USD | G68: =G65*G67 | H68: =H65*H67 | I68: =I65*I67 | J68: =J65*J67 | K68: =K65*K67 | L68: =L65*L67 | M68: =M65*M67
A69: Amortissement restant | B69: USD | G69: =G65-G68 | H69: =H65-H68 | I69: =I65-I68 | J69: =J65-J68 | K69: =K65-K68 | L69: =L65-L68 | M69: =M65-M68
A71: Immobilisations de l'année A6
A72: Durée restante | B72: Années | H72: =IF($C$28<H$3,$C$28,H$3) | I72: =IF(H72=0,0,IF(H72-1<I$3,H72-1,I$3)) | J72: =IF(I72=0,0,IF(I72-1<J$3,I72-1,J$3)) | K72: =IF(J72=0,0,IF(J72-1<K$3,J72-1,K$3)) | L72: =IF(K72=0,0,IF(K72-1<L$3,K72-1,L$3)) | M72: =IF(L72=0,0,IF(L72-1<M$3,L72-1,M$3))
A73: Base amortissable | B73: USD | H73: =Modèle!H$10 | I73: =H77 | J73: =I77 | K73: =J77 | L73: =K77 | M73: =L77
A74: Inverse de la durée restante | B74: % | H74: =IF(H72=0,0,1/H72) | I74: =IF(I72=0,0,1/I72) | J74: =IF(J72=0,0,1/J72) | K74: =IF(K72=0,0,1/K72) | L74: =IF(L72=0,0,1/L72) | M74: =IF(M72=0,0,1/M72)
A75: Taux dégressif | B75: % | H75: =IF(H72=0,0,IF($C$29*1/$C$28>H74,$C$29*1/$C$28,H74)) | I75: =IF(I72=0,0,IF($C$29*1/$C$28>I74,$C$29*1/$C$28,I74)) | J75: =IF(J72=0,0,IF($C$29*1/$C$28>J74,$C$29*1/$C$28,J74)) | K75: =IF(K72=0,0,IF($C$29*1/$C$28>K74,$C$29*1/$C$28,K74)) | L75: =IF(L72=0,0,IF($C$29*1/$C$28>L74,$C$29*1/$C$28,L74)) | M75: =IF(M72=0,0,IF($C$29*1/$C$28>M74,$C$29*1/$C$28,M74))
A76: Charge d'amortissement | B76: USD | H76: =H73*H75 | I76: =I73*I75 | J76: =J73*J75 | K76: =K73*K75 | L76: =L73*L75 | M76: =M73*M75
A77: Amortissement restant | B77: USD | H77: =H73-H76 | I77: =I73-I76 | J77: =J73-J76 | K77: =K73-K76 | L77: =L73-L76 | M77: =M73-M76
A79: Immobilisations de l'année A7
A80: Durée restante | B80: Années | I80: =IF($C$28<I$3,$C$28,I$3) | J80: =IF(I80=0,0,IF(I80-1<J$3,I80-1,J$3)) | K80: =IF(J80=0,0,IF(J80-1<K$3,J80-1,K$3)) | L80: =IF(K80=0,0,IF(K80-1<L$3,K80-1,L$3)) | M80: =IF(L80=0,0,IF(L80-1<M$3,L80-1,M$3))
A81: Base amortissable | B81: USD | I81: =Modèle!I$10 | J81: =I85 | K81: =J85 | L81: =K85 | M81: =L85
A82: Inverse de la durée restante | B82: % | I82: =IF(I80=0,0,1/I80) | J82: =IF(J80=0,0,1/J80) | K82: =IF(K80=0,0,1/K80) | L82: =IF(L80=0,0,1/L80) | M82: =IF(M80=0,0,1/M80)
A83: Taux dégressif | B83: % | I83: =IF(I80=0,0,IF($C$29*1/$C$28>I82,$C$29*1/$C$28,I82)) | J83: =IF(J80=0,0,IF($C$29*1/$C$28>J82,$C$29*1/$C$28,J82)) | K83: =IF(K80=0,0,IF($C$29*1/$C$28>K82,$C$29*1/$C$28,K82)) | L83: =IF(L80=0,0,IF($C$29*1/$C$28>L82,$C$29*1/$C$28,L82)) | M83: =IF(M80=0,0,IF($C$29*1/$C$28>M82,$C$29*1/$C$28,M82))
A84: Charge d'amortissement | B84: USD | I84: =I81*I83 | J84: =J81*J83 | K84: =K81*K83 | L84: =L81*L83 | M84: =M81*M83
A85: Amortissement restant | B85: USD | I85: =I81-I84 | J85: =J81-J84 | K85: =K81-K84 | L85: =L81-L84 | M85: =M81-M84
A87: Immobilisations de l'année A8
A88: Durée restante | B88: Années | J88: =IF($C$28<J$3,$C$28,J$3) | K88: =IF(J88=0,0,IF(J88-1<K$3,J88-1,K$3)) | L88: =IF(K88=0,0,IF(K88-1<L$3,K88-1,L$3)) | M88: =IF(L88=0,0,IF(L88-1<M$3,L88-1,M$3))
A89: Base amortissable | B89: USD | J89: =Modèle!J$10 | K89: =J93 | L89: =K93 | M89: =L93
A90: Inverse de la durée restante | B90: % | J90: =IF(J88=0,0,1/J88) | K90: =IF(K88=0,0,1/K88) | L90: =IF(L88=0,0,1/L88) | M90: =IF(M88=0,0,1/M88)
A91: Taux dégressif | B91: % | J91: =IF(J88=0,0,IF($C$29*1/$C$28>J90,$C$29*1/$C$28,J90)) | K91: =IF(K88=0,0,IF($C$29*1/$C$28>K90,$C$29*1/$C$28,K90)) | L91: =IF(L88=0,0,IF($C$29*1/$C$28>L90,$C$29*1/$C$28,L90)) | M91: =IF(M88=0,0,IF($C$29*1/$C$28>M90,$C$29*1/$C$28,M90))
A92: Charge d'amortissement | B92: USD | J92: =J89*J91 | K92: =K89*K91 | L92: =L89*L91 | M92: =M89*M91
A93: Amortissement restant | B93: USD | J93: =J89-J92 | K93: =K89-K92 | L93: =L89-L92 | M93: =M89-M92
A95: Immobilisations de l'année A9
A96: Durée restante | B96: Années | K96: =IF($C$28<K$3,$C$28,K$3) | L96: =IF(K96=0,0,IF(K96-1<L$3,K96-1,L$3)) | M96: =IF(L96=0,0,IF(L96-1<M$3,L96-1,M$3))
A97: Base amortissable | B97: USD | K97: =Modèle!K$10 | L97: =K101 | M97: =L101
A98: Inverse de la durée restante | B98: % | K98: =IF(K96=0,0,1/K96) | L98: =IF(L96=0,0,1/L96) | M98: =IF(M96=0,0,1/M96)
A99: Taux dégressif | B99: % | K99: =IF(K96=0,0,IF($C$29*1/$C$28>K98,$C$29*1/$C$28,K98)) | L99: =IF(L96=0,0,IF($C$29*1/$C$28>L98,$C$29*1/$C$28,L98)) | M99: =IF(M96=0,0,IF($C$29*1/$C$28>M98,$C$29*1/$C$28,M98))
A100: Charge d'amortissement | B100: USD | K100: =K97*K99 | L100: =L97*L99 | M100: =M97*M99
A101: Amortissement restant | B101: USD | K101: =K97-K100 | L101: =L97-L100 | M101: =M97-M100
A103: Immobilisations de l'année A10
A104: Durée restante | B104: Années | L104: =IF($C$28<L$3,$C$28,L$3) | M104: =IF(L104=0,0,IF(L104-1<M$3,L104-1,M$3))
A105: Base amortissable | B105: USD | L105: =Modèle!L$10 | M105: =L109
A106: Inverse de la durée restante | B106: % | L106: =IF(L104=0,0,1/L104) | M106: =IF(M104=0,0,1/M104)
A107: Taux dégressif | B107: % | L107: =IF(L104=0,0,IF($C$29*1/$C$28>L106,$C$29*1/$C$28,L106)) | M107: =IF(M104=0,0,IF($C$29*1/$C$28>M106,$C$29*1/$C$28,M106))
A108: Charge d'amortissement | B108: USD | L108: =L105*L107 | M108: =M105*M107
A109: Amortissement restant | B109: USD | L109: =L105-L108 | M109: =M105-M108
A111: Immobilisations de l'année A11
A112: Durée restante | B112: Années | M112: =IF($C$28<M$3,$C$28,M$3)
A113: Base amortissable | B113: USD | M113: =Modèle!M$10
A114: Inverse de la durée restante | B114: % | M114: =IF(M112=0,0,1/M112)
A115: Taux dégressif | B115: % | M115: =IF(M112=0,0,IF($C$29*1/$C$28>M114,$C$29*1/$C$28,M114))
A116: Charge d'amortissement | B116: USD | M116: =M113*M115
A117: Amortissement restant | B117: USD | M117: =M113-M116
...

Sheet 07_07_TEMI_1
A1: Nom | B1: Unité | C1: Année 1 | D1: Année 2 | E1: Année 3 | F1: Année 4 | G1: Année 5 | H1: Année 6 | I1: Année 7 | J1: Année 8 | K1: Année 9 | L1: Année 10 | M1: Année 11 | N1: SOMME | O1: VAN
A3: I. PRODUCTION
A4: Production d'or | B4: oz | E4: 250000 | F4: 250000 | G4: 250000 | H4: 250000 | I4: 250000 | J4: 250000 | K4: 250000 | L4: 250000 | N4: =SUM($C4:$M4)
A5: Cours de l'or | B5: USD/oz | E5: 1300 | F5: 1300 | G5: 1300 | H5: 1300 | I5: 1300 | J5: 1300 | K5: 1300 | L5: 1300
A6: Chiffre d'affaires | B6: USD | C6: =C$4*C$5 | D6: =D$4*D$5 | E6: =E$4*E$5 | F6: =F$4*F$5 | G6: =G$4*G$5 | H6: =H$4*H$5 | I6: =I$4*I$5 | J6: =J$4*J$5 | ... M6: =M$4*M$5 | N6: =SUM($C6:$M6) | O6: =$C6+NPV(10%,$D6:$M6)
A8: II. DEPENSES D'INVESTISSEMENT (CAPEX)
A9: Coûts des construction industrielles | B9: USD | C9: 50000000 | D9: 100000000 | N9: =SUM($C9:$M9) | O9: =$C9+NPV(10%,$D9:$M9)
A10: Coûts des biens d'équipement | B10: USD | D10: 50000000 | E10: 5000000 | F10: 5000000 | G10: 5000000 | H10: 5000000 | I10: 5000000 | J10: 5000000 | K10: 5000000 | L10: 5000000 | N10: =SUM($C10:$M10) | O10: =$C10+NPV(10%,$D10:$M10)
A11: Coûts de réhabilitation du site | B11: USD | M11: 10000000 | N11: =SUM($C11:$M11) | O11: =$C11+NPV(10%,$D11:$M11)
A12: Total des dépenses d'investissement | B12: USD | C12: =SUM(C$9:C$11) | D12: =SUM(D$9:D$11) | E12: =SUM(E$9:E$11) | F12: =SUM(F$9:F$11) | G12: =SUM(G$9:G$11) | H12: =SUM(H$9:H$11) | I12: =SUM(I$9:I$11) | J12: =SUM(J$9:J$11) | ... M12: =SUM(M$9:M$11) | N12: =SUM($C12:$M12) | O12: =$C12+NPV(10%,$D12:$M12)
A14: III. COÛTS D'EXPLOITATION (OPEX)
A15: Coût moyen d'exploitation | B15: USD/oz | E15: 700 | F15: 700 | G15: 700 | H15: 700 | I15: 700 | J15: 700 | K15: 700 | L15: 700
A16: Total des coûts d'exploitation | B16: USD | C16: =C$4*C$15 | D16: =D$4*D$15 | E16: =E$4*E$15 | F16: =F$4*F$15 | G16: =G$4*G$15 | H16: =H$4*H$15 | I16: =I$4*I$15 | J16: =J$4*J$15 | ... M16: =M$4*M$15 | N16: =SUM($C16:$M16) | O16: =$C16+NPV(10%,$D16:$M16)
A18: IV. FLUX NETS DE TRESORERIE AVANT IMPÔTS
A19: Flux nets de trésorerie avant impôts | B19: USD | C19: =C$6-C$12-C$16 | D19: =D$6-D$12-D$16 | E19: =E$6-E$12-E$16 | F19: =F$6-F$12-F$16 | G19: =G$6-G$12-G$16 | H19: =H$6-H$12-H$16 | I19: =I$6-I$12-I$16 | J19: =J$6-J$12-J$16 | ... M19: =M$6-M$12-M$16 | N19: =SUM($C19:$M19) | O19: =$C19+NPV(10%,$D19:$M19)
A20: Taux de rendement interne avant impôts | B20: % | C20: =IF(ISNUMBER(IRR($C19:C19)),IF(IRR($C19:C19)>0,IRR($C19:C19),""),"") | D20: =IF(ISNUMBER(IRR($C19:D19)),IF(IRR($C19:D19)>0,IRR($C19:D19),""),"") | E20: =IF(ISNUMBER(IRR($C19:E19)),IF(IRR($C19:E19)>0,IRR($C19:E19),""),"") | F20: =IF(ISNUMBER(IRR($C19:F19)),IF(IRR($C19:F19)>0,IRR($C19:F19),""),"") | G20: =IF(ISNUMBER(IRR($C19:G19)),IF(IRR($C19:G19)>0,IRR($C19:G19),""),"") | H20: =IF(ISNUMBER(IRR($C19:H19)),IF(IRR($C19:H19)>0,IRR($C19:H19),""),"") | I20: =IF(ISNUMBER(IRR($C19:I19)),IF(IRR($C19:I19)>0,IRR($C19:I19),""),"") | J20: =IF(ISNUMBER(IRR($C19:J19)),IF(IRR($C19:J19)>0,IRR($C19:J19),""),"") | ... M20: =IF(ISNUMBER(IRR($C19:M19)),IF(IRR($C19:M19)>0,IRR($C19:M19),""),"")
A22: V. DROITS FIXES
A23: Droits fixes | B23: USD | C23: 100000 | N23: =SUM($C23:$M23) | O23: =$C23+NPV(10%,$D23:$M23)
A25: VI. REDEVANCE SUPERFICAIRE
A26: Superficie de la mine | B26: km² | C26: 100 | D26: 100 | E26: 100 | F26: 100 | G26: 100 | H26: 100 | I26: 100 | J26: 100 | K26: 100 | L26: 100 | M26: 100
A27: Montant de la redevance superfiaire | B27: USD/km² | C27: 100 | D27: 100 | E27: 100 | F27: 100 | G27: 100 | H27: 100 | I27: 100 | J27: 100 | K27: 100 | L27: 100 | M27: 100
A28: Redevance superficiaire | B28: USD | C28: =C$26*C$27 | D28: =D$26*D$27 | E28: =E$26*E$27 | F28: =F$26*F$27 | G28: =G$26*G$27 | H28: =H$26*H$27 | I28: =I$26*I$27 | J28: =J$26*J$27 | ... M28: =M$26*M$27 | N28: =SUM($C28:$M28) | O28: =$C28+NPV(10%,$D28:$M28)
A30: VII. REDEVANCE MINIERE
A31: Taux de la redevance minière | B31: % | C31: =IF(ISNUMBER(C5),IF(C$5<1300,3%,IF(C$5<1500,4%,5%)),"") | D31: =IF(ISNUMBER(D5),IF(D$5<1300,3%,IF(D$5<1500,4%,5%)),"") | E31: =IF(ISNUMBER(E5),IF(E$5<1300,3%,IF(E$5<1500,4%,5%)),"") | F31: =IF(ISNUMBER(F5),IF(F$5<1300,3%,IF(F$5<1500,4%,5%)),"") | G31: =IF(ISNUMBER(G5),IF(G$5<1300,3%,IF(G$5<1500,4%,5%)),"") | H31: =IF(ISNUMBER(H5),IF(H$5<1300,3%,IF(H$5<1500,4%,5%)),"") | I31: =IF(ISNUMBER(I5),IF(I$5<1300,3%,IF(I$5<1500,4%,5%)),"") | J31: =IF(ISNUMBER(J5),IF(J$5<1300,3%,IF(J$5<1500,4%,5%)),"") | ... M31: =IF(ISNUMBER(M5),IF(M$5<1300,3%,IF(M$5<1500,4%,5%)),"")
A32: Redevance minière | B32: USD | C32: =IF(ISNUMBER(C31),C$6*C$31,0) | D32: =IF(ISNUMBER(D31),D$6*D$31,0) | E32: =IF(ISNUMBER(E31),E$6*E$31,0) | F32: =IF(ISNUMBER(F31),F$6*F$31,0) | G32: =IF(ISNUMBER(G31),G$6*G$31,0) | H32: =IF(ISNUMBER(H31),H$6*H$31,0) | I32: =IF(ISNUMBER(I31),I$6*I$31,0) | J32: =IF(ISNUMBER(J31),J$6*J$31,0) | ... M32: =IF(ISNUMBER(M31),M$6*M$31,0) | N32: =SUM($C32:$M32) | O32: =$C32+NPV(10%,$D32:$M32)
A34: VIII. IMPÔT SUR LES SOCIETES (IS)
A35: Bénéfice avant report des pertes | B35: USD | C35: =C$6-C$16-C$23-C$28-C$32-'Amortissements et Emprunt'!C$25-'Amortissements et Emprunt'!C$119-'Amortissements et Emprunt'!C133-'Amortissements et Emprunt'!C$157 | D35: =D$6-D$16-D$23-D$28-D$32-'Amortissements et Emprunt'!D$25-'Amortissements et Emprunt'!D$119-'Amortissements et Emprunt'!D133-'Amortissements et Emprunt'!D$157 | E35: =E$6-E$16-E$23-E$28-E$32-'Amortissements et Emprunt'!E$25-'Amortissements et Emprunt'!E$119-'Amortissements et Emprunt'!E133-'Amortissements et Emprunt'!E$157 | F35: =F$6-F$16-F$23-F$28-F$32-'Amortissements et Emprunt'!F$25-'Amortissements et Emprunt'!F$119-'Amortissements et Emprunt'!F133-'Amortissements et Emprunt'!F$157 | G35: =G$6-G$16-G$23-G$28-G$32-'Amortissements et Emprunt'!G$25-'Amortissements et Emprunt'!G$119-'Amortissements et Emprunt'!G133-'Amortissements et Emprunt'!G$157 | H35: =H$6-H$16-H$23-H$28-H$32-'Amortissements et Emprunt'!H$25-'Amortissements et Emprunt'!H$119-'Amortissements et Emprunt'!H133-'Amortissements et Emprunt'!H$157 | I35: =I$6-I$16-I$23-I$28-I$32-'Amortissements et Emprunt'!I$25-'Amortissements et Emprunt'!I$119-'Amortissements et Emprunt'!I133-'Amortissements et Emprunt'!I$157 | J35: =J$6-J$16-J$23-J$28-J$32-'Amortissements et Emprunt'!J$25-'Amortissements et Emprunt'!J$119-'Amortissements et Emprunt'!J133-'Amortissements et Emprunt'!J$157 | ... M35: =M$6-M$16-M$23-M$28-M$32-'Amortissements et Emprunt'!M$25-'Amortissements et Emprunt'!M$119-'Amortissements et Emprunt'!M133-'Amortissements et Emprunt'!M$157 | N35: =SUM($C35:$M35) | O35: =$C35+NPV(10%,$D35:$M35)
A36: Report des pertes | B36: USD | D36: =IF(C37<0,C37,0) | E36: =IF(D37<0,D37,0) | F36: =IF(E37<0,E37,0) | G36: =IF(F37<0,F37,0) | H36: =IF(G37<0,G37,0) | I36: =IF(H37<0,H37,0) | J36: =IF(I37<0,I37,0) | K36: =IF(J37<0,J37,0) | ... M36: =IF(L37<0,L37,0)
A37: Bénéfice fiscal | B37: USD | C37: =C$35+C$36 | D37: =D$35+D$36 | E37: =E$35+E$36 | F37: =F$35+F$36 | G37: =G$35+G$36 | H37: =H$35+H$36 | I37: =I$35+I$36 | J37: =J$35+J$36 | ... M37: =M$35+M$36 | N37: =SUM($C37:$M37) | O37: =$C37+NPV(10%,$D37:$M37)
A38: Taux de l'impôt sur les sociétés | B38: % | C38: 0.3 | D38: 0.3 | E38: 0.3 | F38: 0.3 | G38: 0.3 | H38: 0.3 | I38: 0.3 | J38: 0.3 | K38: 0.3 | L38: 0.3 | M38: 0.3
A39: Impôt sur les sociétés | B39: USD | C39: =IF(C$37>0,C$37*C$38,0) | D39: =IF(D$37>0,D$37*D$38,0) | E39: =IF(E$37>0,E$37*E$38,0) | F39: =IF(F$37>0,F$37*F$38,0) | G39: =IF(G$37>0,G$37*G$38,0) | H39: =IF(H$37>0,H$37*H$38,0) | I39: =IF(I$37>0,I$37*I$38,0) | J39: =IF(J$37>0,J$37*J$38,0) | ... M39: =IF(M$37>0,M$37*M$38,0) | N39: =SUM($C39:$M39) | O39: =$C39+NPV(10%,$D39:$M39)
A41: IX. IMPÔT MINIMUM FORFAITAIRE (IMF)
A42: Montant minimum | B42: USD | C42: 2000 | D42: 2000 | E42: 2000 | F42: 2000 | G42: 2000 | H42: 2000 | I42: 2000 | J42: 2000 | K42: 2000 | L42: 2000 | M42: 2000
A43: Taux de l'impôt minimum forfaitaire | B43: % | C43: 0.01 | D43: 0.01 | E43: 0.01 | F43: 0.01 | G43: 0.01 | H43: 0.01 | I43: 0.01 | J43: 0.01 | K43: 0.01 | L43: 0.01 | M43: 0.01
A44: Impôt minimum forfaitaire | B44: USD | C44: =IF(C$6*C$43>C$42,C$6*C$43,C$42) | D44: =IF(D$6*D$43>D$42,D$6*D$43,D$42) | E44: =IF(E$6*E$43>E$42,E$6*E$43,E$42) | F44: =IF(F$6*F$43>F$42,F$6*F$43,F$42) | G44: =IF(G$6*G$43>G$42,G$6*G$43,G$42) | H44: =IF(H$6*H$43>H$42,H$6*H$43,H$42) | I44: =IF(I$6*I$43>I$42,I$6*I$43,I$42) | J44: =IF(J$6*J$43>J$42,J$6*J$43,J$42) | ... M44: =IF(M$6*M$43>M$42,M$6*M$43,M$42) | N44: =SUM($C44:$M44) | O44: =$C44+NPV(10%,$D44:$M44)
A46: X. IMPÔT SUR LES SOCIETES (IS) / IMPÔT MINIMUM FORFAITAIRE (IMF)
A47: Impôt sur les sociétés / Impôt minimum forfaitaire | B47: USD | C47: =IF(C$44>C$39,C$44,C$39) | D47: =IF(D$44>D$39,D$44,D$39) | E47: =IF(E$44>E$39,E$44,E$39) | F47: =IF(F$44>F$39,F$44,F$39) | G47: =IF(G$44>G$39,G$44,G$39) | H47: =IF(H$44>H$39,H$44,H$39) | I47: =IF(I$44>I$39,I$44,I$39) | J47: =IF(J$44>J$39,J$44,J$39) | ... M47: =IF(M$44>M$39,M$44,M$39) | N47: =SUM($C47:$M47) | O47: =$C47+NPV(10%,$D47:$M47)
A49: XI. PRELEVEMENTS PUBLICS
A50: Total des prélèvements publics | B50: USD | C50: =C$23+C$28+C$32+C$47 | D50: =D$23+D$28+D$32+D$47 | E50: =E$23+E$28+E$32+E$47 | F50: =F$23+F$28+F$32+F$47 | G50: =G$23+G$28+G$32+G$47 | H50: =H$23+H$28+H$32+H$47 | I50: =I$23+I$28+I$32+I$47 | J50: =J$23+J$28+J$32+J$47 | ... M50: =M$23+M$28+M$32+M$47 | N50: =SUM($C50:$M50) | O50: =$C50+NPV(10%,$D50:$M50)
A52: XII. FLUX NETS DE TRESORERIE APRES IMPÔTS
A53: Flux nets de trésorerie après impôts | B53: USD | C53: =C$19-C$50 | D53: =D$19-D$50 | E53: =E$19-E$50 | F53: =F$19-F$50 | G53: =G$19-G$50 | H53: =H$19-H$50 | I53: =I$19-I$50 | J53: =J$19-J$50 | ... M53: =M$19-M$50 | N53: =SUM($C53:$M53) | O53: =$C53+NPV(10%,$D53:$M53)
A54: Taux de rendement interne après impôts | B54: % | C54: =IF(ISNUMBER(IRR($C53:C53)),IF(IRR($C53:C53)>0,IRR($C53:C53),""),"") | D54: =IF(ISNUMBER(IRR($C53:D53)),IF(IRR($C53:D53)>0,IRR($C53:D53),""),"") | E54: =IF(ISNUMBER(IRR($C53:E53)),IF(IRR($C53:E53)>0,IRR($C53:E53),""),"") | F54: =IF(ISNUMBER(IRR($C53:F53)),IF(IRR($C53:F53)>0,IRR($C53:F53),""),"") | G54: =IF(ISNUMBER(IRR($C53:G53)),IF(IRR($C53:G53)>0,IRR($C53:G53),""),"") | H54: =IF(ISNUMBER(IRR($C53:H53)),IF(IRR($C53:H53)>0,IRR($C53:H53),""),"") | I54: =IF(ISNUMBER(IRR($C53:I53)),IF(IRR($C53:I53)>0,IRR($C53:I53),""),"") | J54: =IF(ISNUMBER(IRR($C53:J53)),IF(IRR($C53:J53)>0,IRR($C53:J53),""),"") | ... M54: =IF(ISNUMBER(IRR($C53:M53)),IF(IRR($C53:M53)>0,IRR($C53:M53),""),"")
A56: XIII. PARTAGE DE LA RENTE MINIERE
A57: Rente minière | B57: USD | N57: =N$19 | O57: =O$19
A58: Part de l'Etat | B58: % | N58: =N$50/N$57 | O58: =O$50/O$57
A59: Part de l'investisseur | B59: % | N59: =N$53/N$57 | O59: =O$53/O$57

Sheet 07_07_TEMI_2
A1: Nom | B1: Unité | C1: Année 1 | D1: Année 2 | E1: Année 3 | F1: Année 4 | G1: Année 5 | H1: Année 6 | I1: Année 7 | J1: Année 8 | K1: Année 9 | L1: Année 10 | M1: Année 11
A3: Durée restante maximum | B3: Années | C3: 11 | D3: 10 | E3: 9 | F3: 8 | G3: 7 | H3: 6 | I3: 5 | J3: 4 | K3: 3 | L3: 2 | M3: 1
A5: I. AMORTISSEMENTS DES CONSTRUCTIONS INDUSTRIELLES
A6: Durée d'amortissement linéaire | B6: Années | C6: 10
A7: Coefficient d'amortissement dégressif | B7: Coefficient | C7: 1
A9: Immobilisations de l'année A1
A10: Durée restante | B10: Années | C10: =IF($C$6<C$3,$C$6,C$3) | D10: =IF(C10=0,0,IF(C10-1<D$3,C10-1,D$3)) | E10: =IF(D10=0,0,IF(D10-1<E$3,D10-1,E$3)) | F10: =IF(E10=0,0,IF(E10-1<F$3,E10-1,F$3)) | G10: =IF(F10=0,0,IF(F10-1<G$3,F10-1,G$3)) | H10: =IF(G10=0,0,IF(G10-1<H$3,G10-1,H$3)) | I10: =IF(H10=0,0,IF(H10-1<I$3,H10-1,I$3)) | J10: =IF(I10=0,0,IF(I10-1<J$3,I10-1,J$3)) | K10: =IF(J10=0,0,IF(J10-1<K$3,J10-1,K$3)) | ... M10: =IF(L10=0,0,IF(L10-1<M$3,L10-1,M$3))
A11: Base amortissable | B11: USD | C11: =Modèle!C$9 | D11: =C15 | E11: =D15 | F11: =E15 | G11: =F15 | H11: =G15 | I11: =H15 | J11: =I15 | K11: =J15 | ... M11: =L15
A12: Inverse de la durée restante | B12: % | C12: =IF(C10=0,0,1/C10) | D12: =IF(D10=0,0,1/D10) | E12: =IF(E10=0,0,1/E10) | F12: =IF(F10=0,0,1/F10) | G12: =IF(G10=0,0,1/G10) | H12: =IF(H10=0,0,1/H10) | I12: =IF(I10=0,0,1/I10) | J12: =IF(J10=0,0,1/J10) | ... M12: =IF(M10=0,0,1/M10)
A13: Taux dégressif | B13: % | C13: =IF(C10=0,0,IF($C$7*1/$C$6>C12,$C$7*1/$C$6,C12)) | D13: =IF(D10=0,0,IF($C$7*1/$C$6>D12,$C$7*1/$C$6,D12)) | E13: =IF(E10=0,0,IF($C$7*1/$C$6>E12,$C$7*1/$C$6,E12)) | F13: =IF(F10=0,0,IF($C$7*1/$C$6>F12,$C$7*1/$C$6,F12)) | G13: =IF(G10=0,0,IF($C$7*1/$C$6>G12,$C$7*1/$C$6,G12)) | H13: =IF(H10=0,0,IF($C$7*1/$C$6>H12,$C$7*1/$C$6,H12)) | I13: =IF(I10=0,0,IF($C$7*1/$C$6>I12,$C$7*1/$C$6,I12)) | J13: =IF(J10=0,0,IF($C$7*1/$C$6>J12,$C$7*1/$C$6,J12)) | ... M13: =IF(M10=0,0,IF($C$7*1/$C$6>M12,$C$7*1/$C$6,M12))
A14: Charge d'amortissement | B14: USD | C14: =C11*C13 | D14: =D11*D13 | E14: =E11*E13 | F14: =F11*F13 | G14: =G11*G13 | H14: =H11*H13 | I14: =I11*I13 | J14: =J11*J13 | ... M14: =M11*M13
A15: Amortissement restant | B15: USD | C15: =C11-C14 | D15: =D11-D14 | E15: =E11-E14 | F15: =F11-F14 | G15: =G11-G14 | H15: =H11-H14 | I15: =I11-I14 | J15: =J11-J14 | ... M15: =M11-M14
A17: Immobilisations de l'année A2
A18: Durée restante | B18: Années | D18: =IF($C$6<D$3,$C$6,D$3) | E18: =IF(D18=0,0,IF(D18-1<E$3,D18-1,E$3)) | F18: =IF(E18=0,0,IF(E18-1<F$3,E18-1,F$3)) | G18: =IF(F18=0,0,IF(F18-1<G$3,F18-1,G$3)) | H18: =IF(G18=0,0,IF(G18-1<H$3,G18-1,H$3)) | I18: =IF(H18=0,0,IF(H18-1<I$3,H18-1,I$3)) | J18: =IF(I18=0,0,IF(I18-1<J$3,I18-1,J$3)) | K18: =IF(J18=0,0,IF(J18-1<K$3,J18-1,K$3)) | L18: =IF(K18=0,0,IF(K18-1<L$3,K18-1,L$3)) | M18: =IF(L18=0,0,IF(L18-1<M$3,L18-1,M$3))
A19: Base amortissable | B19: USD | D19: =Modèle!D$9 | E19: =D23 | F19: =E23 | G19: =F23 | H19: =G23 | I19: =H23 | J19: =I23 | K19: =J23 | L19: =K23 | M19: =L23
A20: Inverse de la durée restante | B20: % | D20: =IF(D18=0,0,1/D18) | E20: =IF(E18=0,0,1/E18) | F20: =IF(F18=0,0,1/F18) | G20: =IF(G18=0,0,1/G18) | H20: =IF(H18=0,0,1/H18) | I20: =IF(I18=0,0,1/I18) | J20: =IF(J18=0,0,1/J18) | K20: =IF(K18=0,0,1/K18) | ... M20: =IF(M18=0,0,1/M18)
A21: Taux dégressif | B21: % | D21: =IF(D18=0,0,IF($C$7*1/$C$6>D20,$C$7*1/$C$6,D20)) | E21: =IF(E18=0,0,IF($C$7*1/$C$6>E20,$C$7*1/$C$6,E20)) | F21: =IF(F18=0,0,IF($C$7*1/$C$6>F20,$C$7*1/$C$6,F20)) | G21: =IF(G18=0,0,IF($C$7*1/$C$6>G20,$C$7*1/$C$6,G20)) | H21: =IF(H18=0,0,IF($C$7*1/$C$6>H20,$C$7*1/$C$6,H20)) | I21: =IF(I18=0,0,IF($C$7*1/$C$6>I20,$C$7*1/$C$6,I20)) | J21: =IF(J18=0,0,IF($C$7*1/$C$6>J20,$C$7*1/$C$6,J20)) | K21: =IF(K18=0,0,IF($C$7*1/$C$6>K20,$C$7*1/$C$6,K20)) | ... M21: =IF(M18=0,0,IF($C$7*1/$C$6>M20,$C$7*1/$C$6,M20))
A22: Charge d'amortissement | B22: USD | D22: =D19*D21 | E22: =E19*E21 | F22: =F19*F21 | G22: =G19*G21 | H22: =H19*H21 | I22: =I19*I21 | J22: =J19*J21 | K22: =K19*K21 | ... M22: =M19*M21
A23: Amortissement restant | B23: USD | D23: =D19-D22 | E23: =E19-E22 | F23: =F19-F22 | G23: =G19-G22 | H23: =H19-H22 | I23: =I19-I22 | J23: =J19-J22 | K23: =K19-K22 | ... M23: =M19-M22
A25: Amortissements des constructions industrielles | B25: USD | C25: =C$14+C$22 | D25: =D$14+D$22 | E25: =E$14+E$22 | F25: =F$14+F$22 | G25: =G$14+G$22 | H25: =H$14+H$22 | I25: =I$14+I$22 | J25: =J$14+J$22 | ... M25: =M$14+M$22
A27: II. AMORTISSEMENTS DES BIENS D'EQUIPEMENT
A28: Durée d'amortissement linéaire | B28: Années | C28: 5
A29: Coefficient d'amortissement dégressif | B29: Coefficient | C29: 2
A31: Immobilisations de l'année A1
A32: Durée restante | B32: Années | C32: =IF($C$28<C$3,$C$28,C$3) | D32: =IF(C32=0,0,IF(C32-1<D$3,C32-1,D$3)) | E32: =IF(D32=0,0,IF(D32-1<E$3,D32-1,E$3)) | F32: =IF(E32=0,0,IF(E32-1<F$3,E32-1,F$3)) | G32: =IF(F32=0,0,IF(F32-1<G$3,F32-1,G$3)) | H32: =IF(G32=0,0,IF(G32-1<H$3,G32-1,H$3)) | I32: =IF(H32=0,0,IF(H32-1<I$3,H32-1,I$3)) | J32: =IF(I32=0,0,IF(I32-1<J$3,I32-1,J$3)) | K32: =IF(J32=0,0,IF(J32-1<K$3,J32-1,K$3)) | ... M32: =IF(L32=0,0,IF(L32-1<M$3,L32-1,M$3))
A33: Base amortissable | B33: USD | C33: =Modèle!C$10 | D33: =C37 | E33: =D37 | F33: =E37 | G33: =F37 | H33: =G37 | I33: =H37 | J33: =I37 | K33: =J37 | ... M33: =L37
A34: Inverse de la durée restante | B34: % | C34: =IF(C32=0,0,1/C32) | D34: =IF(D32=0,0,1/D32) | E34: =IF(E32=0,0,1/E32) | F34: =IF(F32=0,0,1/F32) | G34: =IF(G32=0,0,1/G32) | H34: =IF(H32=0,0,1/H32) | I34: =IF(I32=0,0,1/I32) | J34: =IF(J32=0,0,1/J32) | ... M34: =IF(M32=0,0,1/M32)
A35: Taux dégressif | B35: % | C35: =IF(C32=0,0,IF($C$29*1/$C$28>C34,$C$29*1/$C$28,C34)) | D35: =IF(D32=0,0,IF($C$29*1/$C$28>D34,$C$29*1/$C$28,D34)) | E35: =IF(E32=0,0,IF($C$29*1/$C$28>E34,$C$29*1/$C$28,E34)) | F35: =IF(F32=0,0,IF($C$29*1/$C$28>F34,$C$29*1/$C$28,F34)) | G35: =IF(G32=0,0,IF($C$29*1/$C$28>G34,$C$29*1/$C$28,G34)) | H35: =IF(H32=0,0,IF($C$29*1/$C$28>H34,$C$29*1/$C$28,H34)) | I35: =IF(I32=0,0,IF($C$29*1/$C$28>I34,$C$29*1/$C$28,I34)) | J35: =IF(J32=0,0,IF($C$29*1/$C$28>J34,$C$29*1/$C$28,J34)) | ... M35: =IF(M32=0,0,IF($C$29*1/$C$28>M34,$C$29*1/$C$28,M34))
A36: Charge d'amortissement | B36: USD | C36: =C33*C35 | D36: =D33*D35 | E36: =E33*E35 | F36: =F33*F35 | G36: =G33*G35 | H36: =H33*H35 | I36: =I33*I35 | J36: =J33*J35 | ... M36: =M33*M35
A37: Amortissement restant | B37: USD | C37: =C33-C36 | D37: =D33-D36 | E37: =E33-E36 | F37: =F33-F36 | G37: =G33-G36 | H37: =H33-H36 | I37: =I33-I36 | J37: =J33-J36 | ... M37: =M33-M36
A39: Immobilisations de l'année A2
A40: Durée restante | B40: Années | D40: =IF($C$28<D$3,$C$28,D$3) | E40: =IF(D40=0,0,IF(D40-1<E$3,D40-1,E$3)) | F40: =IF(E40=0,0,IF(E40-1<F$3,E40-1,F$3)) | G40: =IF(F40=0,0,IF(F40-1<G$3,F40-1,G$3)) | H40: =IF(G40=0,0,IF(G40-1<H$3,G40-1,H$3)) | I40: =IF(H40=0,0,IF(H40-1<I$3,H40-1,I$3)) | J40: =IF(I40=0,0,IF(I40-1<J$3,I40-1,J$3)) | K40: =IF(J40=0,0,IF(J40-1<K$3,J40-1,K$3)) | L40: =IF(K40=0,0,IF(K40-1<L$3,K40-1,L$3)) | M40: =IF(L40=0,0,IF(L40-1<M$3,L40-1,M$3))
A41: Base amortissable | B41: USD | D41: =Modèle!D$10 | E41: =D45 | F41: =E45 | G41: =F45 | H41: =G45 | I41: =H45 | J41: =I45 | K41: =J45 | L41: =K45 | M41: =L45
A42: Inverse de la durée restante | B42: % | D42: =IF(D40=0,0,1/D40) | E42: =IF(E40=0,0,1/E40) | F42: =IF(F40=0,0,1/F40) | G42: =IF(G40=0,0,1/G40) | H42: =IF(H40=0,0,1/H40) | I42: =IF(I40=0,0,1/I40) | J42: =IF(J40=0,0,1/J40) | K42: =IF(K40=0,0,1/K40) | ... M42: =IF(M40=0,0,1/M40)
A43: Taux dégressif | B43: % | D43: =IF(D40=0,0,IF($C$29*1/$C$28>D42,$C$29*1/$C$28,D42)) | E43: =IF(E40=0,0,IF($C$29*1/$C$28>E42,$C$29*1/$C$28,E42)) | F43: =IF(F40=0,0,IF($C$29*1/$C$28>F42,$C$29*1/$C$28,F42)) | G43: =IF(G40=0,0,IF($C$29*1/$C$28>G42,$C$29*1/$C$28,G42)) | H43: =IF(H40=0,0,IF($C$29*1/$C$28>H42,$C$29*1/$C$28,H42)) | I43: =IF(I40=0,0,IF($C$29*1/$C$28>I42,$C$29*1/$C$28,I42)) | J43: =IF(J40=0,0,IF($C$29*1/$C$28>J42,$C$29*1/$C$28,J42)) | K43: =IF(K40=0,0,IF($C$29*1/$C$28>K42,$C$29*1/$C$28,K42)) | ... M43: =IF(M40=0,0,IF($C$29*1/$C$28>M42,$C$29*1/$C$28,M42))
A44: Charge d'amortissement | B44: USD | D44: =D41*D43 | E44: =E41*E43 | F44: =F41*F43 | G44: =G41*G43 | H44: =H41*H43 | I44: =I41*I43 | J44: =J41*J43 | K44: =K41*K43 | ... M44: =M41*M43
A45: Amortissement restant | B45: USD | D45: =D41-D44 | E45: =E41-E44 | F45: =F41-F44 | G45: =G41-G44 | H45: =H41-H44 | I45: =I41-I44 | J45: =J41-J44 | K45: =K41-K44 | ... M45: =M41-M44
A47: Immobilisations de l'année A3
A48: Durée restante | B48: Années | E48: =IF($C$28<E$3,$C$28,E$3) | F48: =IF(E48=0,0,IF(E48-1<F$3,E48-1,F$3)) | G48: =IF(F48=0,0,IF(F48-1<G$3,F48-1,G$3)) | H48: =IF(G48=0,0,IF(G48-1<H$3,G48-1,H$3)) | I48: =IF(H48=0,0,IF(H48-1<I$3,H48-1,I$3)) | J48: =IF(I48=0,0,IF(I48-1<J$3,I48-1,J$3)) | K48: =IF(J48=0,0,IF(J48-1<K$3,J48-1,K$3)) | L48: =IF(K48=0,0,IF(K48-1<L$3,K48-1,L$3)) | M48: =IF(L48=0,0,IF(L48-1<M$3,L48-1,M$3))
A49: Base amortissable | B49: USD | E49: =Modèle!E$10 | F49: =E53 | G49: =F53 | H49: =G53 | I49: =H53 | J49: =I53 | K49: =J53 | L49: =K53 | M49: =L53
A50: Inverse de la durée restante | B50: % | E50: =IF(E48=0,0,1/E48) | F50: =IF(F48=0,0,1/F48) | G50: =IF(G48=0,0,1/G48) | H50: =IF(H48=0,0,1/H48) | I50: =IF(I48=0,0,1/I48) | J50: =IF(J48=0,0,1/J48) | K50: =IF(K48=0,0,1/K48) | L50: =IF(L48=0,0,1/L48) | M50: =IF(M48=0,0,1/M48)
A51: Taux dégressif | B51: % | E51: =IF(E48=0,0,IF($C$29*1/$C$28>E50,$C$29*1/$C$28,E50)) | F51: =IF(F48=0,0,IF($C$29*1/$C$28>F50,$C$29*1/$C$28,F50)) | G51: =IF(G48=0,0,IF($C$29*1/$C$28>G50,$C$29*1/$C$28,G50)) | H51: =IF(H48=0,0,IF($C$29*1/$C$28>H50,$C$29*1/$C$28,H50)) | I51: =IF(I48=0,0,IF($C$29*1/$C$28>I50,$C$29*1/$C$28,I50)) | J51: =IF(J48=0,0,IF($C$29*1/$C$28>J50,$C$29*1/$C$28,J50)) | K51: =IF(K48=0,0,IF($C$29*1/$C$28>K50,$C$29*1/$C$28,K50)) | L51: =IF(L48=0,0,IF($C$29*1/$C$28>L50,$C$29*1/$C$28,L50)) | M51: =IF(M48=0,0,IF($C$29*1/$C$28>M50,$C$29*1/$C$28,M50))
A52: Charge d'amortissement | B52: USD | E52: =E49*E51 | F52: =F49*F51 | G52: =G49*G51 | H52: =H49*H51 | I52: =I49*I51 | J52: =J49*J51 | K52: =K49*K51 | L52: =L49*L51 | M52: =M49*M51
A53: Amortissement restant | B53: USD | E53: =E49-E52 | F53: =F49-F52 | G53: =G49-G52 | H53: =H49-H52 | I53: =I49-I52 | J53: =J49-J52 | K53: =K49-K52 | L53: =L49-L52 | M53: =M49-M52
A55: Immobilisations de l'année A4
A56: Durée restante | B56: Années | F56: =IF($C$28<F$3,$C$28,F$3) | G56: =IF(F56=0,0,IF(F56-1<G$3,F56-1,G$3)) | H56: =IF(G56=0,0,IF(G56-1<H$3,G56-1,H$3)) | I56: =IF(H56=0,0,IF(H56-1<I$3,H56-1,I$3)) | J56: =IF(I56=0,0,IF(I56-1<J$3,I56-1,J$3)) | K56: =IF(J56=0,0,IF(J56-1<K$3,J56-1,K$3)) | L56: =IF(K56=0,0,IF(K56-1<L$3,K56-1,L$3)) | M56: =IF(L56=0,0,IF(L56-1<M$3,L56-1,M$3))
A57: Base amortissable | B57: USD | F57: =Modèle!F$10 | G57: =F61 | H57: =G61 | I57: =H61 | J57: =I61 | K57: =J61 | L57: =K61 | M57: =L61
A58: Inverse de la durée restante | B58: % | F58: =IF(F56=0,0,1/F56) | G58: =IF(G56=0,0,1/G56) | H58: =IF(H56=0,0,1/H56) | I58: =IF(I56=0,0,1/I56) | J58: =IF(J56=0,0,1/J56) | K58: =IF(K56=0,0,1/K56) | L58: =IF(L56=0,0,1/L56) | M58: =IF(M56=0,0,1/M56)
A59: Taux dégressif | B59: % | F59: =IF(F56=0,0,IF($C$29*1/$C$28>F58,$C$29*1/$C$28,F58)) | G59: =IF(G56=0,0,IF($C$29*1/$C$28>G58,$C$29*1/$C$28,G58)) | H59: =IF(H56=0,0,IF($C$29*1/$C$28>H58,$C$29*1/$C$28,H58)) | I59: =IF(I56=0,0,IF($C$29*1/$C$28>I58,$C$29*1/$C$28,I58)) | J59: =IF(J56=0,0,IF($C$29*1/$C$28>J58,$C$29*1/$C$28,J58)) | K59: =IF(K56=0,0,IF($C$29*1/$C$28>K58,$C$29*1/$C$28,K58)) | L59: =IF(L56=0,0,IF($C$29*1/$C$28>L58,$C$29*1/$C$28,L58)) | M59: =IF(M56=0,0,IF($C$29*1/$C$28>M58,$C$29*1/$C$28,M58))
A60: Charge d'amortissement | B60: USD | F60: =F57*F59 | G60: =G57*G59 | H60: =H57*H59 | I60: =I57*I59 | J60: =J57*J59 | K60: =K57*K59 | L60: =L57*L59 | M60: =M57*M59
A61: Amortissement restant | B61: USD | F61: =F57-F60 | G61: =G57-G60 | H61: =H57-H60 | I61: =I57-I60 | J61: =J57-J60 | K61: =K57-K60 | L61: =L57-L60 | M61: =M57-M60
A63: Immobilisations de l'année A5
A64: Durée restante | B64: Années | G64: =IF($C$28<G$3,$C$28,G$3) | H64: =IF(G64=0,0,IF(G64-1<H$3,G64-1,H$3)) | I64: =IF(H64=0,0,IF(H64-1<I$3,H64-1,I$3)) | J64: =IF(I64=0,0,IF(I64-1<J$3,I64-1,J$3)) | K64: =IF(J64=0,0,IF(J64-1<K$3,J64-1,K$3)) | L64: =IF(K64=0,0,IF(K64-1<L$3,K64-1,L$3)) | M64: =IF(L64=0,0,IF(L64-1<M$3,L64-1,M$3))
A65: Base amortissable | B65: USD | G65: =Modèle!G$10 | H65: =G69 | I65: =H69 | J65: =I69 | K65: =J69 | L65: =K69 | M65: =L69
A66: Inverse de la durée restante | B66: % | G66: =IF(G64=0,0,1/G64) | H66: =IF(H64=0,0,1/H64) | I66: =IF(I64=0,0,1/I64) | J66: =IF(J64=0,0,1/J64) | K66: =IF(K64=0,0,1/K64) | L66: =IF(L64=0,0,1/L64) | M66: =IF(M64=0,0,1/M64)
A67: Taux dégressif | B67: % | G67: =IF(G64=0,0,IF($C$29*1/$C$28>G66,$C$29*1/$C$28,G66)) | H67: =IF(H64=0,0,IF($C$29*1/$C$28>H66,$C$29*1/$C$28,H66)) | I67: =IF(I64=0,0,IF($C$29*1/$C$28>I66,$C$29*1/$C$28,I66)) | J67: =IF(J64=0,0,IF($C$29*1/$C$28>J66,$C$29*1/$C$28,J66)) | K67: =IF(K64=0,0,IF($C$29*1/$C$28>K66,$C$29*1/$C$28,K66)) | L67: =IF(L64=0,0,IF($C$29*1/$C$28>L66,$C$29*1/$C$28,L66)) | M67: =IF(M64=0,0,IF($C$29*1/$C$28>M66,$C$29*1/$C$28,M66))
A68: Charge d'amortissement | B68: USD | G68: =G65*G67 | H68: =H65*H67 | I68: =I65*I67 | J68: =J65*J67 | K68: =K65*K67 | L68: =L65*L67 | M68: =M65*M67
A69: Amortissement restant | B69: USD | G69: =G65-G68 | H69: =H65-H68 | I69: =I65-I68 | J69: =J65-J68 | K69: =K65-K68 | L69: =L65-L68 | M69: =M65-M68
A71: Immobilisations de l'année A6
A72: Durée restante | B72: Années | H72: =IF($C$28<H$3,$C$28,H$3) | I72: =IF(H72=0,0,IF(H72-1<I$3,H72-1,I$3)) | J72: =IF(I72=0,0,IF(I72-1<J$3,I72-1,J$3)) | K72: =IF(J72=0,0,IF(J72-1<K$3,J72-1,K$3)) | L72: =IF(K72=0,0,IF(K72-1<L$3,K72-1,L$3)) | M72: =IF(L72=0,0,IF(L72-1<M$3,L72-1,M$3))
A73: Base amortissable | B73: USD | H73: =Modèle!H$10 | I73: =H77 | J73: =I77 | K73: =J77 | L73: =K77 | M73: =L77
A74: Inverse de la durée restante | B74: % | H74: =IF(H72=0,0,1/H72) | I74: =IF(I72=0,0,1/I72) | J74: =IF(J72=0,0,1/J72) | K74: =IF(K72=0,0,1/K72) | L74: =IF(L72=0,0,1/L72) | M74: =IF(M72=0,0,1/M72)
A75: Taux dégressif | B75: % | H75: =IF(H72=0,0,IF($C$29*1/$C$28>H74,$C$29*1/$C$28,H74)) | I75: =IF(I72=0,0,IF($C$29*1/$C$28>I74,$C$29*1/$C$28,I74)) | J75: =IF(J72=0,0,IF($C$29*1/$C$28>J74,$C$29*1/$C$28,J74)) | K75: =IF(K72=0,0,IF($C$29*1/$C$28>K74,$C$29*1/$C$28,K74)) | L75: =IF(L72=0,0,IF($C$29*1/$C$28>L74,$C$29*1/$C$28,L74)) | M75: =IF(M72=0,0,IF($C$29*1/$C$28>M74,$C$29*1/$C$28,M74))
A76: Charge d'amortissement | B76: USD | H76: =H73*H75 | I76: =I73*I75 | J76: =J73*J75 | K76: =K73*K75 | L76: =L73*L75 | M76: =M73*M75
A77: Amortissement restant | B77: USD | H77: =H73-H76 | I77: =I73-I76 | J77: =J73-J76 | K77: =K73-K76 | L77: =L73-L76 | M77: =M73-M76
A79: Immobilisations de l'année A7
A80: Durée restante | B80: Années | I80: =IF($C$28<I$3,$C$28,I$3) | J80: =IF(I80=0,0,IF(I80-1<J$3,I80-1,J$3)) | K80: =IF(J80=0,0,IF(J80-1<K$3,J80-1,K$3)) | L80: =IF(K80=0,0,IF(K80-1<L$3,K80-1,L$3)) | M80: =IF(L80=0,0,IF(L80-1<M$3,L80-1,M$3))
A81: Base amortissable | B81: USD | I81: =Modèle!I$10 | J81: =I85 | K81: =J85 | L81: =K85 | M81: =L85
A82: Inverse de la durée restante | B82: % | I82: =IF(I80=0,0,1/I80) | J82: =IF(J80=0,0,1/J80) | K82: =IF(K80=0,0,1/K80) | L82: =IF(L80=0,0,1/L80) | M82: =IF(M80=0,0,1/M80)
A83: Taux dégressif | B83: % | I83: =IF(I80=0,0,IF($C$29*1/$C$28>I82,$C$29*1/$C$28,I82)) | J83: =IF(J80=0,0,IF($C$29*1/$C$28>J82,$C$29*1/$C$28,J82)) | K83: =IF(K80=0,0,IF($C$29*1/$C$28>K82,$C$29*1/$C$28,K82)) | L83: =IF(L80=0,0,IF($C$29*1/$C$28>L82,$C$29*1/$C$28,L82)) | M83: =IF(M80=0,0,IF($C$29*1/$C$28>M82,$C$29*1/$C$28,M82))
A84: Charge d'amortissement | B84: USD | I84: =I81*I83 | J84: =J81*J83 | K84: =K81*K83 | L84: =L81*L83 | M84: =M81*M83
A85: Amortissement restant | B85: USD | I85: =I81-I84 | J85: =J81-J84 | K85: =K81-K84 | L85: =L81-L84 | M85: =M81-M84
A87: Immobilisations de l'année A8
A88: Durée restante | B88: Années | J88: =IF($C$28<J$3,$C$28,J$3) | K88: =IF(J88=0,0,IF(J88-1<K$3,J88-1,K$3)) | L88: =IF(K88=0,0,IF(K88-1<L$3,K88-1,L$3)) | M88: =IF(L88=0,0,IF(L88-1<M$3,L88-1,M$3))
A89: Base amortissable | B89: USD | J89: =Modèle!J$10 | K89: =J93 | L89: =K93 | M89: =L93
A90: Inverse de la durée restante | B90: % | J90: =IF(J88=0,0,1/J88) | K90: =IF(K88=0,0,1/K88) | L90: =IF(L88=0,0,1/L88) | M90: =IF(M88=0,0,1/M88)
A91: Taux dégressif | B91: % | J91: =IF(J88=0,0,IF($C$29*1/$C$28>J90,$C$29*1/$C$28,J90)) | K91: =IF(K88=0,0,IF($C$29*1/$C$28>K90,$C$29*1/$C$28,K90)) | L91: =IF(L88=0,0,IF($C$29*1/$C$28>L90,$C$29*1/$C$28,L90)) | M91: =IF(M88=0,0,IF($C$29*1/$C$28>M90,$C$29*1/$C$28,M90))
A92: Charge d'amortissement | B92: USD | J92: =J89*J91 | K92: =K89*K91 | L92: =L89*L91 | M92: =M89*M91
A93: Amortissement restant | B93: USD | J93: =J89-J92 | K93: =K89-K92 | L93: =L89-L92 | M93: =M89-M92
A95: Immobilisations de l'année A9
A96: Durée restante | B96: Années | K96: =IF($C$28<K$3,$C$28,K$3) | L96: =IF(K96=0,0,IF(K96-1<L$3,K96-1,L$3)) | M96: =IF(L96=0,0,IF(L96-1<M$3,L96-1,M$3))
A97: Base amortissable | B97: USD | K97: =Modèle!K$10 | L97: =K101 | M97: =L101
A98: Inverse de la durée restante | B98: % | K98: =IF(K96=0,0,1/K96) | L98: =IF(L96=0,0,1/L96) | M98: =IF(M96=0,0,1/M96)
A99: Taux dégressif | B99: % | K99: =IF(K96=0,0,IF($C$29*1/$C$28>K98,$C$29*1/$C$28,K98)) | L99: =IF(L96=0,0,IF($C$29*1/$C$28>L98,$C$29*1/$C$28,L98)) | M99: =IF(M96=0,0,IF($C$29*1/$C$28>M98,$C$29*1/$C$28,M98))
A100: Charge d'amortissement | B100: USD | K100: =K97*K99 | L100: =L97*L99 | M100: =M97*M99
A101: Amortissement restant | B101: USD | K101: =K97-K100 | L101: =L97-L100 | M101: =M97-M100
A103: Immobilisations de l'année A10
A104: Durée restante | B104: Années | L104: =IF($C$28<L$3,$C$28,L$3) | M104: =IF(L104=0,0,IF(L104-1<M$3,L104-1,M$3))
A105: Base amortissable | B105: USD | L105: =Modèle!L$10 | M105: =L109
A106: Inverse de la durée restante | B106: % | L106: =IF(L104=0,0,1/L104) | M106: =IF(M104=0,0,1/M104)
A107: Taux dégressif | B107: % | L107: =IF(L104=0,0,IF($C$29*1/$C$28>L106,$C$29*1/$C$28,L106)) | M107: =IF(M104=0,0,IF($C$29*1/$C$28>M106,$C$29*1/$C$28,M106))
A108: Charge d'amortissement | B108: USD | L108: =L105*L107 | M108: =M105*M107
A109: Amortissement restant | B109: USD | L109: =L105-L108 | M109: =M105-M108
A111: Immobilisations de l'année A11
A112: Durée restante | B112: Années | M112: =IF($C$28<M$3,$C$28,M$3)
A113: Base amortissable | B113: USD | M113: =Modèle!M$10
A114: Inverse de la durée restante | B114: % | M114: =IF(M112=0,0,1/M112)
A115: Taux dégressif | B115: % | M115: =IF(M112=0,0,IF($C$29*1/$C$28>M114,$C$29*1/$C$28,M114))
A116: Charge d'amortissement | B116: USD | M116: =M113*M115
A117: Amortissement restant | B117: USD | M117: =M113-M116
...

Sheet 08_08_Taxe_sur__1
A1: Nom | B1: Unité | C1: Année 1 | D1: Année 2 | E1: Année 3 | F1: Année 4 | G1: Année 5 | H1: Année 6 | I1: Année 7 | J1: Année 8 | K1: Année 9 | L1: Année 10 | M1: Année 11 | N1: SOMME | O1: VAN
A3: I. PRODUCTION
A4: Production d'or | B4: oz | E4: 250000 | F4: 250000 | G4: 250000 | H4: 250000 | I4: 250000 | J4: 250000 | K4: 250000 | L4: 250000 | N4: =SUM($C4:$M4)
A5: Cours de l'or | B5: USD/oz | E5: 1300 | F5: 1300 | G5: 1300 | H5: 1300 | I5: 1300 | J5: 1300 | K5: 1300 | L5: 1300
A6: Chiffre d'affaires | B6: USD | C6: =C$4*C$5 | D6: =D$4*D$5 | E6: =E$4*E$5 | F6: =F$4*F$5 | G6: =G$4*G$5 | H6: =H$4*H$5 | I6: =I$4*I$5 | J6: =J$4*J$5 | ... M6: =M$4*M$5 | N6: =SUM($C6:$M6) | O6: =$C6+NPV(10%,$D6:$M6)
A8: II. DEPENSES D'INVESTISSEMENT (CAPEX)
A9: Coûts des construction industrielles | B9: USD | C9: 50000000 | D9: 100000000 | N9: =SUM($C9:$M9) | O9: =$C9+NPV(10%,$D9:$M9)
A10: Coûts des biens d'équipement | B10: USD | D10: 50000000 | E10: 5000000 | F10: 5000000 | G10: 5000000 | H10: 5000000 | I10: 5000000 | J10: 5000000 | K10: 5000000 | L10: 5000000 | N10: =SUM($C10:$M10) | O10: =$C10+NPV(10%,$D10:$M10)
A11: Coûts de réhabilitation du site | B11: USD | M11: 10000000 | N11: =SUM($C11:$M11) | O11: =$C11+NPV(10%,$D11:$M11)
A12: Total des dépenses d'investissement | B12: USD | C12: =SUM(C$9:C$11) | D12: =SUM(D$9:D$11) | E12: =SUM(E$9:E$11) | F12: =SUM(F$9:F$11) | G12: =SUM(G$9:G$11) | H12: =SUM(H$9:H$11) | I12: =SUM(I$9:I$11) | J12: =SUM(J$9:J$11) | ... M12: =SUM(M$9:M$11) | N12: =SUM($C12:$M12) | O12: =$C12+NPV(10%,$D12:$M12)
A14: III. COÛTS D'EXPLOITATION (OPEX)
A15: Coût moyen d'exploitation | B15: USD/oz | E15: 700 | F15: 700 | G15: 700 | H15: 700 | I15: 700 | J15: 700 | K15: 700 | L15: 700
A16: Total des coûts d'exploitation | B16: USD | C16: =C$4*C$15 | D16: =D$4*D$15 | E16: =E$4*E$15 | F16: =F$4*F$15 | G16: =G$4*G$15 | H16: =H$4*H$15 | I16: =I$4*I$15 | J16: =J$4*J$15 | ... M16: =M$4*M$15 | N16: =SUM($C16:$M16) | O16: =$C16+NPV(10%,$D16:$M16)
A18: IV. FLUX NETS DE TRESORERIE AVANT IMPÔTS
A19: Flux nets de trésorerie avant impôts | B19: USD | C19: =C$6-C$12-C$16 | D19: =D$6-D$12-D$16 | E19: =E$6-E$12-E$16 | F19: =F$6-F$12-F$16 | G19: =G$6-G$12-G$16 | H19: =H$6-H$12-H$16 | I19: =I$6-I$12-I$16 | J19: =J$6-J$12-J$16 | ... M19: =M$6-M$12-M$16 | N19: =SUM($C19:$M19) | O19: =$C19+NPV(10%,$D19:$M19)
A20: Taux de rendement interne avant impôts | B20: % | C20: =IF(ISNUMBER(IRR($C19:C19)),IF(IRR($C19:C19)>0,IRR($C19:C19),""),"") | D20: =IF(ISNUMBER(IRR($C19:D19)),IF(IRR($C19:D19)>0,IRR($C19:D19),""),"") | E20: =IF(ISNUMBER(IRR($C19:E19)),IF(IRR($C19:E19)>0,IRR($C19:E19),""),"") | F20: =IF(ISNUMBER(IRR($C19:F19)),IF(IRR($C19:F19)>0,IRR($C19:F19),""),"") | G20: =IF(ISNUMBER(IRR($C19:G19)),IF(IRR($C19:G19)>0,IRR($C19:G19),""),"") | H20: =IF(ISNUMBER(IRR($C19:H19)),IF(IRR($C19:H19)>0,IRR($C19:H19),""),"") | I20: =IF(ISNUMBER(IRR($C19:I19)),IF(IRR($C19:I19)>0,IRR($C19:I19),""),"") | J20: =IF(ISNUMBER(IRR($C19:J19)),IF(IRR($C19:J19)>0,IRR($C19:J19),""),"") | ... M20: =IF(ISNUMBER(IRR($C19:M19)),IF(IRR($C19:M19)>0,IRR($C19:M19),""),"")
A22: V. DROITS FIXES
A23: Droits fixes | B23: USD | C23: 100000 | N23: =SUM($C23:$M23) | O23: =$C23+NPV(10%,$D23:$M23)
A25: VI. REDEVANCE SUPERFICAIRE
A26: Superficie de la mine | B26: km² | C26: 100 | D26: 100 | E26: 100 | F26: 100 | G26: 100 | H26: 100 | I26: 100 | J26: 100 | K26: 100 | L26: 100 | M26: 100
A27: Montant de la redevance superfiaire | B27: USD/km² | C27: 100 | D27: 100 | E27: 100 | F27: 100 | G27: 100 | H27: 100 | I27: 100 | J27: 100 | K27: 100 | L27: 100 | M27: 100
A28: Redevance superficiaire | B28: USD | C28: =C$26*C$27 | D28: =D$26*D$27 | E28: =E$26*E$27 | F28: =F$26*F$27 | G28: =G$26*G$27 | H28: =H$26*H$27 | I28: =I$26*I$27 | J28: =J$26*J$27 | ... M28: =M$26*M$27 | N28: =SUM($C28:$M28) | O28: =$C28+NPV(10%,$D28:$M28)
A30: VII. REDEVANCE MINIERE
A31: Taux de la redevance minière | B31: % | C31: =IF(ISNUMBER(C5),IF(C$5<1300,3%,IF(C$5<1500,4%,5%)),"") | D31: =IF(ISNUMBER(D5),IF(D$5<1300,3%,IF(D$5<1500,4%,5%)),"") | E31: =IF(ISNUMBER(E5),IF(E$5<1300,3%,IF(E$5<1500,4%,5%)),"") | F31: =IF(ISNUMBER(F5),IF(F$5<1300,3%,IF(F$5<1500,4%,5%)),"") | G31: =IF(ISNUMBER(G5),IF(G$5<1300,3%,IF(G$5<1500,4%,5%)),"") | H31: =IF(ISNUMBER(H5),IF(H$5<1300,3%,IF(H$5<1500,4%,5%)),"") | I31: =IF(ISNUMBER(I5),IF(I$5<1300,3%,IF(I$5<1500,4%,5%)),"") | J31: =IF(ISNUMBER(J5),IF(J$5<1300,3%,IF(J$5<1500,4%,5%)),"") | ... M31: =IF(ISNUMBER(M5),IF(M$5<1300,3%,IF(M$5<1500,4%,5%)),"")
A32: Redevance minière | B32: USD | C32: =IF(ISNUMBER(C31),C$6*C$31,0) | D32: =IF(ISNUMBER(D31),D$6*D$31,0) | E32: =IF(ISNUMBER(E31),E$6*E$31,0) | F32: =IF(ISNUMBER(F31),F$6*F$31,0) | G32: =IF(ISNUMBER(G31),G$6*G$31,0) | H32: =IF(ISNUMBER(H31),H$6*H$31,0) | I32: =IF(ISNUMBER(I31),I$6*I$31,0) | J32: =IF(ISNUMBER(J31),J$6*J$31,0) | ... M32: =IF(ISNUMBER(M31),M$6*M$31,0) | N32: =SUM($C32:$M32) | O32: =$C32+NPV(10%,$D32:$M32)
A34: +. LA TAXE SUR LA RENTE
A35: Taux de revalorisation des pertes | B35: % | C35: 0.02 | D35: 0.02 | E35: 0.02 | F35: 0.02 | G35: 0.02 | H35: 0.02 | I35: 0.02 | J35: 0.02 | K35: 0.02 | L35: 0.02 | M35: 0.02
A36: Flux nets de trésorerie revalorisés | B36: USD | C36: =IF(C19<0,C19*(1+C35),C19) | D36: =IF(D19<0,D19*(1+D35),D19) | E36: =IF(E19<0,E19*(1+E35),E19) | F36: =IF(F19<0,F19*(1+F35),F19) | G36: =IF(G19<0,G19*(1+G35),G19) | H36: =IF(H19<0,H19*(1+H35),H19) | I36: =IF(I19<0,I19*(1+I35),I19) | J36: =IF(J19<0,J19*(1+J35),J19) | ... M36: =IF(M19<0,M19*(1+M35),M19) | N36: =SUM($C36:$M36) | O36: =$C36+NPV(10%,$D36:$M36)
A37: Taux de rendement interne | B37: % | C37: =IF(ISNUMBER(IRR($C36:C36)),IF(IRR($C36:C36)>0,IRR($C36:C36),""),"") | D37: =IF(ISNUMBER(IRR($C36:D36)),IF(IRR($C36:D36)>0,IRR($C36:D36),""),"") | E37: =IF(ISNUMBER(IRR($C36:E36)),IF(IRR($C36:E36)>0,IRR($C36:E36),""),"") | F37: =IF(ISNUMBER(IRR($C36:F36)),IF(IRR($C36:F36)>0,IRR($C36:F36),""),"") | G37: =IF(ISNUMBER(IRR($C36:G36)),IF(IRR($C36:G36)>0,IRR($C36:G36),""),"") | H37: =IF(ISNUMBER(IRR($C36:H36)),IF(IRR($C36:H36)>0,IRR($C36:H36),""),"") | I37: =IF(ISNUMBER(IRR($C36:I36)),IF(IRR($C36:I36)>0,IRR($C36:I36),""),"") | J37: =IF(ISNUMBER(IRR($C36:J36)),IF(IRR($C36:J36)>0,IRR($C36:J36),""),"") | ... M37: =IF(ISNUMBER(IRR($C36:M36)),IF(IRR($C36:M36)>0,IRR($C36:M36),""),"")
A38: Seuil de déclenchement de la taxe sur la rente | B38: % | C38: 0.15 | D38: 0.15 | E38: 0.15 | F38: 0.15 | G38: 0.15 | H38: 0.15 | I38: 0.15 | J38: 0.15 | K38: 0.15 | L38: 0.15 | M38: 0.15
A39: Report des pertes revalorisées | D39: =IF(C40<0,C40,0) | E39: =IF(D40<0,D40,0) | F39: =IF(E40<0,E40,0) | G39: =IF(F40<0,F40,0) | H39: =IF(G40<0,G40,0) | I39: =IF(H40<0,H40,0) | J39: =IF(I40<0,I40,0) | K39: =IF(J40<0,J40,0) | ... M39: =IF(L40<0,L40,0)
A40: Flux nets de trésorerie après report des pertes revalorisées | B40: USD | C40: =C36+C39 | D40: =D36+D39 | E40: =E36+E39 | F40: =F36+F39 | G40: =G36+G39 | H40: =H36+H39 | I40: =I36+I39 | J40: =J36+J39 | ... M40: =M36+M39 | N40: =SUM($C40:$M40) | O40: =$C40+NPV(10%,$D40:$M40)
A41: Taux de la taxe sur la rente | B41: % | C41: 0.2 | D41: 0.2 | E41: 0.2 | F41: 0.2 | G41: 0.2 | H41: 0.2 | I41: 0.2 | J41: 0.2 | K41: 0.2 | L41: 0.2 | M41: 0.2
A42: Taxe sur la rente | B42: USD | C42: =IF(C37<C38,0,IF(C40<0,0,C40*C41)) | D42: =IF(D37<D38,0,IF(D40<0,0,D40*D41)) | E42: =IF(E37<E38,0,IF(E40<0,0,E40*E41)) | F42: =IF(F37<F38,0,IF(F40<0,0,F40*F41)) | G42: =IF(G37<G38,0,IF(G40<0,0,G40*G41)) | H42: =IF(H37<H38,0,IF(H40<0,0,H40*H41)) | I42: =IF(I37<I38,0,IF(I40<0,0,I40*I41)) | J42: =IF(J37<J38,0,IF(J40<0,0,J40*J41)) | ... M42: =IF(M37<M38,0,IF(M40<0,0,M40*M41)) | N42: =SUM($C42:$M42) | O42: =$C42+NPV(10%,$D42:$M42)
A44: VIII. IMPÔT SUR LES SOCIETES (IS)
A45: Bénéfice avant report des pertes | B45: USD | C45: =C$6-C$16-C$23-C$28-C$32-C$42-'Amortissements et Emprunt'!C$25-'Amortissements et Emprunt'!C$119-'Amortissements et Emprunt'!C133-'Amortissements et Emprunt'!C$157 | D45: =D$6-D$16-D$23-D$28-D$32-D$42-'Amortissements et Emprunt'!D$25-'Amortissements et Emprunt'!D$119-'Amortissements et Emprunt'!D133-'Amortissements et Emprunt'!D$157 | E45: =E$6-E$16-E$23-E$28-E$32-E$42-'Amortissements et Emprunt'!E$25-'Amortissements et Emprunt'!E$119-'Amortissements et Emprunt'!E133-'Amortissements et Emprunt'!E$157 | F45: =F$6-F$16-F$23-F$28-F$32-F$42-'Amortissements et Emprunt'!F$25-'Amortissements et Emprunt'!F$119-'Amortissements et Emprunt'!F133-'Amortissements et Emprunt'!F$157 | G45: =G$6-G$16-G$23-G$28-G$32-G$42-'Amortissements et Emprunt'!G$25-'Amortissements et Emprunt'!G$119-'Amortissements et Emprunt'!G133-'Amortissements et Emprunt'!G$157 | H45: =H$6-H$16-H$23-H$28-H$32-H$42-'Amortissements et Emprunt'!H$25-'Amortissements et Emprunt'!H$119-'Amortissements et Emprunt'!H133-'Amortissements et Emprunt'!H$157 | I45: =I$6-I$16-I$23-I$28-I$32-I$42-'Amortissements et Emprunt'!I$25-'Amortissements et Emprunt'!I$119-'Amortissements et Emprunt'!I133-'Amortissements et Emprunt'!I$157 | J45: =J$6-J$16-J$23-J$28-J$32-J$42-'Amortissements et Emprunt'!J$25-'Amortissements et Emprunt'!J$119-'Amortissements et Emprunt'!J133-'Amortissements et Emprunt'!J$157 | ... M45: =M$6-M$16-M$23-M$28-M$32-M$42-'Amortissements et Emprunt'!M$25-'Amortissements et Emprunt'!M$119-'Amortissements et Emprunt'!M133-'Amortissements et Emprunt'!M$157 | N45: =SUM($C45:$M45) | O45: =$C45+NPV(10%,$D45:$M45)
A46: Report des pertes | B46: USD | D46: =IF(C47<0,C47,0) | E46: =IF(D47<0,D47,0) | F46: =IF(E47<0,E47,0) | G46: =IF(F47<0,F47,0) | H46: =IF(G47<0,G47,0) | I46: =IF(H47<0,H47,0) | J46: =IF(I47<0,I47,0) | K46: =IF(J47<0,J47,0) | ... M46: =IF(L47<0,L47,0)
A47: Bénéfice fiscal | B47: USD | C47: =C$45+C$46 | D47: =D$45+D$46 | E47: =E$45+E$46 | F47: =F$45+F$46 | G47: =G$45+G$46 | H47: =H$45+H$46 | I47: =I$45+I$46 | J47: =J$45+J$46 | ... M47: =M$45+M$46 | N47: =SUM($C47:$M47) | O47: =$C47+NPV(10%,$D47:$M47)
A48: Taux de l'impôt sur les sociétés | B48: % | C48: 0.3 | D48: 0.3 | E48: 0.3 | F48: 0.3 | G48: 0.3 | H48: 0.3 | I48: 0.3 | J48: 0.3 | K48: 0.3 | L48: 0.3 | M48: 0.3
A49: Impôt sur les sociétés | B49: USD | C49: =IF(C$47>0,C$47*C$48,0) | D49: =IF(D$47>0,D$47*D$48,0) | E49: =IF(E$47>0,E$47*E$48,0) | F49: =IF(F$47>0,F$47*F$48,0) | G49: =IF(G$47>0,G$47*G$48,0) | H49: =IF(H$47>0,H$47*H$48,0) | I49: =IF(I$47>0,I$47*I$48,0) | J49: =IF(J$47>0,J$47*J$48,0) | ... M49: =IF(M$47>0,M$47*M$48,0) | N49: =SUM($C49:$M49) | O49: =$C49+NPV(10%,$D49:$M49)
A51: IX. IMPÔT MINIMUM FORFAITAIRE (IMF)
A52: Montant minimum | B52: USD | C52: 2000 | D52: 2000 | E52: 2000 | F52: 2000 | G52: 2000 | H52: 2000 | I52: 2000 | J52: 2000 | K52: 2000 | L52: 2000 | M52: 2000
A53: Taux de l'impôt minimum forfaitaire | B53: % | C53: 0.01 | D53: 0.01 | E53: 0.01 | F53: 0.01 | G53: 0.01 | H53: 0.01 | I53: 0.01 | J53: 0.01 | K53: 0.01 | L53: 0.01 | M53: 0.01
A54: Impôt minimum forfaitaire | B54: USD | C54: =IF(C$6*C$53>C$52,C$6*C$53,C$52) | D54: =IF(D$6*D$53>D$52,D$6*D$53,D$52) | E54: =IF(E$6*E$53>E$52,E$6*E$53,E$52) | F54: =IF(F$6*F$53>F$52,F$6*F$53,F$52) | G54: =IF(G$6*G$53>G$52,G$6*G$53,G$52) | H54: =IF(H$6*H$53>H$52,H$6*H$53,H$52) | I54: =IF(I$6*I$53>I$52,I$6*I$53,I$52) | J54: =IF(J$6*J$53>J$52,J$6*J$53,J$52) | ... M54: =IF(M$6*M$53>M$52,M$6*M$53,M$52) | N54: =SUM($C54:$M54) | O54: =$C54+NPV(10%,$D54:$M54)
A56: X. IMPÔT SUR LES SOCIETES (IS) / IMPÔT MINIMUM FORFAITAIRE (IMF)
A57: Impôt sur les sociétés / Impôt minimum forfaitaire | B57: USD | C57: =IF(C$54>C$49,C$54,C$49) | D57: =IF(D$54>D$49,D$54,D$49) | E57: =IF(E$54>E$49,E$54,E$49) | F57: =IF(F$54>F$49,F$54,F$49) | G57: =IF(G$54>G$49,G$54,G$49) | H57: =IF(H$54>H$49,H$54,H$49) | I57: =IF(I$54>I$49,I$54,I$49) | J57: =IF(J$54>J$49,J$54,J$49) | ... M57: =IF(M$54>M$49,M$54,M$49) | N57: =SUM($C57:$M57) | O57: =$C57+NPV(10%,$D57:$M57)
A59: XI. PRELEVEMENTS PUBLICS
A60: Total des prélèvements publics | B60: USD | C60: =C$23+C$28+C$32+C$42+C$57 | D60: =D$23+D$28+D$32+D$42+D$57 | E60: =E$23+E$28+E$32+E$42+E$57 | F60: =F$23+F$28+F$32+F$42+F$57 | G60: =G$23+G$28+G$32+G$42+G$57 | H60: =H$23+H$28+H$32+H$42+H$57 | I60: =I$23+I$28+I$32+I$42+I$57 | J60: =J$23+J$28+J$32+J$42+J$57 | ... M60: =M$23+M$28+M$32+M$42+M$57 | N60: =SUM($C60:$M60) | O60: =$C60+NPV(10%,$D60:$M60)
A62: XII. FLUX NETS DE TRESORERIE APRES IMPÔTS
A63: Flux nets de trésorerie après impôts | B63: USD | C63: =C$19-C$60 | D63: =D$19-D$60 | E63: =E$19-E$60 | F63: =F$19-F$60 | G63: =G$19-G$60 | H63: =H$19-H$60 | I63: =I$19-I$60 | J63: =J$19-J$60 | ... M63: =M$19-M$60 | N63: =SUM($C63:$M63) | O63: =$C63+NPV(10%,$D63:$M63)
A64: Taux de rendement interne après impôts | B64: % | C64: =IF(ISNUMBER(IRR($C63:C63)),IF(IRR($C63:C63)>0,IRR($C63:C63),""),"") | D64: =IF(ISNUMBER(IRR($C63:D63)),IF(IRR($C63:D63)>0,IRR($C63:D63),""),"") | E64: =IF(ISNUMBER(IRR($C63:E63)),IF(IRR($C63:E63)>0,IRR($C63:E63),""),"") | F64: =IF(ISNUMBER(IRR($C63:F63)),IF(IRR($C63:F63)>0,IRR($C63:F63),""),"") | G64: =IF(ISNUMBER(IRR($C63:G63)),IF(IRR($C63:G63)>0,IRR($C63:G63),""),"") | H64: =IF(ISNUMBER(IRR($C63:H63)),IF(IRR($C63:H63)>0,IRR($C63:H63),""),"") | I64: =IF(ISNUMBER(IRR($C63:I63)),IF(IRR($C63:I63)>0,IRR($C63:I63),""),"") | J64: =IF(ISNUMBER(IRR($C63:J63)),IF(IRR($C63:J63)>0,IRR($C63:J63),""),"") | ... M64: =IF(ISNUMBER(IRR($C63:M63)),IF(IRR($C63:M63)>0,IRR($C63:M63),""),"")
A66: XIII. PARTAGE DE LA RENTE MINIERE
A67: Rente minière | B67: USD | N67: =N$19 | O67: =O$19
A68: Part de l'Etat | B68: % | N68: =N$60/N$67 | O68: =O$60/O$67
A69: Part de l'investisseur | B69: % | N69: =N$63/N$67 | O69: =O$63/O$67

Sheet 08_08_Taxe_sur__2
A1: Nom | B1: Unité | C1: Année 1 | D1: Année 2 | E1: Année 3 | F1: Année 4 | G1: Année 5 | H1: Année 6 | I1: Année 7 | J1: Année 8 | K1: Année 9 | L1: Année 10 | M1: Année 11
A3: Durée restante maximum | B3: Années | C3: 11 | D3: 10 | E3: 9 | F3: 8 | G3: 7 | H3: 6 | I3: 5 | J3: 4 | K3: 3 | L3: 2 | M3: 1
A5: I. AMORTISSEMENTS DES CONSTRUCTIONS INDUSTRIELLES
A6: Durée d'amortissement linéaire | B6: Années | C6: 10
A7: Coefficient d'amortissement dégressif | B7: Coefficient | C7: 1
A9: Immobilisations de l'année A1
A10: Durée restante | B10: Années | C10: =IF($C$6<C$3,$C$6,C$3) | D10: =IF(C10=0,0,IF(C10-1<D$3,C10-1,D$3)) | E10: =IF(D10=0,0,IF(D10-1<E$3,D10-1,E$3)) | F10: =IF(E10=0,0,IF(E10-1<F$3,E10-1,F$3)) | G10: =IF(F10=0,0,IF(F10-1<G$3,F10-1,G$3)) | H10: =IF(G10=0,0,IF(G10-1<H$3,G10-1,H$3)) | I10: =IF(H10=0,0,IF(H10-1<I$3,H10-1,I$3)) | J10: =IF(I10=0,0,IF(I10-1<J$3,I10-1,J$3)) | K10: =IF(J10=0,0,IF(J10-1<K$3,J10-1,K$3)) | ... M10: =IF(L10=0,0,IF(L10-1<M$3,L10-1,M$3))
A11: Base amortissable | B11: USD | C11: =Modèle!C$9 | D11: =C15 | E11: =D15 | F11: =E15 | G11: =F15 | H11: =G15 | I11: =H15 | J11: =I15 | K11: =J15 | ... M11: =L15
A12: Inverse de la durée restante | B12: % | C12: =IF(C10=0,0,1/C10) | D12: =IF(D10=0,0,1/D10) | E12: =IF(E10=0,0,1/E10) | F12: =IF(F10=0,0,1/F10) | G12: =IF(G10=0,0,1/G10) | H12: =IF(H10=0,0,1/H10) | I12: =IF(I10=0,0,1/I10) | J12: =IF(J10=0,0,1/J10) | ... M12: =IF(M10=0,0,1/M10)
A13: Taux dégressif | B13: % | C13: =IF(C10=0,0,IF($C$7*1/$C$6>C12,$C$7*1/$C$6,C12)) | D13: =IF(D10=0,0,IF($C$7*1/$C$6>D12,$C$7*1/$C$6,D12)) | E13: =IF(E10=0,0,IF($C$7*1/$C$6>E12,$C$7*1/$C$6,E12)) | F13: =IF(F10=0,0,IF($C$7*1/$C$6>F12,$C$7*1/$C$6,F12)) | G13: =IF(G10=0,0,IF($C$7*1/$C$6>G12,$C$7*1/$C$6,G12)) | H13: =IF(H10=0,0,IF($C$7*1/$C$6>H12,$C$7*1/$C$6,H12)) | I13: =IF(I10=0,0,IF($C$7*1/$C$6>I12,$C$7*1/$C$6,I12)) | J13: =IF(J10=0,0,IF($C$7*1/$C$6>J12,$C$7*1/$C$6,J12)) | ... M13: =IF(M10=0,0,IF($C$7*1/$C$6>M12,$C$7*1/$C$6,M12))
A14: Charge d'amortissement | B14: USD | C14: =C11*C13 | D14: =D11*D13 | E14: =E11*E13 | F14: =F11*F13 | G14: =G11*G13 | H14: =H11*H13 | I14: =I11*I13 | J14: =J11*J13 | ... M14: =M11*M13
A15: Amortissement restant | B15: USD | C15: =C11-C14 | D15: =D11-D14 | E15: =E11-E14 | F15: =F11-F14 | G15: =G11-G14 | H15: =H11-H14 | I15: =I11-I14 | J15: =J11-J14 | ... M15: =M11-M14
A17: Immobilisations de l'année A2
A18: Durée restante | B18: Années | D18: =IF($C$6<D$3,$C$6,D$3) | E18: =IF(D18=0,0,IF(D18-1<E$3,D18-1,E$3)) | F18: =IF(E18=0,0,IF(E18-1<F$3,E18-1,F$3)) | G18: =IF(F18=0,0,IF(F18-1<G$3,F18-1,G$3)) | H18: =IF(G18=0,0,IF(G18-1<H$3,G18-1,H$3)) | I18: =IF(H18=0,0,IF(H18-1<I$3,H18-1,I$3)) | J18: =IF(I18=0,0,IF(I18-1<J$3,I18-1,J$3)) | K18: =IF(J18=0,0,IF(J18-1<K$3,J18-1,K$3)) | L18: =IF(K18=0,0,IF(K18-1<L$3,K18-1,L$3)) | M18: =IF(L18=0,0,IF(L18-1<M$3,L18-1,M$3))
A19: Base amortissable | B19: USD | D19: =Modèle!D$9 | E19: =D23 | F19: =E23 | G19: =F23 | H19: =G23 | I19: =H23 | J19: =I23 | K19: =J23 | L19: =K23 | M19: =L23
A20: Inverse de la durée restante | B20: % | D20: =IF(D18=0,0,1/D18) | E20: =IF(E18=0,0,1/E18) | F20: =IF(F18=0,0,1/F18) | G20: =IF(G18=0,0,1/G18) | H20: =IF(H18=0,0,1/H18) | I20: =IF(I18=0,0,1/I18) | J20: =IF(J18=0,0,1/J18) | K20: =IF(K18=0,0,1/K18) | ... M20: =IF(M18=0,0,1/M18)
A21: Taux dégressif | B21: % | D21: =IF(D18=0,0,IF($C$7*1/$C$6>D20,$C$7*1/$C$6,D20)) | E21: =IF(E18=0,0,IF($C$7*1/$C$6>E20,$C$7*1/$C$6,E20)) | F21: =IF(F18=0,0,IF($C$7*1/$C$6>F20,$C$7*1/$C$6,F20)) | G21: =IF(G18=0,0,IF($C$7*1/$C$6>G20,$C$7*1/$C$6,G20)) | H21: =IF(H18=0,0,IF($C$7*1/$C$6>H20,$C$7*1/$C$6,H20)) | I21: =IF(I18=0,0,IF($C$7*1/$C$6>I20,$C$7*1/$C$6,I20)) | J21: =IF(J18=0,0,IF($C$7*1/$C$6>J20,$C$7*1/$C$6,J20)) | K21: =IF(K18=0,0,IF($C$7*1/$C$6>K20,$C$7*1/$C$6,K20)) | ... M21: =IF(M18=0,0,IF($C$7*1/$C$6>M20,$C$7*1/$C$6,M20))
A22: Charge d'amortissement | B22: USD | D22: =D19*D21 | E22: =E19*E21 | F22: =F19*F21 | G22: =G19*G21 | H22: =H19*H21 | I22: =I19*I21 | J22: =J19*J21 | K22: =K19*K21 | ... M22: =M19*M21
A23: Amortissement restant | B23: USD | D23: =D19-D22 | E23: =E19-E22 | F23: =F19-F22 | G23: =G19-G22 | H23: =H19-H22 | I23: =I19-I22 | J23: =J19-J22 | K23: =K19-K22 | ... M23: =M19-M22
A25: Amortissements des constructions industrielles | B25: USD | C25: =C$14+C$22 | D25: =D$14+D$22 | E25: =E$14+E$22 | F25: =F$14+F$22 | G25: =G$14+G$22 | H25: =H$14+H$22 | I25: =I$14+I$22 | J25: =J$14+J$22 | ... M25: =M$14+M$22
A27: II. AMORTISSEMENTS DES BIENS D'EQUIPEMENT
A28: Durée d'amortissement linéaire | B28: Années | C28: 5
A29: Coefficient d'amortissement dégressif | B29: Coefficient | C29: 2
A31: Immobilisations de l'année A1
A32: Durée restante | B32: Années | C32: =IF($C$28<C$3,$C$28,C$3) | D32: =IF(C32=0,0,IF(C32-1<D$3,C32-1,D$3)) | E32: =IF(D32=0,0,IF(D32-1<E$3,D32-1,E$3)) | F32: =IF(E32=0,0,IF(E32-1<F$3,E32-1,F$3)) | G32: =IF(F32=0,0,IF(F32-1<G$3,F32-1,G$3)) | H32: =IF(G32=0,0,IF(G32-1<H$3,G32-1,H$3)) | I32: =IF(H32=0,0,IF(H32-1<I$3,H32-1,I$3)) | J32: =IF(I32=0,0,IF(I32-1<J$3,I32-1,J$3)) | K32: =IF(J32=0,0,IF(J32-1<K$3,J32-1,K$3)) | ... M32: =IF(L32=0,0,IF(L32-1<M$3,L32-1,M$3))
A33: Base amortissable | B33: USD | C33: =Modèle!C$10 | D33: =C37 | E33: =D37 | F33: =E37 | G33: =F37 | H33: =G37 | I33: =H37 | J33: =I37 | K33: =J37 | ... M33: =L37
A34: Inverse de la durée restante | B34: % | C34: =IF(C32=0,0,1/C32) | D34: =IF(D32=0,0,1/D32) | E34: =IF(E32=0,0,1/E32) | F34: =IF(F32=0,0,1/F32) | G34: =IF(G32=0,0,1/G32) | H34: =IF(H32=0,0,1/H32) | I34: =IF(I32=0,0,1/I32) | J34: =IF(J32=0,0,1/J32) | ... M34: =IF(M32=0,0,1/M32)
A35: Taux dégressif | B35: % | C35: =IF(C32=0,0,IF($C$29*1/$C$28>C34,$C$29*1/$C$28,C34)) | D35: =IF(D32=0,0,IF($C$29*1/$C$28>D34,$C$29*1/$C$28,D34)) | E35: =IF(E32=0,0,IF($C$29*1/$C$28>E34,$C$29*1/$C$28,E34)) | F35: =IF(F32=0,0,IF($C$29*1/$C$28>F34,$C$29*1/$C$28,F34)) | G35: =IF(G32=0,0,IF($C$29*1/$C$28>G34,$C$29*1/$C$28,G34)) | H35: =IF(H32=0,0,IF($C$29*1/$C$28>H34,$C$29*1/$C$28,H34)) | I35: =IF(I32=0,0,IF($C$29*1/$C$28>I34,$C$29*1/$C$28,I34)) | J35: =IF(J32=0,0,IF($C$29*1/$C$28>J34,$C$29*1/$C$28,J34)) | ... M35: =IF(M32=0,0,IF($C$29*1/$C$28>M34,$C$29*1/$C$28,M34))
A36: Charge d'amortissement | B36: USD | C36: =C33*C35 | D36: =D33*D35 | E36: =E33*E35 | F36: =F33*F35 | G36: =G33*G35 | H36: =H33*H35 | I36: =I33*I35 | J36: =J33*J35 | ... M36: =M33*M35
A37: Amortissement restant | B37: USD | C37: =C33-C36 | D37: =D33-D36 | E37: =E33-E36 | F37: =F33-F36 | G37: =G33-G36 | H37: =H33-H36 | I37: =I33-I36 | J37: =J33-J36 | ... M37: =M33-M36
A39: Immobilisations de l'année A2
A40: Durée restante | B40: Années | D40: =IF($C$28<D$3,$C$28,D$3) | E40: =IF(D40=0,0,IF(D40-1<E$3,D40-1,E$3)) | F40: =IF(E40=0,0,IF(E40-1<F$3,E40-1,F$3)) | G40: =IF(F40=0,0,IF(F40-1<G$3,F40-1,G$3)) | H40: =IF(G40=0,0,IF(G40-1<H$3,G40-1,H$3)) | I40: =IF(H40=0,0,IF(H40-1<I$3,H40-1,I$3)) | J40: =IF(I40=0,0,IF(I40-1<J$3,I40-1,J$3)) | K40: =IF(J40=0,0,IF(J40-1<K$3,J40-1,K$3)) | L40: =IF(K40=0,0,IF(K40-1<L$3,K40-1,L$3)) | M40: =IF(L40=0,0,IF(L40-1<M$3,L40-1,M$3))
A41: Base amortissable | B41: USD | D41: =Modèle!D$10 | E41: =D45 | F41: =E45 | G41: =F45 | H41: =G45 | I41: =H45 | J41: =I45 | K41: =J45 | L41: =K45 | M41: =L45
A42: Inverse de la durée restante | B42: % | D42: =IF(D40=0,0,1/D40) | E42: =IF(E40=0,0,1/E40) | F42: =IF(F40=0,0,1/F40) | G42: =IF(G40=0,0,1/G40) | H42: =IF(H40=0,0,1/H40) | I42: =IF(I40=0,0,1/I40) | J42: =IF(J40=0,0,1/J40) | K42: =IF(K40=0,0,1/K40) | ... M42: =IF(M40=0,0,1/M40)
A43: Taux dégressif | B43: % | D43: =IF(D40=0,0,IF($C$29*1/$C$28>D42,$C$29*1/$C$28,D42)) | E43: =IF(E40=0,0,IF($C$29*1/$C$28>E42,$C$29*1/$C$28,E42)) | F43: =IF(F40=0,0,IF($C$29*1/$C$28>F42,$C$29*1/$C$28,F42)) | G43: =IF(G40=0,0,IF($C$29*1/$C$28>G42,$C$29*1/$C$28,G42)) | H43: =IF(H40=0,0,IF($C$29*1/$C$28>H42,$C$29*1/$C$28,H42)) | I43: =IF(I40=0,0,IF($C$29*1/$C$28>I42,$C$29*1/$C$28,I42)) | J43: =IF(J40=0,0,IF($C$29*1/$C$28>J42,$C$29*1/$C$28,J42)) | K43: =IF(K40=0,0,IF($C$29*1/$C$28>K42,$C$29*1/$C$28,K42)) | ... M43: =IF(M40=0,0,IF($C$29*1/$C$28>M42,$C$29*1/$C$28,M42))
A44: Charge d'amortissement | B44: USD | D44: =D41*D43 | E44: =E41*E43 | F44: =F41*F43 | G44: =G41*G43 | H44: =H41*H43 | I44: =I41*I43 | J44: =J41*J43 | K44: =K41*K43 | ... M44: =M41*M43
A45: Amortissement restant | B45: USD | D45: =D41-D44 | E45: =E41-E44 | F45: =F41-F44 | G45: =G41-G44 | H45: =H41-H44 | I45: =I41-I44 | J45: =J41-J44 | K45: =K41-K44 | ... M45: =M41-M44
A47: Immobilisations de l'année A3
A48: Durée restante | B48: Années | E48: =IF($C$28<E$3,$C$28,E$3) | F48: =IF(E48=0,0,IF(E48-1<F$3,E48-1,F$3)) | G48: =IF(F48=0,0,IF(F48-1<G$3,F48-1,G$3)) | H48: =IF(G48=0,0,IF(G48-1<H$3,G48-1,H$3)) | I48: =IF(H48=0,0,IF(H48-1<I$3,H48-1,I$3)) | J48: =IF(I48=0,0,IF(I48-1<J$3,I48-1,J$3)) | K48: =IF(J48=0,0,IF(J48-1<K$3,J48-1,K$3)) | L48: =IF(K48=0,0,IF(K48-1<L$3,K48-1,L$3)) | M48: =IF(L48=0,0,IF(L48-1<M$3,L48-1,M$3))
A49: Base amortissable | B49: USD | E49: =Modèle!E$10 | F49: =E53 | G49: =F53 | H49: =G53 | I49: =H53 | J49: =I53 | K49: =J53 | L49: =K53 | M49: =L53
A50: Inverse de la durée restante | B50: % | E50: =IF(E48=0,0,1/E48) | F50: =IF(F48=0,0,1/F48) | G50: =IF(G48=0,0,1/G48) | H50: =IF(H48=0,0,1/H48) | I50: =IF(I48=0,0,1/I48) | J50: =IF(J48=0,0,1/J48) | K50: =IF(K48=0,0,1/K48) | L50: =IF(L48=0,0,1/L48) | M50: =IF(M48=0,0,1/M48)
A51: Taux dégressif | B51: % | E51: =IF(E48=0,0,IF($C$29*1/$C$28>E50,$C$29*1/$C$28,E50)) | F51: =IF(F48=0,0,IF($C$29*1/$C$28>F50,$C$29*1/$C$28,F50)) | G51: =IF(G48=0,0,IF($C$29*1/$C$28>G50,$C$29*1/$C$28,G50)) | H51: =IF(H48=0,0,IF($C$29*1/$C$28>H50,$C$29*1/$C$28,H50)) | I51: =IF(I48=0,0,IF($C$29*1/$C$28>I50,$C$29*1/$C$28,I50)) | J51: =IF(J48=0,0,IF($C$29*1/$C$28>J50,$C$29*1/$C$28,J50)) | K51: =IF(K48=0,0,IF($C$29*1/$C$28>K50,$C$29*1/$C$28,K50)) | L51: =IF(L48=0,0,IF($C$29*1/$C$28>L50,$C$29*1/$C$28,L50)) | M51: =IF(M48=0,0,IF($C$29*1/$C$28>M50,$C$29*1/$C$28,M50))
A52: Charge d'amortissement | B52: USD | E52: =E49*E51 | F52: =F49*F51 | G52: =G49*G51 | H52: =H49*H51 | I52: =I49*I51 | J52: =J49*J51 | K52: =K49*K51 | L52: =L49*L51 | M52: =M49*M51
A53: Amortissement restant | B53: USD | E53: =E49-E52 | F53: =F49-F52 | G53: =G49-G52 | H53: =H49-H52 | I53: =I49-I52 | J53: =J49-J52 | K53: =K49-K52 | L53: =L49-L52 | M53: =M49-M52
A55: Immobilisations de l'année A4
A56: Durée restante | B56: Années | F56: =IF($C$28<F$3,$C$28,F$3) | G56: =IF(F56=0,0,IF(F56-1<G$3,F56-1,G$3)) | H56: =IF(G56=0,0,IF(G56-1<H$3,G56-1,H$3)) | I56: =IF(H56=0,0,IF(H56-1<I$3,H56-1,I$3)) | J56: =IF(I56=0,0,IF(I56-1<J$3,I56-1,J$3)) | K56: =IF(J56=0,0,IF(J56-1<K$3,J56-1,K$3)) | L56: =IF(K56=0,0,IF(K56-1<L$3,K56-1,L$3)) | M56: =IF(L56=0,0,IF(L56-1<M$3,L56-1,M$3))
A57: Base amortissable | B57: USD | F57: =Modèle!F$10 | G57: =F61 | H57: =G61 | I57: =H61 | J57: =I61 | K57: =J61 | L57: =K61 | M57: =L61
A58: Inverse de la durée restante | B58: % | F58: =IF(F56=0,0,1/F56) | G58: =IF(G56=0,0,1/G56) | H58: =IF(H56=0,0,1/H56) | I58: =IF(I56=0,0,1/I56) | J58: =IF(J56=0,0,1/J56) | K58: =IF(K56=0,0,1/K56) | L58: =IF(L56=0,0,1/L56) | M58: =IF(M56=0,0,1/M56)
A59: Taux dégressif | B59: % | F59: =IF(F56=0,0,IF($C$29*1/$C$28>F58,$C$29*1/$C$28,F58)) | G59: =IF(G56=0,0,IF($C$29*1/$C$28>G58,$C$29*1/$C$28,G58)) | H59: =IF(H56=0,0,IF($C$29*1/$C$28>H58,$C$29*1/$C$28,H58)) | I59: =IF(I56=0,0,IF($C$29*1/$C$28>I58,$C$29*1/$C$28,I58)) | J59: =IF(J56=0,0,IF($C$29*1/$C$28>J58,$C$29*1/$C$28,J58)) | K59: =IF(K56=0,0,IF($C$29*1/$C$28>K58,$C$29*1/$C$28,K58)) | L59: =IF(L56=0,0,IF($C$29*1/$C$28>L58,$C$29*1/$C$28,L58)) | M59: =IF(M56=0,0,IF($C$29*1/$C$28>M58,$C$29*1/$C$28,M58))
A60: Charge d'amortissement | B60: USD | F60: =F57*F59 | G60: =G57*G59 | H60: =H57*H59 | I60: =I57*I59 | J60: =J57*J59 | K60: =K57*K59 | L60: =L57*L59 | M60: =M57*M59
A61: Amortissement restant | B61: USD | F61: =F57-F60 | G61: =G57-G60 | H61: =H57-H60 | I61: =I57-I60 | J61: =J57-J60 | K61: =K57-K60 | L61: =L57-L60 | M61: =M57-M60
A63: Immobilisations de l'année A5
A64: Durée restante | B64: Années | G64: =IF($C$28<G$3,$C$28,G$3) | H64: =IF(G64=0,0,IF(G64-1<H$3,G64-1,H$3)) | I64: =IF(H64=0,0,IF(H64-1<I$3,H64-1,I$3)) | J64: =IF(I64=0,0,IF(I64-1<J$3,I64-1,J$3)) | K64: =IF(J64=0,0,IF(J64-1<K$3,J64-1,K$3)) | L64: =IF(K64=0,0,IF(K64-1<L$3,K64-1,L$3)) | M64: =IF(L64=0,0,IF(L64-1<M$3,L64-1,M$3))
A65: Base amortissable | B65: USD | G65: =Modèle!G$10 | H65: =G69 | I65: =H69 | J65: =I69 | K65: =J69 | L65: =K69 | M65: =L69
A66: Inverse de la durée restante | B66: % | G66: =IF(G64=0,0,1/G64) | H66: =IF(H64=0,0,1/H64) | I66: =IF(I64=0,0,1/I64) | J66: =IF(J64=0,0,1/J64) | K66: =IF(K64=0,0,1/K64) | L66: =IF(L64=0,0,1/L64) | M66: =IF(M64=0,0,1/M64)
A67: Taux dégressif | B67: % | G67: =IF(G64=0,0,IF($C$29*1/$C$28>G66,$C$29*1/$C$28,G66)) | H67: =IF(H64=0,0,IF($C$29*1/$C$28>H66,$C$29*1/$C$28,H66)) | I67: =IF(I64=0,0,IF($C$29*1/$C$28>I66,$C$29*1/$C$28,I66)) | J67: =IF(J64=0,0,IF($C$29*1/$C$28>J66,$C$29*1/$C$28,J66)) | K67: =IF(K64=0,0,IF($C$29*1/$C$28>K66,$C$29*1/$C$28,K66)) | L67: =IF(L64=0,0,IF($C$29*1/$C$28>L66,$C$29*1/$C$28,L66)) | M67: =IF(M64=0,0,IF($C$29*1/$C$28>M66,$C$29*1/$C$28,M66))
A68: Charge d'amortissement | B68: USD | G68: =G65*G67 | H68: =H65*H67 | I68: =I65*I67 | J68: =J65*J67 | K68: =K65*K67 | L68: =L65*L67 | M68: =M65*M67
A69: Amortissement restant | B69: USD | G69: =G65-G68 | H69: =H65-H68 | I69: =I65-I68 | J69: =J65-J68 | K69: =K65-K68 | L69: =L65-L68 | M69: =M65-M68
A71: Immobilisations de l'année A6
A72: Durée restante | B72: Années | H72: =IF($C$28<H$3,$C$28,H$3) | I72: =IF(H72=0,0,IF(H72-1<I$3,H72-1,I$3)) | J72: =IF(I72=0,0,IF(I72-1<J$3,I72-1,J$3)) | K72: =IF(J72=0,0,IF(J72-1<K$3,J72-1,K$3)) | L72: =IF(K72=0,0,IF(K72-1<L$3,K72-1,L$3)) | M72: =IF(L72=0,0,IF(L72-1<M$3,L72-1,M$3))
A73: Base amortissable | B73: USD | H73: =Modèle!H$10 | I73: =H77 | J73: =I77 | K73: =J77 | L73: =K77 | M73: =L77
A74: Inverse de la durée restante | B74: % | H74: =IF(H72=0,0,1/H72) | I74: =IF(I72=0,0,1/I72) | J74: =IF(J72=0,0,1/J72) | K74: =IF(K72=0,0,1/K72) | L74: =IF(L72=0,0,1/L72) | M74: =IF(M72=0,0,1/M72)
A75: Taux dégressif | B75: % | H75: =IF(H72=0,0,IF($C$29*1/$C$28>H74,$C$29*1/$C$28,H74)) | I75: =IF(I72=0,0,IF($C$29*1/$C$28>I74,$C$29*1/$C$28,I74)) | J75: =IF(J72=0,0,IF($C$29*1/$C$28>J74,$C$29*1/$C$28,J74)) | K75: =IF(K72=0,0,IF($C$29*1/$C$28>K74,$C$29*1/$C$28,K74)) | L75: =IF(L72=0,0,IF($C$29*1/$C$28>L74,$C$29*1/$C$28,L74)) | M75: =IF(M72=0,0,IF($C$29*1/$C$28>M74,$C$29*1/$C$28,M74))
A76: Charge d'amortissement | B76: USD | H76: =H73*H75 | I76: =I73*I75 | J76: =J73*J75 | K76: =K73*K75 | L76: =L73*L75 | M76: =M73*M75
A77: Amortissement restant | B77: USD | H77: =H73-H76 | I77: =I73-I76 | J77: =J73-J76 | K77: =K73-K76 | L77: =L73-L76 | M77: =M73-M76
A79: Immobilisations de l'année A7
A80: Durée restante | B80: Années | I80: =IF($C$28<I$3,$C$28,I$3) | J80: =IF(I80=0,0,IF(I80-1<J$3,I80-1,J$3)) | K80: =IF(J80=0,0,IF(J80-1<K$3,J80-1,K$3)) | L80: =IF(K80=0,0,IF(K80-1<L$3,K80-1,L$3)) | M80: =IF(L80=0,0,IF(L80-1<M$3,L80-1,M$3))
A81: Base amortissable | B81: USD | I81: =Modèle!I$10 | J81: =I85 | K81: =J85 | L81: =K85 | M81: =L85
A82: Inverse de la durée restante | B82: % | I82: =IF(I80=0,0,1/I80) | J82: =IF(J80=0,0,1/J80) | K82: =IF(K80=0,0,1/K80) | L82: =IF(L80=0,0,1/L80) | M82: =IF(M80=0,0,1/M80)
A83: Taux dégressif | B83: % | I83: =IF(I80=0,0,IF($C$29*1/$C$28>I82,$C$29*1/$C$28,I82)) | J83: =IF(J80=0,0,IF($C$29*1/$C$28>J82,$C$29*1/$C$28,J82)) | K83: =IF(K80=0,0,IF($C$29*1/$C$28>K82,$C$29*1/$C$28,K82)) | L83: =IF(L80=0,0,IF($C$29*1/$C$28>L82,$C$29*1/$C$28,L82)) | M83: =IF(M80=0,0,IF($C$29*1/$C$28>M82,$C$29*1/$C$28,M82))
A84: Charge d'amortissement | B84: USD | I84: =I81*I83 | J84: =J81*J83 | K84: =K81*K83 | L84: =L81*L83 | M84: =M81*M83
A85: Amortissement restant | B85: USD | I85: =I81-I84 | J85: =J81-J84 | K85: =K81-K84 | L85: =L81-L84 | M85: =M81-M84
A87: Immobilisations de l'année A8
A88: Durée restante | B88: Années | J88: =IF($C$28<J$3,$C$28,J$3) | K88: =IF(J88=0,0,IF(J88-1<K$3,J88-1,K$3)) | L88: =IF(K88=0,0,IF(K88-1<L$3,K88-1,L$3)) | M88: =IF(L88=0,0,IF(L88-1<M$3,L88-1,M$3))
A89: Base amortissable | B89: USD | J89: =Modèle!J$10 | K89: =J93 | L89: =K93 | M89: =L93
A90: Inverse de la durée restante | B90: % | J90: =IF(J88=0,0,1/J88) | K90: =IF(K88=0,0,1/K88) | L90: =IF(L88=0,0,1/L88) | M90: =IF(M88=0,0,1/M88)
A91: Taux dégressif | B91: % | J91: =IF(J88=0,0,IF($C$29*1/$C$28>J90,$C$29*1/$C$28,J90)) | K91: =IF(K88=0,0,IF($C$29*1/$C$28>K90,$C$29*1/$C$28,K90)) | L91: =IF(L88=0,0,IF($C$29*1/$C$28>L90,$C$29*1/$C$28,L90)) | M91: =IF(M88=0,0,IF($C$29*1/$C$28>M90,$C$29*1/$C$28,M90))
A92: Charge d'amortissement | B92: USD | J92: =J89*J91 | K92: =K89*K91 | L92: =L89*L91 | M92: =M89*M91
A93: Amortissement restant | B93: USD | J93: =J89-J92 | K93: =K89-K92 | L93: =L89-L92 | M93: =M89-M92
A95: Immobilisations de l'année A9
A96: Durée restante | B96: Années | K96: =IF($C$28<K$3,$C$28,K$3) | L96: =IF(K96=0,0,IF(K96-1<L$3,K96-1,L$3)) | M96: =IF(L96=0,0,IF(L96-1<M$3,L96-1,M$3))
A97: Base amortissable | B97: USD | K97: =Modèle!K$10 | L97: =K101 | M97: =L101
A98: Inverse de la durée restante | B98: % | K98: =IF(K96=0,0,1/K96) | L98: =IF(L96=0,0,1/L96) | M98: =IF(M96=0,0,1/M96)
A99: Taux dégressif | B99: % | K99: =IF(K96=0,0,IF($C$29*1/$C$28>K98,$C$29*1/$C$28,K98)) | L99: =IF(L96=0,0,IF($C$29*1/$C$28>L98,$C$29*1/$C$28,L98)) | M99: =IF(M96=0,0,IF($C$29*1/$C$28>M98,$C$29*1/$C$28,M98))
A100: Charge d'amortissement | B100: USD | K100: =K97*K99 | L100: =L97*L99 | M100: =M97*M99
A101: Amortissement restant | B101: USD | K101: =K97-K100 | L101: =L97-L100 | M101: =M97-M100
A103: Immobilisations de l'année A10
A104: Durée restante | B104: Années | L104: =IF($C$28<L$3,$C$28,L$3) | M104: =IF(L104=0,0,IF(L104-1<M$3,L104-1,M$3))
A105: Base amortissable | B105: USD | L105: =Modèle!L$10 | M105: =L109
A106: Inverse de la durée restante | B106: % | L106: =IF(L104=0,0,1/L104) | M106: =IF(M104=0,0,1/M104)
A107: Taux dégressif | B107: % | L107: =IF(L104=0,0,IF($C$29*1/$C$28>L106,$C$29*1/$C$28,L106)) | M107: =IF(M104=0,0,IF($C$29*1/$C$28>M106,$C$29*1/$C$28,M106))
A108: Charge d'amortissement | B108: USD | L108: =L105*L107 | M108: =M105*M107
A109: Amortissement restant | B109: USD | L109: =L105-L108 | M109: =M105-M108
A111: Immobilisations de l'année A11
A112: Durée restante | B112: Années | M112: =IF($C$28<M$3,$C$28,M$3)
A113: Base amortissable | B113: USD | M113: =Modèle!M$10
A114: Inverse de la durée restante | B114: % | M114: =IF(M112=0,0,1/M112)
A115: Taux dégressif | B115: % | M115: =IF(M112=0,0,IF($C$29*1/$C$28>M114,$C$29*1/$C$28,M114))
A116: Charge d'amortissement | B116: USD | M116: =M113*M115
A117: Amortissement restant | B117: USD | M117: =M113-M116
...

Sheet 09_09_Participa_1
A1: Nom | B1: Unité | C1: Année 1 | D1: Année 2 | E1: Année 3 | F1: Année 4 | G1: Année 5 | H1: Année 6 | I1: Année 7 | J1: Année 8 | K1: Année 9 | L1: Année 10 | M1: Année 11 | N1: SOMME | O1: VAN
A3: I. PRODUCTION
A4: Production d'or | B4: oz | E4: 250000 | F4: 250000 | G4: 250000 | H4: 250000 | I4: 250000 | J4: 250000 | K4: 250000 | L4: 250000 | N4: =SUM($C4:$M4)
A5: Cours de l'or | B5: USD/oz | E5: 1300 | F5: 1300 | G5: 1300 | H5: 1300 | I5: 1300 | J5: 1300 | K5: 1300 | L5: 1300
A6: Chiffre d'affaires | B6: USD | C6: =C$4*C$5 | D6: =D$4*D$5 | E6: =E$4*E$5 | F6: =F$4*F$5 | G6: =G$4*G$5 | H6: =H$4*H$5 | I6: =I$4*I$5 | J6: =J$4*J$5 | ... M6: =M$4*M$5 | N6: =SUM($C6:$M6) | O6: =$C6+NPV(10%,$D6:$M6)
A8: II. DEPENSES D'INVESTISSEMENT (CAPEX)
A9: Coûts des construction industrielles | B9: USD | C9: 50000000 | D9: 100000000 | N9: =SUM($C9:$M9) | O9: =$C9+NPV(10%,$D9:$M9)
A10: Coûts des biens d'équipement | B10: USD | D10: 50000000 | E10: 5000000 | F10: 5000000 | G10: 5000000 | H10: 5000000 | I10: 5000000 | J10: 5000000 | K10: 5000000 | L10: 5000000 | N10: =SUM($C10:$M10) | O10: =$C10+NPV(10%,$D10:$M10)
A11: Coûts de réhabilitation du site | B11: USD | M11: 10000000 | N11: =SUM($C11:$M11) | O11: =$C11+NPV(10%,$D11:$M11)
A12: Total des dépenses d'investissement | B12: USD | C12: =SUM(C$9:C$11) | D12: =SUM(D$9:D$11) | E12: =SUM(E$9:E$11) | F12: =SUM(F$9:F$11) | G12: =SUM(G$9:G$11) | H12: =SUM(H$9:H$11) | I12: =SUM(I$9:I$11) | J12: =SUM(J$9:J$11) | ... M12: =SUM(M$9:M$11) | N12: =SUM($C12:$M12) | O12: =$C12+NPV(10%,$D12:$M12)
A14: III. COÛTS D'EXPLOITATION (OPEX)
A15: Coût moyen d'exploitation | B15: USD/oz | E15: 700 | F15: 700 | G15: 700 | H15: 700 | I15: 700 | J15: 700 | K15: 700 | L15: 700
A16: Total des coûts d'exploitation | B16: USD | C16: =C$4*C$15 | D16: =D$4*D$15 | E16: =E$4*E$15 | F16: =F$4*F$15 | G16: =G$4*G$15 | H16: =H$4*H$15 | I16: =I$4*I$15 | J16: =J$4*J$15 | ... M16: =M$4*M$15 | N16: =SUM($C16:$M16) | O16: =$C16+NPV(10%,$D16:$M16)
A18: IV. FLUX NETS DE TRESORERIE AVANT IMPÔTS
A19: Flux nets de trésorerie avant impôts | B19: USD | C19: =C$6-C$12-C$16 | D19: =D$6-D$12-D$16 | E19: =E$6-E$12-E$16 | F19: =F$6-F$12-F$16 | G19: =G$6-G$12-G$16 | H19: =H$6-H$12-H$16 | I19: =I$6-I$12-I$16 | J19: =J$6-J$12-J$16 | ... M19: =M$6-M$12-M$16 | N19: =SUM($C19:$M19) | O19: =$C19+NPV(10%,$D19:$M19)
A20: Taux de rendement interne avant impôts | B20: % | C20: =IF(ISNUMBER(IRR($C19:C19)),IF(IRR($C19:C19)>0,IRR($C19:C19),""),"") | D20: =IF(ISNUMBER(IRR($C19:D19)),IF(IRR($C19:D19)>0,IRR($C19:D19),""),"") | E20: =IF(ISNUMBER(IRR($C19:E19)),IF(IRR($C19:E19)>0,IRR($C19:E19),""),"") | F20: =IF(ISNUMBER(IRR($C19:F19)),IF(IRR($C19:F19)>0,IRR($C19:F19),""),"") | G20: =IF(ISNUMBER(IRR($C19:G19)),IF(IRR($C19:G19)>0,IRR($C19:G19),""),"") | H20: =IF(ISNUMBER(IRR($C19:H19)),IF(IRR($C19:H19)>0,IRR($C19:H19),""),"") | I20: =IF(ISNUMBER(IRR($C19:I19)),IF(IRR($C19:I19)>0,IRR($C19:I19),""),"") | J20: =IF(ISNUMBER(IRR($C19:J19)),IF(IRR($C19:J19)>0,IRR($C19:J19),""),"") | ... M20: =IF(ISNUMBER(IRR($C19:M19)),IF(IRR($C19:M19)>0,IRR($C19:M19),""),"")
A22: V. DROITS FIXES
A23: Droits fixes | B23: USD | C23: 100000 | N23: =SUM($C23:$M23) | O23: =$C23+NPV(10%,$D23:$M23)
A25: VI. REDEVANCE SUPERFICAIRE
A26: Superficie de la mine | B26: km² | C26: 100 | D26: 100 | E26: 100 | F26: 100 | G26: 100 | H26: 100 | I26: 100 | J26: 100 | K26: 100 | L26: 100 | M26: 100
A27: Montant de la redevance superfiaire | B27: USD/km² | C27: 100 | D27: 100 | E27: 100 | F27: 100 | G27: 100 | H27: 100 | I27: 100 | J27: 100 | K27: 100 | L27: 100 | M27: 100
A28: Redevance superficiaire | B28: USD | C28: =C$26*C$27 | D28: =D$26*D$27 | E28: =E$26*E$27 | F28: =F$26*F$27 | G28: =G$26*G$27 | H28: =H$26*H$27 | I28: =I$26*I$27 | J28: =J$26*J$27 | ... M28: =M$26*M$27 | N28: =SUM($C28:$M28) | O28: =$C28+NPV(10%,$D28:$M28)
A30: VII. REDEVANCE MINIERE
A31: Taux de la redevance minière | B31: % | C31: =IF(ISNUMBER(C5),IF(C$5<1300,3%,IF(C$5<1500,4%,5%)),"") | D31: =IF(ISNUMBER(D5),IF(D$5<1300,3%,IF(D$5<1500,4%,5%)),"") | E31: =IF(ISNUMBER(E5),IF(E$5<1300,3%,IF(E$5<1500,4%,5%)),"") | F31: =IF(ISNUMBER(F5),IF(F$5<1300,3%,IF(F$5<1500,4%,5%)),"") | G31: =IF(ISNUMBER(G5),IF(G$5<1300,3%,IF(G$5<1500,4%,5%)),"") | H31: =IF(ISNUMBER(H5),IF(H$5<1300,3%,IF(H$5<1500,4%,5%)),"") | I31: =IF(ISNUMBER(I5),IF(I$5<1300,3%,IF(I$5<1500,4%,5%)),"") | J31: =IF(ISNUMBER(J5),IF(J$5<1300,3%,IF(J$5<1500,4%,5%)),"") | ... M31: =IF(ISNUMBER(M5),IF(M$5<1300,3%,IF(M$5<1500,4%,5%)),"")
A32: Redevance minière | B32: USD | C32: =IF(ISNUMBER(C31),C$6*C$31,0) | D32: =IF(ISNUMBER(D31),D$6*D$31,0) | E32: =IF(ISNUMBER(E31),E$6*E$31,0) | F32: =IF(ISNUMBER(F31),F$6*F$31,0) | G32: =IF(ISNUMBER(G31),G$6*G$31,0) | H32: =IF(ISNUMBER(H31),H$6*H$31,0) | I32: =IF(ISNUMBER(I31),I$6*I$31,0) | J32: =IF(ISNUMBER(J31),J$6*J$31,0) | ... M32: =IF(ISNUMBER(M31),M$6*M$31,0) | N32: =SUM($C32:$M32) | O32: =$C32+NPV(10%,$D32:$M32)
A34: +. LA TAXE SUR LA RENTE
A35: Taux de revalorisation des pertes | B35: % | C35: 0.02 | D35: 0.02 | E35: 0.02 | F35: 0.02 | G35: 0.02 | H35: 0.02 | I35: 0.02 | J35: 0.02 | K35: 0.02 | L35: 0.02 | M35: 0.02
A36: Flux nets de trésorerie revalorisés | B36: USD | C36: =IF(C19<0,C19*(1+C35),C19) | D36: =IF(D19<0,D19*(1+D35),D19) | E36: =IF(E19<0,E19*(1+E35),E19) | F36: =IF(F19<0,F19*(1+F35),F19) | G36: =IF(G19<0,G19*(1+G35),G19) | H36: =IF(H19<0,H19*(1+H35),H19) | I36: =IF(I19<0,I19*(1+I35),I19) | J36: =IF(J19<0,J19*(1+J35),J19) | ... M36: =IF(M19<0,M19*(1+M35),M19) | N36: =SUM($C36:$M36) | O36: =$C36+NPV(10%,$D36:$M36)
A37: Taux de rendement interne | B37: % | C37: =IF(ISNUMBER(IRR($C36:C36)),IF(IRR($C36:C36)>0,IRR($C36:C36),""),"") | D37: =IF(ISNUMBER(IRR($C36:D36)),IF(IRR($C36:D36)>0,IRR($C36:D36),""),"") | E37: =IF(ISNUMBER(IRR($C36:E36)),IF(IRR($C36:E36)>0,IRR($C36:E36),""),"") | F37: =IF(ISNUMBER(IRR($C36:F36)),IF(IRR($C36:F36)>0,IRR($C36:F36),""),"") | G37: =IF(ISNUMBER(IRR($C36:G36)),IF(IRR($C36:G36)>0,IRR($C36:G36),""),"") | H37: =IF(ISNUMBER(IRR($C36:H36)),IF(IRR($C36:H36)>0,IRR($C36:H36),""),"") | I37: =IF(ISNUMBER(IRR($C36:I36)),IF(IRR($C36:I36)>0,IRR($C36:I36),""),"") | J37: =IF(ISNUMBER(IRR($C36:J36)),IF(IRR($C36:J36)>0,IRR($C36:J36),""),"") | ... M37: =IF(ISNUMBER(IRR($C36:M36)),IF(IRR($C36:M36)>0,IRR($C36:M36),""),"")
A38: Seuil de déclenchement de la taxe sur la rente | B38: % | C38: 0.15 | D38: 0.15 | E38: 0.15 | F38: 0.15 | G38: 0.15 | H38: 0.15 | I38: 0.15 | J38: 0.15 | K38: 0.15 | L38: 0.15 | M38: 0.15
A39: Report des pertes revalorisées | D39: =IF(C40<0,C40,0) | E39: =IF(D40<0,D40,0) | F39: =IF(E40<0,E40,0) | G39: =IF(F40<0,F40,0) | H39: =IF(G40<0,G40,0) | I39: =IF(H40<0,H40,0) | J39: =IF(I40<0,I40,0) | K39: =IF(J40<0,J40,0) | ... M39: =IF(L40<0,L40,0)
A40: Flux nets de trésorerie après report des pertes revalorisées | B40: USD | C40: =C36+C39 | D40: =D36+D39 | E40: =E36+E39 | F40: =F36+F39 | G40: =G36+G39 | H40: =H36+H39 | I40: =I36+I39 | J40: =J36+J39 | ... M40: =M36+M39 | N40: =SUM($C40:$M40) | O40: =$C40+NPV(10%,$D40:$M40)
A41: Taux de la taxe sur la rente | B41: % | C41: 0.2 | D41: 0.2 | E41: 0.2 | F41: 0.2 | G41: 0.2 | H41: 0.2 | I41: 0.2 | J41: 0.2 | K41: 0.2 | L41: 0.2 | M41: 0.2
A42: Taxe sur la rente | B42: USD | C42: =IF(C37<C38,0,IF(C40<0,0,C40*C41)) | D42: =IF(D37<D38,0,IF(D40<0,0,D40*D41)) | E42: =IF(E37<E38,0,IF(E40<0,0,E40*E41)) | F42: =IF(F37<F38,0,IF(F40<0,0,F40*F41)) | G42: =IF(G37<G38,0,IF(G40<0,0,G40*G41)) | H42: =IF(H37<H38,0,IF(H40<0,0,H40*H41)) | I42: =IF(I37<I38,0,IF(I40<0,0,I40*I41)) | J42: =IF(J37<J38,0,IF(J40<0,0,J40*J41)) | ... M42: =IF(M37<M38,0,IF(M40<0,0,M40*M41)) | N42: =SUM($C42:$M42) | O42: =$C42+NPV(10%,$D42:$M42)
A44: VIII. IMPÔT SUR LES SOCIETES (IS)
A45: Bénéfice avant report des pertes | B45: USD | C45: =C$6-C$16-C$23-C$28-C$32-C$42-'Amortissements et Emprunt'!C$25-'Amortissements et Emprunt'!C$119-'Amortissements et Emprunt'!C133-'Amortissements et Emprunt'!C$157 | D45: =D$6-D$16-D$23-D$28-D$32-D$42-'Amortissements et Emprunt'!D$25-'Amortissements et Emprunt'!D$119-'Amortissements et Emprunt'!D133-'Amortissements et Emprunt'!D$157 | E45: =E$6-E$16-E$23-E$28-E$32-E$42-'Amortissements et Emprunt'!E$25-'Amortissements et Emprunt'!E$119-'Amortissements et Emprunt'!E133-'Amortissements et Emprunt'!E$157 | F45: =F$6-F$16-F$23-F$28-F$32-F$42-'Amortissements et Emprunt'!F$25-'Amortissements et Emprunt'!F$119-'Amortissements et Emprunt'!F133-'Amortissements et Emprunt'!F$157 | G45: =G$6-G$16-G$23-G$28-G$32-G$42-'Amortissements et Emprunt'!G$25-'Amortissements et Emprunt'!G$119-'Amortissements et Emprunt'!G133-'Amortissements et Emprunt'!G$157 | H45: =H$6-H$16-H$23-H$28-H$32-H$42-'Amortissements et Emprunt'!H$25-'Amortissements et Emprunt'!H$119-'Amortissements et Emprunt'!H133-'Amortissements et Emprunt'!H$157 | I45: =I$6-I$16-I$23-I$28-I$32-I$42-'Amortissements et Emprunt'!I$25-'Amortissements et Emprunt'!I$119-'Amortissements et Emprunt'!I133-'Amortissements et Emprunt'!I$157 | J45: =J$6-J$16-J$23-J$28-J$32-J$42-'Amortissements et Emprunt'!J$25-'Amortissements et Emprunt'!J$119-'Amortissements et Emprunt'!J133-'Amortissements et Emprunt'!J$157 | ... M45: =M$6-M$16-M$23-M$28-M$32-M$42-'Amortissements et Emprunt'!M$25-'Amortissements et Emprunt'!M$119-'Amortissements et Emprunt'!M133-'Amortissements et Emprunt'!M$157 | N45: =SUM($C45:$M45) | O45: =$C45+NPV(10%,$D45:$M45)
A46: Report des pertes | B46: USD | D46: =IF(C47<0,C47,0) | E46: =IF(D47<0,D47,0) | F46: =IF(E47<0,E47,0) | G46: =IF(F47<0,F47,0) | H46: =IF(G47<0,G47,0) | I46: =IF(H47<0,H47,0) | J46: =IF(I47<0,I47,0) | K46: =IF(J47<0,J47,0) | ... M46: =IF(L47<0,L47,0)
A47: Bénéfice fiscal | B47: USD | C47: =C$45+C$46 | D47: =D$45+D$46 | E47: =E$45+E$46 | F47: =F$45+F$46 | G47: =G$45+G$46 | H47: =H$45+H$46 | I47: =I$45+I$46 | J47: =J$45+J$46 | ... M47: =M$45+M$46 | N47: =SUM($C47:$M47) | O47: =$C47+NPV(10%,$D47:$M47)
A48: Taux de l'impôt sur les sociétés | B48: % | C48: 0.3 | D48: 0.3 | E48: 0.3 | F48: 0.3 | G48: 0.3 | H48: 0.3 | I48: 0.3 | J48: 0.3 | K48: 0.3 | L48: 0.3 | M48: 0.3
A49: Impôt sur les sociétés | B49: USD | C49: =IF(C$47>0,C$47*C$48,0) | D49: =IF(D$47>0,D$47*D$48,0) | E49: =IF(E$47>0,E$47*E$48,0) | F49: =IF(F$47>0,F$47*F$48,0) | G49: =IF(G$47>0,G$47*G$48,0) | H49: =IF(H$47>0,H$47*H$48,0) | I49: =IF(I$47>0,I$47*I$48,0) | J49: =IF(J$47>0,J$47*J$48,0) | ... M49: =IF(M$47>0,M$47*M$48,0) | N49: =SUM($C49:$M49) | O49: =$C49+NPV(10%,$D49:$M49)
A51: IX. IMPÔT MINIMUM FORFAITAIRE (IMF)
A52: Montant minimum | B52: USD | C52: 2000 | D52: 2000 | E52: 2000 | F52: 2000 | G52: 2000 | H52: 2000 | I52: 2000 | J52: 2000 | K52: 2000 | L52: 2000 | M52: 2000
A53: Taux de l'impôt minimum forfaitaire | B53: % | C53: 0.01 | D53: 0.01 | E53: 0.01 | F53: 0.01 | G53: 0.01 | H53: 0.01 | I53: 0.01 | J53: 0.01 | K53: 0.01 | L53: 0.01 | M53: 0.01
A54: Impôt minimum forfaitaire | B54: USD | C54: =IF(C$6*C$53>C$52,C$6*C$53,C$52) | D54: =IF(D$6*D$53>D$52,D$6*D$53,D$52) | E54: =IF(E$6*E$53>E$52,E$6*E$53,E$52) | F54: =IF(F$6*F$53>F$52,F$6*F$53,F$52) | G54: =IF(G$6*G$53>G$52,G$6*G$53,G$52) | H54: =IF(H$6*H$53>H$52,H$6*H$53,H$52) | I54: =IF(I$6*I$53>I$52,I$6*I$53,I$52) | J54: =IF(J$6*J$53>J$52,J$6*J$53,J$52) | ... M54: =IF(M$6*M$53>M$52,M$6*M$53,M$52) | N54: =SUM($C54:$M54) | O54: =$C54+NPV(10%,$D54:$M54)
A56: X. IMPÔT SUR LES SOCIETES (IS) / IMPÔT MINIMUM FORFAITAIRE (IMF)
A57: Impôt sur les sociétés / Impôt minimum forfaitaire | B57: USD | C57: =IF(C$54>C$49,C$54,C$49) | D57: =IF(D$54>D$49,D$54,D$49) | E57: =IF(E$54>E$49,E$54,E$49) | F57: =IF(F$54>F$49,F$54,F$49) | G57: =IF(G$54>G$49,G$54,G$49) | H57: =IF(H$54>H$49,H$54,H$49) | I57: =IF(I$54>I$49,I$54,I$49) | J57: =IF(J$54>J$49,J$54,J$49) | ... M57: =IF(M$54>M$49,M$54,M$49) | N57: =SUM($C57:$M57) | O57: =$C57+NPV(10%,$D57:$M57)
A59: XI. PARTICIPATION DE L'ETAT
A60: Bénéfice distribuable | B60: USD | C60: =IF(C$47-C$57>0,C$47-C$57,0) | D60: =IF(D$47-D$57>0,D$47-D$57,0) | E60: =IF(E$47-E$57>0,E$47-E$57,0) | F60: =IF(F$47-F$57>0,F$47-F$57,0) | G60: =IF(G$47-G$57>0,G$47-G$57,0) | H60: =IF(H$47-H$57>0,H$47-H$57,0) | I60: =IF(I$47-I$57>0,I$47-I$57,0) | J60: =IF(J$47-J$57>0,J$47-J$57,0) | ... M60: =IF(M$47-M$57>0,M$47-M$57,0) | N60: =SUM($C60:$M60) | O60: =$C60+NPV(10%,$D60:$M60)
A61: Taux de la participation de l'Etat | B61: % | C61: 0.1 | D61: 0.1 | E61: 0.1 | F61: 0.1 | G61: 0.1 | H61: 0.1 | I61: 0.1 | J61: 0.1 | K61: 0.1 | L61: 0.1 | M61: 0.1
A62: Participation de l'Etat | B62: USD | C62: =C$60*C$61 | D62: =D$60*D$61 | E62: =E$60*E$61 | F62: =F$60*F$61 | G62: =G$60*G$61 | H62: =H$60*H$61 | I62: =I$60*I$61 | J62: =J$60*J$61 | ... M62: =M$60*M$61 | N62: =SUM($C62:$M62) | O62: =$C62+NPV(10%,$D62:$M62)
A64: XII. IMPÔT SUR LE REVENU DES VALEURS MOBILIERS (IRVM)
A65: Part distribuée aux actionnaires privés | B65: % | C65: 0.2 | D65: 0.2 | E65: 0.2 | F65: 0.2 | G65: 0.2 | H65: 0.2 | I65: 0.2 | J65: 0.2 | K65: 0.2 | L65: 0.2 | M65: 0.2
A66: Dividendes distribués aux actionnaires privés | B66: USD | C66: =C$60*C$65 | D66: =D$60*D$65 | E66: =E$60*E$65 | F66: =F$60*F$65 | G66: =G$60*G$65 | H66: =H$60*H$65 | I66: =I$60*I$65 | J66: =J$60*J$65 | ... M66: =M$60*M$65 | N66: =SUM($C66:$M66) | O66: =$C66+NPV(10%,$D66:$M66)
A67: Taux de l'impöt sur le revenu des valeurs mobilières | B67: % | C67: 0.1 | D67: 0.1 | E67: 0.1 | F67: 0.1 | G67: 0.1 | H67: 0.1 | I67: 0.1 | J67: 0.1 | K67: 0.1 | L67: 0.1 | M67: 0.1
A68: Impöt sur le revenu des valeurs mobilières | B68: USD | C68: =C$66*C$67 | D68: =D$66*D$67 | E68: =E$66*E$67 | F68: =F$66*F$67 | G68: =G$66*G$67 | H68: =H$66*H$67 | I68: =I$66*I$67 | J68: =J$66*J$67 | ... M68: =M$66*M$67 | N68: =SUM($C68:$M68) | O68: =$C68+NPV(10%,$D68:$M68)
A70: XIII. PRELEVEMENTS PUBLICS
A71: Total des prélèvements publics | B71: USD | C71: =C$23+C$28+C$32+C$42+C$57+C$62+C$68 | D71: =D$23+D$28+D$32+D$42+D$57+D$62+D$68 | E71: =E$23+E$28+E$32+E$42+E$57+E$62+E$68 | F71: =F$23+F$28+F$32+F$42+F$57+F$62+F$68 | G71: =G$23+G$28+G$32+G$42+G$57+G$62+G$68 | H71: =H$23+H$28+H$32+H$42+H$57+H$62+H$68 | I71: =I$23+I$28+I$32+I$42+I$57+I$62+I$68 | J71: =J$23+J$28+J$32+J$42+J$57+J$62+J$68 | ... M71: =M$23+M$28+M$32+M$42+M$57+M$62+M$68 | N71: =SUM($C71:$M71) | O71: =$C71+NPV(10%,$D71:$M71)
A73: XIV. FLUX NETS DE TRESORERIE APRES IMPÔTS
A74: Flux nets de trésorerie après impôts | B74: USD | C74: =C$19-C$71 | D74: =D$19-D$71 | E74: =E$19-E$71 | F74: =F$19-F$71 | G74: =G$19-G$71 | H74: =H$19-H$71 | I74: =I$19-I$71 | J74: =J$19-J$71 | ... M74: =M$19-M$71 | N74: =SUM($C74:$M74) | O74: =$C74+NPV(10%,$D74:$M74)
A75: Taux de rendement interne après impôts | B75: % | C75: =IF(ISNUMBER(IRR($C74:C74)),IF(IRR($C74:C74)>0,IRR($C74:C74),""),"") | D75: =IF(ISNUMBER(IRR($C74:D74)),IF(IRR($C74:D74)>0,IRR($C74:D74),""),"") | E75: =IF(ISNUMBER(IRR($C74:E74)),IF(IRR($C74:E74)>0,IRR($C74:E74),""),"") | F75: =IF(ISNUMBER(IRR($C74:F74)),IF(IRR($C74:F74)>0,IRR($C74:F74),""),"") | G75: =IF(ISNUMBER(IRR($C74:G74)),IF(IRR($C74:G74)>0,IRR($C74:G74),""),"") | H75: =IF(ISNUMBER(IRR($C74:H74)),IF(IRR($C74:H74)>0,IRR($C74:H74),""),"") | I75: =IF(ISNUMBER(IRR($C74:I74)),IF(IRR($C74:I74)>0,IRR($C74:I74),""),"") | J75: =IF(ISNUMBER(IRR($C74:J74)),IF(IRR($C74:J74)>0,IRR($C74:J74),""),"") | ... M75: =IF(ISNUMBER(IRR($C74:M74)),IF(IRR($C74:M74)>0,IRR($C74:M74),""),"")
A77: XV. PARTAGE DE LA RENTE MINIERE
A78: Rente minière | B78: USD | N78: =N$19 | O78: =O$19
A79: Part de l'Etat | B79: % | N79: =N$71/N$78 | O79: =O$71/O$78
A80: Part de l'investisseur | B80: % | N80: =N$74/N$78 | O80: =O$74/O$78

Sheet 09_09_Participa_2
A1: Nom | B1: Unité | C1: Année 1 | D1: Année 2 | E1: Année 3 | F1: Année 4 | G1: Année 5 | H1: Année 6 | I1: Année 7 | J1: Année 8 | K1: Année 9 | L1: Année 10 | M1: Année 11
A3: Durée restante maximum | B3: Années | C3: 11 | D3: 10 | E3: 9 | F3: 8 | G3: 7 | H3: 6 | I3: 5 | J3: 4 | K3: 3 | L3: 2 | M3: 1
A5: I. AMORTISSEMENTS DES CONSTRUCTIONS INDUSTRIELLES
A6: Durée d'amortissement linéaire | B6: Années | C6: 10
A7: Coefficient d'amortissement dégressif | B7: Coefficient | C7: 1
A9: Immobilisations de l'année A1
A10: Durée restante | B10: Années | C10: =IF($C$6<C$3,$C$6,C$3) | D10: =IF(C10=0,0,IF(C10-1<D$3,C10-1,D$3)) | E10: =IF(D10=0,0,IF(D10-1<E$3,D10-1,E$3)) | F10: =IF(E10=0,0,IF(E10-1<F$3,E10-1,F$3)) | G10: =IF(F10=0,0,IF(F10-1<G$3,F10-1,G$3)) | H10: =IF(G10=0,0,IF(G10-1<H$3,G10-1,H$3)) | I10: =IF(H10=0,0,IF(H10-1<I$3,H10-1,I$3)) | J10: =IF(I10=0,0,IF(I10-1<J$3,I10-1,J$3)) | K10: =IF(J10=0,0,IF(J10-1<K$3,J10-1,K$3)) | ... M10: =IF(L10=0,0,IF(L10-1<M$3,L10-1,M$3))
A11: Base amortissable | B11: USD | C11: =Modèle!C$9 | D11: =C15 | E11: =D15 | F11: =E15 | G11: =F15 | H11: =G15 | I11: =H15 | J11: =I15 | K11: =J15 | ... M11: =L15
A12: Inverse de la durée restante | B12: % | C12: =IF(C10=0,0,1/C10) | D12: =IF(D10=0,0,1/D10) | E12: =IF(E10=0,0,1/E10) | F12: =IF(F10=0,0,1/F10) | G12: =IF(G10=0,0,1/G10) | H12: =IF(H10=0,0,1/H10) | I12: =IF(I10=0,0,1/I10) | J12: =IF(J10=0,0,1/J10) | ... M12: =IF(M10=0,0,1/M10)
A13: Taux dégressif | B13: % | C13: =IF(C10=0,0,IF($C$7*1/$C$6>C12,$C$7*1/$C$6,C12)) | D13: =IF(D10=0,0,IF($C$7*1/$C$6>D12,$C$7*1/$C$6,D12)) | E13: =IF(E10=0,0,IF($C$7*1/$C$6>E12,$C$7*1/$C$6,E12)) | F13: =IF(F10=0,0,IF($C$7*1/$C$6>F12,$C$7*1/$C$6,F12)) | G13: =IF(G10=0,0,IF($C$7*1/$C$6>G12,$C$7*1/$C$6,G12)) | H13: =IF(H10=0,0,IF($C$7*1/$C$6>H12,$C$7*1/$C$6,H12)) | I13: =IF(I10=0,0,IF($C$7*1/$C$6>I12,$C$7*1/$C$6,I12)) | J13: =IF(J10=0,0,IF($C$7*1/$C$6>J12,$C$7*1/$C$6,J12)) | ... M13: =IF(M10=0,0,IF($C$7*1/$C$6>M12,$C$7*1/$C$6,M12))
A14: Charge d'amortissement | B14: USD | C14: =C11*C13 | D14: =D11*D13 | E14: =E11*E13 | F14: =F11*F13 | G14: =G11*G13 | H14: =H11*H13 | I14: =I11*I13 | J14: =J11*J13 | ... M14: =M11*M13
A15: Amortissement restant | B15: USD | C15: =C11-C14 | D15: =D11-D14 | E15: =E11-E14 | F15: =F11-F14 | G15: =G11-G14 | H15: =H11-H14 | I15: =I11-I14 | J15: =J11-J14 | ... M15: =M11-M14
A17: Immobilisations de l'année A2
A18: Durée restante | B18: Années | D18: =IF($C$6<D$3,$C$6,D$3) | E18: =IF(D18=0,0,IF(D18-1<E$3,D18-1,E$3)) | F18: =IF(E18=0,0,IF(E18-1<F$3,E18-1,F$3)) | G18: =IF(F18=0,0,IF(F18-1<G$3,F18-1,G$3)) | H18: =IF(G18=0,0,IF(G18-1<H$3,G18-1,H$3)) | I18: =IF(H18=0,0,IF(H18-1<I$3,H18-1,I$3)) | J18: =IF(I18=0,0,IF(I18-1<J$3,I18-1,J$3)) | K18: =IF(J18=0,0,IF(J18-1<K$3,J18-1,K$3)) | L18: =IF(K18=0,0,IF(K18-1<L$3,K18-1,L$3)) | M18: =IF(L18=0,0,IF(L18-1<M$3,L18-1,M$3))
A19: Base amortissable | B19: USD | D19: =Modèle!D$9 | E19: =D23 | F19: =E23 | G19: =F23 | H19: =G23 | I19: =H23 | J19: =I23 | K19: =J23 | L19: =K23 | M19: =L23
A20: Inverse de la durée restante | B20: % | D20: =IF(D18=0,0,1/D18) | E20: =IF(E18=0,0,1/E18) | F20: =IF(F18=0,0,1/F18) | G20: =IF(G18=0,0,1/G18) | H20: =IF(H18=0,0,1/H18) | I20: =IF(I18=0,0,1/I18) | J20: =IF(J18=0,0,1/J18) | K20: =IF(K18=0,0,1/K18) | ... M20: =IF(M18=0,0,1/M18)
A21: Taux dégressif | B21: % | D21: =IF(D18=0,0,IF($C$7*1/$C$6>D20,$C$7*1/$C$6,D20)) | E21: =IF(E18=0,0,IF($C$7*1/$C$6>E20,$C$7*1/$C$6,E20)) | F21: =IF(F18=0,0,IF($C$7*1/$C$6>F20,$C$7*1/$C$6,F20)) | G21: =IF(G18=0,0,IF($C$7*1/$C$6>G20,$C$7*1/$C$6,G20)) | H21: =IF(H18=0,0,IF($C$7*1/$C$6>H20,$C$7*1/$C$6,H20)) | I21: =IF(I18=0,0,IF($C$7*1/$C$6>I20,$C$7*1/$C$6,I20)) | J21: =IF(J18=0,0,IF($C$7*1/$C$6>J20,$C$7*1/$C$6,J20)) | K21: =IF(K18=0,0,IF($C$7*1/$C$6>K20,$C$7*1/$C$6,K20)) | ... M21: =IF(M18=0,0,IF($C$7*1/$C$6>M20,$C$7*1/$C$6,M20))
A22: Charge d'amortissement | B22: USD | D22: =D19*D21 | E22: =E19*E21 | F22: =F19*F21 | G22: =G19*G21 | H22: =H19*H21 | I22: =I19*I21 | J22: =J19*J21 | K22: =K19*K21 | ... M22: =M19*M21
A23: Amortissement restant | B23: USD | D23: =D19-D22 | E23: =E19-E22 | F23: =F19-F22 | G23: =G19-G22 | H23: =H19-H22 | I23: =I19-I22 | J23: =J19-J22 | K23: =K19-K22 | ... M23: =M19-M22
A25: Amortissements des constructions industrielles | B25: USD | C25: =C$14+C$22 | D25: =D$14+D$22 | E25: =E$14+E$22 | F25: =F$14+F$22 | G25: =G$14+G$22 | H25: =H$14+H$22 | I25: =I$14+I$22 | J25: =J$14+J$22 | ... M25: =M$14+M$22
A27: II. AMORTISSEMENTS DES BIENS D'EQUIPEMENT
A28: Durée d'amortissement linéaire | B28: Années | C28: 5
A29: Coefficient d'amortissement dégressif | B29: Coefficient | C29: 2
A31: Immobilisations de l'année A1
A32: Durée restante | B32: Années | C32: =IF($C$28<C$3,$C$28,C$3) | D32: =IF(C32=0,0,IF(C32-1<D$3,C32-1,D$3)) | E32: =IF(D32=0,0,IF(D32-1<E$3,D32-1,E$3)) | F32: =IF(E32=0,0,IF(E32-1<F$3,E32-1,F$3)) | G32: =IF(F32=0,0,IF(F32-1<G$3,F32-1,G$3)) | H32: =IF(G32=0,0,IF(G32-1<H$3,G32-1,H$3)) | I32: =IF(H32=0,0,IF(H32-1<I$3,H32-1,I$3)) | J32: =IF(I32=0,0,IF(I32-1<J$3,I32-1,J$3)) | K32: =IF(J32=0,0,IF(J32-1<K$3,J32-1,K$3)) | ... M32: =IF(L32=0,0,IF(L32-1<M$3,L32-1,M$3))
A33: Base amortissable | B33: USD | C33: =Modèle!C$10 | D33: =C37 | E33: =D37 | F33: =E37 | G33: =F37 | H33: =G37 | I33: =H37 | J33: =I37 | K33: =J37 | ... M33: =L37
A34: Inverse de la durée restante | B34: % | C34: =IF(C32=0,0,1/C32) | D34: =IF(D32=0,0,1/D32) | E34: =IF(E32=0,0,1/E32) | F34: =IF(F32=0,0,1/F32) | G34: =IF(G32=0,0,1/G32) | H34: =IF(H32=0,0,1/H32) | I34: =IF(I32=0,0,1/I32) | J34: =IF(J32=0,0,1/J32) | ... M34: =IF(M32=0,0,1/M32)
A35: Taux dégressif | B35: % | C35: =IF(C32=0,0,IF($C$29*1/$C$28>C34,$C$29*1/$C$28,C34)) | D35: =IF(D32=0,0,IF($C$29*1/$C$28>D34,$C$29*1/$C$28,D34)) | E35: =IF(E32=0,0,IF($C$29*1/$C$28>E34,$C$29*1/$C$28,E34)) | F35: =IF(F32=0,0,IF($C$29*1/$C$28>F34,$C$29*1/$C$28,F34)) | G35: =IF(G32=0,0,IF($C$29*1/$C$28>G34,$C$29*1/$C$28,G34)) | H35: =IF(H32=0,0,IF($C$29*1/$C$28>H34,$C$29*1/$C$28,H34)) | I35: =IF(I32=0,0,IF($C$29*1/$C$28>I34,$C$29*1/$C$28,I34)) | J35: =IF(J32=0,0,IF($C$29*1/$C$28>J34,$C$29*1/$C$28,J34)) | ... M35: =IF(M32=0,0,IF($C$29*1/$C$28>M34,$C$29*1/$C$28,M34))
A36: Charge d'amortissement | B36: USD | C36: =C33*C35 | D36: =D33*D35 | E36: =E33*E35 | F36: =F33*F35 | G36: =G33*G35 | H36: =H33*H35 | I36: =I33*I35 | J36: =J33*J35 | ... M36: =M33*M35
A37: Amortissement restant | B37: USD | C37: =C33-C36 | D37: =D33-D36 | E37: =E33-E36 | F37: =F33-F36 | G37: =G33-G36 | H37: =H33-H36 | I37: =I33-I36 | J37: =J33-J36 | ... M37: =M33-M36
A39: Immobilisations de l'année A2
A40: Durée restante | B40: Années | D40: =IF($C$28<D$3,$C$28,D$3) | E40: =IF(D40=0,0,IF(D40-1<E$3,D40-1,E$3)) | F40: =IF(E40=0,0,IF(E40-1<F$3,E40-1,F$3)) | G40: =IF(F40=0,0,IF(F40-1<G$3,F40-1,G$3)) | H40: =IF(G40=0,0,IF(G40-1<H$3,G40-1,H$3)) | I40: =IF(H40=0,0,IF(H40-1<I$3,H40-1,I$3)) | J40: =IF(I40=0,0,IF(I40-1<J$3,I40-1,J$3)) | K40: =IF(J40=0,0,IF(J40-1<K$3,J40-1,K$3)) | L40: =IF(K40=0,0,IF(K40-1<L$3,K40-1,L$3)) | M40: =IF(L40=0,0,IF(L40-1<M$3,L40-1,M$3))
A41: Base amortissable | B41: USD | D41: =Modèle!D$10 | E41: =D45 | F41: =E45 | G41: =F45 | H41: =G45 | I41: =H45 | J41: =I45 | K41: =J45 | L41: =K45 | M41: =L45
A42: Inverse de la durée restante | B42: % | D42: =IF(D40=0,0,1/D40) | E42: =IF(E40=0,0,1/E40) | F42: =IF(F40=0,0,1/F40) | G42: =IF(G40=0,0,1/G40) | H42: =IF(H40=0,0,1/H40) | I42: =IF(I40=0,0,1/I40) | J42: =IF(J40=0,0,1/J40) | K42: =IF(K40=0,0,1/K40) | ... M42: =IF(M40=0,0,1/M40)
A43: Taux dégressif | B43: % | D43: =IF(D40=0,0,IF($C$29*1/$C$28>D42,$C$29*1/$C$28,D42)) | E43: =IF(E40=0,0,IF($C$29*1/$C$28>E42,$C$29*1/$C$28,E42)) | F43: =IF(F40=0,0,IF($C$29*1/$C$28>F42,$C$29*1/$C$28,F42)) | G43: =IF(G40=0,0,IF($C$29*1/$C$28>G42,$C$29*1/$C$28,G42)) | H43: =IF(H40=0,0,IF($C$29*1/$C$28>H42,$C$29*1/$C$28,H42)) | I43: =IF(I40=0,0,IF($C$29*1/$C$28>I42,$C$29*1/$C$28,I42)) | J43: =IF(J40=0,0,IF($C$29*1/$C$28>J42,$C$29*1/$C$28,J42)) | K43: =IF(K40=0,0,IF($C$29*1/$C$28>K42,$C$29*1/$C$28,K42)) | ... M43: =IF(M40=0,0,IF($C$29*1/$C$28>M42,$C$29*1/$C$28,M42))
A44: Charge d'amortissement | B44: USD | D44: =D41*D43 | E44: =E41*E43 | F44: =F41*F43 | G44: =G41*G43 | H44: =H41*H43 | I44: =I41*I43 | J44: =J41*J43 | K44: =K41*K43 | ... M44: =M41*M43
A45: Amortissement restant | B45: USD | D45: =D41-D44 | E45: =E41-E44 | F45: =F41-F44 | G45: =G41-G44 | H45: =H41-H44 | I45: =I41-I44 | J45: =J41-J44 | K45: =K41-K44 | ... M45: =M41-M44
A47: Immobilisations de l'année A3
A48: Durée restante | B48: Années | E48: =IF($C$28<E$3,$C$28,E$3) | F48: =IF(E48=0,0,IF(E48-1<F$3,E48-1,F$3)) | G48: =IF(F48=0,0,IF(F48-1<G$3,F48-1,G$3)) | H48: =IF(G48=0,0,IF(G48-1<H$3,G48-1,H$3)) | I48: =IF(H48=0,0,IF(H48-1<I$3,H48-1,I$3)) | J48: =IF(I48=0,0,IF(I48-1<J$3,I48-1,J$3)) | K48: =IF(J48=0,0,IF(J48-1<K$3,J48-1,K$3)) | L48: =IF(K48=0,0,IF(K48-1<L$3,K48-1,L$3)) | M48: =IF(L48=0,0,IF(L48-1<M$3,L48-1,M$3))
A49: Base amortissable | B49: USD | E49: =Modèle!E$10 | F49: =E53 | G49: =F53 | H49: =G53 | I49: =H53 | J49: =I53 | K49: =J53 | L49: =K53 | M49: =L53
A50: Inverse de la durée restante | B50: % | E50: =IF(E48=0,0,1/E48) | F50: =IF(F48=0,0,1/F48) | G50: =IF(G48=0,0,1/G48) | H50: =IF(H48=0,0,1/H48) | I50: =IF(I48=0,0,1/I48) | J50: =IF(J48=0,0,1/J48) | K50: =IF(K48=0,0,1/K48) | L50: =IF(L48=0,0,1/L48) | M50: =IF(M48=0,0,1/M48)
A51: Taux dégressif | B51: % | E51: =IF(E48=0,0,IF($C$29*1/$C$28>E50,$C$29*1/$C$28,E50)) | F51: =IF(F48=0,0,IF($C$29*1/$C$28>F50,$C$29*1/$C$28,F50)) | G51: =IF(G48=0,0,IF($C$29*1/$C$28>G50,$C$29*1/$C$28,G50)) | H51: =IF(H48=0,0,IF($C$29*1/$C$28>H50,$C$29*1/$C$28,H50)) | I51: =IF(I48=0,0,IF($C$29*1/$C$28>I50,$C$29*1/$C$28,I50)) | J51: =IF(J48=0,0,IF($C$29*1/$C$28>J50,$C$29*1/$C$28,J50)) | K51: =IF(K48=0,0,IF($C$29*1/$C$28>K50,$C$29*1/$C$28,K50)) | L51: =IF(L48=0,0,IF($C$29*1/$C$28>L50,$C$29*1/$C$28,L50)) | M51: =IF(M48=0,0,IF($C$29*1/$C$28>M50,$C$29*1/$C$28,M50))
A52: Charge d'amortissement | B52: USD | E52: =E49*E51 | F52: =F49*F51 | G52: =G49*G51 | H52: =H49*H51 | I52: =I49*I51 | J52: =J49*J51 | K52: =K49*K51 | L52: =L49*L51 | M52: =M49*M51
A53: Amortissement restant | B53: USD | E53: =E49-E52 | F53: =F49-F52 | G53: =G49-G52 | H53: =H49-H52 | I53: =I49-I52 | J53: =J49-J52 | K53: =K49-K52 | L53: =L49-L52 | M53: =M49-M52
A55: Immobilisations de l'année A4
A56: Durée restante | B56: Années | F56: =IF($C$28<F$3,$C$28,F$3) | G56: =IF(F56=0,0,IF(F56-1<G$3,F56-1,G$3)) | H56: =IF(G56=0,0,IF(G56-1<H$3,G56-1,H$3)) | I56: =IF(H56=0,0,IF(H56-1<I$3,H56-1,I$3)) | J56: =IF(I56=0,0,IF(I56-1<J$3,I56-1,J$3)) | K56: =IF(J56=0,0,IF(J56-1<K$3,J56-1,K$3)) | L56: =IF(K56=0,0,IF(K56-1<L$3,K56-1,L$3)) | M56: =IF(L56=0,0,IF(L56-1<M$3,L56-1,M$3))
A57: Base amortissable | B57: USD | F57: =Modèle!F$10 | G57: =F61 | H57: =G61 | I57: =H61 | J57: =I61 | K57: =J61 | L57: =K61 | M57: =L61
A58: Inverse de la durée restante | B58: % | F58: =IF(F56=0,0,1/F56) | G58: =IF(G56=0,0,1/G56) | H58: =IF(H56=0,0,1/H56) | I58: =IF(I56=0,0,1/I56) | J58: =IF(J56=0,0,1/J56) | K58: =IF(K56=0,0,1/K56) | L58: =IF(L56=0,0,1/L56) | M58: =IF(M56=0,0,1/M56)
A59: Taux dégressif | B59: % | F59: =IF(F56=0,0,IF($C$29*1/$C$28>F58,$C$29*1/$C$28,F58)) | G59: =IF(G56=0,0,IF($C$29*1/$C$28>G58,$C$29*1/$C$28,G58)) | H59: =IF(H56=0,0,IF($C$29*1/$C$28>H58,$C$29*1/$C$28,H58)) | I59: =IF(I56=0,0,IF($C$29*1/$C$28>I58,$C$29*1/$C$28,I58)) | J59: =IF(J56=0,0,IF($C$29*1/$C$28>J58,$C$29*1/$C$28,J58)) | K59: =IF(K56=0,0,IF($C$29*1/$C$28>K58,$C$29*1/$C$28,K58)) | L59: =IF(L56=0,0,IF($C$29*1/$C$28>L58,$C$29*1/$C$28,L58)) | M59: =IF(M56=0,0,IF($C$29*1/$C$28>M58,$C$29*1/$C$28,M58))
A60: Charge d'amortissement | B60: USD | F60: =F57*F59 | G60: =G57*G59 | H60: =H57*H59 | I60: =I57*I59 | J60: =J57*J59 | K60: =K57*K59 | L60: =L57*L59 | M60: =M57*M59
A61: Amortissement restant | B61: USD | F61: =F57-F60 | G61: =G57-G60 | H61: =H57-H60 | I61: =I57-I60 | J61: =J57-J60 | K61: =K57-K60 | L61: =L57-L60 | M61: =M57-M60
A63: Immobilisations de l'année A5
A64: Durée restante | B64: Années | G64: =IF($C$28<G$3,$C$28,G$3) | H64: =IF(G64=0,0,IF(G64-1<H$3,G64-1,H$3)) | I64: =IF(H64=0,0,IF(H64-1<I$3,H64-1,I$3)) | J64: =IF(I64=0,0,IF(I64-1<J$3,I64-1,J$3)) | K64: =IF(J64=0,0,IF(J64-1<K$3,J64-1,K$3)) | L64: =IF(K64=0,0,IF(K64-1<L$3,K64-1,L$3)) | M64: =IF(L64=0,0,IF(L64-1<M$3,L64-1,M$3))
A65: Base amortissable | B65: USD | G65: =Modèle!G$10 | H65: =G69 | I65: =H69 | J65: =I69 | K65: =J69 | L65: =K69 | M65: =L69
A66: Inverse de la durée restante | B66: % | G66: =IF(G64=0,0,1/G64) | H66: =IF(H64=0,0,1/H64) | I66: =IF(I64=0,0,1/I64) | J66: =IF(J64=0,0,1/J64) | K66: =IF(K64=0,0,1/K64) | L66: =IF(L64=0,0,1/L64) | M66: =IF(M64=0,0,1/M64)
A67: Taux dégressif | B67: % | G67: =IF(G64=0,0,IF($C$29*1/$C$28>G66,$C$29*1/$C$28,G66)) | H67: =IF(H64=0,0,IF($C$29*1/$C$28>H66,$C$29*1/$C$28,H66)) | I67: =IF(I64=0,0,IF($C$29*1/$C$28>I66,$C$29*1/$C$28,I66)) | J67: =IF(J64=0,0,IF($C$29*1/$C$28>J66,$C$29*1/$C$28,J66)) | K67: =IF(K64=0,0,IF($C$29*1/$C$28>K66,$C$29*1/$C$28,K66)) | L67: =IF(L64=0,0,IF($C$29*1/$C$28>L66,$C$29*1/$C$28,L66)) | M67: =IF(M64=0,0,IF($C$29*1/$C$28>M66,$C$29*1/$C$28,M66))
A68: Charge d'amortissement | B68: USD | G68: =G65*G67 | H68: =H65*H67 | I68: =I65*I67 | J68: =J65*J67 | K68: =K65*K67 | L68: =L65*L67 | M68: =M65*M67
A69: Amortissement restant | B69: USD | G69: =G65-G68 | H69: =H65-H68 | I69: =I65-I68 | J69: =J65-J68 | K69: =K65-K68 | L69: =L65-L68 | M69: =M65-M68
A71: Immobilisations de l'année A6
A72: Durée restante | B72: Années | H72: =IF($C$28<H$3,$C$28,H$3) | I72: =IF(H72=0,0,IF(H72-1<I$3,H72-1,I$3)) | J72: =IF(I72=0,0,IF(I72-1<J$3,I72-1,J$3)) | K72: =IF(J72=0,0,IF(J72-1<K$3,J72-1,K$3)) | L72: =IF(K72=0,0,IF(K72-1<L$3,K72-1,L$3)) | M72: =IF(L72=0,0,IF(L72-1<M$3,L72-1,M$3))
A73: Base amortissable | B73: USD | H73: =Modèle!H$10 | I73: =H77 | J73: =I77 | K73: =J77 | L73: =K77 | M73: =L77
A74: Inverse de la durée restante | B74: % | H74: =IF(H72=0,0,1/H72) | I74: =IF(I72=0,0,1/I72) | J74: =IF(J72=0,0,1/J72) | K74: =IF(K72=0,0,1/K72) | L74: =IF(L72=0,0,1/L72) | M74: =IF(M72=0,0,1/M72)
A75: Taux dégressif | B75: % | H75: =IF(H72=0,0,IF($C$29*1/$C$28>H74,$C$29*1/$C$28,H74)) | I75: =IF(I72=0,0,IF($C$29*1/$C$28>I74,$C$29*1/$C$28,I74)) | J75: =IF(J72=0,0,IF($C$29*1/$C$28>J74,$C$29*1/$C$28,J74)) | K75: =IF(K72=0,0,IF($C$29*1/$C$28>K74,$C$29*1/$C$28,K74)) | L75: =IF(L72=0,0,IF($C$29*1/$C$28>L74,$C$29*1/$C$28,L74)) | M75: =IF(M72=0,0,IF($C$29*1/$C$28>M74,$C$29*1/$C$28,M74))
A76: Charge d'amortissement | B76: USD | H76: =H73*H75 | I76: =I73*I75 | J76: =J73*J75 | K76: =K73*K75 | L76: =L73*L75 | M76: =M73*M75
A77: Amortissement restant | B77: USD | H77: =H73-H76 | I77: =I73-I76 | J77: =J73-J76 | K77: =K73-K76 | L77: =L73-L76 | M77: =M73-M76
A79: Immobilisations de l'année A7
A80: Durée restante | B80: Années | I80: =IF($C$28<I$3,$C$28,I$3) | J80: =IF(I80=0,0,IF(I80-1<J$3,I80-1,J$3)) | K80: =IF(J80=0,0,IF(J80-1<K$3,J80-1,K$3)) | L80: =IF(K80=0,0,IF(K80-1<L$3,K80-1,L$3)) | M80: =IF(L80=0,0,IF(L80-1<M$3,L80-1,M$3))
A81: Base amortissable | B81: USD | I81: =Modèle!I$10 | J81: =I85 | K81: =J85 | L81: =K85 | M81: =L85
A82: Inverse de la durée restante | B82: % | I82: =IF(I80=0,0,1/I80) | J82: =IF(J80=0,0,1/J80) | K82: =IF(K80=0,0,1/K80) | L82: =IF(L80=0,0,1/L80) | M82: =IF(M80=0,0,1/M80)
A83: Taux dégressif | B83: % | I83: =IF(I80=0,0,IF($C$29*1/$C$28>I82,$C$29*1/$C$28,I82)) | J83: =IF(J80=0,0,IF($C$29*1/$C$28>J82,$C$29*1/$C$28,J82)) | K83: =IF(K80=0,0,IF($C$29*1/$C$28>K82,$C$29*1/$C$28,K82)) | L83: =IF(L80=0,0,IF($C$29*1/$C$28>L82,$C$29*1/$C$28,L82)) | M83: =IF(M80=0,0,IF($C$29*1/$C$28>M82,$C$29*1/$C$28,M82))
A84: Charge d'amortissement | B84: USD | I84: =I81*I83 | J84: =J81*J83 | K84: =K81*K83 | L84: =L81*L83 | M84: =M81*M83
A85: Amortissement restant | B85: USD | I85: =I81-I84 | J85: =J81-J84 | K85: =K81-K84 | L85: =L81-L84 | M85: =M81-M84
A87: Immobilisations de l'année A8
A88: Durée restante | B88: Années | J88: =IF($C$28<J$3,$C$28,J$3) | K88: =IF(J88=0,0,IF(J88-1<K$3,J88-1,K$3)) | L88: =IF(K88=0,0,IF(K88-1<L$3,K88-1,L$3)) | M88: =IF(L88=0,0,IF(L88-1<M$3,L88-1,M$3))
A89: Base amortissable | B89: USD | J89: =Modèle!J$10 | K89: =J93 | L89: =K93 | M89: =L93
