Workbook

Sheet Modèle_législation en vigueur
A1: Nom | B1: Unité | C1: Année 1 | D1: Année 2 | E1: Année 3 | F1: Année 4 | G1: Année 5 | H1: Année 6 | I1: Année 7 | J1: Année 8 | K1: Année 9 | L1: Année 10 | M1: Année 11 | N1: Année 12 | O1: Année 13 | P1: Année 14 | Q1: Année 15 | R1: SOMME | S1: VAN
A3: I. PRODUCTION
A4: Production d'or | B4: oz | E4: 300000 | F4: 300000 | G4: 300000 | H4: 300000 | I4: 300000 | J4: 300000 | K4: 300000 | L4: 300000 | M4: 300000 | N4: 300000 | O4: 300000 | P4: 300000 | R4: =SUM($C4:$Q4) -> 3600000
A5: Cours de l'or | B5: USD/oz | E5: 1600 | F5: 1300 | G5: 1300 | H5: 1300 | I5: 1300 | J5: 1300 | K5: 1300 | L5: 1300 | M5: 1300 | N5: 1300 | O5: 1300 | P5: 1300
A6: Chiffre d'affaires | B6: USD | C6: =C$4*C$5 -> 0 | D6: =D$4*D$5 -> 0 | E6: =E$4*E$5 -> 480000000 | F6: =F$4*F$5 -> 390000000 | G6: =G$4*G$5 -> 390000000 | H6: =H$4*H$5 -> 390000000 | I6: =I$4*I$5 -> 390000000 | J6: =J$4*J$5 -> 390000000 | ... Q6: =Q$4*Q$5 -> 0 | R6: =SUM($C6:$Q6) -> 4770000000 | S6: =$C6+NPV(10%,$D6:$Q6) -> 2.4901436e+09
A8: II. DEPENSES D'INVESTISSEMENT (CAPEX)
A9: Coûts des construction industrielles | B9: USD | C9: 50000000 | D9: 150000000 | R9: =SUM($C9:$Q9) -> 200000000 | S9: =$C9+NPV(10%,$D9:$Q9) -> 1.8636364e+08
A10: Coûts des biens d'équipement | B10: USD | D10: 80000000 | E10: 10000000 | F10: 10000000 | G10: 10000000 | H10: 10000000 | I10: 10000000 | J10: 10000000 | K10: 10000000 | L10: 10000000 | M10: 10000000 | N10: 10000000 | O10: 10000000 | P10: 10000000 | R10: =SUM($C10:$Q10) -> 200000000 | S10: =$C10+NPV(10%,$D10:$Q10) -> 1.3466993e+08
A11: Coûts de réhabilitation du site | B11: USD | Q11: 30000000 | R11: =SUM($C11:$Q11) -> 30000000 | S11: =$C11+NPV(10%,$D11:$Q11) -> 27272727
A12: Total des dépenses d'investissement | B12: USD | C12: =SUM(C$9:C$11) -> 50000000 | D12: =SUM(D$9:D$11) -> 230000000 | E12: =SUM(E$9:E$11) -> 10000000 | F12: =SUM(F$9:F$11) -> 10000000 | G12: =SUM(G$9:G$11) -> 10000000 | H12: =SUM(H$9:H$11) -> 10000000 | I12: =SUM(I$9:I$11) -> 10000000 | J12: =SUM(J$9:J$11) -> 10000000 | ... Q12: =SUM(Q$9:Q$11) -> 30000000 | R12: =SUM($C12:$Q12) -> 430000000 | S12: =$C12+NPV(10%,$D12:$Q12) -> 3.289335e+08
A14: III. COÛTS D'EXPLOITATION (OPEX)
A15: Coût moyen d'exploitation | B15: USD/oz | E15: 800 | F15: 800 | G15: 800 | H15: 800 | I15: 800 | J15: 800 | K15: 800 | L15: 800 | M15: 800 | N15: 800 | O15: 800 | P15: 800
A16: Total des coûts d'exploitation | B16: USD | C16: =C$4*C$15 -> 0 | D16: =D$4*D$15 -> 0 | E16: =E$4*E$15 -> 240000000 | F16: =F$4*F$15 -> 240000000 | G16: =G$4*G$15 -> 240000000 | H16: =H$4*H$15 -> 240000000 | I16: =I$4*I$15 -> 240000000 | J16: =J$4*J$15 -> 240000000 | ... Q16: =Q$4*Q$15 -> 0 | R16: =SUM($C16:$Q16) -> 2880000000 | S16: =$C16+NPV(10%,$D16:$Q16) -> 1.4866237e+09
A18: IV. FLUX NETS DE TRESORERIE AVANT IMPÔTS
A19: Flux nets de trésorerie avant impôts | B19: USD | C19: =C$6-C$12-C$16 -> -50000000 | D19: =D$6-D$12-D$16 -> -230000000 | E19: =E$6-E$12-E$16 -> 230000000 | F19: =F$6-F$12-F$16 -> 140000000 | G19: =G$6-G$12-G$16 -> 140000000 | H19: =H$6-H$12-H$16 -> 140000000 | I19: =I$6-I$12-I$16 -> 140000000 | J19: =J$6-J$12-J$16 -> 140000000 | ... Q19: =Q$6-Q$12-Q$16 -> -30000000 | R19: =SUM($C19:$Q19) -> 1460000000 | S19: =$C19+NPV(10%,$D19:$Q19) -> 6.7458646e+08
A20: Taux de rendement interne avant impôts | B20: % | C20: =IF(ISNUMBER(IRR($C19:C19)),IF(IRR($C19:C19)>0,IRR($C19:C19),""),"") | D20: =IF(ISNUMBER(IRR($C19:D19)),IF(IRR($C19:D19)>0,IRR($C19:D19),""),"") | E20: =IF(ISNUMBER(IRR($C19:E19)),IF(IRR($C19:E19)>0,IRR($C19:E19),""),"") | F20: =IF(ISNUMBER(IRR($C19:F19)),IF(IRR($C19:F19)>0,IRR($C19:F19),""),"") -> 0.19701925 | G20: =IF(ISNUMBER(IRR($C19:G19)),IF(IRR($C19:G19)>0,IRR($C19:G19),""),"") -> 0.36607214 | H20: =IF(ISNUMBER(IRR($C19:H19)),IF(IRR($C19:H19)>0,IRR($C19:H19),""),"") -> 0.45069468 | I20: =IF(ISNUMBER(IRR($C19:I19)),IF(IRR($C19:I19)>0,IRR($C19:I19),""),"") -> 0.49588878 | J20: =IF(ISNUMBER(IRR($C19:J19)),IF(IRR($C19:J19)>0,IRR($C19:J19),""),"") -> 0.52127836 | ... Q20: =IF(ISNUMBER(IRR($C19:Q19)),IF(IRR($C19:Q19)>0,IRR($C19:Q19),""),"") -> 0.55693685
A22: V. DROITS FIXES
A23: Droits fixes | B23: USD | C23: 50000 | R23: =SUM($C23:$Q23) -> 50000 | S23: =$C23+NPV(10%,$D23:$Q23) -> 50000
A25: VI. REDEVANCE SUPERFICAIRE
A26: Superficie de la mine | B26: km² | C26: 150 | D26: 150 | E26: 150 | F26: 150 | G26: 150 | H26: 150 | I26: 150 | J26: 150 | K26: 150 | L26: 150 | M26: 150 | N26: 150 | O26: 150 | P26: 150 | Q26: 150
A27: Montant de la redevance superfiaire | B27: USD/km² | C27: 100 | D27: 100 | E27: 100 | F27: 100 | G27: 100 | H27: 500 | I27: 500 | J27: 500 | K27: 500 | L27: 500 | M27: 500 | N27: 500 | O27: 500 | P27: 500 | Q27: 500
A28: Redevance superficiaire | B28: USD | C28: =C$26*C$27 -> 15000 | D28: =D$26*D$27 -> 15000 | E28: =E$26*E$27 -> 15000 | F28: =F$26*F$27 -> 15000 | G28: =G$26*G$27 -> 15000 | H28: =H$26*H$27 -> 75000 | I28: =I$26*I$27 -> 75000 | J28: =J$26*J$27 -> 75000 | ... Q28: =Q$26*Q$27 -> 75000 | R28: =SUM($C28:$Q28) -> 825000 | S28: =$C28+NPV(10%,$D28:$Q28) -> 377309.63 | U28: =S28/$S$71 -> 0.00089160537
A30: VII. REDEVANCE MINIERE
A31: Taux de la redevance minière | B31: % | C31: 0.03 | D31: 0.03 | E31: 0.03 | F31: 0.03 | G31: 0.03 | H31: 0.03 | I31: 0.03 | J31: 0.03 | K31: 0.03 | L31: 0.03 | M31: 0.03 | N31: 0.03 | O31: 0.03 | P31: 0.03 | Q31: 0.03
A32: Redevance minière | B32: USD | C32: =IF(ISNUMBER(C31),C$6*C$31,0) -> 0 | D32: =IF(ISNUMBER(D31),D$6*D$31,0) -> 0 | E32: =IF(ISNUMBER(E31),E$6*E$31,0) -> 14400000 | F32: =IF(ISNUMBER(F31),F$6*F$31,0) -> 11700000 | G32: =IF(ISNUMBER(G31),G$6*G$31,0) -> 11700000 | H32: =IF(ISNUMBER(H31),H$6*H$31,0) -> 11700000 | I32: =IF(ISNUMBER(I31),I$6*I$31,0) -> 11700000 | J32: =IF(ISNUMBER(J31),J$6*J$31,0) -> 11700000 | ... Q32: =IF(ISNUMBER(Q31),Q$6*Q$31,0) -> 0 | R32: =SUM($C32:$Q32) -> 143100000 | S32: =$C32+NPV(10%,$D32:$Q32) -> 74704309 | U32: =S32/$S$71 -> 0.17653078
A34: +. LA TAXE SUR LA RENTE
A35: Taux de revalorisation des pertes | B35: % | C35: 0.02 | D35: 0.02 | E35: 0.02 | F35: 0.02 | G35: 0.02 | H35: 0.02 | I35: 0.02 | J35: 0.02 | K35: 0.02 | L35: 0.02 | M35: 0.02 | N35: 0.02 | O35: 0.02 | P35: 0.02 | Q35: 0.02
A36: Flux nets de trésorerie revalorisés | B36: USD | C36: =IF(C19<0,C19*(1+C35),C19) -> -51000000 | D36: =IF(D19<0,D19*(1+D35),D19) -> -234600000 | E36: =IF(E19<0,E19*(1+E35),E19) -> 230000000 | F36: =IF(F19<0,F19*(1+F35),F19) -> 140000000 | G36: =IF(G19<0,G19*(1+G35),G19) -> 140000000 | H36: =IF(H19<0,H19*(1+H35),H19) -> 140000000 | I36: =IF(I19<0,I19*(1+I35),I19) -> 140000000 | J36: =IF(J19<0,J19*(1+J35),J19) -> 140000000 | ... Q36: =IF(Q19<0,Q19*(1+Q35),Q19) -> -30600000 | R36: =SUM($C36:$Q36) -> 1453800000 | S36: =$C36+NPV(10%,$D36:$Q36) -> 6.6924664e+08
A37: Taux de rendement interne | B37: % | C37: =IF(ISNUMBER(IRR($C36:C36)),IF(IRR($C36:C36)>0,IRR($C36:C36),""),"") | D37: =IF(ISNUMBER(IRR($C36:D36)),IF(IRR($C36:D36)>0,IRR($C36:D36),""),"") | E37: =IF(ISNUMBER(IRR($C36:E36)),IF(IRR($C36:E36)>0,IRR($C36:E36),""),"") | F37: =IF(ISNUMBER(IRR($C36:F36)),IF(IRR($C36:F36)>0,IRR($C36:F36),""),"") -> 0.18176457 | G37: =IF(ISNUMBER(IRR($C36:G36)),IF(IRR($C36:G36)>0,IRR($C36:G36),""),"") -> 0.35153498 | H37: =IF(ISNUMBER(IRR($C36:H36)),IF(IRR($C36:H36)>0,IRR($C36:H36),""),"") -> 0.43695198 | I37: =IF(ISNUMBER(IRR($C36:I36)),IF(IRR($C36:I36)>0,IRR($C36:I36),""),"") -> 0.48279067 | J37: =IF(ISNUMBER(IRR($C36:J36)),IF(IRR($C36:J36)>0,IRR($C36:J36),""),"") -> 0.50866839 | ... Q37: =IF(ISNUMBER(IRR($C36:Q36)),IF(IRR($C36:Q36)>0,IRR($C36:Q36),""),"") -> 0.54544451
A38: Seuil de déclenchement de la taxe sur la rente | B38: % | C38: 0.15 | D38: 0.15 | E38: 0.15 | F38: 0.15 | G38: 0.15 | H38: 0.15 | I38: 0.15 | J38: 0.15 | K38: 0.15 | L38: 0.15 | M38: 0.15 | N38: 0.15 | O38: 0.15 | P38: 0.15 | Q38: 0.15
A39: Report des pertes revalorisées | D39: =IF(C40<0,C40,0) -> -51000000 | E39: =IF(D40<0,D40,0) -> -285600000 | F39: =IF(E40<0,E40,0) -> -55600000 | G39: =IF(F40<0,F40,0) -> 0 | H39: =IF(G40<0,G40,0) -> 0 | I39: =IF(H40<0,H40,0) -> 0 | J39: =IF(I40<0,I40,0) -> 0 | K39: =IF(J40<0,J40,0) -> 0 | ... Q39: =IF(P40<0,P40,0) -> 0
A40: Flux nets de trésorerie après report des pertes revalorisées | B40: USD | C40: =C36+C39 -> -51000000 | D40: =D36+D39 -> -285600000 | E40: =E36+E39 -> -55600000 | F40: =F36+F39 -> 84400000 | G40: =G36+G39 -> 140000000 | H40: =H36+H39 -> 140000000 | I40: =I36+I39 -> 140000000 | J40: =J36+J39 -> 140000000 | ... Q40: =Q36+Q39 -> -30600000 | R40: =SUM($C40:$Q40) -> 1061600000 | S40: =$C40+NPV(10%,$D40:$Q40) -> 3.4507685e+08
A41: Taux de la taxe sur la rente | B41: % | C41: 0.2 | D41: 0.2 | E41: 0.2 | F41: 0.2 | G41: 0.2 | H41: 0.2 | I41: 0.2 | J41: 0.2 | K41: 0.2 | L41: 0.2 | M41: 0.2 | N41: 0.2 | O41: 0.2 | P41: 0.2 | Q41: 0.2
A42: Taxe sur la rente | B42: USD | C42: =IF(C37<C38,0,IF(C40<0,0,C40*C41)) -> 0 | D42: =IF(D37<D38,0,IF(D40<0,0,D40*D41)) -> 0 | E42: =IF(E37<E38,0,IF(E40<0,0,E40*E41)) -> 0 | F42: =IF(F37<F38,0,IF(F40<0,0,F40*F41)) -> 16880000 | G42: =IF(G37<G38,0,IF(G40<0,0,G40*G41)) -> 28000000 | H42: =IF(H37<H38,0,IF(H40<0,0,H40*H41)) -> 28000000 | I42: =IF(I37<I38,0,IF(I40<0,0,I40*I41)) -> 28000000 | J42: =IF(J37<J38,0,IF(J40<0,0,J40*J41)) -> 28000000 | ... Q42: =IF(Q37<Q38,0,IF(Q40<0,0,Q40*Q41)) -> 0 | R42: =SUM($C42:$Q42) -> 296880000 | S42: =$C42+NPV(10%,$D42:$Q42) -> 1.4194431e+08 | U42: =S42/$S$71 -> 0.33542295
A44: VIII. IMPÔT SUR LES SOCIETES (IS)
A45: Bénéfice avant report des pertes | B45: USD | C45: =C$6-C$16-C$23-C$28-C$32-C$42+'Amortissements et Emprunt'!C191 -> -7565000 | D45: =D$6-D$16-D$23-D$28-D$32-D$42+'Amortissements et Emprunt'!D191 -> -41765000 | E45: =E$6-E$16-E$23-E$28-E$32-E$42+'Amortissements et Emprunt'!E191 -> 184235000 | F45: =F$6-F$16-F$23-F$28-F$32-F$42+'Amortissements et Emprunt'!F191 -> 80455000 | G45: =G$6-G$16-G$23-G$28-G$32-G$42+'Amortissements et Emprunt'!G191 -> 69735000 | H45: =H$6-H$16-H$23-H$28-H$32-H$42+'Amortissements et Emprunt'!H191 -> 70075000 | I45: =I$6-I$16-I$23-I$28-I$32-I$42+'Amortissements et Emprunt'!I191 -> 70363889 | J45: =J$6-J$16-J$23-J$28-J$32-J$42+'Amortissements et Emprunt'!J191 -> 70513889 | ... Q45: =Q$6-Q$16-Q$23-Q$28-Q$32-Q$42+'Amortissements et Emprunt'!Q191 -> -49364683 | R45: =SUM($C45:$Q45) -> 942145000 | S45: =$C45+NPV(10%,$D45:$Q45) -> 5.023728e+08
A46: Report des pertes | B46: USD | D46: =IF(C47<0,C47,0) -> -7565000 | E46: =IF(D47<0,D47,0) -> -49330000 | F46: =IF(E47<0,E47,0) -> 0 | G46: =IF(F47<0,F47,0) -> 0 | H46: =IF(G47<0,G47,0) -> 0 | I46: =IF(H47<0,H47,0) -> 0 | J46: =IF(I47<0,I47,0) -> 0 | K46: =IF(J47<0,J47,0) -> 0 | ... Q46: =IF(P47<0,P47,0) -> 0
A47: Bénéfice fiscal | B47: USD | C47: =C$45+C$46 -> -7565000 | D47: =D$45+D$46 -> -49330000 | E47: =E$45+E$46 -> 134905000 | F47: =F$45+F$46 -> 80455000 | G47: =G$45+G$46 -> 69735000 | H47: =H$45+H$46 -> 70075000 | I47: =I$45+I$46 -> 70363889 | J47: =J$45+J$46 -> 70513889 | ... Q47: =Q$45+Q$46 -> -49364683 | R47: =SUM($C47:$Q47) -> 885250000 | S47: =$C47+NPV(10%,$D47:$Q47) -> 4.5472693e+08
A48: Taux de l'impôt sur les sociétés | B48: % | C48: 0.3 | D48: 0.3 | E48: 0.3 | F48: 0.3 | G48: 0.3 | H48: 0.3 | I48: 0.3 | J48: 0.3 | K48: 0.3 | L48: 0.3 | M48: 0.3 | N48: 0.3 | O48: 0.3 | P48: 0.3 | Q48: 0.3
A49: Impôt sur les sociétés | B49: USD | C49: =IF(C$47>0,C$47*C$48,0) -> 0 | D49: =IF(D$47>0,D$47*D$48,0) -> 0 | E49: =IF(E$47>0,E$47*E$48,0) -> 40471500 | F49: =IF(F$47>0,F$47*F$48,0) -> 24136500 | G49: =IF(G$47>0,G$47*G$48,0) -> 20920500 | H49: =IF(H$47>0,H$47*H$48,0) -> 21022500 | I49: =IF(I$47>0,I$47*I$48,0) -> 21109167 | J49: =IF(J$47>0,J$47*J$48,0) -> 21154167 | ... Q49: =IF(Q$47>0,Q$47*Q$48,0) -> 0 | R49: =SUM($C49:$Q49) -> 2.974529e+08 | S49: =$C49+NPV(10%,$D49:$Q49) -> 1.56041e+08
A51: IX. IMPÔT MINIMUM FORFAITAIRE (IMF)
A52: Montant minimum | B52: USD | C52: 0 | D52: 0 | E52: 0 | F52: 0 | G52: 0 | H52: 0 | I52: 0 | J52: 0 | K52: 0 | L52: 0 | M52: 0 | N52: 0 | O52: 0 | P52: 0 | Q52: 0
A53: Taux de l'impôt minimum forfaitaire | B53: % | C53: 0.005 | D53: 0.005 | E53: 0.005 | F53: 0.005 | G53: 0.005 | H53: 0.005 | I53: 0.005 | J53: 0.005 | K53: 0.005 | L53: 0.005 | M53: 0.005 | N53: 0.005 | O53: 0.005 | P53: 0.005 | Q53: 0.005
A54: Impôt minimum forfaitaire | B54: USD | C54: =IF(C$6*C$53>C$52,C$6*C$53,C$52) -> 0 | D54: =IF(D$6*D$53>D$52,D$6*D$53,D$52) -> 0 | E54: =IF(E$6*E$53>E$52,E$6*E$53,E$52) -> 2400000 | F54: =IF(F$6*F$53>F$52,F$6*F$53,F$52) -> 1950000 | G54: =IF(G$6*G$53>G$52,G$6*G$53,G$52) -> 1950000 | H54: =IF(H$6*H$53>H$52,H$6*H$53,H$52) -> 1950000 | I54: =IF(I$6*I$53>I$52,I$6*I$53,I$52) -> 1950000 | J54: =IF(J$6*J$53>J$52,J$6*J$53,J$52) -> 1950000 | ... Q54: =IF(Q$6*Q$53>Q$52,Q$6*Q$53,Q$52) -> 0 | R54: =SUM($C54:$Q54) -> 23850000 | S54: =$C54+NPV(10%,$D54:$Q54) -> 12450718
A56: X. IMPÔT SUR LES SOCIETES (IS) / IMPÔT MINIMUM FORFAITAIRE (IMF)
A57: Impôt sur les sociétés / Impôt minimum forfaitaire | B57: USD | C57: =IF(C$54>C$49,C$54,C$49) -> 0 | D57: =IF(D$54>D$49,D$54,D$49) -> 0 | E57: =IF(E$54>E$49,E$54,E$49) -> 40471500 | F57: =IF(F$54>F$49,F$54,F$49) -> 24136500 | G57: =IF(G$54>G$49,G$54,G$49) -> 20920500 | H57: =IF(H$54>H$49,H$54,H$49) -> 21022500 | I57: =IF(I$54>I$49,I$54,I$49) -> 21109167 | J57: =IF(J$54>J$49,J$54,J$49) -> 21154167 | ... Q57: =IF(Q$54>Q$49,Q$54,Q$49) -> 0 | R57: =SUM($C57:$Q57) -> 2.974529e+08 | S57: =$C57+NPV(10%,$D57:$Q57) -> 1.56041e+08 | U57: =S57/$S$71 -> 0.36873427
A59: XI. PARTICIPATION DE L'ETAT
A60: Bénéfice distribuable | B60: USD | C60: =IF(C$47-C$57>0,C$47-C$57,0) -> 0 | D60: =IF(D$47-D$57>0,D$47-D$57,0) -> 0 | E60: =IF(E$47-E$57>0,E$47-E$57,0) -> 94433500 | F60: =IF(F$47-F$57>0,F$47-F$57,0) -> 56318500 | G60: =IF(G$47-G$57>0,G$47-G$57,0) -> 48814500 | H60: =IF(H$47-H$57>0,H$47-H$57,0) -> 49052500 | I60: =IF(I$47-I$57>0,I$47-I$57,0) -> 49254722 | J60: =IF(J$47-J$57>0,J$47-J$57,0) -> 49359722 | ... Q60: =IF(Q$47-Q$57>0,Q$47-Q$57,0) -> 0 | R60: =SUM($C60:$Q60) -> 6.9405678e+08 | S60: =$C60+NPV(10%,$D60:$Q60) -> 3.6409566e+08
A61: Taux de la participation de l'Etat | B61: % | C61: 0.1 | D61: 0.1 | E61: 0.1 | F61: 0.1 | G61: 0.1 | H61: 0.1 | I61: 0.1 | J61: 0.1 | K61: 0.1 | L61: 0.1 | M61: 0.1 | N61: 0.1 | O61: 0.1 | P61: 0.1 | Q61: 0.1
A62: Participation de l'Etat | B62: USD | C62: =C$60*C$61 -> 0 | D62: =D$60*D$61 -> 0 | E62: =E$60*E$61 -> 9443350 | F62: =F$60*F$61 -> 5631850 | G62: =G$60*G$61 -> 4881450 | H62: =H$60*H$61 -> 4905250 | I62: =I$60*I$61 -> 4925472.2 | J62: =J$60*J$61 -> 4935972.2 | ... Q62: =Q$60*Q$61 -> 0 | R62: =SUM($C62:$Q62) -> 69405678 | S62: =$C62+NPV(10%,$D62:$Q62) -> 36409566 | U62: =S62/$S$71 -> 0.086037995
A64: XII. IMPÔT SUR LE REVENU DES VALEURS MOBILIERS (IRVM)
A65: Part distribuée aux actionnaires privés | B65: % | C65: 0.25 | D65: 0.25 | E65: 0.25 | F65: 0.25 | G65: 0.25 | H65: 0.25 | I65: 0.25 | J65: 0.25 | K65: 0.25 | L65: 0.25 | M65: 0.25 | N65: 0.25 | O65: 0.25 | P65: 0.25 | Q65: 0.25
A66: Dividendes distribués aux actionnaires privés | B66: USD | C66: =C$60*C$65 -> 0 | D66: =D$60*D$65 -> 0 | E66: =E$60*E$65 -> 23608375 | F66: =F$60*F$65 -> 14079625 | G66: =G$60*G$65 -> 12203625 | H66: =H$60*H$65 -> 12263125 | I66: =I$60*I$65 -> 12313681 | J66: =J$60*J$65 -> 12339931 | ... Q66: =Q$60*Q$65 -> 0 | R66: =SUM($C66:$Q66) -> 1.7351419e+08 | S66: =$C66+NPV(10%,$D66:$Q66) -> 91023914
A67: Taux de l'impöt sur le revenu des valeurs mobilières | B67: % | C67: 0.15 | D67: 0.15 | E67: 0.15 | F67: 0.15 | G67: 0.15 | H67: 0.15 | I67: 0.15 | J67: 0.15 | K67: 0.15 | L67: 0.15 | M67: 0.15 | N67: 0.15 | O67: 0.15 | P67: 0.15 | Q67: 0.15
A68: Impöt sur le revenu des valeurs mobilières | B68: USD | C68: =C$66*C$67 -> 0 | D68: =D$66*D$67 -> 0 | E68: =E$66*E$67 -> 3541256.2 | F68: =F$66*F$67 -> 2111943.8 | G68: =G$66*G$67 -> 1830543.8 | H68: =H$66*H$67 -> 1839468.8 | I68: =I$66*I$67 -> 1847052.1 | J68: =J$66*J$67 -> 1850989.6 | ... Q68: =Q$66*Q$67 -> 0 | R68: =SUM($C68:$Q68) -> 26027129 | S68: =$C68+NPV(10%,$D68:$Q68) -> 13653587 | U68: =S68/$S$71 -> 0.032264248
A70: XIII. PRELEVEMENTS PUBLICS
A71: Total des prélèvements publics | B71: USD | C71: =C$23+C$28+C$32+C$42+C$57+C$62+C$68 -> 65000 | D71: =D$23+D$28+D$32+D$42+D$57+D$62+D$68 -> 15000 | E71: =E$23+E$28+E$32+E$42+E$57+E$62+E$68 -> 67871106 | F71: =F$23+F$28+F$32+F$42+F$57+F$62+F$68 -> 60475294 | G71: =G$23+G$28+G$32+G$42+G$57+G$62+G$68 -> 67347494 | H71: =H$23+H$28+H$32+H$42+H$57+H$62+H$68 -> 67542219 | I71: =I$23+I$28+I$32+I$42+I$57+I$62+I$68 -> 67656691 | J71: =J$23+J$28+J$32+J$42+J$57+J$62+J$68 -> 67716128 | ... Q71: =Q$23+Q$28+Q$32+Q$42+Q$57+Q$62+Q$68 -> 75000 | R71: =SUM($C71:$Q71) -> 8.3374071e+08 | S71: =$C71+NPV(10%,$D71:$Q71) -> 4.2318008e+08
A73: XIV. FLUX NETS DE TRESORERIE APRES IMPÔTS
A74: Flux nets de trésorerie après impôts | B74: USD | C74: =C$19-C$71 -> -50065000 | D74: =D$19-D$71 -> -230015000 | E74: =E$19-E$71 -> 1.6212889e+08 | F74: =F$19-F$71 -> 79524706 | G74: =G$19-G$71 -> 72652506 | H74: =H$19-H$71 -> 72457781 | I74: =I$19-I$71 -> 72343309 | J74: =J$19-J$71 -> 72283872 | ... Q74: =Q$19-Q$71 -> -30075000 | R74: =SUM($C74:$Q74) -> 6.2625929e+08 | S74: =$C74+NPV(10%,$D74:$Q74) -> 2.5140638e+08
A75: Taux de rendement interne après impôts | B75: % | C75: =IF(ISNUMBER(IRR($C74:C74)),IF(IRR($C74:C74)>0,IRR($C74:C74),""),"") | D75: =IF(ISNUMBER(IRR($C74:D74)),IF(IRR($C74:D74)>0,IRR($C74:D74),""),"") | E75: =IF(ISNUMBER(IRR($C74:E74)),IF(IRR($C74:E74)>0,IRR($C74:E74),""),"") | F75: =IF(ISNUMBER(IRR($C74:F74)),IF(IRR($C74:F74)>0,IRR($C74:F74),""),"") | G75: =IF(ISNUMBER(IRR($C74:G74)),IF(IRR($C74:G74)>0,IRR($C74:G74),""),"") -> 0.063300609 | H75: =IF(ISNUMBER(IRR($C74:H74)),IF(IRR($C74:H74)>0,IRR($C74:H74),""),"") -> 0.15502156 | I75: =IF(ISNUMBER(IRR($C74:I74)),IF(IRR($C74:I74)>0,IRR($C74:I74),""),"") -> 0.21072177 | J75: =IF(ISNUMBER(IRR($C74:J74)),IF(IRR($C74:J74)>0,IRR($C74:J74),""),"") -> 0.24595252 | ... Q75: =IF(ISNUMBER(IRR($C74:Q74)),IF(IRR($C74:Q74)>0,IRR($C74:Q74),""),"") -> 0.30862359
A77: XV. PARTAGE DE LA RENTE MINIERE
A78: Rente minière | B78: USD | R78: =R$19 -> 1460000000 | S78: =S$19 -> 6.7458646e+08
A79: Part de l'Etat | B79: % | R79: =R$71/R$78 -> 0.57105528 | S79: =S$71/S$78 -> 0.62731778
A80: Part de l'investisseur | B80: % | R80: =R$74/R$78 -> 0.42894472 | S80: =S$74/S$78 -> 0.37268222

Sheet Modèle_projet de loi
A1: Nom | B1: Unité | C1: Année 1 | D1: Année 2 | E1: Année 3 | F1: Année 4 | G1: Année 5 | H1: Année 6 | I1: Année 7 | J1: Année 8 | K1: Année 9 | L1: Année 10 | M1: Année 11 | N1: Année 12 | O1: Année 13 | P1: Année 14 | Q1: Année 15 | R1: SOMME | S1: VAN
A3: I. PRODUCTION
A4: Production d'or | B4: oz | E4: 300000 | F4: 300000 | G4: 300000 | H4: 300000 | I4: 300000 | J4: 300000 | K4: 300000 | L4: 300000 | M4: 300000 | N4: 300000 | O4: 300000 | P4: 300000 | R4: =SUM($C4:$Q4) -> 3600000
A5: Cours de l'or | B5: USD/oz | E5: 1600 | F5: 1600 | G5: 1600 | H5: 1600 | I5: 1600 | J5: 1600 | K5: 1600 | L5: 1600 | M5: 1600 | N5: 1600 | O5: 1600 | P5: 1600
A6: Chiffre d'affaires | B6: USD | C6: =C$4*C$5 -> 0 | D6: =D$4*D$5 -> 0 | E6: =E$4*E$5 -> 480000000 | F6: =F$4*F$5 -> 480000000 | G6: =G$4*G$5 -> 480000000 | H6: =H$4*H$5 -> 480000000 | I6: =I$4*I$5 -> 480000000 | J6: =J$4*J$5 -> 480000000 | ... Q6: =Q$4*Q$5 -> 0 | R6: =SUM($C6:$Q6) -> 5760000000 | S6: =$C6+NPV(10%,$D6:$Q6) -> 2.9732473e+09
A8: II. DEPENSES D'INVESTISSEMENT (CAPEX)
A9: Coûts des construction industrielles | B9: USD | C9: 50000000 | D9: 150000000 | R9: =SUM($C9:$Q9) -> 200000000 | S9: =$C9+NPV(10%,$D9:$Q9) -> 1.8636364e+08
A10: Coûts des biens d'équipement | B10: USD | D10: 80000000 | E10: 10000000 | F10: 10000000 | G10: 10000000 | H10: 10000000 | I10: 10000000 | J10: 10000000 | K10: 10000000 | L10: 10000000 | M10: 10000000 | N10: 10000000 | O10: 10000000 | P10: 10000000 | R10: =SUM($C10:$Q10) -> 200000000 | S10: =$C10+NPV(10%,$D10:$Q10) -> 1.3466993e+08
A11: Coûts de réhabilitation du site | B11: USD | Q11: 30000000 | R11: =SUM($C11:$Q11) -> 30000000 | S11: =$C11+NPV(10%,$D11:$Q11) -> 27272727
A12: Total des dépenses d'investissement | B12: USD | C12: =SUM(C$9:C$11) -> 50000000 | D12: =SUM(D$9:D$11) -> 230000000 | E12: =SUM(E$9:E$11) -> 10000000 | F12: =SUM(F$9:F$11) -> 10000000 | G12: =SUM(G$9:G$11) -> 10000000 | H12: =SUM(H$9:H$11) -> 10000000 | I12: =SUM(I$9:I$11) -> 10000000 | J12: =SUM(J$9:J$11) -> 10000000 | ... Q12: =SUM(Q$9:Q$11) -> 30000000 | R12: =SUM($C12:$Q12) -> 430000000 | S12: =$C12+NPV(10%,$D12:$Q12) -> 3.289335e+08
A14: III. COÛTS D'EXPLOITATION (OPEX)
A15: Coût moyen d'exploitation | B15: USD/oz | E15: 800 | F15: 800 | G15: 800 | H15: 800 | I15: 800 | J15: 800 | K15: 800 | L15: 800 | M15: 800 | N15: 800 | O15: 800 | P15: 800
A16: Total des coûts d'exploitation | B16: USD | C16: =C$4*C$15 -> 0 | D16: =D$4*D$15 -> 0 | E16: =E$4*E$15 -> 240000000 | F16: =F$4*F$15 -> 240000000 | G16: =G$4*G$15 -> 240000000 | H16: =H$4*H$15 -> 240000000 | I16: =I$4*I$15 -> 240000000 | J16: =J$4*J$15 -> 240000000 | ... Q16: =Q$4*Q$15 -> 0 | R16: =SUM($C16:$Q16) -> 2880000000 | S16: =$C16+NPV(10%,$D16:$Q16) -> 1.4866237e+09
A18: IV. FLUX NETS DE TRESORERIE AVANT IMPÔTS
A19: Flux nets de trésorerie avant impôts | B19: USD | C19: =C$6-C$12-C$16 -> -50000000 | D19: =D$6-D$12-D$16 -> -230000000 | E19: =E$6-E$12-E$16 -> 230000000 | F19: =F$6-F$12-F$16 -> 230000000 | G19: =G$6-G$12-G$16 -> 230000000 | H19: =H$6-H$12-H$16 -> 230000000 | I19: =I$6-I$12-I$16 -> 230000000 | J19: =J$6-J$12-J$16 -> 230000000 | ... Q19: =Q$6-Q$12-Q$16 -> -30000000 | R19: =SUM($C19:$Q19) -> 2450000000 | S19: =$C19+NPV(10%,$D19:$Q19) -> 1.1576902e+09
A20: Taux de rendement interne avant impôts | B20: % | C20: =IF(ISNUMBER(IRR($C19:C19)),IF(IRR($C19:C19)>0,IRR($C19:C19),""),"") | D20: =IF(ISNUMBER(IRR($C19:D19)),IF(IRR($C19:D19)>0,IRR($C19:D19),""),"") | E20: =IF(ISNUMBER(IRR($C19:E19)),IF(IRR($C19:E19)>0,IRR($C19:E19),""),"") | F20: =IF(ISNUMBER(IRR($C19:F19)),IF(IRR($C19:F19)>0,IRR($C19:F19),""),"") -> 0.34744637 | G20: =IF(ISNUMBER(IRR($C19:G19)),IF(IRR($C19:G19)>0,IRR($C19:G19),""),"") -> 0.54585935 | H20: =IF(ISNUMBER(IRR($C19:H19)),IF(IRR($C19:H19)>0,IRR($C19:H19),""),"") -> 0.63444649 | I20: =IF(ISNUMBER(IRR($C19:I19)),IF(IRR($C19:I19)>0,IRR($C19:I19),""),"") -> 0.67761811 | J20: =IF(ISNUMBER(IRR($C19:J19)),IF(IRR($C19:J19)>0,IRR($C19:J19),""),"") -> 0.69990923 | ... Q20: =IF(ISNUMBER(IRR($C19:Q19)),IF(IRR($C19:Q19)>0,IRR($C19:Q19),""),"") -> 0.72605458
A22: V. DROITS FIXES
A23: Droits fixes | B23: USD | C23: 5000000 | R23: =SUM($C23:$Q23) -> 5000000 | S23: =$C23+NPV(10%,$D23:$Q23) -> 5000000
A25: VI. REDEVANCE SUPERFICAIRE
A26: Superficie de la mine | B26: km² | C26: 150 | D26: 150 | E26: 150 | F26: 150 | G26: 150 | H26: 150 | I26: 150 | J26: 150 | K26: 150 | L26: 150 | M26: 150 | N26: 150 | O26: 150 | P26: 150 | Q26: 150
A27: Montant de la redevance superfiaire | B27: USD/km² | C27: 100 | D27: 100 | E27: 100 | F27: 100 | G27: 100 | H27: 500 | I27: 500 | J27: 500 | K27: 500 | L27: 500 | M27: 500 | N27: 500 | O27: 500 | P27: 500 | Q27: 500
A28: Redevance superficiaire | B28: USD | C28: =C$26*C$27 -> 15000 | D28: =D$26*D$27 -> 15000 | E28: =E$26*E$27 -> 15000 | F28: =F$26*F$27 -> 15000 | G28: =G$26*G$27 -> 15000 | H28: =H$26*H$27 -> 75000 | I28: =I$26*I$27 -> 75000 | J28: =J$26*J$27 -> 75000 | ... Q28: =Q$26*Q$27 -> 75000 | R28: =SUM($C28:$Q28) -> 825000 | S28: =$C28+NPV(10%,$D28:$Q28) -> 377309.63 | U28: =S28/$S$71 -> 0.00050563352
A30: VII. REDEVANCE MINIERE
A31: Taux de la redevance minière | B31: % | C31: 0.06 | D31: 0.06 | E31: 0.06 | F31: 0.06 | G31: 0.06 | H31: 0.06 | I31: 0.06 | J31: 0.06 | K31: 0.06 | L31: 0.06 | M31: 0.06 | N31: 0.06 | O31: 0.06 | P31: 0.06 | Q31: 0.06
A32: Redevance minière | B32: USD | C32: =IF(ISNUMBER(C31),C$6*C$31,0) -> 0 | D32: =IF(ISNUMBER(D31),D$6*D$31,0) -> 0 | E32: =IF(ISNUMBER(E31),E$6*E$31,0) -> 28800000 | F32: =IF(ISNUMBER(F31),F$6*F$31,0) -> 28800000 | G32: =IF(ISNUMBER(G31),G$6*G$31,0) -> 28800000 | H32: =IF(ISNUMBER(H31),H$6*H$31,0) -> 28800000 | I32: =IF(ISNUMBER(I31),I$6*I$31,0) -> 28800000 | J32: =IF(ISNUMBER(J31),J$6*J$31,0) -> 28800000 | ... Q32: =IF(ISNUMBER(Q31),Q$6*Q$31,0) -> 0 | R32: =SUM($C32:$Q32) -> 345600000 | S32: =$C32+NPV(10%,$D32:$Q32) -> 1.7839484e+08 | U32: =S32/$S$71 -> 0.23906734
A34: +. LA TAXE SUR LA RENTE
A35: Taux de revalorisation des pertes | B35: % | C35: 0.02 | D35: 0.02 | E35: 0.02 | F35: 0.02 | G35: 0.02 | H35: 0.02 | I35: 0.02 | J35: 0.02 | K35: 0.02 | L35: 0.02 | M35: 0.02 | N35: 0.02 | O35: 0.02 | P35: 0.02 | Q35: 0.02
A36: Flux nets de trésorerie revalorisés | B36: USD | C36: =IF(C19<0,C19*(1+C35),C19) -> -51000000 | D36: =IF(D19<0,D19*(1+D35),D19) -> -234600000 | E36: =IF(E19<0,E19*(1+E35),E19) -> 230000000 | F36: =IF(F19<0,F19*(1+F35),F19) -> 230000000 | G36: =IF(G19<0,G19*(1+G35),G19) -> 230000000 | H36: =IF(H19<0,H19*(1+H35),H19) -> 230000000 | I36: =IF(I19<0,I19*(1+I35),I19) -> 230000000 | J36: =IF(J19<0,J19*(1+J35),J19) -> 230000000 | ... Q36: =IF(Q19<0,Q19*(1+Q35),Q19) -> -30600000 | R36: =SUM($C36:$Q36) -> 2443800000 | S36: =$C36+NPV(10%,$D36:$Q36) -> 1.1523504e+09
A37: Taux de rendement interne | B37: % | C37: =IF(ISNUMBER(IRR($C36:C36)),IF(IRR($C36:C36)>0,IRR($C36:C36),""),"") | D37: =IF(ISNUMBER(IRR($C36:D36)),IF(IRR($C36:D36)>0,IRR($C36:D36),""),"") | E37: =IF(ISNUMBER(IRR($C36:E36)),IF(IRR($C36:E36)>0,IRR($C36:E36),""),"") | F37: =IF(ISNUMBER(IRR($C36:F36)),IF(IRR($C36:F36)>0,IRR($C36:F36),""),"") -> 0.33140025 | G37: =IF(ISNUMBER(IRR($C36:G36)),IF(IRR($C36:G36)>0,IRR($C36:G36),""),"") -> 0.53041424 | H37: =IF(ISNUMBER(IRR($C36:H36)),IF(IRR($C36:H36)>0,IRR($C36:H36),""),"") -> 0.61973587 | I37: =IF(ISNUMBER(IRR($C36:I36)),IF(IRR($C36:I36)>0,IRR($C36:I36),""),"") -> 0.66348955 | J37: =IF(ISNUMBER(IRR($C36:J36)),IF(IRR($C36:J36)>0,IRR($C36:J36),""),"") -> 0.68620185 | ... Q37: =IF(ISNUMBER(IRR($C36:Q36)),IF(IRR($C36:Q36)>0,IRR($C36:Q36),""),"") -> 0.71316911
A38: Seuil de déclenchement de la taxe sur la rente | B38: % | C38: 0.15 | D38: 0.15 | E38: 0.15 | F38: 0.15 | G38: 0.15 | H38: 0.15 | I38: 0.15 | J38: 0.15 | K38: 0.15 | L38: 0.15 | M38: 0.15 | N38: 0.15 | O38: 0.15 | P38: 0.15 | Q38: 0.15
A39: Report des pertes revalorisées | D39: =IF(C40<0,C40,0) -> -51000000 | E39: =IF(D40<0,D40,0) -> -285600000 | F39: =IF(E40<0,E40,0) -> -55600000 | G39: =IF(F40<0,F40,0) -> 0 | H39: =IF(G40<0,G40,0) -> 0 | I39: =IF(H40<0,H40,0) -> 0 | J39: =IF(I40<0,I40,0) -> 0 | K39: =IF(J40<0,J40,0) -> 0 | ... Q39: =IF(P40<0,P40,0) -> 0
A40: Flux nets de trésorerie après report des pertes revalorisées | B40: USD | C40: =C36+C39 -> -51000000 | D40: =D36+D39 -> -285600000 | E40: =E36+E39 -> -55600000 | F40: =F36+F39 -> 174400000 | G40: =G36+G39 -> 230000000 | H40: =H36+H39 -> 230000000 | I40: =I36+I39 -> 230000000 | J40: =J36+J39 -> 230000000 | ... Q40: =Q36+Q39 -> -30600000 | R40: =SUM($C40:$Q40) -> 2051600000 | S40: =$C40+NPV(10%,$D40:$Q40) -> 8.2818056e+08
A41: Taux de la taxe sur la rente | B41: % | C41: 0.2 | D41: 0.2 | E41: 0.2 | F41: 0.2 | G41: 0.2 | H41: 0.2 | I41: 0.2 | J41: 0.2 | K41: 0.2 | L41: 0.2 | M41: 0.2 | N41: 0.2 | O41: 0.2 | P41: 0.2 | Q41: 0.2
A42: Taxe sur la rente | B42: USD | C42: =IF(C37<C38,0,IF(C40<0,0,C40*C41)) -> 0 | D42: =IF(D37<D38,0,IF(D40<0,0,D40*D41)) -> 0 | E42: =IF(E37<E38,0,IF(E40<0,0,E40*E41)) -> 0 | F42: =IF(F37<F38,0,IF(F40<0,0,F40*F41)) -> 34880000 | G42: =IF(G37<G38,0,IF(G40<0,0,G40*G41)) -> 46000000 | H42: =IF(H37<H38,0,IF(H40<0,0,H40*H41)) -> 46000000 | I42: =IF(I37<I38,0,IF(I40<0,0,I40*I41)) -> 46000000 | J42: =IF(J37<J38,0,IF(J40<0,0,J40*J41)) -> 46000000 | ... Q42: =IF(Q37<Q38,0,IF(Q40<0,0,Q40*Q41)) -> 0 | R42: =SUM($C42:$Q42) -> 494880000 | S42: =$C42+NPV(10%,$D42:$Q42) -> 2.3856505e+08 | U42: =S42/$S$71 -> 0.31970159
A44: VIII. IMPÔT SUR LES SOCIETES (IS)
A45: Bénéfice avant report des pertes | B45: USD | C45: =C$6-C$16-C$23-C$28-C$32-C$42+'Amortissements et Emprunt'!C191 -> -12515000 | D45: =D$6-D$16-D$23-D$28-D$32-D$42+'Amortissements et Emprunt'!D191 -> -41765000 | E45: =E$6-E$16-E$23-E$28-E$32-E$42+'Amortissements et Emprunt'!E191 -> 169835000 | F45: =F$6-F$16-F$23-F$28-F$32-F$42+'Amortissements et Emprunt'!F191 -> 135355000 | G45: =G$6-G$16-G$23-G$28-G$32-G$42+'Amortissements et Emprunt'!G191 -> 124635000 | H45: =H$6-H$16-H$23-H$28-H$32-H$42+'Amortissements et Emprunt'!H191 -> 124975000 | I45: =I$6-I$16-I$23-I$28-I$32-I$42+'Amortissements et Emprunt'!I191 -> 1.2526389e+08 | J45: =J$6-J$16-J$23-J$28-J$32-J$42+'Amortissements et Emprunt'!J191 -> 1.2541389e+08 | ... Q45: =Q$6-Q$16-Q$23-Q$28-Q$32-Q$42+'Amortissements et Emprunt'!Q191 -> -49364683 | R45: =SUM($C45:$Q45) -> 1.526695e+09 | S45: =$C45+NPV(10%,$D45:$Q45) -> 7.8021524e+08
A46: Report des pertes | B46: USD | D46: =IF(C47<0,C47,0) -> -12515000 | E46: =IF(D47<0,D47,0) -> -54280000 | F46: =IF(E47<0,E47,0) -> 0 | G46: =IF(F47<0,F47,0) -> 0 | H46: =IF(G47<0,G47,0) -> 0 | I46: =IF(H47<0,H47,0) -> 0 | J46: =IF(I47<0,I47,0) -> 0 | K46: =IF(J47<0,J47,0) -> 0 | ... Q46: =IF(P47<0,P47,0) -> 0
A47: Bénéfice fiscal | B47: USD | C47: =C$45+C$46 -> -12515000 | D47: =D$45+D$46 -> -54280000 | E47: =E$45+E$46 -> 115555000 | F47: =F$45+F$46 -> 135355000 | G47: =G$45+G$46 -> 124635000 | H47: =H$45+H$46 -> 124975000 | I47: =I$45+I$46 -> 1.2526389e+08 | J47: =J$45+J$46 -> 1.2541389e+08 | ... Q47: =Q$45+Q$46 -> -49364683 | R47: =SUM($C47:$Q47) -> 1.4599e+09 | S47: =$C47+NPV(10%,$D47:$Q47) -> 7.2397846e+08
A48: Taux de l'impôt sur les sociétés | B48: % | C48: 0 | D48: 0 | E48: 0 | F48: 0.35 | G48: 0.35 | H48: 0.35 | I48: 0.35 | J48: 0.35 | K48: 0.35 | L48: 0.35 | M48: 0.35 | N48: 0.35 | O48: 0.35 | P48: 0.35 | Q48: 0.35
A49: Impôt sur les sociétés | B49: USD | C49: =IF(C$47>0,C$47*C$48,0) -> 0 | D49: =IF(D$47>0,D$47*D$48,0) -> 0 | E49: =IF(E$47>0,E$47*E$48,0) -> 0 | F49: =IF(F$47>0,F$47*F$48,0) -> 47374250 | G49: =IF(G$47>0,G$47*G$48,0) -> 43622250 | H49: =IF(H$47>0,H$47*H$48,0) -> 43741250 | I49: =IF(I$47>0,I$47*I$48,0) -> 43842361 | J49: =IF(J$47>0,J$47*J$48,0) -> 43894861 | ... Q49: =IF(Q$47>0,Q$47*Q$48,0) -> 0 | R49: =SUM($C49:$Q49) -> 5.1117664e+08 | S49: =$C49+NPV(10%,$D49:$Q49) -> 2.4616836e+08
A51: IX. IMPÔT MINIMUM FORFAITAIRE (IMF)
A52: Montant minimum | B52: USD | C52: 1500 | D52: 1500 | E52: 1500 | F52: 1500 | G52: 1500 | H52: 1500 | I52: 1500 | J52: 1500 | K52: 1500 | L52: 1500 | M52: 1500 | N52: 1500 | O52: 1500 | P52: 1500 | Q52: 1500
A53: Taux de l'impôt minimum forfaitaire | B53: % | C53: 0.005 | D53: 0.005 | E53: 0.005 | F53: 0.005 | G53: 0.005 | H53: 0.005 | I53: 0.005 | J53: 0.005 | K53: 0.005 | L53: 0.005 | M53: 0.005 | N53: 0.005 | O53: 0.005 | P53: 0.005 | Q53: 0.005
A54: Impôt minimum forfaitaire | B54: USD | C54: =IF(C$6*C$53>C$52,C$6*C$53,C$52) -> 1500 | D54: =IF(D$6*D$53>D$52,D$6*D$53,D$52) -> 1500 | E54: =IF(E$6*E$53>E$52,E$6*E$53,E$52) -> 2400000 | F54: =IF(F$6*F$53>F$52,F$6*F$53,F$52) -> 2400000 | G54: =IF(G$6*G$53>G$52,G$6*G$53,G$52) -> 2400000 | H54: =IF(H$6*H$53>H$52,H$6*H$53,H$52) -> 2400000 | I54: =IF(I$6*I$53>I$52,I$6*I$53,I$52) -> 2400000 | J54: =IF(J$6*J$53>J$52,J$6*J$53,J$52) -> 2400000 | ... Q54: =IF(Q$6*Q$53>Q$52,Q$6*Q$53,Q$52) -> 1500 | R54: =SUM($C54:$Q54) -> 28804500 | S54: =$C54+NPV(10%,$D54:$Q54) -> 14869495
A56: X. IMPÔT SUR LES SOCIETES (IS) / IMPÔT MINIMUM FORFAITAIRE (IMF)
A57: Impôt sur les sociétés / Impôt minimum forfaitaire | B57: USD | C57: =IF(C$54>C$49,C$54,C$49) -> 1500 | D57: =IF(D$54>D$49,D$54,D$49) -> 1500 | E57: =IF(E$54>E$49,E$54,E$49) -> 2400000 | F57: =IF(F$54>F$49,F$54,F$49) -> 47374250 | G57: =IF(G$54>G$49,G$54,G$49) -> 43622250 | H57: =IF(H$54>H$49,H$54,H$49) -> 43741250 | I57: =IF(I$54>I$49,I$54,I$49) -> 43842361 | J57: =IF(J$54>J$49,J$54,J$49) -> 43894861 | ... Q57: =IF(Q$54>Q$49,Q$54,Q$49) -> 1500 | R57: =SUM($C57:$Q57) -> 5.1358114e+08 | S57: =$C57+NPV(10%,$D57:$Q57) -> 2.4815509e+08 | U57: =S57/$S$71 -> 0.33255322
A59: XI. PARTICIPATION DE L'ETAT
A60: Bénéfice distribuable | B60: USD | C60: =IF(C$47-C$57>0,C$47-C$57,0) -> 0 | D60: =IF(D$47-D$57>0,D$47-D$57,0) -> 0 | E60: =IF(E$47-E$57>0,E$47-E$57,0) -> 113155000 | F60: =IF(F$47-F$57>0,F$47-F$57,0) -> 87980750 | G60: =IF(G$47-G$57>0,G$47-G$57,0) -> 81012750 | H60: =IF(H$47-H$57>0,H$47-H$57,0) -> 81233750 | I60: =IF(I$47-I$57>0,I$47-I$57,0) -> 81421528 | J60: =IF(J$47-J$57>0,J$47-J$57,0) -> 81519028 | ... Q60: =IF(Q$47-Q$57>0,Q$47-Q$57,0) -> 0 | R60: =SUM($C60:$Q60) -> 1.062483e+09 | S60: =$C60+NPV(10%,$D60:$Q60) -> 5.5068635e+08
A61: Taux de la participation de l'Etat | B61: % | C61: 0.1 | D61: 0.1 | E61: 0.1 | F61: 0.1 | G61: 0.1 | H61: 0.1 | I61: 0.1 | J61: 0.1 | K61: 0.1 | L61: 0.1 | M61: 0.1 | N61: 0.1 | O61: 0.1 | P61: 0.1 | Q61: 0.1
A62: Participation de l'Etat | B62: USD | C62: =C$60*C$61 -> 0 | D62: =D$60*D$61 -> 0 | E62: =E$60*E$61 -> 11315500 | F62: =F$60*F$61 -> 8798075 | G62: =G$60*G$61 -> 8101275 | H62: =H$60*H$61 -> 8123375 | I62: =I$60*I$61 -> 8142152.8 | J62: =J$60*J$61 -> 8151902.8 | ... Q62: =Q$60*Q$61 -> 0 | R62: =SUM($C62:$Q62) -> 1.062483e+08 | S62: =$C62+NPV(10%,$D62:$Q62) -> 55068635 | U62: =S62/$S$71 -> 0.073797606
A64: XII. IMPÔT SUR LE REVENU DES VALEURS MOBILIERS (IRVM)
A65: Part distribuée aux actionnaires privés | B65: % | C65: 0.25 | D65: 0.25 | E65: 0.25 | F65: 0.25 | G65: 0.25 | H65: 0.25 | I65: 0.25 | J65: 0.25 | K65: 0.25 | L65: 0.25 | M65: 0.25 | N65: 0.25 | O65: 0.25 | P65: 0.25 | Q65: 0.25
A66: Dividendes distribués aux actionnaires privés | B66: USD | C66: =C$60*C$65 -> 0 | D66: =D$60*D$65 -> 0 | E66: =E$60*E$65 -> 28288750 | F66: =F$60*F$65 -> 21995188 | G66: =G$60*G$65 -> 20253188 | H66: =H$60*H$65 -> 20308438 | I66: =I$60*I$65 -> 20355382 | J66: =J$60*J$65 -> 20379757 | ... Q66: =Q$60*Q$65 -> 0 | R66: =SUM($C66:$Q66) -> 2.6562076e+08 | S66: =$C66+NPV(10%,$D66:$Q66) -> 1.3767159e+08
A67: Taux de l'impöt sur le revenu des valeurs mobilières | B67: % | C67: 0.15 | D67: 0.15 | E67: 0.15 | F67: 0.15 | G67: 0.15 | H67: 0.15 | I67: 0.15 | J67: 0.15 | K67: 0.15 | L67: 0.15 | M67: 0.15 | N67: 0.15 | O67: 0.15 | P67: 0.15 | Q67: 0.15
A68: Impöt sur le revenu des valeurs mobilières | B68: USD | C68: =C$66*C$67 -> 0 | D68: =D$66*D$67 -> 0 | E68: =E$66*E$67 -> 4243312.5 | F68: =F$66*F$67 -> 3299278.1 | G68: =G$66*G$67 -> 3037978.1 | H68: =H$66*H$67 -> 3046265.6 | I68: =I$66*I$67 -> 3053307.3 | J68: =J$66*J$67 -> 3056963.5 | ... Q68: =Q$66*Q$67 -> 0 | R68: =SUM($C68:$Q68) -> 39843114 | S68: =$C68+NPV(10%,$D68:$Q68) -> 20650738 | U68: =S68/$S$71 -> 0.027674102
A70: XIII. PRELEVEMENTS PUBLICS
A71: Total des prélèvements publics | B71: USD | C71: =C$23+C$28+C$32+C$42+C$57+C$62+C$68 -> 5016500 | D71: =D$23+D$28+D$32+D$42+D$57+D$62+D$68 -> 16500 | E71: =E$23+E$28+E$32+E$42+E$57+E$62+E$68 -> 46773812 | F71: =F$23+F$28+F$32+F$42+F$57+F$62+F$68 -> 1.231666e+08 | G71: =G$23+G$28+G$32+G$42+G$57+G$62+G$68 -> 1.295765e+08 | H71: =H$23+H$28+H$32+H$42+H$57+H$62+H$68 -> 1.2978589e+08 | I71: =I$23+I$28+I$32+I$42+I$57+I$62+I$68 -> 1.2991282e+08 | J71: =J$23+J$28+J$32+J$42+J$57+J$62+J$68 -> 1.2997873e+08 | ... Q71: =Q$23+Q$28+Q$32+Q$42+Q$57+Q$62+Q$68 -> 76500 | R71: =SUM($C71:$Q71) -> 1.5059776e+09 | S71: =$C71+NPV(10%,$D71:$Q71) -> 7.4621167e+08
A73: XIV. FLUX NETS DE TRESORERIE APRES IMPÔTS
A74: Flux nets de trésorerie après impôts | B74: USD | C74: =C$19-C$71 -> -55016500 | D74: =D$19-D$71 -> -230016500 | E74: =E$19-E$71 -> 1.8322619e+08 | F74: =F$19-F$71 -> 1.068334e+08 | G74: =G$19-G$71 -> 1.004235e+08 | H74: =H$19-H$71 -> 1.0021411e+08 | I74: =I$19-I$71 -> 1.0008718e+08 | J74: =J$19-J$71 -> 1.0002127e+08 | ... Q74: =Q$19-Q$71 -> -30076500 | R74: =SUM($C74:$Q74) -> 9.4402244e+08 | S74: =$C74+NPV(10%,$D74:$Q74) -> 4.114785e+08
A75: Taux de rendement interne après impôts | B75: % | C75: =IF(ISNUMBER(IRR($C74:C74)),IF(IRR($C74:C74)>0,IRR($C74:C74),""),"") | D75: =IF(ISNUMBER(IRR($C74:D74)),IF(IRR($C74:D74)>0,IRR($C74:D74),""),"") | E75: =IF(ISNUMBER(IRR($C74:E74)),IF(IRR($C74:E74)>0,IRR($C74:E74),""),"") | F75: =IF(ISNUMBER(IRR($C74:F74)),IF(IRR($C74:F74)>0,IRR($C74:F74),""),"") -> 0.011262472 | G75: =IF(ISNUMBER(IRR($C74:G74)),IF(IRR($C74:G74)>0,IRR($C74:G74),""),"") -> 0.17617686 | H75: =IF(ISNUMBER(IRR($C74:H74)),IF(IRR($C74:H74)>0,IRR($C74:H74),""),"") -> 0.26642849 | I75: =IF(ISNUMBER(IRR($C74:I74)),IF(IRR($C74:I74)>0,IRR($C74:I74),""),"") -> 0.31841387 | J75: =IF(ISNUMBER(IRR($C74:J74)),IF(IRR($C74:J74)>0,IRR($C74:J74),""),"") -> 0.34980117 | ... Q75: =IF(ISNUMBER(IRR($C74:Q74)),IF(IRR($C74:Q74)>0,IRR($C74:Q74),""),"") -> 0.40069973
A77: XV. PARTAGE DE LA RENTE MINIERE
A78: Rente minière | B78: USD | R78: =R$19 -> 2450000000 | S78: =S$19 -> 1.1576902e+09
A79: Part de l'Etat | B79: % | R79: =R$71/R$78 -> 0.61468472 | S79: =S$71/S$78 -> 0.64456941
A80: Part de l'investisseur | B80: % | R80: =R$74/R$78 -> 0.38531528 | S80: =S$74/S$78 -> 0.35543059

Sheet Amortissements et Emprunt
A1: Nom | B1: Unité | C1: Année 1 | D1: Année 2 | E1: Année 3 | F1: Année 4 | G1: Année 5 | H1: Année 6 | I1: Année 7 | J1: Année 8 | K1: Année 9 | L1: Année 10 | M1: Année 11 | N1: Année 12 | O1: Année 13 | P1: Année 14 | Q1: Année 15
A3: Durée restante maximum | B3: Années | C3: 15 | D3: 14 | E3: 13 | F3: 12 | G3: 11 | H3: 10 | I3: 9 | J3: 8 | K3: 7 | L3: 6 | M3: 5 | N3: 4 | O3: 3 | P3: 2 | Q3: 1
A5: I. AMORTISSEMENTS DES CONSTRUCTIONS INDUSTRIELLES
A6: Durée d'amortissement linéaire | B6: Années | C6: 10
A7: Coefficient d'amortissement dégressif | B7: Coefficient | C7: 1
A9: Immobilisations de l'année A1
A10: Durée restante | B10: Années | C10: =IF($C$6<C$3,$C$6,C$3) -> 10 | D10: =IF(C10=0,0,IF(C10-1<D$3,C10-1,D$3)) -> 9 | E10: =IF(D10=0,0,IF(D10-1<E$3,D10-1,E$3)) -> 8 | F10: =IF(E10=0,0,IF(E10-1<F$3,E10-1,F$3)) -> 7 | G10: =IF(F10=0,0,IF(F10-1<G$3,F10-1,G$3)) -> 6 | H10: =IF(G10=0,0,IF(G10-1<H$3,G10-1,H$3)) -> 5 | I10: =IF(H10=0,0,IF(H10-1<I$3,H10-1,I$3)) -> 4 | J10: =IF(I10=0,0,IF(I10-1<J$3,I10-1,J$3)) -> 3 | K10: =IF(J10=0,0,IF(J10-1<K$3,J10-1,K$3)) -> 2 | ... Q10: =IF(P10=0,0,IF(P10-1<Q$3,P10-1,Q$3)) -> 0
A11: Base amortissable | B11: USD | C11: ='Modèle_législation en vigueur'!C9 -> 50000000 | D11: =C15 -> 45000000 | E11: =D15 -> 40000000 | F11: =E15 -> 35000000 | G11: =F15 -> 30000000 | H11: =G15 -> 25000000 | I11: =H15 -> 20000000 | J11: =I15 -> 15000000 | K11: =J15 -> 10000000 | ... Q11: =P15 -> 0
A12: Inverse de la durée restante | B12: % | C12: =IF(C10=0,0,1/C10) -> 0.1 | D12: =IF(D10=0,0,1/D10) -> 0.11111111 | E12: =IF(E10=0,0,1/E10) -> 0.125 | F12: =IF(F10=0,0,1/F10) -> 0.14285714 | G12: =IF(G10=0,0,1/G10) -> 0.16666667 | H12: =IF(H10=0,0,1/H10) -> 0.2 | I12: =IF(I10=0,0,1/I10) -> 0.25 | J12: =IF(J10=0,0,1/J10) -> 0.33333333 | ... Q12: =IF(Q10=0,0,1/Q10) -> 0
A13: Taux dégressif | B13: % | C13: =IF(C10=0,0,IF($C$7*1/$C$6>C12,$C$7*1/$C$6,C12)) -> 0.1 | D13: =IF(D10=0,0,IF($C$7*1/$C$6>D12,$C$7*1/$C$6,D12)) -> 0.11111111 | E13: =IF(E10=0,0,IF($C$7*1/$C$6>E12,$C$7*1/$C$6,E12)) -> 0.125 | F13: =IF(F10=0,0,IF($C$7*1/$C$6>F12,$C$7*1/$C$6,F12)) -> 0.14285714 | G13: =IF(G10=0,0,IF($C$7*1/$C$6>G12,$C$7*1/$C$6,G12)) -> 0.16666667 | H13: =IF(H10=0,0,IF($C$7*1/$C$6>H12,$C$7*1/$C$6,H12)) -> 0.2 | I13: =IF(I10=0,0,IF($C$7*1/$C$6>I12,$C$7*1/$C$6,I12)) -> 0.25 | J13: =IF(J10=0,0,IF($C$7*1/$C$6>J12,$C$7*1/$C$6,J12)) -> 0.33333333 | ... Q13: =IF(Q10=0,0,IF($C$7*1/$C$6>Q12,$C$7*1/$C$6,Q12)) -> 0
A14: Charge d'amortissement | B14: USD | C14: =C11*C13 -> 5000000 | D14: =D11*D13 -> 5000000 | E14: =E11*E13 -> 5000000 | F14: =F11*F13 -> 5000000 | G14: =G11*G13 -> 5000000 | H14: =H11*H13 -> 5000000 | I14: =I11*I13 -> 5000000 | J14: =J11*J13 -> 5000000 | ... Q14: =Q11*Q13 -> 0
A15: Amortissement restant | B15: USD | C15: =C11-C14 -> 45000000 | D15: =D11-D14 -> 40000000 | E15: =E11-E14 -> 35000000 | F15: =F11-F14 -> 30000000 | G15: =G11-G14 -> 25000000 | H15: =H11-H14 -> 20000000 | I15: =I11-I14 -> 15000000 | J15: =J11-J14 -> 10000000 | ... Q15: =Q11-Q14 -> 0
A17: Immobilisations de l'année A2
A18: Durée restante | B18: Années | D18: =IF($C$6<D$3,$C$6,D$3) -> 10 | E18: =IF(D18=0,0,IF(D18-1<E$3,D18-1,E$3)) -> 9 | F18: =IF(E18=0,0,IF(E18-1<F$3,E18-1,F$3)) -> 8 | G18: =IF(F18=0,0,IF(F18-1<G$3,F18-1,G$3)) -> 7 | H18: =IF(G18=0,0,IF(G18-1<H$3,G18-1,H$3)) -> 6 | I18: =IF(H18=0,0,IF(H18-1<I$3,H18-1,I$3)) -> 5 | J18: =IF(I18=0,0,IF(I18-1<J$3,I18-1,J$3)) -> 4 | K18: =IF(J18=0,0,IF(J18-1<K$3,J18-1,K$3)) -> 3 | L18: =IF(K18=0,0,IF(K18-1<L$3,K18-1,L$3)) -> 2 | ... Q18: =IF(P18=0,0,IF(P18-1<Q$3,P18-1,Q$3)) -> 0
A19: Base amortissable | B19: USD | D19: ='Modèle_législation en vigueur'!D9 -> 150000000 | E19: =D23 -> 135000000 | F19: =E23 -> 120000000 | G19: =F23 -> 105000000 | H19: =G23 -> 90000000 | I19: =H23 -> 75000000 | J19: =I23 -> 60000000 | K19: =J23 -> 45000000 | L19: =K23 -> 30000000 | ... Q19: =P23 -> 0
A20: Inverse de la durée restante | B20: % | D20: =IF(D18=0,0,1/D18) -> 0.1 | E20: =IF(E18=0,0,1/E18) -> 0.11111111 | F20: =IF(F18=0,0,1/F18) -> 0.125 | G20: =IF(G18=0,0,1/G18) -> 0.14285714 | H20: =IF(H18=0,0,1/H18) -> 0.16666667 | I20: =IF(I18=0,0,1/I18) -> 0.2 | J20: =IF(J18=0,0,1/J18) -> 0.25 | K20: =IF(K18=0,0,1/K18) -> 0.33333333 | ... Q20: =IF(Q18=0,0,1/Q18) -> 0
A21: Taux dégressif | B21: % | D21: =IF(D18=0,0,IF($C$7*1/$C$6>D20,$C$7*1/$C$6,D20)) -> 0.1 | E21: =IF(E18=0,0,IF($C$7*1/$C$6>E20,$C$7*1/$C$6,E20)) -> 0.11111111 | F21: =IF(F18=0,0,IF($C$7*1/$C$6>F20,$C$7*1/$C$6,F20)) -> 0.125 | G21: =IF(G18=0,0,IF($C$7*1/$C$6>G20,$C$7*1/$C$6,G20)) -> 0.14285714 | H21: =IF(H18=0,0,IF($C$7*1/$C$6>H20,$C$7*1/$C$6,H20)) -> 0.16666667 | I21: =IF(I18=0,0,IF($C$7*1/$C$6>I20,$C$7*1/$C$6,I20)) -> 0.2 | J21: =IF(J18=0,0,IF($C$7*1/$C$6>J20,$C$7*1/$C$6,J20)) -> 0.25 | K21: =IF(K18=0,0,IF($C$7*1/$C$6>K20,$C$7*1/$C$6,K20)) -> 0.33333333 | ... Q21: =IF(Q18=0,0,IF($C$7*1/$C$6>Q20,$C$7*1/$C$6,Q20)) -> 0
A22: Charge d'amortissement | B22: USD | D22: =D19*D21 -> 15000000 | E22: =E19*E21 -> 15000000 | F22: =F19*F21 -> 15000000 | G22: =G19*G21 -> 15000000 | H22: =H19*H21 -> 15000000 | I22: =I19*I21 -> 15000000 | J22: =J19*J21 -> 15000000 | K22: =K19*K21 -> 15000000 | ... Q22: =Q19*Q21 -> 0
A23: Amortissement restant | B23: USD | D23: =D19-D22 -> 135000000 | E23: =E19-E22 -> 120000000 | F23: =F19-F22 -> 105000000 | G23: =G19-G22 -> 90000000 | H23: =H19-H22 -> 75000000 | I23: =I19-I22 -> 60000000 | J23: =J19-J22 -> 45000000 | K23: =K19-K22 -> 30000000 | ... Q23: =Q19-Q22 -> 0
A25: Amortissements des constructions industrielles | B25: USD | C25: =C$14+C$22 -> 5000000 | D25: =D$14+D$22 -> 20000000 | E25: =E$14+E$22 -> 20000000 | F25: =F$14+F$22 -> 20000000 | G25: =G$14+G$22 -> 20000000 | H25: =H$14+H$22 -> 20000000 | I25: =I$14+I$22 -> 20000000 | J25: =J$14+J$22 -> 20000000 | ... Q25: =Q$14+Q$22 -> 0
A27: II. AMORTISSEMENTS DES BIENS D'EQUIPEMENT
A28: Durée d'amortissement linéaire | B28: Années | C28: 15
A29: Coefficient d'amortissement dégressif | B29: Coefficient | C29: 1.5
A31: Immobilisations de l'année A1
A32: Durée restante | B32: Années | C32: =IF($C$6<C$3,$C$6,C$3) -> 10 | D32: =IF(C32=0,0,IF(C32-1<D$3,C32-1,D$3)) -> 9 | E32: =IF(D32=0,0,IF(D32-1<E$3,D32-1,E$3)) -> 8 | F32: =IF(E32=0,0,IF(E32-1<F$3,E32-1,F$3)) -> 7 | G32: =IF(F32=0,0,IF(F32-1<G$3,F32-1,G$3)) -> 6 | H32: =IF(G32=0,0,IF(G32-1<H$3,G32-1,H$3)) -> 5 | I32: =IF(H32=0,0,IF(H32-1<I$3,H32-1,I$3)) -> 4 | J32: =IF(I32=0,0,IF(I32-1<J$3,I32-1,J$3)) -> 3 | K32: =IF(J32=0,0,IF(J32-1<K$3,J32-1,K$3)) -> 2 | ... Q32: =IF(P32=0,0,IF(P32-1<Q$3,P32-1,Q$3)) -> 0
A33: Base amortissable | B33: USD | C33: ='Modèle_législation en vigueur'!C10 -> 0 | D33: =C37 -> 0 | E33: =D37 -> 0 | F33: =E37 -> 0 | G33: =F37 -> 0 | H33: =G37 -> 0 | I33: =H37 -> 0 | J33: =I37 -> 0 | K33: =J37 -> 0 | ... Q33: =P37 -> 0
A34: Inverse de la durée restante | B34: % | C34: =IF(C32=0,0,1/C32) -> 0.1 | D34: =IF(D32=0,0,1/D32) -> 0.11111111 | E34: =IF(E32=0,0,1/E32) -> 0.125 | F34: =IF(F32=0,0,1/F32) -> 0.14285714 | G34: =IF(G32=0,0,1/G32) -> 0.16666667 | H34: =IF(H32=0,0,1/H32) -> 0.2 | I34: =IF(I32=0,0,1/I32) -> 0.25 | J34: =IF(J32=0,0,1/J32) -> 0.33333333 | ... Q34: =IF(Q32=0,0,1/Q32) -> 0
A35: Taux dégressif | B35: % | C35: =IF(C32=0,0,IF($C$29*1/$C$28>C34,$C$29*1/$C$28,C34)) -> 0.1 | D35: =IF(D32=0,0,IF($C$29*1/$C$28>D34,$C$29*1/$C$28,D34)) -> 0.11111111 | E35: =IF(E32=0,0,IF($C$29*1/$C$28>E34,$C$29*1/$C$28,E34)) -> 0.125 | F35: =IF(F32=0,0,IF($C$29*1/$C$28>F34,$C$29*1/$C$28,F34)) -> 0.14285714 | G35: =IF(G32=0,0,IF($C$29*1/$C$28>G34,$C$29*1/$C$28,G34)) -> 0.16666667 | H35: =IF(H32=0,0,IF($C$29*1/$C$28>H34,$C$29*1/$C$28,H34)) -> 0.2 | I35: =IF(I32=0,0,IF($C$29*1/$C$28>I34,$C$29*1/$C$28,I34)) -> 0.25 | J35: =IF(J32=0,0,IF($C$29*1/$C$28>J34,$C$29*1/$C$28,J34)) -> 0.33333333 | ... Q35: =IF(Q32=0,0,IF($C$29*1/$C$28>Q34,$C$29*1/$C$28,Q34)) -> 0
A36: Charge d'amortissement | B36: USD | C36: =C33*C35 -> 0 | D36: =D33*D35 -> 0 | E36: =E33*E35 -> 0 | F36: =F33*F35 -> 0 | G36: =G33*G35 -> 0 | H36: =H33*H35 -> 0 | I36: =I33*I35 -> 0 | J36: =J33*J35 -> 0 | ... Q36: =Q33*Q35 -> 0
A37: Amortissement restant | B37: USD | C37: =C33-C36 -> 0 | D37: =D33-D36 -> 0 | E37: =E33-E36 -> 0 | F37: =F33-F36 -> 0 | G37: =G33-G36 -> 0 | H37: =H33-H36 -> 0 | I37: =I33-I36 -> 0 | J37: =J33-J36 -> 0 | ... Q37: =Q33-Q36 -> 0
A39: Immobilisations de l'année A2
A40: Durée restante | B40: Années | D40: =IF($C$6<D$3,$C$6,D$3) -> 10 | E40: =IF(D40=0,0,IF(D40-1<E$3,D40-1,E$3)) -> 9 | F40: =IF(E40=0,0,IF(E40-1<F$3,E40-1,F$3)) -> 8 | G40: =IF(F40=0,0,IF(F40-1<G$3,F40-1,G$3)) -> 7 | H40: =IF(G40=0,0,IF(G40-1<H$3,G40-1,H$3)) -> 6 | I40: =IF(H40=0,0,IF(H40-1<I$3,H40-1,I$3)) -> 5 | J40: =IF(I40=0,0,IF(I40-1<J$3,I40-1,J$3)) -> 4 | K40: =IF(J40=0,0,IF(J40-1<K$3,J40-1,K$3)) -> 3 | L40: =IF(K40=0,0,IF(K40-1<L$3,K40-1,L$3)) -> 2 | ... Q40: =IF(P40=0,0,IF(P40-1<Q$3,P40-1,Q$3)) -> 0
A41: Base amortissable | B41: USD | D41: ='Modèle_législation en vigueur'!D10 -> 80000000 | E41: =D45 -> 72000000 | F41: =E45 -> 64000000 | G41: =F45 -> 56000000 | H41: =G45 -> 48000000 | I41: =H45 -> 40000000 | J41: =I45 -> 32000000 | K41: =J45 -> 24000000 | L41: =K45 -> 16000000 | ... Q41: =P45 -> 0
A42: Inverse de la durée restante | B42: % | D42: =IF(D40=0,0,1/D40) -> 0.1 | E42: =IF(E40=0,0,1/E40) -> 0.11111111 | F42: =IF(F40=0,0,1/F40) -> 0.125 | G42: =IF(G40=0,0,1/G40) -> 0.14285714 | H42: =IF(H40=0,0,1/H40) -> 0.16666667 | I42: =IF(I40=0,0,1/I40) -> 0.2 | J42: =IF(J40=0,0,1/J40) -> 0.25 | K42: =IF(K40=0,0,1/K40) -> 0.33333333 | ... Q42: =IF(Q40=0,0,1/Q40) -> 0
A43: Taux dégressif | B43: % | D43: =IF(D40=0,0,IF($C$29*1/$C$28>D42,$C$29*1/$C$28,D42)) -> 0.1 | E43: =IF(E40=0,0,IF($C$29*1/$C$28>E42,$C$29*1/$C$28,E42)) -> 0.11111111 | F43: =IF(F40=0,0,IF($C$29*1/$C$28>F42,$C$29*1/$C$28,F42)) -> 0.125 | G43: =IF(G40=0,0,IF($C$29*1/$C$28>G42,$C$29*1/$C$28,G42)) -> 0.14285714 | H43: =IF(H40=0,0,IF($C$29*1/$C$28>H42,$C$29*1/$C$28,H42)) -> 0.16666667 | I43: =IF(I40=0,0,IF($C$29*1/$C$28>I42,$C$29*1/$C$28,I42)) -> 0.2 | J43: =IF(J40=0,0,IF($C$29*1/$C$28>J42,$C$29*1/$C$28,J42)) -> 0.25 | K43: =IF(K40=0,0,IF($C$29*1/$C$28>K42,$C$29*1/$C$28,K42)) -> 0.33333333 | ... Q43: =IF(Q40=0,0,IF($C$29*1/$C$28>Q42,$C$29*1/$C$28,Q42)) -> 0
A44: Charge d'amortissement | B44: USD | D44: =D41*D43 -> 8000000 | E44: =E41*E43 -> 8000000 | F44: =F41*F43 -> 8000000 | G44: =G41*G43 -> 8000000 | H44: =H41*H43 -> 8000000 | I44: =I41*I43 -> 8000000 | J44: =J41*J43 -> 8000000 | K44: =K41*K43 -> 8000000 | ... Q44: =Q41*Q43 -> 0
A45: Amortissement restant | B45: USD | D45: =D41-D44 -> 72000000 | E45: =E41-E44 -> 64000000 | F45: =F41-F44 -> 56000000 | G45: =G41-G44 -> 48000000 | H45: =H41-H44 -> 40000000 | I45: =I41-I44 -> 32000000 | J45: =J41-J44 -> 24000000 | K45: =K41-K44 -> 16000000 | ... Q45: =Q41-Q44 -> 0
A47: Immobilisations de l'année A3
A48: Durée restante | B48: Années | E48: =IF($C$6<E$3,$C$6,E$3) -> 10 | F48: =IF(E48=0,0,IF(E48-1<F$3,E48-1,F$3)) -> 9 | G48: =IF(F48=0,0,IF(F48-1<G$3,F48-1,G$3)) -> 8 | H48: =IF(G48=0,0,IF(G48-1<H$3,G48-1,H$3)) -> 7 | I48: =IF(H48=0,0,IF(H48-1<I$3,H48-1,I$3)) -> 6 | J48: =IF(I48=0,0,IF(I48-1<J$3,I48-1,J$3)) -> 5 | K48: =IF(J48=0,0,IF(J48-1<K$3,J48-1,K$3)) -> 4 | L48: =IF(K48=0,0,IF(K48-1<L$3,K48-1,L$3)) -> 3 | M48: =IF(L48=0,0,IF(L48-1<M$3,L48-1,M$3)) -> 2 | ... Q48: =IF(P48=0,0,IF(P48-1<Q$3,P48-1,Q$3)) -> 0
A49: Base amortissable | B49: USD | E49: ='Modèle_législation en vigueur'!E10 -> 10000000 | F49: =E53 -> 9000000 | G49: =F53 -> 8000000 | H49: =G53 -> 7000000 | I49: =H53 -> 6000000 | J49: =I53 -> 5000000 | K49: =J53 -> 4000000 | L49: =K53 -> 3000000 | M49: =L53 -> 2000000 | ... Q49: =P53 -> 0
A50: Inverse de la durée restante | B50: % | E50: =IF(E48=0,0,1/E48) -> 0.1 | F50: =IF(F48=0,0,1/F48) -> 0.11111111 | G50: =IF(G48=0,0,1/G48) -> 0.125 | H50: =IF(H48=0,0,1/H48) -> 0.14285714 | I50: =IF(I48=0,0,1/I48) -> 0.16666667 | J50: =IF(J48=0,0,1/J48) -> 0.2 | K50: =IF(K48=0,0,1/K48) -> 0.25 | L50: =IF(L48=0,0,1/L48) -> 0.33333333 | ... Q50: =IF(Q48=0,0,1/Q48) -> 0
A51: Taux dégressif | B51: % | E51: =IF(E48=0,0,IF($C$29*1/$C$28>E50,$C$29*1/$C$28,E50)) -> 0.1 | F51: =IF(F48=0,0,IF($C$29*1/$C$28>F50,$C$29*1/$C$28,F50)) -> 0.11111111 | G51: =IF(G48=0,0,IF($C$29*1/$C$28>G50,$C$29*1/$C$28,G50)) -> 0.125 | H51: =IF(H48=0,0,IF($C$29*1/$C$28>H50,$C$29*1/$C$28,H50)) -> 0.14285714 | I51: =IF(I48=0,0,IF($C$29*1/$C$28>I50,$C$29*1/$C$28,I50)) -> 0.16666667 | J51: =IF(J48=0,0,IF($C$29*1/$C$28>J50,$C$29*1/$C$28,J50)) -> 0.2 | K51: =IF(K48=0,0,IF($C$29*1/$C$28>K50,$C$29*1/$C$28,K50)) -> 0.25 | L51: =IF(L48=0,0,IF($C$29*1/$C$28>L50,$C$29*1/$C$28,L50)) -> 0.33333333 | ... Q51: =IF(Q48=0,0,IF($C$29*1/$C$28>Q50,$C$29*1/$C$28,Q50)) -> 0
A52: Charge d'amortissement | B52: USD | E52: =E49*E51 -> 1000000 | F52: =F49*F51 -> 1000000 | G52: =G49*G51 -> 1000000 | H52: =H49*H51 -> 1000000 | I52: =I49*I51 -> 1000000 | J52: =J49*J51 -> 1000000 | K52: =K49*K51 -> 1000000 | L52: =L49*L51 -> 1000000 | ... Q52: =Q49*Q51 -> 0
A53: Amortissement restant | B53: USD | E53: =E49-E52 -> 9000000 | F53: =F49-F52 -> 8000000 | G53: =G49-G52 -> 7000000 | H53: =H49-H52 -> 6000000 | I53: =I49-I52 -> 5000000 | J53: =J49-J52 -> 4000000 | K53: =K49-K52 -> 3000000 | L53: =L49-L52 -> 2000000 | ... Q53: =Q49-Q52 -> 0
A55: Immobilisations de l'année A4
A56: Durée restante | B56: Années | F56: =IF($C$6<F$3,$C$6,F$3) -> 10 | G56: =IF(F56=0,0,IF(F56-1<G$3,F56-1,G$3)) -> 9 | H56: =IF(G56=0,0,IF(G56-1<H$3,G56-1,H$3)) -> 8 | I56: =IF(H56=0,0,IF(H56-1<I$3,H56-1,I$3)) -> 7 | J56: =IF(I56=0,0,IF(I56-1<J$3,I56-1,J$3)) -> 6 | K56: =IF(J56=0,0,IF(J56-1<K$3,J56-1,K$3)) -> 5 | L56: =IF(K56=0,0,IF(K56-1<L$3,K56-1,L$3)) -> 4 | M56: =IF(L56=0,0,IF(L56-1<M$3,L56-1,M$3)) -> 3 | N56: =IF(M56=0,0,IF(M56-1<N$3,M56-1,N$3)) -> 2 | ... Q56: =IF(P56=0,0,IF(P56-1<Q$3,P56-1,Q$3)) -> 0
A57: Base amortissable | B57: USD | F57: ='Modèle_législation en vigueur'!F10 -> 10000000 | G57: =F61 -> 9000000 | H57: =G61 -> 8000000 | I57: =H61 -> 7000000 | J57: =I61 -> 6000000 | K57: =J61 -> 5000000 | L57: =K61 -> 4000000 | M57: =L61 -> 3000000 | N57: =M61 -> 2000000 | ... Q57: =P61 -> 0
A58: Inverse de la durée restante | B58: % | F58: =IF(F56=0,0,1/F56) -> 0.1 | G58: =IF(G56=0,0,1/G56) -> 0.11111111 | H58: =IF(H56=0,0,1/H56) -> 0.125 | I58: =IF(I56=0,0,1/I56) -> 0.14285714 | J58: =IF(J56=0,0,1/J56) -> 0.16666667 | K58: =IF(K56=0,0,1/K56) -> 0.2 | L58: =IF(L56=0,0,1/L56) -> 0.25 | M58: =IF(M56=0,0,1/M56) -> 0.33333333 | ... Q58: =IF(Q56=0,0,1/Q56) -> 0
A59: Taux dégressif | B59: % | F59: =IF(F56=0,0,IF($C$29*1/$C$28>F58,$C$29*1/$C$28,F58)) -> 0.1 | G59: =IF(G56=0,0,IF($C$29*1/$C$28>G58,$C$29*1/$C$28,G58)) -> 0.11111111 | H59: =IF(H56=0,0,IF($C$29*1/$C$28>H58,$C$29*1/$C$28,H58)) -> 0.125 | I59: =IF(I56=0,0,IF($C$29*1/$C$28>I58,$C$29*1/$C$28,I58)) -> 0.14285714 | J59: =IF(J56=0,0,IF($C$29*1/$C$28>J58,$C$29*1/$C$28,J58)) -> 0.16666667 | K59: =IF(K56=0,0,IF($C$29*1/$C$28>K58,$C$29*1/$C$28,K58)) -> 0.2 | L59: =IF(L56=0,0,IF($C$29*1/$C$28>L58,$C$29*1/$C$28,L58)) -> 0.25 | M59: =IF(M56=0,0,IF($C$29*1/$C$28>M58,$C$29*1/$C$28,M58)) -> 0.33333333 | ... Q59: =IF(Q56=0,0,IF($C$29*1/$C$28>Q58,$C$29*1/$C$28,Q58)) -> 0
A60: Charge d'amortissement | B60: USD | F60: =F57*F59 -> 1000000 | G60: =G57*G59 -> 1000000 | H60: =H57*H59 -> 1000000 | I60: =I57*I59 -> 1000000 | J60: =J57*J59 -> 1000000 | K60: =K57*K59 -> 1000000 | L60: =L57*L59 -> 1000000 | M60: =M57*M59 -> 1000000 | ... Q60: =Q57*Q59 -> 0
A61: Amortissement restant | B61: USD | F61: =F57-F60 -> 9000000 | G61: =G57-G60 -> 8000000 | H61: =H57-H60 -> 7000000 | I61: =I57-I60 -> 6000000 | J61: =J57-J60 -> 5000000 | K61: =K57-K60 -> 4000000 | L61: =L57-L60 -> 3000000 | M61: =M57-M60 -> 2000000 | ... Q61: =Q57-Q60 -> 0
A63: Immobilisations de l'année A5
A64: Durée restante | B64: Années | G64: =IF($C$6<G$3,$C$6,G$3) -> 10 | H64: =IF(G64=0,0,IF(G64-1<H$3,G64-1,H$3)) -> 9 | I64: =IF(H64=0,0,IF(H64-1<I$3,H64-1,I$3)) -> 8 | J64: =IF(I64=0,0,IF(I64-1<J$3,I64-1,J$3)) -> 7 | K64: =IF(J64=0,0,IF(J64-1<K$3,J64-1,K$3)) -> 6 | L64: =IF(K64=0,0,IF(K64-1<L$3,K64-1,L$3)) -> 5 | M64: =IF(L64=0,0,IF(L64-1<M$3,L64-1,M$3)) -> 4 | N64: =IF(M64=0,0,IF(M64-1<N$3,M64-1,N$3)) -> 3 | O64: =IF(N64=0,0,IF(N64-1<O$3,N64-1,O$3)) -> 2 | ... Q64: =IF(P64=0,0,IF(P64-1<Q$3,P64-1,Q$3)) -> 0
A65: Base amortissable | B65: USD | G65: ='Modèle_législation en vigueur'!G10 -> 10000000 | H65: =G69 -> 9000000 | I65: =H69 -> 8000000 | J65: =I69 -> 7000000 | K65: =J69 -> 6000000 | L65: =K69 -> 5000000 | M65: =L69 -> 4000000 | N65: =M69 -> 3000000 | O65: =N69 -> 2000000 | ... Q65: =P69 -> 0
A66: Inverse de la durée restante | B66: % | G66: =IF(G64=0,0,1/G64) -> 0.1 | H66: =IF(H64=0,0,1/H64) -> 0.11111111 | I66: =IF(I64=0,0,1/I64) -> 0.125 | J66: =IF(J64=0,0,1/J64) -> 0.14285714 | K66: =IF(K64=0,0,1/K64) -> 0.16666667 | L66: =IF(L64=0,0,1/L64) -> 0.2 | M66: =IF(M64=0,0,1/M64) -> 0.25 | N66: =IF(N64=0,0,1/N64) -> 0.33333333 | ... Q66: =IF(Q64=0,0,1/Q64) -> 0
A67: Taux dégressif | B67: % | G67: =IF(G64=0,0,IF($C$29*1/$C$28>G66,$C$29*1/$C$28,G66)) -> 0.1 | H67: =IF(H64=0,0,IF($C$29*1/$C$28>H66,$C$29*1/$C$28,H66)) -> 0.11111111 | I67: =IF(I64=0,0,IF($C$29*1/$C$28>I66,$C$29*1/$C$28,I66)) -> 0.125 | J67: =IF(J64=0,0,IF($C$29*1/$C$28>J66,$C$29*1/$C$28,J66)) -> 0.14285714 | K67: =IF(K64=0,0,IF($C$29*1/$C$28>K66,$C$29*1/$C$28,K66)) -> 0.16666667 | L67: =IF(L64=0,0,IF($C$29*1/$C$28>L66,$C$29*1/$C$28,L66)) -> 0.2 | M67: =IF(M64=0,0,IF($C$29*1/$C$28>M66,$C$29*1/$C$28,M66)) -> 0.25 | N67: =IF(N64=0,0,IF($C$29*1/$C$28>N66,$C$29*1/$C$28,N66)) -> 0.33333333 | ... Q67: =IF(Q64=0,0,IF($C$29*1/$C$28>Q66,$C$29*1/$C$28,Q66)) -> 0
A68: Charge d'amortissement | B68: USD | G68: =G65*G67 -> 1000000 | H68: =H65*H67 -> 1000000 | I68: =I65*I67 -> 1000000 | J68: =J65*J67 -> 1000000 | K68: =K65*K67 -> 1000000 | L68: =L65*L67 -> 1000000 | M68: =M65*M67 -> 1000000 | N68: =N65*N67 -> 1000000 | ... Q68: =Q65*Q67 -> 0
A69: Amortissement restant | B69: USD | G69: =G65-G68 -> 9000000 | H69: =H65-H68 -> 8000000 | I69: =I65-I68 -> 7000000 | J69: =J65-J68 -> 6000000 | K69: =K65-K68 -> 5000000 | L69: =L65-L68 -> 4000000 | M69: =M65-M68 -> 3000000 | N69: =N65-N68 -> 2000000 | ... Q69: =Q65-Q68 -> 0
A71: Immobilisations de l'année A6
A72: Durée restante | B72: Années | H72: =IF($C$6<H$3,$C$6,H$3) -> 10 | I72: =IF(H72=0,0,IF(H72-1<I$3,H72-1,I$3)) -> 9 | J72: =IF(I72=0,0,IF(I72-1<J$3,I72-1,J$3)) -> 8 | K72: =IF(J72=0,0,IF(J72-1<K$3,J72-1,K$3)) -> 7 | L72: =IF(K72=0,0,IF(K72-1<L$3,K72-1,L$3)) -> 6 | M72: =IF(L72=0,0,IF(L72-1<M$3,L72-1,M$3)) -> 5 | N72: =IF(M72=0,0,IF(M72-1<N$3,M72-1,N$3)) -> 4 | O72: =IF(N72=0,0,IF(N72-1<O$3,N72-1,O$3)) -> 3 | P72: =IF(O72=0,0,IF(O72-1<P$3,O72-1,P$3)) -> 2 | Q72: =IF(P72=0,0,IF(P72-1<Q$3,P72-1,Q$3)) -> 1
A73: Base amortissable | B73: USD | H73: ='Modèle_législation en vigueur'!H10 -> 10000000 | I73: =H77 -> 9000000 | J73: =I77 -> 8000000 | K73: =J77 -> 7000000 | L73: =K77 -> 6000000 | M73: =L77 -> 5000000 | N73: =M77 -> 4000000 | O73: =N77 -> 3000000 | P73: =O77 -> 2000000 | Q73: =P77 -> 1000000
A74: Inverse de la durée restante | B74: % | H74: =IF(H72=0,0,1/H72) -> 0.1 | I74: =IF(I72=0,0,1/I72) -> 0.11111111 | J74: =IF(J72=0,0,1/J72) -> 0.125 | K74: =IF(K72=0,0,1/K72) -> 0.14285714 | L74: =IF(L72=0,0,1/L72) -> 0.16666667 | M74: =IF(M72=0,0,1/M72) -> 0.2 | N74: =IF(N72=0,0,1/N72) -> 0.25 | O74: =IF(O72=0,0,1/O72) -> 0.33333333 | ... Q74: =IF(Q72=0,0,1/Q72) -> 1
A75: Taux dégressif | B75: % | H75: =IF(H72=0,0,IF($C$29*1/$C$28>H74,$C$29*1/$C$28,H74)) -> 0.1 | I75: =IF(I72=0,0,IF($C$29*1/$C$28>I74,$C$29*1/$C$28,I74)) -> 0.11111111 | J75: =IF(J72=0,0,IF($C$29*1/$C$28>J74,$C$29*1/$C$28,J74)) -> 0.125 | K75: =IF(K72=0,0,IF($C$29*1/$C$28>K74,$C$29*1/$C$28,K74)) -> 0.14285714 | L75: =IF(L72=0,0,IF($C$29*1/$C$28>L74,$C$29*1/$C$28,L74)) -> 0.16666667 | M75: =IF(M72=0,0,IF($C$29*1/$C$28>M74,$C$29*1/$C$28,M74)) -> 0.2 | N75: =IF(N72=0,0,IF($C$29*1/$C$28>N74,$C$29*1/$C$28,N74)) -> 0.25 | O75: =IF(O72=0,0,IF($C$29*1/$C$28>O74,$C$29*1/$C$28,O74)) -> 0.33333333 | ... Q75: =IF(Q72=0,0,IF($C$29*1/$C$28>Q74,$C$29*1/$C$28,Q74)) -> 1
A76: Charge d'amortissement | B76: USD | H76: =H73*H75 -> 1000000 | I76: =I73*I75 -> 1000000 | J76: =J73*J75 -> 1000000 | K76: =K73*K75 -> 1000000 | L76: =L73*L75 -> 1000000 | M76: =M73*M75 -> 1000000 | N76: =N73*N75 -> 1000000 | O76: =O73*O75 -> 1000000 | ... Q76: =Q73*Q75 -> 1000000
A77: Amortissement restant | B77: USD | H77: =H73-H76 -> 9000000 | I77: =I73-I76 -> 8000000 | J77: =J73-J76 -> 7000000 | K77: =K73-K76 -> 6000000 | L77: =L73-L76 -> 5000000 | M77: =M73-M76 -> 4000000 | N77: =N73-N76 -> 3000000 | O77: =O73-O76 -> 2000000 | ... Q77: =Q73-Q76 -> 0
A79: Immobilisations de l'année A7
A80: Durée restante | B80: Années | I80: =IF($C$6<I$3,$C$6,I$3) -> 9 | J80: =IF(I80=0,0,IF(I80-1<J$3,I80-1,J$3)) -> 8 | K80: =IF(J80=0,0,IF(J80-1<K$3,J80-1,K$3)) -> 7 | L80: =IF(K80=0,0,IF(K80-1<L$3,K80-1,L$3)) -> 6 | M80: =IF(L80=0,0,IF(L80-1<M$3,L80-1,M$3)) -> 5 | N80: =IF(M80=0,0,IF(M80-1<N$3,M80-1,N$3)) -> 4 | O80: =IF(N80=0,0,IF(N80-1<O$3,N80-1,O$3)) -> 3 | P80: =IF(O80=0,0,IF(O80-1<P$3,O80-1,P$3)) -> 2 | Q80: =IF(P80=0,0,IF(P80-1<Q$3,P80-1,Q$3)) -> 1
A81: Base amortissable | B81: USD | I81: ='Modèle_législation en vigueur'!I10 -> 10000000 | J81: =I85 -> 8888888.9 | K81: =J85 -> 7777777.8 | L81: =K85 -> 6666666.7 | M81: =L85 -> 5555555.6 | N81: =M85 -> 4444444.4 | O81: =N85 -> 3333333.3 | P81: =O85 -> 2222222.2 | Q81: =P85 -> 1111111.1
A82: Inverse de la durée restante | B82: % | I82: =IF(I80=0,0,1/I80) -> 0.11111111 | J82: =IF(J80=0,0,1/J80) -> 0.125 | K82: =IF(K80=0,0,1/K80) -> 0.14285714 | L82: =IF(L80=0,0,1/L80) -> 0.16666667 | M82: =IF(M80=0,0,1/M80) -> 0.2 | N82: =IF(N80=0,0,1/N80) -> 0.25 | O82: =IF(O80=0,0,1/O80) -> 0.33333333 | P82: =IF(P80=0,0,1/P80) -> 0.5 | Q82: =IF(Q80=0,0,1/Q80) -> 1
A83: Taux dégressif | B83: % | I83: =IF(I80=0,0,IF($C$29*1/$C$28>I82,$C$29*1/$C$28,I82)) -> 0.11111111 | J83: =IF(J80=0,0,IF($C$29*1/$C$28>J82,$C$29*1/$C$28,J82)) -> 0.125 | K83: =IF(K80=0,0,IF($C$29*1/$C$28>K82,$C$29*1/$C$28,K82)) -> 0.14285714 | L83: =IF(L80=0,0,IF($C$29*1/$C$28>L82,$C$29*1/$C$28,L82)) -> 0.16666667 | M83: =IF(M80=0,0,IF($C$29*1/$C$28>M82,$C$29*1/$C$28,M82)) -> 0.2 | N83: =IF(N80=0,0,IF($C$29*1/$C$28>N82,$C$29*1/$C$28,N82)) -> 0.25 | O83: =IF(O80=0,0,IF($C$29*1/$C$28>O82,$C$29*1/$C$28,O82)) -> 0.33333333 | P83: =IF(P80=0,0,IF($C$29*1/$C$28>P82,$C$29*1/$C$28,P82)) -> 0.5 | Q83: =IF(Q80=0,0,IF($C$29*1/$C$28>Q82,$C$29*1/$C$28,Q82)) -> 1
A84: Charge d'amortissement | B84: USD | I84: =I81*I83 -> 1111111.1 | J84: =J81*J83 -> 1111111.1 | K84: =K81*K83 -> 1111111.1 | L84: =L81*L83 -> 1111111.1 | M84: =M81*M83 -> 1111111.1 | N84: =N81*N83 -> 1111111.1 | O84: =O81*O83 -> 1111111.1 | P84: =P81*P83 -> 1111111.1 | Q84: =Q81*Q83 -> 1111111.1
A85: Amortissement restant | B85: USD | I85: =I81-I84 -> 8888888.9 | J85: =J81-J84 -> 7777777.8 | K85: =K81-K84 -> 6666666.7 | L85: =L81-L84 -> 5555555.6 | M85: =M81-M84 -> 4444444.4 | N85: =N81-N84 -> 3333333.3 | O85: =O81-O84 -> 2222222.2 | P85: =P81-P84 -> 1111111.1 | Q85: =Q81-Q84 -> 0
A87: Immobilisations de l'année A8
A88: Durée restante | B88: Années | J88: =IF($C$6<J$3,$C$6,J$3) -> 8 | K88: =IF(J88=0,0,IF(J88-1<K$3,J88-1,K$3)) -> 7 | L88: =IF(K88=0,0,IF(K88-1<L$3,K88-1,L$3)) -> 6 | M88: =IF(L88=0,0,IF(L88-1<M$3,L88-1,M$3)) -> 5 | N88: =IF(M88=0,0,IF(M88-1<N$3,M88-1,N$3)) -> 4 | O88: =IF(N88=0,0,IF(N88-1<O$3,N88-1,O$3)) -> 3 | P88: =IF(O88=0,0,IF(O88-1<P$3,O88-1,P$3)) -> 2 | Q88: =IF(P88=0,0,IF(P88-1<Q$3,P88-1,Q$3)) -> 1
A89: Base amortissable | B89: USD | J89: ='Modèle_législation en vigueur'!J10 -> 10000000 | K89: =J93 -> 8750000 | L89: =K93 -> 7500000 | M89: =L93 -> 6250000 | N89: =M93 -> 5000000 | O89: =N93 -> 3750000 | P89: =O93 -> 2500000 | Q89: =P93 -> 1250000
A90: Inverse de la durée restante | B90: % | J90: =IF(J88=0,0,1/J88) -> 0.125 | K90: =IF(K88=0,0,1/K88) -> 0.14285714 | L90: =IF(L88=0,0,1/L88) -> 0.16666667 | M90: =IF(M88=0,0,1/M88) -> 0.2 | N90: =IF(N88=0,0,1/N88) -> 0.25 | O90: =IF(O88=0,0,1/O88) -> 0.33333333 | P90: =IF(P88=0,0,1/P88) -> 0.5 | Q90: =IF(Q88=0,0,1/Q88) -> 1
A91: Taux dégressif | B91: % | J91: =IF(J88=0,0,IF($C$29*1/$C$28>J90,$C$29*1/$C$28,J90)) -> 0.125 | K91: =IF(K88=0,0,IF($C$29*1/$C$28>K90,$C$29*1/$C$28,K90)) -> 0.14285714 | L91: =IF(L88=0,0,IF($C$29*1/$C$28>L90,$C$29*1/$C$28,L90)) -> 0.16666667 | M91: =IF(M88=0,0,IF($C$29*1/$C$28>M90,$C$29*1/$C$28,M90)) -> 0.2 | N91: =IF(N88=0,0,IF($C$29*1/$C$28>N90,$C$29*1/$C$28,N90)) -> 0.25 | O91: =IF(O88=0,0,IF($C$29*1/$C$28>O90,$C$29*1/$C$28,O90)) -> 0.33333333 | P91: =IF(P88=0,0,IF($C$29*1/$C$28>P90,$C$29*1/$C$28,P90)) -> 0.5 | Q91: =IF(Q88=0,0,IF($C$29*1/$C$28>Q90,$C$29*1/$C$28,Q90)) -> 1
A92: Charge d'amortissement | B92: USD | J92: =J89*J91 -> 1250000 | K92: =K89*K91 -> 1250000 | L92: =L89*L91 -> 1250000 | M92: =M89*M91 -> 1250000 | N92: =N89*N91 -> 1250000 | O92: =O89*O91 -> 1250000 | P92: =P89*P91 -> 1250000 | Q92: =Q89*Q91 -> 1250000
A93: Amortissement restant | B93: USD | J93: =J89-J92 -> 8750000 | K93: =K89-K92 -> 7500000 | L93: =L89-L92 -> 6250000 | M93: =M89-M92 -> 5000000 | N93: =N89-N92 -> 3750000 | O93: =O89-O92 -> 2500000 | P93: =P89-P92 -> 1250000 | Q93: =Q89-Q92 -> 0
A95: Immobilisations de l'année A9
A96: Durée restante | B96: Années | K96: =IF($C$6<K$3,$C$6,K$3) -> 7 | L96: =IF(K96=0,0,IF(K96-1<L$3,K96-1,L$3)) -> 6 | M96: =IF(L96=0,0,IF(L96-1<M$3,L96-1,M$3)) -> 5 | N96: =IF(M96=0,0,IF(M96-1<N$3,M96-1,N$3)) -> 4 | O96: =IF(N96=0,0,IF(N96-1<O$3,N96-1,O$3)) -> 3 | P96: =IF(O96=0,0,IF(O96-1<P$3,O96-1,P$3)) -> 2 | Q96: =IF(P96=0,0,IF(P96-1<Q$3,P96-1,Q$3)) -> 1
A97: Base amortissable | B97: USD | K97: ='Modèle_législation en vigueur'!K10 -> 10000000 | L97: =K101 -> 8571428.6 | M97: =L101 -> 7142857.1 | N97: =M101 -> 5714285.7 | O97: =N101 -> 4285714.3 | P97: =O101 -> 2857142.9 | Q97: =P101 -> 1428571.4
A98: Inverse de la durée restante | B98: % | K98: =IF(K96=0,0,1/K96) -> 0.14285714 | L98: =IF(L96=0,0,1/L96) -> 0.16666667 | M98: =IF(M96=0,0,1/M96) -> 0.2 | N98: =IF(N96=0,0,1/N96) -> 0.25 | O98: =IF(O96=0,0,1/O96) -> 0.33333333 | P98: =IF(P96=0,0,1/P96) -> 0.5 | Q98: =IF(Q96=0,0,1/Q96) -> 1
A99: Taux dégressif | B99: % | K99: =IF(K96=0,0,IF($C$29*1/$C$28>K98,$C$29*1/$C$28,K98)) -> 0.14285714 | L99: =IF(L96=0,0,IF($C$29*1/$C$28>L98,$C$29*1/$C$28,L98)) -> 0.16666667 | M99: =IF(M96=0,0,IF($C$29*1/$C$28>M98,$C$29*1/$C$28,M98)) -> 0.2 | N99: =IF(N96=0,0,IF($C$29*1/$C$28>N98,$C$29*1/$C$28,N98)) -> 0.25 | O99: =IF(O96=0,0,IF($C$29*1/$C$28>O98,$C$29*1/$C$28,O98)) -> 0.33333333 | P99: =IF(P96=0,0,IF($C$29*1/$C$28>P98,$C$29*1/$C$28,P98)) -> 0.5 | Q99: =IF(Q96=0,0,IF($C$29*1/$C$28>Q98,$C$29*1/$C$28,Q98)) -> 1
A100: Charge d'amortissement | B100: USD | K100: =K97*K99 -> 1428571.4 | L100: =L97*L99 -> 1428571.4 | M100: =M97*M99 -> 1428571.4 | N100: =N97*N99 -> 1428571.4 | O100: =O97*O99 -> 1428571.4 | P100: =P97*P99 -> 1428571.4 | Q100: =Q97*Q99 -> 1428571.4
A101: Amortissement restant | B101: USD | K101: =K97-K100 -> 8571428.6 | L101: =L97-L100 -> 7142857.1 | M101: =M97-M100 -> 5714285.7 | N101: =N97-N100 -> 4285714.3 | O101: =O97-O100 -> 2857142.9 | P101: =P97-P100 -> 1428571.4 | Q101: =Q97-Q100 -> 0
A103: Immobilisations de l'année A10
A104: Durée restante | B104: Années | L104: =IF($C$6<L$3,$C$6,L$3) -> 6 | M104: =IF(L104=0,0,IF(L104-1<M$3,L104-1,M$3)) -> 5 | N104: =IF(M104=0,0,IF(M104-1<N$3,M104-1,N$3)) -> 4 | O104: =IF(N104=0,0,IF(N104-1<O$3,N104-1,O$3)) -> 3 | P104: =IF(O104=0,0,IF(O104-1<P$3,O104-1,P$3)) -> 2 | Q104: =IF(P104=0,0,IF(P104-1<Q$3,P104-1,Q$3)) -> 1
A105: Base amortissable | B105: USD | L105: ='Modèle_législation en vigueur'!L10 -> 10000000 | M105: =L109 -> 8333333.3 | N105: =M109 -> 6666666.7 | O105: =N109 -> 5000000 | P105: =O109 -> 3333333.3 | Q105: =P109 -> 1666666.7
A106: Inverse de la durée restante | B106: % | L106: =IF(L104=0,0,1/L104) -> 0.16666667 | M106: =IF(M104=0,0,1/M104) -> 0.2 | N106: =IF(N104=0,0,1/N104) -> 0.25 | O106: =IF(O104=0,0,1/O104) -> 0.33333333 | P106: =IF(P104=0,0,1/P104) -> 0.5 | Q106: =IF(Q104=0,0,1/Q104) -> 1
A107: Taux dégressif | B107: % | L107: =IF(L104=0,0,IF($C$29*1/$C$28>L106,$C$29*1/$C$28,L106)) -> 0.16666667 | M107: =IF(M104=0,0,IF($C$29*1/$C$28>M106,$C$29*1/$C$28,M106)) -> 0.2 | N107: =IF(N104=0,0,IF($C$29*1/$C$28>N106,$C$29*1/$C$28,N106)) -> 0.25 | O107: =IF(O104=0,0,IF($C$29*1/$C$28>O106,$C$29*1/$C$28,O106)) -> 0.33333333 | P107: =IF(P104=0,0,IF($C$29*1/$C$28>P106,$C$29*1/$C$28,P106)) -> 0.5 | Q107: =IF(Q104=0,0,IF($C$29*1/$C$28>Q106,$C$29*1/$C$28,Q106)) -> 1
A108: Charge d'amortissement | B108: USD | L108: =L105*L107 -> 1666666.7 | M108: =M105*M107 -> 1666666.7 | N108: =N105*N107 -> 1666666.7 | O108: =O105*O107 -> 1666666.7 | P108: =P105*P107 -> 1666666.7 | Q108: =Q105*Q107 -> 1666666.7
A109: Amortissement restant | B109: USD | L109: =L105-L108 -> 8333333.3 | M109: =M105-M108 -> 6666666.7 | N109: =N105-N108 -> 5000000 | O109: =O105-O108 -> 3333333.3 | P109: =P105-P108 -> 1666666.7 | Q109: =Q105-Q108 -> 0
A111: Immobilisations de l'année A11
A112: Durée restante | B112: Années | M112: =IF($C$6<M$3,$C$6,M$3) -> 5 | N112: =IF(M112=0,0,IF(M112-1<N$3,M112-1,N$3)) -> 4 | O112: =IF(N112=0,0,IF(N112-1<O$3,N112-1,O$3)) -> 3 | P112: =IF(O112=0,0,IF(O112-1<P$3,O112-1,P$3)) -> 2 | Q112: =IF(P112=0,0,IF(P112-1<Q$3,P112-1,Q$3)) -> 1
A113: Base amortissable | B113: USD | M113: ='Modèle_législation en vigueur'!M10 -> 10000000 | N113: =M117 -> 8000000 | O113: =N117 -> 6000000 | P113: =O117 -> 4000000 | Q113: =P117 -> 2000000
A114: Inverse de la durée restante | B114: % | M114: =IF(M112=0,0,1/M112) -> 0.2 | N114: =IF(N112=0,0,1/N112) -> 0.25 | O114: =IF(O112=0,0,1/O112) -> 0.33333333 | P114: =IF(P112=0,0,1/P112) -> 0.5 | Q114: =IF(Q112=0,0,1/Q112) -> 1
A115: Taux dégressif | B115: % | M115: =IF(M112=0,0,IF($C$29*1/$C$28>M114,$C$29*1/$C$28,M114)) -> 0.2 | N115: =IF(N112=0,0,IF($C$29*1/$C$28>N114,$C$29*1/$C$28,N114)) -> 0.25 | O115: =IF(O112=0,0,IF($C$29*1/$C$28>O114,$C$29*1/$C$28,O114)) -> 0.33333333 | P115: =IF(P112=0,0,IF($C$29*1/$C$28>P114,$C$29*1/$C$28,P114)) -> 0.5 | Q115: =IF(Q112=0,0,IF($C$29*1/$C$28>Q114,$C$29*1/$C$28,Q114)) -> 1
A116: Charge d'amortissement | B116: USD | M116: =M113*M115 -> 2000000 | N116: =N113*N115 -> 2000000 | O116: =O113*O115 -> 2000000 | P116: =P113*P115 -> 2000000 | Q116: =Q113*Q115 -> 2000000
A117: Amortissement restant | B117: USD | M117: =M113-M116 -> 8000000 | N117: =N113-N116 -> 6000000 | O117: =O113-O116 -> 4000000 | P117: =P113-P116 -> 2000000 | Q117: =Q113-Q116 -> 0
...

Sheet Feuil1
D2: 1300 | E2: 1600
B3: Ligne | C3: Variable | D3: Valeur
B4: 1 | C4: Chiffre d'affaire (CA) | D4: ='Modèle_législation en vigueur'!S6 -> 2.4901436e+09 | E4: ='Modèle_projet de loi'!S6 -> 2.9732473e+09
B5: 2 | C5: Dépenses d'investissement (CAPEX) | D5: ='Modèle_législation en vigueur'!S12 -> 3.289335e+08 | E5: ='Modèle_projet de loi'!S12 -> 3.289335e+08
B6: 3 | C6: Dépenses d'exploitations (OPEX) | D6: ='Modèle_législation en vigueur'!S16 -> 1.4866237e+09 | E6: ='Modèle_projet de loi'!S16 -> 1.4866237e+09
B7: 4 | C7: Rente minière | D7: =D4-D5-D6 -> 6.7458646e+08 | E7: =E4-E5-E6 -> 1.1576902e+09
C8: Taux de rendement interne (TRI) | D8: ='Modèle_législation en vigueur'!Q20 -> 0.55693685 | E8: ='Modèle_projet de loi'!Q20 -> 0.72605458
