Workbook

Sheet Page de garde
A1: Page de garde
B5: REPUBLIQUE | I5: REPUBLIQUE DU SENEGAL
B7: MINISTERE | I7: FINANCES
B9: DIRECTION | I9: IMPOTS
B17: CENTRE DE DEPÔT: IMPOTS & DOMAINES
A23: ETATS FINANCIERS NORMALISES DU SYSTEME
A24: COMPTABLE OUEST AFRICAIN (SYSCOHADA)
B27: EXERCICE CLOS LE : | M27: 45657
A30: DESIGNATION DE L'ENTREPRISE
C35: DENOMINATION SOCIALE : | L35: SOCIETE NOUVELLE DES SALINS DU SINE SALOUM
C36: (ou nom et prénoms de l'exploitant)
C41: SIGLE USUEL : | H41: SNSSS
C46: ADRESSE COMPLETE : | J46: DIORHANE BP 200
C51: N° D'IDENTIFICATION FISCALE : | N51: 000018699
C55: SYSTEME NORMAL
C59: Documents déposés | V59: Réservé à la Direction Générale des Impôts
C62: Fiche d'identification et renseignements divers | S62: X | V62: Date de dépôt
C64: Bilan | S64: X
C66: Compte de résultat | S66: X | V66: Nom de l'agent de DGI ayant réceptionné le dépôt
C68: Tableau financier des ressources et emplois | S68: X
C70: Etat supplémentaire | S70: X | V70: Signature de l'agent et cachet du service
C72: Nombre de pages déposées par exemplaire | R72: 0
C73: Nombre d'exemplaires déposés | R73: 0

Sheet Fiche de renseignement R1
A1: Fiche R1
J3: SOCIETE NOUVELLE DES SALINS DU SINE SALOUM
B4: Désignation de l'entreprise | J4: =+'Page de garde'!L35 -> SOCIETE NOUVELLE DES SALINS DU SINE SALOUM
J6: DIORHANE BP 200 | AD6: SNSSS
C7: Adresse de l'entreprise | J7: ='Page de garde'!J46 -> DIORHANE BP 200 | AA7: Sigle usuel | AD7: =+'Page de garde'!H41 -> SNSSS
J9: 000018699
D10: N° d'identification | J10: =+'Page de garde'!N51 -> 000018699 | R10: Exercice clos le | V10: =+'Page de garde'!M27 -> 45657 | AC10: Durée (en mois) | AH10: 12
B13: ZA | E13: EXERCICE COMPTABLE | W13: DU | Y13: 45292 | AF13: AU | AH13: 45657
B16: ZB | E16: DATE D'ARRETE EFFECTIF DES COMPTES | U16: 45657
B20: ZC | E20: EXERCICE PRECEDENT CLOS LE | Q20: 45291 | Z20: DUREE EXERCICE PRECEDENT EN MOIS : | AL20: 12
B24: ZD | F24: 8520 | I24: SN-KLK-1965-B-10668 | W24: 0
F25: Greffe | I25: N° registre du Commerce | W25: N° répertoire des entreprises
B28: ZE | G28: 1413865720 | AE28: 030001
G29: N° de sécurité sociale | S29: N° Code employeur | AE29: Code activité principale
B32: ZF | D32: SOCIETE NOUVELLE DES SALINS DU SINE SALOUM | AE32: SNSSS
D33: Désignation de l'entreprise | AE33: Sigle
B36: ZG | G36: 33 941 19 04 | AA36: 200 | AE36: KAOLACK
G37: N° de téléphone | Q37: Télécopie | Y37: Code | AA37: Boîte postale | AE37: Ville
B40: ZH | D40: DIORHANE BP 200,KAOLACK
D41: Adresse géographique complète (Immeuble, rue, quartier, ville, pays)
B44: ZI | D44: INDUSTRIES ALIMENTAIRES
D45: Désignation précise de l'activité principale exercée par l'entreprise | AE45: % capacité production utilisée
D48: Rolande AKA EKPONON
D49: Nom, adresse et qualité de personne à contacter en cas de demande d'informations complémentaires
D52: MAMADOU DIEYE EXPETRT FISCAL TEL 77 523 64 00
D53: Nom du professionnel salarié de l'entreprise ou Nom, adresse et téléphone du cabinet comptable ou du professionnel INSCRIT A L'ORDRE NATIONAL DES EXPERTS COMPTABLES ET DES COMPTABLES AGREES ayant établi les états financiers.
D56: GAYE & ASSOCIES SARL VILLA 10564 DAKAR SACRE COEUR 3 VDN
D57: Noms et adresses du ou des commissaires au comptes
E64: Non assujettie | K64: Non (refus) | O64: Oui avec réserves | S64: X | T64: Oui sans réserves | Z64: Non assujettie | AG64: Non | AK64: X | AL64: Oui
C66: Etats financiers certifiés (cocher la case) | X66: Etats financiers approuvés par l'Assemblée Générale (cocher la case)
D69: ALAIN BOSSUYT | T69: Domiciliations bancaires
D70: Nom du signataire des états financiers | T70: Banque | AD70: Numéro de compte
T71: ECOBANK | AD71: SN094 01001 100000230001 54
D72: DIRECTEUR GENERAL | T72: BANQUE ATLANTIQUE | AD72: SN137 01001 080135650005 49
D73: Qualité du signataire des états financiers | T73: B.I.C.I.S | AD73: SN010 01520 000102000082 56
T74: CREDIT DU SENEGAL | AD74: SN 060 01030 165055062000 29
D75: 45712 | T75: B.O.A.S. | AD75: SN100 01003 001017420007 82
D76: Date de signature | T76: S.G.B.S. | AD76: SN011 02030 005000000089 43
T77: CBAO | AD77: SN012 02214 021436025526 11
T78: UBA PLATEAU | AD78: SN153 01303 303090005143 93
D83: Signature

Sheet Activités de l'entreprise R2
A1: Fiche R2
B4: Désignation de l'entreprise : | C4: =+'Page de garde'!L35 -> SOCIETE NOUVELLE DES SALINS DU SINE SALOUM
B5: Adresse de l'entreprise :
B6: ='Fiche de renseignement R1'!J7 -> DIORHANE BP 200 | L6: Sigle usuel : | M6: =+'Page de garde'!H41 -> SNSSS
B7: N° d'identification : | L7: Exercice clos le :
B8: =+'Fiche de renseignement R1'!$J$10 -> 000018699 | L8: ='Fiche de renseignement R1'!V10 -> 45657 | M8: Durée (en mois) | N8: ='Fiche de renseignement R1'!AH10 -> 12
A10: FICHE D'IDENTIFICATION ET RENSEIGNEMENTS DIVERS 2
L12: Contrôle de l'entreprise (cocher la case)
A14: ZK | B14: Forme juridique (1) | F14: 0 | G14: 1 | K14: ZQ | L14: Entreprise sous contrôle public
A16: ZL | B16: Régime fiscal (1) | F16: 1 | K16: ZR | L16: Entreprise sous contrôle privé national | Q16: X
A18: ZM | B18: Pays du siège social (1) | F18: 0 | G18: 7 | K18: ZS | L18: Entreprise sous contrôle privé étranger
A20: ZN | B20: Nbre d'établissements dans le pays | F20: 1 | G20: 1
A22: ZO | B22: Nbre d'établissements hors du pays | F22: 0 | G22: 0
B23: pour lesquels une comptabilité distincte est tenue
A25: ZP | B25: 1ère année exercice dans le pays | E25: 0 | F25: 0 | G25: 0 | H25: 0
A28: ACTIVITE DE L'ENTREPRISE
B30: DESIGNATION DE L'ACTIVITE (2) | C30: Code nomenclature d'activité (1) | K30: Valeur Ajoutée (VA) HT | M30: % activité dans le CA HT ou la VA
B33: INDUSTRIES ALIMENTAIRES | D33: 0 | E33: 3 | F33: 0 | G33: 0 | H33: 0 | I33: 1 | L33: 15118888788 | M33: =+L33/$L$59 -> 1
M36: =+L36/$L$59 -> 0
M39: =+L39/$L$59 -> 0
M42: =+L42/$L$59 -> 0
M45: =+L45/$L$59 -> 0
M48: =+L48/$L$59 -> 0
M51: =+L51/$L$59 -> 0
M54: =+L54/$L$59 -> 0
B57: Divers
C59: TOTAL | L59: =SUM(L32:L56) -> 15118888788 | M59: =SUM(M32:M57) -> 1
B62: (1) Se réréfer aux tables des codes
B63: (2) Lister de manière précise les activités dans l'ordre décroissant du CAHT, ou de la valeur ajoutée (V.A.)
B64: (3) Rayer la mention inutile (utiliser de préférence la V.A.)

Sheet Dirigeants R3
A1: Fiche R3
A3: Désignation de l'entreprise | B3: ='Fiche de renseignement R1'!$J$4 -> SOCIETE NOUVELLE DES SALINS DU SINE SALOUM
A4: Adresse de l'entreprise | B4: ='Fiche de renseignement R1'!J7 -> DIORHANE BP 200 | D4: Sigle usuel | E4: ='Fiche de renseignement R1'!AD7 -> SNSSS
A5: N° d'identification fiscale | B5: =+'Fiche de renseignement R1'!$J$10 -> 000018699 | C5: Exercice clos le | D5: ='Fiche de renseignement R1'!V10 -> 45657 | E5: Durée (en mois) | F5: ='Fiche de renseignement R1'!AH10 -> 12
A7: FICHE D'IDENTIFICATION ET RENSEIGNEMENTS DIVERS 3
A9: DIRIGEANTS (1)
A11: Nom | B11: Prénoms | C11: Qualité | D11: N° d'identification fiscale | E11: Adressse (BP, ville, pays)
A12: BOSSUYT | B12: ALAIN | C12: DIRECTEUR GÉNÉRAL | E12: DIORHANE BP 200 KAOLACK
A27: (1) Dirigeants = Président Directeur Général, Directeur Général, Adminsitrateur Général, Gérant, Autres.
A29: MEMBRES DU CONSEIL D'ADMINISTRATION
A31: Nom | B31: Prénoms | C31: Qualité | E31: Adressse (BP, ville, pays)
A32: TIDIANE | B32: SYLLA | C32: Président | E32: Dakar
A33: FINACHEF | C33: Administrateur | E33: France
A34: COMPAGNIE COMERCIALE DES SELS MARINS | C34: Administrateur | E34: France
A35: ALPHA | B35: DIENG | C35: Administrateur | E35: Dakar
A36: COMPAGNIE DES SELS DU MIDI ET DES SALINES DE L'EST | C36: Administrateur | E36: France
A37: SALINS DU MIDI PARTICIPATIONS | C37: Administrateur | E37: France

Sheet Tableau des Notes R4
A1: FICHE R4
A2: Désignation entité : | D2: Excercice clos le : | E2: ='Fiche de renseignement R1'!V10 -> 45657
A3: ='Fiche de renseignement R1'!$J$4 -> SOCIETE NOUVELLE DES SALINS DU SINE SALOUM | D3: Durée en mois : | E3: ='Fiche de renseignement R1'!AH10 -> 12
A4: Numéro d'identification : | B4: =+'Fiche de renseignement R1'!$J$10 -> 000018699
A6: FICHE RECAPITULATIVE DES NOTES ANNEXES PRESENTEES
A8: NOTES | B8: INTITULES | C8: A | D8: N/A
A9: NOTE 1 | B9: DETTES GARANTIES PAR DES SURETES REELLES | D9: X
A10: NOTE 2 | B10: INFORMATIONS OBLIGATOIRES | C10: X
A11: NOTE 3A | B11: IMMOBILISATION BRUTE | C11: X
A12: NOTE 3B | B12: BIENS PRIS EN LOCATION ACQUISITION | D12: X
A13: NOTE 3C | B13: IMMOBILISATIONS : AMORTISSEMENTS | C13: X
A14: NOTE 3D | B14: IMMOBILISATIONS : PLUS -VALUES ET MOINS VALUE DE CESSION | C14: X
A15: NOTE 3E | B15: INFORMATION SUR LES REEVALUATIONS EFFECTUEES PAR L'ENTITE | D15: X
A16: NOTE 4 | B16: IMMOBILISATIONS FINANCIERES | C16: X
A17: NOTE 5 | B17: ACTIF CIRCULANT ET DETTES CIRCULANTES HAO | D17: X
A18: NOTE 6 | B18: STOCKS ET ENCOURS | C18: X
A19: NOTE 7 | B19: CLIENTS PRODUITS A RECEVOIR | C19: X
A20: NOTE 8 | B20: AUTRES CREANCES | C20: X
A21: NOTE 8A | B21: TABLEAU D’ETALEMENT DES CHARGES IMMOBILISEES | D21: X
A22: NOTE 9 | B22: TITRES DE PLACEMENT | D22: X
A23: NOTE 10 | B23: VALEURS A ENCAISSER | C23: X
A24: NOTE 11 | B24: DISPONIBILITES | C24: X
A25: NOTE 12 | B25: ECARTS DE CONVERSION ET TRANSFERTS DE CHARGES | D25: X
A26: NOTE 13 | B26: CAPITAL: VALEUR NOMINALE DES ACTIONS OU PARTS | C26: X
A27: NOTE 14 | B27: PRIMES ET RESERVES | C27: X
A28: NOTE 15A | B28: SUBVENTIONS ET PROVISIONS REGLEMENTEES | D28: X
A29: NOTE 15B | B29: AUTRES FONDS PROPRES | D29: X
A30: NOTE 16A | B30: DETTES FINANCIERES ET RESSOURCES ASSIMILEES | C30: X
A31: NOTE 16B | B31: ENGAGEMENTS DE RETRAITE ET AVANTAGES ASSIMILES ( METHODE ACTUARIELLE ) | D31: X
A32: NOTE 16B bis | B32: ENGAGEMENTS DE RETRAITE ET AVANTAGES ASSIMILES ( METHODE ACTUARIELLE ) | D32: X
A33: NOTE 16C | B33: ACTIFS ET PASSIFS EVENTUELS | D33: X
A34: NOTE 17 | B34: FOURNISSEURS D'EXPLOITATION | C34: X
A35: NOTE 18 | B35: DETTES FISCALES ET SOCIALES | C35: X
A36: NOTE 19 | B36: AUTRES DETTES ET PROVISIONS POUR RISQUES A COURT TERME | C36: X
A37: NOTE 20 | B37: BANQUES , CREDITS D'ESCOMPTE ET DE TRESORERIE | D37: X
A38: NOTE 21 | B38: CHIFFRES D'AFFAIRES ET AUTRES PRODUITS | C38: X
A39: NOTE 22 | B39: ACHATS | C39: X
A40: NOTE 23 | B40: TRANSPORTS | C40: X
A41: NOTE 24 | B41: SERVICES EXTERIEURS | C41: X
A42: NOTE 25 | B42: IMPOTS ET TAXES | C42: X
A43: NOTE 26 | B43: AUTRES CHARGES | C43: X
A44: NOTE 27A | B44: CHARGES DE PERSONNEL | C44: X
A45: NOTE 27B | B45: EFFECTIFS , MASSE SALARIALE ET PERSONNEL EXTERIEUR | C45: X
A46: NOTE 28 | B46: PROVISIONS ET DEPRECIATIONS INSCRITES AU BILAN | C46: X
A47: NOTE 29 | B47: CHARGES ET REVENUS FINANCIERS | C47: X
A48: NOTE 30 | B48: AUTRES CHARGES ET PRODUITS HAO | D48: X
A49: NOTE 31 | B49: REPARTITION DU RESULTAT ET AUTRES ELEMENTS CARACTERISTIQUES DES CINQ DERNIERS EXCERCICES | C49: X
A50: NOTE 32 | B50: PRODUCTION DE L'EXERCICE | C50: X
A51: NOTE 33 | B51: ACHATS DESTINES A LA PRODUCTION | C51: X
A52: NOTE 34 | B52: FICHE DE SYNTHESE DES PRINCIPAUX INDICATEURS FINANCIERS | C52: X
A53: NOTE 35 | B53: LISTE DES INFORMATIONS SOCIALES , ENVIRONNEMENTALES ET SOCIETALES A FOURNIR | C53: X
A54: NOTE 36 | B54: TABLES DES CODES | C54: X

Sheet BILAN PAYSAGE
A1: BILAN PAYSAGE
A3: Désignation entité : | E3: =+'Fiche de renseignement R1'!$V$10 -> 45657 | I3: Excercice clos le : | J3: 0
A4: ='Fiche de renseignement R1'!$J$4 -> SOCIETE NOUVELLE DES SALINS DU SINE SALOUM | I4: Durée en mois : | J4: =+'Fiche de renseignement R1'!$AH$10 -> 12
A5: Numéro d'identification : | D5: =+'Fiche de renseignement R1'!$J$10 -> 000018699
A7: REF | B7: ACTIF | C7: Note | E7: Exercice au 31/12/N | G7: Exercice au 31/12/N-1 | H7: REF | I7: PASSIF | J7: Note | K7: Exercice au 31/12/N | L7: Exercice au 31/12/N-1
D8: Brut | E8: Amorts et Dépréc. | F8: Net | G8: Net | K8: Net | L8: Net
A9: AD | B9: IMMOBILISATIONS INCORPORELLES | C9: 3 | D9: 83951848 | E9: 22265627 | F9: 61686221 | G9: 61351638 | H9: CA | I9: CAPITAL | J9: 13 | K9: 554420000 | L9: 554420000
A10: AE | B10: Frais de développement et de prospection | D10: 26937701 | E10: 0 | F10: 26937701 | G10: 26937701 | H10: CB | I10: Apporteurs capital non appelé | J10: 13 | K10: 0 | L10: 0
A11: AF | B11: Brevets, licences, logiciels et droits similaires | D11: 23214147 | E11: 22265627 | F11: 948520 | G11: 613937 | H11: CD | I11: Primes liées au capital social | J11: 14 | K11: 0 | L11: 0
A12: AG | B12: Fonds commercial et droit au bail | D12: 0 | E12: 0 | F12: 0 | G12: 0 | H12: CE | I12: Ecarts de réévaluation | J12: 3e | K12: 0 | L12: 0
A13: AH | B13: Autres immobilisations incorporelles | D13: 33800000 | E13: 0 | F13: 33800000 | G13: 33800000 | H13: CF | I13: Réserves indisponibles | J13: 14 | K13: 112600000 | L13: 112600000
A14: AI | B14: IMMOBILISATIONS CORPORELLES | C14: 3 | D14: 10773653852 | E14: 7890614507 | F14: 2883039345 | G14: 2837221684 | H14: CG | I14: Réserves libres | J14: 14 | K14: 4665384806 | L14: 3899990322
A15: AJ | B15: Terrains (1) (1) dont placement en net ………../………… | D15: 1150375194 | E15: 888883591 | F15: 261491603 | G15: 358944554 | H15: CH | I15: Report à nouveau | J15: 14 | K15: 0 | L15: 0
A16: AK | B16: Bâtiments (1) dont placement en net ………../………… | D16: 1202980009 | E16: 390975978 | F16: 812004031 | G16: 701901602 | H16: CJ | I16: Résutat net de l'exercice (bénéfice + ou perte -) | K16: 3693778426 | L16: 4369124484
A17: AL | B17: Aménagements, agencements et installations | D17: 1411661925 | E17: 699436255 | F17: 712225670 | G17: 759335572 | H17: CL | I17: Subventions d'investissement | J17: 15 | K17: 0 | L17: 0
A18: AM | B18: Matériel, mobilier et actifs biologiques | D18: 6698804860 | E18: 5722626288 | F18: 976178572 | G18: 980520500 | H18: CM | I18: Provisions réglementées et fonds assimilés | J18: 15 | K18: 0 | L18: 0
A19: AN | B19: Matériel de transport | D19: 292836864 | E19: 180697395 | F19: 112139469 | G19: 30219456 | H19: CP | I19: TOTAL CAPITAUX PROPRES ET RESSOURCES ASSIMILEES | K19: 9026183232 | L19: 8936134806
A20: AP | B20: Avances & acomptes versés sur immobilisations | C20: 3 | D20: 16995000 | E20: 7995000 | F20: 9000000 | G20: 6300000 | H20: DA | I20: Emprunts et dettes financières diverses | J20: 16 | K20: 0 | L20: 0
A21: AQ | B21: IMMOBILISATIONS FINANCIERES | C21: 4 | D21: 185805618 | E21: 50237009 | F21: 135568609 | G21: 135568609 | H21: DB | I21: Dettes de location acquisition | J21: 16 | K21: 0 | L21: 0
A22: AR | B22: Titres de participation | D22: 115827689 | E22: 50227689 | F22: 65600000 | G22: 65595340 | H22: DC | I22: Provisions pour risques et charges | J22: 16 | K22: 1678869395 | L22: 1677152885
A23: AS | B23: Autres immobilisations financières | D23: 69977929 | E23: 9320 | F23: 69968609 | G23: 69973269 | H23: DD | I23: TOTAL DETTES FINANCIERES ET RESSOURCES ASSIMILEES | K23: 1678869395 | L23: 1677152885
A24: AZ | B24: TOTAL ACTIF IMMOBILISE | D24: 11043411318 | E24: 7963117143 | F24: 3080294175 | G24: 3034158551 | H24: DF | I24: TOTAL RESSOURCES STABLES | K24: 10705052627 | L24: 10613287691
A25: BA | B25: ACTIF CIRCULANT H.A.O. | C25: 5 | D25: 0 | E25: 0 | F25: 0 | G25: 0 | H25: DH | I25: Dettes circulantes HAO | J25: 5 | K25: 0 | L25: 0
A26: BB | B26: STOCKS ET ENCOURS | C26: 6 | D26: 5661958301 | E26: 193239513 | F26: 5468718788 | G26: 5434145929 | H26: DI | I26: Clients, avances reçues | J26: 7 | K26: 100649106 | L26: 130101598
A27: BG | B27: CREANCES ET EMPLOIS ASSIMILES | D27: 589493628 | E27: 0 | F27: 589493628 | G27: 502573136 | H27: DJ | I27: Fournisseurs d'exploitation | J27: 17 | K27: 658207070 | L27: 895063997
A28: BH | B28: Fournisseurs, avances versées | C28: 17 | D28: 72960138 | E28: 0 | F28: 72960138 | G28: 40979446 | H28: DK | I28: Dettes fiscales et sociales | J28: 18 | K28: 1039280617 | L28: 1105229702
A29: BI | B29: Clients | C29: 7 | D29: 401035558 | E29: 0 | F29: 401035558 | G29: 368525336 | H29: DM | I29: Autres dettes | J29: 19 | K29: 55426179 | L29: 10027048
A30: BJ | B30: Autres créances | C30: 8 | D30: 115497932 | E30: 0 | F30: 115497932 | G30: 93068354 | H30: DN | I30: Provisions pour risques à court terme | J30: 19 | K30: 0 | L30: 0
A31: BK | B31: TOTAL ACTIF CIRCULANT | D31: 6251451929 | E31: 193239513 | F31: 6058212416 | G31: 5936719065 | H31: DP | I31: TOTAL PASSIF CIRCULANT | K31: 1853562972 | L31: 2140422345
A32: BQ | B32: Titres de placement | C32: 9 | D32: 0 | E32: 0 | F32: 0 | G32: 0 | K32: 0 | L32: 0
A33: BR | B33: Valeurs à encaisser | C33: 10 | D33: 647200000 | E33: 0 | F33: 647200000 | G33: 1127750000 | H33: DQ | I33: Banques, crédit d'escompte | J33: 20 | K33: 0 | L33: 0
A34: BS | B34: Banques, chèques postaux, caisse et assimilés | C34: 11 | D34: 2780738330 | E34: 7829322 | F34: 2772909008 | G34: 2655082420 | H34: DR | I34: Banques, établissements financiers et crédits de trésorerie | J34: 20
A35: BT | B35: TOTAL TRESORERIE - ACTIF | D35: 3427938330 | E35: 7829322 | F35: 3420109008 | G35: 3782832420 | H35: DT | I35: TOTAL TRESORERIE - PASSIF | K35: 0 | L35: 0
A36: BU | B36: Ecarts de conversion - Actif | C36: 12 | D36: 0 | E36: 0 | F36: 0 | G36: 0 | H36: DV | I36: Ecarts de conversion - Passif | J36: 12 | K36: 0 | L36: 0
A37: BZ | B37: TOTAL GENERAL | D37: 20722801577 | E37: 8164185978 | F37: 12558615599 | G37: 12753710036 | H37: DZ | I37: TOTAL GENERAL | K37: 12558615599 | L37: 12753710036

Sheet COMPTE DE RESULTAT
A1: COMPTE DE RESULTAT
A3: Désignation entité : | D3: Excercice clos le : | E3: =+'Fiche de renseignement R1'!$V$10 -> 45657
A4: ='Fiche de renseignement R1'!$J$4 -> SOCIETE NOUVELLE DES SALINS DU SINE SALOUM | D4: Durée en mois : | E4: =+'Fiche de renseignement R1'!$AH$10 -> 12
A5: Numéro d'identification : | B5: =+'Fiche de renseignement R1'!$J$10 -> 000018699
A7: REF | B7: LIBELLES | D7: NOTE | E7: 31/12/N | F7: 31/12/N-1
A8: TA | B8: Ventes de marchandises | C8: + | D8: 21 | E8: 0 | F8: 0
A9: RA | B9: Achats de marchandises | C9: - | D9: 22 | E9: 0 | F9: 0
A10: RB | B10: Variation de stocks | C10: -/+ | D10: 6 | E10: 0 | F10: 0
A11: XA | B11: MARGE BRUTE SUR MARCHANDISES (somme TA à RB) | E11: 0 | F11: 0
A12: TB | B12: Ventes de produits fabriqués | C12: + | D12: 21 | E12: 15098202108 | F12: 17748425468
A13: TC | B13: Travaux, services vendus | C13: + | D13: 21 | E13: 0 | F13: 0
A14: TD | B14: Produits accessoires | C14: + | D14: 21 | E14: 20686680 | F14: 12712
A15: XB | B15: CHIFFRE D'AFFAIRES (A + B + C + D) | E15: 15118888788 | F15: 17748438180
A16: TE | B16: Production stockée (ou destockage) | C16: -/+ | D16: 6 | E16: 237085553 | F16: 100359957
A17: TF | B17: Production immobilisée | D17: 21 | E17: 63508535 | F17: 31315159
A18: TG | B18: Subventions d'exploitation | D18: 21 | E18: 0 | F18: 0
A19: TH | B19: Autres produits | C19: + | D19: 21 | E19: 1000949 | F19: 531038
A20: TI | B20: Transferts de charges | C20: + | D20: 12 | E20: 0 | F20: 53520000
A21: RC | B21: Achats de matières premières et fournitures liées | C21: - | D21: 22 | E21: 0 | F21: 0
A22: RD | B22: Variation de stocks de stocks de matières premières et fournitures liées | C22: -/+ | D22: 6 | E22: 0 | F22: 0
A23: RE | B23: Autres achats | C23: - | D23: 22 | E23: -3585894455 | F23: -4237015280
A24: RF | B24: Variation de stocks d'autres approvisionnements | C24: -/+ | D24: 6 | E24: 119698651 | F24: 330742202
A25: RG | B25: Transports | C25: - | D25: 23 | E25: -3453328573 | F25: -4753977481
A26: RH | B26: Services extérieurs | C26: - | D26: 24 | E26: -831356141 | F26: -818209910
A27: RI | B27: Impôts et taxes | C27: - | D27: 25 | E27: -12622427 | F27: -126423698
A28: RJ | B28: Autres charges | C28: - | D28: 26 | E28: -206216425 | F28: -107531581
A29: XC | B29: VALEUR AJOUTEE (XB + RA + RB) + (somme TE à RJ) | E29: 7450764455 | F29: 8221748586
A30: RK | B30: Charges de personnel | C30: - | D30: 27 | E30: -2313753672 | F30: -2215358068
A31: XD | B31: EXCEDENT BRUT D'EXPLOITATION (XC + RK) | E31: 5137010783 | F31: 6006390518
A32: TJ | B32: Reprises d'amortissements | C32: + | D32: 28 | E32: 82283490 | F32: 582203207
A33: RL | B33: Dotations aux amortissements, aux provisions et dépréciations | C33: - | D33: 3C & 28 | E33: -861586282 | F33: -874274421
A34: XE | B34: RESULTAT D'EXPLOITATION (XD + TJ + RL) | E34: 4357707991 | F34: 5714319304
A35: TK | B35: Revenus financiers et assimilés | C35: + | D35: 29 | E35: 23880790 | F35: 12452925
A36: TL | B36: Reprises de provisions et dépréciations financières | C36: + | D36: 28 | E36: 0 | F36: 0
A37: TM | B37: Tranfert de charges financières | C37: + | D37: 12 | E37: 0 | F37: 0
A38: RM | B38: Frais financiers et charges assimilées | C38: - | D38: 29 | E38: 0 | F38: -8096
A39: RN | B39: Dotations aux provisions et aux dépréciations financières | C39: - | D39: 3C & 28 | E39: 0 | F39: 0
A40: XF | B40: RESULTAT FINANCIER (somme TK à RN) | E40: 23880790 | F40: 12444829
A41: XG | B41: RESULTAT DES ACTIVITES ORDINAIRES (XE + XF) | E41: 4381588781 | F41: 5726764133
A42: TN | B42: Produits des cessions d'immobilisations | C42: + | D42: 3D | E42: 2118644 | F42: 0
A43: TO | B43: Autres produits H.A.O. | C43: + | D43: 30 | E43: 0 | F43: 0
A44: RO | B44: Valeurs comptables des cessions d'immobilisations | C44: - | D44: 3D | E44: -604299 | F44: -4614421
A45: RP | B45: Charges H.A.O. | C45: - | D45: 30 | E45: 0 | F45: -530648278
A46: XH | B46: RESULTAT HORS ACTIVITES ORDINAIRES (somme TN à RP) | E46: 1514345 | F46: -535262699
A47: RQ | B47: Participations des travailleurs | C47: - | D47: 30 | E47: 0 | F47: 0
A48: RS | B48: Impôts sur le résultat | C48: - | D48: 37 | E48: -689324700 | F48: -822376950
A49: XI | B49: RESULTAT NET (XG + XH + RQ + RS) | E49: 3693778426 | F49: 4369124484

Sheet FLUX DE TRESORERIE
A1: FLUX DE TRESORERIE
A3: Désignation entité : | D3: Excercice clos le : | E3: =+'Fiche de renseignement R1'!$V$10 -> 45657
A4: ='Fiche de renseignement R1'!$J$4 -> SOCIETE NOUVELLE DES SALINS DU SINE SALOUM | D4: Durée en mois : | E4: =+'Fiche de renseignement R1'!$AH$10 -> 12
A5: Numéro d'identification : | B5: =+'Fiche de renseignement R1'!$J$10 -> 000018699
A7: REF | B7: LIBELLES | D7: NOTE | E7: 31/12/N | F7: 31/12/N-1
A8: ZA | B8: Trésorerie nette au 1er janvier (Trésorerie actif N-1 - Trésorerie passif N-1) | C8: A | E8: 3782657420 | F8: 4084398932
B9: Flux de trésorerie provenant des activités opérationnelles
A10: FA | B10: Capacité d'Autofinancement Globale (CAFG) | E10: 4471566873 | F10: 4665810119
A11: FB | B11: - Variation de l'actif circulant HAO (1) | E11: 0 | F11: 0
A12: FC | B12: - Variation des stocks | E12: -34572859 | F12: -409104732
A13: FD | B13: - Variation des créances | E13: -86920492 | F13: 90268291
A14: FE | B14: + Variation du passif circulant (1) | E14: -286859373 | F14: -491347949
B15: Variation du BF lié aux activités opérationnelles (FB + FC + FD + FE) : …………………………………………….. | E15: -408352724 | F15: -810184390
A16: ZB | B16: Flux de trésorerie provenant des activités opérationnelles (somme FA à FE) | C16: B | E16: 4063214149 | F16: 3855625729
B17: Flux de trésorerie provenant des activités d'investissement
A18: FF | B18: - Décaissements liés aux acquisitions d'immobilisations incorporelles | E18: -760532 | F18: -329980
A19: FG | B19: - Décaissements liés aux acquisitions d'immobilisations corporelles | E19: -823390673 | F19: -553307261
A20: FH | B20: - Décaissements liés aux acquisitions d'immobilisations financières | E20: 0 | F20: 0
A21: FI | B21: + Encaissements liés aux cessions d'immobilisations incorporelles et corporelles | E21: 2118644 | F21: 0
A22: FJ | B22: + Encaissements liés aux cessions d'immobilisations financières | E22: 0
A23: ZC | B23: Flux de trésorerie provenant des activités d'investissement (somme FF à FJ) | C23: C | E23: -822032561 | F23: -553637241
B24: Flux de trésorerie provenant du financement par les capitaux propres
A25: FK | B25: + Augmentations de capital par apports nouveaux | E25: 0
A26: FL | B26: + Subventions d'investissements reçues | E26: 0
A27: FM | B27: - Prélèvements sur le capital | E27: 0
A28: FN | B28: - Dividendes versés | E28: -3603730000 | F28: -3603730000
A29: ZD | B29: Flux de trésorerie provenant du financement par les capitaux propres (somme FK à FN) | C29: D | E29: -3603730000 | F29: -3603730000
B30: Flux de trésorerie provenant du financement par les capitaux étrangers | E30: 0
A31: FO | B31: + Emprunts | E31: 0
A32: FP | B32: + Autres dettes financières | E32: 0
A33: FQ | B33: - Remboursements des emprunts et autres dettes financières | E33: 0
A34: ZE | B34: Flux de trésorerie provenant du financement par les capitaux étrangers (somme FO à FQ) | C34: E | E34: 0
A35: ZF | B35: Flux de trésorerie provenant des capitaux étrangers (D + E) | C35: F | E35: -3603730000 | F35: -3603730000
A36: ZG | B36: VARIATION DE LA TRESORERIE NETTE DE LA PERIODE (B + C + F) | C36: G | E36: -362548412 | F36: -301741512
A37: ZH | B37: Trésorerie nette au 31 décembre (G + A) Contrôle : Trésorerie actif N - Trésorerie passif N | C37: H | E37: 3420109008 | F37: 3782657420
B38: Contrôle

Sheet Note 1
A1: NOTE 1 : DETTES GARANTIES PAR DES SURETES REELLES
A3: Désignation entité : | D3: Excercice clos le : | E3: =+'Fiche de renseignement R1'!$V$10 -> 45657
A4: ='Fiche de renseignement R1'!$J$4 -> SOCIETE NOUVELLE DES SALINS DU SINE SALOUM | D4: Durée en mois : | E4: =+'Fiche de renseignement R1'!$AH$10 -> 12
A5: Numéro d'identification : | B5: =+'Fiche de renseignement R1'!$J$10 -> 000018699
A7: LIBELLES | B7: Note | C7: Montant brut | D7: SURETES REELLES
D8: Hypothèques | E8: Nantissements | F8: Gages/Autres
A10: Dettes financières et ressources assimilées :
A11: Emprunts obligataires convertibles | C11: 0 | D11: 0 | E11: 0 | F11: 0
A12: Autres emprunts obligataires | C12: 0 | D12: 0 | E12: 0 | F12: 0
A13: Emprunts et dette des établissements de crédit | C13: 0 | D13: 0 | E13: 0 | F13: 0
A14: Autres dettes financières | C14: 0 | D14: 0 | E14: 0 | F14: 0
A15: SOUS TOTAL (1) | C15: 0 | D15: 0 | E15: 0 | F15: 0
A17: Dettes de location-acquisition :
A18: Dettes de crédit-bail immobilier | C18: 0 | D18: 0 | E18: 0 | F18: 0
A19: Dettes de crédit-bail mobilier | C19: 0 | D19: 0 | E19: 0 | F19: 0
A20: Dettes sur contrats de location-vente | C20: 0 | D20: 0 | E20: 0 | F20: 0
A21: Dettes sur contrats de location-acquisition | C21: 0 | D21: 0 | E21: 0 | F21: 0
A22: SOUS TOTAL (2) | C22: 0 | D22: 0 | E22: 0 | F22: 0
A24: Dettes du passif circulant :
A25: Fournisseurs et comptes rattachés | C25: 0 | D25: 0 | E25: 0 | F25: 0
A26: Clients | C26: 0 | D26: 0 | E26: 0 | F26: 0
A27: Personnel | C27: 0 | D27: 0 | E27: 0 | F27: 0
A28: Sécurité sociale et organismes sociaux | C28: 0 | D28: 0 | E28: 0 | F28: 0
A29: Etat | C29: 0 | D29: 0 | E29: 0 | F29: 0
A30: Organismes internationaux | C30: 0 | D30: 0 | E30: 0 | F30: 0
A31: Associés et groupe | C31: 0 | D31: 0 | E31: 0 | F31: 0
A32: Créditeurs divers | C32: 0 | D32: 0 | E32: 0 | F32: 0
A33: SOUS TOTAL (3) | C33: 0 | D33: 0 | E33: 0 | F33: 0
A34: TOTAL (1) + (2) + (3) | C34: 0 | D34: 0 | E34: 0 | F34: 0
A35: ENGAGEMENTS FINANCIERS | E35: Engagements donnés | F35: Engagements reçus
A36: Engagements consentis à des entités liées | D36: 0 | E36: 0 | F36: 0
A37: Primes de remboursement non échus | D37: 0 | E37: 0 | F37: 0
A38: Avals, cautions, garanties | D38: 0 | E38: 0 | F38: 0
A39: Hypothèques, nantissements, gages, autres | D39: 0 | E39: 0 | F39: 0
A40: Effets escomptés non échus | D40: 0 | E40: 0 | F40: 0
A41: Créances commerciales et professionnelles cédées | D41: 0 | E41: 0 | F41: 0
A42: Abandon de créances conditionnelles | D42: 0 | E42: 0 | F42: 0
A43: TOTAL | E43: =SUM(E36:E42) -> 0 | F43: =SUM(F36:F42) -> 0
A44: Commentaire :
A45: NEANT

Sheet Note 2
A1: NOTE 2 : INFORMATIONS OBLIGATOIRES
A3: Désignation entité : | C3: Excercice clos le : | D3: =+'Fiche de renseignement R1'!$V$10 -> 45657
A4: ='Fiche de renseignement R1'!$J$4 -> SOCIETE NOUVELLE DES SALINS DU SINE SALOUM | C4: Durée en mois : | D4: =+'Fiche de renseignement R1'!$AH$10 -> 12
A5: Numéro d'identification : | B5: =+'Fiche de renseignement R1'!$J$10 -> 000018699
A7: A - DECLARATION DE CONFORMITE AU SYSCOHADA
A8: Les états financiers sont établis en conformité avec le Système comptable OHADA et l'acte uniforme relatif au droit comptable et à l'information financière
A9: B - REGLES ET METHODES COMPTABLES
A10: Les états financiers ont été confectionnés dans le respect desconventions, des postulats et des régles d'évaluation édictés par le SYSOHADA et l'acte uniforme
A11: C - DEROGATION AUX POSTULATS ET CONVENTIONS COMPTABLES
A12: Respect de tous les postulats et conventions comptables sans aucune dérogation
A13: D - INFORMATIONS COMPLEMENTAIRES RELATIVES AU BILAN, AU COMPTE DE RESULTAT ET AU TABLEAU DES FLUX DE TRESORERIE
A14: Pas d'informations complémentaires relatives aux autres états financiers

Sheet Note 3A
A1: NOTE 3A : IMMOBILISATION BRUTE
A3: Désignation entité : | E3: Excercice clos le : | F3: =+'Fiche de renseignement R1'!$V$10 -> 45657
A4: ='Fiche de renseignement R1'!$J$4 -> SOCIETE NOUVELLE DES SALINS DU SINE SALOUM | E4: Durée en mois : | F4: =+'Fiche de renseignement R1'!$AH$10 -> 12
A5: Numéro d'identification : | B5: =+'Fiche de renseignement R1'!$J$10 -> 000018699
A7: SITUATIONS ET MOUVEMENTS | B7: Montant brut à l'ouverture de l'exercice | C7: Acquisitions Apports Créations | D7: Virements de poste à poste | E7: Suite à une réévaluation pratiquée au cours de l'exercice | F7: Cessions Scissions Hors service | G7: Virements de poste à poste | H7: Montant brut à la clôture de l'exercice
A10: IMMOBILISATIONS INCORPORELLES | B10: 87818015 | C10: 760532 | D10: 0 | E10: 0 | F10: 4626699 | G10: 0 | H10: 83951848
A11: Frais de développement et de prospection | B11: 26937701 | C11: 0 | F11: 0 | H11: 26937701
A12: Brevets, licences, logiciels et droits similaires | B12: 27080314 | C12: 760532 | F12: 4626699 | H12: 23214147
A13: Fonds commercial et droit au bail | B13: 0 | C13: 0 | H13: 0
A14: Autres immobilisations incorporelles | B14: 33800000 | C14: 0 | H14: 33800000
A15: IMMOBILISATIONS CORPORELLES | B15: 10304845104 | C15: 823390673 | D15: 120864821 | E15: 0 | F15: 354756925 | G15: 120689821 | H15: 10773653852
A16: Terrains hors immeuble de placement | B16: 1163994254 | C16: 27940078 | F16: 0 | G16: 41559138 | H16: 1150375194
A17: Terrains immeuble de placement | B17: 0 | C17: 0 | F17: 0 | H17: 0
A18: Bâtiments hors immeuble de placement | B18: 1040275840 | C18: 175762729 | F18: 0 | G18: 13058560 | H18: 1202980009
A19: Bâtiments immeuble de placement | B19: 0 | C19: 0 | F19: 0 | H19: 0
A20: Aménagements, agencements et installations | B20: 1359502455 | C20: 115625148 | F20: 0 | G20: 63465678 | H20: 1411661925
A21: Matériel, mobilier et actifs biologiques | B21: 6508955691 | C21: 390956273 | D21: 120864821 | F21: 321971925 | H21: 6698804860
A22: Matériel de transport | B22: 217821864 | C22: 107800000 | F22: 32785000 | H22: 292836864
A23: AVANCES ET ACOMPTES VERSES SUR IMMOBILISATIONS | B23: 14295000 | C23: 5306445 | D23: 0 | E23: 0 | F23: 0 | G23: 2606445 | H23: 16995000
A24: IMMOBILISATIONS FINANCIERES | B24: 185805618 | C24: 0 | D24: 9320 | E24: 0 | F24: 0 | G24: 9320 | H24: 185805618
A25: Titres de participation | B25: 115837009 | C25: 0 | G25: 9320 | H25: 115827689
A26: Autres immobilisations financières | B26: 69968609 | C26: 0 | D26: 9320 | F26: 0 | H26: 69977929
A27: TOTAL GENERAL | B27: 10578468737 | C27: 824151205 | D27: 120874141 | E27: 0 | F27: 359383624 | G27: 120699141 | H27: 11043411318
A28: Commentaire :
A29: Les investissements ont porté :- sur la suite des travaux Kousmar phase 2 : digues, surverses, bois de planchéiage( 91,3 M ); -L'installation d'une Centrale photovoltaïque pour alimentation pompes station I1 ,2 x 22KW ,(87,1M) ; - l'acquistion de Pièces de rechange Liebherr pour roue pelle (25,8 M); -l'acquisition de Pompe VI350 – 1500m3/H – 22KW pour doublement capacité Station I1 (24,4M); 2 jeux de chaînes de traction pour 2 pelles flottantes EIK (25,5M); 1 train de roulement pour pelle Caterpillar 320D1 (27,0M); 4 chaînes nues pour les récolteurs 744LL1 et 744LL2 (21,6M); Pièces de rechanges pour récolteurs 744LL1 et 744LL2 (38,9M); Acquisition d'outillage d’atelier mécanique, Gaussmètre (17,9M); l'installation d'un portail coulissant ( 10,2 M) . En matière de Matériel de transport , nous avons effectué l'aquisition de 3 véhicules Toyota (107, 8 M) .

Sheet Note 3B
A1: NOTE 3B : BIENS PRIS EN LOCATION ACQUISITION
A3: Désignation entité : | G3: Excercice clos le : | H3: =+'Fiche de renseignement R1'!$V$10 -> 45657
A4: ='Fiche de renseignement R1'!$J$4 -> SOCIETE NOUVELLE DES SALINS DU SINE SALOUM | G4: Durée en mois : | H4: =+'Fiche de renseignement R1'!$AH$10 -> 12
A5: Numéro d'identification : | B5: =+'Fiche de renseignement R1'!$J$10 -> 000018699
A7: SITUATIONS ET MOUVEMENTS | B7: NATURE DU CONTRAT (I; M; A) | C7: A | D7: AUGMENTATIONS B | G7: DIMINUTIONS C | I7: D = A +B - C
C8: Montant brut à l'ouverture de l'exercice | D8: Acquisitions Apports Créations | E8: Virements de poste à poste | F8: Suite à une réévaluation pratiquée au cours de l'exercice | G8: Cessions Scissions Hors service | H8: Virements de poste à poste | I8: Montant brut à l'ouverture de l'exercice
B9: [1]
A10: Brevets, licences, logiciels et droits similaires | B10: 0 | C10: 0 | D10: 0 | E10: 0 | F10: 0 | G10: 0 | H10: 0 | I10: 0
A11: Fonds commercial et droit au bail | B11: 0 | C11: 0 | D11: 0 | E11: 0 | F11: 0 | G11: 0 | H11: 0 | I11: 0
A12: Autres immobilisations incorporelles | B12: 0 | C12: 0 | D12: 0 | E12: 0 | F12: 0 | G12: 0 | H12: 0 | I12: 0
A13: SOUS TOTAL : IMMOBILISATIONS INCORPORELLES | B13: 0 | C13: 0 | D13: 0 | E13: 0 | F13: 0 | G13: 0 | H13: 0 | I13: 0
A14: Terrains | B14: 0 | C14: 0 | D14: 0 | E14: 0 | F14: 0 | G14: 0 | H14: 0 | I14: 0
A15: Bâtiments | B15: 0 | C15: 0 | D15: 0 | E15: 0 | F15: 0 | G15: 0 | H15: 0 | I15: 0
A16: Aménagements, agencements et installations | B16: 0 | C16: 0 | D16: 0 | E16: 0 | F16: 0 | G16: 0 | H16: 0 | I16: 0
A17: Matériel, mobilier et actifs biologiques | B17: 0 | C17: 0 | D17: 0 | E17: 0 | F17: 0 | G17: 0 | H17: 0 | I17: 0
A18: Matériel de transport | B18: 0 | C18: 0 | D18: 0 | E18: 0 | F18: 0 | G18: 0 | H18: 0 | I18: 0
A19: SOUS TOTAL : IMMOBILISATIONS CORPORELLES | B19: 0 | C19: 0 | D19: 0 | E19: 0 | F19: 0 | G19: 0 | H19: 0 | I19: 0
A21: TOTAL GENERAL | B21: 0 | C21: 0 | D21: 0 | E21: 0 | F21: 0 | G21: 0 | H21: 0 | I21: 0
A22: [1] I : crédit-bail immobilier; M : crédit-bail mobilier; A : autres contrats (dédoubler le poste si montants significatifs)
A23: Commentaire :
A24: NEANT

Sheet Note 3C
A1: NOTE 3C : IMMOBILISATIONS (AMORTISSEMENTS)
A3: Désignation entité : | D3: Excercice clos le : | E3: =+'Fiche de renseignement R1'!$V$10 -> 45657
A4: ='Fiche de renseignement R1'!$J$4 -> SOCIETE NOUVELLE DES SALINS DU SINE SALOUM | D4: Durée en mois :
A5: Numéro d'identification : | B5: =+'Fiche de renseignement R1'!$J$10 -> 000018699
A7: SITUATIONS ET MOUVEMENTS | B7: A | C7: B | D7: C | E7: D = A +B - C
B8: Amortissements cumulés à l'ouverture de l'exercice | C8: Augmentations : Dotations de l'exercice | D8: Diminutions : Amortissements relatifs aux éléments sortis de l'actif | E8: Cumul des amortissements à la clôture de l'exercice
A10: Frais de développement et de prospection | B10: 0 | C10: 0 | D10: 0 | E10: 0
A11: Brevets, licences, logiciels et droits similaires | B11: 26449757 | C11: 422671 | D11: 4606801 | E11: 22265627
A12: Fonds commercial et droit au bail | B12: 0 | C12: 0 | D12: 0 | E12: 0
A13: Autres immobilisations incorporelles | B13: 0 | C13: 0 | D13: 0 | E13: 0
A14: SOUS TOTAL : IMMOBILISATIONS INCORPORELLES | B14: 26449757 | C14: 422671 | D14: 4606801 | E14: 22265627
A15: Terrains hors immeuble de placement | B15: 805049700 | C15: 83833891 | D15: 0 | E15: 888883591
A16: Terrains immeuble de placement | B16: 0 | C16: 0 | D16: 0 | E16: 0
A17: Bâtiments hors immeuble de placement | B17: 338374238 | C17: 52601740 | D17: 0 | E17: 390975978
A18: Bâtiments immeuble de placement | B18: 0 | C18: 0 | D18: 0 | E18: 0
A19: Aménagements, agencements et installations | B19: 600166883 | C19: 99269372 | D19: 0 | E19: 699436255
A20: Matériel, mobilier et actifs biologiques | B20: 5528435191 | C20: 515578621 | D20: 321387524 | E20: 5722626288
A21: Matériel de transport | B21: 187602408 | C21: 25879987 | D21: 32785000 | E21: 180697395
... A24: TOTAL GENERAL | B24: 7486078177 | C24: 777586282 | D24: 358779325 | E24: 7904885134
A25: Commentaire :
A26: La méthode de l'amortissement linéaire est la seule utilisée.

Sheet Note 3D
A1: NOTE 3D : IMMOBILISATIONS (PLUS-VALUES ET MOINS VALUES DE CESSION)
A3: Désignation entité : | D3: Excercice clos le : | E3: =+'Fiche de renseignement R1'!$V$10 -> 45657
A4: ='Fiche de renseignement R1'!$J$4 -> SOCIETE NOUVELLE DES SALINS DU SINE SALOUM | D4: Durée en mois : | E4: =+'Fiche de renseignement R1'!$AH$10 -> 12
A5: Numéro d'identification : | B5: =+'Fiche de renseignement R1'!$J$10 -> 000018699
B7: MONTANT BRUT | C7: AMORTISSEMENTS | D7: VALEUR COMPTABLE NETTE | E7: PRIX DE CESSION | F7: PLUS VALUE OU MOINS VALUE
C8: PRATIQUES
B9: A | C9: B | D9: C = A - B | E9: D | F9: E = D - C
A10: Frais de développement et de prospection | B10: 0 | C10: 0 | D10: 0 | E10: 0 | F10: 0
A11: Brevets, licences, logiciels et droits similaires | B11: 4626699 | C11: 4606801 | D11: 19898 | F11: -19898
A12: Fonds commercial et droit au bail | B12: 0 | C12: 0 | D12: 0 | E12: 0 | F12: 0
A13: Autres immobilisations incorporelles | B13: 0 | C13: 0 | D13: 0 | E13: 0 | F13: 0
A14: SOUS TOTAL : IMMOBILISATIONS INCORPORELLES | B14: 4626699 | C14: 4606801 | D14: 19898 | E14: 0 | F14: -19898
A15: Terrains | B15: 0 | C15: 0 | D15: 0 | E15: 0 | F15: 0
A16: Bâtiments | B16: 0 | C16: 0 | D16: 0 | E16: 0 | F16: 0
A17: Aménagements, agencements et installations | B17: 0 | C17: 0 | D17: 0 | E17: 0 | F17: 0
A18: Matériel, mobilier et actifs biologiques | B18: 321971925 | C18: 321387524 | D18: 584401 | E18: 0 | F18: -584401
A19: Matériel de transport | B19: 32785000 | C19: 32785000 | D19: 0 | E19: 0 | F19: 0
A20: SOUS TOTAL : IMMOBILISATIONS CORPORELLES | B20: 354756925 | C20: 354172524 | D20: 584401 | E20: 0 | F20: -584401
A21: Titres de participation | B21: 0 | C21: 0 | D21: 0 | E21: 0 | F21: 0
A22: Autres immobilisations financières | B22: 0 | C22: 0 | D22: 0 | E22: 0 | F22: 0
A23: SOUS TOTAL : IMMOBILISATIONS FINANCIERES | B23: 0 | C23: 0 | D23: 0 | E23: 0 | F23: 0
A25: TOTAL GENERAL | B25: 359383624 | C25: 358779325 | D25: 604299 | E25: 0 | F25: -604299
A26: Commentaire :
A27: Toutes les sorties correspondent à des mises au rebut. Le résultat sur cession correpond à une valeur nette comptable.

Sheet Note 3E
A1: NOTE 3E : INFORMATIONS SUR LES REEVALUATIONS EFFECTUEES PAR L'ENTITE
A3: Désignation entité : | C3: Excercice clos le : | D3: =+'Fiche de renseignement R1'!$V$10 -> 45657
A4: ='Fiche de renseignement R1'!$J$4 -> SOCIETE NOUVELLE DES SALINS DU SINE SALOUM | C4: Durée en mois : | D4: =+'Fiche de renseignement R1'!$AH$10 -> 12
A5: Numéro d'identification : | B5: =+'Fiche de renseignement R1'!$J$10 -> 000018699
A7: Nature et date des réévaluations :
A13: Eléments réévalués par postes du bilan | B13: Montants coûts historiques | C13: Amortissements supplémentaires
A22: Méthode de réévaluation utilisée :
A24: Traitement fiscal de l'écart de réévaluation
A25: et des amortissements supplémentaires :
A27: Montant de l'écart incorporé au capital :

Sheet Note 4
A1: NOTE 4 : IMMOBILISATIONS FINANCIERES
A3: Désignation entité : | E3: Excercice clos le : | F3: =+'Fiche de renseignement R1'!$V$10 -> 45657
A4: ='Fiche de renseignement R1'!$J$4 -> SOCIETE NOUVELLE DES SALINS DU SINE SALOUM | E4: Durée en mois : | F4: =+'Fiche de renseignement R1'!$AH$10 -> 12
A5: Numéro d'identification : | B5: =+'Fiche de renseignement R1'!$J$10 -> 000018699
A7: SITUATIONS ET MOUVEMENTS | B7: ANNEE N | C7: ANNEE N-1 | D7: Variation en % | E7: Créances à un an au plus | F7: Créances à plus d'un an et à deux ans au plus | G7: Créances à plus de deux ans
A9: Titres de participation | B9: 115827689 | C9: 115827689 | D9: 0 | G9: 115827689
A10: Prêts et créances
A11: Prêt au personnel
A12: Créances sur l'Etat
A13: Titres immobilisés
A14: Dépôts et cautionnements | B14: 69977929 | C14: 69973269 | D14: 6.659686e-05 | G14: 69973269
A15: Intérêts courus | B15: 0 | C15: 0 | E15: 0 | F15: 0 | G15: 0
A16: TOTAL BRUT | B16: 185805618 | C16: 185800958 | D16: 2.5080603e-05 | G16: 185805618
A17: Dépréciations titres de participation | B17: 50227689 | C17: 50227689 | D17: 0 | G17: 50227689
A18: Dépréciations autres immobilisations | B18: 9320 | C18: 9320 | D18: 0 | G18: 9320
A19: TOTAL NET DE DEPRECIATION | B19: 135568609 | C19: 135563949 | D19: 3.4374921e-05 | G19: 135568609
A21: Liste des filiales et participations :
A23: Dénomination sociale | B23: Localisation (ville/pays) | C23: Valeur d'acquisition | E23: % détenu | F23: Montant des capitaux propres filiale | G23: Résultat dernier exercice filiale
A25: Salins du Sénégal SA (1) | B25: Kaolack, Sénégal | C25: 65600000 | E25: 0.2 | F25: 328000000 | G25: néant
A26: Chérifienne des sels (2) | B26: Maroc | C26: 0 | E26: 0.35 | F26: 0 | G26: 0
C27: 0 | E27: 0 | F27: 0 | G27: 0
C28: 0 | E28: 0 | F28: 0 | G28: 0
C29: 0 | E29: 0 | F29: 0 | G29: 0
C30: 0 | E30: 0 | F30: 0 | G30: 0
C31: 0 | E31: 0 | F31: 0 | G31: 0
A32: Commentaire :
A33: (2) Absence d'informations sur cette société dont les actions sont totalement provisionnées.

Sheet Note 5
A1: NOTE 5 : ACTIF CIRCULANT HAO
A3: Désignation entité : | E3: Excercice clos le : | F3: =+'Fiche de renseignement R1'!$V$10 -> 45657
A4: ='Fiche de renseignement R1'!$J$4 -> SOCIETE NOUVELLE DES SALINS DU SINE SALOUM | E4: Durée en mois : | F4: =+'Fiche de renseignement R1'!$AH$10 -> 12
A5: Numéro d'identification : | B5: =+'Fiche de renseignement R1'!$J$10 -> 000018699
A8: LIBELLES | B8: ANNEE N | C8: ANNEE N-1 | D8: Variation en %
A10: Créances sur cessions d'immobilisations | B10: 0 | C10: 0
A11: Autres créances hors activités ordinaires | B11: 0 | C11: 0
A12: TOTAL BRUT | B12: 0 | C12: 0
A13: Dépréciations des créances HAO | B13: 0 | C13: 0
A14: TOTAL NET DE DEPRECIATION | B14: 0 | C14: 0
A15: Commentaire :
A20: DETTES CIRCULANTES HAO
A22: LIBELLES | B22: ANNEE N | D22: ANNEE N-1 | F22: VARIATION EN %
A24: Fournisseurs d'investissements | B24: 0 | D24: 0
A25: Fournisseurs d'investissements effets à payer | B25: 0 | D25: 0
A26: Versements restant à effectuer sur titres de participation et titres immobilisés non libérés | B26: 0 | D26: 0
A27: Autres dettes hors activités ordinaires | B27: 0 | D27: 0
A28: TOTAL | B28: 0 | D28: 0
A29: Commentaire :

Sheet Note 6
A1: NOTE 6 : STOCKS ET ENCOURS(1)
A3: Désignation entité : | C3: Excercice clos le : | D3: =+'Fiche de renseignement R1'!$V$10 -> 45657
A4: ='Fiche de renseignement R1'!$J$4 -> SOCIETE NOUVELLE DES SALINS DU SINE SALOUM | C4: Durée en mois : | D4: =+'Fiche de renseignement R1'!$AH$10 -> 12
A5: Numéro d'identification : | B5: =+'Fiche de renseignement R1'!$J$10 -> 000018699
A7: LIBELLES | B7: ANNEE N | C7: ANNEE N-1 | D7: VARIATION EN %
A9: Marchandises | B9: 0 | C9: 0
A10: Matières premmières et fournitures liées | B10: 0 | C10: 0
A11: Autres approvisionnements | B11: 3238992246 | C11: 3201175281 | D11: 0.011813463
A12: Produits en cours | B12: 683129800 | C12: 689421375 | D12: -0.0091258775
A13: Services en cours | B13: 0 | C13: 0
A14: Produits finis | B14: 1633464012 | C14: 1390086884 | D14: 0.17508052
A15: Produits intermédiaires | B15: 0 | C15: 0
A16: Stocks en cours de cours, en consignation ou en dépôt | B16: 0 | C16: 253311589 | D16: -1
A17: TOTAL BRUT STOCKS ET EN COURS | B17: 5555586058 | C17: 5533995129 | D17: 0.0039015085
A18: Dépréciations des stocks | B18: 193239513 | C18: 99849200 | D18: 0.93531358
A20: Total net de dépréciation | B20: 5362346545 | C20: 5434145929 | D20: -0.013212635
A21: (1) : Les stocks HAO seront inscrits dans l'actif circulant HAO que lorsque leur montant total est significatif
A22: (supérieur à 5% du total de l'actif circulant)
A23: Commentaire :
A24: Pas d'évolution signification sur les stocks

Sheet Note 7
A1: NOTE 7 : CLIENTS
A3: Désignation entité : | E3: Excercice clos le : | F3: =+'Fiche de renseignement R1'!$V$10 -> 45657
A4: ='Fiche de renseignement R1'!$J$4 -> SOCIETE NOUVELLE DES SALINS DU SINE SALOUM | E4: Durée en mois : | F4: =+'Fiche de renseignement R1'!$AH$10 -> 12
A5: Numéro d'identification : | B5: =+'Fiche de renseignement R1'!$J$10 -> 000018699
A7: LIBELLES | B7: ANNEE N | C7: ANNEE N-1 | D7: Variation en % | E7: Créances à un an au plus | F7: Créances à plus d'un an et à deux ans au plus | G7: Créances à plus de deux ans
A9: Clients (hors réserves de propriété Groupe) | B9: 401035558 | C9: 368525336 | D9: 0.088217061 | E9: 401035558 | F9: 0 | G9: 0
A10: Clients effets à recevoir (hors réserves de propriété Groupe) | B10: 0 | C10: 0 | E10: 0 | F10: 0 | G10: 0
A11: Clients effets à recevoir avec réserves de propriété | B11: 0 | C11: 0 | E11: 0 | F11: 0 | G11: 0
A12: Clients effets à recevoir Groupe | B12: 0 | C12: 0 | E12: 0 | F12: 0 | G12: 0
A13: Créances sur cession d'immobilisations | B13: 0 | C13: 0 | E13: 0 | F13: 0 | G13: 0
A14: Clients effets escomptés et non échus | B14: 0 | C14: 0 | E14: 0 | F14: 0 | G14: 0
A15: Créances litigieuses ou douteuses | B15: 0 | C15: 0 | E15: 0 | F15: 0 | G15: 0
A16: Clients produits à recevoir | B16: 0 | C16: 0 | E16: 0 | F16: 0 | G16: 0
A17: TOTAL BRUT CLIENTS | B17: 401035558 | C17: 368525336 | D17: 0.088217061 | E17: 401035558 | F17: 0 | G17: 0
A18: Dépréciations des comptes clients | B18: 0 | C18: 0 | E18: 0 | F18: 0 | G18: 0
A19: TOTAL NET DE DEPRECIATION | B19: 401035558 | C19: 368525336 | D19: 0.088217061 | E19: 401035558 | F19: 0 | G19: 0
A20: Clients, avances reçues hors groupe | B20: 100649106 | C20: 130101598 | D20: -0.22638071 | E20: 100649106 | F20: 0 | G20: 0
A21: Clients, avances reçues groupe | B21: 0 | C21: 0 | E21: 0 | F21: 0 | G21: 0
A22: Autres clients créditeurs | B22: 0 | C22: 0 | E22: 0 | F22: 0 | G22: 0
A23: TOTAL CLIENTS CREDITEURS | B23: 100649106 | C23: 130101598 | D23: -0.22638071 | E23: 100649106 | F23: 0 | G23: 0
A24: Commentaire :
A25: cette hausse de créances clients de 9% s'explique principalement par des retards de paiement de moins de 60 jours, qui ont été soldé à 60% sur le 1ier trimestre 2025

Sheet Note 8
A1: NOTE 8 : AUTRES CREANCES
A3: Désignation entité : | E3: Excercice clos le : | F3: =+'Fiche de renseignement R1'!$V$10 -> 45657
A4: ='Fiche de renseignement R1'!$J$4 -> SOCIETE NOUVELLE DES SALINS DU SINE SALOUM | E4: Durée en mois : | F4: =+'Fiche de renseignement R1'!$AH$10 -> 12
A5: Numéro d'identification : | B5: =+'Fiche de renseignement R1'!$J$10 -> 000018699
A7: LIBELLES | B7: ANNEE N | C7: ANNEE N-1 | D7: Variation en % | E7: Créances à un an au plus | F7: Créances à plus d'un an et à deux ans au plus | G7: Créances à plus de deux ans
A9: Personnel | B9: 31363230 | C9: 39425083 | D9: -0.20448538 | E9: 31363230 | F9: 0 | G9: 0
A10: Organismes sociaux | B10: 10820270 | C10: 5064464 | D10: 1.1365084 | E10: 10820270 | F10: 0 | G10: 0
A11: État et Collectivités publiques | B11: 8696565 | C11: 8696565 | D11: 0 | E11: 0 | F11: 0 | G11: 8696565
A12: Organismes internationaux | B12: 0 | C12: 0 | E12: 0 | F12: 0 | G12: 0
A13: Apporteurs, associés et groupe | F13: 0 | G13: 0
A14: Compte transitoire ajustement spécial lié à la révision du SYSCOHADA | B14: 0 | C14: 0 | E14: 0 | F14: 0 | G14: 0
A15: Autres débiteurs divers | B15: 64617867 | C15: 39882242 | D15: 0.62021651 | E15: 64617867 | F15: 0 | G15: 0
A16: Comptes permanents non bloqués des établissements et des succursales | B16: 0 | C16: 0 | E16: 0 | F16: 0 | G16: 0
A17: Comptes de liaison charges et produits | B17: 0 | C17: 0 | E17: 0 | F17: 0 | G17: 0
A18: Comptes de liaison des sociétés en participation | B18: 0 | C18: 0 | E18: 0 | F18: 0 | G18: 0
A19: TOTAL BRUT AUTRES CREANCES | B19: 115497932 | C19: 93068354 | D19: 0.24100112 | E19: 106801367 | F19: 0 | G19: 8696565
A20: Dépréciations des autres créances | B20: 0 | C20: 0
A21: TOTAL NET DE DEPRECIATION | B21: 115497932 | C21: 93068354 | D21: 0.24100112 | E21: 106801367 | F21: 0 | G21: 8696565
A22: Commentaire :
A23: Le poste autre débiteur enrégistre une importante augmentation due essentiellement aux charges constatées d'avance.

Sheet Note 8A
A1: NOTE 8A : TABLEAU D'ETALEMENT DES CHARGES IMMOBILISEES
A3: Désignation entité : | E3: Excercice clos le : | F3: =+'Fiche de renseignement R1'!$V$10 -> 45657
A4: ='Fiche de renseignement R1'!$J$4 -> SOCIETE NOUVELLE DES SALINS DU SINE SALOUM | E4: Durée en mois : | F4: =+'Fiche de renseignement R1'!$AH$10 -> 12
A5: Numéro d'identification : | B5: =+'Fiche de renseignement R1'!$J$10 -> 000018699
A7: LIBELLES | B7: Frais d'établissement | D7: Charges à répartir sur plusiers exercices | F7: Primes de remboursement des obligations
A9: Montant global à étaler au 1er janvier 2018
A10: Durée d'étalement
A12: Exercice 2018
A17: Total exercice 2018
A18: Total exercice 2019
A19: Total exercice 2020
A20: Total exercice 2021
A21: Total exercice 2022
A22: TOTAL GENERAL
A26: NEANT

Sheet Note 9
A1: NOTE 9 : TITRES DE PLACEMENT
A3: Désignation entité : | C3: Excercice clos le : | D3: =+'Fiche de renseignement R1'!$V$10 -> 45657
A4: ='Fiche de renseignement R1'!$J$4 -> SOCIETE NOUVELLE DES SALINS DU SINE SALOUM | C4: Durée en mois : | D4: =+'Fiche de renseignement R1'!$AH$10 -> 12
A5: Numéro d'identification : | B5: =+'Fiche de renseignement R1'!$J$10 -> 000018699
A7: LIBELLES | B7: ANNEE N | C7: ANNEE N-1 | D7: VARIATION EN %
A9: Titres de trésor et bons de caisse à court terme | B9: 0 | C9: 0
A10: Actions | B10: 0 | C10: 0
A11: Obligations | B11: 0 | C11: 0
A12: Bons de souscription | B12: 0 | C12: 0
A13: Titres négociables hors régions | B13: 0 | C13: 0
A14: Intérêts courus | B14: 0 | C14: 0
A15: Autres valeurs assimilées | B15: 0 | C15: 0
A16: TOTAL BRUT STOCKS ET EN COURS | B16: 0 | C16: 0
A17: Dépréciations des titres | B17: 0 | C17: 0
A19: TOTAL | B19: 0 | C19: 0
A20: Commentaire :

Sheet Note 10
A1: NOTE 10 : VALEURS A ENCAISSER
A3: Désignation entité : | C3: Excercice clos le : | D3: =+'Fiche de renseignement R1'!$V$10 -> 45657
A4: ='Fiche de renseignement R1'!$J$4 -> SOCIETE NOUVELLE DES SALINS DU SINE SALOUM | C4: Durée en mois : | D4: =+'Fiche de renseignement R1'!$AH$10 -> 12
A5: Numéro d'identification : | B5: =+'Fiche de renseignement R1'!$J$10 -> 000018699
A7: LIBELLES | B7: ANNEE N | C7: ANNEE N-1 | D7: VARIATION EN %
A9: Effets à encaisser | B9: 647200000 | C9: 1127750000 | D9: -0.42611394
A10: Effets à l'encaissement | B10: 0 | C10: 0
A11: Chèques à encaisser | B11: 0 | C11: 0
A12: Chèques à l'encaissement | B12: 0 | C12: 0
A13: Cartes de crédit à encaisser | B13: 0 | C13: 0
A14: Autres valeurs à encaisser | B14: 0 | C14: 0
A15: TOTAL BRUT VALEURS A ENCAISSER | B15: 647200000 | C15: 1127750000 | D15: -0.42611394
A16: Dépréciations des valeurs à encaisser | B16: 0 | C16: 0
A18: TOTAL NET DE DEPRECIATIONS | B18: 647200000 | C18: 1127750000 | D18: -0.42611394
A19: Commentaire :
A20: Diminution des effets à encaisser due à la baisse de volume de vente (Notons que sur Décembre il n'y a pas eu de vente vers la Côte d'Ivoire, le Bénin.

Sheet Note 11
A1: NOTE 11 : DISPONIBILITES
A3: Désignation entité : | C3: Excercice clos le : | D3: =+'Fiche de renseignement R1'!$V$10 -> 45657
A4: ='Fiche de renseignement R1'!$J$4 -> SOCIETE NOUVELLE DES SALINS DU SINE SALOUM | C4: Durée en mois : | D4: =+'Fiche de renseignement R1'!$AH$10 -> 12
A5: Numéro d'identification : | B5: =+'Fiche de renseignement R1'!$J$10 -> 000018699
A7: LIBELLES | B7: ANNEE N | C7: ANNEE N-1 | D7: VARIATION EN %
A9: Banques locales | B9: 2767672277 | C9: 2652354879 | D9: 0.043477364
A10: Banques autres états région
A11: Banques, dépôt à terme | B11: 0 | C11: 0
A12: Autres banques | B12: 7829322 | C12: 7829322 | D12: 0 %
A13: Banques, intérêts courus
A14: Chèques postaux | B14: 1613420 | C14: 1613420 | D14: 0
A15: Autres établissements financiers
A16: Etablissements financiers intérêts courus
A17: Intruments de trésorerie
A18: Caisse | B18: 3623311 | C18: 1114121 | D18: 2.2521701
A19: Caisse électronique mobile
A20: Régies d'avances et virements accréditifs | B20: 0 | C20: 0
A21: TOTAL BRUT DISPONIBILITES | B21: 2780738330 | C21: 2662911742 | D21: 0.044247275
A22: Dépréciations | B22: 7829322 | C22: 7829322
A24: TOTAL NET DE DEPRECIATIONS | B24: 2772909008 | C24: 2655082420 | D24: 0.044247275
A25: Commentaire :
A32: NB : Banques et intérêts courus et Etablissement financiers intérêts courus figurent dans cette rubrique
A33: en négatif si le compte principal est débiteur

Sheet Note 12
A1: NOTE 12 : ECARTS DE CONVERSION
A3: Désignation entité : | E3: Excercice clos le : | F3: =+'Fiche de renseignement R1'!$V$10 -> 45657
A4: ='Fiche de renseignement R1'!$J$4 -> SOCIETE NOUVELLE DES SALINS DU SINE SALOUM | E4: Durée en mois : | F4: =+'Fiche de renseignement R1'!$AH$10 -> 12
A5: Numéro d'identification : | B5: =+'Fiche de renseignement R1'!$J$10 -> 000018699
A7: LIBELLES | B7: Devises | C7: Montant en devises | E7: Cours UML année acquisition | F7: Cours UML 31/12 | G7: Variation en valeur absolue
A9: Ecarts de conversion actif : Détailler les créances et dettes concernées | B9: 0 | C9: 0 | E9: 0 | F9: 0 | G9: 0
B10: 0 | C10: 0 | E10: 0 | F10: 0 | G10: 0
B11: 0 | C11: 0 | E11: 0 | F11: 0 | G11: 0
A12: Ecarts de conversion passif : Détailler les créances et dettes concernées | B12: 0 | C12: 0 | E12: 0 | F12: 0 | G12: 0
B13: 0 | C13: 0 | E13: 0 | F13: 0 | G13: 0
B14: 0 | C14: 0 | E14: 0 | F14: 0 | G14: 0
B15: 0 | C15: 0 | E15: 0 | F15: 0 | G15: 0
B16: 0 | C16: 0 | E16: 0 | F16: 0 | G16: 0
A17: Commentaire :
A22: TRANSFERTS DE CHARGES
A24: LIBELLES | B24: ANNEE N | D24: ANNEE N-1 | F24: VARIATION EN %
A26: Transferts de charges d'exploitation : Détailler la nature des charges transférées | B26: 0 | D26: 0
B27: 0 | D27: 0
B28: 0 | D28: 0
A29: Transferts de charges financières : Détailler la nature des charges transférées | B29: 0 | D29: 0
B30: 0 | D30: 0
B31: 0 | D31: 0
B32: 0 | D32: 0
B33: 0 | D33: 0
A34: Commentaire :
A35: NEANT

Sheet Note 13
A1: NOTE 13 : CAPITAL
A3: Désignation entité : | E3: Excercice clos le : | F3: =+'Fiche de renseignement R1'!$V$10 -> 45657
A4: ='Fiche de renseignement R1'!$J$4 -> SOCIETE NOUVELLE DES SALINS DU SINE SALOUM | E4: Durée en mois : | F4: =+'Fiche de renseignement R1'!$AH$10 -> 12
A5: Numéro d'identification : | B5: =+'Fiche de renseignement R1'!$J$10 -> 000018699
E7: Valeur nominale des actions ou parts : | G7: 10000
A8: NOMS ET PRENOMS | B8: Nationalité | C8: Nature des actions ou parts (ordinaires ou préférences) | E8: Nombre | F8: Montant total | G8: Cessions ou remboursements en cours d'exercice
A10: SALINS DU MIDI PARTICIPATION | B10: FRANCAISE | C10: ORDINAIRES | E10: 40060 | F10: 400600000 | G10: 0
A11: Héritiers feu Idrissa Gueye | B11: Sénégalaise | C11: ORDINAIRES | E11: 10718 | F11: 107180000 | G11: 0
A12: M. Moustapha Seck | B12: Sénégalaise | C12: ORDINAIRES | E12: 1710 | F12: 17100000 | G12: 0
A13: Mme Yaye Bani DIALLO-Veuve DIOP | B13: Sénégalaise | C13: ORDINAIRES | E13: 1446 | F13: 14460000 | G13: 0
A14: Héritiers Feu Abdoulaye Fofana | B14: Sénégalaise | C14: ORDINAIRES | E14: 800 | F14: 8000000 | G14: 0
A15: Héritiers feu Amadou Ly | B15: Sénégalaise | C15: ORDINAIRES | E15: 687 | F15: 6870000 | G15: 0
A16: Compagnie Commerciale des Sel Marins | B16: Française | C16: ORDINAIRES | E16: 9 | F16: 90000 | G16: 0
A17: TIDIANE SYLLA / ALPHA DIENG | B17: SENEGALAISE | C17: ORDINAIRES | E17: 6 | F17: 60000 | G17: 0
A18: GUY DESCHAMPS /OMAR GUEYE | B18: SENEGALAISE | C18: ORDINAIRES | E18: 6 | F18: 60000 | G18: 0
C19: TOTAL | E19: 55442 | F19: 554420000 | G19: 0
A21: Le capital social n'a pas connu d'évolution.

Sheet Note 14
A1: NOTE 14 : PRIMES ET RESERVES
A3: Désignation entité : | E3: Excercice clos le : | F3: =+'Fiche de renseignement R1'!$V$10 -> 45657
A4: ='Fiche de renseignement R1'!$J$4 -> SOCIETE NOUVELLE DES SALINS DU SINE SALOUM | E4: Durée en mois : | F4: =+'Fiche de renseignement R1'!$AH$10 -> 12
A5: Numéro d'identification : | B5: =+'Fiche de renseignement R1'!$J$10 -> 000018699
A7: LIBELLES | B7: ANNEE N | D7: ANNEE N-1 | F7: VARIATION EN VALEUR ABSOLUE
A9: Primes d'apport | B9: 0 | D9: 0 | F9: 0
A10: Primes d'émission | B10: 0 | D10: 0 | F10: 0
A11: Primes de fusion | B11: 0 | D11: 0 | F11: 0
A12: Primes de conversion | B12: 0 | D12: 0 | F12: 0
A13: Autres primes | B13: 0 | D13: 0 | F13: 0
A14: TOTAL PRIMES | B14: 0 | D14: 0 | F14: 0
A16: Réserves légales | B16: 112600000 | D16: 112600000 | F16: 0
A17: Réserves statutaires | B17: 0 | D17: 0 | F17: 0
A18: Réserves de plus-values nettes à long terme | B18: 0 | D18: 0 | F18: 0
A19: Réserves d'attribution gratuite d'actions au personnel salarié et aux dirigeants | B19: 0 | D19: 0 | F19: 0
A20: Autres réserves réglementées | B20: 0 | D20: 0 | F20: 0
A21: TOTAL RESERVES INDISPONIBLES | B21: 112600000 | D21: 112600000 | F21: 0
... A25: Report à nouveau | B25: 0 | D25: 0 | F25: 0
A27: Commentaire :
A28: L'Assemblée Générale Ordinaire (AGO) du 14-05-2024 avait décidé d'augmenter les réserves libres de 765 394 484 XOF

Sheet Note 15A
A1: NOTE 15A : SUBVENTIONS ET PROVISIONS REGLEMENTEES
A3: Désignation entité : | E3: Excercice clos le : | F3: =+'Fiche de renseignement R1'!$V$10 -> 45657
A4: ='Fiche de renseignement R1'!$J$4 -> SOCIETE NOUVELLE DES SALINS DU SINE SALOUM | E4: Durée en mois : | F4: =+'Fiche de renseignement R1'!$AH$10 -> 12
A5: Numéro d'identification : | B5: =+'Fiche de renseignement R1'!$J$10 -> 000018699
A7: LIBELLES | B7: NOTE | C7: Année N | D7: ANNEE N-1 | E7: Variation en valeur absolue | F7: Variation en % | G7: Régime fiscal | H7: Échéances
A9: Etat | C9: 0 | D9: 0 | E9: 0 | G9: 0
A10: Régions | C10: 0 | D10: 0 | E10: 0 | G10: 0
A11: Départements | C11: 0 | D11: 0 | E11: 0 | G11: 0
A12: Communes et collectivités publiques décentralisées | C12: 0 | D12: 0 | E12: 0 | G12: 0
A13: Entités publiques ou mixtes | C13: 0 | D13: 0 | E13: 0 | G13: 0
A14: Entités et organismes privés | C14: 0 | D14: 0 | E14: 0 | G14: 0
A15: Organismes internationaux | C15: 0 | D15: 0 | E15: 0 | G15: 0
A16: Autres | C16: 0 | D16: 0 | E16: 0 | G16: 0
A17: TOTAL SUBVENTIONS | C17: 0 | D17: 0 | E17: 0 | G17: 0
C18: 0 | D18: 0 | E18: 0 | G18: 0
A19: Amortissements dérogatoires | C19: 0 | D19: 0 | E19: 0 | G19: 0
A20: Plus-values de cession à réinvestir | C20: 0 | D20: 0 | E20: 0 | G20: 0
A21: Provision spéciale de réévaluation | C21: 0 | D21: 0 | E21: 0 | G21: 0
A22: Provisions réglementées relatives aux immobilisations | C22: 0 | D22: 0 | E22: 0 | G22: 0
A23: Provisions réglementées relatives aux stocks | C23: 0 | D23: 0 | E23: 0 | G23: 0
A24: Provisions pour investissement | C24: 0 | D24: 0 | E24: 0 | G24: 0
A25: Autres provisions et fonds réglementés | C25: 0 | D25: 0 | E25: 0 | G25: 0
A26: TOTAL PROVISIONS REGLEMENTEES | C26: 0 | D26: 0 | E26: 0 | G26: 0
A28: TOTAL SUBVENTIONS ET PROVISIONS REGLEMENTEES | C28: 0 | D28: 0 | E28: 0 | G28: 0
A30: Commentaire :
A31: NEANT

Sheet Note 15B
A1: NOTE 15B : AUTRES FONDS PROPRES(1)
A3: Désignation entité : | E3: Excercice clos le : | F3: =+'Fiche de renseignement R1'!$V$10 -> 45657
A4: ='Fiche de renseignement R1'!$J$4 -> SOCIETE NOUVELLE DES SALINS DU SINE SALOUM | E4: Durée en mois : | F4: =+'Fiche de renseignement R1'!$AH$10 -> 12
A5: Numéro d'identification : | B5: =+'Fiche de renseignement R1'!$J$10 -> 000018699
A7: LIBELLES | B7: NOTE | C7: Année N | D7: ANNEE N-1 | E7: Variation en valeur absolue | F7: Variation en % | G7: Échéances
A9: Titres participatifs | C9: 0 | D9: 0 | E9: 0
A10: Avances conditionnées | C10: 0 | D10: 0 | E10: 0
A11: Titres subordonnés à durée indéterminée (TSDI) | C11: 0 | D11: 0 | E11: 0
A12: Obligations remboursables en actions (ORA) | C12: 0 | D12: 0 | E12: 0
A13: Autres | C13: 0 | D13: 0 | E13: 0
A14: TOTAL AUTRES FONDS PROPRES | C14: 0 | D14: 0 | E14: 0
A16: (1) : Le cas échéant, une rubrique "Autres fonds propre" (montant des émissions de titres participatifs,
A17: avances conditionnées,…) sur une ligne séparée est intercalée entre les rubriques
A18: "TOTAL CAPTAUX PROPRES ET RESSOURCES ASSIMILEES" et "EMPRUNTS ET DETTES FINANCIERES" si le
A19: montant des autres fonds propres est significatif.
A21: Commentaire :
A22: NEANT

Sheet Note 16A
A1: NOTE 16A : DETTES FINANCIERES ET RESSOURCES ASSIMILEES
A3: Désignation entité : | D3: Excercice clos le : | F3: =+'Fiche de renseignement R1'!$V$10 -> 45657
A4: ='Fiche de renseignement R1'!$J$4 -> SOCIETE NOUVELLE DES SALINS DU SINE SALOUM | D4: Durée en mois : | F4: =+'Fiche de renseignement R1'!$AH$10 -> 12
A5: Numéro d'identification : | B5: =+'Fiche de renseignement R1'!$J$10 -> 000018699
A7: LIBELLES | B7: Année N | C7: ANNEE N-1 | D7: Variation en valeur absolue | E7: Variation en % | F7: Dettes à un an au plus | G7: Dettes à plus d'un an et à deux ans au plus | H7: Dettes à plus de deux ans
A9: Emprunts obligataires | B9: 0 | C9: 0 | D9: 0 | F9: 0 | G9: 0 | H9: 0
A10: Emprunts et dettes auprès des établissements de crédit | B10: 0 | C10: 0 | D10: 0 | F10: 0 | G10: 0 | H10: 0
A11: Avances reçues de l'Etat | B11: 0 | C11: 0 | D11: 0 | F11: 0 | G11: 0 | H11: 0
A12: Avances reçues et comptes courants bloqués | B12: 0 | C12: 0 | D12: 0 | F12: 0 | G12: 0 | H12: 0
A13: Dépôts et cautionnement reçus | B13: 0 | C13: 0 | D13: 0 | F13: 0 | G13: 0 | H13: 0
A14: Intérêts courus | B14: 0 | C14: 0 | D14: 0 | F14: 0 | G14: 0 | H14: 0
A15: Avances assorties de conditions particulières | B15: 0 | C15: 0 | D15: 0 | F15: 0 | G15: 0 | H15: 0
A16: Autres emprunts et dettes | B16: 0 | C16: 0 | D16: 0 | F16: 0 | G16: 0 | H16: 0
A17: Dettes liées à des participations | B17: 0 | C17: 0 | D17: 0 | F17: 0 | G17: 0 | H17: 0
A18: Comptes permanents bloqués des établissements et succursales | B18: 0 | C18: 0 | D18: 0 | F18: 0 | G18: 0 | H18: 0
A19: TOTAL EMPRUNTS ET DETTES FINANCIERES | B19: 0 | C19: 0 | D19: 0 | F19: 0 | G19: 0 | H19: 0
A21: Crédit bail immobilier | B21: 0 | C21: 0 | D21: 0 | F21: 0 | G21: 0 | H21: 0
... A26: TOTAL DETTES DE LOCATION ACQUISITION | B26: 0 | C26: 0 | D26: 0 | F26: 0 | G26: 0 | H26: 0
A28: Provisions pour litiges | B28: 0 | C28: 0 | D28: 0
A29: Provisions pour garantie données aux clients | B29: 1320851722 | C29: 1320851722 | D29: 0 | E29: 0
A30: Provisions pour pertes sur marchés à achèvement futur | B30: 0 | C30: 0 | D30: 0
A31: Provisions pour perte de change | B31: 0 | C31: 0 | D31: 0
A32: Provisions pour impôts | B32: 0 | C32: 0 | D32: 0
A33: Provisions pour pensions et obligations assimilées | B33: 358017673 | C33: 356301163 | D33: 1716510 | E33: =(B33-C33)/C33 -> 0.0048175818
A34: Actif du régime de retraite | B34: 0 | C34: 0 | D34: 0
A35: Provisions pour amendes et pénalités | B35: 0 | C35: 0 | D35: 0
A36: Provisions de propre assureur | B36: 0 | C36: 0 | D36: 0
A37: Provisions pour démantèlement et remise en état | B37: 0 | C37: 0 | D37: 0
A38: Autres provisions | B38: 0 | C38: 0 | D38: 0
A39: Provisions pour restructuration | B39: 0 | C39: 0 | D39: 0
A40: Provisions de droits à déduction | B40: 0 | C40: 0 | D40: 0
A41: TOTAL PROVISIONS FINANCIERES POUR RISQUES ET CHARGES | B41: 1678869395 | C41: 1677152885 | D41: 1716510 | E41: =IFERROR((B41/C41)/C41,"-") -> 5.968588e-10
A43: Commentaire :

Sheet Note 16B
A1: NOTE 16B : ENGAGEMENTS DE RETRAITE ET AVANTAGES ASSIMILES (METHODE ACTURIELLE)
A3: Désignation entité : | D3: Excercice clos le : | E3: =+'Fiche de renseignement R1'!$V$10 -> 45657
A4: ='Fiche de renseignement R1'!$J$4 -> SOCIETE NOUVELLE DES SALINS DU SINE SALOUM | D4: Durée en mois : | E4: =+'Fiche de renseignement R1'!$AH$10 -> 12
A5: Numéro d'identification : | B5: =+'Fiche de renseignement R1'!$J$10 -> 000018699
A7: HYPOTHESES ACTUARIELLES
A8: LIBELLES | B8: ANNEE N | D8: ANNEE N-1
A9: Taux d'augmentation des salaires | B9: 0 | D9: 0
A10: Taux d'actualisation | B10: 0 | D10: 0
A11: Taux d'inflation | B11: 0 | D11: 0
A12: Probabilité d'être présent dans l'entité à la date de départ à la retraite (expérience passée) | D12: 0
A13: Probabilité d'être en vie à l'âge de départ à la retraite (table de mortalité) | B13: 0 | D13: 0
A14: Taux de rendement effectif des actifs du régime | B14: 0 | D14: 0
A16: Commentaire :
A21: VARIATION DE LA VALEUR DE L'ENGAGEMENT DE RETRAITE AU COURS DE L'EXERCICE
A22: LIBELLES | B22: ANNEE N | D22: ANNEE N-1
A23: OBLIGATION AU TITRE DES ENGAGEMENTS DE RETRAITE A L'OUVERTURE
A24: Coût des services rendus aucours de l'exercice | B24: 0 | D24: 0
A25: Coût financier | B25: 0 | D25: 0
A26: Pertes actuarielles / (gain) | B26: 0 | D26: 0
A27: Prestations payées au cours de l'exercice | B27: 0 | D27: 0
A28: Coût des services passés
A29: OBLIGATION AU TITRE DES ENGAGEMENTS DE RETRAITE A L'OUVERTURE | B29: 0 | D29: 0
A31: Commentaire :
A35: ANALYSES DE SENSIBILITE DES HYPOTHESES ACTUARIELLES
A36: LIBELLES | C36: ANNEE N | E36: ANNEE N-1
C37: Augmentation | D37: Diminution | E37: Augmentation | F37: Diminution
A38: Taux d'actualisation (variation de …%) | C38: 0 | D38: 0 | E38: 0 | F38: 0
A39: Taux de progression des salaires (variation de …%) | C39: 0 | D39: 0 | E39: 0 | F39: 0
A40: Taux de départ du personnel (variation de …%) | C40: 0 | D40: 0 | E40: 0 | F40: 0
A41: Commentaire :
A42: NEANT

Sheet Note 16B bis
A1: NOTE 16B bis : ENGAGEMENTS DE RETRAITE ET AVANTAGES ASSIMILES (METHODE ACTURIELLE)
A3: Désignation entité : | C3: Excercice clos le : | E3: =+'Fiche de renseignement R1'!$V$10 -> 45657
A4: ='Fiche de renseignement R1'!$J$4 -> SOCIETE NOUVELLE DES SALINS DU SINE SALOUM | C4: Durée en mois : | E4: =+'Fiche de renseignement R1'!$AH$10 -> 12
A5: Numéro d'identification : | B5: =+'Fiche de renseignement R1'!$J$10 -> 000018699
A8: ACTIF/PASSIF NET COMPTABILISE AU TITRE DES REGIMES FINANCES
A9: LIBELLES | B9: ANNEE N | C9: ANNEE N-1
A10: Valeur actuelle de l'obligation résultant de régimes financés | B10: 0 | C10: 0
A11: Valeur actuelle des actifs affectés aux plans de retraite | B11: 0 | C11: 0
A12: Excédent / Déficit de régime | B12: 0 | C12: 0
A14: Commentaire :
A18: VALEUR ACTUELLE DES ACTIFS DU REGIME
A19: LIBELLES | B19: ANNEE N
B20: Rendement attendu | C20: Juste valeur des actifs | D20: Rendement attendu | E20: Juste valeur des actifs
A21: Actions | B21: 0 | C21: 0 | D21: 0 | E21: 0
A22: Obligations | B22: 0 | C22: 0 | D22: 0 | E22: 0
A23: Autres | B23: 0 | C23: 0 | D23: 0 | E23: 0
A24: TOTAL | B24: 0 | C24: 0 | D24: 0 | E24: 0
A26: Commentaire :
A27: NEANT

Sheet Note 16C
A1: NOTE 16C : ACTIFS ET PASSIFS EVENTUELS
A3: Désignation entité : | C3: Excercice clos le : | D3: =+'Fiche de renseignement R1'!$V$10 -> 45657
A4: ='Fiche de renseignement R1'!$J$4 -> SOCIETE NOUVELLE DES SALINS DU SINE SALOUM | C4: Durée en mois : | D4: =+'Fiche de renseignement R1'!$AH$10 -> 12
A5: Numéro d'identification : | B5: =+'Fiche de renseignement R1'!$J$10 -> 000018699
A8: LIBELLES | C8: ANNEE N | D8: ANNEE N-1
A9: ACTIF EVENTUEL
A10: Litiges | C10: 0 | D10: 0
A11: ………………………….. | C11: 0 | D11: 0
A12: ………………………….. | C12: 0 | D12: 0
A13: PASSIF EVENTUEL
A14: Litiges | C14: 0 | D14: 0
A15: ………………………….. | C15: 0 | D15: 0
A16: ………………………….. | C16: 0 | D16: 0
A18: Commentaire :

Sheet Note 17
A1: NOTE 17 : FOURNISSEURS D'EXPLOITATION
A3: Désignation entité : | E3: Excercice clos le : | F3: =+'Fiche de renseignement R1'!$V$10 -> 45657
A4: ='Fiche de renseignement R1'!$J$4 -> SOCIETE NOUVELLE DES SALINS DU SINE SALOUM | E4: Durée en mois : | F4: =+'Fiche de renseignement R1'!$AH$10 -> 12
A5: Numéro d'identification : | B5: =+'Fiche de renseignement R1'!$J$10 -> 000018699
A7: LIBELLES | B7: ANNEE N | C7: ANNEE N-1 | D7: Variation en % | E7: Dettes à un an au plus | F7: Dettes à plus d'un an et à deux ans au plus | G7: Dettes à plus de deux ans
A9: Fournisseurs dettes en compte (hors groupe) | B9: 636712368 | C9: 786475224 | D9: -20 % | E9: 636712368 | F9: 0 | G9: 0
A10: Fournisseurs effets à payer (hors groupe) | B10: 0 | C10: 0 | E10: 0 | F10: 0 | G10: 0
A11: Fournisseurs, dettes et effets à payer (groupe) | B11: 0 | C11: 0 | E11: 0 | F11: 0 | G11: 0
A12: Fournisseurs, factures non parvenues (hors groupe) | B12: 21494702 | C12: 108588773 | D12: -0.8020541 | E12: 21494702 | F12: 0 | G12: 0
A13: Fournisseurs, factures non parvenues (groupe) | B13: 0 | C13: 0 | E13: 0 | F13: 0 | G13: 0
A14: TOTAL FOURNISSEURS | B14: 658207070 | C14: 895063997 | D14: -0.26462569 | E14: 658207070 | F14: 0 | G14: 0
A16: Fournisseurs, avances et acomptes (hors groupe) | B16: 72960138 | C16: 40979446 | D16: 0.78040811 | E16: 72960138 | F16: 0 | G16: 0
A17: Fournisseurs, avances et acomptes (groupe) | B17: 0 | C17: 0 | E17: 0 | F17: 0 | G17: 0
A18: Autres fournisseurs débiteurs | B18: 0 | C18: 0 | E18: 0 | F18: 0 | G18: 0
A19: TOTAL FOURNISSEURS DEBITEURS | B19: 72960138 | C19: 40979446 | D19: 0.78040811 | E19: 72960138 | F19: 0 | G19: 0
A21: Commentaire :

Sheet Note 18
A1: NOTE 18 : DETTES FISCALES ET SOCIALES
A3: Désignation entité : | F3: Excercice clos le : | G3: =+'Fiche de renseignement R1'!$V$10 -> 45657
A4: ='Fiche de renseignement R1'!$J$4 -> SOCIETE NOUVELLE DES SALINS DU SINE SALOUM | F4: Durée en mois : | G4: =+'Fiche de renseignement R1'!$AH$10 -> 12
A5: Numéro d'identification : | B5: =+'Fiche de renseignement R1'!$J$10 -> 000018699
A7: LIBELLES | B7: ANNEE N | C7: ANNEE N-1 | D7: Variations en valeurs absolues | E7: Variation en % | F7: Dettes à un an au plus | G7: Dettes à plus d'un an et à deux ans au plus | H7: Dettes à plus de deux ans
A9: Personnel congés à payer | B9: 3204125 | C9: 3439125 | D9: -235000 | E9: -0.068331334 | F9: 3204125 | G9: 0 | H9: 0
A10: Personnel rémunérations dues | B10: 0 | C10: 1276100 | D10: -1276100 | E10: -1 | F10: 0 | G10: 0 | H10: 0
A11: Autres personnel | B11: 9719056 | C11: 13678245 | D11: -3959189 | E11: -28.945153 | F11: 9719056 | G11: 0 | H11: 0
A12: Caisse de sécurité sociale | B12: 0 | C12: 0 | D12: 0 | E12: 0 | F12: 0 | G12: 0 | H12: 0
A13: Caisse de retraite | B13: 26513029 | C13: 15890659 | D13: 10622370 | E13: 66.84663 | F13: 26513029 | G13: 0 | H13: 0
A14: Autres organismes sociaux | B14: 114929325 | C14: 51735900 | D14: 63193425 | E14: 122.14618 | F14: 114929325 | G14: 0 | H14: 0
A15: TOTAL DETTES SOCIALES | B15: 154365535 | C15: 86020029 | D15: 68345506 | E15: 79.453014 | F15: 154365535
B16: 0 | C16: 0 | D16: 0 | F16: 0 | G16: 0 | H16: 0
A17: Etat, impôts sur les bénéfices | B17: 689324700 | C17: 822376950 | D17: -133052250 | E17: -16.178986 | F17: 689324700 | G17: 0 | H17: 0
A18: Etat, impôts et taxes | B18: 28828777 | C18: 29526094 | D18: -697317 | E18: -2.3616974 | F18: 28828777 | G18: 0 | H18: 0
A19: Etat, TVA | B19: 32542243 | C19: 37934283 | D19: -5392040 | E19: -14.214161 | F19: 32542243 | G19: 0 | H19: 0
A20: Etat, impôts retenus à la source | B20: 35352296 | C20: 25686930 | D20: 9665366 | E20: 37.627564 | F20: 35352296 | G20: 0 | H20: 0
A21: Autres dettes Etat | B21: 29073647 | C21: 29148647 | D21: -75000 | E21: -0.25730182 | F21: 29073647 | G21: 0 | H21: 0
A22: TOTAL DETTES FISACLE | B22: 815121663 | C22: 944672904 | D22: -129551241 | E22: -13.713873 | F22: 815121663 | G22: 0 | H22: 0
D23: 0
A24: TOTAL DETTES SOCIALES ET FISCACLE | B24: 969487198 | C24: 1030692933 | D24: -61205735 | E24: -5.9383094 | F24: 969487198 | G24: 0 | H24: 0
A26: Commentaire :

Sheet Note 19
A1: NOTE 19 : AUTRES DETTES ET PROVISIONS POUR RISQUES A COURT TERME
A3: Désignation entité : | F3: Excercice clos le : | G3: =+'Fiche de renseignement R1'!$V$10 -> 45657
A4: ='Fiche de renseignement R1'!$J$4 -> SOCIETE NOUVELLE DES SALINS DU SINE SALOUM | F4: Durée en mois : | G4: =+'Fiche de renseignement R1'!$AH$10 -> 12
A5: Numéro d'identification : | B5: =+'Fiche de renseignement R1'!$J$10 -> 000018699
A7: LIBELLES | B7: ANNEE N | C7: ANNEE N-1 | D7: VARIATION EN VALEUR ABSOLUE | E7: Variation en % | F7: Dettes à un an au plus | G7: Dettes à plus d'un an et à deux ans au plus | H7: Dettes à plus de deux ans
A9: Organismes internationaux | B9: 0 | C9: 0 | D9: 0 | F9: 0 | G9: 0
H10: 0
A11: Apporteurs, opérations sur le capital | B11: 0 | C11: 0 | D11: 0 | F11: 0 | G11: 0 | H11: 0
A12: Associés, compte courant | B12: 0 | C12: 0 | D12: 0 | F12: 0 | G12: 0 | H12: 0
A13: Associés, dividendes à payer | B13: 0 | C13: 0 | D13: 0 | F13: 0 | G13: 0 | H13: 0
A14: Groupe, comptes courants | B14: 3442717 | C14: 3664176 | D14: -221459 | E14: -0.060438964 | F14: 3442717 | G14: 0 | H14: 0
A15: Autres dettes associés | B15: 0 | C15: 0 | D15: 0 | F15: 0 | G15: 0 | H15: 0
A16: TOTAL DETTES ASSOCIES | B16: 3442717 | C16: 3664176 | D16: -221459 | E16: -0.060438964 | F16: 3442717 | G16: 0 | H16: 0
H17: 0
A18: Créditeurs divers | B18: 5672505 | C18: 6362872 | D18: -690367 | E18: -0.10849928 | F18: 5672505 | G18: 0 | H18: 0
A19: Obligataires | B19: 0 | C19: 0 | D19: 0 | F19: 0 | G19: 0 | H19: 0
A20: Rémunérations d'administrateurs | B20: 0 | C20: 0 | D20: 0 | F20: 0 | G20: 0 | H20: 0
A21: Compte du factor | B21: 0 | C21: 0 | D21: 0 | F21: 0 | G21: 0 | H21: 0
A22: Versements restant à effectuer sur titres de placements non libérés | B22: 0 | C22: 0 | D22: 0 | F22: 0 | G22: 0 | H22: 0
A23: Compte transitoire ajustement spécial lié à la révision du SYSCOHADA | B23: 0 | C23: 0 | D23: 0 | F23: 0 | G23: 0 | H23: 0
A24: Autres créditeur divers | B24: 0 | C24: 0 | D24: 0 | F24: 0 | G24: 0 | H24: 0
A25: TOTAL CREDITEURS DIVERS | B25: 5672505 | C25: 6362872 | D25: -690367 | E25: -0.10849928 | F25: 5672505 | G25: 0 | H25: 0
H26: 0
A27: Comptes permanents non bloqués des établissements et des succursales | B27: 0 | C27: 0 | D27: 0 | F27: 0 | G27: 0 | H27: 0
A28: Comptes de liaison charges et produits | B28: 0 | C28: 0 | D28: 0 | F28: 0 | G28: 0 | H28: 0
A29: Comptes de liaison des sociétés en participation | B29: 0 | C29: 0 | D29: 0 | F29: 0 | G29: 0 | H29: 0
A30: TOTAL COMPTES DE LIAISON | B30: 0 | C30: 0 | D30: 0 | F30: 0 | G30: 0 | H30: 0
H31: 0
A32: TOTAL AUTRES DETTES | B32: 9115222 | C32: 10027048 | D32: -911826 | E32: -0.090936635 | F32: 9115222 | G32: 0 | H32: 0
H33: 0
A34: Provisions pour risques à court terme (voir note 28) | B34: 0 | C34: 0 | D34: 0 | F34: 0 | G34: 0 | H34: 0

Sheet Note 20
A1: NOTE 20 : BANQUES, CREDIT D'ESCOMPTE ET TRESORERIE
A3: Désignation entité : | C3: Excercice clos le : | D3: =+'Fiche de renseignement R1'!$V$10 -> 45657
A4: ='Fiche de renseignement R1'!$J$4 -> SOCIETE NOUVELLE DES SALINS DU SINE SALOUM | C4: Durée en mois : | D4: =+'Fiche de renseignement R1'!$AH$10 -> 12
A5: Numéro d'identification : | B5: =+'Fiche de renseignement R1'!$J$10 -> 000018699
A7: LIBELLES | B7: ANNEE N | C7: ANNEE N-1 | D7: VARIATION EN %
A9: Escomptes de crédit de campagne | B9: 0 | C9: 0
A10: Escomptes de crédit ordinaires | B10: 0 | C10: 0
A11: TOTAL : BANQUES, CREDITS D'ESCOMPTE ET DE TRESORERIE | B11: 0 | C11: 0
A13: Banques locales | B13: 0 | C13: 0
A14: Banques autres états région | B14: 0 | C14: 0
A15: Autres Banques | B15: 0 | C15: 0
A16: Banques intérêts courus | B16: 0 | C16: 0
A17: Crédit de trésorerie | B17: 0 | C17: 0
A18: TOTAL BANQUES, CREDITS DE TRESORERIE | B18: 0 | C18: 0
A19: TOTAL GENERAL
A20: TOTAL GENERAL | B20: 0 | C20: 0 | D20: 0
A22: Commentaire :
A23: NEANT
A26: NB : Banques et intérêts courus figure dans cette rubrique en négatif si le compte principal attaché est créditeur.

Sheet Note 21
A1: NOTE 21 : CHIFFRE D'AFFAIRES ET AUTRES PRODUITS
A3: Désignation entité : | C3: Excercice clos le : | D3: =+'Fiche de renseignement R1'!$V$10 -> 45657
A4: ='Fiche de renseignement R1'!$J$4 -> SOCIETE NOUVELLE DES SALINS DU SINE SALOUM | C4: Durée en mois : | D4: =+'Fiche de renseignement R1'!$AH$10 -> 12
A5: Numéro d'identification : | B5: =+'Fiche de renseignement R1'!$J$10 -> 000018699
A7: LIBELLES | B7: ANNEE N | C7: ANNEE N-1 | D7: VARIATION EN %
A9: Ventes dans la région | B9: 0 | C9: 0
A10: Ventes hors région | B10: 0 | C10: 0
A11: Ventes Groupe | B11: 0 | C11: 0
A12: Ventes sur internet | B12: 0 | C12: 0
A13: TOTAL VENTES MARCHANDISES | B13: 0 | C13: 0
A15: Ventes dans la région | B15: 14785568312 | C15: 17228828664 | D15: -0.14181233
A16: Ventes hors région | B16: 312633796 | C16: 519596804 | D16: -0.39831463
A17: Ventes Groupe | B17: 0 | C17: 0
A18: Ventes sur internet | B18: 0 | C18: 0
A19: TOTAL VENTES PRODUITS FABRIQUES | B19: 15098202108 | C19: 17748425468 | D19: -0.1493216
A21: Ventes dans la région | B21: 0 | C21: 0
A22: Ventes hors région | B22: 0 | C22: 0
A23: Ventes Groupe | B23: 0 | C23: 0
A24: Ventes sur internet | B24: 0 | C24: 0
A25: TOTAL VENTES DE TRAVAUX ET SERVICES VENDUS | B25: 0 | C25: 0
A27: Produits accessoires | B27: 20686680 | C27: 12712 | D27: 824.99119
A30: TOTAL CHIFFRE D'AFFAIRES | B30: 15118888788 | C30: 17748438180 | D30: -0.14873061
A32: Production immobilisée | B32: 63508535 | C32: 31315159 | D32: 1.0280445
A33: Subventions d'exploitation | C33: 0
A34: Autres produits | B34: 1000949 | C34: 531038 | D34: 0.88489148
A35: TOTAL AUTRES PRODUITS | B35: 64509484 | C35: 31846197 | D35: 1.0256574
A37: TOTAL | B37: 15183398272 | C37: 17780284377 | D37: -0.14662717
A39: Commentaire :
A40: Le chiffre d'affaire a connu une diminution en raison de la baisse du volume de vente de -15,20%.

Sheet Note 22
A1: NOTE 22 : ACHATS
A3: Désignation entité : | C3: Excercice clos le : | D3: =+'Fiche de renseignement R1'!$V$10 -> 45657
A4: ='Fiche de renseignement R1'!$J$4 -> SOCIETE NOUVELLE DES SALINS DU SINE SALOUM | C4: Durée en mois : | D4: =+'Fiche de renseignement R1'!$AH$10 -> 12
A5: Numéro d'identification : | B5: =+'Fiche de renseignement R1'!$J$10 -> 000018699
A7: LIBELLES | B7: ANNEE N | C7: ANNEE N-1 | D7: VARIATION EN %
A9: Achats dans la région | B9: 0 | C9: 0
A10: Achats hors région | B10: 0 | C10: 0
A11: Achats Groupe | B11: 0 | C11: 0
A12: TOTAL ACHATS DE MARCHANDISES | B12: 0 | C12: 0
A14: Achats dans la région | B14: 0 | C14: 0
A15: Ventes hors région | B15: 0 | C15: 0
A16: Achats Groupe | B16: 0 | C16: 0
A17: TOTAL ACHATS MATIERES PREMIERES ET FOURNITURES LEES | B17: 0 | C17: 0
A19: Matières consommables | B19: 0 | C19: 0
A20: Matières combustibles | B20: 367022548 | C20: 400782151 | D20: -0.084234298
A21: Produits d'entretien | B21: 0 | C21: 0 | D21: -
A22: Fournitures d'atelier, d'usine et de magasin | B22: 1493016390 | C22: 1804357199 | D22: -0.17254943
A23: Eau | B23: 3941109 | C23: 3311235 | D23: 0.19022329
A24: Electricité | B24: 350374400 | C24: 356508080 | D24: -0.017204884
A25: Autres énergies | B25: 16761753 | C25: 15405530 | D25: 0.088034816
A26: Fournitures d'entretien | B26: 190659145 | C26: 183295862 | D26: 0.040171572
A27: Fourniture de bureau | B27: 14771966 | C27: 11843473 | D27: 0.24726641
A28: Petit matériel et outillages | B28: 7783884 | C28: 6392674 | D28: 0.21762568
A29: Achats d'études, prestations de services, de travaux matériel et équipements | B29: 656 | C29: 0 | D29: -
A30: Achats d'emballages | B30: 1088037783 | C30: 1392492281 | D30: -0.21863999
A31: Frais sur achats | B31: 53524821 | C31: 62626795 | D31: -0.14533674
A32: Remise, rabais, remises et ristournes | B32: 0 | C32: 0 | D32: -
A33: TOTAL AUTRES ACHATS | B33: 3585894455 | C33: 4237015280 | D33: -0.15367441
A35: Commentaire :
A36: la diminution du volume de vente a aussi entrainé la diminution de la production d'où cette baisse constatée sur les achats

Sheet Note 23
A1: NOTE 23 : TRANSPORTS
A3: Désignation entité : | C3: Excercice clos le : | D3: =+'Fiche de renseignement R1'!$V$10 -> 45657
A4: ='Fiche de renseignement R1'!$J$4 -> SOCIETE NOUVELLE DES SALINS DU SINE SALOUM | C4: Durée en mois : | D4: =+'Fiche de renseignement R1'!$AH$10 -> 12
A5: Numéro d'identification : | B5: =+'Fiche de renseignement R1'!$J$10 -> 000018699
A7: LIBELLES | B7: ANNEE N | C7: ANNEE N-1 | D7: VARIATION EN %
A9: Transports sur ventes | B9: 3332565336 | C9: 4628126270 | D9: -0.27993206
A10: Transports pour le compte de tiers | B10: 0 | C10: 0
A11: Transport du personnel | B11: 88583687 | C11: 88841214 | D11: -0.0028987335
A12: Transport de plis | B12: 1727998 | C12: 2804078 | D12: -0.38375537
A13: Autres transports | B13: 30451552 | C13: 34205919 | D13: -0.10975782
A14: TOTAL TRANSPORTS | B14: 3453328573 | C14: 4753977481 | D14: -0.27359173
A16: Commentaire :
A17: la dimunition du transport sur vente s'explique par la baisse du volume d'activité vers la Côte d'Ivoire et le Bénin

Sheet Note 24
A1: NOTE 24 : SERVICES EXTERIEURS
A3: Désignation entité : | C3: Excercice clos le : | D3: =+'Fiche de renseignement R1'!$V$10 -> 45657
A4: ='Fiche de renseignement R1'!$J$4 -> SOCIETE NOUVELLE DES SALINS DU SINE SALOUM | C4: Durée en mois : | D4: =+'Fiche de renseignement R1'!$AH$10 -> 12
A5: Numéro d'identification : | B5: =+'Fiche de renseignement R1'!$J$10 -> 000018699
A7: LIBELLES | B7: ANNEE N | C7: ANNEE N-1 | D7: VARIATION EN %
A9: Sous-traitance générale | B9: 36364510 | C9: 34518313 | D9: 0.053484566
A10: Locations et charges locatives | B10: 76624158 | C10: 45097930 | D10: 0.69906153
A11: Redevances de location acquisition | B11: 0 | C11: 0
A12: Entretien, réparations et maintenance | B12: 248218828 | C12: 240178168 | D12: 0.033477897
A13: Primes d'assurance | B13: 39706211 | C13: 32510448 | D13: 0.22133694
A14: Etudes, recherches et documentation | B14: 0 | C14: 72000 | D14: -1
A15: Publicité, publications, relations publiques | B15: 5006320 | C15: 9123870 | D15: -0.45129424
A16: Frais de télécommunications | B16: 12049400 | C16: 8447764 | D16: 0.42634193
A17: Frais bancaires | B17: 147122975 | C17: 200981755 | D17: -0.26797845
A18: Rémunérations d'intermédiaires et de conseils | B18: 221268390 | C18: 208294284 | D18: 0.062287384
A19: Frais de formation du personnel | B19: 8576300 | C19: 14346500 | D19: -0.40220263
A20: Redevances pour brevets, licences, logiciels, concession et droits similaires | B20: 3486238 | C20: 3535435 | D20: -0.013915402
A21: Cotisations | B21: 6600000 | C21: 6000000 | D21: 0.1
A22: Autres charges externes | B22: 26332811 | C22: 15103443 | D22: 0.74349723
D23: 0
A24: TOTAL SERVICES EXTERIEURS | B24: 831356141 | C24: 818209910 | D24: 0.016067064
A26: Commentaire :

Sheet Note 25
A1: NOTE 25 : IMPOTS ET TAXES
A3: Désignation entité : | C3: Excercice clos le : | D3: =+'Fiche de renseignement R1'!$V$10 -> 45657
A4: ='Fiche de renseignement R1'!$J$4 -> SOCIETE NOUVELLE DES SALINS DU SINE SALOUM | C4: Durée en mois : | D4: =+'Fiche de renseignement R1'!$AH$10 -> 12
A5: Numéro d'identification : | B5: =+'Fiche de renseignement R1'!$J$10 -> 000018699
A7: LIBELLES | B7: ANNEE N | C7: ANNEE N-1 | D7: VARIATION EN %
A9: Impôts et taxes directs | B9: 12585643 | C9: 24253811 | D9: -0.48108596
A10: Impôts et taxes indirects | B10: 0 | C10: 0
A11: Droits d'enregistrement | B11: 0 | C11: 0
A12: Pénalités et amendes fiscales | B12: 0 | C12: 100000000 | D12: -100 %
A13: Autres impôts et taxes | B13: 36784 | C13: 2169887 | D13: -0.98304797
A15: TOTAL IMPOTS ET TAXES | B15: 12622427 | C15: 126423698 | D15: -0.90015775
A17: Commentaire :

Sheet Note 26
A1: NOTE 26 : AUTRES CHARGES
A3: Désignation entité : | C3: Excercice clos le : | D3: =+'Fiche de renseignement R1'!$V$10 -> 45657
A4: ='Fiche de renseignement R1'!$J$4 -> SOCIETE NOUVELLE DES SALINS DU SINE SALOUM | C4: Durée en mois : | D4: =+'Fiche de renseignement R1'!$AH$10 -> 12
A5: Numéro d'identification : | B5: =+'Fiche de renseignement R1'!$J$10 -> 000018699
A7: LIBELLES | B7: ANNEE N | C7: ANNEE N-1 | D7: VARIATION EN %
A9: Pertes sur créances clients | B9: 0 | C9: 0
A10: Pertes sur autres débiteurs | B10: 0 | C10: 0
A11: Quote-part de résultat sur opérations faites en commun | B11: 0 | C11: 0
A12: Valeur nette comptable des cessions courantes d'immobilisations | B12: 0 | C12: 0
A13: Indemnités de fonction et autres rémunérations d'administrateurs | B13: 44260341 | C13: 44260341 | D13: 0
A14: Dons et mécénat | B14: 64932726 | C14: 62348600 | D14: 0.041446416
A15: Autres charges diverses | B15: 3633045 | C15: 887463 | D15: 3.0937425
A16: Charges pour provisions et provisons pour risques à court terme d'exploitation (voir note 28) | B16: 93390313 | C16: 35177
A18: TOTAL AUTRES CHARGES | B18: 206216425 | C18: 107531581 | D18: 0.91772894
A20: Commentaire :

Sheet Note 27A
A1: NOTE 27A : CHARGES DE PERSONNEL
A3: Désignation entité : | C3: Excercice clos le : | D3: =+'Fiche de renseignement R1'!$V$10 -> 45657
A4: ='Fiche de renseignement R1'!$J$4 -> SOCIETE NOUVELLE DES SALINS DU SINE SALOUM | C4: Durée en mois : | D4: =+'Fiche de renseignement R1'!$AH$10 -> 12
A5: Numéro d'identification : | B5: =+'Fiche de renseignement R1'!$J$10 -> 000018699
A7: LIBELLES | B7: ANNEE N | C7: ANNEE N-1 | D7: VARIATION EN %
A9: Rémunérations directes versées au personnel | B9: 1699274204 | C9: 1601438728 | D9: 0.061092238
A10: Indemnités forfaitaires versées au personnel | B10: 24315693 | C10: 17262966 | D10: 0.40854665
A11: Charges sociales | B11: 266099734 | C11: 243258769 | D11: 0.093895752
A12: Rémunérations et charges sociales de l'exploitant individuel | B12: 0 | C12: 0
A13: Rémunération transférée de personnel extérieur | B13: 204020450 | C13: 235485402 | D13: -0.13361742
A14: Autres charges sociales | B14: 120043591 | C14: 117912203 | D14: 0.01807606
A16: TOTAL CHARGES DE PERSONNEL | B16: 2313753672 | C16: 2215358068 | D16: 0.044415215
A18: Commentaire :

Sheet Note 27B
B1: NOTE 27B : EFFECTIFS, MASSE SALARIALE ET PERSONNEL EXTERIEUR
B3: Désignation entité : | K3: Excercice clos le : | N3: =+'Fiche de renseignement R1'!$V$10 -> 45657
B4: ='Fiche de renseignement R1'!$J$4 -> SOCIETE NOUVELLE DES SALINS DU SINE SALOUM
B5: Numéro d'identification : | C5: =+'Fiche de renseignement R1'!$J$10 -> 000018699 | K5: Durée en mois : | M5: =+'Fiche de renseignement R1'!$AH$10 -> 12
B7: EFFECTIF ET MASSE SALARIALE | C7: EFFECTIFS | J7: MASSE SALARIALE
C8: NATIONAUX | E8: AUTRES ETATS DE L'OHADA | G8: HORS OHADA | I8: TOTAL | J8: NATIONAUX | L8: AUTRES ETATS DE L'OHADA | N8: HORS OHADA | P8: TOTAL
C9: M | D9: F | E9: M | F9: F | G9: M | H9: F | J9: M | K9: F | L9: M | M9: F | N9: M | O9: F
A10: YA | B10: 1 - Cadres supérieurs | C10: 5 | F10: 1 | G10: 3 | I10: 9 | J10: 180 | K10: 17 | L10: 0 | M10: 76 | N10: 455 | P10: 728
A11: YB | B11: 2 - Techniciens supérieurs et cadres moyens | I11: 0 | P11: 0
A12: YC | B12: 3 - Techniciens, agents de maîtrise et ouvriers qualifiés | C12: 11 | D12: 3 | E12: 1 | I12: 15 | J12: 124 | K12: 23 | L12: 7 | P12: 154
A13: YD | B13: 4 - Employés, manœuvres, ouvriers et apprentis | C13: 120 | D13: 6 | I13: 126 | J13: 568 | K13: 24 | P13: 592
A14: YE | B14: TOTAL (1) | C14: 136 | D14: 9 | E14: 1 | F14: 1 | G14: 3 | H14: 0 | I14: 150 | J14: 872 | K14: 64 | L14: 7 | M14: 76 | N14: 455 | O14: 0 | P14: 1474
L15: 0 | M15: 0 | N15: 0 | O15: 0 | P15: 0
A16: YF | B16: Permanents | C16: 136 | D16: 9 | E16: 1 | F16: 1 | G16: 3 | H16: 0 | I16: 150 | J16: 872 | K16: 64 | L16: 7 | M16: 76 | N16: 455 | O16: 0 | P16: 1474
A17: YG | B17: Saisonniers | C17: 197 | I17: 197 | J17: 254 | P17: 254
B20: 2. Personnel extérieur | J20: FACTURATION A L'ENTITE
A21: YH | B21: 1 - Cadres supérieurs | C21: 0 | D21: 0 | E21: 0 | F21: 0 | G21: 0 | H21: 0 | I21: 0 | J21: 0 | K21: 0
A22: YI | B22: 2 - Techniciens supérieurs et cadres moyens | C22: 0 | D22: 0 | E22: 0 | F22: 0 | G22: 0 | H22: 0 | I22: 0 | J22: 0 | K22: 0
A23: YJ | B23: 3 - Techniciens, agents de maîtrise et ouvriers qualifiés | C23: 0 | D23: 0 | E23: 0 | F23: 0 | G23: 0 | H23: 0 | I23: 0 | J23: 0 | K23: 0
A24: YK | B24: 4 - Employés, manœuvres, ouvriers et apprentis | C24: 149 | I24: 149 | J24: 204 | K24: 0
A25: YL | B25: TOTAL (2) | C25: 149 | I25: 149 | J25: 204 | K25: 0
A27: YM | B27: Permanents | C27: 0 | D27: 0 | E27: 0 | F27: 0 | G27: 0 | H27: 0 | I27: 0 | J27: 0 | K27: 0
A28: YN | B28: Saisonniers | C28: 0 | D28: 0 | E28: 0 | F28: 0 | G28: 0 | H28: 0 | I28: 0 | J28: 0 | K28: 0
A30: YO | B30: TOTAL (1 + 2) | C30: 285 | D30: 9 | E30: 1 | F30: 1 | G30: 3 | H30: 0 | I30: 299 | J30: 204 | K30: 0
B32: Commentaire :

Sheet Note 28
A1: NOTE 28 : PROVISIONS ET DEPRECIATIONS INSCRITES AU BILAN
A3: Désignation entité : | G3: Excercice clos le : | H3: =+'Fiche de renseignement R1'!$V$10 -> 45657
A4: ='Fiche de renseignement R1'!$J$4 -> SOCIETE NOUVELLE DES SALINS DU SINE SALOUM | G4: Durée en mois : | H4: =+'Fiche de renseignement R1'!$AH$10 -> 12
A5: Numéro d'identification : | B5: =+'Fiche de renseignement R1'!$J$10 -> 000018699
A7: SITUATIONS ET MOUVEMENTS | B7: A | C7: B | F7: C | I7: D = A + B - C
B8: PROVISIONS A L'OUVERTURE DE L'EXERCICE | C8: AUGMENTATIONS : DOTATIONS | F8: DIMINUTIONS : REPRISES | I8: PROVISIONS A LA CLOTURE DE L'EXERCICE
A9: NATURE | C9: D'EXPLOITATION | D9: FINANCIERES | E9: HORS ACTIVITES ORDINAIRES | F9: D'EXPLOITATION | G9: FINANCIERES | H9: HORS ACTIVITES ORDINAIRES
A10: 1. Provisions réglementées | B10: 0 | C10: 0 | D10: 0 | E10: 0 | F10: 0 | G10: 0 | H10: 0 | I10: 0
A11: 2. Provisions financières pour risques et charges | B11: 1677152885 | C11: 1716510 | D11: 0 | E11: 0 | F11: 0 | G11: 0 | H11: 0 | I11: 1678869395
A12: 3. Dépréciations des immobilisations | B12: 58232009 | C12: 0 | D12: 0 | E12: 0 | F12: 0 | G12: 0 | H12: 0 | I12: 58232009
A13: TOTAL DOTATIONS | B13: 1735384894 | C13: 1716510 | D13: 0 | E13: 0 | F13: 0 | G13: 0 | H13: 0 | I13: 1737101404
A15: 4. Dépréciations des stocks | B15: 99849200 | C15: 93390313 | F15: 0 | I15: 193239513
A16: 5. Dépréciations actif circulant HAO | B16: 0 | C16: 0 | D16: 0 | E16: 0 | F16: 0 | G16: 0 | H16: 0 | I16: 0
A17: 6. Dépréciations fournisseurs | B17: 0 | C17: 0 | D17: 0 | E17: 0 | F17: 0 | G17: 0 | H17: 0 | I17: 0
A18: 7. Dépréciations clients | B18: 0 | C18: 0 | D18: 0 | E18: 0 | F18: 0 | G18: 0 | H18: 0 | I18: 0
A19: 8. Dépréciations autres créances | B19: 0 | C19: 0 | D19: 0 | E19: 0 | F19: 0 | G19: 0 | H19: 0 | I19: 0
A20: 9. Dépréciations titres de placement | B20: 0 | C20: 0 | D20: 0 | E20: 0 | F20: 0 | G20: 0 | H20: 0 | I20: 0
A21: 10. Dépréciations valeurs à encaisser | B21: 0 | C21: 0 | D21: 0 | E21: 0 | F21: 0 | G21: 0 | H21: 0 | I21: 0
A22: 11. Dépréciations disponibilité | B22: 7829322 | C22: 0 | F22: 0 | I22: 7829322
A23: 12. Dépréciations et provisions pour risques à court termes exploitation | B23: 0 | C23: 0 | D23: 0 | E23: 0 | F23: 0 | G23: 0 | H23: 0 | I23: 69793419
A24: 13. Dépréciations et provisions pour risques à court termes à caractére financier | B24: 0 | C24: 0 | D24: 0 | E24: 0 | F24: 0 | G24: 0 | H24: 0 | I24: 7829322
A25: TOTAL: CHARGE POUR DEPRECIATIONS ET PROVISIONS A COURT TERME | B25: 107678522 | C25: 93390313 | D25: 0 | E25: 0 | F25: 0 | G25: 0 | H25: 0 | I25: 201068835
A27: TOTAL PROVISIONS ET DEPRECIATIONS | B27: 1843063416 | C27: 95106823 | D27: 0 | E27: 0 | F27: 0 | G27: 0 | H27: 0 | I27: 1938170239
A29: Commentaire :

Sheet Note 29
A1: NOTE 29 : CHARGES ET REVENUS FINANCIERS
A3: Désignation entité : | C3: Excercice clos le : | D3: =+'Fiche de renseignement R1'!$V$10 -> 45657
A4: ='Fiche de renseignement R1'!$J$4 -> SOCIETE NOUVELLE DES SALINS DU SINE SALOUM | C4: Durée en mois : | D4: =+'Fiche de renseignement R1'!$AH$10 -> 12
A5: Numéro d'identification : | B5: =+'Fiche de renseignement R1'!$J$10 -> 000018699
A7: LIBELLES | B7: ANNEE N | C7: ANNEE N-1 | D7: VARIATION EN %
A9: Intérêts des emprunts | B9: 0 | C9: 0
A10: Intérêts dans loyers de location acquisition | B10: 0 | C10: 0
A11: Escomptes accordés | B11: 0 | C11: 0
A12: Autres intérêts | B12: 0 | C12: 0
A13: Escomptes des effets de commerce | B13: 0 | C13: 0
A14: Pertes de change | B14: 0 | C14: 8096 | D14: -100 %
A15: Pertes sur cessions de titres de placement | B15: 0 | C15: 0
A16: Malis provenant d'attribution gratuite d'actions au personnel salarié et aux dirigeants | B16: 0 | C16: 0
A17: Pertes sur risques financiers | B17: 0 | C17: 0
A18: Charges pour dépréciations et provisons à court terme à caractère financier (voir note 28) | B18: 0 | C18: 0
A19: SOUS TOTAL FRAIS FINANCIERS | B19: 0 | C19: 0
A21: Intérêts de prêts et créances diverses | B21: 6528111 | C21: 12269602 | D21: -0.46794436
A22: Revenus de participations | B22: 0 | C22: 0
A23: Escomptes obtenus | B23: 0 | C23: 0
A24: Revenus de placement | B24: 17352679 | C24: 0
A25: Intérêts dans loyers de location-financement | B25: 0 | C25: 0
A26: Gains de change | B26: 0 | C26: 183323 | D26: -1
A27: Gains sur cessions de titres de placement | B27: 0 | C27: 0
A28: Gains sur risques financiers | B28: 0 | C28: 0
A29: Reprises de charges pour dépréciation et provisions à court terme à caractère financier (voir note 28) | B29: 0 | C29: 0
A30: SOUS TOTAL REVENUS FINANCIERS | B30: 23880790 | C30: 12452925 | D30: 0.9176852
A32: TOTAL | B32: 23880790 | C32: 12444829 | D32: 0.91893276
A34: Commentaire :

Sheet Note 30
A1: NOTE 30 : AUTRES CHARGES ET PRODUITS HAO
A3: Désignation entité : | C3: Excercice clos le : | D3: =+'Fiche de renseignement R1'!$V$10 -> 45657
A4: ='Fiche de renseignement R1'!$J$4 -> SOCIETE NOUVELLE DES SALINS DU SINE SALOUM | C4: Durée en mois : | D4: =+'Fiche de renseignement R1'!$AH$10 -> 12
A5: Numéro d'identification : | B5: =+'Fiche de renseignement R1'!$J$10 -> 000018699
A7: LIBELLES | B7: ANNEE N | C7: ANNEE N-1 | D7: VARIATION EN %
A9: Charges HAO constatées (1) à détailler | B9: 0 | C9: 530648278
A10: (1) ........................................................... | B10: 0 | C10: 0
A11: (1) ........................................................... | B11: 0 | C11: 0
A12: Pertes sur créances HAO | B12: 0 | C12: 0
A13: Dons et libéralités accordés | B13: 0 | C13: 0
A14: Abandons de créances consentis | B14: 0 | C14: 0
A15: Charges provisionnées HAO | B15: 0 | C15: 0
A16: Dotation hors activités ordinaires | B16: 0 | C16: 0
A17: Participation des travailleurs | B17: 0 | C17: 0
A18: SOUS TOTAL: AUTRES CHARGES HAO | B18: 0 | C18: 530648278
A19: Produits HAO constatés (1) à détailler | B19: 0 | C19: 0
A20: (1) ........................................................... | B20: 0 | C20: 0
... A30: TOTAL | B30: 0 | C30: 530648278
A32: Commentaire :

Sheet Note 31
A1: NOTE 31 : REPARTITION DU RESULTAT ET AUTRES ELEMENTS CARACTERISTIQUES DES CINQ DERNIERS EXERCICES
A3: Désignation entité : | D3: Excercice clos le : | E3: =+'Fiche de renseignement R1'!$V$10 -> 45657
A4: ='Fiche de renseignement R1'!$J$4 -> SOCIETE NOUVELLE DES SALINS DU SINE SALOUM | D4: Durée en mois : | E4: =+'Fiche de renseignement R1'!$AH$10 -> 12
A5: Numéro d'identification : | B5: =+'Fiche de renseignement R1'!$J$10 -> 000018699
A7: EXERCICES CONCERNES (1) | B7: N | C7: N - 1 | D7: N - 2 | E7: N - 3 | F7: N - 4
A9: STRUCTURE DU CAPITAL A LA CLOTURE DE L'EXERCICE (2)
A10: Capital social | B10: 554420000 | C10: 554420000 | D10: 554420000 | E10: 554420000 | F10: 554420000
A11: Actions ordinaires | B11: 55442 | C11: 55442 | D11: 55442 | E11: 55442 | F11: 55442
A12: Actions à dividendes prioritaires (ADP) sans droit de vote | B12: 0 | C12: 0 | D12: 0 | E12: 0 | F12: 0
A13: Actions nouvelles à émettre : | B13: 0 | C13: 0 | D13: 0 | E13: 0 | F13: 0
A14: -par conversion d'obligations | B14: 0 | C14: 0 | D14: 0 | E14: 0 | F14: 0
A15: -par exercice de droits de souscription | B15: 0 | C15: 0 | D15: 0 | E15: 0 | F15: 0
A16: OPERATIONS ET RESULTATS DE L'EXERCICE (3)
A17: Chiffre d'affaires hors taxes | B17: 15118888788 | C17: 17748438180 | D17: 17756037547 | E17: 15125278265 | F17: 14194822618
A18: Résultat des activités ordinaires (RAO) hors dotations et reprises (exploitation et financières) | B18: 5160891573 | C18: 6018835347 | D18: 5695910923 | E18: 5162555732 | F18: 4312470038
A19: Participation des travailleurs aux bénéfices | B19: 0 | C19: 0 | E19: 0 | F19: 0
A20: Impôt sur le résultat | B20: 689324700 | C20: 822376950 | D20: 770337900 | E20: 702253950 | F20: 245703150
A21: Résultat net (4) | B21: 3693778426 | C21: 4369124484 | D21: 4495076397 | E21: 3851027626 | F21: 1153625579
A22: RESULTAT ET DIVIDENDE DISTRIBUES
A23: Résultat distribué (5) | B23: 3603730000 | C23: 3603730000 | D23: 3853219000 | E23: 1153193600 | F23: 2217680000
A24: Dividende attribué à chaque action | B24: 65000 | C24: 65000 | D24: 69500 | E24: 20800 | F24: 40000
A25: PERSONNEL ET POLITIQUES SALARIALE
A26: Effectif moyen des travailleurs au cours de l'exercice (6) | B26: 150 | C26: 152 | D26: 153 | E26: 135 | F26: 135
A27: Effectif moyen de personnel extérieur | B27: 149 | C27: 183 | D27: 183 | E27: 181 | F27: 189
A28: Masse salariale distribuée au cours de l'exercice (7) | B28: 1723589897 | C28: 1618701694 | D28: 1841506997 | E28: 1683783511 | F28: 1535940590
A29: Avantages sociaux versés au cours de l'exercice (8) {Sécurité sociale, œuvres sociales} | B29: 386143325 | C29: 361170972 | D29: 378107696 | E29: 384674881 | F29: 379350764
A30: Personnel extérieur facturé à l'entreprise (9) | B30: 204020450 | C30: 235485402 | D30: 227403029 | E30: 216225207 | F30: 227444659
A32: (1) Y compris l'exercice dont les états financiers sont soumis à l'approbation de l'Assemblée | C32: (6) Personnel propre
A33: (2) Indication, en cas de libération partielle du capital, du montant du capital non appelé | C33: (7) Total des comptes 661, 662, 663
A34: (3) Les éléments de cette rubrique sont ceux figurant au compte de résultat | C34: (8) Total des comptes 664, 668
A35: (4) Le résultat, lorsqu'il est négatif, doit être mis entre parenthèses | C35: (9) Compte 667.
A36: (5) L'exercice N correspond au dividende proposé du dernier exercice

Sheet Note 32
A1: NOTE 32 : PRODUCTION DE L'EXERCICE
A3: Désignation entité : | K3: Excercice clos le : | L3: =+'Fiche de renseignement R1'!$V$10 -> 45657
A4: ='Fiche de renseignement R1'!$J$4 -> SOCIETE NOUVELLE DES SALINS DU SINE SALOUM | K4: Durée en mois : | L4: =+'Fiche de renseignement R1'!$AH$10 -> 12
A5: Numéro d'identification : | B5: =+'Fiche de renseignement R1'!$J$10 -> 000018699
A7: DESIGNATION DU PRODUIT | B7: UNITE DE QUANTITE CHOISIE | C7: PRODUCTION VENDUE DANS LE PAYS | E7: PRODUCTION VENDUE DANS LES AUTRES PAYS DE L'OHADA | G7: PRODUCTION VENDUE HORS L'OHADA | I7: PRODUCTION IMMOBILISEE | K7: STOCK OUVERTURE DE L'EXERCICE | M7: STOCK CLOTURE DE L'EXERCICE
C8: Quantité | D8: Valeur | E8: Quantité | F8: Valeur | G8: Quantité | H8: Valeur | I8: Quantité | J8: Valeur | K8: Quantité | L8: Valeur | M8: Quantité | N8: Valeur
A9: Sel ensaché et en camelle | B9: Tonnes | C9: 52917 | D9: 2985215 | E9: =17780+37558+60200+78388 -> 193926 | F9: 11800353 | G9: 4450 | H9: 312634 | K9: 197342 | L9: 1390087 | M9: 234554.75 | N9: 1633464
A10: Production d'immobilisation | B10: 0 | C10: 0 | D10: 0 | E10: 0 | F10: 0 | G10: 0 | H10: 0 | I10: 0 | J10: 63509 | K10: 0 | L10: 0 | M10: 0 | N10: 0
A11: Fabrication en cours de sel | B11: Tonnes | C11: 0 | D11: 0 | E11: 0 | F11: 0 | G11: 0 | H11: 0 | I11: 0 | J11: 0 | K11: 0 | L11: 689421 | M11: 0 | N11: 683130
B12: 0 | C12: 0 | D12: 0 | E12: 0 | F12: 0 | G12: 0 | H12: 0 | I12: 0 | J12: 0 | K12: 0 | L12: 0 | M12: 0 | N12: 0
B13: 0 | C13: 0 | D13: 0 | E13: 0 | F13: 0 | G13: 0 | H13: 0 | I13: 0 | J13: 0 | K13: 0 | L13: 0 | M13: 0 | N13: 0
B14: 0 | C14: 0 | D14: 0 | E14: 0 | F14: 0 | G14: 0 | H14: 0 | I14: 0 | J14: 0 | K14: 0 | L14: 0 | M14: 0 | N14: 0
B15: 0 | C15: 0 | D15: 0 | E15: 0 | F15: 0 | G15: 0 | H15: 0 | I15: 0 | J15: 0 | K15: 0 | L15: 0 | M15: 0 | N15: 0
B16: 0 | C16: 0 | D16: 0 | E16: 0 | F16: 0 | G16: 0 | H16: 0 | I16: 0 | J16: 0 | K16: 0 | L16: 0 | M16: 0 | N16: 0
B17: 0 | C17: 0 | D17: 0 | E17: 0 | F17: 0 | G17: 0 | H17: 0 | I17: 0 | J17: 0 | K17: 0 | L17: 0 | M17: 0 | N17: 0
B18: 0 | C18: 0 | D18: 0 | E18: 0 | F18: 0 | G18: 0 | H18: 0 | I18: 0 | J18: 0 | K18: 0 | L18: 0 | M18: 0 | N18: 0
B19: 0 | C19: 0 | D19: 0 | E19: 0 | F19: 0 | G19: 0 | H19: 0 | I19: 0 | J19: 0 | K19: 0 | L19: 0 | M19: 0 | N19: 0
B20: 0 | C20: 0 | D20: 0 | E20: 0 | F20: 0 | G20: 0 | H20: 0 | I20: 0 | J20: 0 | K20: 0 | L20: 0 | M20: 0 | N20: 0
B21: 0 | C21: 0 | D21: 0 | E21: 0 | F21: 0 | G21: 0 | H21: 0 | I21: 0 | J21: 0 | K21: 0 | L21: 0 | M21: 0 | N21: 0
B22: 0 | C22: 0 | D22: 0 | E22: 0 | F22: 0 | G22: 0 | H22: 0 | I22: 0 | J22: 0 | K22: 0 | L22: 0 | M22: 0 | N22: 0
A23: NON VENTILE | B23: 0 | C23: 0 | D23: 0 | E23: 0 | F23: 0 | G23: 0 | H23: 0 | I23: 0 | J23: 0 | K23: 0 | L23: 0 | M23: 0 | N23: 0
A25: 0 | B25: 0 | C25: 55691 | D25: 0 | E25: 233104 | F25: 14785568 | G25: 7553 | H25: 312634 | I25: 0 | J25: 63509 | K25: 228690 | L25: 1979148 | M25: 197342 | N25: 2316594

Sheet Note 33
A1: NOTE 33 : ACHATS DESTINES A LA PRODUCTION
A3: Désignation entité : | G3: Excercice clos le : | H3: =+'Fiche de renseignement R1'!$V$10 -> 45657
A4: ='Fiche de renseignement R1'!$J$4 -> SOCIETE NOUVELLE DES SALINS DU SINE SALOUM | G4: Durée en mois : | H4: =+'Fiche de renseignement R1'!$AH$10 -> 12
A5: Numéro d'identification : | B5: =+'Fiche de renseignement R1'!$J$10 -> 000018699
A7: DESIGNATION DES MATIERES ET PRODUITS | B7: UNITE DE QUANTITE CHOISIE | C7: ACHATS EFFECTUES AU COURS DE L'EXERCICE | I7: VARIATION DES STOCKS
C8: PRODUITS DE L'ETAT | E8: PRODUITS IMPORTES
E9: ACHETES DANS L'ETAT | G9: ACHETES HORS DE L'ETAT
C10: Quantité | D10: Valeur | E10: Quantité | F10: Valeur | G10: Quantité | H10: Valeur | I10: Valeur
A11: Emballages | B11: 0 | C11: 0 | D11: 231045 | E11: 0 | F11: 15572 | G11: 0 | H11: 856930 | I11: 89696.043
A12: Produits pétroliers | B12: 0 | C12: 0 | E12: 0 | F12: 358098 | G12: 0 | I12: -27654.47
A13: Bois | B13: 0 | C13: 0 | D13: 27422 | E13: 0 | G13: 0 | I13: -2464.191
A14: Divers | B14: 0 | C14: 0 | D14: 43077 | E14: 0 | F14: 320358 | G14: 0 | H14: 1026510 | I14: 60121.269
B15: 0 | C15: 0 | D15: 0 | E15: 0 | F15: 0 | G15: 0 | H15: 0 | I15: 0
B16: 0 | C16: 0 | D16: 0 | E16: 0 | F16: 0 | G16: 0 | H16: 0 | I16: 0
B17: 0 | C17: 0 | D17: 0 | E17: 0 | F17: 0 | G17: 0 | H17: 0 | I17: 0
B18: 0 | C18: 0 | D18: 0 | E18: 0 | F18: 0 | G18: 0 | H18: 0 | I18: 0
B19: 0 | C19: 0 | D19: 0 | E19: 0 | F19: 0 | G19: 0 | H19: 0 | I19: 0
B20: 0 | C20: 0 | D20: 0 | E20: 0 | F20: 0 | G20: 0 | H20: 0 | I20: 0
B21: 0 | C21: 0 | D21: 0 | E21: 0 | F21: 0 | G21: 0 | H21: 0 | I21: 0
B22: 0 | C22: 0 | D22: 0 | E22: 0 | F22: 0 | G22: 0 | H22: 0 | I22: 0
B23: 0 | C23: 0 | D23: 0 | E23: 0 | F23: 0 | G23: 0 | H23: 0 | I23: 0
B24: 0 | C24: 0 | D24: 0 | E24: 0 | F24: 0 | G24: 0 | H24: 0 | I24: 0
A25: NON VENTILES | B25: 0 | C25: 0 | D25: 0 | E25: 0 | F25: 0 | G25: 0 | H25: 0 | I25: 0
A27: TOTAL | D27: 301544 | F27: 694028 | H27: 1883440 | I27: 119699

Sheet Note 34
A1: NOTE 34 : FICHE DE SYNTHESE DES PRINCIPAUX INDICATEURS FINANCIERS
A3: Désignation entité : | B3: Excercice clos le : | C3: =+'Fiche de renseignement R1'!$V$10 -> 45657
A4: ='Fiche de renseignement R1'!$J$4 -> SOCIETE NOUVELLE DES SALINS DU SINE SALOUM | C4: Durée en mois : | D4: =+'Fiche de renseignement R1'!$AH$10 -> 12
A5: Numéro d'identification : | B5: =+'Fiche de renseignement R1'!$J$10 -> 000018699
A7: (EN MILIERS DE FRANCS) | B7: ANNEE N | C7: ANNEE N-1 | D7: VARIATION EN %
A8: ANALYSE DE L'ACTIVITE | B8: 0 | C8: 0
A9: SOLDES INTERMEDIAIRES DE GESTION
A10: CHIFFRE D'AFFAIRES | B10: 15118889 | C10: 17748438 | D10: -0.14815666
A11: MARGE COMMERCIALE | B11: 0 | C11: 0 | D11: -
A12: VALEUR AJOUTEE | B12: 7450764.5 | C12: 8221748.6 | D12: -0.093773742
A13: EXCEDENT BRUT D'EXPLOITATION (EBE) | B13: 5137010.8 | C13: 6006390.5 | D13: -0.14474246
A14: RESULTAT D'EXPLOITATION | B14: 4357708 | C14: 5714319.3 | D14: -0.23740558
A15: RESULTAT FINANCIER | B15: 23880.79 | C15: 12444.829 | D15: 0.91893276
A16: RESULTAT DES ACTIVITES ORDINAIRES | B16: 4381588.8 | C16: 5726764.1 | D16: -0.23489275
A17: RESULTAT HORS ACTIVITES ORDINAIRES | B17: 1514.345 | C17: -535262.7 | D17: -1.0028292
A18: RESULTAT NET | B18: 3693778.4 | C18: 4369124.5 | D18: -0.1545724
A19: DETERMINATION DE LA CAPACITE D'AUTOFINANCEMENT | B19: 0 | C19: 0
A20: EBE | B20: 5137010.8 | C20: 6006390.5
A21: + Valeurs comptables des cessions courantes d'immobilisation (compte 654) | B21: 0 | C21: 0
A22: - Produits ces cessions courantes d'immobilisation (compte 754) | B22: 0 | C22: 0
A23: = CAPACITE D'AUTOFINANCEMENT D'EXPLOITATION | B23: 5137010.8 | C23: 6006390.5
A24: + Revenus financiers | B24: 23880.79 | C24: 12452.925
A25: + Gains de change | B25: 0 | C25: 0
A26: + Transferts de charges financières | B26: 0 | C26: 0
A27: + Produits HAO | B27: 0 | C27: 0
A28: +Transferts de charges HAO | B28: 0 | C28: 0
A29: - Frais financiers | B29: 0 | C29: -8.096
A30: - Pertes de change | B30: 0 | C30: 0
... A35: - Distributions de dividendes opérées durant l'exercice | B35: -3603730 | C35: -3603730
A36: = AUTOFINANCEMENT | B36: 867836.87 | C36: 1062080 | E36: 219336.87
A37: ANALYSE DE LA RENTABILITE | B37: 0 | C37: 0
B38: 0.40707021 | C38: 0.5384118 | D38: -0.32265095
B39: 0.40922928 | C39: 0.48892777 | D39: -0.19475268
A40: ANALYSE DE LA STRUCTURE FINANCIERE | B40: 0 | C40: 0
A41: Capitaux propres et ressources assimilées | B41: 9026183.2 | C41: 8936134.8 | D41: 0.010076888
A42: + Dettes financières* et autres ressources assimilées (b) | B42: 1678869.4 | C42: 1677152.9 | D42: 0.0010234666
A43: = Ressources stables | B43: 10705053 | C43: 10613288 | D43: 0.0086462309
A44: - Actif immobilisé (b) | B44: 3080294.2 | C44: 3034158.6 | D44: 0.01520541
A45: = FONDS DE ROULEMENT (1) | B45: 7624758.5 | C45: 7579129.1 | D45: 0.0060203898
A46: Actif circulant d'exploitation (b) | B46: 6058212.4 | C46: 5936719.1 | D46: 0.02046473
A47: - Passif circulant d'exploitation (b) | B47: 1853563 | C47: 2140422.3 | D47: -0.13401999
A48: = BESOIN DE FINANCEMENT D'EXPLOITATION (2) | B48: 4204649.4 | C48: 3796296.7 | D48: 0.10756607
A49: Actif circulant HAO (b) | B49: 0 | C49: 0
A50: - Passif circulant HAO (b) | B50: 0 | C50: 0
A51: = BESOIN DE FINANCEMENT HAO (3) | B51: 0 | C51: 0
A52: BESOIN DE FINANCEMENT GLOBAL (4) = (2) + (3) | B52: 4204649.4 | C52: 3796296.7 | D52: 0.10756607
B53: 0 | C53: 0
A54: TRESORERIE NETTE (5) = (1) - (4) | B54: 3420109 | C54: 3782832.4
A55: CONTRÔLE : TRESORERIE NETTE = TRESORERIE ACTIF - TRESORERIE PASSIF | B55: 3420109 | C55: 3782832
A56: ANALYSE DE LA VARIATION DE LA TRESORERIE | B56: 0 | C56: 0
A57: Flux de trésorerie des activités opérationnelles | B57: 4063214.1 | C57: 3855625.7 | D57: 0.053840397
A58: - Flux de trésorerie des activités d'investissement | B58: -822032.56 | C58: -553637.24 | D58: 0.48478552
A59: + Flux de trésorerie des activités de financement | B59: -3603730 | C59: -3603730 | D59: 0
A60: = VARIATION DE LA TRESORERIE NETTE DE LA PERIODE | B60: -362548.41 | C60: -301741.51 | D60: 0.20151984
A61: ANALYSE DE LA VARIATION DE L'ENDETTEMENT FINANCIER NET | B61: 0 | C61: 0
A62: Endettement financier brut (Dettes financières* + Trésorerie passif) - Trésorerie actif | B62: 3420109 | C62: 3782832.4 | D62: -0.095886625
A63: = ENDETTEMENT FINANCIER NET | B63: -3420109 | C63: -3782832.4 | D63: -0.095886725
A64: (a) Résultat d'exploitation après impôt théorique sur le bénéfice.
A65: (b) Les écarts de conversion doivent être éliminés afin de ramener les créances et les dettes concernées à leur valeur initiale.
A66: Dettes financières* = emprunts et dettes financières diverses + dettes de location acquisition.

Sheet Note 35
A1: NOTE 35 : LISTE DES INFORMATIONS SOCIALES, ENVIRONNEMENTALES ET SOCIETALES A FOURNIR
A3: Désignation entité : | B3: Excercice clos le : | C3: =+'Fiche de renseignement R1'!$V$10 -> 45657
A4: ='Fiche de renseignement R1'!$J$4 -> SOCIETE NOUVELLE DES SALINS DU SINE SALOUM
A5: Numéro d'identification : | B5: Durée en mois : | C5: =+'Fiche de renseignement R1'!$AH$10 -> 12
A6: =+'Fiche de renseignement R1'!$J$10 -> 000018699
A8: Note obligatoire pour les entités ayant un effectif de plus de 250 salariés
A9: Liste des informations sociales, environnementales et sociétales à fournir
A10: INFORMATIONS SOCIALES
A11: Emploi : • l'effectif total et la répartition des salariés par sexe, âge et zone géographique ; • les embauches et les licenciements ; • les rémunérations et leur évolution.
A12: Relations sociales : • l'organisation du dialogue social ; • le bilan des accords collectifs.
A13: Santé et sécurité : • les conditions de santé et de sécurité au travail ; • le bilan des accords signés avec les organisations syndicales ou les représentants du personnel en matière de santé et de sécurité au travail.
A14: Formation : • les politiques mises en œuvre en matière de formation ; • le nombre total d'heures de formation.
A15: Égalité de traitement : • les mesures prises en faveur de l'égalité entre les femmes et les hommes ; • les mesures prises en faveur de l'emploi et de l'insertion des personnes handicapées ;
A16: INFORMATIONS ENVIRONNEMENTALES
A17: Politique générale en matière environnementale : • l'organisation de la société pour prendre en compte les questions environnementales et, le cas échéant, les démarches d'évaluation ou de certification en matière d'environnement ; • les actions de formation et d'information des salariés menées en matière de protection de l'environnement ; les moyens consacrés à la prévention des risques environnementaux et des pollutions.
A18: Pollution et gestion des déchets : • les mesures de prévention, de réduction ou de réparation de rejets dans l'air, l'eau et le sol affectant gravement l'environnement ; • les mesures de prévention, de recyclage et d'élimination des déchets ; • la prise en compte des nuisances sonores et de toute autre forme de pollution spécifique à une activité.
A19: Utilisation durable des ressources : • la consommation d'eau et l'approvisionnement en eau en fonction des contraintes locales ; • la consommation de matières premières et les mesures prises pour améliorer l'efficacité dans leur utilisation ; • la consommation d'énergie, les mesures prises pour améliorer l'efficacité énergétique et le recours aux énergies renouvelables.
... A25: Sous-traitance et fournisseurs : • la prise en compte dans la politique d'achat des enjeux sociaux et environnementaux.

Sheet Note 36
A1: NOTE 36 : TABLE DES CODES
A6: 1 - Code forme juridique (1) | H6: 3 - Code pays du siège social
A8: Société Anonyme (SA) à participation publique | C8: 0 | F8: 0 | H8: Pays OHADA (2)
A10: Société Anonyme (SA) | C10: 0 | F10: 1 | H10: Autres pays africains | J10: 2 | M10: 1
A12: Société à Responsabilité Limitée (SARL) | C12: 0 | F12: 2 | H12: France | J12: 2 | M12: 3
A14: Société en Commandite Simple (SCS) | C14: 0 | F14: 3 | H14: Autres pays de l'Union Européenne | J14: 3 | M14: 9
A16: Société en Nom Collectif (SNC) | C16: 0 | F16: 4 | H16: U.S.A. | J16: 4 | M16: 0
A18: Société en Participation (SP) | C18: 0 | F18: 5 | H18: Canada | J18: 4 | M18: 1
A20: Groupement d'Intérêt Économique (GIE) | C20: 0 | F20: 6 | H20: Autres pays américains | J20: 4 | M20: 9
A22: Association | C22: 0 | F22: 7 | H22: Pays asiatiques | J22: 5 | M22: 0
A24: Société par Actions Simplifiée | C24: 0 | F24: 8 | H24: Autres pays | J24: 9 | M24: 9
A26: Autre forme juridique (à préciser) | C26: 0 | F26: 9
A28: 2 - Code régime fiscal
A30: Réel normal | F30: 1
A32: Réel simplifié | F32: 2
A34: Synthétique | F34: 3
A36: Forfait | F36: 4
A39: (1) Remplacer le premier 0 par 1 si l'entité bénéficie d'un agrément prioritaire
A40: (2) Bénin = 01; Burkina = 02; Côte d'Ivoire = 03; Guinée Bissau = 04; Mali = 05; Niger = 06; Sénégal = 07; Togo = 08
A41: Cameroun = 09; Congo = 10; Gabon = 11; République Centrafricaine = 12; Tchad = 13; Comores = 14; Guinée = 15;
A42: Guinée Equatoriale = 16; Congo RDC = 17.

Sheet Codes activités
A1: CODES DES ACTIVITES ECONOMIQUES
A4: Agriculture vivrière | C4: Industries du caoutchouc et des plastiques
A5: 001 001 Culture céréalière | C5: 022 001 Fabrication du caoutchouc naturel
A6: 001 002 Culture de tubercules et plantains | C6: 022 002 Industries du caoutchouc
A7: 001 003 Culture de légumes | C7: 022 003 Fabrication de matières plastiques
A8: 001 004 Culture de condiments | C8: Fabrication d'autres produits minéraux non métalliques et de matériaux
A9: 001 005 Culture de fruits | C9: de construction
A10: 001 006 Culture d'autres produits de l'Agriculture vivrière | C10: 023 001 Industrie du verre
A11: Agriculture industrielle et d'exportation | C11: 023 002 Fabrication de produits minéraux pour la construction
A12: 002 001 Culture de canne à sucre | C12: 023 003 Fabrication d'autres produits minéraux non métalliques
A13: 002 002 Culture d'arachide d'huilerie | C13: Métallurgie et travail des métaux
A14: 002 003 Culture d'arachide de bouche | C14: 024 001 Métallurgie
A15: 002 004 Culture de tabac | C15: 024 002 Travail des métaux
... A85: 021 005 Fabrication d'autres produits chimiques | C85: Correction territoriale
C86: 044 000 Correction territoriale
