Workbook

Sheet Page de garde
B3: REPUBLIQUE | I3: DU SENEGAL
B5: MINISTERE | I5: DES FINANCES ET DU BUDGET
B7: DIRECTION | I7: DIRECTION GENERALE DES IMÔTS ET DES DOMAINES
B15: CENTRE DE DEPOT : DIRECTION DES GRANDES ENTREPRISES
A21: ETATS FINANCIERS NORMALISES DU SYSCOHADA
B25: EXERCICE CLOS LE : | M25: 44926
A28: DESIGNATION DE L'ENTREPRISE
C33: DENOMINATION SOCIALE : | L33: IAMGOLD BOTO SA
C34: (ou nom et prénoms de l'exploitant)
C39: SIGLE USUEL :
C44: ADRESSE COMPLETE : | J44: PARCELLE 08 ZONE 7 ALMADIES DERRIERE HOTEL LODGE
C49: N° D'IDENTIFICATION FISCALE : | N49: 007768007
C53: SYSTEME NORMAL
C57: Documents déposés | V57: Réservé à la Direction Générale des Impôts
C60: Fiche d'identification et renseignements divers | S60: X | V60: Date de dépôt
C62: Bilan | S62: X
C64: Compte de résultat | S64: X | V64: Nom de l'agent de DGI ayant réceptionné le dépôt
C66: Tableau des flux de trésorerie | S66: X
C68: Notes annexes | S68: X | V68: Signature de l'agent et cachet du service
C70: Nombre de pages déposées par exemplaire
C71: Nombre d'exemplaires déposés | R71: 5

Sheet Fiche de renseignement R1
I3: Désignation de l'entreprise | J3: =+'Page de garde'!L33 -> IAMGOLD BOTO SA
I6: Adresse de l'entreprise | J6: ='Page de garde'!J44 -> PARCELLE 08 ZONE 7 ALMADIES DERRIERE HOTEL LODGE | AC6: Sigle usuel | AD6: =+'Page de garde'!H39 -> 0
I9: N° d'identification | J9: ='Page de garde'!N49 -> 007768007 | U9: Exercice clos le | V9: =+'Page de garde'!M25 -> 44926 | AG9: Durée (en mois) | AH9: 12
B12: ZA | E12: EXERCICE COMPTABLE | W12: DU | Y12: 44562 | AF12: AU | AH12: 44926
B15: ZB | E15: DATE D'ARRETE EFFECTIF DES COMPTES | U15: =+V9 -> 44926
B19: ZC | E19: EXERCICE PRECEDENT CLOS LE | Q19: 44561 | AK19: DUREE EXERCICE PRECEDENT EN MOIS : | AL19: 12
B23: ZD | F23: SN | I23: SN-DKR-2020-B 3772
F24: Greffe | I24: N° registre du Commerce | W24: N° répertoire des entreprises
B27: ZE | G27: 14202037720 | AE27: 006 002
G28: N° de sécurité sociale | S28: N° Code employeur | AE28: Code activité principale
B31: ZF | D31: =+J3 -> IAMGOLD BOTO SA | AE31: =+AD6 -> 0
D32: Désignation de l'entreprise | AE32: Sigle
B35: ZG | G35: 33 859 55 12 | AE35: Dakar
G36: N° de téléphone | Q36: Télécopie | Y36: Code | AA36: Boîte postale | AE36: Ville
B39: ZH | D39: PARCELLE 08 ZONE 7 ALMADIES DERRIERE HOTEL LODGE
D40: Adresse géographique complète (Immeuble, rue, quartier, ville, pays)
B43: ZI | D43: EXTRACTIONS DE MINERAIS METALLIQUES
D44: Désignation précise de l'activité principale exercée par l'entreprise | AE44: % capacité production utilisée
D47: AWA GUEYE DIAW
D48: Nom, adresse et qualité de personne à contacter en cas de demande d'informations complémentaires
D51: AWA GUEYE DIAW
D52: Nom du professionnel salarié de l'entreprise ou Nom, adresse et téléphone du cabinet comptable ou du professionnel INSCRIT A L'ORDRE NATIONAL DES EXPERTS COMPTABLES ET DES COMPTABLES AGREES ayant établi les états financiers.
D55: KPMG SENEGAL 2, Place de l’Indépendance | Sis Immeuble Ex-Hôtel de l’Indépendance (10e)
D56: Noms et adresses du ou des commissaires au comptes
E63: Non assujettie | K63: Non (refus) | O63: Oui avec réserves | S63: X | T63: Oui sans réserves | Z63: Non assujettie | AG63: Non | AK63: X | AL63: Oui
C65: Etats financiers certifiés (cocher la case) | X65: Etats financiers approuvés par l'Assemblée Générale (cocher la case)
D68: SEBASTIEN PERREAULT | T68: Domiciliations bancaires
D69: Nom du signataire des états financiers | T69: Banque | AD69: Numéro de compte
D71: DIRECTEUR GENERAL | T71: BICIS | AD71: SN0100152800060230008232
D72: Qualité du signataire des états financiers | T72: BOA SENEGAL | AD72: SN1000100300254657000785
D74: 45028
D75: Date de signature
D82: Signature

Sheet Activités de l'entreprise R2
B1: Désignation de l'entreprise : | C1: ='Fiche de renseignement R1'!$J$3 -> IAMGOLD BOTO SA
B2: Adresse de l'entreprise :
B3: ='Fiche de renseignement R1'!J6 -> PARCELLE 08 ZONE 7 ALMADIES DERRIERE HOTEL LODGE | L3: Sigle usuel : | M3: ='Fiche de renseignement R1'!AD6 -> 0
B4: N° d'identification : | L4: Exercice clos le :
B5: =+'Fiche de renseignement R1'!J9 -> 007768007 | L5: ='Fiche de renseignement R1'!V9 -> 44926 | M5: Durée (en mois) | N5: ='Fiche de renseignement R1'!AH9 -> 12
L7: Contrôle de l'entreprise (cocher la case)
A9: ZK | B9: Forme juridique (1) | F9: 0 | G9: 1 | K9: ZQ | L9: Entreprise sous contrôle public
A11: ZL | B11: Régime fiscal (1) | F11: 2 | K11: ZR | L11: Entreprise sous contrôle privé national
A13: ZM | B13: Pays du siège social (1) | F13: 0 | G13: 7 | K13: ZS | L13: Entreprise sous contrôle privé étranger | Q13: X
A15: ZN | B15: Nbre d'établissements dans le pays | F15: 0 | G15: 1
A17: ZO | B17: Nbre d'établissements hors du pays | F17: 0 | G17: 0
B18: pour lesquels une comptabilité distincte est tenue
A20: ZP | B20: 1ère année exercice dans le pays | E20: 2 | F20: 0 | G20: 2 | H20: 0
A23: ACTIVITE DE L'ENTREPRISE
B25: DESIGNATION DE L'ACTIVITE (2) | C25: Code nomenclature d'activité (1) | K25: Valeur Ajoutée (VA) HT | M25: % activité dans le CA HT ou la VA
B28: EXTRACTION DE MINERAIS METALLIQUES | D28: 0 | E28: 0 | F28: 6 | G28: 0 | H28: 0 | I28: 2 | M28: 1
M31: =+L31/$L$54 -> #DIV/0!
M34: =+L34/$L$54 -> #DIV/0!
M37: =+L37/$L$54 -> #DIV/0!
M40: =+L40/$L$54 -> #DIV/0!
M43: =+L43/$L$54 -> #DIV/0!
M46: =+L46/$L$54 -> #DIV/0!
M49: =+L49/$L$54 -> #DIV/0!
B52: Divers
I54: TOTAL | L54: =SUM(L27:L51) -> 0 | M54: =SUM(M27:M52) -> #DIV/0!
B57: (1) Se réréfer aux tables des codes
B58: (2) Lister de manière précise les activités dans l'ordre décroissant du CAHT, ou de la valeur ajoutée (V.A.)
B59: (3) Rayer la mention inutile (utiliser de préférence la V.A.)

Sheet Dirigeants R3
A1: Désignation de l'entreprise | B1: ='Fiche de renseignement R1'!$J$3 -> IAMGOLD BOTO SA
A2: Adresse de l'entreprise | B2: ='Activités de l''entreprise R2'!B3 -> PARCELLE 08 ZONE 7 ALMADIES DERRIERE HOTEL LODGE | D2: Sigle usuel | E2: ='Activités de l''entreprise R2'!M3 -> 0
A3: N° d'identification fiscale | B3: ='Activités de l''entreprise R2'!B5 -> 007768007 | C3: Exercice clos le | D3: ='Activités de l''entreprise R2'!L5 -> 44926 | E3: Durée (en mois) | F3: ='Activités de l''entreprise R2'!N5 -> 12
A5: DIRIGEANTS (1)
A7: Nom | B7: Prénoms | C7: Qualité | D7: N° d'identification fiscale | E7: Adressse (BP, ville, pays)
A8: PERREAULT | B8: SEBASTIEN | C8: DIRECTEUR GENERAL | E8: CANADA
A23: (1) Dirigeants = Président Directeur Général, Directeur Général, Adminsitrateur Général, Gérant, Autres.
A25: MEMBRES DU CONSEIL D'ADMINISTRATION
A27: Nom | B27: Prénoms | C27: Qualité | E27: Adressse (BP, ville, pays)
A28: TOGUYENI | B28: OUMAR | C28: PRESIDENT DU CONSEIL D'ADMINISTRATION | E28: DAKAR
A29: GUEYE | B29: IBRAHIMA | C29: ADMINISTRATEUR | E29: DAKAR
A30: SARR | B30: BASSIROU | C30: ADMINISTRATEUR | E30: DAKAR
A31: GILLES | B31: FERLATTE | C31: ADMINISTRATEUR | E31: CANADA
A32: CRAIG | B32: MACDOUGAL | C32: ADMINISTRATEUR | E32: CANADA

Sheet Tableau des Notes R4
A1: NOTES | B1: INTITULES | C1: A | D1: N/A
A2: NOTE 1 | B2: DETTES GARANTIES PAR DES SURETES REELLES | D2: X
A3: NOTE 2 | B3: INFORMATIONS OBLIGATOIRES | C3: X
A4: NOTE 3A | B4: IMMOBILISATION BRUTE | C4: X
A5: NOTE 3B | B5: BIENS PRIS EN LOCATION ACQUISITION | D5: X
A6: NOTE 3C | B6: IMMOBILISATIONS : AMORTISSEMENTS | C6: X
A7: NOTE 3D | B7: IMMOBILISATIONS : PLUS-VALUES ET MOINS VALUES DE CESSION | D7: X
A8: NOTE 3E | B8: INFORMATIONS SUR LES REEVALUATIONS EFFECTUEES PAR L'ENTITE | D8: X
A9: NOTE 3F | B9: TABLEAU D'ETALEMENT DES CHARGES IMMOBILISEES | C9: X
A10: NOTE 4 | B10: IMMOBILISATIONS FINANCIERES | D10: X
A11: NOTE 5 | B11: ACTIF CIRCULANT HAO | C11: X
A12: NOTE 6 | B12: STOCKS ET ENCOURS | D12: X
A13: NOTE 7 | B13: CLIENTS PRODUITS A RECEVOIR | C13: X
A14: NOTE 8 | B14: AUTRES CREANCES | D14: X
A15: NOTE 9 | B15: TITRES DE PLACEMENT | D15: X
A16: NOTE 10 | B16: VALEURS A ENCAISSER | D16: X
A17: NOTE 11 | B17: DISPONIBILITES | C17: X
A18: NOTE 12 | B18: ECARTS DE CONVERSION | C18: X
A19: NOTE 13 | B19: CAPITAL : VALEUR NOMINALE DES ACTIONS OU PARTS | C19: X
A20: NOTE 14 | B20: PRIMES ET RESERVES | D20: X
A21: NOTE 15A | B21: SUBVENTIONS ET PROVISIONS REGLEMENTEES | D21: X
A22: NOTE 15B | B22: AUTRES FONDS PROPRES | D22: X
A23: NOTE 16A | B23: DETTES FINANCIERES ET RESSOURCES ASSIMILEES | C23: X
A24: NOTE 16B | B24: ENGAGEMENTS DE RETRAITE ET AVANTAGES ASSIMILES (METHODE ACTURIELLE) | D24: X
A25: NOTE 16B bis | B25: ENGAGEMENTS DE RETRAITE ET AVANTAGES ASSIMILES (METHODE ACTURIELLE) | D25: X
A26: NOTE 16C | B26: ACTIFS ET PASSIFS EVENTUELS | D26: X
A27: NOTE 17 | B27: FOURNISSEURS D'EXPLOITATION | C27: X
A28: NOTE 18 | B28: DETTES FISCALES ET SOCIALES | C28: X
A29: NOTE 19 | B29: AUTRES DETTES ET PROVISIONS POUR RISQUES A COURT TERME | C29: X
A30: NOTE 20 | B30: BANQUES, CREDIT D'ESCOMPTE ET TRESORERIE | D30: X
A31: NOTE 21 | B31: CHIFFRE D'AFFAIRES ET AUTRES PRODUITS | C31: X
A32: NOTE 22 | B32: ACHATS | C32: X
A33: NOTE 23 | B33: TRANSPORTS | C33: X
A34: NOTE 24 | B34: SERVICES EXTERIEURS | C34: X
A35: NOTE 25 | B35: IMPOTS ET TAXES | C35: X
A36: NOTE 26 | B36: AUTRES CHARGES | C36: X
A37: NOTE 27A | B37: CHARGES DE PERSONNEL | C37: X
A38: NOTE 27B | B38: EFFECTIFS, MASSE SALARIALE ET PERSONNEL EXTERIEUR | C38: X
A39: NOTE 28 | B39: PROVISIONS ET DEPRECIATIONS INSCRITES AU BILAN | C39: X
A40: NOTE 29 | B40: CHARGES ET REVENUS FINANCIERS | C40: X
A41: NOTE 30 | B41: AUTRES CHARGES ET PRODUITS HAO | D41: X
A42: NOTE 31 | B42: REPARTITION DU RESULTAT ET AUTRES ELEMENTS CARACTERISTIQUES DES CINQ DERNIERES ANNEES | C42: X
A43: NOTE 32 | B43: PRODUCTION DE L'EXERCICE | C43: X
A44: NOTE 33 | B44: ACHATS DESTINES A LA PRODUCTION | D44: X
A45: NOTE 34 | B45: FICHE DE SYNTHESE DES PRINCIPAUX INDICATEURS FINANCIERS | C45: X
A46: NOTE 35 | B46: LISTE DES INFORMATIONS SOCIALES, ENVIRONNEMENTALES ET SOCIALES A FOURNIR | D46: X
A47: NOTE 36 | B47: TABLES DES CODES | C47: X

Sheet BILAN PAYSAGE
A1: REF | B1: ACTIF | C1: Note | E1: Exercice au 31/12/N | G1: Exercice au 31/12/N-1 | H1: REF | I1: PASSIF | J1: Note | K1: Exercice au 31/12/N | L1: Exercice au 31/12/N-1
D2: Brut | E2: Amorts et Dépréc. | F2: Net | G2: Net | K2: Net | L2: Net
A3: AD | B3: IMMOBILISATIONS INCORPORELLES | C3: 3 | D3: 44124617079 | E3: 52630775 | F3: 44071986304 | G3: 52124996 | H3: CA | I3: CAPITAL | J3: 13 | K3: 10000000 | L3: 10000000
A4: AE | B4: Frais de développement et de prospection | D4: 44028439487 | E4: 0 | F4: 44028439487 | G4: 0 | H4: CB | I4: Apporteurs capital non appelé | J4: 13
A5: AF | B5: Brevets, licences, logiciels et droits similaires | D5: 96177592 | E5: 52630775 | F5: 43546817 | G5: 52124996 | H5: CD | I5: Primes liées au capital social | J5: 14
A6: AG | B6: Fonds commercial et droit au bail | D6: 0 | E6: 0 | F6: 0 | G6: 0 | H6: CE | I6: Ecarts de réévaluation | J6: 3e
A7: AH | B7: Autres immobilisations incorporelles | D7: 0 | E7: 0 | F7: 0 | G7: 0 | H7: CF | I7: Réserves indisponibles | J7: 14
A8: AI | B8: IMMOBILISATIONS CORPORELLES | C8: 3 | D8: 42428515811 | E8: 243672245 | F8: 42184843566 | G8: 32575963615 | H8: CG | I8: Réserves libres | J8: 14
A9: AJ | B9: Terrains (1) (1) dont placement en net ………../………… | H9: CH | I9: Report à nouveau | J9: 14
A10: AK | B10: Bâtiments (1) dont placement en net ………../………… | H10: CJ | I10: Résutat net de l'exercice (bénéfice + ou perte -)
A11: AL | B11: Aménagements, agencements et installations | D11: 41216985491 | E11: 79793984 | F11: 41137191507 | G11: 31386687217 | H11: CL | I11: Subventions d'investissement | J11: 15
A12: AM | B12: Matériel, mobilier et actifs biologiques | D12: 393560030 | E12: 77887090 | F12: 315672940 | G12: 343602332 | H12: CM | I12: Provisions réglementées et fonds assimilés | J12: 15
A13: AN | B13: Matériel de transport | D13: 194438234 | E13: 85991171 | F13: 108447063 | G13: 157056622 | H13: CP | I13: TOTAL CAPITAUX PROPRES ET RESSOURCES ASSIMILEES | K13: 10000000 | L13: 10000000
A14: AP | B14: Avances & acomptes versés sur immobilisations | C14: 3 | D14: 623532056 | E14: 0 | F14: 623532056 | G14: 688617444 | H14: DA | I14: Emprunts et dettes financières diverses | J14: 16 | K14: 85897310394 | L14: 28095007190
A15: AQ | B15: IMMOBILISATIONS FINANCIERES | C15: 4 | D15: 1266202 | E15: 0 | F15: 1266202 | G15: 1266202 | H15: DB | I15: Dettes de location acquisition | J15: 16 | K15: 0 | L15: 0
A16: AR | B16: Titres de participation | H16: DC | I16: Provisions pour risques et charges | J16: 16 | K16: 2923279196 | L16: 42172294
A17: AS | B17: Autres immobilisations financières | D17: 1266202 | E17: 0 | F17: 1266202 | G17: 1266202 | H17: DD | I17: TOTAL DETTES FINANCIERES ET RESSOURCES ASSIMILEES | K17: 88820589590 | L17: 28137179484
A18: AZ | B18: TOTAL ACTIF IMMOBILISE | D18: 86554399092 | E18: 296303020 | F18: 86258096072 | G18: 32629354813 | H18: DF | I18: TOTAL RESSOURCES STABLES | K18: 88830589590 | L18: 28147179484
A19: BA | B19: ACTIF CIRCULANT H.A.O. | C19: 5 | H19: DH | I19: Dettes circulantes HAO | J19: 5
A20: BB | B20: STOCKS ET ENCOURS | C20: 6 | D20: 59194011 | E20: 0 | F20: 59194011 | G20: 38519190 | H20: DI | I20: Clients, avances reçues | J20: 7
A21: BG | B21: CREANCES ET EMPLOIS ASSIMILES | H21: DJ | I21: Fournisseurs d'exploitation | J21: 17 | K21: 334533601 | L21: 1321415095
A22: BH | B22: Fournisseurs, avances versées | C22: 17 | D22: 2911340 | E22: 0 | F22: 2911340 | G22: 2000000 | H22: DK | I22: Dettes fiscales et sociales | J22: 18 | K22: 254689679 | L22: 123670544
A23: BI | B23: Clients | C23: 7 | D23: 0 | E23: 0 | F23: 0 | G23: 0 | H23: DM | I23: Autres dettes | J23: 19 | K23: 652023381 | L23: 4856230416
A24: BJ | B24: Autres créances | C24: 8 | D24: 70137987 | E24: 191029 | F24: 69946958 | G24: 51787880 | H24: DN | I24: Provisions pour risques à court terme | J24: 19 | K24: 0 | L24: 0
A25: BK | B25: TOTAL ACTIF CIRCULANT | D25: 132243338 | E25: 191029 | F25: 132052309 | G25: 92307070 | H25: DP | I25: TOTAL PASSIF CIRCULANT | K25: 1241246661 | L25: 6301316055
A26: BQ | B26: Titres de placement | C26: 9
A27: BR | B27: Valeurs à encaisser | C27: 10 | H27: DQ | I27: Banques, crédit d'escompte | J27: 20
A28: BS | B28: Banques, chèques postaux, caisse et assimilés | C28: 11 | D28: 814679608 | E28: 0 | F28: 814679608 | G28: 1677943871 | H28: DR | I28: Banques, établissements financiers et crédits de trésorerie | J28: 20
A29: BT | B29: TOTAL TRESORERIE - ACTIF | D29: 814679608 | E29: 0 | F29: 814679608 | G29: 1677943871 | H29: DT | I29: TOTAL TRESORERIE - PASSIF
A30: BU | B30: Ecarts de conversion - Actif | C30: 12 | D30: 2869989451 | F30: 2869989451 | G30: 49246590 | H30: DV | I30: Ecarts de conversion - Passif | J30: 12 | K30: 2981189 | L30: 356805
A31: BZ | B31: TOTAL GENERAL | D31: 87501322038 | E31: 296494049 | F31: 90074817440 | G31: 34448852344 | H31: DZ | I31: TOTAL GENERAL

Sheet COMPTE DE RESULTAT
A1: REF | B1: LIBELLES | D1: NOTE | E1: 31/12/N | F1: 31/12/N-1
A2: TA | B2: Ventes de marchandises A | C2: + | D2: 21
A3: RA | B3: Achats de marchandises | C3: - | D3: 22
A4: RB | B4: Variation de stocks | C4: -/+ | D4: 6
A5: XA | B5: MARGE BRUTE SUR MARCHANDISES (somme TA à RB)
A6: TB | B6: Ventes de produits fabriqués B | C6: + | D6: 21
A7: TC | B7: Travaux, services vendus C | C7: + | D7: 21
A8: TD | B8: Produits accessoires D | C8: + | D8: 21
A9: XB | B9: CHIFFRE D'AFFAIRES (A + B + C + D) | E9: 0
A10: TE | B10: Production stockée (ou destockage) | C10: -/+ | D10: 6
A11: TF | B11: Production immobilisée | D11: 21 | E11: 9236283675 | F11: 9652980330
A12: TG | B12: Subventions d'exploitation | D12: 21 | E12: 0 | F12: 0
A13: TH | B13: Autres produits | C13: + | D13: 21 | E13: 2861563 | F13: 4846702
A14: TI | B14: Transferts de charges | C14: + | D14: 12 | E14: 46112334 | F14: 137671940
A15: RC | B15: Achats de matières premières et fournitures liées | C15: - | D15: 22 | E15: 0 | F15: 0
A16: RD | B16: Variation de stocks de stocks de matières premières et fournitures liées | C16: -/+ | D16: 6 | E16: 0 | F16: 0
A17: RE | B17: Autres achats | C17: - | D17: 22 | E17: 349152470 | F17: 713609614
A18: RF | B18: Variation de stocks d'autres approvisionnements | C18: -/+ | D18: 6 | E18: -20674821 | F18: -14631508
A19: RG | B19: Transports | C19: - | D19: 23 | E19: 146271853 | F19: 185281834
A20: RH | B20: Services extérieurs | C20: - | D20: 24 | E20: 3536776621 | F20: 6829030561
A21: RI | B21: Impôts et taxes | C21: - | D21: 25 | E21: 13207676 | F21: 9661831
A22: RJ | B22: Autres charges | C22: - | D22: 26 | E22: 786944946 | F22: 518558600
A23: XC | B23: VALEUR AJOUTEE (XB + RA + RB) + (somme TE à RJ) | E23: 4473578827 | F23: 1553988040
A24: RK | B24: Charges de personnel | C24: - | D24: 27 | E24: 1138660841 | F24: 1434746792
A25: XD | B25: EXCEDENT BRUT D'EXPLOITATION (XC + RK) | E25: 3334917986 | F25: 119241248
A26: TJ | B26: Reprises d'amortissements | C26: + | D26: 28 | E26: 0 | F26: 0
A27: RL | B27: Dotations aux amortissements, aux provisions et dépréciations | C27: - | D27: 3C & 28 | E27: 174654368 | F27: 142175480
A28: XE | B28: RESULTAT D'EXPLOITATION (XD + TJ + RL) | E28: 3160263618 | F28: -22934232
A29: TK | B29: Revenus financiers et assimilés | C29: + | D29: 29 | E29: 9643057 | F29: 30480926
A30: TL | B30: Reprises de provisions et dépréciations financières | C30: + | D30: 28 | E30: 0 | F30: 0
A31: TM | B31: Tranfert de charges financières | C31: + | D31: 12 | E31: 0 | F31: 0
A32: RM | B32: Frais financiers et charges assimilées | C32: - | D32: 29 | E32: 300108253 | F32: 7546694
A33: RN | B33: Dotations aux provisions et aux dépréciations financières | C33: - | D33: 3C & 28 | E33: 2869798422 | F33: 0
A34: XF | B34: RESULTAT FINANCIER (somme TK à RN) | E34: -3160263618 | F34: 22934232
A35: XG | B35: RESULTAT DES ACTIVITES ORDINAIRES (XE + XF)
A36: TN | B36: Produits des cessions d'immobilisations | C36: + | D36: 3D
A37: TO | B37: Autres produits H.A.O. | C37: + | D37: 30
A38: RO | B38: Valeurs comptables des cessions d'immobilisations | C38: - | D38: 3D
A39: RP | B39: Charges H.A.O. | C39: - | D39: 30
A40: XH | B40: RESULTAT HORS ACTIVITES ORDINAIRES (somme TN à RP)
A41: RQ | B41: Participations des travailleurs | C41: - | D41: 30
A42: RS | B42: Impôts sur le résultat | C42: -
A43: XI | B43: RESULTAT NET (XG + XH + RQ + RS) | E43: 0 | F43: 0

Sheet FLUX DE TRESORERIE
A1: REF | B1: LIBELLES | D1: NOTE | E1: 31/12/N | F1: 31/12/N-1
A2: ZA | B2: Trésorerie nette au 1er janvier (Trésorerie actif N-1 - Trésorerie passif N-1) | C2: A | E2: 1677943871 | F2: 2753722181
B3: Flux de trésorerie provenant des activités opérationnelles
A4: FA | B4: Capacité d'Autofinancement Globale (CAFG) | E4: 3044452790 | F4: 142175480
A5: FB | B5: - Variation de l'actif circulant HAO (1) | E5: 0 | F5: 0
A6: FC | B6: - Variation des stocks | E6: 20674821 | F6: 14631508
A7: FD | B7: - Variation des créances | E7: 19070418 | F7: 46897264
A8: FE | B8: + Variation du passif circulant (1) | E8: -5060069394 | F8: 1024893595
B9: Variation du BF lié aux activités opérationnelles (FB + FC + FD + FE) : …………………………………………….. | E9: -5099814633 | F9: 963364823
A10: ZB | B10: Flux de trésorerie provenant des activités opérationnelles (somme FA à FE) | C10: B | E10: -2055361843 | F10: 1105540303
B11: Flux de trésorerie provenant des activités d'investissement
A12: FF | B12: - Décaissements liés aux acquisitions d'immobilisations incorporelles | E12: 44050301125 | F12: 53243934
A13: FG | B13: - Décaissements liés aux acquisitions d'immobilisations corporelles | E13: 9741786022 | F13: 20444771948
A14: FH | B14: - Décaissements liés aux acquisitions d'immobilisations financières | E14: 0 | F14: 1266202
A15: FI | B15: + Encaissements liés aux cessions d'immobilisations incorporelles et corporelles | E15: 0 | F15: 0
A16: FJ | B16: + Encaissements liés aux cessions d'immobilisations financières | E16: 0 | F16: 0
A17: ZC | B17: Flux de trésorerie provenant des activités d'investissement (somme FF à FJ) | C17: C | E17: -53792087147 | F17: -20499282084
B18: Flux de trésorerie provenant du financement par les capitaux propres
A19: FK | B19: + Augmentations de capital par apports nouveaux
A20: FL | B20: + Subventions d'investissements reçues
A21: FM | B21: - Prélèvements sur le capital
A22: FN | B22: - Dividendes versés
A23: ZD | B23: Flux de trésorerie provenant du financement par les capitaux propres (somme FK à FN) | C23: D
B24: Flux de trésorerie provenant du financement par les capitaux étrangers
A25: FO | B25: + Emprunts
A26: FP | B26: + Autres dettes financières | E26: 58921929719 | F26: 18967705746
A27: FQ | B27: - Remboursements des emprunts et autres dettes financières | E27: 1119626515 | F27: 0
A28: ZE | B28: Flux de trésorerie provenant du financement par les capitaux étrangers (somme FO à FQ) | C28: E | E28: 57802303204 | F28: 18967705746
A29: ZF | B29: Flux de trésorerie provenant des capitaux étrangers (D + E) | C29: F | E29: 57802303204 | F29: 18967705746
A30: ZG | B30: VARIATION DE LA TRESORERIE NETTE DE LA PERIODE (B + C + F) | C30: G | E30: 1954854214 | F30: -426036035
A31: ZH | B31: Trésorerie nette au 31 décembre (G + A) Contrôle : Trésorerie actif N - Trésorerie passif N | C31: H | E31: 814679608 | F31: 1677943871
B32: Contrôle

Sheet Note 1
A1: NOTE 1 : DETTES GARANTIES PAR DES SURETES REELLES
A3: Désignation entité : | D3: Excercice clos le : | E3: =+'Fiche de renseignement R1'!$V$9 -> 44926
A4: IAMGOLD BOTO SA | D4: Durée en mois : | E4: =+'Fiche de renseignement R1'!$AH$9 -> 12
A5: Numéro d'identification : | B5: =+'Fiche de renseignement R1'!$J$9 -> 007768007
A7: LIBELLES | B7: Note | C7: Montant brut | D7: SURETES REELLES
D8: Hypothèques | E8: Nantissements | F8: Gages
F9: Autres
A10: Dettes financières et ressources assimilées :
A11: Emprunts obligataires convertibles
A12: Autres emprunts obligataires
A13: Emprunts et dette des établissements de crédit
A14: Autres dettes financières
A15: SOUS TOTAL (1) | C15: =SUM(C11:C14) -> 0 | D15: =SUM(D11:D14) -> 0 | E15: =SUM(E11:E14) -> 0 | F15: =SUM(F11:F14) -> 0
A17: Dettes de location-acquisition :
A18: Dettes de crédit-bail immobilier
A19: Dettes de crédit-bail mobilier
A20: Dettes sur contrats de location-vente
A21: Dettes sur contrats de location-acquisition
A22: SOUS TOTAL (2) | C22: =SUM(C18:C21) -> 0 | D22: =SUM(D18:D21) -> 0 | E22: =SUM(E18:E21) -> 0 | F22: =SUM(F18:F21) -> 0
A24: Dettes du passif circulant :
A25: Fournisseurs
A26: Clients
A27: Personnel
A28: Sécurité sociale et organismes sociaux
A29: Etat
A30: Organismes internationaux
A31: Associéss et groupe
A32: Crédits divers
A33: SOUS TOTAL (3) | C33: =SUM(C25:C32) -> 0 | D33: =SUM(D25:D32) -> 0 | E33: =SUM(E25:E32) -> 0 | F33: =SUM(F25:F32) -> 0
A34: TOTAL (1) + (2) + (3) | C34: =+C15+C22+C33 -> 0 | D34: =+D15+D22+D33 -> 0 | E34: =+E15+E22+E33 -> 0 | F34: =+F15+F22+F33 -> 0
A35: ENGAGEMENTS FINANCIERS | E35: Engagements donnés | F35: Engagements reçus
A36: Engagements consentis à des entités liées
A37: Primes de remboursement non échus
A38: Avals, cautions, garanties
A39: Hypothèques, nantissements, gages, autres
A40: Effets escomptés non échus
A41: Créances commerciales et professionnelles cédées
A42: Abandon de créances conditionnelles
A43: TOTAL | E43: =SUM(E36:E42) -> 0 | F43: =SUM(F36:F42) -> 0
A44: Commentaire :
A45: · Indiquer la raison d’être des suretés

Sheet Note 2
A1: NOTE 2 : INFORMATIONS OBLIGATOIRES
A3: Désignation entité : | C3: Excercice clos le : | D3: =+'Note 1'!E3 -> 44926
A4: =+'Note 1'!A4 -> IAMGOLD BOTO SA | C4: Durée en mois : | D4: =+'Note 1'!E4 -> 12
A5: Numéro d'identification : | B5: =+'Note 1'!B5 -> 007768007
A7: A - DECLARATION DE CONFORMITE AU SYSCOHADA
A8: Les états financiers sont établis en conformité avec le systéme comptable OHADA et l'acte uniforme relatif au droit comptable et à l'information financiére
A9: B - REGLES ET METHODES COMPTABLES
A10: les états financiers ont été confectionnés dans le respect des postulats, des conventions et des régles d'évaluation édictés par le SYSCOHADA et l'Acte Uniforme
A11: C - DEROGATION AUX POSTULATS ET CONVENTIONS COMPTABLES
A12: Respect de tous les postulats et conventions comptables sans aucune dérogation
A13: D - INFORMATIONS COMPLEMENTAIRES RELATIVES AU BILAN, AU COMPTE DE RESULTAT ET AU TABLEAU DES FLUX DE TRESORERIE
A14: Pas d'informations complémentaires relatives aux autres états financiers

Sheet Note 3A
A1: NOTE 3A : IMMOBILISATION BRUTE
A3: Désignation entité : | E3: Excercice clos le : | F3: =+'Note 1'!E3 -> 44926
A4: =+'Note 1'!A4 -> IAMGOLD BOTO SA | E4: Durée en mois : | F4: =+'Note 1'!E4 -> 12
A5: Numéro d'identification : | B5: =+'Note 1'!B5 -> 007768007
A7: SITUATIONS ET MOUVEMENTS | B7: Montant brut à l'ouverture de l'exercice | C7: Acquisitions Apports Créations | D7: Virements de poste à poste | E7: Suite à une réévaluation pratiquée au cours de l'exercice | F7: Cessions Scissions Hors service | G7: Virements de poste à poste | H7: Montant brut à la clôture de l'exercice
A10: IMMOBILISATIONS INCORPORELLES | B10: 74315954 | C10: 44050301125 | D10: 0 | E10: 0 | F10: 0 | G10: 0 | H10: 44124617079
A11: Frais de développement et de prospection | B11: 0 | C11: 44028439487 | F11: 0 | H11: 44028439487
A12: Brevets, licences, logiciels et droits similaires | B12: 74315954 | C12: 21861638 | F12: 0 | H12: 96177592
A13: Fonds commercial et droit au bail | B13: 0 | C13: 0 | F13: 0 | H13: 0
A14: Autres immobilisations incorporelles | B14: 0 | C14: 0 | F14: 0 | H14: 0
A15: IMMOBILISATIONS CORPORELLES | B15: 31998112345 | C15: 9806871410 | D15: 0 | E15: 0 | F15: -134807064 | G15: 134807064 | H15: 41804983755
A16: Terrains hors immeuble de placement | B16: 0 | C16: 0 | F16: 0 | H16: 0
A17: Terrains immeuble de placement | B17: 0 | C17: 0 | F17: 0 | H17: 0
A18: Bâtiments hors immeuble de placement | B18: 31064914570 | C18: 9750915545 | F18: 0 | H18: 40815830115
A19: Bâtiments immeuble de placement | B19: 0 | C19: 0 | F19: 0 | H19: 0
A20: Aménagements, agencements et installations | B20: 359083339 | C20: 42072037 | F20: -2920000 | G20: 2920000 | H20: 401155376
A21: Matériel, mobilier et actifs biologiques | B21: 379676202 | C21: 13883828 | F21: -3974400 | G21: 3974400 | H21: 393560030
A22: Matériel de transport | B22: 194438234 | C22: 0 | F22: -127912664 | G22: 127912664 | H22: 194438234
A23: AVANCES ET ACOMPTES VERSES SUR IMMOBILISATIONS | B23: 688617444 | C23: 0 | D23: 0 | E23: 0 | F23: 65085388 | G23: 0 | H23: 623532056
A24: Immobilisations incorporelles | B24: 0 | C24: 0 | F24: 0 | H24: 0
A25: Immoblisations corporelles | B25: 688617444 | C25: 0 | F25: 65085388 | H25: 623532056
A26: IMMOBILISATIONS FINANCIERES | B26: 1266202 | C26: 0 | D26: 0 | E26: 0 | F26: 0 | G26: 0 | H26: 1266202
A27: Titres de placement | B27: 0 | C27: 0 | F27: 0 | H27: 0
A28: Autres immobilisations financières | B28: 1266202 | C28: 0 | F28: 0 | H28: 1266202
A29: TOTAL GENERAL | B29: 32762311945 | C29: 53857172535 | D29: 0 | E29: 0 | F29: -69721676 | G29: 134807064 | H29: 86554399092
A30: Commentaire :
A31: · Toute variation significative doit être commentée
A32: · Détailler les éléments constitutifs du fonds commercial et indiquer la date d'acquisition
A33: · Pour l'immobilisation incorporelle relative à la concession faire un descriptif de l'accord
A34: · Indiquer :
A35: - la nature de la créance ;
A36: - la durée de la concession ;
A37: - l'échéance ;
A38: · Indiquer les créances du groupe avec nature et date d'échéance
A39: · Pour les banques, DAT indiquer le nom de labanque, le montant et la date d'échéance
A40: Cette augmentation des immobilisations est principalement expliquée par la comptabilisation des frais de recherche dans les immobilisations corporelles suite à la validation en Mars 2022 par
A41: le Ministère des Mines et de la Géologie , de ces dépenses , à hauteur de 42 908 812 972 FCFA sur les 44 312 076 640 engagés.

Sheet Note 3B
A1: NOTE 3B : BIENS PRIS EN LOCATION ACQUISITION
A3: Désignation entité : | G3: Excercice clos le : | H3: =+'Note 1'!E3 -> 44926
A4: =+'Note 1'!A4 -> IAMGOLD BOTO SA | G4: Durée en mois : | H4: =+'Note 1'!E4 -> 12
A5: Numéro d'identification : | B5: =+'Note 1'!B5 -> 007768007
A7: SITUATIONS ET MOUVEMENTS | B7: NATURE DU CONTRAT (I; M; A) | C7: A | D7: AUGMENTATIONS B | G7: DIMINUTIONS C | I7: D = A +B - C
C8: Montant brut à l'ouverture de l'exercice | D8: Acquisitions Apports Créations | E8: Virements de poste à poste | F8: Suite à une réévaluation pratiquée au cours de l'exercice | G8: Cessions Scissions Hors service | H8: Virements de poste à poste | I8: Montant brut à l'ouverture de l'exercice
B9: [1]
A10: Brevets, licences, logiciels et droits similaires
A11: Fonds commercial et droit au bail
A12: Autres immobilisations incorporelles
A13: SOUS TOTAL : IMMOBILISATIONS INCORPORELLES
A14: Terrains
A15: Bâtiments
A16: Aménagements, agencements et installations
A17: Matériel, mobilier et actifs biologiques
A18: Matériel de transport
A19: SOUS TOTAL : IMMOBILISATIONS CORPORELLES
A21: TOTAL GENERAL
A22: [1] I : crédit-bail immobilier; M : crédit-bail mobilier; A : autres contrats (dédoubler le poste si montants significatifs)
... A24: · Indiquer la nature du bien, le nom du bailleur et la durée du bail

Sheet Note 3C
A1: NOTE 3C : IMMOBILISATIONS (AMORTISSEMENTS)
A3: Désignation entité : | D3: Excercice clos le : | E3: =+'Note 1'!E3 -> 44926
A4: =+'Note 1'!A4 -> IAMGOLD BOTO SA | D4: Durée en mois : | E4: =+'Note 1'!E4 -> 12
A5: Numéro d'identification : | B5: =+'Note 1'!B5 -> 007768007
A7: SITUATIONS ET MOUVEMENTS | B7: A | C7: B | D7: C | E7: D = A +B - C
B8: Amortissements cumulés à l'ouverture de l'exercice | C8: Augmentations : Dotations de l'exercice | D8: Diminutions : Amortissements relatifs aux éléments sortis de l'actif | E8: Cumul des amortissements à la clôture de l'exercice
A10: Frais de développement et de prospection
A11: Brevets, licences, logiciels et droits similaires | B11: 22190958 | C11: 30439817 | D11: 0 | E11: 52630775
A12: Fonds commercial et droit au bail
A13: Autres immobilisations incorporelles
A14: SOUS TOTAL : IMMOBILISATIONS INCORPORELLES | B14: 22190958 | C14: 30439817 | D14: 0 | E14: 52630775
A15: Terrains hors immeuble de placement
A16: Terrains immeuble de placement
A17: Bâtiments hors immeuble de placement
A18: Bâtiments immeuble de placement
A19: Aménagements, agencements et installations | B19: 37310692 | C19: 42483292 | D19: 0 | E19: 79793984
A20: Matériel, mobilier et actifs biologiques | B20: 36073870 | C20: 41813220 | D20: 0 | E20: 77887090
A21: Matériel de transport | B21: 37381612 | C21: 48609559 | D21: 0 | E21: 85991171
A22: SOUS TOTAL : IMMOBILISATIONS CORPORELLES | B22: 110766174 | C22: 132906071 | D22: 0 | E22: 243672245
A24: TOTAL GENERAL | B24: 132957132 | C24: 163345888 | D24: 0 | E24: 296303020
A25: Commentaire :
A26: · Indiquer :
A27: - les modes d'amortissements utilisés : amortissement linéaire
A28: - la durée de vie ou les taux d'amortissements utilisés ;
A30: Type d'immobilisation | B30: Methode damortissement | C30: Durée
A32: Immobilisations incorporelles | B32: Linéaire | C32: 3 ans
A33: Bâtiments, agencements et Installations techniques | B33: Linéaire | C33: Durée de vie de la mine
A34: Equipements informatiques et Logiciels | B34: Linéaire | C34: 3 ans
A35: Matériels et mobiliers | B35: Linéaire | C35: 5 ans
A36: Matériels de transport | B36: Linéaire | C36: 5 ans
A37: Engins lourds miniers | B37: Linéaire | C37: Durée de vie de la mine

Sheet Note 3C Bis
A1: NOTE 3C : IMMOBILISATIONS (DEPRECIATIONS)
A3: Désignation entité : | D3: Excercice clos le : | E3: =+'Note 1'!E3 -> 44926
A4: =+'Note 1'!A4 -> IAMGOLD BOTO SA | D4: Durée en mois : | E4: =+'Note 1'!E4 -> 12
A5: Numéro d'identification : | B5: =+'Note 1'!B5 -> 007768007
A7: SITUATIONS ET MOUVEMENTS | B7: A | C7: B | D7: C | E7: D = A +B - C
B8: Amortissements cumulés à l'ouverture de l'exercice | C8: Augmentations : Dotations de l'exercice | D8: Diminutions : Amortissements relatifs aux éléments sortis de l'actif | E8: Cumul des amortissements à la clôture de l'exercice
A10: Frais de développement et de prospection
A11: Brevets, licences, logiciels et droits similaires
A12: Fonds commercial et droit au bail
A13: Autres immobilisations incorporelles
A14: SOUS TOTAL : IMMOBILISATIONS INCORPORELLES
A15: Terrains hors immeuble de placement
A16: Terrains immeuble de placement
A17: Bâtiments hors immeuble de placement
A18: Bâtiments immeuble de placement
A19: Aménagements, agencements et installations
A20: Matériel, mobilier et actifs biologiques
A21: Matériel de transport
... A34: - la durée de vie ou les taux d'amortissements utilisés ;

Sheet Note 3D
A1: NOTE 3D : IMMOBILISATIONS (PLUS-VALUES ET MOINS VALUES DE CESSION)
A3: Désignation entité : | D3: Excercice clos le : | E3: =+'Note 1'!E3 -> 44926
A4: =+'Note 1'!A4 -> IAMGOLD BOTO SA | D4: Durée en mois : | E4: =+'Note 1'!E4 -> 12
A5: Numéro d'identification : | B5: =+'Note 1'!B5 -> 007768007
B7: MONTANT BRUT | C7: AMORTISSEMENTS | D7: VALEUR COMPTABLE NETTE | E7: PRIX DE CESSION | F7: PLUS VALUE OU MOINS VALUE
C8: PRATIQUES
B9: A | C9: B | D9: C = A - B | E9: D | F9: E = D - C
A10: Frais de développement et de prospection
A11: Brevets, licences, logiciels et droits similaires
A12: Fonds commercial et droit au bail
A13: Autres immobilisations incorporelles
A14: SOUS TOTAL : IMMOBILISATIONS INCORPORELLES
A15: Terrains
A16: Bâtiments
A17: Aménagements, agencements et installations
A18: Matériel, mobilier et actifs biologiques
A19: Matériel de transport
A20: SOUS TOTAL : IMMOBILISATIONS CORPORELLES
A21: Titres de placement
... A27: · Mentionner la justification de la cession ainsi que la date d'acquisition et la date de sortie

Sheet Note 3E
A1: NOTE 3E : INFORMATIONS SUR LES REEVALUATIONS EFFECTUEES PAR L'ENTITE
A3: Désignation entité : | C3: Excercice clos le : | D3: =+'Note 1'!E3 -> 44926
A4: =+'Note 1'!A4 -> IAMGOLD BOTO SA | C4: Durée en mois : | D4: =+'Note 1'!E4 -> 12
A5: Numéro d'identification : | B5: =+'Note 1'!B5 -> 007768007
A7: Nature et date des réévaluations :
A13: Eléments réévalués par postes du bilan | B13: Montants coûts historiques | C13: Amortissements supplémentaires
A22: Méthode de réévaluation utilisée :
A24: Traitement fiscal de l'écart de réévaluation
A25: et des amortissements supplémentaires :
A27: Montant de l'écart incorporé au capital :

Sheet Note 4
A1: NOTE 4 : IMMOBILISATIONS FINANCIERES
A3: Désignation entité : | F3: Excercice clos le : | G3: =+'Note 1'!E3 -> 44926
A4: =+'Note 1'!A4 -> IAMGOLD BOTO SA | F4: Durée en mois : | G4: =+'Note 1'!E4 -> 12
A5: Numéro d'identification : | B5: =+'Note 1'!B5 -> 007768007
A7: SITUATIONS ET MOUVEMENTS | B7: ANNEE 2022 | C7: ANNEE 2021 | D7: Variation en valeur absolue | E7: Variation en % | F7: Créances à un an au plus | G7: Créances à plus d'un an et à deux ans au plus | H7: Créances à plus de deux ans
A9: Titres de participation | B9: 0 | C9: 0
A10: Prêts et créances | B10: 0 | C10: 0
A11: Prêt au personnel | B11: 0 | C11: 0
A12: Créances sur l'Etat | B12: 0 | C12: 0
A13: Créances sur le concédant | B13: 0 | C13: 0
A14: Titres immobilisés | B14: 0 | C14: 0
A15: Dépôts et cautionnements | B15: 1266202 | C15: 1266202
A16: Intérêts courus | B16: 0 | C16: 0
A17: Créances rattachées à des avances et participations à des GIE | B17: 0 | C17: 0
A18: Immobilisations financières diverse | B18: 0 | C18: 0
A19: TOTAL BRUT | B19: 1266202 | C19: 1266202
A20: Dépréciations titres de participation
A21: Dépréciations autres immobilisations
A22: TOTAL NET DE DEPRECIATION | B22: 1266202 | C22: 1266202
A24: Liste des filiales et participations :
A26: Dénomination sociale | B26: Localisation (ville/pays) | C26: Valeur d'acquisition | F26: % détenu | G26: Montant des capitaux propres filiale | H26: Résultat dernier exercice filiale
A35: Commentaire :
A36: · Justifier toute variation significative
A37: · Commenter toutes les créances anciennes
A38: · Pour les créances relatives à la concession, faire un descriptif de l'accord
A39: · Indiquer :
A40: - la nature de la créance ;
A41: - la durée de la concession ;
A42: - l'échéance ;
A43: · Indiquer le nombre et la date d'acquisition des actions ou parts propres
A44: · Dépréciation : indiquer les évènements et les circonstances qui ont motivé
A45: la dépréciation ou la reprise
A46: Il s'agit de cautions versées pour le branchement au réseaux d'eau et electrique au niveau du siège social

Sheet Note 5
A1: NOTE 5 : ACTIF CIRCULANT HAO
A3: Désignation entité : | F3: Excercice clos le : | G3: =+'Note 1'!E3 -> 44926
A4: =+'Note 1'!A4 -> IAMGOLD BOTO SA | F4: Durée en mois : | G4: =+'Note 1'!E4 -> 12
A5: Numéro d'identification : | B5: =+'Note 1'!B5 -> 007768007
A7: LIBELLES | B7: ANNEE 2022 | C7: ANNEE 2021 | D7: Variation en valeur absolue | E7: Variation en % | F7: Créances à un an au plus | G7: Créances à plus d'un an et à deux ans au plus | H7: Créances à plus de deux ans
A9: Créances sur cessions d'immobilisations
A10: Autres créances hors activités ordinaires
A11: TOTAL BRUT
A12: Dépréciations des créances HAO
A13: TOTAL NET DE DEPRECIATION
A14: Commentaire :
A15: · Commenter touter variation significative
A16: · Dépréciation : indiquer les évènements et les circonstances qui ont motivé
A17: la dépréciation ou la reprise
A19: DETTES CIRCULANTES HAO
A21: LIBELLES | B21: ANNEE 2022 | E21: ANNEE 2021 | G21: VARIATION EN %
A23: Fournisseurs d'investissements
A24: Fournisseurs d'investissements effets à payer
A25: Versements restant à effectuer sur titres de participation et titres immobilisés non libérés
A26: Autres dettes hors activités ordinaires
A27: TOTAL
A28: Commentaire :
A29: · Indiquer la date de cession et la nature de l'immobilisation achétée et/ou cédée
A30: · Expliquer toute variation significative

Sheet Note 6
A1: NOTE 6 : STOCKS ET ENCOURS(1)
A3: Désignation entité : | C3: Excercice clos le : | D3: =+'Note 1'!E3 -> 44926
A4: =+'Note 1'!A4 -> IAMGOLD BOTO SA | C4: Durée en mois : | D4: =+'Note 1'!E4 -> 12
A5: Numéro d'identification : | B5: =+'Note 1'!B5 -> 007768007
A7: LIBELLES | B7: ANNEE 2022 | C7: ANNEE 2021 | D7: VARIATION EN %
A9: Marchandises
A10: Marchandises HAO
A11: Matières premmières et fournitures liées
A12: Autres approvisionnements | B12: 59194011 | C12: 38519190 | D12: 0.5367408
A13: Emballages
A14: Produits en cours
A15: Services en cours
A16: Produits finis
A17: Produits intermédiaires
A18: Stocks en cours de cours, en consignation ou en dépôt
A19: TOTAL BRUT STOCKS ET EN COURS | B19: 59194011 | C19: 38519190 | D19: 0.5367408
A20: Dépréciations des stocks
A22: TOTAL | B22: 59194011 | C22: 38519190 | D22: 0.5367408
A23: (1) : Les stocks HAO seront inscrits dans l'actif circulant HAO que lorsque leur montant total est significatif
A24: (supérieur à 5% du total de l'actif circulant)
A25: Commentaire :
A26: · Indiquer la date de prise d'inventaire et décrire brièvement la procédure, les méthodes comptables adoptées
A27: pour évaluer le stock
A28: · Commenter toute variation significative des stocks
A29: · Indiquer le détail des stocks dépréciés et les évènements et circonstances qui ont conduit à la dépréciation
A30: et à la reprise
A32: Le stock est relatif aux approvisionnements en carburant.
A33: L'inventaire a été effectué au 31/12/2022, la méthode PEPS (Premier entré Premier sorti) a été utilisée.

Sheet Note 7
A1: NOTE 7 : CLIENTS PRODUITS A RECEVOIR
A3: Désignation entité : | F3: Excercice clos le : | G3: =+'Note 1'!E3 -> 44926
A4: =+'Note 1'!A4 -> IAMGOLD BOTO SA | F4: Durée en mois : | G4: =+'Note 1'!E4 -> 12
A5: Numéro d'identification : | B5: =+'Note 1'!B5 -> 007768007
A7: LIBELLES | B7: ANNEE 2022 | C7: ANNEE 2021 | D7: Variation en valeur absolue | E7: Variation en % | F7: Créances à un an au plus | G7: Créances à plus d'un an et à deux ans au plus | H7: Créances à plus de deux ans
A9: Clients (hors réserves de propriété Groupe)
A10: Clients effets à recevoir (hors réserves de propriété Groupe)
A11: Clients effets à recevoir avec réserves de propriété Groupe
A12: Clients et effets à recevoir Etat, Collectivités, et organismes internationaux
A13: Clients chèques et valeurs impayés
A14: Clients avec réserve de propriété
A15: Clients effets à recevoir Groupe
A16: Créances sur cession d'immobilisations
A17: Clients effets escomptés et non échus
A18: Créances litigieuses ou douteuses
A19: Clients produits à recevoir
A20: TOTAL BRUT CLIENTS
... A31: · Indiquer les évènements et les circonstances qui ont conduit à la dépréciation et à la reprise

Sheet Note 8
A1: NOTE 8 : AUTRES CREANCES
A3: Désignation entité : | E3: Excercice clos le : | F3: =+'Note 1'!E3 -> 44926
A4: =+'Note 1'!A4 -> IAMGOLD BOTO SA | E4: Durée en mois : | F4: =+'Note 1'!E4 -> 12
A5: Numéro d'identification : | B5: =+'Note 1'!B5 -> 007768007
A7: LIBELLES | B7: ANNEE 2022 | C7: ANNEE 2021 | D7: Variation en % | E7: Créances à un an au plus | F7: Créances à plus d'un an et à deux ans au plus | G7: Créances à plus de deux ans
A9: Personnel | B9: 2260528 | C9: 609763 | D9: 2.707224
A10: Organismes sociaux | B10: 0 | C10: 0 | D10: 0
A11: Etat et collectivités publiques | B11: 31021327 | C11: 31021327 | D11: 0 | E11: 31021327 | F11: 0
A12: Organismes internationaux | B12: 0 | C12: 0 | D12: 0
A13: Apporteurs, associés et Groupe | B13: 5090586 | C13: 5578895 | D13: -0.087527907
A14: Compte transitoire ajustement spécial lié à la révision du SYSCOHADA | B14: 0 | C14: 0 | D14: 0
A15: Autres débiteurs divers | B15: 992925 | C15: 63824485 | D15: -0.98444288 | F15: 992925
A16: Comptes permanents non bloqués des établissements et des succursales | B16: 0 | C16: 0 | F16: 0
A17: Comptes de liaison charges et produits | B17: 0 | C17: 0
A18: Comptes de liaison des sociétés en participation | B18: 0 | C18: 0
A19: TOTAL BRUT CLIENTS | B19: 39365366 | C19: 101034470 | D19: -0.61037687 | E19: 31021327 | F19: 992925 | G19: 0
A20: Dépréciations des autres créances | B20: 191029 | C20: 0 | D20: 0
A21: TOTAL NET DE DEPRECIATION | B21: 39174337 | C21: 101034470 | D21: -0.61226761 | E21: 0 | F21: 992925 | G21: 0
A22: Commentaire :
A23: · Justifier toute variation significative
A24: · Détailler les créances dont le montant est significatif
A25: · Justifier les créances anciennes
A26: · Indiquer les évènements et les circonstances qui ont conduit à la dépréciation et à la reprise
A27: · Compte transitoire ajustement spécial, indiquer le détail du compte et la durée restant pour l'apurement
A29: La créance sur le personnel correspond à des avances de salaire et au paiement de la quote part employé de frais médicaux.
A30: La créance sur l'Etat est quant elle due à une retenue BNC versée par erreur.
A31: La créance sur les Apporteurs, associés et groupe est due à la refacturation des charges communes à des sociétés liées et établies au Sénégal.

Sheet Note 8A
A1: NOTE 8 : TABLEAU D'ETALEMENT DES CHARGES IMMOBILISEES
A3: Désignation entité : | E3: Excercice clos le : | F3: =+'Note 1'!E3 -> 44926
A4: =+'Note 1'!A4 -> IAMGOLD BOTO SA | E4: Durée en mois : | F4: =+'Note 1'!E4 -> 12
A5: Numéro d'identification : | B5: =+'Note 1'!B5 -> 007768007
A7: LIBELLES | B7: Frais d'établissement | D7: Charges à répartir sur plusiers exercices | F7: Primes de remboursement des obligations
A9: Montant global à étaler au 1er janvier 2018
A10: Durée d'étalement
B11: Comptes | C11: Montants | D11: Comptes | E11: Montants | F11: Comptes | G11: Montants
A12: Exercice 2018 | B12: 60… | D12: 60… | F12: 60…
B13: 61… | D13: 61… | F13: 61…
B14: 62… | D14: 62… | F14: 62…
B15: 63… | D15: 63… | F15: 63…
B16: 64… | D16: 64… | F16: 64…
B17: 65… | D17: 65… | F17: 65…
B18: 66… | D18: 66… | F18: 66…
B19: 67… | D19: 67… | F19: 67…
B20: 68… | D20: 68… | F20: 68…
B21: 69… | D21: 69… | F21: 69…
B22: …….. | D22: …….. | F22: ……..
A23: Total exercice 2018
A24: Total exercice 2019
A25: Total exercice 2020
A26: Total exercice 2021
A27: Total exercice 2022
A28: TOTAL GENERAL

Sheet Note 8B
A1: NOTE 8B : TABLEAU D'ETALEMENT DES PROVISIONS POUR CHARGES A REPARTIR
A3: Désignation entité : | E3: Excercice clos le : | F3: =+'Note 1'!E3 -> 44926
A4: =+'Note 1'!A4 -> IAMGOLD BOTO SA | E4: Durée en mois : | F4: =+'Note 1'!E4 -> 12
A5: Numéro d'identification : | B5: =+'Note 1'!B5 -> 007768007
A7: LIBELLES | B7: Primes de remboursement des obligations
A9: Compte transitoire à solder: 4752 compte transitoire, ajustement spécial lié à la révision
A10: Montant global à étaler au 1er janvier 2018
A11: Durée d'étalement
A12: Exercice 2018 | B12: Comptes | C12: Montants
B13: 791 Reprises de procisions et dépréciations d'exploitation
A17: Total exercice 2018
A18: Total exercice 2019
A19: Total exercice 2020
A20: Total exercice 2021
A21: Total exercice 2022
A22: TOTAL GENERAL

Sheet Note 8C
A1: NOTE 8B : TABLEAU D'ETALEMENT DES PROVISIONS POUR CHARGES A REPARTIR
A3: Désignation entité : | E3: Excercice clos le : | F3: =+'Note 1'!E3 -> 44926
A4: =+'Note 1'!A4 -> IAMGOLD BOTO SA | E4: Durée en mois : | F4: =+'Note 1'!E4 -> 12
A5: Numéro d'identification : | B5: =+'Note 1'!B5 -> 007768007
A7: LIBELLES | B7: Primes de remboursement des obligations
A9: Compte transitoire à solder: 4752 compte transitoire, ajustement spécial lié à la révision
A10: Montant global à étaler au 1er janvier 2018
A11: Durée d'étalement
A12: Exercice 2018 | B12: Comptes | C12: Montants
B13: 6911 Dotations aux provisions pour risques et charges
A16: Total exercice 2018
A17: Total exercice 2019
A18: Total exercice 2020
A19: Total exercice 2021
A20: Total exercice 2022
A21: TOTAL GENERAL

Sheet Note 9
A1: NOTE 9 : TITRES DE PLACEMENT
A3: Désignation entité : | C3: Excercice clos le : | D3: =+'Note 1'!E3 -> 44926
A4: =+'Note 1'!A4 -> IAMGOLD BOTO SA | C4: Durée en mois : | D4: =+'Note 1'!E4 -> 12
A5: Numéro d'identification : | B5: =+'Note 1'!B5 -> 007768007
A7: LIBELLES | B7: ANNEE 2022 | C7: ANNEE 2021 | D7: VARIATION EN %
A9: Titres de trésor et bons de caisse à court terme
A10: Actions
A11: Obligations
A12: Bons de souscription
A13: Titres négociables hors régions
A14: Intérêts courus
A15: Autres valeurs assimilées
A16: TOTAL BRUT STOCKS ET EN COURS
A17: Dépréciations des titres
A19: TOTAL
A20: Commentaire :
A21: · Justifier toutes variations significatives
... A25: · Indiquer les évènements et les circonstances qui ont conduit à la dépréciation et à la reprise

Sheet Note 10
A1: NOTE 10 : VALEURS A ENCAISSER
A3: Désignation entité : | C3: Excercice clos le : | D3: =+'Note 1'!E3 -> 44926
A4: =+'Note 1'!A4 -> IAMGOLD BOTO SA | C4: Durée en mois : | D4: =+'Note 1'!E4 -> 12
A5: Numéro d'identification : | B5: =+'Note 1'!B5 -> 007768007
A7: LIBELLES | B7: ANNEE 2022 | C7: ANNEE 2021 | D7: VARIATION EN %
A9: Effets à encaisser
A10: Effets à l'encaissement
A11: Chèques à encaisser
A12: Chèques à l'encaissement
A13: Cartes de crédit à encaisser
A14: Autres valeurs à encaisser
A15: TOTAL BRUT VALEURS A ENCAISSER
A16: Dépréciations des valeurs à encaisser
A18: TOTAL
A19: Commentaire :
A20: · Commenter toute variation significative
A21: · Indiquer les évènements et les circonstances qui ont conduit à la dépréciation et à la reprise

Sheet Note 11
A1: NOTE 11 : DISPONIBILITES
A3: Désignation entité : | C3: Excercice clos le : | D3: =+'Note 1'!E3 -> 44926
A4: =+'Note 1'!A4 -> IAMGOLD BOTO SA | C4: Durée en mois : | D4: =+'Note 1'!E4 -> 12
A5: Numéro d'identification : | B5: =+'Note 1'!B5 -> 007768007
A7: LIBELLES | B7: ANNEE 2022 | C7: ANNEE 2021 | D7: VARIATION EN %
A9: Banques locales | B9: 810329958 | C9: 1672364151 | D9: -0.51545843
A10: Banques autres états région | B10: 0 | C10: 0 | D10: 0
A11: Banques, dépôt à terme | B11: 0 | C11: 0 | D11: 0
A12: Autres banques | B12: 0 | C12: 0 | D12: 0
A13: Banques, intérêts courus | B13: 0 | C13: 0 | D13: 0
A14: Chèques postaux | B14: 0 | C14: 0 | D14: 0
A15: Autres établissements financiers | B15: 0 | C15: 0 | D15: 0
A16: Etablissements financiers intérêts courus | B16: 0 | C16: 0 | D16: 0
A17: Intruments de trésorerie | B17: 0 | C17: 0 | D17: 0
A18: Caisse | B18: 4349650 | C18: 5579720 | D18: -0.22045371
A19: Casse électronique mobile | B19: 0 | C19: 0 | D19: 0
A20: Régies d'avances et virements accréditifs | B20: 0 | C20: 0 | D20: 0
... A24: TOTAL | B24: 814679608 | C24: 1677943871 | D24: -0.51447744
A25: Commentaire :
A26: · Indiquer la date de rapprochement des comptes bancaires
A27: · Indiquer la date d'inventaire de la caisse et des instruments de monnaie électronique
A28: · Justifier toute variation significative
A29: · Détailler les instruments de monnaie électronique si le montant est significatif
A30: · Indiquer les évènements et les circonstances qui ont conduit à la dépréciation et à la reprise
A32: NB : Banques et intérêts courus et Etablissement financiers intérêts courus figurent dans cette rubrique
A33: en négatif si le compte principal est débiteur
A35: Le solde du compte de banque s'explique par les avances de fonds reçues de l'associé principal dans le cadre de la convention de prêt qui nous lie et dont le but est de
A36: soutenir les activités de la société dans cette phase où la production n'a pas encore démarrée.La diminution notée au niveau du solde est principalement due à la baisse notable des
A37: activités en 2022.

Sheet Note 12
A1: NOTE 12 : ECARTS DE CONVERSION
A3: Désignation entité : | E3: Excercice clos le : | F3: =+'Note 1'!E3 -> 44926
A4: =+'Note 1'!A4 -> IAMGOLD BOTO SA | E4: Durée en mois : | F4: =+'Note 1'!E4 -> 12
A5: Numéro d'identification : | B5: =+'Note 1'!B5 -> 007768007
A7: LIBELLES | B7: Devises | C7: Montant en devises | E7: Cours UML année acquisition | F7: Cours UML 31/12 | G7: Variation en valeur absolue
A9: Ecarts de conversion actif : Détailler les créances et dettes concernées
B10: USD | C10: 68257289 | E10: 38999072485 | F10: 4.1868871e+10 | G10: 2.8697984e+09
B11: USD | C11: 35923.64 | E11: 21844453 | F11: 22035482 | G11: 191028.74
A12: Ecarts de conversion passif : Détailler les créances et dettes concernées
B13: USD | C13: 822750.95 | E13: 507654812 | F13: 5.0467362e+08 | G13: 2981189.3
A15: Commentaire :
A16: · Faire un commentaire
A20: TRANSFERTS DE CHARGES
A22: LIBELLES | B22: ANNEE N | D22: ANNEE N-1 | F22: VARIATION EN %
A24: Transferts de charges d'exploitation : Détailler la nature des charges transférées
A25: Charges communes | B25: 46112334 | D25: 42493272 | F25: 0.09
A26: Paiement pour compte | B26: 0 | D26: 95178668 | F26: -1
A27: Transferts de charges financières : Détailler la nature des charges transférées
A30: TOTAL
A31: Commentaire :
A32: · Faire un commentaire

Sheet Note 13
A1: NOTE 13 : CAPITAL (VALEUR NOMINALE DES ACTIONS OU PARTS)
A3: Désignation entité : | E3: Excercice clos le : | F3: =+'Note 1'!E3 -> 44926
A4: =+'Note 1'!A4 -> IAMGOLD BOTO SA | E4: Durée en mois : | F4: =+'Note 1'!E4 -> 12
A5: Numéro d'identification : | B5: =+'Note 1'!B5 -> 007768007
E7: Valeur nominale des actions ou parts : | G7: 6765
A8: NOMS ET PRENOMS | B8: Nationalité | C8: Nature des actions ou parts (ordinaires ou préférences) | E8: Nombre | F8: Montant total | G8: Cessions ou remboursements en cours d'exercice
A10: IAMGOLD CORPORATION | B10: CANADIENNE | C10: Actions | E10: 900 | F10: 9000000 | G10: 0
A11: ETAT DU SENEGAL | B11: SENEGALAISE | E11: 100 | F11: 1000000
A18: Apporteurs, capital non appelé
E19: TOTAL | F19: 10000000
A20: Commentaire :
A21: · Indiquer si possible le montant du capital à la constitution
A22: · Indiquer si possible les dates des AGE et le montant du capital augmenté en cas d'augmentation de capital
A23: · Indiquer si possible les dates des AGE et le montant du capital diminué en cas de réduction de capital
A24: · Indiquer les avantages accordés aux actions de préférence
A25: · Apporteurs, capital non appelé : indiquer le délai restant pour appeler le capital
A27: En fin 2022 des négociations ont été entamées en vue de la cession des parts de l'associé principal à savoir Iamgold Corporation. Ce changement devrait intervenir
A28: courant 2023. Le Minstère des Mines ayant déjà donné son accord.

Sheet Note 14
A1: NOTE 14 : PRIMES ET RESERVES
A3: Désignation entité : | E3: Excercice clos le : | F3: =+'Note 1'!E3 -> 44926
A4: =+'Note 1'!A4 -> IAMGOLD BOTO SA | E4: Durée en mois : | F4: =+'Note 1'!E4 -> 12
A5: Numéro d'identification : | B5: =+'Note 1'!B5 -> 007768007
A7: LIBELLES | B7: ANNEE 2022 | D7: ANNEE 2021 | F7: VARIATION EN VALEUR ABSOLUE
A9: Prime d'apport
A10: Primes d'émission
A11: Prime de fusion
A12: Primes de conversion
A13: Autres primes
A15: TOTAL PRIMES
A16: Réserves légales
A17: Réserves statutaires
A18: Réserves de plus-values nettes à long terme
A19: Réserves d'attribution gratuite d'actions au personnel salarié et aux dirigeants
A20: Autres réserves réglementées
A22: TOTAL RESERVES INDISPONIBLES
... A31: · Indiquer la date de l'AGO qui justifie la variation des réserves et du report à nouveau

Sheet Note 15A
A1: NOTE 15A : SUBVENTIONS ET PROVISIONS REGLEMENTEES
A3: Désignation entité : | E3: Excercice clos le : | F3: =+'Note 1'!E3 -> 44926
A4: =+'Note 1'!A4 -> IAMGOLD BOTO SA | E4: Durée en mois : | F4: =+'Note 1'!E4 -> 12
A5: Numéro d'identification : | B5: =+'Note 1'!B5 -> 007768007
A7: LIBELLES | B7: NOTE | C7: Année 2022 | D7: ANNEE 2021 | E7: Variation en valeur absolue | F7: Variation en % | G7: Régime fiscal | H7: Échéances
A9: Etat
A10: Régions
A11: Départements
A12: Communes et collectivités publiques décentralisées
A13: Entités publiques ou mixtes
A14: Entités et organismes privés
A15: Organismes internationaux
A16: Autres
A17: TOTAL SUBVENTIONS
A18: Amortissements dérogatoires
A19: Plus-values de cession à réinvestir
A20: Provision spéciale de réévaluation | B20: 3E
A21: Provisions réglementées relatives aux immobilisations
A22: Provisions réglementées relatives aux stocks
A23: Provisions pour investissement
A24: Autres provisions et fonds réglementés
A25: TOTAL PROVISIONS REGLEMENTEES
A27: TOTAL SUBVENTIONS ET PROVISIONS REGLEMENTEES
A28: Commentaire :
A29: Indiquer pour la subvention la date d'octroi, la nature, les obligations éventuelles.
A30: Pour les provisions réglementées, indiquer le texte de référence, les obligation.
A31: Commenter toute variation significative.

Sheet Note 15B
A1: NOTE 15B : AUTRES FONDS PROPRES(1)
A3: Désignation entité : | E3: Excercice clos le : | F3: =+'Note 1'!E3 -> 44926
A4: =+'Note 1'!A4 -> IAMGOLD BOTO SA | E4: Durée en mois : | F4: =+'Note 1'!E4 -> 12
A5: Numéro d'identification : | B5: =+'Note 1'!B5 -> 007768007
A7: LIBELLES | B7: NOTE | C7: Année 2022 | D7: ANNEE 2021 | E7: Variation en valeur absolue | F7: Variation en % | G7: Échéances
A9: Titres de participation
A10: Avances conditionnées
A11: Titres subordonnés à durée indéterminée (TSDI)
A12: Obligations remboursables en actions (ORA)
A13: Autres
A14: TOTAL SUBVENTIONS ET PROVISIONS REGLEMENTEES
A15: (1) : Le cas échéant, une rubrique "Autres fonds propre" (montant des émissions de titres participatifs,
A16: avances conditionnées,…) sur une ligne séparée est intercalée entre les rubriques
A17: "TOTAL CAPTAUX PROPRES ET RESSOURCES ASSIMILEES" et "EMPRUNTS ET DETTES FINANCIERES" si le
A18: montant des autres fonds propres est significatif.
A19: Commentaire :
A20: · Justifier l'inscription de ces dettes dans une rubrique spécifique du passif du bilan "autres fonds
... A23: · Commenter toute variation significative

Sheet Note 16A
A1: NOTE 16A : DETTES FINANCIERES ET RESSOURCES ASSIMILEES
A3: Désignation entité : | E3: Excercice clos le : | F3: =+'Note 1'!E3 -> 44926
A4: =+'Note 1'!A4 -> IAMGOLD BOTO SA | D4: Durée en mois : | F4: =+'Note 1'!E4 -> 12
A5: Numéro d'identification : | B5: =+'Note 1'!B5 -> 007768007
A7: LIBELLES | B7: Année 202 | C7: ANNEE 2021 | D7: Variation en valeur absolue | E7: Variation en % | F7: Dettes à un an au plus | G7: Dettes à plus d'un an et à deux ans au plus | H7: Dettes à plus de deux ans
A9: Emprunts obligataires
A10: Emprunts et dettes auprès des établissements de crédit
A11: Avances reçues de l'Etat
A12: Avances reçues et comptes courants bloqués
A13: Dépôts et cautionnements reçus
A14: Intérêts courus
A15: Avances assorties de conditions particulières
A16: Autres emprunts et dettes | B16: 85897310394 | C16: 28095007190 | D16: 57802303204 | E16: 2.057387
A17: Dettes liées à des participations
A18: Comptes permanents bloqués des établissements et succursales
A19: TOTAL EMPRUNTS ET DETTES FINANCIERES | B19: 85897310394 | C19: 28095007190 | D19: 57802303204 | E19: 2.057387
A20: Crédit bail immobilier
A21: Crédit bail mobilier
A22: Location vente
A23: Intérêts courus
A24: Autres dettes de location acquisition
A25: TOTAL DETTES DE LOCATION ACQUISITION
A26: Provisions pour litiges
A27: Provisions pour garantie donnés aux clients
A28: Provisions pour pertes sur marchés à achèvement futur
A29: Provisions pour pertes de change | B29: 2869798422 | C29: 0 | D29: 2869798422 | E29: 0
A30: Provisions pour impôts | B30: 0 | C30: 0 | D30: 0 | E30: 0
A31: Provisions pour pensions et obligations assimilées | B31: 53480774 | C31: 42172294 | D31: 11308480 | E31: 0.26814951
A32: Actif du régime de retraite
A33: Provisions pour restructuration
A34: Provisions pour amendes et pénalités
A35: Provisions de propre assureur
A36: Provisions pour démantèlement et remise en état
A37: Provisions de droits à déduction
A38: Autres provisions
A39: TOTAL PROVISIONS POUR RISQUES ET CHARGES | B39: 2923279196 | C39: 42172294 | D39: 2881106902 | E39: 68.317529
A40: Commentaire :
A41: Pour chaque emprunt et dette de location acquisition : mentionner la date d'octroi, le nom de l'organisme
A42: financier, le montant initial de l'emprunt ou de la dette, la durée du crédit, les garanties donnéee par la société.
A43: Indiquer les évènements et circonstances qui ont conduit à la provision et à la reprise.
A44: Pour les pensions et obligations de retraite indiquer :
A45: · la méthode d'évaluation retenue ;
A46: · pour les actifs du régime, indiquer le nom de la compagnie d'assurance ou du fonds de pension, le descriptif
A47: de la convention signée avec l'orgganisme, la périodicité des versements, le montant et la durée de la convention ;
A48: · indication de la valeur retenue pour les principales hypothèses actuarielles à la date de clôture et leur base de
A49: détermination.
A51: Une convention de prêt avec le principal associé, IAMGOLD CORPORATION, a été signée dans le but de financer les activités de la société, de combler ses besoins en fonds de roulement
A52: et aussi à des fins générales de l'entreprise. Le déboursement du prêt se fait mensuellement sous forme d'avance de fonds. Le montant total de l'emprunt est estimé à 87 Millions USD et la durée de
... A57: au niveau des Emrpunts.

Sheet Note 16B
A1: NOTE 16B : ENGAGEMENTS DE RETRAITE ET AVANTAGES ASSIMILES (METHODE ACTURIELLE)
A3: Désignation entité : | D3: Excercice clos le : | E3: =+'Note 1'!E3 -> 44926
A4: =+'Note 1'!A4 -> IAMGOLD BOTO SA | D4: Durée en mois : | E4: =+'Note 1'!E4 -> 12
A5: Numéro d'identification : | B5: =+'Note 1'!B5 -> 007768007
A7: HYPOTHESES ACTUARIELLES
A8: LIBELLES | B8: ANNEE 2022 | D8: ANNEE 2021
A9: Taux d'augmentation des salaires
A10: Taux d'actualisation
A11: Taux d'inflation
A12: Probabilité d'être présent dans l'entité à la date de départ à la retraite (expérience passée)
A13: Probabilité d'être en vie à l'âge de départ à la retraite (table de mortalité)
A14: Taux de rendement effectif des actifs du régime
A15: Commentaire :
A16: · Commenter les variations d'hypothèses actuarielles utilisées pour le calcul des
A17: engagements de retraite et avantages assimilés.
A20: VARIATION DE LA VALEUR DE L'ENGAGEMENT DE RETRAITE AU COURS DE L'EXERCICE
A21: LIBELLES | B21: ANNEE 2022 | D21: ANNEE 2021
A22: OBLIGATION AU TITRE DES ENGAGEMENTS DE RETRAITE A L'OUVERTURE
A23: Coût des services rendus aucours de l'exercice
A24: Coût financier
A25: Pertes actuarielles / (gain)
A26: Prestations payées au cours de l'exercice
A27: Coût des services passés
A28: OBLIGATION AU TITRE DES ENGAGEMENTS DE RETRAITE A L'OUVERTURE
A29: Commentaire :
A30: · indiquer le montant de la charge par nature comptabilisée au cours de l'exercice.
A33: ANALYSES DE SENSIBILITE DES HYPOTHESES ACTUARIELLES
A34: LIBELLES | C34: ANNEE 2022 | E34: ANNEE 2021
C35: Augmentation | D35: Diminution | E35: Augmentation | F35: Diminution
A36: Taux d'actualisation (variation de …%)
A37: Taux de progression des salaires (variation de …%)
A38: Taux de départ du personnel (variation de …%)
A39: Commentaire :
A40: · Indiquer l'impact des variations obtenues sur lemontant des engagements de retraite.

Sheet Note 16B bis
A1: NOTE 16B bis : ENGAGEMENTS DE RETRAITE ET AVANTAGES ASSIMILES (METHODE ACTURIELLE)
A3: Désignation entité : | C3: Excercice clos le : = | D3: =+'Note 1'!E3 -> 44926
A4: =+'Note 1'!A4 -> IAMGOLD BOTO SA | C4: Durée en mois : =
A5: Numéro d'identification : | D5: =+'Note 1'!E4 -> 12
B6: =+'Note 1'!B5 -> 007768007
A8: ACTIF/PASSIF NET COMPTABILISE AU TITRE DES REGIMES FINANCES
A9: LIBELLES | B9: ANNEE 2022 | C9: ANNEE 2021
A10: Valeur actuelle de l'obligation résultant de régimes financés
A11: Valeur actuelle des actifs affectés aux plans de retraite
A12: Excédent / Déficit de régime
A13: Commentaire :
A14: · indiquer le montant comptabilisé au passif (ou actif) à la clôture de l'exercice.
A17: VALEUR ACTUELLE DES ACTIFS DU REGIME
A18: LIBELLES | B18: ANNEE 2022
B19: Rendement attendu | C19: Juste valeur des actifs | D19: Rendement attendu | E19: Juste valeur des actifs
A20: Actions
A21: Obligations
A22: Autres
A23: TOTAL
A24: Commentaire :
A25: · Expliquer comment les taux de rendement par catégorie d'actifs et global ont été déterminés.
A26: · Indiquer le montant des rendements réels des actifs affectés aux plans en N et N-1.

Sheet Note 16C
A1: NOTE 16C : ACTIFS ET PASSIFS EVENTUELS
A3: Désignation entité : | C3: Excercice clos le : | D3: =+'Note 1'!E3 -> 44926
A4: =+'Note 1'!A4 -> IAMGOLD BOTO SA | C4: Durée en mois : | D4: =+'Note 1'!E4 -> 12
A5: Numéro d'identification : | B5: =+'Note 1'!B5 -> 007768007
A8: LIBELLES | C8: ANNEE 2022 | D8: ANNEE 2021
A9: ACTIF EVENTUEL
A10: Litiges
A11: …………………………..
A12: …………………………..
A13: …………………………..
A14: …………………………..
A15: PASSIF EVENTUEL
A16: Litiges
A17: …………………………..
A18: …………………………..
A19: …………………………..
A20: …………………………..
... A23: les encaissements / décaissements sont attendus et les éventuels remboursements à percevoir.

Sheet Note 17
A1: NOTE 17 : FOURNISSEURS D'EXPLOITATION
A3: Désignation entité : | F3: Excercice clos le : | G3: =+'Note 1'!E3 -> 44926
A4: =+'Note 1'!A4 -> IAMGOLD BOTO SA | F4: Durée en mois : | G4: =+'Note 1'!E4 -> 12
A5: Numéro d'identification : | B5: =+'Note 1'!B5 -> 007768007
A7: LIBELLES | B7: ANNEE N | C7: ANNEE N-1 | D7: Variation en valeur absolue | E7: Variation en % | F7: Dettes à un an au plus | G7: Dettes à plus d'un an et à deux ans au plus | H7: Dettes à plus de deux ans
A9: Fournisseurs (hors groupe) | B9: 97327655 | C9: 103970309 | D9: -2072929 | E9: -0.019937702 | F9: 101897380
A10: Fournisseurs sous-traitants
A11: Fournisseurs réserve de propriété
A12: Fournisseurs retenues de garantie | B12: 4569725 | C12: 1825000 | D12: 2744725 | E12: =IF(C12<>0,(B12-C12)/C12,0) -> 1.5039589
A13: Fournisseurs effets à payer (hors groupe)
A14: Fournisseurs, dettes et effets à payer groupe
A15: Fournisseurs acquisition courantes immobilisation
A16: Fournisseurs, factures non parvenues (hors groupe) | B16: 232636221 | C16: 1217444786 | D16: -984808565 | E16: -0.80891436 | F16: 232636221
A17: Fournisseurs, factures non parvenues (groupe)
A18: TOTAL FOURNISSEURS | B18: 334533601 | C18: 1321415095 | D18: -986881494 | E18: -0.74683686 | F18: 334533601
A19: Fournisseurs, avances et acomptes (hors groupe)
A20: Fournisseurs, avances et acomptes (groupe)
A21: Autres fournisseurs débiteurs
A22: TOTAL FOURNISSEURS DEBITEURS
A23: Commentaire :
A24: · Commenter toutes variations significatives
A25: · Indiquer pour les dettes du groupe, le nom de la société du groupe et le % de titres détenues
A26: · Commenter toutes les dettes anciennes
A28: La dette fournisseur a baissé de façon globale grâce aux paiements réguliers effectués mais aussi du fait de la baisse des activités en 2022.

Sheet Note 18
A1: NOTE 18 : DETTES FISCALES ET SOCIALES
A3: Désignation entité : | F3: Excercice clos le : | G3: =+'Note 1'!E3 -> 44926
A4: =+'Note 1'!A4 -> IAMGOLD BOTO SA | F4: Durée en mois : | G4: =+'Note 1'!E4 -> 12
A5: Numéro d'identification : | B5: =+'Note 1'!B5 -> 007768007
A7: LIBELLES | B7: ANNEE 2022 | C7: ANNEE 2021 | D7: Variation en valeur absolue | E7: Variation en % | F7: Dettes à un an au plus | G7: Dettes à plus d'un an et à deux ans au plus | H7: Dettes à plus de deux ans
A9: Personnel congés à payer
A10: Autre personnel | B10: 193715 | C10: 0 | D10: 193715 | E10: 0 | F10: 0
A11: Autres personnel | B11: 142921564 | C11: 15222148 | D11: 127699416 | E11: 8.3890536 | F11: 142921564
A12: Caisse de sécurité sociale | B12: 331437 | C12: 243581 | D12: 87856 | E12: 0.36068495 | F12: 331437
A13: Caisse de retraite | B13: 4141997 | C13: 3705698 | D13: 436299 | E13: 0.11773733 | F13: 4141997
A14: Mutuelle de santé | B14: 460000 | C14: 372104 | D14: 87896 | E14: 0.23621353 | F14: 460000
A15: Assurance retraite
A16: Autres charges sociales à payer
A17: Autres organismes sociaux
A18: TOTAL FOURNISSEURS | B18: 148048713 | C18: 19543531 | D18: 128505182 | E18: 6.5753308 | F18: 147854998
A19: Etat, impôts sur les bénéfices
A20: Etat, impôts et taxes
A21: Etat, TVA
A22: Etat, impôts retenus à la source | B22: 102161135 | C22: 102857489 | D22: -696354 | E22: -0.0067700856 | F22: 102161135
A23: Autres dettes Etat | B23: 4479831 | C23: 0 | D23: 4479831 | E23: 0 | F23: 4479831
A24: TOTAL FOURNISSEURS | B24: 106640966 | C24: 102857489 | D24: 3783477 | E24: 0.03678368 | F24: 106640966
A25: TOTAL FOURNISSEURS DEBITEURS | B25: 254689679 | C25: 122401020 | D25: 132288659 | E25: 1.0807807 | F25: 254495964
A26: Commentaire :
A27: · Commenter toutes variations significatives
A28: · Commenter toutes les dettes anciennes
A30: Les dettes fiscales correspondent aux dettes issues de l'exploitation normale de l'entité. L'augmentation du poste est due au montant provisionné des bonus de 2022 à payer sur 2023.

Sheet Note 19
A1: NOTE 19 : AUTRES DETTES ET PROVISIONS POUR RISQUES A COURT TERME
A3: Désignation entité : | F3: Excercice clos le : | G3: =+'Note 1'!E3 -> 44926
A4: =+'Note 1'!A4 -> IAMGOLD BOTO SA | F4: Durée en mois : | G4: =+'Note 1'!E4 -> 12
A5: Numéro d'identification : | B5: =+'Note 1'!B5 -> 007768007
A7: LIBELLES | B7: ANNEE 2022 | C7: ANNEE 2021 | D7: Variation en valeur absolue | E7: Variation en % | F7: Dettes à un an au plus | G7: Dettes à plus d'un an et à deux ans au plus | H7: Dettes à plus de deux ans
A9: Organismes sociaux
A10: Apporteurs, opérations sur le capital
A11: Associés, compte courant
A12: Associés, dividendes à payer
A13: Groupe, comptes courants | B13: 648414728 | C13: 4731343048 | D13: -4082928320 | E13: -0.86295335
A14: Autres dettes associés
A15: TOTAL DETTES ASSOCIES | B15: 648414728 | C15: 4731343048 | D15: -4082928320 | E15: -0.86295335
A16: Créditeurs divers | B16: 3608653 | C16: 124887368 | D16: -121278715 | E16: -0.97110474
A17: Obligataires
A18: Rémunérations d'administrateurs
A19: Compte du factor
A20: Versements restant à effectuer sur titres de placements non libérés
A21: Intermédiaires-opérations faites pour comptes de tiers
A22: Compte transitoire ajustement spécial lié à la révision du SYSCOHADA
A23: Produits constatés d’avance
A24: Autres créditeur divers | B24: 0 | C24: 356805 | D24: -356805 | E24: -1
A25: TOTAL CREDITEURS DIVERS | B25: 3608653 | C25: 125244173 | D25: -121635520 | E25: -0.97118706
A26: Comptes permanents non bloqués des établissements et des succursales
A27: Comptes de liaison charges et produits
A28: Comptes de liaison des sociétés en participation
A29: TOTAL COMPTES DE LIAISON
A31: TOTAL AUTRES DETTES
A33: Provisions pour risques à court terme (voir note 28)
A34: Commentaire :
A35: · Commenter toutes variations significatives
A36: · Indiquer le taux de rémunération si compte courant rémunéré
A37: · Commenter les dettes anciennes
A38: · Compte transitoire ajustement spécial, indiquer le détail du compte et la durée restant pour l'apurement.
A40: Cette baisse est relative aux remboursements du compte courant.

Sheet Note 20
A1: NOTE 20 : BANQUES, CREDIT D'ESCOMPTE ET TRESORERIE
A3: Désignation entité : | C3: Excercice clos le : | D3: =+'Note 1'!E3 -> 44926
A4: =+'Note 1'!A4 -> IAMGOLD BOTO SA | C4: Durée en mois : | D4: =+'Note 1'!E4 -> 12
A5: Numéro d'identification : | B5: =+'Note 1'!B5 -> 007768007
A7: LIBELLES | B7: ANNEE N | C7: ANNEE N-1 | D7: VARIATION EN %
A9: Escomptes de crédit de campagne
A10: Escomptes de crédit ordinaires
A11: TOTAL BANQUES, CREDITS D'ESCOMPTE ET DE TRESORERIE
A12: Banques locales
A13: Banques autres états régions
A14: Auttres banques
A15: Banques intérêts courus
A16: Crédits de trésorerie
A17: TOTAL BANQUES, CREDITS DE TRESORERIE
A19: TOTAL
A20: Commentaire :
A21: · Commenter toute variation significative
... A24: NB : Banques et intérêts courus figure dans cette rubrique en négatif si le compte principal attaché est créditeur.

Sheet Note 21
A1: NOTE 21 : CHIFFRE D'AFFAIRES ET AUTRES PRODUITS
A3: Désignation entité : | C3: Excercice clos le : | D3: =+'Note 1'!E3 -> 44926
A4: =+'Note 1'!A4 -> IAMGOLD BOTO SA | C4: Durée en mois : | D4: =+'Note 1'!E4 -> 12
A5: Numéro d'identification : | B5: =+'Note 1'!B5 -> 007768007
A7: LIBELLES | B7: ANNEE 2022 | C7: ANNEE 2021 | D7: VARIATION EN %
A9: Ventes dans l'Etat partie
A10: Ventes dans les autres Etats parties de la région
A11: Ventes hors région
A12: Ventes Groupe
A13: Ventes sur internet
A14: Rabais, remises, ristournes accordés
A15: TOTAL VENTES MARCHANDISES
A16: Ventes dans l'Etat partie
A17: Ventes dans les autres Etats parties de la région
A18: Ventes hors région
A19: Ventes Groupe
A20: Ventes sur internet
... A33: TOTAL CHIFFRE D'AFFAIRES
A35: Production immobilisée | B35: 9236283675 | C35: 9652980330 | D35: -0.043167669
A36: Subventions d'exploitation | B36: 0 | C36: 0 | D36: 0
A37: Autres produits | B37: 2861563 | C37: 4846702 | D37: -0.40958553
A38: TOTAL AUTRES PRODUITS | B38: 9239145238 | C38: 9657827032 | D38: -0.043351552
A40: TOTAL | B40: 9239145238 | C40: 9657827032 | D40: -0.043351552
A41: Commentaire :
A42: · Justifier toute variation significative
A43: · Détailler, produits intermédiaires, produits résiduels, produits accessoires, autres produits si significatifs.
A45: Ce montant correspond à la contrepartie de la capitaliation des dépenses liées au développement du projet. La dimunition notée sur les différents postes est fortement
A46: liée à la baisse d'activité notée en 2022.

Sheet Note 22
A1: NOTE 22 : ACHATS
A3: Désignation entité : | C3: Excercice clos le : | D3: =+'Note 1'!E3 -> 44926
A4: =+'Note 1'!A4 -> IAMGOLD BOTO SA | C4: Durée en mois : | D4: =+'Note 1'!E4 -> 12
A5: Numéro d'identification : | B5: =+'Note 1'!B5 -> 007768007
A7: LIBELLES | B7: ANNEE 2022 | C7: ANNEE 2021 | D7: VARIATION EN %
A9: Ventes dans l'Etat partie
A10: Ventes dans les autres Etats parties de la région
A11: Ventes hors région
A12: Ventes Groupe
A13: Frais sur achats (en cas d'option)
A14: Rabais, remises, ristournes accordés
A15: TOTAL ACHATS DE MARCHANDISES
A16: Ventes dans l'Etat partie
A17: Ventes dans les autres Etats parties de la région
A18: Ventes hors région
A19: Ventes Groupe
A20: Frais sur achats (en cas d'option)
... A23: Matières consommables
A24: Matières combustibles | B24: 281706176 | C24: 580059377 | D24: -0.51434941
A25: Produits d'entretien | B25: 0 | C25: 0 | D25: 0
A26: Fournitures d'atelier, d'usine et de magasin | B26: 0 | C26: 0 | D26: 0
A27: Eau | B27: 563183 | C27: 653722 | D27: -0.13849771
A28: Electricité | B28: 11361000 | C28: 9529600 | D28: 0.19218015
A29: Autres énergies | B29: 3754963 | C29: 93509266 | D29: -0.95984395
A30: Fournitures d'entretien | B30: 4062041 | C30: 5209375 | D30: -0.22024408
A31: Fourniture de bureau | B31: 2223200 | C31: 11114472 | D31: -0.7999725
A32: Petit matériel et outillages | B32: 25517259 | C32: 46004951 | D32: -0.44533668
A33: Achats d'études, prestations de services, de travaux matériel et équipements | B33: 19964648 | C33: 227500 | D33: 86.756695
A34: Achats d'emballages
A35: Frais sur achats (en cas d'option)
A36: Remise, rabais, remises et ristournes
A37: TOTAL AUTRES ACHATS | B37: 349152470 | C37: 746308263 | D37: -0.53216052
A38: Commentaire :
A39: · Commenter toute variation significative
A41: La baisse des Achats est liée à la sous activité notée en 2022.

Sheet Note 23
A1: NOTE 23 : TRANSPORTS
A3: Désignation entité : | C3: Excercice clos le : | D3: =+'Note 1'!E3 -> 44926
A4: =+'Note 1'!A4 -> IAMGOLD BOTO SA | C4: Durée en mois : | D4: =+'Note 1'!E4 -> 12
A5: Numéro d'identification : | B5: =+'Note 1'!B5 -> 007768007
A7: LIBELLES | B7: ANNEE 2022 | C7: ANNEE 2021 | D7: VARIATION EN %
A9: Transports sur ventes
A10: Transports pour le compte de tiers
A11: Transport du personnel
A12: Transport de plis | B12: 3178728 | C12: 2275166 | D12: 0.39714113
A13: Voyages et déplacements | B13: 143093125 | C13: 183006668 | D13: -0.21809885
A14: Transport entre établissement ou chantier
A15: Transport administratif
A16: Rabais remises et ristournes obtenus
A17: TOTAL TRANSPORTS | B17: 146271853 | C17: 185281834 | D17: -0.21054401
A18: Commentaire :
A19: · Commenter toute variation significative

Sheet Note 24
A1: NOTE 24 : SERVICES EXTERIEURS
A3: Désignation entité : | C3: Excercice clos le : | D3: =+'Note 1'!E3 -> 44926
A4: =+'Note 1'!A4 -> IAMGOLD BOTO SA | C4: Durée en mois : | D4: =+'Note 1'!E4 -> 12
A5: Numéro d'identification : | B5: =+'Note 1'!B5 -> 007768007
A7: LIBELLES | B7: ANNEE 2022 | C7: ANNEE 2021 | D7: VARIATION EN %
A9: Sous-traitance générale | B9: 1239507028 | C9: 1719353508 | D9: -0.27908541
A10: Locations et charges locatives | B10: 117862473 | C10: 56607263 | D10: 1.0821087
A11: Redevances de location acquisition
A12: Entretien, réparations et maintenance | B12: 17216462 | C12: 18622609 | D12: -0.075507519
A13: Primes d'assurance | B13: 44675612 | C13: 31128977 | D13: 0.43517765
A14: Etudes, recherches et documentation | B14: 0 | C14: 77000 | D14: -1
A15: Publicité, publications, relations publiques | B15: 44085880 | C15: 4730698 | D15: 8.3191068
A16: Frais de télécommunications | B16: 33682617 | C16: 39388211 | D16: -0.14485537
A17: Frais bancaires | B17: 63486915 | C17: 33511781 | D17: 0.89446556
A18: Rémunérations d'intermédiaires et de conseils | B18: 1884669473 | C18: 4770139718 | D18: -0.60490267
A19: Frais de formation du personnel | B19: 5445406 | C19: 44251671 | D19: -0.87694462
A20: Redevances pour brevets, licences, logiciels, concession et droits similaires | B20: 58743392 | C20: 60444910 | D20: -0.028149897
A21: Cotisations | B21: 2347605 | C21: 152765 | D21: 14.367427
A22: Redevances versées au concédant (concession service public)
A23: Rémunération de personnel extérieur à l’entité
A24: Autres charges externes | B24: 25053758 | C24: 50621450 | D24: -0.50507625
A25: TOTAL SERVICES EXTERIEURS | B25: 3536776621 | C25: 6829030561 | D25: -0.48201238
A26: Commentaire :
A27: · Commenter toute variation significative
A29: De façon globale nous notons une forte baisse sur ce poste. Celle-ci confirme la baisse d'activité constatée en 2022.

Sheet Note 25
A1: NOTE 25 : IMPOTS ET TAXES
A3: Désignation entité : | C3: Excercice clos le : | D3: =+'Note 1'!E3 -> 44926
A4: =+'Note 1'!A4 -> IAMGOLD BOTO SA | C4: Durée en mois : | D4: =+'Note 1'!E4 -> 12
A5: Numéro d'identification : | B5: =+'Note 1'!B5 -> 007768007
A7: LIBELLES | B7: ANNEE 2022 | C7: ANNEE 2021 | D7: VARIATION EN %
A9: Impôts et taxes directs | B9: 7774927 | C9: 5929820 | D9: 0.31115734
A10: Impôts et taxes indirects | B10: 0 | C10: 0 | D10: 0
A11: Droits d'enregistrement | B11: 0 | C11: 0 | D11: 0
A12: Pénalités et amendes fiscales | B12: 0 | C12: 0 | D12: 0
A13: Autres impôts et taxes | B13: 5432749 | C13: 3732011 | D13: 0.45571623
A15: TOTAL IMPOTS ET TAXES | B15: 13207676 | C15: 9661831 | D15: 0.36699514
A16: Commentaire :
A17: · Commenter toute variation significative
A18: · Détailler les pénalités et amendes et indiquer la cause

Sheet Note 26
A1: NOTE 26 : AUTRES CHARGES
A3: Désignation entité : | C3: Excercice clos le : | D3: =+'Note 1'!E3 -> 44926
A4: =+'Note 1'!A4 -> IAMGOLD BOTO SA | C4: Durée en mois : | D4: =+'Note 1'!E4 -> 12
A5: Numéro d'identification : | B5: =+'Note 1'!B5 -> 007768007
A7: LIBELLES | B7: ANNEE 2022 | C7: ANNEE 2021 | D7: VARIATION EN %
A9: Pertes sur créances clients
A10: Pertes sur autres débiteurs
A11: Quote-part de résultat sur opérations faites en commun
A12: Valeur nette comptable des cessions courantes d'immobilisations
A13: Indemnités de fonction et autres rémunérations d'administrateurs | B13: 8000000 | C13: 10938400 | D13: -0.26863161
A14: Dons et mécénat | B14: 649943094 | C14: 349202654 | D14: 0.86122037
A15: Autres charges diverses | B15: 128810823 | C15: 117373662 | D15: 0.097442312
A16: Charges pour provisions et provisons pour risques à court terme d'exploitation (voir note 28) | B16: 191029 | C16: 0
A18: TOTAL AUTRES CHARGES | B18: 786944946 | C18: 477514716 | D18: 0.64800145
A19: Commentaire :
A20: · Commenter toute variation significative
A21: · Indiquer la date du PV de l'AGO ou du CA qui fixe les rémunérationsdes administrateurs
A22: · Indiquer les organismes bénéficiaires des dons
A24: Ce poste a connu une nette augmentation cette année car beaucoup de projets communautaires ont été bouclés courant 2022. Cette évolution s'explique également par le
A25: démarrage du projet de reconstruction du village devant abriter une partie de la population impactée par le projet.

Sheet Note 27A
A1: NOTE 27A : CHARGES DE PERSONNEL
A3: Désignation entité : | C3: Excercice clos le : | D3: =+'Note 1'!E3 -> 44926
A4: =+'Note 1'!A4 -> IAMGOLD BOTO SA | C4: Durée en mois : | D4: =+'Note 1'!E4 -> 12
A5: Numéro d'identification : | B5: =+'Note 1'!B5 -> 007768007
A7: LIBELLES | B7: ANNEE 2022 | C7: ANNEE 2021 | D7: VARIATION EN %
A9: Rémunérations directes versées au personnel | B9: 843360997 | C9: 1071252601 | D9: -0.21273377
A10: Indemnités forfaitaires versées au personnel | B10: 63308888 | C10: 99479801 | D10: -0.36360058
A11: Charges sociales | B11: 25648223 | C11: 22587379 | D11: 0.13551125
A12: Rémunérations et charges sociales de l'exploitant individuel | B12: 0 | C12: 0 | D12: 0
A13: Rémunération transférée de personnel extérieur | B13: 52563290 | C13: 14497587 | D13: 2.6256578
A14: Autres charges sociales | B14: 153779443 | C14: 235011824 | D14: -0.34565231
A16: TOTAL CHARGES DE PERSONNEL | B16: 1138660841 | C16: 1442829192 | D16: -0.21081383
A17: Commentaire :
A18: · Commenter toute variation significative
A19: · Indiquer la nature et la durée du contrat du personnel extérieur
A21: Cette baisse des charges salariales est liée aux départs notés parmi les salariés expatriés qui constituaient une part importante de la masse salariale.

Sheet Note 27B
B1: NOTE 27B : EFFECTIFS, MASSE SALARIALE ET PERSONNEL EXTERIEUR
B3: Désignation entité : | K3: Excercice clos le : | N3: =+'Note 1'!E3 -> 44926
B4: =+'Note 1'!A4 -> IAMGOLD BOTO SA
B5: Numéro d'identification : | C5: =+'Note 1'!B5 -> 007768007 | K5: Durée en mois : | M5: =+'Note 1'!E4 -> 12
B7: EFFECTIF ET MASSE SALARIALE | C7: EFFECTIFS | J7: MASSE SALARIALE
C8: NATIONAUX | E8: AUTRES ETATS DE L'OHADA | G8: HORS OHADA | I8: TOTAL | J8: NATIONAUX | L8: AUTRES ETATS DE L'OHADA | N8: HORS OHADA | P8: TOTAL
C9: M | D9: F | E9: M | F9: F | G9: M | H9: F | J9: M | K9: F | L9: M | M9: F | N9: M | O9: F
A10: YA | B10: 1 - Cadres supérieurs | C10: 1 | D10: 1 | E10: 1 | G10: 3 | I10: =SUM(C10:H10) -> 6 | J10: 66462582 | K10: 61751210 | L10: 81432206 | N10: 126815305 | P10: =SUM(J10:O10) -> 336461303
A11: YB | B11: 2 - Techniciens supérieurs et cadres moyens | C11: 9 | D11: 2 | E11: 2 | G11: 1 | I11: =SUM(C11:H11) -> 14 | J11: 280918342 | K11: 74679674 | L11: 69336102 | N11: 21943979 | P11: =SUM(J11:O11) -> 446878097
A12: YC | B12: 3 - Techniciens, agents de maîtrise et ouvriers qualifiés | C12: 3 | I12: =SUM(C12:H12) -> 3 | J12: 7646464 | P12: =SUM(J12:O12) -> 7646464
A13: YD | B13: 4 - Employés, manœuvres, ouvriers et apprentis | C13: 30 | D13: 3 | I13: =SUM(C13:H13) -> 33 | J13: 96151410 | K13: 8044321 | P13: =SUM(J13:O13) -> 104195731
A14: YE | B14: TOTAL (1) | C14: =SUM(C10:C13) -> 43 | D14: =SUM(D10:D13) -> 6 | E14: =SUM(E10:E13) -> 3 | F14: =SUM(F10:F13) -> 0 | G14: =SUM(G10:G13) -> 4 | H14: =SUM(H10:H13) -> 0 | I14: =SUM(C14:H14) -> 56 | J14: =SUM(J10:J13) -> 451178798 | K14: =SUM(K10:K13) -> 144475205 | L14: =SUM(L10:L13) -> 150768308 | M14: =SUM(M10:M13) -> 0 | N14: =SUM(N10:N13) -> 148759284 | O14: =SUM(O10:O13) -> 0 | P14: =SUM(P10:P13) -> 895181595
A16: YF | B16: PERMANENTS | C16: 34 | D16: 5 | E16: 3 | F16: 0 | G16: 4 | H16: 0 | I16: =I14-I17 -> 46
A17: YG | B17: SAISONNIERS | C17: 9 | D17: 1 | E17: 0 | F17: 0 | G17: 0 | H17: 0 | I17: =SUM(C17:H17) -> 10 | P17: =SUM(J17:O17) -> 0
B20: 2. Personnel extérieur | J20: FACTURATION A L'ENTITE
A21: YH | B21: 1 - Cadres supérieurs
A22: YI | B22: 2 - Techniciens supérieurs et cadres moyens | I22: =SUM(C22:H22) -> 0
A23: YJ | B23: 3 - Techniciens, agents de maîtrise et ouvriers qualifiés | C23: 7 | I23: =SUM(C23:H23) -> 7 | J23: 52563290 | Q23: =Q20+Q21+R21 -> 0
A24: YK | B24: 4 - Employés, manœuvres, ouvriers et apprentis | I24: =SUM(C24:H24) -> 0
A25: YL | B25: TOTAL (2) | C25: =SUM(C21:C24) -> 7 | D25: =SUM(D21:D24) -> 0 | E25: =SUM(E21:E24) -> 0 | F25: =SUM(F21:F24) -> 0 | G25: =SUM(G21:G24) -> 0 | H25: =SUM(H21:H24) -> 0 | I25: =SUM(C25:H25) -> 7 | J25: =SUM(J21:J24) -> 52563290 | K25: =SUM(K21:K24) -> 0
A27: YM | B27: PERMANENTS | C27: 7 | I27: =SUM(C27:H27) -> 7
A28: YN | B28: SAISONNIERS | I28: =SUM(C28:H28) -> 0
A30: YO | B30: TOTAL (1 + 2) | C30: =+C14+C25 -> 50 | D30: =+D14+D25 -> 6 | E30: =+E14+E25 -> 3 | F30: =+F14+F25 -> 0 | G30: =+G14+G25 -> 4 | H30: =+H14+H25 -> 0 | I30: =+I14+I25 -> 63
B31: Commentaire :
B32: · Faire un commentaire si nécessaire en cas de mouvement significatif du personnel.

Sheet Note 28
A1: NOTE 28 : PROVISIONS ET DEPRECIATIONS INSCRITES AU BILAN
A3: Désignation entité : | G3: Excercice clos le : | H3: =+'Note 1'!E3 -> 44926
A4: =+'Note 1'!A4 -> IAMGOLD BOTO SA | G4: Durée en mois : | H4: =+'Note 1'!E4 -> 12
A5: Numéro d'identification : | B5: =+'Note 1'!B5 -> 007768007
A7: SITUATIONS ET MOUVEMENTS | B7: A | C7: B | F7: C | I7: D = A + B - C
B8: PROVISIONS A L'OUVERTURE DE L'EXERCICE | C8: AUGMENTATIONS : DOTATIONS | F8: DIMINUTIONS : REPRISES | I8: PROVISIONS A LA CLOTURE DE L'EXERCICE
A9: NATURE | C9: D'EXPLOITATION | D9: FINANCIERES | E9: HORS ACTIVITES ORDINAIRES | F9: D'EXPLOITATION | G9: FINANCIERES | H9: HORS ACTIVITES ORDINAIRES
A10: 1. Provisions réglementées
A11: 2. Provisions financières pour risques et charges | B11: 42172294 | D11: 2881106902 | G11: 0 | I11: 2923279196
A12: 3. Dépréciation des immobilisations
A13: TOTAL DOTATIONS | B13: =SUM(B10:B12) -> 42172294 | C13: =SUM(C10:C12) -> 0 | D13: =SUM(D10:D12) -> 2881106902 | E13: =SUM(E10:E12) -> 0 | F13: =SUM(F10:F12) -> 0 | G13: =SUM(G10:G12) -> 0 | H13: =SUM(H10:H12) -> 0 | I13: =SUM(I10:I12) -> 2923279196
A14: 4. Dépréciations des stocks
A15: 5. Dépréciations actif circulant HAO
A16: 6. Dépréciations fournisseurs
A17: 7. Dépréciations des clients
A18: 8. Dépréciations titres de placement
A19: 9. Dépréciations valeurs à encaisser
A20: 10. Dépréciations disponibilité
A21: 11. Dépréciations et provisions pour risques à court terme exploitation | B21: 0 | C21: 191029 | F21: 0 | G21: 0 | I21: 191029
A22: 12. Dépréciations et provisions pour risques à court terme à caractère financier
A23: TOTAL CHARGES POUR DEPRECIATIONS ET PROVISIONS A COURT TERME | B23: =SUM(B14:B22) -> 0 | C23: =SUM(C14:C22) -> 191029 | D23: =SUM(D14:D22) -> 0 | E23: =SUM(E14:E22) -> 0 | F23: =SUM(F14:F22) -> 0 | G23: =SUM(G14:G22) -> 0 | H23: =SUM(H14:H22) -> 0 | I23: =SUM(I14:I22) -> 191029
A25: TOTAL PROVISIONS ET DEPRECIATIONS | B25: =+B13+B23 -> 42172294 | C25: =+C13+C23 -> 191029 | D25: =+D13+D23 -> 2881106902 | E25: =+E13+E23 -> 0 | F25: =+F13+F23 -> 0 | G25: =+G13+G23 -> 0 | H25: =+H13+H23 -> 0 | I25: =+I13+I23 -> 2923470225
A26: Commentaire :
A27: · Indiquer les évènements et circonstances qui ont conduit à la constitution et à la reprise de la dépréciation et de la provision.
A29: La provision est essentiellement constituée par la provision pour pertes de change liée à l'emprunt et à la provision pour départ à la retraite.

Sheet Note 29
A1: NOTE 29 : CHARGES ET REVENUS FINANCIERS
A3: Désignation entité : | C3: Excercice clos le : | D3: =+'Note 1'!E3 -> 44926
A4: =+'Note 1'!A4 -> IAMGOLD BOTO SA | C4: Durée en mois : | D4: =+'Note 1'!E4 -> 12
A5: Numéro d'identification : | B5: =+'Note 1'!B5 -> 007768007
A7: LIBELLES | B7: ANNEE 2019 | C7: ANNEE 2018 | D7: VARIATION EN %
A9: Intérêts des emprunts
A10: Intérêts dans loyers de location acquisition
A11: Escomptes accordés
A12: Autres intérêts
A13: Escomptes des effets de commerce
A14: Pertes de change financiére | B14: 300108253 | C14: 7546694 | D14: 38.766851
A15: Pertes sur cessions de titres de placement
A16: Malis provenant d'attribution gratuite d'actions au personnel salarié et aux dirigeants
A17: Pertes sur risques financiers
A18: Charges pour dépréciations et provisons à court terme à caractère financier (voir note 28)
A19: SOUS TOTAL FRAIS FINANCIERS | B19: 300108253 | C19: 7546694 | D19: 38.766851
A20: Intérêts de prêts et créances diverses | B20: 9061673 | C20: 27765387 | D20: -0.67363419
A21: Revenus de participations
A22: Escomptes obtenus
A23: Revenus de placement
A24: Intérêts dans loyers de location-financement
A25: Gains de change | B25: 581384 | C25: 2715539 | D25: -0.78590475
A26: Gains sur cessions de titres de placement
A27: Gains sur risques financiers
A28: Reprises de charges pour dépréciation et provisions à court terme à caractère financier (voir note 28)
A29: SOUS TOTAL REVENUS FINANCIERS | B29: 9643057 | C29: 30480926 | D29: -0.68363635
A31: TOTAL | B31: -290465196 | C31: 22934232 | D31: -13.665137
A32: Commentaire :
A33: · Commenter toute variation significative
A34: · En cas de paiement à terme, indiquer le montant des intérêts non comptabilisés
A36: La hausse des pertes de change est non seulement liée à l'arrêt des paiements par l'agent payeur mais aussi au remboursement du compte courant associé.

Sheet Note 30
A1: NOTE 30 : AUTRES CHARGES ET PRODUITS HAO
A3: Désignation entité : | C3: Excercice clos le : | D3: =+'Note 1'!E3 -> 44926
A4: =+'Note 1'!A4 -> IAMGOLD BOTO SA | C4: Durée en mois : | D4: =+'Note 1'!E4 -> 12
A5: Numéro d'identification : | B5: =+'Note 1'!B5 -> 007768007
A7: LIBELLES | B7: ANNEE 2019 | C7: ANNEE 2018 | D7: VARIATION EN %
A9: Charges HAO constatées (1) à détailler
A10: (1) …………………
A11: (1) …………………
A12: Charges liées aux opérations de restructuration
A13: Pertes sur créances HAO
A14: Dons et libéralités accordés
A15: Abandons de créances consentis
A16: Charges liées aux opérations de liquidation
A17: charges pour dépréciations et provisions our risques à court terme HAO
A18: Dotations hors activités ordinaires
A19: Participation des travailleurs
A20: SOUS TOTAL AUTRES CHARGES HAO
... A37: · Commenter toute variation significative

Sheet Note 31
A1: NOTE 31 : REPARTITION DU RESULTAT ET AUTRES ELEMENTS CARACTERISTIQUES DES CINQ DERNIERS EXERCICES
A3: Désignation entité : | D3: Excercice clos le : | E3: =+'Note 1'!E3 -> 44926
A4: =+'Note 1'!A4 -> IAMGOLD BOTO SA | D4: Durée en mois : | E4: =+'Note 1'!E4 -> 12
A5: Numéro d'identification : | B5: =+'Note 1'!B5 -> 007768007
A7: EXERCICES CONCERNES (1) | B7: 2022 | C7: 2021 | D7: 2020 | E7: 2019 | F7: 2018
A9: STRUCTURE DU CAPITAL A LA CLOTURE DE L'EXERCICE (2)
A10: Capital social | B10: 10000000 | C10: 10000000 | D10: 10000000 | E10: 0 | F10: 0
A11: Actions ordinaires
A12: Actions à dividendes prioritaires (ADP) sans droit de vote
A13: Actions nouvelles à émettre :
A14: -par conversion d'obligations
A15: -par exercice de droits de souscription
A16: OPERATIONS ET RESULTATS DE L'EXERCICE (3)
A17: Chiffre d'affaires hors taxes
A18: Résultat des activités ordinaires (RAO) hors dotations et reprises (exploitation et financières)
A19: Participation des travailleurs aux bénéfices
A20: Impôt sur le résultat
A21: Résultat net (4)
A22: RESULTAT ET DIVIDENDE DISTRIBUES
... A25: PERSONNEL ET POLITIQUES SALARIALE
A26: Effectif moyen des travailleurs au cours de l'exercice (6) | B26: 56 | C26: 53 | D26: 33
A27: Effectif moyen de personnel extérieur
A28: Masse salariale distribuée au cours de l'exercice (7) | B28: 906669885 | C28: 1170732402 | D28: 397343606
A29: Avantages sociaux versés au cours de l'exercice (8) {Sécurité sociale, œuvres sociales} | B29: 179427666 | C29: 257599203 | D29: 20347342
A30: Personnel extérieur facturé à l'entreprise (9) | B30: 52563290 | C30: 14497587 | D30: 0
A32: (1) Y compris l'exercice dont les états financiers sont soumis à l'approbation de l'Assemblée | C32: (6) Personnel propre
A33: (2) Indication, en cas de libération partielle du capital, du montant du capital non appelé | C33: (7) Total des comptes 661, 662, 663
A34: (3) Les éléments de cette rubrique sont ceux figurant au compte de résultat | C34: (8) Total des comptes 664, 668
A35: (4) Le résultat, lorsqu'il est négatif, doit être mis entre parenthèses | C35: (9) Compte 667.
A36: (5) L'exercice N correspond au dividende proposé du dernier exercice

Sheet Note 32
A1: NOTE 32 : PRODUCTION DE L'EXERCICE
A3: Désignation entité : | K3: Excercice clos le : | L3: =+'Note 1'!E3 -> 44926
A4: =+'Note 1'!A4 -> IAMGOLD BOTO SA | K4: Durée en mois : | L4: =+'Note 1'!E4 -> 12
A5: Numéro d'identification : | B5: =+'Note 1'!B5 -> 007768007
A7: DESIGNATION DU PRODUIT | B7: UNITE DE QUANTITE CHOISIE | C7: PRODUCTION VENDUE DANS LE PAYS | E7: PRODUCTION VENDUE DANS LES AUTRES PAYS DE L'OHADA | G7: PRODUCTION VENDUE HORS L'OHADA | I7: PRODUCTION IMMOBILISEE | K7: STOCK OUVERTURE DE L'EXERCICE | M7: STOCK CLOTURE DE L'EXERCICE
C8: Quantité | D8: Valeur | E8: Quantité | F8: Valeur | G8: Quantité | H8: Valeur | I8: Quantité | J8: Valeur | K8: Quantité | L8: Valeur | M8: Quantité | N8: Valeur
A9: CAPITATLISATION DES DEPENSES DE DEVELOPPEMENT | B9: 0 | C9: 0 | D9: 0 | E9: 0 | F9: 0 | H9: 0 | J9: 9236283675
A23: NON VENTILE
A25: TOTAL

Sheet Note 33
A1: NOTE 33 : ACHATS DESTINES A LA PRODUCTION
A3: Désignation entité : | G3: Excercice clos le : | H3: =+'Note 1'!E3 -> 44926
A4: =+'Note 1'!A4 -> IAMGOLD BOTO SA | G4: Durée en mois : | H4: =+'Note 1'!E4 -> 12
A5: Numéro d'identification : | B5: =+'Note 1'!B5 -> 007768007
A7: DESIGNATION DES MATIERES ET PRODUITS | B7: UNITE DE QUANTITE CHOISIE | C7: ACHATS EFFECTUES AU COURS DE L'EXERCICE | I7: VARIATION DES STOCKS
C8: PRODUITS DE L'ETAT | E8: PRODUITS IMPORTES
E9: ACHETES DANS L'ETAT | G9: ACHETES HORS DE L'ETAT
C10: Quantité | D10: Valeur | E10: Quantité | F10: Valeur | G10: Quantité | H10: Valeur | I10: Valeur
A25: NON VENTILES
A27: TOTAL

Sheet Note 34
A1: NOTE 34 : FICHE DE SYNTHESE DES PRINCIPAUX INDICATEURS FINANCIERS
A3: Désignation entité : | B3: Excercice clos le : | C3: =+'Note 1'!E3 -> 44926
A4: =+'Note 1'!A4 -> IAMGOLD BOTO SA | C4: Durée en mois : | D4: =+'Note 1'!E4 -> 12
A5: Numéro d'identification : | B5: =+'Note 1'!B5 -> 007768007
A7: (EN FRANCS) | B7: ANNEE 2022 | C7: ANNEE 2021 | D7: VARIATION EN %
A8: ANALYSE DE L'ACTIVITE
A9: SOLDES INTERMEDIAIRES DE GESTION
A10: CHIFFRE D'AFFAIRES
A11: MARGE COMMERCIALE
A12: VALEUR AJOUTEE | B12: 4473578827 | C12: 1553988040 | D12: 1.878773
A13: EXCEDENT BRUT D'EXPLOITATION (EBE) | B13: 3334917986 | C13: 119241248 | D13: 26.967822
A14: RESULTAT D'EXPLOITATION
A15: RESULTAT FINANCIER | B15: -3160263618 | C15: 22934232 | D15: -138.79679
A16: RESULTAT DES ACTIVITES ORDINAIRES
A17: RESULTAT HORS ACTIVITES ORDINAIRES
A18: RESULTAT NET
A19: DETERMINATION DE LA CAPACITE D'AUTOFINANCEMENT
A20: EBE | B20: 3334917986 | C20: 119241248
A21: + Valeurs comptables des cessions courantes d'immobilisation (compte 654)
A22: - Produits ces cessions courantes d'immobilisation (compte 754)
A23: = CAPACITE D'AUTOFINANCEMENT D'EXPLOITATION | B23: 3334917986 | C23: 119241248
A24: + Revenus financiers | B24: 9061673 | C24: 27765387
A25: + Gains de change | B25: 581384 | C25: 2715539
A26: + Transferts de charges financières
A27: + Produits HAO
A28: + Transferts de charges HAO
A29: - Frais financiers
A30: - Pertes de change | B30: 300108253 | C30: 7546694
A31: - Change HAO
A32: - Participation
A33: - Impôts sur le résultat
A34: = CAPACITE D'AUTOFINANCEMENT GLOBALE (C.A.F.G) | B34: 3044452790 | C34: 142175480 | D34: 20.413346
A35: - Distributions de dividendes opérées durant l'exercice
A36: = AUTOFINANCEMENT
A37: ANALYSE DE LA RENTABILITE
B38: 0.035576299 | C38: -0.00081479681 | D38: -44.662786
A40: ANALYSE DE LA STRUCTURE FINANCIERE
A41: Capitaux propres et ressources assimilées | B41: 10000000 | C41: 10000000 | D41: 0
A42: + Dettes financières* et autres ressources assimilées (b) | B42: 85950791168 | C42: 28137179484 | D42: 2.0547053
A43: = Ressources stables | B43: 85960791168 | C43: 28147179484 | D43: 2.0539753
A44: - Actif immobilisé (b) | B44: 86258096072 | C44: 32629354813 | D44: 1.6435734
A45: = FONDS DE ROULEMENT (1) | B45: =+B43-B44 -> -297304904 | C45: =+C43-C44 -> -4482175329 | D45: -0.93366951
A46: Actif circulant d'exploitation (b) | B46: 132243338 | C46: 141553660 | D46: -0.065772386
A47: - Passif circulant d'exploitation (b) | B47: 1244227850 | C47: 6301672860 | D47: -0.80255594
A48: = BESOIN DE FINANCEMENT D'EXPLOITATION (2) | B48: -1111984512 | C48: -6160119200 | D48: -0.81948653
A49: Actif circulant HAO (b)
A50: - Passif circulant HAO (b)
A51: = BESOIN DE FINANCEMENT HAO (3)
A52: BESOIN DE FINANCEMENT GLOBAL (4) = (2) + (3) | B52: -1111984512 | C52: -6160119200 | D52: -0.81948653
A54: TRESORERIE NETTE (5) = (1) - (4) | B54: =+B45-B52 -> 814679608 | C54: =+C45-C52 -> 1677943871
A55: CONTRÔLE : TRESORERIE NETTE = TRESORERIE ACTIF - TRESORERIE PASSIF
A56: ANALYSE DE LA VARIATION DE LA TRESORERIE
A57: Flux de trésorerie des activités opérationnelles | B57: -2055361843 | C57: 1105540303 | D57: -2.8591469
A58: - Flux de trésorerie des activités d'investissement | B58: -53792087147 | C58: -20499282084 | D58: 1.6240961
A59: + Flux de trésorerie des activités de financement | B59: 57802303204 | C59: 18967705746 | D59: 2.0474062
A60: = VARIATION DE LA TRESORERIE NETTE DE LA PERIODE | B60: 1954854214 | C60: -426036035
A61: ANALYSE DE LA VARIATION DE L'ENDETTEMENT FINANCIER NET
A62: Endettement financier brut (Dettes financières* + Trésorerie passif) - Trésorerie actif | B62: 88820589590 | C62: 28137179484 | D62: 2.1566984
A63: = ENDETTEMENT FINANCIER NET | B63: 88005909982 | C63: 26459235613 | D63: 2.3260942
A64: (a) Résultat d'exploitation après impôt théorique sur le bénéfice.
A65: (b) Les écarts de conversion doivent être éliminés afin de ramener les créances et les dettes concernées à leur valeur initiale.
A66: Dettes financières* = emprunts et dettes financières diverses + dettes de location acquisition.

Sheet Note 35
A1: NOTE 35 : LISTE DES INFORMATIONS SOCIALES, ENVIRONNEMENTALES ET SOCIETALES A FOURNIR
A3: Désignation entité : | B3: Excercice clos le : | C3: =+'Note 1'!E3 -> 44926
A4: =+'Note 1'!A4 -> IAMGOLD BOTO SA
A5: Numéro d'identification : | B5: Durée en mois : | C5: =+'Note 1'!E4 -> 12
A6: =+'Note 1'!B5 -> 007768007
A8: Note obligatoire pour les entités ayant un effectif de plus de 250 salariés
A9: Liste des informations sociales, environnementales et sociétales à fournir
A10: INFORMATIONS SOCIALES
A11: Emploi : • l'effectif total et la répartition des salariés par sexe, âge et zone géographique ; • les embauches et les licenciements ; • les rémunérations et leur évolution.
A12: Relations sociales : • l'organisation du dialogue social ; • le bilan des accords collectifs.
A13: Santé et sécurité : • les conditions de santé et de sécurité au travail ; • le bilan des accords signés avec les organisations syndicales ou les représentants du personnel en matière de santé et de sécurité au travail.
A14: Formation : • les politiques mises en œuvre en matière de formation ; • le nombre total d'heures de formation.
A15: Égalité de traitement : • les mesures prises en faveur de l'égalité entre les femmes et les hommes ; • les mesures prises en faveur de l'emploi et de l'insertion des personnes handicapées ;
A16: INFORMATIONS ENVIRONNEMENTALES
A17: Politique générale en matière environnementale : • l'organisation de la société pour prendre en compte les questions environnementales et, le cas échéant, les démarches d'évaluation ou de certification en matière d'environnement ; • les actions de formation et d'information des salariés menées en matière de protection de l'environnement ; les moyens consacrés à la prévention des risques environnementaux et des pollutions.
A18: Pollution et gestion des déchets : • les mesures de prévention, de réduction ou de réparation de rejets dans l'air, l'eau et le sol affectant gravement l'environnement ; • les mesures de prévention, de recyclage et d'élimination des déchets ; • la prise en compte des nuisances sonores et de toute autre forme de pollution spécifique à une activité.
A19: Utilisation durable des ressources : • la consommation d'eau et l'approvisionnement en eau en fonction des contraintes locales ; • la consommation de matières premières et les mesures prises pour améliorer l'efficacité dans leur utilisation ; • la consommation d'énergie, les mesures prises pour améliorer l'efficacité énergétique et le recours aux énergies renouvelables.
... A25: Sous-traitance et fournisseurs : • la prise en compte dans la politique d'achat des enjeux sociaux et environnementaux.

Sheet Note 36
A1: NOTE 36 : TABLE DES CODES
A6: 1 - Code forme juridique (1) | H6: 3 - Code pays du siège social
A8: Société Anonyme (SA) à participation publique | C8: 0 | F8: 0 | H8: Pays OHADA (2)
A10: Société Anonyme (SA) | C10: 0 | F10: 1 | H10: Autres pays africains | J10: 2 | M10: 1
A12: Société à Responsabilité Limitée (SARL) | C12: 0 | F12: 2 | H12: France | J12: 2 | M12: 3
A14: Société en Commandite Simple (SCS) | C14: 0 | F14: 3 | H14: Autres pays de l'Union Européenne | J14: 3 | M14: 9
A16: Société en Nom Collectif (SNC) | C16: 0 | F16: 4 | H16: U.S.A. | J16: 4 | M16: 0
A18: Société en Participation (SP) | C18: 0 | F18: 5 | H18: Canada | J18: 4 | M18: 1
A20: Groupement d'Intérêt Économique (GIE) | C20: 0 | F20: 6 | H20: Autres pays américains | J20: 4 | M20: 9
A22: Association | C22: 0 | F22: 7 | H22: Pays asiatiques | J22: 5 | M22: 0
A24: Société par Actions Simplifiée | C24: 0 | F24: 8 | H24: Autres pays | J24: 9 | M24: 9
A26: Autre forme juridique (à préciser) | C26: 0 | F26: 9
A28: 2 - Code régime fiscal
A30: Réel normal | F30: 1
A32: Réel simplifié | F32: 2
A34: Synthétique | F34: 3
A36: Forfait | F36: 4
A55: (1) Remplacer le premier 0 par 1 si l'entreprise bénéficie d'un agrément prioritaire
A56: (2) Bénin = 01; Burkina = 02; Côte d'Ivoire = 03; Guinée Bissau = 04; Mali = 05; Niger = 06; Sénégal = 07; Togo = 08
A57: Cameroun = 09; Congo = 10; Gabon = 11; République Centrafricaine = 12; Tchad = 13; Comores = 14; Guinée = 15;
A58: Guinée Equatoriale = 16; Congo RDC = 17.

Sheet Codes activités
A1: CODES DES ACTIVITES ECONOMIQUES
A4: Agriculture vivrière | C4: Industries du caoutchouc et des plastiques
A5: 001 001 Culture céréalière | C5: 022 001 Fabrication du caoutchouc naturel
A6: 001 002 Culture de tubercules et plantains | C6: 022 002 Industries du caoutchouc
A7: 001 003 Culture de légumes | C7: 022 003 Fabrication de matières plastiques
A8: 001 004 Culture de condiments | C8: Fabrication d'autres produits minéraux non métalliques et de matériaux
A9: 001 005 Culture de fruits | C9: de construction
A10: 001 006 Culture d'autres produits de l'Agriculture vivrière | C10: 023 001 Industrie du verre
A11: Agriculture industrielle et d'exportation | C11: 023 002 Fabrication de produits minéraux pour la construction
A12: 002 001 Culture de canne à sucre | C12: 023 003 Fabrication d'autres produits minéraux non métalliques
A13: 002 002 Culture d'arachide d'huilerie | C13: Métallurgie et travail des métaux
A14: 002 003 Culture d'arachide de bouche | C14: 024 001 Métallurgie
A15: 002 004 Culture de tabac | C15: 024 002 Travail des métaux
... A85: 021 005 Fabrication d'autres produits chimiques | C85: Correction territoriale
C86: 044 000 Correction territoriale
