Workbook
Name _xlfn_IFERROR: none
Name _xlfn_STDEV_S: none
Name conv_ton_to_lb: [1]ControlPanel!$C$10
Name Excel_BuiltIn__FilterDatabase: #REF!
Name Excel_BuiltIn__FilterDatabase: Résultats!$F$183:$G$194

Sheet Présentation
I5: Modèle financier: mine d'or
B10: Objectif
B23: Table des matières
B44: Relation au modele FARI du FMI
B60: DISCLAIMER
J72: Ce travail est sous la licence Creative Commons Attribution 4.0 International.
J73: Pour une copie de cette licence, merci de vous rendre sur le site : https://creativecommons.org/licenses/by/4.0/deed.fr

Sheet Résultats
B1: Resultats
B4: Hypothèses - synthèse | C4: unités
B5: Réserves récupérables | C5: tonnes | D5: =SUM(Modèle!G8:BD8) -> 4284000
B6: Première production | C6: année | D6: =Modèle!$C$31 -> 1
B7: Couts d'exploration | C7: $m | D7: =Paramètres!C118 -> 0
B8: Couts de développement (CAPEX) | C8: $m | D8: =Paramètres!C120 -> 407
B9: Production / CAPEX | C9: tonnes/$m | D9: =D5/D8 -> 10525.799
B10: Prix du minerai | C10: $/tonne | D10: =Paramètres!$G$108 -> 1600
B11: Prix du minerai | C11: $/lb
B12: Cout opérationnel par tonne | C12: $/tonne | D12: =Paramètres!J122 -> 507.5
B13: Cout opérationnel par tonne | C13: $/lb
B14: Charge de traitement / raffinage | C14: $/lb | D14: =Paramètres!F104 -> 0
B15: Total C1 cash costs | C15: $/lb | D15: =D12+Paramètres!F101+Paramètres!F103+(Modèle!C376*1000000/Modèle!C8) -> 587.5
B16: Taux d'actualisation (investisseurs) | C16: % | D16: =Paramètres!F93 -> 0.1
B17: Taux d'actualisation (Etat) | C17: % | D17: =Paramètres!F94 -> 0.125
B18: Inflation | C18: % | D18: =Paramètres!F95 -> 0.02
B19: Taux d’intérêt réel | C19: % | D19: =Paramètres!F92 -> 0.125
B20: Endettement (capitaux propres/actifs) | C20: % | D20: =Paramètres!F90 -> 0.5
B22: Résultats - synthèse | C22: unités
B23: Flux de trésorerie nets avant impôts du projet (actualisés) | C23: $m | D23: =Modèle!C25 -> 2122.6808
B24: TRI avant impôt du projet | C24: % | D24: =Modèle!C24 -> 0
B25: TRI après impôt du projet | C25: % | D25: =Modèle!C351 -> 0
B26: Taux de rendement minimum - investisseurs | C26: % | D26: =D17 -> 0.125
B27: TRI supérieur au rendement minimum? | D27: =D25>D26 -> FALSE
B28: Période de retour sur investissement (cash-flow non actualisés) | C28: années | D28: =Modèle!C283 -> 0
B29: Période de retour sur investissement (cash-flow actualisés) | C29: années | D29: =Modèle!C288 -> 0
B32: Utiliser « sélection des données » dans chaque graphique pour ajuster la longueur des axes et les cellules de données, par exemple, après avoir changé le régime fiscal ou le profil du projet.
J145: Projet selectionné:
J146: =Paramètres!$F$7 -> Sénégal (SGO - Convention Sabodala)
B180: Tableaux utilises pour certains graphiques
B182: Graphique 1. TEMI
C183: TEMI
B184: {=TRANSPOSE(Modèle!G426:Q426)} -> RDC - 2002 | C184: {=TRANSPOSE(Modèle!G430:Q430)} -> 0.44477093
B185: RDC - amendement | C185: 0.57598027
B186: Chili | C186: 0.53409525
B187: Perou | C187: 0.37911521
B188: Australie Occidentale | C188: 0.54683945
B189: Tanzanie | C189: 0.40238031
B190: Ghana | C190: 0.50177467
B191: Zambie - 2016 | C191: 0.42882023
B192: RDC - redevance a taux variable | C192: 0.44834453
B193: RDC - taxe sur la rente | C193: 0.50715072
B194: Sénégal (SGO - Convention Sabodala) | C194: 0.44273693
B198: Graphique 3a. Profil des recettes de l'Etat - comparaison des regimes fiscaux (VAN10)
C200: VAN | D200: Proportion
B201: =Modèle!D374 -> Bonus de signature | C201: =Modèle!C374 -> 0 | D201: =C201/$C$213 -> 0
B202: =Modèle!D375 -> Droits de douane | C202: =Modèle!C375 -> 0 | D202: =C202/$C$213 -> 0
B203: =Modèle!D376 -> Redevance | C203: =Modèle!C376 -> 342.72 | D203: =C203/$C$213 -> 0.21558145
B204: =Modèle!D377 -> Taxe provinciale | C204: =Modèle!C377 -> 0 | D204: =C204/$C$213 -> 0
B205: =Modèle!D378 -> Redevance a taux variable - sur les prix | C205: =Modèle!C378 -> 0 | D205: =C205/$C$213 -> 0
B206: =Modèle!D379 -> Impot sur la marge operationnelle | C206: =Modèle!C379 -> 0 | D206: =C206/$C$213 -> 0
B207: =Modèle!D380 -> Impot sur les benefices et profits | C207: =Modèle!C380 -> 776.56851 | D207: =C207/$C$213 -> 0.48848555
B208: =Modèle!D381 -> Impot sur la rente | C208: =Modèle!C381 -> 0 | D208: =C208/$C$213 -> 0
B209: =Modèle!D382 -> Impot sur les benefices a taux variable | C209: =Modèle!C382 -> 0 | D209: =C209/$C$213 -> 0
B210: =Modèle!D383 -> Impot sur les profits excedentaires | C210: =Modèle!C383 -> 0 | D210: =C210/$C$213 -> 0
B211: =Modèle!D384 -> Participation de l'Etat | C211: =Modèle!C384 -> 247.60981 | D211: =C211/$C$213 -> 0.15575421
B212: =Modèle!D385 -> Prelevement a la source sur les dividendes | C212: =Modèle!C385 -> 222.84883 | D212: =C212/$C$213 -> 0.14017879
B213: =Modèle!D386 -> Recettes totales de l'Etat | C213: =Modèle!C386 -> 1589.7471 | D213: =C213/$C$213 -> 1

Sheet Paramètres
A1: INPUTS
D3: Hypotheses du regime fiscal - principaux impots et taxes
L5: --- Selection de regimes fiscaux a comparer ---
D6: Choisir le numero du regime fiscal | F6: 11 | H6: 1 | I6: 2 | J6: 3 | K6: 4 | L6: 5 | M6: 6 | N6: 7 | O6: 8 | P6: 9 | Q6: 10 | R6: 11
D7: Nom du regime fiscal | F7: =INDEX(H7:R7,$F$6) -> Sénégal (SGO - Convention Sabodala) | H7: RDC - 2002 | I7: RDC - amendement | J7: Chili | K7: Perou | L7: Australie Occidentale | M7: Tanzanie | N7: Ghana | O7: Zambie - 2016 | P7: RDC - redevance a taux variable | Q7: RDC - taxe sur la rente | R7: Sénégal (SGO - Convention Sabodala)
D9: Bonus de signature | E9: $mm | F9: =INDEX(H9:R9,$F$138) -> 0 | H9: 0 | I9: 0 | J9: 0 | K9: 0 | L9: 0 | M9: 0 | N9: 0 | O9: 0 | P9: 0 | Q9: 0 | R9: 0
D10: Redevance
D11: Taux de redevance | E11: % | F11: =INDEX(H11:R11,$F$138) -> 0.05 | H11: 0.025 | I11: 0.035 | J11: 0 | K11: 0 | L11: 0.025 | M11: 0.04 | N11: 0.05 | O11: 0.05 | P11: 0.025 | Q11: 0.025 | R11: 0.05
D12: Assiette de la redevance (nette / brute) | E12: switch | F12: =INDEX(H12:R12,$F$138) -> gross | H12: net | I12: gross | J12: gross | K12: gross | L12: gross | M12: gross | N12: gross | O12: gross | P12: gross | Q12: gross | R12: gross
D13: Impôt sur les bénéfices
D14: Taux de l’impôt sur les bénéfices | E14: % | F14: =INDEX(H14:R14,$F$138) -> 0.25 | H14: 0.3 | I14: 0.35 | J14: 0.224 | K14: 0.28 | L14: 0.3 | M14: 0.3 | N14: 0.35 | O14: 0.3 | P14: 0.3 | Q14: 0.3 | R14: 0.25
D15: Deductibilite des couts d'exploration | E15: switch | F15: =INDEX(H15:R15,$F$138) -> deferred | H15: deferred | I15: deferred | J15: deferred | K15: deferred | L15: deferred | M15: deferred | N15: deferred | O15: deferred | P15: deferred | Q15: deferred | R15: deferred
D16: Deductibilite des couts d'investissement - immobilisation incorporelles | E16: switch | F16: =INDEX(H16:R16,$F$138) -> deferred | H16: deferred | I16: deferred | J16: deferred | K16: deferred | L16: deferred | M16: deferred | N16: deferred | O16: deferred | P16: deferred | Q16: deferred | R16: deferred
D17: Amortissement des couts d'investissement - immobilisations corporelles | E17: switch | F17: =INDEX(H17:R17,$F$138) -> deferred | H17: deferred | I17: deferred | J17: deferred | K17: deferred | L17: deferred | M17: deferred | N17: deferred | O17: deferred | P17: deferred | Q17: deferred | R17: deferred
D18: Report des pertes | E18: years | F18: =INDEX(H18:R18,$F$138) -> 5 | H18: 5 | I18: 5 | J18: 100 | K18: 4 | L18: 100 | M18: 100 | N18: 5 | O18: 10 | P18: 5 | Q18: 5 | R18: 5
D19: Report des pertes (limite) | E19: % | F19: =INDEX(H19:R19,$F$138) -> 1 | H19: 1 | I19: 1 | J19: 1 | K19: 1 | L19: 1 | M19: 1 | N19: 1 | O19: 0.5 | P19: 1 | Q19: 1 | R19: 1
D20: Regime d'amortissement (sur le capital physique et de remplacement) | E20: years | F20: =INDEX(H20:R20,$F$138) -> 5 | H20: 2 | I20: 5 | J20: 10 | K20: 10 | L20: 20 | M20: 1 | N20: 5 | O20: 4 | P20: 5 | Q20: 5 | R20: 5
D21: Amortissement accelere | F21: =INDEX(H21:R21,$F$138) -> 0 | H21: 1
D22: Option pour les redevances a taux variables (variables dans les tableaux ci-dessous)
D23: Redevance a taux variable - basee sur les prix (choisir entre les systemes 1 et 2) | E23: switch | F23: =INDEX(H23:R23,$F$138) -> 1 | H23: 1 | I23: 1 | J23: 1 | K23: 1 | L23: 1 | M23: 1 | N23: 1 | O23: 1 | P23: 4 | Q23: 1 | R23: 1
D24: Redevance a taux variable - basee sur les prix, pas sur le revenu marginal (choisir entre les systemes 1 et 2) | F24: =INDEX(H24:R24,$F$138) -> 1 | H24: 1 | I24: 1 | J24: 1 | K24: 1 | L24: 1 | M24: 1 | N24: 1 | O24: 1 | P24: 1 | Q24: 1 | R24: 1
D25: Taux de la taxe sur la rente | E25: % | F25: =INDEX(H25:R25,$F$138) -> 0 | Q25: 0.075
D26: Seuil de la taxe sur la rente | E26: % | F26: =INDEX(H26:R26,$F$138) -> 0 | Q26: 0.25
D27: Deductibilite de l'Impot sur les benefices (oui/non) | E27: switch | F27: =INDEX(H27:R27,$F$138) -> 0
D28: Taxe sur la marge opérationnelle (Choisir 1, 2, 3, 4 dans la section des taux variables) | E28: switch | F28: =INDEX(H28:R28,$F$138) -> 1 | H28: 1 | I28: 1 | J28: 3 | K28: 2 | L28: 1 | M28: 1 | N28: 1 | O28: 1 | P28: 1 | Q28: 1 | R28: 1
D29: Impôt variable sur les bénéfices (1 = off, 2 = on) | E29: switch | F29: =INDEX(H29:R29,$F$138) -> 1 | H29: 1 | I29: 1 | J29: 1 | K29: 1 | L29: 1 | M29: 1 | N29: 1 | O29: 1 | P29: 1 | Q29: 1 | R29: 1
D30: Taux de l'mpot sur les profits excedentaires (RDC amendement) | E30: % | F30: =INDEX(H30:R30,$F$138) -> 0 | H30: 0 | I30: 0.5 | J30: 0 | K30: 0 | L30: 0 | M30: 0 | N30: 0 | O30: 0 | P30: 0 | Q30: 0 | R30: 0
D31: Seuil de l'impot sur les profits excedentaires (RDC amendement) | E31: % | F31: =INDEX(H31:R31,$F$138) -> 0 | H31: 0 | I31: 0.25 | J31: 0 | K31: 0 | L31: 0 | M31: 0 | N31: 0 | O31: 0 | P31: 0 | Q31: 0 | R31: 0
D32: Taux du surcout sur les flux de tresorerie | E32: % | F32: =INDEX(H32:R32,$F$138) -> 0 | H32: 0 | I32: 0 | J32: 0 | K32: 0 | L32: 0 | M32: 0 | N32: 0 | O32: 0 | P32: 0 | Q32: 0 | R32: 0
D33: Deductibilite de l'Impot sur les benefices (oui/non) | E33: switch | F33: =INDEX(H33:R33,$F$138) -> 0
D34: Autres taxes et dispositions pertinentes
D35: Impôt sur le revenu des valeurs mobilières | E35: % | F35: =INDEX(H35:R35,$F$138) -> 0.1 | H35: 0.1 | I35: 0.1 | J35: 0.35 | K35: 0.068 | L35: 0.3 | M35: 0.1 | N35: 0.08 | O35: 0.1 | P35: 0.1 | Q35: 0.1 | R35: 0.1
D36: Participation gratuite de l’Etat (sans contribution) | E36: % | F36: =INDEX(H36:R36,$F$138) -> 0.1 | H36: 0.05 | I36: 0.1 | J36: 0 | K36: 0 | L36: 0 | M36: 0 | N36: 0.1 | O36: 0 | P36: 0.05 | Q36: 0.05 | R36: 0.1
D37: Tax provincial (redevance unitaire) | E37: $/ton | F37: =INDEX(H37:R37,$F$138) -> 0
D38: Drotis de douane | E38: % | F38: =INDEX(H38:R38,$F$138) -> 0 | H38: 0.05 | I38: 0.05 | J38: 0 | K38: 0 | L38: 0 | M38: 0 | N38: 0 | O38: 0 | P38: 0.05 | Q38: 0.05 | R38: 0
D39: Clause de rehabilitation (oui/non) | E39: switch | F39: =INDEX(H39:R39,$F$138) -> 0
D40: Clause sur le declenchement de la rehabilitation | E40: % depletion | F40: =INDEX(H40:R40,$F$138) -> 0
D42: Amortissement accelere
D44: Amortissement annee 1 | H44: 0.6
D45: Amortissement annee 2 | H45: 0.2
D46: Amortissement annee 3 | H46: 0.1
D47: Amortissement annee 4 | H47: 0.05
D48: Amortissement annee 5 | H48: 0.05
D49: Amortissement annee 6 | H49: 0
D50: Amortissement annee 7 | H50: 0
D51: Amortissement annee 8 | H51: 0
D52: Amortissement annee 9 | H52: 0
D53: Amortissement annee 10 | H53: 0
D55: Impôts variables - regimes
D56: Les "impots variables" sont les taxes dont le taux depend de mesures economiques telles que la marge operationnelle ou le prix des minerais.
D58: Redevance a taux variable | F58: Tableau | H58: 1 - No RTV | J58: 2 - Zambie 2016 | L58: 3 - Zambie 2008 | N58: 4 - Alternative
D59: Paliers | E59: Limite inferieure ($mm) | F59: Taux marginal | H59: Limite inferieure ($mm) | I59: Taux marginal | J59: Limite inferieure ($mm) | K59: Taux marginal | L59: Limite inferieure ($mm) | M59: Taux marginal | N59: Limite inferieure ($mm) | O59: Taux marginal
D60: 1 | E60: =CHOOSE($F$23,H60,J60,L60,N60) -> 0 | F60: =CHOOSE($F$23,I60,K60,M60,O60) -> 0 | H60: 0 | I60: 0 | J60: 4000 | K60: 0.04 | L60: 0 | M60: 0 | N60: 4000 | O60: 0
D61: 2 | E61: =CHOOSE($F$23,H61,J61,L61,N61) -> 0 | F61: =CHOOSE($F$23,I61,K61,M61,O61) -> 0 | H61: 0 | I61: 0 | J61: 5000 | K61: 0.05 | L61: 5511.5566 | M61: 0.25 | N61: 6000 | O61: 0.05
D62: 3 | E62: =CHOOSE($F$23,H62,J62,L62,N62) -> 0 | F62: =CHOOSE($F$23,I62,K62,M62,O62) -> 0 | H62: 0 | I62: 0 | J62: 6000 | K62: 0.06 | L62: 6613.8679 | M62: 0.5 | N62: 8000 | O62: 0.15
D63: 4 | E63: =CHOOSE($F$23,H63,J63,L63,N63) -> 0 | F63: =CHOOSE($F$23,I63,K63,M63,O63) -> 0 | H63: 0 | I63: 0 | L63: 7716.1792 | M63: 0.75 | N63: 10000 | O63: 0.2
D65: Impot sur la marge operationnelle | F65: Tableau | H65: 1 - No IMO | J65: 2 - Perou | L65: 3 - Chili | N65: 4 - Alternative
D66: Paliers | E66: Limite inferieure | F66: Taux marginal | H66: Limite inferieure | I66: Taux marginal | J66: Limite inferieure | K66: Taux marginal | L66: Limite inferieure | M66: Taux marginal | N66: Limite inferieure | O66: Taux marginal
D67: 1 | E67: =CHOOSE($F$28,H67,J67,L67,N67) -> 0 | F67: =CHOOSE($F$28,I67,K67,M67,O67) -> 0 | H67: 0 | I67: 0 | J67: 0 | K67: 0.03 | L67: 0 | M67: 0.05
D68: 2 | E68: =CHOOSE($F$28,H68,J68,L68,N68) -> 0 | F68: =CHOOSE($F$28,I68,K68,M68,O68) -> 0 | H68: 0 | I68: 0 | J68: 0.1 | K68: 0.0415 | L68: 0.35 | M68: 0.08
D69: 3 | E69: =CHOOSE($F$28,H69,J69,L69,N69) -> 0 | F69: =CHOOSE($F$28,I69,K69,M69,O69) -> 0 | H69: 0 | I69: 0 | J69: 0.15 | K69: 0.053 | L69: 0.4 | M69: 0.105
D70: 4 | E70: =CHOOSE($F$28,H70,J70,L70,N70) -> 0 | F70: =CHOOSE($F$28,I70,K70,M70,O70) -> 0 | H70: 0 | I70: 0 | J70: 0.2 | K70: 0.0645 | L70: 0.45 | M70: 0.13
D71: 5 | E71: =CHOOSE($F$28,H71,J71,L71,N71) -> 0 | F71: =CHOOSE($F$28,I71,K71,M71,O71) -> 0 | H71: 0 | I71: 0 | J71: 0.25 | K71: 0.076 | L71: 0.5 | M71: 0.155 | Q71: `
D72: 6 | E72: =CHOOSE($F$28,H72,J72,L72,N72) -> 0 | F72: =CHOOSE($F$28,I72,K72,M72,O72) -> 0 | H72: 0 | I72: 0 | J72: 0.3 | K72: 0.0875 | L72: 0.55 | M72: 0.18
D73: 7 | E73: =CHOOSE($F$28,H73,J73,L73,N73) -> 0 | F73: =CHOOSE($F$28,I73,K73,M73,O73) -> 0 | H73: 0 | I73: 0 | J73: 0.35 | K73: 0.099 | L73: 0.6 | M73: 0.21
D74: 8 | E74: =CHOOSE($F$28,H74,J74,L74,N74) -> 0 | F74: =CHOOSE($F$28,I74,K74,M74,O74) -> 0 | H74: 0 | I74: 0 | J74: 0.4 | K74: 0.1105 | L74: 0.65 | M74: 0.24
D75: 9 | E75: =CHOOSE($F$28,H75,J75,L75,N75) -> 0 | F75: =CHOOSE($F$28,I75,K75,M75,O75) -> 0 | H75: 0 | I75: 0 | J75: 0.45 | K75: 0.122 | L75: 0.7 | M75: 0.275
D76: 10 | E76: =CHOOSE($F$28,H76,J76,L76,N76) -> 0 | F76: =CHOOSE($F$28,I76,K76,M76,O76) -> 0 | H76: 0 | I76: 0 | J76: 0.5 | K76: 0.1335 | L76: 0.75 | M76: 0.31
D77: 11 | E77: =CHOOSE($F$28,H77,J77,L77,N77) -> 0 | F77: =CHOOSE($F$28,I77,K77,M77,O77) -> 0 | H77: 0 | I77: 0 | J77: 0.55 | K77: 0.145 | L77: 0.8 | M77: 0.345
D78: 12 | E78: =CHOOSE($F$28,H78,J78,L78,N78) -> 0 | F78: =CHOOSE($F$28,I78,K78,M78,O78) -> 0 | H78: 0 | I78: 0 | J78: 0.6 | K78: 0.1565 | L78: 0.85 | M78: 0.345
D79: 13 | E79: =CHOOSE($F$28,H79,J79,L79,N79) -> 0 | F79: =CHOOSE($F$28,I79,K79,M79,O79) -> 0 | H79: 0 | I79: 0 | J79: 0.65 | K79: 0.168 | L79: 0.85 | M79: 0.345
D80: 14 | E80: =CHOOSE($F$28,H80,J80,L80,N80) -> 0 | F80: =CHOOSE($F$28,I80,K80,M80,O80) -> 0 | H80: 0 | I80: 0 | J80: 0.7 | K80: 0.1795 | L80: 0.85 | M80: 0.345
D81: 15 | E81: =CHOOSE($F$28,H81,J81,L81,N81) -> 0 | F81: =CHOOSE($F$28,I81,K81,M81,O81) -> 0 | H81: 0 | I81: 0 | J81: 0.75 | K81: 0.191 | L81: 0.85 | M81: 0.345
D82: 16 | E82: =CHOOSE($F$28,H82,J82,L82,N82) -> 0 | F82: =CHOOSE($F$28,I82,K82,M82,O82) -> 0 | H82: 0 | I82: 0 | J82: 0.8 | K82: 0.2 | L82: 0.85 | M82: 0.345
D83: 17 | E83: =CHOOSE($F$28,H83,J83,L83,N83) -> 0 | F83: =CHOOSE($F$28,I83,K83,M83,O83) -> 0 | H83: 0 | I83: 0 | J83: 0.85 | K83: 0.204 | L83: 0.85 | M83: 0.345
D84: Impot variable sur les benefices - Zambie
D85: Variable "a" dans la formule | F85: 0.15
D86: Variable "c" dans la formule | F86: 0.08
D88: Hypotheses economiques et financieres
D90: Pourcentage des couts de developpement emprunte | E90: % | F90: 0.5
D91: Periode de remboursement (a partir du debut de la production) | E91: annees | F91: 5
D92: Taux d'interet reel | E92: % | F92: 0.125
D93: Taux d'actualisation de l'Etat | E93: % | F93: 0.1
D94: Taux d'actualisation de l'investisseur | E94: % | F94: 0.125
D95: Taux d'inflation du dollar US | E95: % | F95: 0.02
D97: Prix
D98: Prix du minerai | E98: $/Once | F98: 1600
D100: Prix de l'etude de faisabilite (pour le calcul de l'impot sur les profits excedentaires de RDC 2015) | E100: $/Once | F100: 1250
D101: Transport après imposition | E101: $/Once | F101: 0
D103: Charge de traitement / raffinage | E103: $/Once | F103: 0
D106: Hypotheses de prix | E106: year | G106: 1 | H106: 2 | I106: 3 | J106: 4 | K106: 5 | L106: 6 | M106: 7 | N106: 8 | O106: 9 | P106: 10 | Q106: 11 | R106: 12 | S106: 13 | T106: 14 | U106: 15 | V106: 16 | W106: 17 | X106: 18 | Y106: 19 | Z106: 20 | AA106: 21 | AB106: 22 | AC106: 23 | AD106: 24 | AE106: 25 | AF106: 26 | AG106: 27 | AH106: 28 | AI106: 29 | AJ106: 30 | AK106: 31 | AL106: 32 | AM106: 33 | AN106: 34 | AO106: 35 | AP106: 36 | AQ106: 37 | AR106: 38 | AS106: 39 | AT106: 40 | AU106: 41 | AV106: 42 | AW106: 43 | AX106: 44 | AY106: 45 | AZ106: 46 | BA106: 47 | BB106: 48 | BC106: 49 | BD106: 50
D108: Prix (reel) | G108: =F98 -> 1600 | H108: =$F$137 -> 1600 | I108: =$F$137 -> 1600 | J108: =$F$137 -> 1600 | K108: =$F$137 -> 1600 | L108: =$F$137 -> 1600 | M108: =$F$137 -> 1600 | N108: =$F$137 -> 1600 | O108: =$F$137 -> 1600 | ... BD108: =$F$137 -> 1600
D109: Prix de l'etude de faisabilite (pour le calcul de l'impot sur les profits excedentaires de RDC 2015) | F109: =F100 -> 1250
D111: Hypothese du profil de projet (valeurs reelles)
C113: Total | D113: Sabodala-Massawa (SGO) - Sénégal | E113: year | G113: 1 | H113: =G113+1 -> 2 | I113: =H113+1 -> 3 | J113: =I113+1 -> 4 | K113: =J113+1 -> 5 | L113: =K113+1 -> 6 | M113: =L113+1 -> 7 | N113: =M113+1 -> 8 | O113: =N113+1 -> 9 | ... BD113: =BC113+1 -> 50
C115: =SUM(G115:BD115) -> 4284000 | D115: Production | E115: onces | G115: 245000 | H115: 359000 | I115: 360000 | J115: 400000 | K115: 400000 | L115: 400000 | M115: 400000 | N115: 320000 | O115: 173000 | P115: 173000 | Q115: 173000 | R115: 173000 | S115: 173000 | T115: 173000 | U115: 173000 | V115: 133000 | W115: 56000
C116: =SUM(G116:BD116) -> 0 | D116: Transport après imposition | E116: $mm reel
C117: =SUM(G117:BD117) -> 0 | D117: Charge de traitement / raffinage après imposition | E117: $mm reel
C118: =SUM(G118:BD118) -> 0 | D118: Couts d’exploration | E118: $mm reel | G118: 0
C119: =SUM(G119:BD119) -> 0 | D119: Couts d’investissement en capital - incorporel | E119: $mm reel
...

Sheet Modèle
A2: Verification: | C2: =AND(A:A) -> TRUE | E2: annee | G2: 1 | H2: =G2+1 -> 2 | I2: =H2+1 -> 3 | J2: =I2+1 -> 4 | K2: =J2+1 -> 5 | L2: =K2+1 -> 6 | M2: =L2+1 -> 7 | N2: =M2+1 -> 8 | O2: =N2+1 -> 9 | ... BD2: =BC2+1 -> 50
A4: Flux de tresorerie du projet
D7: Flux de tresorerie du projet avant impots: reel | E7: annee | G7: =G$2 -> 1 | H7: =H$2 -> 2 | I7: =I$2 -> 3 | J7: =J$2 -> 4 | K7: =K$2 -> 5 | L7: =L$2 -> 6 | M7: =M$2 -> 7 | N7: =N$2 -> 8 | ... BD7: =BD$2 -> 50
C8: =SUM(G8:BD8) -> 4284000 | D8: Production | E8: tonnes | G8: =Paramètres!G115 -> 245000 | H8: =Paramètres!H115 -> 359000 | I8: =Paramètres!I115 -> 360000 | J8: =Paramètres!J115 -> 400000 | K8: =Paramètres!K115 -> 400000 | L8: =Paramètres!L115 -> 400000 | M8: =Paramètres!M115 -> 400000 | N8: =Paramètres!N115 -> 320000 | ... BD8: =Paramètres!BD115 -> 0
C9: =SUM(G9:BD9) -> 6854.4 | D9: Chiffre d'affaires brut | E9: $mm reel | G9: =G8*Paramètres!G108/1000000 -> 392 | H9: =H8*Paramètres!H108/1000000 -> 574.4 | I9: =I8*Paramètres!I108/1000000 -> 576 | J9: =J8*Paramètres!J108/1000000 -> 640 | K9: =K8*Paramètres!K108/1000000 -> 640 | L9: =L8*Paramètres!L108/1000000 -> 640 | M9: =M8*Paramètres!M108/1000000 -> 640 | N9: =N8*Paramètres!N108/1000000 -> 512 | ... BD9: =BD8*Paramètres!BD108/1000000 -> 0
C10: =SUM(G10:BD10) -> 0 | D10: Transport et traitement apres imposition | E10: $mm reel | G10: =Paramètres!G116+Paramètres!G117 -> 0 | H10: =Paramètres!H116+Paramètres!H117 -> 0 | I10: =Paramètres!I116+Paramètres!I117 -> 0 | J10: =Paramètres!J116+Paramètres!J117 -> 0 | K10: =Paramètres!K116+Paramètres!K117 -> 0 | L10: =Paramètres!L116+Paramètres!L117 -> 0 | M10: =Paramètres!M116+Paramètres!M117 -> 0 | N10: =Paramètres!N116+Paramètres!N117 -> 0 | ... BD10: =Paramètres!BD116+Paramètres!BD117 -> 0
A11: =ROUND(C11-(C9-C10),5)=0 -> TRUE | C11: =SUM(G11:BD11) -> 6854.4 | D11: Chiffre d'affaires net | E11: $mm reel | G11: =G9-G10 -> 392 | H11: =H9-H10 -> 574.4 | I11: =I9-I10 -> 576 | J11: =J9-J10 -> 640 | K11: =K9-K10 -> 640 | L11: =L9-L10 -> 640 | M11: =M9-M10 -> 640 | N11: =N9-N10 -> 512 | ... BD11: =BD9-BD10 -> 0
C12: =SUM(G12:BD12) -> 0 | D12: Couts d’exploration | E12: $mm reel | G12: =Paramètres!G118 -> 0 | H12: =Paramètres!H118 -> 0 | I12: =Paramètres!I118 -> 0 | J12: =Paramètres!J118 -> 0 | K12: =Paramètres!K118 -> 0 | L12: =Paramètres!L118 -> 0 | M12: =Paramètres!M118 -> 0 | N12: =Paramètres!N118 -> 0 | ... BD12: =Paramètres!BD118 -> 0
C13: =SUM(G13:BD13) -> 0 | D13: Couts d’investissement en capital - incorporel | E13: $mm reel | G13: =Paramètres!G119 -> 0 | H13: =Paramètres!H119 -> 0 | I13: =Paramètres!I119 -> 0 | J13: =Paramètres!J119 -> 0 | K13: =Paramètres!K119 -> 0 | L13: =Paramètres!L119 -> 0 | M13: =Paramètres!M119 -> 0 | N13: =Paramètres!N119 -> 0 | ... BD13: =Paramètres!BD119 -> 0
C14: =SUM(G14:BD14) -> 407 | D14: Couts d’investissement en capital - corporel | E14: $mm reel | G14: =Paramètres!G120 -> 37 | H14: =Paramètres!H120 -> 109 | I14: =Paramètres!I120 -> 160 | J14: =Paramètres!J120 -> 0 | K14: =Paramètres!K120 -> 0 | L14: =Paramètres!L120 -> 0 | M14: =Paramètres!M120 -> 0 | N14: =Paramètres!N120 -> 24 | ... BD14: =Paramètres!BD120 -> 0
C15: =SUM(G15:BD15) -> 253 | D15: Capital de réinvestissement | E15: $mm reel | G15: =Paramètres!G121 -> 41 | H15: =Paramètres!H121 -> 37 | I15: =Paramètres!I121 -> 45 | J15: =Paramètres!J121 -> 25 | K15: =Paramètres!K121 -> 27 | L15: =Paramètres!L121 -> 12 | M15: =Paramètres!M121 -> 11 | N15: =Paramètres!N121 -> 8 | ... BD15: =Paramètres!BD121 -> 0
D16: Couts opérationnels - extraction | E16: $mm reel | G16: =Paramètres!G122*G$8/1000000 -> 171.01 | H16: =Paramètres!H122*H$8/1000000 -> 169.0172 | I16: =Paramètres!I122*I$8/1000000 -> 177.984 | J16: =Paramètres!J122*J$8/1000000 -> 203 | K16: =Paramètres!K122*K$8/1000000 -> 217 | L16: =Paramètres!L122*L$8/1000000 -> 203 | M16: =Paramètres!M122*M$8/1000000 -> 180 | N16: =Paramètres!N122*N$8/1000000 -> 176 | ... BD16: =Paramètres!BD122*BD$8/1000000 -> 0
C17: =SUM(G17:BD17) -> 2594.0134 | D17: Couts opérationnels - total | E17: $mm reel | G17: =SUM(G16:G16) -> 171.01 | H17: =SUM(H16:H16) -> 169.0172 | I17: =SUM(I16:I16) -> 177.984 | J17: =SUM(J16:J16) -> 203 | K17: =SUM(K16:K16) -> 217 | L17: =SUM(L16:L16) -> 203 | M17: =SUM(M16:M16) -> 180 | N17: =SUM(N16:N16) -> 176 | ... BD17: =SUM(BD16:BD16) -> 0
C18: =SUM(G18:BD18) -> 0 | D18: Parafiscalité | E18: $mm reel | G18: =Paramètres!G127 -> 0 | H18: =Paramètres!H127 -> 0 | I18: =Paramètres!I127 -> 0 | J18: =Paramètres!J127 -> 0 | K18: =Paramètres!K127 -> 0 | L18: =Paramètres!L127 -> 0 | M18: =Paramètres!M127 -> 0 | N18: =Paramètres!N127 -> 0 | ... BD18: =Paramètres!BD127 -> 0
C19: =SUM(G19:BD19) -> 5 | D19: Couts de fermeture et de rehabilitation | E19: $mm reel | G19: =Paramètres!G128 -> 0 | H19: =Paramètres!H128 -> 0 | I19: =Paramètres!I128 -> 0 | J19: =Paramètres!J128 -> 0 | K19: =Paramètres!K128 -> 0 | L19: =Paramètres!L128 -> 0 | M19: =Paramètres!M128 -> 0 | N19: =Paramètres!N128 -> 0 | ... BD19: =Paramètres!BD128 -> 0
C20: =SUM(G20:BD20) -> 3259.0134 | D20: Couts totaux | E20: $mm reel | G20: =SUM(G12:G15)+G17+G18+G19 -> 249.01 | H20: =SUM(H12:H15)+H17+H18+H19 -> 315.0172 | I20: =SUM(I12:I15)+I17+I18+I19 -> 382.984 | J20: =SUM(J12:J15)+J17+J18+J19 -> 228 | K20: =SUM(K12:K15)+K17+K18+K19 -> 244 | L20: =SUM(L12:L15)+L17+L18+L19 -> 215 | M20: =SUM(M12:M15)+M17+M18+M19 -> 191 | N20: =SUM(N12:N15)+N17+N18+N19 -> 208 | ... BD20: =SUM(BD12:BD15)+BD17+BD18+BD19 -> 0
A21: =ROUND(C21-(C11-SUM(C12:C19)),5)=0 -> TRUE | C21: =SUM(G21:BD21) -> 3595.3866 | D21: Flux de tresorerie du projet avant redevances, droits de douanes et impots | E21: $mm reel | G21: =G11-G20 -> 142.99 | H21: =H11-H20 -> 259.3828 | I21: =I11-I20 -> 193.016 | J21: =J11-J20 -> 412 | K21: =K11-K20 -> 396 | L21: =L11-L20 -> 425 | M21: =M11-M20 -> 449 | N21: =N11-N20 -> 304 | ... BD21: =BD11-BD20 -> 0
C23: =AVERAGE(G23:BD23) -> 0.50058345 | D23: Marge operationnelle (EBITDA/CA brut) | E23: % | G23: =IFERROR(G21/G11,"") -> 0.36477041 | H23: =IFERROR(H21/H11,"") -> 0.45157173 | I23: =IFERROR(I21/I11,"") -> 0.33509722 | J23: =IFERROR(J21/J11,"") -> 0.64375 | K23: =IFERROR(K21/K11,"") -> 0.61875 | L23: =IFERROR(L21/L11,"") -> 0.6640625 | M23: =IFERROR(M21/M11,"") -> 0.7015625 | N23: =IFERROR(N21/N11,"") -> 0.59375 | ... BD23: =IFERROR(BD21/BD11,"")
C24: =IFERROR(IRR($G21:BD21),0) -> 0 | D24: Taux de rendement interne (reel) | E24: % | G24: =IFERROR(IRR($G21:G21),"--") -> -- | H24: =IFERROR(IRR($G21:H21),"--") -> -- | I24: =IFERROR(IRR($G21:I21),"--") -> -- | J24: =IFERROR(IRR($G21:J21),"--") -> -- | K24: =IFERROR(IRR($G21:K21),"--") -> -- | L24: =IFERROR(IRR($G21:L21),"--") -> -- | M24: =IFERROR(IRR($G21:M21),"--") -> -- | N24: =IFERROR(IRR($G21:N21),"--") -> -- | ... BD24: =IFERROR(IRR($G21:BD21),"--") -> --
C25: =NPV(Paramètres!$F$93,$H$21:$BD$21)+$G$21 -> 2122.6808 | D25: Flux de tresorerie du projet avant impots, VAN10 | E25: $mm reel
D27: Reperes
C28: =MAX(G28:BD28) -> 50 | D28: Annees du projet | E28: annee | G28: =(SUM($G$8:G20)>0)*1+F28 -> 1 | H28: =(SUM($G$8:H20)>0)*1+G28 -> 2 | I28: =(SUM($G$8:I20)>0)*1+H28 -> 3 | J28: =(SUM($G$8:J20)>0)*1+I28 -> 4 | K28: =(SUM($G$8:K20)>0)*1+J28 -> 5 | L28: =(SUM($G$8:L20)>0)*1+K28 -> 6 | M28: =(SUM($G$8:M20)>0)*1+L28 -> 7 | N28: =(SUM($G$8:N20)>0)*1+M28 -> 8 | ... BD28: =(SUM($G$8:BD20)>0)*1+BC28 -> 50
C29: =MAX(G29:BD29) -> 17 | D29: Annees de production | E29: annee | G29: =((G8>0)*1+F29)*(G8>0) -> 1 | H29: =((H8>0)*1+G29)*(H8>0) -> 2 | I29: =((I8>0)*1+H29)*(I8>0) -> 3 | J29: =((J8>0)*1+I29)*(J8>0) -> 4 | K29: =((K8>0)*1+J29)*(K8>0) -> 5 | L29: =((L8>0)*1+K29)*(L8>0) -> 6 | M29: =((M8>0)*1+L29)*(M8>0) -> 7 | N29: =((N8>0)*1+M29)*(N8>0) -> 8 | ... BD29: =((BD8>0)*1+BC29)*(BD8>0) -> 0
C30: =MAX(G30:BD30) -> 17 | D30: Annees de production restantes | E30: annee | G30: =($C$29-G29+1)*(G8>0) -> 17 | H30: =($C$29-H29+1)*(H8>0) -> 16 | I30: =($C$29-I29+1)*(I8>0) -> 15 | J30: =($C$29-J29+1)*(J8>0) -> 14 | K30: =($C$29-K29+1)*(K8>0) -> 13 | L30: =($C$29-L29+1)*(L8>0) -> 12 | M30: =($C$29-M29+1)*(M8>0) -> 11 | N30: =($C$29-N29+1)*(N8>0) -> 10 | ... BD30: =($C$29-BD29+1)*(BD8>0) -> 0
C31: =SUM(G31:BD31) -> 1 | D31: Annee de premiere production | E31: annee | G31: =IF(G29=1,G28,0) -> 1 | H31: =IF(H29=1,H28,0) -> 0 | I31: =IF(I29=1,I28,0) -> 0 | J31: =IF(J29=1,J28,0) -> 0 | K31: =IF(K29=1,K28,0) -> 0 | L31: =IF(L29=1,L28,0) -> 0 | M31: =IF(M29=1,M28,0) -> 0 | N31: =IF(N29=1,N28,0) -> 0 | ... BD31: =IF(BD29=1,BD28,0) -> 0
D34: Periode de retour sur investissement
C35: =MAX(G35:BD35) -> 449 | D35: Flux de tresorerie du projet avant impot | E35: $mm reel | G35: =G21 -> 142.99 | H35: =H21 -> 259.3828 | I35: =I21 -> 193.016 | J35: =J21 -> 412 | K35: =K21 -> 396 | L35: =L21 -> 425 | M35: =M21 -> 449 | N35: =N21 -> 304 | ... BD35: =BD21 -> 0
C36: =MAX(G36:BD36) -> 3595.3866 | D36: Flux cumulatifs de tresorerie du projet avant impot | E36: $mm reel | G36: =G35+F36 -> 142.99 | H36: =H35+G36 -> 402.3728 | I36: =I35+H36 -> 595.3888 | J36: =J35+I36 -> 1007.3888 | K36: =K35+J36 -> 1403.3888 | L36: =L35+K36 -> 1828.3888 | M36: =M35+L36 -> 2277.3888 | N36: =N35+M36 -> 2581.3888 | ... BD36: =BD35+BC36 -> 3595.3866
C37: =MAX(G37:BD37) -> 0 | D37: Periode de retour sur investissement | E37: annee | G37: =IF(AND(G36<=0,H36>0),G28+(-G36/H35),0) -> 0 | H37: =IF(AND(H36<=0,I36>0),H28+(-H36/I35),0) -> 0 | I37: =IF(AND(I36<=0,J36>0),I28+(-I36/J35),0) -> 0 | J37: =IF(AND(J36<=0,K36>0),J28+(-J36/K35),0) -> 0 | K37: =IF(AND(K36<=0,L36>0),K28+(-K36/L35),0) -> 0 | L37: =IF(AND(L36<=0,M36>0),L28+(-L36/M35),0) -> 0 | M37: =IF(AND(M36<=0,N36>0),M28+(-M36/N35),0) -> 0 | N37: =IF(AND(N36<=0,O36>0),N28+(-N36/O35),0) -> 0 | ... BD37: =IF(AND(BD36<=0,BE36>0),BD28+(-BD36/BE35),0) -> 0
D39: Inflation
D40: Indice d'inflation | E40: indice | G40: =IF(Paramètres!G$113=1,1,(1+Paramètres!$F$95)^(Paramètres!G$113-1)) -> 1 | H40: =IF(Paramètres!H$113=1,1,(1+Paramètres!$F$95)^(Paramètres!H$113-1)) -> 1.02 | I40: =IF(Paramètres!I$113=1,1,(1+Paramètres!$F$95)^(Paramètres!I$113-1)) -> 1.0404 | J40: =IF(Paramètres!J$113=1,1,(1+Paramètres!$F$95)^(Paramètres!J$113-1)) -> 1.061208 | K40: =IF(Paramètres!K$113=1,1,(1+Paramètres!$F$95)^(Paramètres!K$113-1)) -> 1.0824322 | L40: =IF(Paramètres!L$113=1,1,(1+Paramètres!$F$95)^(Paramètres!L$113-1)) -> 1.1040808 | M40: =IF(Paramètres!M$113=1,1,(1+Paramètres!$F$95)^(Paramètres!M$113-1)) -> 1.1261624 | N40: =IF(Paramètres!N$113=1,1,(1+Paramètres!$F$95)^(Paramètres!N$113-1)) -> 1.1486857 | ... BD40: =IF(Paramètres!BD$113=1,1,(1+Paramètres!$F$95)^(Paramètres!BD$113-1)) -> 2.6388118
D42: Flux de tresorerie du projet avant impot: Nominal | E42: year | G42: =G$2 -> 1 | H42: =H$2 -> 2 | I42: =I$2 -> 3 | J42: =J$2 -> 4 | K42: =K$2 -> 5 | L42: =L$2 -> 6 | M42: =M$2 -> 7 | N42: =N$2 -> 8 | ... BD42: =BD$2 -> 50
C43: =SUM(G43:BD43) -> 7785.0252 | D43: Chiffre d'affaires brut | E43: $mm reel | G43: =G9*G$40 -> 392 | H43: =H9*H$40 -> 585.888 | I43: =I9*I$40 -> 599.2704 | J43: =J9*J$40 -> 679.17312 | K43: =K9*K$40 -> 692.75658 | L43: =L9*L$40 -> 706.61171 | M43: =M9*M$40 -> 720.74395 | N43: =N9*N$40 -> 588.12706 | ... BD43: =BD9*BD$40 -> 0
C44: =SUM(G44:BD44) -> 0 | D44: Transport et traitement apres imposition | E44: $mm reel | G44: =G10*G$40 -> 0 | H44: =H10*H$40 -> 0 | I44: =I10*I$40 -> 0 | J44: =J10*J$40 -> 0 | K44: =K10*K$40 -> 0 | L44: =L10*L$40 -> 0 | M44: =M10*M$40 -> 0 | N44: =N10*N$40 -> 0 | ... BD44: =BD10*BD$40 -> 0
A45: =ROUND(C45-(C43-C44),5)=0 -> TRUE | C45: =SUM(G45:BD45) -> 7785.0252 | D45: Chiffre d'affaires net | E45: $mm reel | G45: =G11*G$40 -> 392 | H45: =H11*H$40 -> 585.888 | I45: =I11*I$40 -> 599.2704 | J45: =J11*J$40 -> 679.17312 | K45: =K11*K$40 -> 692.75658 | L45: =L11*L$40 -> 706.61171 | M45: =M11*M$40 -> 720.74395 | N45: =N11*N$40 -> 588.12706 | ... BD45: =BD11*BD$40 -> 0
C46: =SUM(G46:BD46) -> 0 | D46: Couts d’exploration | E46: $mm reel | G46: =G12*G$40 -> 0 | H46: =H12*H$40 -> 0 | I46: =I12*I$40 -> 0 | J46: =J12*J$40 -> 0 | K46: =K12*K$40 -> 0 | L46: =L12*L$40 -> 0 | M46: =M12*M$40 -> 0 | N46: =N12*N$40 -> 0 | ... BD46: =BD12*BD$40 -> 0
C47: =SUM(G47:BD47) -> 0 | D47: Couts d’investissement en capital - incorporel | E47: $mm reel | G47: =G13*G$40 -> 0 | H47: =H13*H$40 -> 0 | I47: =I13*I$40 -> 0 | J47: =J13*J$40 -> 0 | K47: =K13*K$40 -> 0 | L47: =L13*L$40 -> 0 | M47: =M13*M$40 -> 0 | N47: =N13*N$40 -> 0 | ... BD47: =BD13*BD$40 -> 0
C48: =SUM(G48:BD48) -> 438.24796 | D48: Couts d’investissement en capital - corporel | E48: $mm reel | G48: =G14*G$40 -> 37 | H48: =H14*H$40 -> 111.18 | I48: =I14*I$40 -> 166.464 | J48: =J14*J$40 -> 0 | K48: =K14*K$40 -> 0 | L48: =L14*L$40 -> 0 | M48: =M14*M$40 -> 0 | N48: =N14*N$40 -> 27.568456 | ... BD48: =BD14*BD$40 -> 0
C49: =SUM(G49:BD49) -> 274.3098 | D49: Capital de réinvestissement | E49: $mm reel | G49: =G15*G$40 -> 41 | H49: =H15*H$40 -> 37.74 | I49: =I15*I$40 -> 46.818 | J49: =J15*J$40 -> 26.5302 | K49: =K15*K$40 -> 29.225668 | L49: =L15*L$40 -> 13.24897 | M49: =M15*M$40 -> 12.387787 | N49: =N15*N$40 -> 9.1894853 | ... BD49: =BD15*BD$40 -> 0
C50: =SUM(G50:BD50) -> 2979.6184 | D50: Couts opérationnels - extraction | E50: $mm reel | G50: =G17*G$40 -> 171.01 | H50: =H17*H$40 -> 172.39754 | I50: =I17*I$40 -> 185.17455 | J50: =J17*J$40 -> 215.42522 | K50: =K17*K$40 -> 234.88778 | L50: =L17*L$40 -> 224.1284 | M50: =M17*M$40 -> 202.70924 | N50: =N17*N$40 -> 202.16868 | ... BD50: =BD17*BD$40 -> 0
C51: =SUM(G51:BD51) -> 0 | D51: Parafiscalité | E51: $mm reel | G51: =G18*G$40 -> 0 | H51: =H18*H$40 -> 0 | I51: =I18*I$40 -> 0 | J51: =J18*J$40 -> 0 | K51: =K18*K$40 -> 0 | L51: =L18*L$40 -> 0 | M51: =M18*M$40 -> 0 | N51: =N18*N$40 -> 0 | ... BD51: =BD18*BD$40 -> 0
C52: =SUM(G52:BD52) -> 6.8639285 | D52: Couts de fermeture et de rehabilitation | E52: $mm reel | G52: =G19*G$40 -> 0 | H52: =H19*H$40 -> 0 | I52: =I19*I$40 -> 0 | J52: =J19*J$40 -> 0 | K52: =K19*K$40 -> 0 | L52: =L19*L$40 -> 0 | M52: =M19*M$40 -> 0 | N52: =N19*N$40 -> 0 | ... BD52: =BD19*BD$40 -> 0
C53: =SUM(G53:BD53) -> 3699.0401 | D53: Couts totaux | E53: $mm reel | G53: =SUM(G46:G52) -> 249.01 | H53: =SUM(H46:H52) -> 321.31754 | I53: =SUM(I46:I52) -> 398.45655 | J53: =SUM(J46:J52) -> 241.95542 | K53: =SUM(K46:K52) -> 264.11345 | L53: =SUM(L46:L52) -> 237.37737 | M53: =SUM(M46:M52) -> 215.09702 | N53: =SUM(N46:N52) -> 238.92662 | ... BD53: =SUM(BD46:BD52) -> 0
A54: =ROUND(C54-(C45-SUM(C46:C52)),5)=0 -> TRUE | C54: =SUM(G54:BD54) -> 4085.9851 | D54: Flux de tresorerie du projet avant redevances, droits de douanes et impots | E54: $mm reel | G54: =G45-G53 -> 142.99 | H54: =H45-H53 -> 264.57046 | I54: =I45-I53 -> 200.81385 | J54: =J45-J53 -> 437.2177 | K54: =K45-K53 -> 428.64314 | L54: =L45-L53 -> 469.23434 | M54: =M45-M53 -> 505.64693 | N54: =N45-N53 -> 349.20044 | ... BD54: =BD45-BD53 -> 0
C57: =IFERROR(IRR($G54:BD54),0) -> 0 | D57: Taux de rendement interne (nominal) | E57: % | G57: =IFERROR(IRR($G54:G54),"--") -> -- | H57: =IFERROR(IRR($G54:H54),"--") -> -- | I57: =IFERROR(IRR($G54:I54),"--") -> -- | J57: =IFERROR(IRR($G54:J54),"--") -> -- | K57: =IFERROR(IRR($G54:K54),"--") -> -- | L57: =IFERROR(IRR($G54:L54),"--") -> -- | M57: =IFERROR(IRR($G54:M54),"--") -> -- | N57: =IFERROR(IRR($G54:N54),"--") -> -- | ... BD57: =IFERROR(IRR($G54:BD54),"--") -> --
C58: =NPV(Paramètres!$F$93,$H$54:$BD$54)+$G$54 -> 2342.665 | D58: Flux de tresorerie du projet avant impots, VAN10 | E58: $mm nominal
A61: Calculs - fiscalite
C63: Total | D63: Fermeture et rehabilitation
C64: =SUM(G64:BD64) -> 17 | D64: Annee de fermeture | E64: years | G64: =Paramètres!G113*(G65>0) -> 0 | H64: =Paramètres!H113*(H65>0) -> 0 | I64: =Paramètres!I113*(I65>0) -> 0 | J64: =Paramètres!J113*(J65>0) -> 0 | K64: =Paramètres!K113*(K65>0) -> 0 | L64: =Paramètres!L113*(L65>0) -> 0 | M64: =Paramètres!M113*(M65>0) -> 0 | N64: =Paramètres!N113*(N65>0) -> 0 | ... BD64: =Paramètres!BD113*(BD65>0) -> 0
C65: =SUM(G65:BD65) -> 6.8639285 | D65: Couts de fermeture et rehabilitation | E65: $mm nominal | G65: =G52 -> 0 | H65: =H52 -> 0 | I65: =I52 -> 0 | J65: =J52 -> 0 | K65: =K52 -> 0 | L65: =L52 -> 0 | M65: =M52 -> 0 | N65: =N52 -> 0 | ... BD65: =BD52 -> 0
C66: =SUM(G66:BD66) -> 5 | D66: Couts de fermeture et rehabilitation (reel) | E66: $mm const | G66: =G65/G40 -> 0 | H66: =H65/H40 -> 0 | I66: =I65/I40 -> 0 | J66: =J65/J40 -> 0 | K66: =K65/K40 -> 0 | L66: =L65/L40 -> 0 | M66: =M65/M40 -> 0 | N66: =N65/N40 -> 0 | ... BD66: =BD65/BD40 -> 0
D67: Couts de fermeture, equivalent par annee | E67: $mm nominal | G67: =$C$66*G40*(Paramètres!G113<=$C$64)*(1+Paramètres!$F$95) -> 5.1 | H67: =$C$66*H40*(Paramètres!H113<=$C$64)*(1+Paramètres!$F$95) -> 5.202 | I67: =$C$66*I40*(Paramètres!I113<=$C$64)*(1+Paramètres!$F$95) -> 5.30604 | J67: =$C$66*J40*(Paramètres!J113<=$C$64)*(1+Paramètres!$F$95) -> 5.4121608 | K67: =$C$66*K40*(Paramètres!K113<=$C$64)*(1+Paramètres!$F$95) -> 5.520404 | L67: =$C$66*L40*(Paramètres!L113<=$C$64)*(1+Paramètres!$F$95) -> 5.6308121 | M67: =$C$66*M40*(Paramètres!M113<=$C$64)*(1+Paramètres!$F$95) -> 5.7434283 | N67: =$C$66*N40*(Paramètres!N113<=$C$64)*(1+Paramètres!$F$95) -> 5.8582969 | ... BD67: =$C$66*BD40*(Paramètres!BD113<=$C$64)*(1+Paramètres!$F$95) -> 0
D69: % des reserves extraites, par annee | E69: % | G69: =SUM(Paramètres!$G$115:G115)/Paramètres!$C$115 -> 0.057189542 | H69: =SUM(Paramètres!$G$115:H115)/Paramètres!$C$115 -> 0.14098973 | I69: =SUM(Paramètres!$G$115:I115)/Paramètres!$C$115 -> 0.22502334 | J69: =SUM(Paramètres!$G$115:J115)/Paramètres!$C$115 -> 0.31839402 | K69: =SUM(Paramètres!$G$115:K115)/Paramètres!$C$115 -> 0.41176471 | L69: =SUM(Paramètres!$G$115:L115)/Paramètres!$C$115 -> 0.50513539 | M69: =SUM(Paramètres!$G$115:M115)/Paramètres!$C$115 -> 0.59850607 | N69: =SUM(Paramètres!$G$115:N115)/Paramètres!$C$115 -> 0.67320261 | ... BD69: =SUM(Paramètres!$G$115:BD115)/Paramètres!$C$115 -> 1
D70: Reserves exploitables restantes au 31 decembre | E70: tons | G70: =Paramètres!$C$115-SUM(Paramètres!$G$115:G115) -> 4039000 | H70: =Paramètres!$C$115-SUM(Paramètres!$G$115:H115) -> 3680000 | I70: =Paramètres!$C$115-SUM(Paramètres!$G$115:I115) -> 3320000 | J70: =Paramètres!$C$115-SUM(Paramètres!$G$115:J115) -> 2920000 | K70: =Paramètres!$C$115-SUM(Paramètres!$G$115:K115) -> 2520000 | L70: =Paramètres!$C$115-SUM(Paramètres!$G$115:L115) -> 2120000 | M70: =Paramètres!$C$115-SUM(Paramètres!$G$115:M115) -> 1720000 | N70: =Paramètres!$C$115-SUM(Paramètres!$G$115:N115) -> 1400000 | ... BD70: =Paramètres!$C$115-SUM(Paramètres!$G$115:BD115) -> 0
D71: Repere - fonds de rehabilitation | E71: repere | G71: =1*(G69>Paramètres!$F$40)*(Paramètres!G115>0) -> 1 | H71: =1*(H69>Paramètres!$F$40)*(Paramètres!H115>0) -> 1 | I71: =1*(I69>Paramètres!$F$40)*(Paramètres!I115>0) -> 1 | J71: =1*(J69>Paramètres!$F$40)*(Paramètres!J115>0) -> 1 | K71: =1*(K69>Paramètres!$F$40)*(Paramètres!K115>0) -> 1 | L71: =1*(L69>Paramètres!$F$40)*(Paramètres!L115>0) -> 1 | M71: =1*(M69>Paramètres!$F$40)*(Paramètres!M115>0) -> 1 | N71: =1*(N69>Paramètres!$F$40)*(Paramètres!N115>0) -> 1 | ... BD71: =1*(BD69>Paramètres!$F$40)*(Paramètres!BD115>0) -> 0
C72: =SUM(G72:BD72) -> 4284000 | D72: Production pendant la periode de rehabilitation | E72: tonnes | G72: =G71*Paramètres!G115 -> 245000 | H72: =H71*Paramètres!H115 -> 359000 | I72: =I71*Paramètres!I115 -> 360000 | J72: =J71*Paramètres!J115 -> 400000 | K72: =K71*Paramètres!K115 -> 400000 | L72: =L71*Paramètres!L115 -> 400000 | M72: =M71*Paramètres!M115 -> 400000 | N72: =N71*Paramètres!N115 -> 320000 | ... BD72: =BD71*Paramètres!BD115 -> 0
C73: =SUM(G73:BD73) -> 46097000 | D73: Production cumulee pendant la periode de rehabilitation | E73: tonnes | G73: =(G72+F73)*G71 -> 245000 | H73: =(H72+G73)*H71 -> 604000 | I73: =(I72+H73)*I71 -> 964000 | J73: =(J72+I73)*J71 -> 1364000 | K73: =(K72+J73)*K71 -> 1764000 | L73: =(L72+K73)*L71 -> 2164000 | M73: =(M72+L73)*M71 -> 2564000 | N73: =(N72+M73)*N71 -> 2884000 | ... BD73: =(BD72+BC73)*BD71 -> 0
C74: =SUM(G74:BD74) -> 0 | D74: Solde initial du fonds de rehabilitation | E74: $mm nominal | G74: =F78 -> 0 | H74: =G78 -> 0 | I74: =H78 -> 0 | J74: =I78 -> 0 | K74: =J78 -> 0 | L74: =K78 -> 0 | M74: =L78 -> 0 | N74: =M78 -> 0 | ... BD74: =BC78 -> 0
C75: =SUM(G75:BD75) -> 0 | D75: Provision autorisee pendant l'annee | E75: $mm nominal | G75: =IF(G71<>0,(G67-G74)*IFERROR(G72/F70,1)*(Paramètres!$F$39="yes"),0) -> 0 | H75: =IF(H71<>0,(H67-H74)*IFERROR(H72/G70,1)*(Paramètres!$F$39="yes"),0) -> 0 | I75: =IF(I71<>0,(I67-I74)*IFERROR(I72/H70,1)*(Paramètres!$F$39="yes"),0) -> 0 | J75: =IF(J71<>0,(J67-J74)*IFERROR(J72/I70,1)*(Paramètres!$F$39="yes"),0) -> 0 | K75: =IF(K71<>0,(K67-K74)*IFERROR(K72/J70,1)*(Paramètres!$F$39="yes"),0) -> 0 | L75: =IF(L71<>0,(L67-L74)*IFERROR(L72/K70,1)*(Paramètres!$F$39="yes"),0) -> 0 | M75: =IF(M71<>0,(M67-M74)*IFERROR(M72/L70,1)*(Paramètres!$F$39="yes"),0) -> 0 | N75: =IF(N71<>0,(N67-N74)*IFERROR(N72/M70,1)*(Paramètres!$F$39="yes"),0) -> 0 | ... BD75: =IF(BD71<>0,(BD67-BD74)*IFERROR(BD72/BC70,1)*(Paramètres!$F$39="yes"),0) -> 0
C76: =SUM(G76:BD76) -> 0 | D76: Retraits du fonds pour payer les couts de rehabilitation | E76: $mm nominal | G76: =MIN(G65,F78)*-1 -> 0 | H76: =MIN(H65,G78)*-1 -> 0 | I76: =MIN(I65,H78)*-1 -> 0 | J76: =MIN(J65,I78)*-1 -> 0 | K76: =MIN(K65,J78)*-1 -> 0 | L76: =MIN(L65,K78)*-1 -> 0 | M76: =MIN(M65,L78)*-1 -> 0 | N76: =MIN(N65,M78)*-1 -> 0 | ... BD76: =MIN(BD65,BC78)*-1 -> 0
C77: =SUM(G77:BD77) -> 0 | D77: Solde positive | E77: $mm nominal | G77: =(G76<>0)*(G74+G76)*-1 -> 0 | H77: =(H76<>0)*(H74+H76)*-1 -> 0 | I77: =(I76<>0)*(I74+I76)*-1 -> 0 | J77: =(J76<>0)*(J74+J76)*-1 -> 0 | K77: =(K76<>0)*(K74+K76)*-1 -> 0 | L77: =(L76<>0)*(L74+L76)*-1 -> 0 | M77: =(M76<>0)*(M74+M76)*-1 -> 0 | N77: =(N76<>0)*(N74+N76)*-1 -> 0 | ... BD77: =(BD76<>0)*(BD74+BD76)*-1 -> 0
D78: Solde final | E78: $mm nominal | G78: =SUM(G74:G77) -> 0 | H78: =SUM(H74:H77) -> 0 | I78: =SUM(I74:I77) -> 0 | J78: =SUM(J74:J77) -> 0 | K78: =SUM(K74:K77) -> 0 | L78: =SUM(L74:L77) -> 0 | M78: =SUM(M74:M77) -> 0 | N78: =SUM(N74:N77) -> 0 | ... BD78: =SUM(BD74:BD77) -> 0
D80: Redevance
C81: =SUM(G81:BD81) -> 7785.0252 | D81: Chiffre d'affaires brut | E81: $mm nominal | G81: =G43 -> 392 | H81: =H43 -> 585.888 | I81: =I43 -> 599.2704 | J81: =J43 -> 679.17312 | K81: =K43 -> 692.75658 | L81: =L43 -> 706.61171 | M81: =M43 -> 720.74395 | N81: =N43 -> 588.12706 | ... BD81: =BD43 -> 0
C82: =SUM(G82:BD82) -> 7785.0252 | D82: Chiffre d'affaires net | E82: $mm nominal | G82: =G45 -> 392 | H82: =H45 -> 585.888 | I82: =I45 -> 599.2704 | J82: =J45 -> 679.17312 | K82: =K45 -> 692.75658 | L82: =L45 -> 706.61171 | M82: =M45 -> 720.74395 | N82: =N45 -> 588.12706 | ... BD82: =BD45 -> 0
C83: =SUM(G83:BD83) -> 7785.0252 | D83: Assiette de la redevance: revenu net | E83: $mm nominal | G83: =IF(G29=0,0,IF(Paramètres!$F$12="gross",G81,G82)) -> 392 | H83: =IF(H29=0,0,IF(Paramètres!$F$12="gross",H81,H82)) -> 585.888 | I83: =IF(I29=0,0,IF(Paramètres!$F$12="gross",I81,I82)) -> 599.2704 | J83: =IF(J29=0,0,IF(Paramètres!$F$12="gross",J81,J82)) -> 679.17312 | K83: =IF(K29=0,0,IF(Paramètres!$F$12="gross",K81,K82)) -> 692.75658 | L83: =IF(L29=0,0,IF(Paramètres!$F$12="gross",L81,L82)) -> 706.61171 | M83: =IF(M29=0,0,IF(Paramètres!$F$12="gross",M81,M82)) -> 720.74395 | N83: =IF(N29=0,0,IF(Paramètres!$F$12="gross",N81,N82)) -> 588.12706 | ... BD83: =IF(BD29=0,0,IF(Paramètres!$F$12="gross",BD81,BD82)) -> 0
D84: Taux 1 | E84: % | G84: =Paramètres!$F$11 -> 0.05 | H84: =Paramètres!$F$11 -> 0.05 | I84: =Paramètres!$F$11 -> 0.05 | J84: =Paramètres!$F$11 -> 0.05 | K84: =Paramètres!$F$11 -> 0.05 | L84: =Paramètres!$F$11 -> 0.05 | M84: =Paramètres!$F$11 -> 0.05 | N84: =Paramètres!$F$11 -> 0.05 | ... BD84: =Paramètres!$F$11 -> 0.05
D85: Taux 2 | E85: % | G85: =IF(Paramètres!G$108<Paramètres!$J$60,Paramètres!$K$60,IF(Paramètres!G$108<Paramètres!$J$61,Paramètres!$K$61,IF(Paramètres!G$108>Paramètres!$J$61,Paramètres!$K$62,Paramètres!$K$62))) -> 0.04 | H85: =IF(Paramètres!H$108<Paramètres!$J$60,Paramètres!$K$60,IF(Paramètres!H$108<Paramètres!$J$61,Paramètres!$K$61,IF(Paramètres!H$108>Paramètres!$J$61,Paramètres!$K$62,Paramètres!$K$62))) -> 0.04 | I85: =IF(Paramètres!I$108<Paramètres!$J$60,Paramètres!$K$60,IF(Paramètres!I$108<Paramètres!$J$61,Paramètres!$K$61,IF(Paramètres!I$108>Paramètres!$J$61,Paramètres!$K$62,Paramètres!$K$62))) -> 0.04 | J85: =IF(Paramètres!J$108<Paramètres!$J$60,Paramètres!$K$60,IF(Paramètres!J$108<Paramètres!$J$61,Paramètres!$K$61,IF(Paramètres!J$108>Paramètres!$J$61,Paramètres!$K$62,Paramètres!$K$62))) -> 0.04 | K85: =IF(Paramètres!K$108<Paramètres!$J$60,Paramètres!$K$60,IF(Paramètres!K$108<Paramètres!$J$61,Paramètres!$K$61,IF(Paramètres!K$108>Paramètres!$J$61,Paramètres!$K$62,Paramètres!$K$62))) -> 0.04 | L85: =IF(Paramètres!L$108<Paramètres!$J$60,Paramètres!$K$60,IF(Paramètres!L$108<Paramètres!$J$61,Paramètres!$K$61,IF(Paramètres!L$108>Paramètres!$J$61,Paramètres!$K$62,Paramètres!$K$62))) -> 0.04 | M85: =IF(Paramètres!M$108<Paramètres!$J$60,Paramètres!$K$60,IF(Paramètres!M$108<Paramètres!$J$61,Paramètres!$K$61,IF(Paramètres!M$108>Paramètres!$J$61,Paramètres!$K$62,Paramètres!$K$62))) -> 0.04 | N85: =IF(Paramètres!N$108<Paramètres!$J$60,Paramètres!$K$60,IF(Paramètres!N$108<Paramètres!$J$61,Paramètres!$K$61,IF(Paramètres!N$108>Paramètres!$J$61,Paramètres!$K$62,Paramètres!$K$62))) -> 0.04 | ... BD85: =IF(Paramètres!BD$108<Paramètres!$J$60,Paramètres!$K$60,IF(Paramètres!BD$108<Paramètres!$J$61,Paramètres!$K$61,IF(Paramètres!BD$108>Paramètres!$J$61,Paramètres!$K$62,Paramètres!$K$62))) -> 0.04
C86: =SUM(G86:BD86) -> 389.25126 | D86: Montant de la redevance | E86: $mm nominal | G86: =G83*CHOOSE(Paramètres!$F$24,G84,G85) -> 19.6 | H86: =H83*CHOOSE(Paramètres!$F$24,H84,H85) -> 29.2944 | I86: =I83*CHOOSE(Paramètres!$F$24,I84,I85) -> 29.96352 | J86: =J83*CHOOSE(Paramètres!$F$24,J84,J85) -> 33.958656 | K86: =K83*CHOOSE(Paramètres!$F$24,K84,K85) -> 34.637829 | L86: =L83*CHOOSE(Paramètres!$F$24,L84,L85) -> 35.330586 | M86: =M83*CHOOSE(Paramètres!$F$24,M84,M85) -> 36.037197 | N86: =N83*CHOOSE(Paramètres!$F$24,N84,N85) -> 29.406353 | ... BD86: =BD83*CHOOSE(Paramètres!$F$24,BD84,BD85) -> 0
D88: Taxe provinciale (redevance unitaire)
D89: Production | E89: tonnes | G89: =G8 -> 245000 | H89: =H8 -> 359000 | I89: =I8 -> 360000 | J89: =J8 -> 400000 | K89: =K8 -> 400000 | L89: =L8 -> 400000 | M89: =M8 -> 400000 | N89: =N8 -> 320000 | ... BD89: =BD8 -> 0
D90: Taxe provinciale | E90: $mm nominal | G90: =(Paramètres!$F$37*Modèle!G89)/1000000 -> 0 | H90: =(Paramètres!$F$37*Modèle!H89)/1000000 -> 0 | I90: =(Paramètres!$F$37*Modèle!I89)/1000000 -> 0 | J90: =(Paramètres!$F$37*Modèle!J89)/1000000 -> 0 | K90: =(Paramètres!$F$37*Modèle!K89)/1000000 -> 0 | L90: =(Paramètres!$F$37*Modèle!L89)/1000000 -> 0 | M90: =(Paramètres!$F$37*Modèle!M89)/1000000 -> 0 | N90: =(Paramètres!$F$37*Modèle!N89)/1000000 -> 0 | ... BD90: =(Paramètres!$F$37*Modèle!BD89)/1000000 -> 0
D92: Redevance a taux variable
D93: Assiette | G93: =G45 -> 392 | H93: =H45 -> 585.888 | I93: =I45 -> 599.2704 | J93: =J45 -> 679.17312 | K93: =K45 -> 692.75658 | L93: =L45 -> 706.61171 | M93: =M45 -> 720.74395 | N93: =N45 -> 588.12706 | ... BD93: =BD45 -> 0
D95: Fourchette de prix 1 | E95: $ | G95: =MIN(Paramètres!G$108,Paramètres!$E60) -> 0 | H95: =MIN(Paramètres!H$108,Paramètres!$E60) -> 0 | I95: =MIN(Paramètres!I$108,Paramètres!$E60) -> 0 | J95: =MIN(Paramètres!J$108,Paramètres!$E60) -> 0 | K95: =MIN(Paramètres!K$108,Paramètres!$E60) -> 0 | L95: =MIN(Paramètres!L$108,Paramètres!$E60) -> 0 | M95: =MIN(Paramètres!M$108,Paramètres!$E60) -> 0 | N95: =MIN(Paramètres!N$108,Paramètres!$E60) -> 0 | ... BD95: =MIN(Paramètres!BD$108,Paramètres!$E60) -> 0
D96: Fourchette de prix 2 | E96: $ | G96: =IF(Paramètres!G$108>Paramètres!$E61,Paramètres!G$108-Paramètres!$E61,0) -> 1600 | H96: =IF(Paramètres!H$108>Paramètres!$E61,Paramètres!H$108-Paramètres!$E61,0) -> 1600 | I96: =IF(Paramètres!I$108>Paramètres!$E61,Paramètres!I$108-Paramètres!$E61,0) -> 1600 | J96: =IF(Paramètres!J$108>Paramètres!$E61,Paramètres!J$108-Paramètres!$E61,0) -> 1600 | K96: =IF(Paramètres!K$108>Paramètres!$E61,Paramètres!K$108-Paramètres!$E61,0) -> 1600 | L96: =IF(Paramètres!L$108>Paramètres!$E61,Paramètres!L$108-Paramètres!$E61,0) -> 1600 | M96: =IF(Paramètres!M$108>Paramètres!$E61,Paramètres!M$108-Paramètres!$E61,0) -> 1600 | N96: =IF(Paramètres!N$108>Paramètres!$E61,Paramètres!N$108-Paramètres!$E61,0) -> 1600 | ... BD96: =IF(Paramètres!BD$108>Paramètres!$E61,Paramètres!BD$108-Paramètres!$E61,0) -> 1600
D97: Fourchette de prix 3 | E97: $ | G97: =IF(Paramètres!G$108>Paramètres!$E62,Paramètres!G$108-Paramètres!$E62,0) -> 1600 | H97: =IF(Paramètres!H$108>Paramètres!$E62,Paramètres!H$108-Paramètres!$E62,0) -> 1600 | I97: =IF(Paramètres!I$108>Paramètres!$E62,Paramètres!I$108-Paramètres!$E62,0) -> 1600 | J97: =IF(Paramètres!J$108>Paramètres!$E62,Paramètres!J$108-Paramètres!$E62,0) -> 1600 | K97: =IF(Paramètres!K$108>Paramètres!$E62,Paramètres!K$108-Paramètres!$E62,0) -> 1600 | L97: =IF(Paramètres!L$108>Paramètres!$E62,Paramètres!L$108-Paramètres!$E62,0) -> 1600 | M97: =IF(Paramètres!M$108>Paramètres!$E62,Paramètres!M$108-Paramètres!$E62,0) -> 1600 | N97: =IF(Paramètres!N$108>Paramètres!$E62,Paramètres!N$108-Paramètres!$E62,0) -> 1600 | ... BD97: =IF(Paramètres!BD$108>Paramètres!$E62,Paramètres!BD$108-Paramètres!$E62,0) -> 1600
D98: Fourchette de prix 4 | E98: $ | G98: =IF(Paramètres!G$108>Paramètres!$E63,Paramètres!G$108-Paramètres!$E63,0) -> 1600 | H98: =IF(Paramètres!H$108>Paramètres!$E63,Paramètres!H$108-Paramètres!$E63,0) -> 1600 | I98: =IF(Paramètres!I$108>Paramètres!$E63,Paramètres!I$108-Paramètres!$E63,0) -> 1600 | J98: =IF(Paramètres!J$108>Paramètres!$E63,Paramètres!J$108-Paramètres!$E63,0) -> 1600 | K98: =IF(Paramètres!K$108>Paramètres!$E63,Paramètres!K$108-Paramètres!$E63,0) -> 1600 | L98: =IF(Paramètres!L$108>Paramètres!$E63,Paramètres!L$108-Paramètres!$E63,0) -> 1600 | M98: =IF(Paramètres!M$108>Paramètres!$E63,Paramètres!M$108-Paramètres!$E63,0) -> 1600 | N98: =IF(Paramètres!N$108>Paramètres!$E63,Paramètres!N$108-Paramètres!$E63,0) -> 1600 | ... BD98: =IF(Paramètres!BD$108>Paramètres!$E63,Paramètres!BD$108-Paramètres!$E63,0) -> 1600
D100: Palier 1 | E100: $mm nominal | G100: =Paramètres!$F60*G95 -> 0 | H100: =Paramètres!$F60*H95 -> 0 | I100: =Paramètres!$F60*I95 -> 0 | J100: =Paramètres!$F60*J95 -> 0 | K100: =Paramètres!$F60*K95 -> 0 | L100: =Paramètres!$F60*L95 -> 0 | M100: =Paramètres!$F60*M95 -> 0 | N100: =Paramètres!$F60*N95 -> 0 | ... BD100: =Paramètres!$F60*BD95 -> 0
D101: Palier 2 | E101: $mm nominal | G101: =Paramètres!$F61*G96 -> 0 | H101: =Paramètres!$F61*H96 -> 0 | I101: =Paramètres!$F61*I96 -> 0 | J101: =Paramètres!$F61*J96 -> 0 | K101: =Paramètres!$F61*K96 -> 0 | L101: =Paramètres!$F61*L96 -> 0 | M101: =Paramètres!$F61*M96 -> 0 | N101: =Paramètres!$F61*N96 -> 0 | ... BD101: =Paramètres!$F61*BD96 -> 0
D102: Palier 3 | E102: $mm nominal | G102: =Paramètres!$F62*G97 -> 0 | H102: =Paramètres!$F62*H97 -> 0 | I102: =Paramètres!$F62*I97 -> 0 | J102: =Paramètres!$F62*J97 -> 0 | K102: =Paramètres!$F62*K97 -> 0 | L102: =Paramètres!$F62*L97 -> 0 | M102: =Paramètres!$F62*M97 -> 0 | N102: =Paramètres!$F62*N97 -> 0 | ... BD102: =Paramètres!$F62*BD97 -> 0
D103: Palier 4 | E103: $mm nominal | G103: =Paramètres!$F63*G98 -> 0 | H103: =Paramètres!$F63*H98 -> 0 | I103: =Paramètres!$F63*I98 -> 0 | J103: =Paramètres!$F63*J98 -> 0 | K103: =Paramètres!$F63*K98 -> 0 | L103: =Paramètres!$F63*L98 -> 0 | M103: =Paramètres!$F63*M98 -> 0 | N103: =Paramètres!$F63*N98 -> 0 | ... BD103: =Paramètres!$F63*BD98 -> 0
C105: =SUM(G105:BD105) -> 0 | D105: Redevance a taux variable | E105: $mm nominal | G105: =SUM(G100:G103)*G8/1000000 -> 0 | H105: =SUM(H100:H103)*H8/1000000 -> 0 | I105: =SUM(I100:I103)*I8/1000000 -> 0 | J105: =SUM(J100:J103)*J8/1000000 -> 0 | K105: =SUM(K100:K103)*K8/1000000 -> 0 | L105: =SUM(L100:L103)*L8/1000000 -> 0 | M105: =SUM(M100:M103)*M8/1000000 -> 0 | N105: =SUM(N100:N103)*N8/1000000 -> 0 | ... BD105: =SUM(BD100:BD103)*BD8/1000000 -> 0
D107: Droits de douane
C108: =SUM(G108:BD108) -> 0 | D108: Droits de douane | E108: $mm nominal | G108: =G50*Paramètres!$F$38 -> 0 | H108: =H50*Paramètres!$F$38 -> 0 | I108: =I50*Paramètres!$F$38 -> 0 | J108: =J50*Paramètres!$F$38 -> 0 | K108: =K50*Paramètres!$F$38 -> 0 | L108: =L50*Paramètres!$F$38 -> 0 | M108: =M50*Paramètres!$F$38 -> 0 | N108: =N50*Paramètres!$F$38 -> 0 | ... BD108: =BD50*Paramètres!$F$38 -> 0
D110: Bonus
C111: =SUM(G111:BD111) -> 0 | D111: Bonus de signature | E111: $mm nominal | G111: =(G28=1)*Paramètres!$F$9 -> 0 | H111: =(H28=1)*Paramètres!$F$9 -> 0 | I111: =(I28=1)*Paramètres!$F$9 -> 0 | J111: =(J28=1)*Paramètres!$F$9 -> 0 | K111: =(K28=1)*Paramètres!$F$9 -> 0 | L111: =(L28=1)*Paramètres!$F$9 -> 0 | M111: =(M28=1)*Paramètres!$F$9 -> 0 | N111: =(N28=1)*Paramètres!$F$9 -> 0 | ... BD111: =(BD28=1)*Paramètres!$F$9 -> 0
D114: EBITDA | E114: $mm nominal | G114: =G54-G86-G90-G105-G108-G111 -> 123.39 | H114: =H54-H86-H90-H105-H108-H111 -> 235.27606 | I114: =I54-I86-I90-I105-I108-I111 -> 170.85033 | J114: =J54-J86-J90-J105-J108-J111 -> 403.25904 | K114: =K54-K86-K90-K105-K108-K111 -> 394.00531 | L114: =L54-L86-L90-L105-L108-L111 -> 433.90376 | M114: =M54-M86-M90-M105-M108-M111 -> 469.60973 | N114: =N54-N86-N90-N105-N108-N111 -> 319.79409 | ... BD114: =BD54-BD86-BD90-BD105-BD108-BD111 -> 0
D116: Taxe sur la marge operationnelle
D117: Profit operationnel [EBITDA] | E117: $mm nominal | G117: =IF(G114<0,0,G114) -> 123.39 | H117: =IF(H114<0,0,H114) -> 235.27606 | I117: =IF(I114<0,0,I114) -> 170.85033 | J117: =IF(J114<0,0,J114) -> 403.25904 | K117: =IF(K114<0,0,K114) -> 394.00531 | L117: =IF(L114<0,0,L114) -> 433.90376 | M117: =IF(M114<0,0,M114) -> 469.60973 | N117: =IF(N114<0,0,N114) -> 319.79409 | ... BD117: =IF(BD114<0,0,BD114) -> 0
D118: Marge operationnelle | E118: % | G118: =IFERROR(IF(G54/G45>0,G54/G45,0),0) -> 0.36477041 | H118: =IFERROR(IF(H54/H45>0,H54/H45,0),0) -> 0.45157173 | I118: =IFERROR(IF(I54/I45>0,I54/I45,0),0) -> 0.33509722 | J118: =IFERROR(IF(J54/J45>0,J54/J45,0),0) -> 0.64375 | K118: =IFERROR(IF(K54/K45>0,K54/K45,0),0) -> 0.61875 | L118: =IFERROR(IF(L54/L45>0,L54/L45,0),0) -> 0.6640625 | M118: =IFERROR(IF(M54/M45>0,M54/M45,0),0) -> 0.7015625 | N118: =IFERROR(IF(N54/N45>0,N54/N45,0),0) -> 0.59375 | ... BD118: =IFERROR(IF(BD54/BD45>0,BD54/BD45,0),0) -> 0
D120: Palier 1 | E120: % | G120: =MIN(G$118,Paramètres!$E$68) -> 0 | H120: =MIN(H$118,Paramètres!$E$68) -> 0 | I120: =MIN(I$118,Paramètres!$E$68) -> 0 | J120: =MIN(J$118,Paramètres!$E$68) -> 0 | K120: =MIN(K$118,Paramètres!$E$68) -> 0 | L120: =MIN(L$118,Paramètres!$E$68) -> 0 | M120: =MIN(M$118,Paramètres!$E$68) -> 0 | N120: =MIN(N$118,Paramètres!$E$68) -> 0 | ... BD120: =MIN(BD$118,Paramètres!$E$68) -> 0
D121: Palier 2 | E121: % | G121: =(G$118>Paramètres!$E68)*(G$118-Paramètres!$E68-SUM(G122:G$136)) -> 0 | H121: =(H$118>Paramètres!$E68)*(H$118-Paramètres!$E68-SUM(H122:H$136)) -> 0 | I121: =(I$118>Paramètres!$E68)*(I$118-Paramètres!$E68-SUM(I122:I$136)) -> 0 | J121: =(J$118>Paramètres!$E68)*(J$118-Paramètres!$E68-SUM(J122:J$136)) -> 0 | K121: =(K$118>Paramètres!$E68)*(K$118-Paramètres!$E68-SUM(K122:K$136)) -> 0 | L121: =(L$118>Paramètres!$E68)*(L$118-Paramètres!$E68-SUM(L122:L$136)) -> 0 | M121: =(M$118>Paramètres!$E68)*(M$118-Paramètres!$E68-SUM(M122:M$136)) -> 0 | N121: =(N$118>Paramètres!$E68)*(N$118-Paramètres!$E68-SUM(N122:N$136)) -> 0 | ... BD121: =(BD$118>Paramètres!$E68)*(BD$118-Paramètres!$E68-SUM(BD122:BD$136)) -> 0
D122: Palier 3 | E122: % | G122: =(G$118>Paramètres!$E69)*(G$118-Paramètres!$E69-SUM(G123:G$136)) -> 0 | H122: =(H$118>Paramètres!$E69)*(H$118-Paramètres!$E69-SUM(H123:H$136)) -> 0 | I122: =(I$118>Paramètres!$E69)*(I$118-Paramètres!$E69-SUM(I123:I$136)) -> 0 | J122: =(J$118>Paramètres!$E69)*(J$118-Paramètres!$E69-SUM(J123:J$136)) -> 0 | K122: =(K$118>Paramètres!$E69)*(K$118-Paramètres!$E69-SUM(K123:K$136)) -> 0 | L122: =(L$118>Paramètres!$E69)*(L$118-Paramètres!$E69-SUM(L123:L$136)) -> 0 | M122: =(M$118>Paramètres!$E69)*(M$118-Paramètres!$E69-SUM(M123:M$136)) -> 0 | N122: =(N$118>Paramètres!$E69)*(N$118-Paramètres!$E69-SUM(N123:N$136)) -> 0 | ... BD122: =(BD$118>Paramètres!$E69)*(BD$118-Paramètres!$E69-SUM(BD123:BD$136)) -> 0
D123: Palier 4 | E123: % | G123: =(G$118>Paramètres!$E70)*(G$118-Paramètres!$E70-SUM(G124:G$136)) -> 0 | H123: =(H$118>Paramètres!$E70)*(H$118-Paramètres!$E70-SUM(H124:H$136)) -> 0 | I123: =(I$118>Paramètres!$E70)*(I$118-Paramètres!$E70-SUM(I124:I$136)) -> 0 | J123: =(J$118>Paramètres!$E70)*(J$118-Paramètres!$E70-SUM(J124:J$136)) -> 0 | K123: =(K$118>Paramètres!$E70)*(K$118-Paramètres!$E70-SUM(K124:K$136)) -> 0 | L123: =(L$118>Paramètres!$E70)*(L$118-Paramètres!$E70-SUM(L124:L$136)) -> 0 | M123: =(M$118>Paramètres!$E70)*(M$118-Paramètres!$E70-SUM(M124:M$136)) -> 0 | N123: =(N$118>Paramètres!$E70)*(N$118-Paramètres!$E70-SUM(N124:N$136)) -> 0 | ... BD123: =(BD$118>Paramètres!$E70)*(BD$118-Paramètres!$E70-SUM(BD124:BD$136)) -> 0
D124: Palier 5 | E124: % | G124: =(G$118>Paramètres!$E71)*(G$118-Paramètres!$E71-SUM(G125:G$136)) -> 0 | H124: =(H$118>Paramètres!$E71)*(H$118-Paramètres!$E71-SUM(H125:H$136)) -> 0 | I124: =(I$118>Paramètres!$E71)*(I$118-Paramètres!$E71-SUM(I125:I$136)) -> 0 | J124: =(J$118>Paramètres!$E71)*(J$118-Paramètres!$E71-SUM(J125:J$136)) -> 0 | K124: =(K$118>Paramètres!$E71)*(K$118-Paramètres!$E71-SUM(K125:K$136)) -> 0 | L124: =(L$118>Paramètres!$E71)*(L$118-Paramètres!$E71-SUM(L125:L$136)) -> 0 | M124: =(M$118>Paramètres!$E71)*(M$118-Paramètres!$E71-SUM(M125:M$136)) -> 0 | N124: =(N$118>Paramètres!$E71)*(N$118-Paramètres!$E71-SUM(N125:N$136)) -> 0 | ... BD124: =(BD$118>Paramètres!$E71)*(BD$118-Paramètres!$E71-SUM(BD125:BD$136)) -> 0
D125: Palier 6 | E125: % | G125: =(G$118>Paramètres!$E72)*(G$118-Paramètres!$E72-SUM(G126:G$136)) -> 0 | H125: =(H$118>Paramètres!$E72)*(H$118-Paramètres!$E72-SUM(H126:H$136)) -> 0 | I125: =(I$118>Paramètres!$E72)*(I$118-Paramètres!$E72-SUM(I126:I$136)) -> 0 | J125: =(J$118>Paramètres!$E72)*(J$118-Paramètres!$E72-SUM(J126:J$136)) -> 0 | K125: =(K$118>Paramètres!$E72)*(K$118-Paramètres!$E72-SUM(K126:K$136)) -> 0 | L125: =(L$118>Paramètres!$E72)*(L$118-Paramètres!$E72-SUM(L126:L$136)) -> 0 | M125: =(M$118>Paramètres!$E72)*(M$118-Paramètres!$E72-SUM(M126:M$136)) -> 0 | N125: =(N$118>Paramètres!$E72)*(N$118-Paramètres!$E72-SUM(N126:N$136)) -> 0 | ... BD125: =(BD$118>Paramètres!$E72)*(BD$118-Paramètres!$E72-SUM(BD126:BD$136)) -> 0
D126: Palier 7 | E126: % | G126: =(G$118>Paramètres!$E73)*(G$118-Paramètres!$E73-SUM(G127:G$136)) -> 0 | H126: =(H$118>Paramètres!$E73)*(H$118-Paramètres!$E73-SUM(H127:H$136)) -> 0 | I126: =(I$118>Paramètres!$E73)*(I$118-Paramètres!$E73-SUM(I127:I$136)) -> 0 | J126: =(J$118>Paramètres!$E73)*(J$118-Paramètres!$E73-SUM(J127:J$136)) -> 0 | K126: =(K$118>Paramètres!$E73)*(K$118-Paramètres!$E73-SUM(K127:K$136)) -> 0 | L126: =(L$118>Paramètres!$E73)*(L$118-Paramètres!$E73-SUM(L127:L$136)) -> 0 | M126: =(M$118>Paramètres!$E73)*(M$118-Paramètres!$E73-SUM(M127:M$136)) -> 0 | N126: =(N$118>Paramètres!$E73)*(N$118-Paramètres!$E73-SUM(N127:N$136)) -> 0 | ... BD126: =(BD$118>Paramètres!$E73)*(BD$118-Paramètres!$E73-SUM(BD127:BD$136)) -> 0
D127: Palier 8 | E127: % | G127: =(G$118>Paramètres!$E74)*(G$118-Paramètres!$E74-SUM(G128:G$136)) -> 0 | H127: =(H$118>Paramètres!$E74)*(H$118-Paramètres!$E74-SUM(H128:H$136)) -> 0 | I127: =(I$118>Paramètres!$E74)*(I$118-Paramètres!$E74-SUM(I128:I$136)) -> 0 | J127: =(J$118>Paramètres!$E74)*(J$118-Paramètres!$E74-SUM(J128:J$136)) -> 0 | K127: =(K$118>Paramètres!$E74)*(K$118-Paramètres!$E74-SUM(K128:K$136)) -> 0 | L127: =(L$118>Paramètres!$E74)*(L$118-Paramètres!$E74-SUM(L128:L$136)) -> 0 | M127: =(M$118>Paramètres!$E74)*(M$118-Paramètres!$E74-SUM(M128:M$136)) -> 0 | N127: =(N$118>Paramètres!$E74)*(N$118-Paramètres!$E74-SUM(N128:N$136)) -> 0 | ... BD127: =(BD$118>Paramètres!$E74)*(BD$118-Paramètres!$E74-SUM(BD128:BD$136)) -> 0
D128: Palier 9 | E128: % | G128: =(G$118>Paramètres!$E75)*(G$118-Paramètres!$E75-SUM(G129:G$136)) -> 0 | H128: =(H$118>Paramètres!$E75)*(H$118-Paramètres!$E75-SUM(H129:H$136)) -> 0 | I128: =(I$118>Paramètres!$E75)*(I$118-Paramètres!$E75-SUM(I129:I$136)) -> 0 | J128: =(J$118>Paramètres!$E75)*(J$118-Paramètres!$E75-SUM(J129:J$136)) -> 0 | K128: =(K$118>Paramètres!$E75)*(K$118-Paramètres!$E75-SUM(K129:K$136)) -> 0 | L128: =(L$118>Paramètres!$E75)*(L$118-Paramètres!$E75-SUM(L129:L$136)) -> 0 | M128: =(M$118>Paramètres!$E75)*(M$118-Paramètres!$E75-SUM(M129:M$136)) -> 0 | N128: =(N$118>Paramètres!$E75)*(N$118-Paramètres!$E75-SUM(N129:N$136)) -> 0 | ... BD128: =(BD$118>Paramètres!$E75)*(BD$118-Paramètres!$E75-SUM(BD129:BD$136)) -> 0
...
