Workbook
Name Agency_type: Table15[Type d''Agence]
Name Commodities_list: Table5_Commodities_list[Description de produit HS av. volume]
Name Commodity_names: Table5_Commodities_list[Description de produit HS]
Name Companies_list: Companies[Nom complet de l’entreprise]
Name Currency_code_list: Table1_Country_codes_and_currencies[Code de devise (ISO 4217)]
Name GFS_list: Table6_GFS_codes_classification[Combiné]
Name Government_entities_list: Government_agencies[Nom complet de l’entité]
Name Project_phases_list: Table12[Étapes du projet]
Name Projectname: Companies15[Nom complet du projet]
Name Reporting_options_list: Table3_Reporting_options[Liste]
Name Revenue_stream_list: Government_revenues_table[Nom du flux de revenus]
Name Sector_list: Table7_sectors[Secteur (s)]
Name Simple_options_list: Table2_Simple_options[Liste]
Name Total_reconciled: Table10[Valeur de revenus]
Name Total_revenues: Government_revenues_table[Valeur des revenus]

Sheet Introduction
E4: Rempli le : | F4: 45293
C10: Modèle de données résumées pour les divulgations ITIE
C11: Version 2.0 appliquée le 1er Juillet 2019
C13: En remplissant ce modèle de données résumées avec des données de votre Rapport ITIE, vous rendrez ces dernières accessibles sous un format lisible par machine (Exigence 7.2.d).
C14: « Rendre le Rapport ITIE disponible en format données ouvertes (xlsx ou csv) en ligne et faire connaître sa disponibilité » - Exigence ITIE 7.1.c
C16: Comment fonctionne la publication de données ITIE :
C17: 1. N’utiliser qu’un classeur Excel par exercice fiscal couvert. Si la déclaration porte à la fois sur les hydrocarbures et l’exploitation minière, ces deux secteurs peuvent être inclus dans un seul classeur.
C18: 2. Remplir le classeur entier - parties 1 à 5
C19: 3. Prière de soumettre cette fiche de données en même temps que le Rapport ITIE. L’envoyer au Secrétariat international à : data@eiti.org.
C20: 4. Les données serviront à alimenter le référentiel mondial de données ITIE, disponible sur le site Internet international de l’ITIE à https://eiti.org/fr/donnees. Le fichier vous sera renvoyé, afin de pouvoir être publié sur les canaux de votre choix.
C22: Le présent formulaire modèle devra être rempli intégralement et soumis au Secrétariat international de l’ITIE pour chaque exercice fiscal couvert par le rapportage ITIE.
C25: Ce classeur comporte cinq parties. Insérer vos données en commençant par la partie 1 et continuer jusqu’à la partie 5
C27: Partie 1 (Présentation) : Insérer les caractéristiques relatives au pays et aux données.
... C31: Partie 5 (Données d’entreprise) : Inscrire des données d’entreprise - et celle de niveau projet - par flux de revenus.
C33: Le Secrétariat international peut prodiguer conseils et soutien sur demande. Veuillez le contacter à | E33: data@eiti.org
C35: Les cellules en orange doivent être complétées avant la soumission | E35: Les cellules en bleu ne servent qu’à indiquer les sources et/ou à inscrire des commentaires | G35: Les cellules en blanc n’exigent aucune action
C37: Vous recevrez des retours immédiats sur un certain nombre des données que vous aurez inscrites, et certaines cellules se rempliront automatiquement.
C40: Terminologie : Divulgation | E40: Terminologie : Options simples
C41: Oui, divulgation systématique : Si les données sont divulguées régulièrement et systématiquement par des entités de l’État et ou des entreprises, et si ces données sont fiables, sélectionner Oui, divulgation systématique | E41: Oui : Tous les aspects de la question ont reçu une réponse/ont été couverts.
C42: Oui, à travers le rapportage ITIE : Si le Rapport ITIE ou son site couvre certaines lacunes de divulgation relatives aux données du gouvernement ou des entreprises, sélectionner « Oui, dans le Rapport ITIE ». | E42: Partiellement : Des aspects de la question ont reçu une réponse/ont été couverts.
C43: Non disponible : Les données sont applicables au pays, mais il n’y a pas de données ou d’informations disponibles. | E43: Non : Aucune information n’est couverte.
C44: Sans objet : Si une exigence n’est pas pertinente, sélectionner « Sans objet ». Faire référence à toute information à ce sujet, telle que contenue dans le Rapport ITIE ou dans le procès-verbal d’une réunion du Groupe multipartite. | E44: Sans objet : La question n’est pas pertinente pour la rubrique en question. Si une explication est requise, faire référence à toute information démontrant la non-applicabilité.
C46: Pour plus d’information sur l’ITIE, visitez notre site Internet https://eiti.org/fr
C47: Vous voulez en savoir plus sur votre pays ? Vérifiez si votre pays met en œuvre la Norme ITIE en visitant https://eiti.org/fr/pays
C48: Pour la version la plus récente des modèles de données résumées, consultez https://eiti.org/fr/document/modele-donnees-resumees-itie
C49: Faites-nous connaître vos réactions ou signalez tout conflit au niveau des données ! Écrivez-nous à data@eiti.org
C51: Site Internet www.eiti.org Courriel secretariat@eiti.org Téléphone +47 22 20 08 00 Télécopieur +47 22 83 08 02
C52: Adresse EITI International Secretariat, Rådhusgata 26, 0151 Oslo, Norvège
B53: Pays ou région
B55: Exercice fiscal couvert par ce fichier de données
B56: Exercice fiscal couvert par ce fichier de données
B58: Source de données
B59: Source de données
B60: Source de données
B61: Source de données
B62: Source de données
B63: Source de données
B64: Source de données
B65: Source de données
B66: Source de données
... B93: Coordonnées de contact : soumission de données

Sheet Partie 1 - Présentation
G3: Modèle de données résumées
G4: =Introduction!G4 -> 0
C8: Partie 1 - (Présentation) Elle couvre les caractéristiques du pays et des données
C9: Comment remplir cette feuille :
C10: 1. Commençant par en haut, sélectionner votre réponse dans la colonne grise. Des indications s’affichent dans les cadres jaunes dès que la cellule a été sélectionnée.
C11: 2. Lorsqu’il aura été répondu à certaines questions, de nouvelles indications et questions peuvent s’afficher. Merci de répondre à chacune d’elles jusqu’à ce que la section ait été remplie.
C12: 3. Inclure au besoin toute information supplémentaire ou tout commentaire dans la colonne Source/Commentaires.
C13: Si vous avez des questions, veuillez contacter data@eiti.org
C15: Les cellules en orange doivent être complétées avant la soumission | E15: Les cellules en bleu pâle ne servent qu’à indiquer les sources et/ou à inscrire des commentaires | G15: Les cellules en blanc n’exigent aucune action
C17: Partie 1 - Présentation
C18: Description | E18: Inscrire les données dans cette colonne | G18: Source/Commentaires
C19: Pays ou région
B20: Pays ou région | C20: Nom du pays ou de la région | E20: Sénégal
B21: Pays ou région | C21: Code ISO de la devise | E21: =IFERROR(VLOOKUP($E$20,Table1_Country_codes_and_currencies[],3,FALSE),"") -> SEN
B22: Pays ou région | C22: Nom de la monnaie nationale | E22: =IFERROR(VLOOKUP($E$20,Table1_Country_codes_and_currencies[],7,FALSE),"") -> Franc CFA d’Afrique de l’Ouest
B23: Pays ou région | C23: Monnaie nationale selon ISO-4217 | E23: =IFERROR(VLOOKUP($E$20,Table1_Country_codes_and_currencies[],5,FALSE),"") -> XOF
C24: Exercice fiscal couvert par ce fichier de données
B25: Exercice fiscal couvert par ce fichier de données | C25: Date de début | E25: 44562
B26: Exercice fiscal couvert par ce fichier de données | C26: Date de fin | E26: 44926
C27: Source de données
B28: Source de données | C28: Un Rapport ITIE a-t-il été préparé par un Administrateur indépendant ? | E28: Oui
B29: Source de données | C29: Quel est le nom de l’entreprise ? | E29: Enerteam
B30: Source de données | C30: Date à laquelle le Rapport ITIE a été rendu public | E30: 45282
B31: Source de données | C31: URL, Rapport ITIE | E31: https://itie.sn/rapport-itie-2022/
B32: Source de données | C32: Les données ITIE sont-elles systématiquement divulguées par le gouvernement à une adresse unique? | E32: Oui | G32: A travers la plateforme "Fusion"
B33: Source de données | C33: Date de publication des données ITIE | G33: Annuellement avec la publication du rapport ITIE
B34: Source de données | C34: Lien vers le site Internet (URL) de données ITIE | E34: https://donnees.itie.sn/dashboard/
B35: Source de données | C35: Existe-t-il d’autres fichiers de caractère pertinent ? | E35: Oui | G35: Les annexes au rapport ITIE 2022
B36: Source de données | C36: Date à laquelle l’autre fichier a été rendu public | E36: 45282
B37: Source de données | C37: URL | E37: https://itie.sn/rapport-itie-2022/ | G37: Les annexes au rapport ITIE 2022
C38: Accessibilités des données et données ouvertes (Exigence 7.2)
C39: Le gouvernement applique-t-il une politique de données ouvertes ? | E39: Oui, à travers le rapportage ITIE
B40: Couverture/périmètre des données | C40: Portail/fichiers de données ouvertes | E40: https://donnees.itie.sn/dashboard/
B41: Couverture/périmètre des données | C41: Couverture/périmètre des données
B42: Couverture/périmètre des données | C42: Couverture sectorielle
B43: Couverture/périmètre des données | C43: Pétrole | E43: Oui
B44: Couverture/périmètre des données | C44: Gaz | E44: Oui
B45: Couverture/périmètre des données | C45: Mines (y compris carrières) | E45: Oui
B46: Couverture/périmètre des données | C46: Autres secteurs (autres que les secteur en amont) | E46: Sans objet
B47: Couverture/périmètre des données | C47: Si oui, préciser le nom (insérer de nouvelles lignes si multiples) | E47: Sans objet
B48: Couverture/périmètre des données | C48: Nombre d’entités de l’État déclarantes (Entreprises d'Etat incluses si collectant) | E48: 9
B49: Couverture/périmètre des données | C49: Nombre d’entreprises déclarantes (Entreprises d'Etat incluses si payeur) | E49: 29
B50: Couverture/périmètre des données | C50: Devise de déclaration (codes de devise ISO-4217) | E50: XOF
B51: Couverture/périmètre des données | C51: Taux de change utilisé : 1 USD = | E51: 621.118
B52: Couverture/périmètre des données | C52: Source du taux de change (URL,…): | E52: Rapport annuel 2022 de la BCEAO
B53: Couverture/périmètre des données | C53: Exigence ITIE 4.7: Désagrégation
B54: Couverture/périmètre des données | C54: ... par flux de revenus | E54: Oui
C55: ... par entité de l’État | E55: Oui
C56: ... par entreprise | E56: Oui
C57: ... par projet | E57: Oui
C58: Vue d’ensemble /exigence relative aux données | E58: =SUM(E59:E62) -> 1
C59: Divulgation systématique | E59: =COUNTIF('Partie 2 - Liste de pointage'!$D:$D,Listes!$K$4)/SUM(COUNTIF('Partie 2 - Liste de pointage'!$D:$D,"*Rapportage ITIE ou divulgation systématique?*"),COUNTIF('Partie 2 - Liste de pointage'!$D:$D,Listes!$K$4),COUNTIF('Partie 2 - Liste de pointage'!$D:$D,Listes!$K$5),COUNTIF('Partie 2 - Liste de pointage'!$D:$D,Listes!$K$6),COUNTIF('Partie 2 - Liste de pointage'!$D:$D,Listes!$K$7)) -> 0.12962963 | G59: Calcul à l’aide de la liste de vérification
C60: À travers le rapportage ITIE | E60: =COUNTIF('Partie 2 - Liste de pointage'!$D:$D,Listes!$K$5)/SUM(COUNTIF('Partie 2 - Liste de pointage'!$D:$D,"*Rapportage ITIE ou divulgation systématique?*"),COUNTIF('Partie 2 - Liste de pointage'!$D:$D,Listes!$K$4),COUNTIF('Partie 2 - Liste de pointage'!$D:$D,Listes!$K$5),COUNTIF('Partie 2 - Liste de pointage'!$D:$D,Listes!$K$6),COUNTIF('Partie 2 - Liste de pointage'!$D:$D,Listes!$K$7)) -> 0.81481481 | G60: Calcul à l’aide de la liste de vérification
B61: Coordonnées de contact : soumission de données | C61: Sans objet. | E61: =COUNTIF('Partie 2 - Liste de pointage'!$D:$D,Listes!$K$6)/SUM(COUNTIF('Partie 2 - Liste de pointage'!$D:$D,"*Rapportage ITIE ou divulgation systématique?*"),COUNTIF('Partie 2 - Liste de pointage'!$D:$D,Listes!$K$4),COUNTIF('Partie 2 - Liste de pointage'!$D:$D,Listes!$K$5),COUNTIF('Partie 2 - Liste de pointage'!$D:$D,Listes!$K$6),COUNTIF('Partie 2 - Liste de pointage'!$D:$D,Listes!$K$7)) -> 0.037037037 | G61: Calcul à l’aide de la liste de vérification
B62: Coordonnées de contact : soumission de données | C62: Information non disponible | E62: =COUNTIF('Partie 2 - Liste de pointage'!$D:$D,Listes!$K$7)/SUM(COUNTIF('Partie 2 - Liste de pointage'!$D:$D,"*Rapportage ITIE ou divulgation systématique?*"),COUNTIF('Partie 2 - Liste de pointage'!$D:$D,Listes!$K$4),COUNTIF('Partie 2 - Liste de pointage'!$D:$D,Listes!$K$5),COUNTIF('Partie 2 - Liste de pointage'!$D:$D,Listes!$K$6),COUNTIF('Partie 2 - Liste de pointage'!$D:$D,Listes!$K$7)) -> 0.018518519 | G62: Calcul à l’aide de la liste de vérification
B63: Coordonnées de contact : soumission de données | C63: Nom et coordonnées de contact de la personne soumettant ce fichier
B64: Coordonnées de contact : soumission de données | C64: Name | E64: Othman Marzouk
C65: Organisation | E65: Enerteam
C66: Adresse électronique | E66: itie.sn@enerteam.tn
C69: Pour plus d’information sur l’ITIE, visitez notre site Internet https://eiti.org/fr
C70: Vous voulez en savoir plus sur votre pays ? Vérifiez si votre pays met en œuvre la Norme ITIE en visitant https://eiti.org/fr/pays
C71: Pour la version la plus récente des modèles de données résumées, consultez https://eiti.org/fr/document/modele-donnees-resumees-itie
C72: Faites-nous connaître vos réactions ou signalez tout conflit au niveau des données ! Écrivez-nous à data@eiti.org
B73: Couverture/périmètre des données
B74: Couverture/périmètre des données | C74: Site Internet www.eiti.org Courriel secretariat@eiti.org Téléphone +47 22 20 08 00 Télécopieur +47 22 83 08 02
B75: Couverture/périmètre des données | C75: Adresse EITI International Secretariat, Rådhusgata 26, 0151 Oslo, Norvège
B76: Couverture/périmètre des données
B77: Couverture/périmètre des données
B78: Couverture/périmètre des données
B79: Couverture/périmètre des données
B80: Couverture/périmètre des données
B81: Couverture/périmètre des données
B82: Couverture/périmètre des données
B83: Couverture/périmètre des données
B84: Couverture/périmètre des données
B85: Couverture/périmètre des données
B86: Couverture/périmètre des données
B87: Couverture/périmètre des données
... B97: Coordonnées de contact : soumission de données

Sheet Partie 2 - Liste de pointage
H3: Modèle de données résumées
H4: =Introduction!G4 -> 0
B8: Partie 2 (liste de vérification) Elle couvre l’information contextuelle et financière agrégée prévue par les Exigences ITIE 2,3,4,5 et 6.
B9: Comment remplir cette feuille :
B10: Pour chaque ligne, veuillez procéder comme suit
B11: 1. Commençant par le haut, répondez aux questions de la première colonne (Inclusion). Des indications vous sont données dans les cadres jaunes une fois que la cellule est mise en évidence. Cliquez sur les cellules relatives à chaque Exigence ITIE pour faire apparaître le libellé de la Norme ITIE.
B12: 2. D’autres orientations apparaissent lorsque vous remplissez les cellules. Remplissez-les comme indiqué, complétant chaque colonne de chaque ligne avant de remplir la ligne suivante.
B13: Par exemple, en sélectionnant « Oui, dans le Rapport ITIE », le texte « Veuillez inclure la section du Rapport ITIE » dans la case Source/unités apparaît.
B14: 3. Insérez au besoin toute information supplémentaire ou tout commentaire dans la colonne Commentaires/Notes.
B15: Si vous avez des questions, veuillez contacter data@eiti.org
B17: Les cellules en orange doivent être complétées avant la soumission | D17: Les cellules en bleu pâle ne servent qu’à indiquer les sources et/ou inscrire des commentaires | F17: Ignorez les cellules en blanc, car elles n’exigent aucune action
B19: Partie 2 - Liste de pointage
B20: Veuillez répondre à toutes les questions posées ci-dessous.
B22: Exigence | D22: Inclusion | F22: Source/unités | H22: Commentaires/Notes
B23: Exigence ITIE 2.1 : Cadre légal et régime fiscal
B24: Le gouvernement publie-t-il des informations concernant
B25: Les lois et réglementations ? | D25: Oui, à travers le rapportage ITIE | F25: Section 4.1.3.1 et 4.2.2.1 du rapport ITIE 2022
B26: Vue d’ensemble des rôles des agences gouvernementales ? | D26: Oui, à travers le rapportage ITIE | F26: Section 4.1.3.2 et 4.2.2.2 du rapport ITIE 2022
B27: Régime des droits pétroliers et miniers? | D27: Oui, à travers le rapportage ITIE | F27: Section 4.1.4.2 et 4.2.3.2 du rapport ITIE 2022
B28: Régime fiscal ? | D28: Oui, à travers le rapportage ITIE | F28: Section 4.1.3.3 et 4.2.2.3 du rapport ITIE 2022
B30: Exigence ITIE 2.2: Octroi des contrats et licences
B31: Le gouvernement publie-t-il des informations concernant
B32: le processus d’octroi des licences ? | D32: Oui, à travers le rapportage ITIE | F32: Section 4.1.5.1 du Rapport ITIE 2022 (Mines) Section 4.2.4.1 du Rapport ITIE 2022 (Hydrocarbures)
B33: et les critères techniques et financiers utilisés ? | D33: Oui, à travers le rapportage ITIE | F33: Section 4.1.5.1 du Rapport ITIE 2022 (Mines) Section 4.2.4.1 du Rapport ITIE 2022 (Hydrocarbures) Section 4.2.4.5 du Rapport ITIE 2022 (Hydrocarbures)
B34: le(s) processus de transfert de licences ? | D34: Oui, à travers le rapportage ITIE | F34: Section 4.1.5.2 du Rapport ITIE 2022 (Mines) Section 4.2.4.2 du Rapport ITIE 2022 (Hydrocarbures)
B35: et les critères techniques et financiers utilisés ? | D35: Oui, à travers le rapportage ITIE | F35: Section 4.1.5.2 du Rapport ITIE 2022 (Mines) Section 4.2.4.2 du Rapport ITIE 2022 (Hydrocarbures) Section 4.2.4.5 du Rapport ITIE 2022 (Hydrocarbures)
B36: processus d’appel d’offres : | D36: Oui, à travers le rapportage ITIE | F36: Section 4.1.5.6 du Rapport ITIE 2022 (Mines) Section 4.2.4.6 du Rapport ITIE 2022 (Hydrocarbures)
B37: Nombre d’octrois et de transferts pour l’exercice couvert | D37: Oui, à travers le rapportage ITIE | F37: Section 4.1.5.5 du Rapport ITIE 2022 (Mines) Section 4.2.4.6 du Rapport ITIE 2022 (Hydrocarbures) | H37: Secteur minier : 17 octrois, Les renouvellements opérés en 2022 ne peuvent pas être consultés dans le registre des titres miniers communiqué par la DGM Dix (10) transferts ont été opéré en 2022 Secteur des hydrocarbures : Aucun nouvel octroi réalisé en 2022 1 seul renouvellement en 2022 Pas de transfert en 2022
B39: Exigence ITIE 2.3: Registre des licences
B40: Registres des licences pour le secteur minier | D40: Oui, divulgation systématique | F40: https://cadastreminiersenegal.sn/FR/
B41: Registre des licences pour le secteur pétrolier | D41: Oui, divulgation systématique | F41: https ://cadastrepetrolier.sec.gouv.sn/
B42: Registre des licences pour tout autre secteur - ajouter des lignes au besoin | D42: Sans objet.
B44: Exigence ITIE 2.4: Divulgation des contrats
B45: Politique sur la divulgation des contrats | D45: Oui, à travers le rapportage ITIE | F45: Section 4.7 du Rapport ITIE 2022
B46: Les contrats sont-ils divulgués ? | D46: Oui, divulgation systématique | F46: http://itie.sn/contrats-miniers/ http://itie.sn/hydrocarbure/contrats-petroliers/
B47: Registre des contrats pour le secteur minier | D47: Oui, divulgation systématique
B48: Registre des contrats pour le secteur pétrolier | D48: Oui, divulgation systématique
B49: Registre des contrats pour tout autre secteur - ajouter des ligne s’il y en a plusieurs | D49: Sans objet.
B51: Exigence ITIE 2.5: Propriété réelle
B52: Politique du gouvernement concernant la propriété réelle | D52: Oui, à travers le rapportage ITIE | F52: Section 4.6 du Rapport ITIE 2022
B53: Des données de propriété réelle sont-elles divulguées ? | D53: Oui, à travers le rapportage ITIE | F53: Section 4.6 du Rapport ITIE 2022
B54: Registre de la propriété réelle | D54: =IF(OR(D53=Listes!$K$4),"< nom du registre >","") | F54: =IF(D54="< nom du registre >","< Indiquez l'URL de la source >",IF(D54=Listes!$K$5,"< Référence de la section dans le Rapport ITIE ou URL>",IF(D54=Listes!$K$6,"< Référence de la non-applicabilité >","")))
B56: Exigence ITIE 2.6 : Participation de l’État
B57: Le gouvernement rend-il compte de sa participation dans le secteur extractif ? | D57: Oui, à travers le rapportage ITIE | F57: Section 4.1.7 du Rapport ITIE 2022 Section 4.2.5 du Rapport ITIE 2022
B58: Toute référence à des entreprises d’État (portails ou sites Internet d’entreprise), telle que paraissant dans le Rapport (Ajouter des lignes si plusieurs Entreprises D'Etat) | D58: Oui, divulgation systématique | F58: https://itie.sn/entreprises-detat/ http://www.petrosen.sn/ http://www.miferso.sn/
B59: Référence au(s) rapport(s) financier(s) audité(s) (Ajouter des lignes si plusieurs Entreprises d'Etat) | D59: Oui, à travers le rapportage ITIE | F59: Section 4.1.7.3 du Rapport ITIE 2022 Section 4.2.5.4 du Rapport ITIE 2022
B61: Exigence ITIE 3.1: Prospection
B62: Vue d’ensemble des industries extractives, y compris de toute activité importante de prospection. | D62: Oui, à travers le rapportage ITIE | F62: Section 4.1.6 du Rapport ITIE 2022 Section 4.2.5 du Rapport ITIE 2022
B64: Exigence ITIE 3.2: Production
B65: (Nomenclature SH des Nations Unies)
B66: Divulgation des volumes de production | D66: Oui, à travers le rapportage ITIE | F66: Section 5.4 du Rapport ITIE 2022
B67: Divulgation des valeurs de production | D67: Oui, à travers le rapportage ITIE | F67: Section 5.4 du Rapport ITIE 2022
B68: Or (7108), volume | D68: 15.074027 | F68: Tonnes | H68: Or
B69: Or (7108), valeur | D69: 539698675869 | F69: XOF | H69: Or | P69: 390697165834 | Q69: £
B70: Gaz naturel (2711), volume | D70: 4446906 | F70: Sm3 | H70: Gaz Naturel
B71: =LEFT(B70,SEARCH(",",B70))&" valeur" -> Gaz naturel (2711), valeur | D71: 876975000 | F71: XOF | H71: Gaz Naturel | P71: 1040490000 | Q71: £
B72: Ciment Portland (2523), volume | D72: 4019398 | F72: Tonnes | H72: CIMENT
B73: Ciment Portland (2523), valeur | D73: 179409239495 | F73: XOF | H73: CIMENT | P73: 76722890327 | Q73: £
B74: Autres (2617), volume | D74: 2348892 | F74: Tonnes | H74: CLINKER
B75: Autres (2617), valeur | D75: 83039776543 | F75: XOF | H75: CLINKER | P75: 1847636811 | Q75: £
B76: Autres (2617), volume | D76: 328742 | F76: Tonnes | H76: ILMENITE 54
B77: Autres (2617), valeur | D77: 66987102119 | F77: XOF | H77: ILMENITE 54 | P77: 292022380000 | Q77: £
B78: Phosphates de calcium naturels (2510), volume | D78: 1987398 | F78: Tonnes | H78: PHOSPHATE
B79: Phosphates de calcium naturels (2510), valeur | D79: 59957389947 | F79: XOF | H79: PHOSPHATE | P79: 157671670 | Q79: £
B80: Phosphates de calcium naturels (2510), volume | D80: 549556 | F80: Tonnes | H80: PHOSPHATE NATUREL
B81: Phosphates de calcium naturels (2510), valeur | D81: 56442979011 | F81: XOF | H81: PHOSPHATE NATUREL | P81: 11426587417 | Q81: £
B82: Autres (2617), volume | D82: 34583 | F82: Tonnes | H82: ZIRCON PREMIUM
B83: Autres (2617), valeur | D83: 46680083232 | F83: XOF | H83: ZIRCON PREMIUM | P83: 518248093 | Q83: £
B84: Autres (2617), volume | D84: 4053382 | F84: Tonnes | H84: Basalte
B85: Autres (2617), valeur | D85: 32711986033 | F85: XOF | H85: Basalte | P85: 583517114 | Q85: £
B86: Autres (2617), volume | D86: 22498 | F86: Tonnes | H86: ZIRCON STANDARD
B87: Autres (2617), valeur | D87: 29136495247 | F87: XOF | H87: ZIRCON STANDARD | P87: 267111000 | Q87: £
B88: Autres (2617), volume | D88: 133804 | F88: Tonnes | H88: ILMENITE 58
B89: Autres (2617), valeur | D89: 28951526564 | F89: XOF | H89: ILMENITE 58 | P89: 7551095651 | Q89: £
B90: Calcaire (2521), volume | D90: 1599934 | F90: Sm3 | H90: CALCAIRE
B91: Calcaire (2521), valeur | D91: 7999670000 | F91: XOF | H91: CALCAIRE | P91: 4315183425 | Q91: £
B92: Autres (2617), volume | D92: 35551 | F92: Tonnes | H92: ILMENITE 56
B93: Autres (2617), valeur | D93: 7543497575 | F93: XOF | H93: ILMENITE 56 | P93: 13897822000 | Q93: £
B94: Autres (2617), volume | D94: 26981 | F94: Tonnes | H94: ZIRCON SAND MEDIUM GRADE
B95: Autres (2617), valeur | D95: 7039966533 | F95: XOF | H95: ZIRCON SAND MEDIUM GRADE | P95: 54216941469 | Q95: £
B96: Phosphates de calcium naturels (2510), volume | D96: 69006 | F96: Tonnes | H96: PHOSPHATE SEC CRIBLE
B97: Phosphates de calcium naturels (2510), valeur | D97: 6091675324 | F97: XOF | H97: PHOSPHATE SEC CRIBLE | P97: 3690588362 | Q97: £
B98: Autres (2617), volume | D98: 6284 | F98: Tonnes | H98: LEUCOXENE
B99: Autres (2617), valeur | D99: 5343597553 | F99: XOF | H99: LEUCOXENE | P99: 20728624548 | Q99: £
B100: Autres (2617), volume | D100: 4203 | F100: Tonnes | H100: RUTILE
B101: Autres (2617), valeur | D101: 5251482196 | F101: XOF | H101: RUTILE | P101: 3595901024 | Q101: £
B102: Calcaire (2521), volume | D102: 1990935 | F102: Tonnes | H102: MARNO-CALCAIRE
B103: Calcaire (2521), valeur | D103: 4370102325 | F103: XOF | H103: MARNO-CALCAIRE | P103: 6696786033 | Q103: £
B104: Calcaire (2521), volume | D104: 4242228 | F104: Tonnes | H104: CALCAIRE
B105: Calcaire (2521), valeur | D105: 3557171168 | F105: XOF | H105: CALCAIRE | P105: 3629677988 | Q105: £
B106: Argent (7106), volume | D106: 1.3254081 | F106: Tonnes | H106: Argent
B107: Argent (7106), valeur | D107: 524686399 | F107: XOF | H107: Argent | P107: 33867923004 | Q107: £
B108: Autres (2617), volume | D108: 183914 | F108: Tonnes | H108: LATERITE
B109: Autres (2617), valeur | D109: 395011254 | F109: XOF | H109: LATERITE | P109: 21177898265 | Q109: £
B110: Argile (2509), volume | D110: 400578 | F110: Tonnes | H110: Argile
B111: Argile (2509), valeur | D111: NC | F111: XOF | H111: Argile | P111: 21177898265 | Q111: £
B112: Manganèse (2602), volume | D112: 31092 | F112: Tonnes | H112: Manganèse
B113: Manganèse (2602), valeur | D113: NC | F113: XOF | H113: Manganèse
B115: Exigences ITIE 3.3 : Exportations
B116: Divulgation des volumes d’exportation | D116: Oui, à travers le rapportage ITIE | F116: Section 5.5 du Rapport ITIE 2022
...

Sheet Partie 3 - Entités déclarantes
E3: Modèle de données résumées
E4: =Introduction!G4 -> 0
B8: Partie 3 (Entités déclarantes) Elle énumère les entités déclarantes (entités de l’État, entreprises et projets) et fournit des informations y afférentes.
B9: Comment remplir cette feuille :
B10: 1. Veuillez commencer par la première case (liste des entités déclarantes de l’État), en indiquant le nom de chacune d’elles
B11: 2. Remplissez la ligne des identifiants d’entreprise Des orientations vous seront données dans les cases jaunes lorsque la cellule est mise en évidence
B12: 3. Remplissez la liste des entreprises déclarantes, commençant par la première colonne, « Nom complet de l’entreprise » Remplissez en suivant les instructions, complétant chaque colonne sur chaque ligne avant de commencer la ligne suivante.
B13: 4. Remplissez la liste des Projets à déclarer, commençant par la première colonne, « Nom complet du projet »
B14: Si vous avez des questions, veuillez contacter data@eiti.org
B16: Partie 3 - Entités déclarantes
B17: Veuillez fournir une liste de toutes les entités déclarantes, accompagnée de l’information y afférente
B19: Liste des entités de l’État déclarantes
B20: Nom complet de l’entité | C20: Type d'Agence | D20: N° d’identifiant (le cas échéant) | E20: Total déclaré
B21: Direction Générale des Impôts et des Domaines | C21: Administration centrale | E21: 1.4444216e+11
B22: Direction Générale des Douanes | C22: Administration centrale | E22: 4.4632321e+10
B23: Direction Générale des Mines | C23: Administration centrale | E23: 43205899976
B24: Direction Générale de la Comptabilité Publique et du Trésor | C24: Administration centrale | E24: 20167182595
B25: Institution de Prévoyance Retraite du Sénégal | C25: Administration centrale | E25: 4872733599
B26: Société des Pétroles du Sénégal | C26: Société publique financière et Entreprise d'Etat | E26: 1.4660184e+09
B27: Caisse de Sécurité Sociale | C27: Administration centrale | E27: 8.7298828e+08
B28: Direction des Eaux, Forêts, Chasses et Conservation des Sols | C28: Administration centrale | E28: 5.3841661e+08
B29: Direction de l'Environnement et des Etablissements Classés | C29: Administration centrale | E29: 215142411
E30: =SUBTOTAL(109,Government_agencies[Total déclaré]) -> 2.6041286e+11
B32: Liste des entreprises déclarantes
B33: Identifiants d’entreprise
B34: Exemple : N° identification de contribuable | C34: The Brønnøysund Register Centre | D34: Si possible, indiquer le lien vers le registre ou l’entité
B36: Nom complet de l’entreprise | C36: Type d'entreprise | D36: Identifiant de l’entreprise | E36: Secteur | F36: Matières premières (séparation par virgule) | G36: Cotation boursière ou site Internet d’entreprise | H36: Rapport financier audité (si indisponible, bilan comptable ou flux de trésorerie…) | I36: Rapport de paiements à l’État | J36: Colonne1
B37: Sabodala Gold Operations (SGO) | C37: Privée | D37: 2850023 2G3 | E37: Minier | F37: Or | G37: https://www.endeavourmining.com/investors/institutional-ownership%20https://www.londonstockexchange.com/stock/EDV/endeavour-mining-plc/analysis | H37: Oui | I37: =SUMIF(Table10[Entreprise],Companies[[#This Row],[Nom complet de l’entreprise]],Table10[Valeur de revenus]) -> 79362301472
B38: Société de Commercialisation du Ciment (SOCOCIM) | C38: Privée | D38: 16627 | E38: Minier | F38: Calcaire/Marne | G38: http://www.sococim.com/SOCOCIM-INDUSTRIES | H38: Oui | I38: =SUMIF(Table10[Entreprise],Companies[[#This Row],[Nom complet de l’entreprise]],Table10[Valeur de revenus]) -> 49422883618
B39: Ciments du Sahel (CDS) | C39: Privée | D39: 0325995 2G3 | E39: Minier | F39: Calcaire/Argile/Latérite | H39: Oui | I39: =SUMIF(Table10[Entreprise],Companies[[#This Row],[Nom complet de l’entreprise]],Table10[Valeur de revenus]) -> 31680942223
B40: Grande Côte Opérations (GCO) | C40: Privée | D40: 2849258 2G3 | E40: Minier | F40: Minéraux lourds | G40: https://gco.eramet.com/ | H40: Oui | I40: =SUMIF(Table10[Entreprise],Companies[[#This Row],[Nom complet de l’entreprise]],Table10[Valeur de revenus]) -> 19192313250
B41: Petowal Mining Company (PMC) SA | C41: Privée | D41: 005844700 | E41: Minier | F41: Or/Argent | G41: https://www.rml.com.au/ | H41: Oui | I41: =SUMIF(Table10[Entreprise],Companies[[#This Row],[Nom complet de l’entreprise]],Table10[Valeur de revenus]) -> 18111307290
B42: Dangote Industries Sénégal SA (DANGOTE) | C42: Privée | D42: 2707208 2G3 | E42: Minier | F42: Argile, Calcaire, Latérite | G42: https://www.dangotecement.com/operations/senegal/ | H42: Oui | I42: =SUMIF(Table10[Entreprise],Companies[[#This Row],[Nom complet de l’entreprise]],Table10[Valeur de revenus]) -> 15636352228
B43: Woodside Energy Senegal | C43: Privée | D43: 005014204 2G0 | E43: Pétrole & Gaz | F43: Gaz | G43: https://www.woodside.com.au/fr/what-we-do/international-exploration-developments-and-marketing/s%c3%a9n%c3%a9gal | H43: Oui | I43: =SUMIF(Table10[Entreprise],Companies[[#This Row],[Nom complet de l’entreprise]],Table10[Valeur de revenus]) -> 1.3300041e+10
B44: BP Sénégal Investments Limited | C44: Privée | D44: 006420509 | E44: Pétrole & Gaz | F44: Gaz | G44: https://www.bp.com/ | H44: Oui | I44: =SUMIF(Table10[Entreprise],Companies[[#This Row],[Nom complet de l’entreprise]],Table10[Valeur de revenus]) -> 8882740419
B45: Industries Chimiques du Sénégal (ICS) | C45: Privée | D45: 0022955 2G3 | E45: Minier | F45: Phosphates | G45: http://www.ics.sn/ | H45: Oui | I45: =SUMIF(Table10[Entreprise],Companies[[#This Row],[Nom complet de l’entreprise]],Table10[Valeur de revenus]) -> 6382723361
B46: Compagnie Générale d'Exploitation de Carrière (COGECA) | C46: Privée | D46: 0196784 | E46: Minier | F46: Basalte/calcaire | H46: Oui | I46: =SUMIF(Table10[Entreprise],Companies[[#This Row],[Nom complet de l’entreprise]],Table10[Valeur de revenus]) -> 3845633020
B47: Gécamines (GECAMINES) | C47: Privée | D47: 2292168 2G3 | E47: Minier | F47: Basalte | G47: https://www.gecamines.cd/ | H47: Oui | I47: =SUMIF(Table10[Entreprise],Companies[[#This Row],[Nom complet de l’entreprise]],Table10[Valeur de revenus]) -> 3544861329
B48: Société Minière de la Vallée du fleuve Sénégal (SOMIVA) | C48: Privée | D48: 4475142 2G3 | E48: Minier | F48: Phosphates | H48: Non | I48: =SUMIF(Table10[Entreprise],Companies[[#This Row],[Nom complet de l’entreprise]],Table10[Valeur de revenus]) -> 1872119684
B49: Société des Pétroles du Sénégal (PETROSEN) | C49: Société publique financière et Entreprise d'Etat | D49: 0224498 2G3 | E49: Pétrole & Gaz | F49: Gaz | G49: http://www.petrosen.sn/ | H49: Oui | I49: =SUMIF(Table10[Entreprise],Companies[[#This Row],[Nom complet de l’entreprise]],Table10[Valeur de revenus]) -> 942684751
B50: Oranto Petroleum | C50: Privée | D50: 003059434 | E50: Pétrole & Gaz | F50: Gaz | G50: https://atlas-oranto.com/portfolio/senegal/ | H50: Oui | I50: =SUMIF(Table10[Entreprise],Companies[[#This Row],[Nom complet de l’entreprise]],Table10[Valeur de revenus]) -> 7.9115676e+08
B51: Baobab Mining and Chemical Corp SA | E51: Minier | I51: =SUMIF(Table10[Entreprise],Companies[[#This Row],[Nom complet de l’entreprise]],Table10[Valeur de revenus]) -> 755740640
B52: IAMGOLD BOTO | C52: Privée | D52: 007768007 | E52: Minier | F52: Or | G52: https://www.iamgold.com/French/exploitations/projets-de-developpement/Projet-Boto-Sngal/default.aspx | H52: Oui | I52: =SUMIF(Table10[Entreprise],Companies[[#This Row],[Nom complet de l’entreprise]],Table10[Valeur de revenus]) -> 664821836
B53: Agem Sénégal Exploration SUARL (AGEM) | C53: Privée | D53: 4151750 2Y2 | E53: Minier | F53: Or | H53: Oui | I53: =SUMIF(Table10[Entreprise],Companies[[#This Row],[Nom complet de l’entreprise]],Table10[Valeur de revenus]) -> 487814268
B54: Sephos Senegal SA (SEPHOS) | C54: Privée | D54: 4013041 | E54: Minier | F54: Phosphates | H54: Oui | I54: =SUMIF(Table10[Entreprise],Companies[[#This Row],[Nom complet de l’entreprise]],Table10[Valeur de revenus]) -> 431725575
B55: Société Sénégalaise des Phosphates de Thiès (SSPT) | C55: Privée | D55: 0028797 2G3 | E55: Minier | F55: Attapulgites/Phosphates | H55: Oui | I55: =SUMIF(Table10[Entreprise],Companies[[#This Row],[Nom complet de l’entreprise]],Table10[Valeur de revenus]) -> 409340042
B56: Sabodala Mining Company (SMC) | C56: Privée | D56: 2464410 0G2 | E56: Minier | F56: Or | G56: https://www.endeavourmining.com/investors/institutional-ownership%20https://www.londonstockexchange.com/stock/EDV/endeavour-mining-plc/analysis | H56: Oui | I56: =SUMIF(Table10[Entreprise],Companies[[#This Row],[Nom complet de l’entreprise]],Table10[Valeur de revenus]) -> 379579268
B57: Kosmos Energy Senegal | C57: Privée | D57: 0066487132V2 | E57: Pétrole & Gaz | F57: Gaz | G57: https://www.kosmosenergy.com/senegal/ | H57: Non | I57: =SUMIF(Table10[Entreprise],Companies[[#This Row],[Nom complet de l’entreprise]],Table10[Valeur de revenus]) -> 373391362
B58: Barrick Gold | E58: Minier | I58: =SUMIF(Table10[Entreprise],Companies[[#This Row],[Nom complet de l’entreprise]],Table10[Valeur de revenus]) -> 310662287
B59: Total E&P Sénégal | C59: Privée | D59: 6501383 | E59: Pétrole & Gaz | F59: Gaz | G59: https://www.total.sn/ | H59: Oui | I59: =SUMIF(Table10[Entreprise],Companies[[#This Row],[Nom complet de l’entreprise]],Table10[Valeur de revenus]) -> 216874671
B60: Fortesa International Senegal | C60: Privée | D60: 415770 | E60: Gaz | F60: Gaz | H60: Oui | I60: =SUMIF(Table10[Entreprise],Companies[[#This Row],[Nom complet de l’entreprise]],Table10[Valeur de revenus]) -> 180826630
B61: Talix Mines | C61: Privée | D61: NC | E61: Minier | F61: NC | G61: NC | H61: NC | I61: =SUMIF(Table10[Entreprise],Companies[[#This Row],[Nom complet de l’entreprise]],Table10[Valeur de revenus]) -> 90533438
B62: African Investment Group SA (AIG) | C62: Privée | D62: 4507995 2G3 | E62: Minier | F62: Phosphates / Minéraux lourds | G62: https://www.africainvestmentgroup.co.uk/ | H62: Oui | I62: =SUMIF(Table10[Entreprise],Companies[[#This Row],[Nom complet de l’entreprise]],Table10[Valeur de revenus]) -> 71068544
B63: G-PHOS SA | C63: Privée | D63: 004716033 | E63: Minier | F63: Phosphates | H63: Oui | I63: =SUMIF(Table10[Entreprise],Companies[[#This Row],[Nom complet de l’entreprise]],Table10[Valeur de revenus]) -> 15305854
B64: SORED Mines | C64: Privée | D64: NC | E64: Minier | F64: NC | G64: NC | H64: NC | I64: =SUMIF(Table10[Entreprise],Companies[[#This Row],[Nom complet de l’entreprise]],Table10[Valeur de revenus]) -> 10063169
B65: La Société des Mines de Fer du Sénégal Oriental (MIFERSO) | C65: Société publique financière et Entreprise d'Etat | D65: 0023896 2G3 | E65: Minier | F65: Fer | G65: http://www.miferso.sn/ | H65: Oui | I65: =SUMIF(Table10[Entreprise],Companies[[#This Row],[Nom complet de l’entreprise]],Table10[Valeur de revenus]) -> 8553257
B71: Liste des projets à déclarer
B72: Nom complet du projet | C72: Référence(s) de la convention juridique : contrat, licence, bail, concession,... | D72: Sociétés associées, commencer par l’Opérateur | E72: Matières premières (une matière/ligne) | F72: Statut | G72: Volume de production | H72: Unité | I72: Valeur de production | J72: Devise
B73: Sabodala | D73: SGO | E73: Or | F73: Production | G73: 11 | H73: TONNE | I73: 393709507828 | J73: XOF
B74: Mako | D74: PMC | E74: Or | F74: Production | G74: 4.025527 | H74: TONNE | I74: 145989168041 | J74: XOF
B75: NC | D75: AFRIGOLD | E75: Or | F75: Production | G75: 0.0485 | H75: TONNE | I75: NC | J75: XOF
B76: BARGNY | D76: SOCOCIM | E76: CIMENT | F76: Production | G76: 3373277 | H76: TONNE | I76: 160037236423 | J76: XOF
B77: POUT | D77: Dangote | E77: CIMENT | F77: Production | G77: 646121 | H77: TONNE | I77: 19372003072 | J77: XOF
B78: BARGNY | D78: SOCOCIM | E78: CLINKER | F78: Production | G78: 1881642 | H78: TONNE | I78: 69606686944 | J78: XOF
B79: POUT | D79: Dangote | E79: CLINKER | F79: Production | G79: 467250 | H79: TONNE | I79: 13433089599 | J79: XOF
B80: DIOGO | D80: GCO | E80: ILMENITE 54 | F80: Production | G80: 328742 | H80: TONNE | I80: 66987102119 | J80: XOF
B81: Tobène | D81: ICS | E81: PHOSPHATE | F81: Production | G81: 1771000 | H81: TONNE | I81: 5.6392616e+10 | J81: XOF
B82: Allou Kagne | D82: SSPT | E82: PHOSPHATE | F82: Production | G82: 144956 | H82: TONNE | I82: 3564774127 | J82: XOF
B83: NC | D83: BMCC | E83: PHOSPHATE | F83: Production | G83: 71442 | H83: TONNE | I83: NC | J83: XOF
B84: NDENDORY | D84: SOMIVA | E84: PHOSPHATE NATUREL | F84: Production | G84: 549556 | H84: TONNE | I84: 56442979011 | J84: XOF
B85: DIOGO | D85: GCO | E85: ZIRCON PREMIUM | F85: Production | G85: 34583 | H85: TONNE | I85: 46680083232 | J85: XOF
B86: NC | D86: COGECA | E86: Basalte | F86: Production | G86: 2205996 | H86: TONNE | I86: 18482949000 | J86: XOF
B87: DIACK | D87: Gécamines | E87: Basalte | F87: Production | G87: 1847386 | H87: TONNE | I87: 14229037033 | J87: XOF
B88: DIOGO | D88: GCO | E88: ZIRCON STANDARD | F88: Production | G88: 22498 | H88: TONNE | I88: 29136495247 | J88: XOF
B89: DIOGO | D89: GCO | E89: ILMENITE 58 | F89: Production | G89: 133804 | H89: TONNE | I89: 28951526564 | J89: XOF
B90: NC | D90: COGECA | E90: CALCAIRE | F90: Production | G90: 1599934 | H90: METRE CUBE | I90: 7999670000 | J90: XOF
B91: POUT | D91: SOCOCIM | E91: CALCAIRE | F91: Production | G91: 762283 | H91: TONNE | I91: 1673211185 | J91: XOF
B92: BANDIA | D92: Gécamines | E92: CALCAIRE | F92: Production | G92: 436732 | H92: TONNE | I92: 1574493518 | J92: XOF
B93: BANDIA | D93: SOCOCIM | E93: CALCAIRE | F93: Production | G93: 140987 | H93: TONNE | I93: 309466465 | J93: XOF
B94: NC | D94: CDS | E94: CALCAIRE | F94: Production | G94: 2902226 | H94: TONNE | I94: NC | J94: XOF
B95: DIOGO | D95: GCO | E95: ILMENITE 56 | F95: Production | G95: 35551 | H95: TONNE | I95: 7543497575 | J95: XOF
B96: DIOGO | D96: GCO | E96: ZIRCON SAND MEDIUM GRADE | F96: Production | G96: 26981 | H96: TONNE | I96: 7039966533 | J96: XOF
B97: LAMLAM | D97: Sephos / G-PHOS | E97: PHOSPHATE SEC CRIBLE | F97: Production | G97: 69006 | H97: TONNE | I97: 6091675324 | J97: XOF
B98: DIOGO | D98: GCO | E98: LEUCOXENE | F98: Production | G98: 6284 | H98: TONNE | I98: 5343597553 | J98: XOF
B99: DIOGO | D99: GCO | E99: RUTILE | F99: Production | G99: 4203 | H99: TONNE | I99: 5251482196 | J99: XOF
B100: BARGNY | D100: SOCOCIM | E100: MARNO-CALCAIRE | F100: Production | G100: 1990935 | H100: TONNE | I100: 4370102325 | J100: XOF
B101: Sabodala | D101: SGO | E101: Argent | F101: Production | G101: 1 | H101: TONNE | I101: 382666065 | J101: XOF
B102: Mako | D102: PMC | E102: Argent | F102: Production | G102: 0.3254081 | H102: TONNE | I102: 142020334 | J102: XOF
B103: DIACK | D103: SOCOCIM | E103: LATERITE | F103: Production | G103: 101441 | H103: TONNE | I103: 395011254 | J103: XOF
B104: NC | D104: CDS | E104: LATERITE | F104: Production | G104: 82473 | H104: TONNE | I104: NC | J104: XOF
B105: NC | D105: CDS | E105: Argile | F105: Production | G105: 400578 | H105: TONNE | I105: NC | J105: XOF
B106: NC | D106: GH MINING | E106: Manganèse | F106: Production | G106: 31092 | H106: TONNE | I106: NC | J106: XOF
B107: Diender | D107: Fortesa | E107: Gaz naturel | F107: Production | G107: 4446906 | H107: Nm3 | I107: 876975000 | J107: XOF
B110: Pour plus d’information sur l’ITIE, visitez notre site Internet https://eiti.org/fr
B111: Vous voulez en savoir plus sur votre pays ? Vérifiez si votre pays met en œuvre la Norme ITIE en visitant https://eiti.org/fr/pays
B112: Pour la version la plus récente des modèles de données résumées, consultez https://eiti.org/fr/document/modele-donnees-resumees-itie
B113: Faites-nous connaître vos réactions ou signalez tout conflit au niveau des données ! Écrivez-nous à data@eiti.org
B115: Site Internet www.eiti.org Courriel secretariat@eiti.org Téléphone +47 22 20 08 00 Télécopieur +47 22 83 08 02
B116: Adresse EITI International Secretariat, Rådhusgata 26, 0151 Oslo, Norvège

Sheet Partie 4 - Recettes de l’État
N3: Modèle de données résumées
N4: =Introduction!G4 -> 0
F8: Partie 4 (Recettes de l’État) Elle contient des données exhaustives sur les revenus de l’État par flux de revenu, en utilisant la classification SFP.
F9: Comment remplir cette feuille :
F10: 1. Inscrivez le nom de tous les flux de revenus de l’État pour le secteur extractif, y compris les flux inférieurs aux seuils de matérialité convenus (utiliser une ligne pour chaque flux de revenus et pour chaque entité de l’État)
F11: 2. Inscrivez le nom de l’entité de l’État percevant les revenus (sélectionnez celle-ci sur la liste déroulante) Elle y figurera parce que vous aurez déjà inscrit l’entité de l’État à la Partie 3).
F12: 3. Choisissez le Secteur et la Classification SFP auxquels ce flux de revenus s’applique. Consultez les orientations fournies dans le Cadre SFP pour le rapportage ITIE. Si un flux de revenus ne peut être désagrégé par secteur, sélectionnez « Autre ».
F13: 4. Dans la colonne Valeur des revenus inscrivez le chiffre total de chaque flux de revenus tel que divulgué par le gouvernement, qui inclut également les revenus qui n’ont pas été rapprochés.
F14: Nota : Les paiements versés par les entreprises aux gouvernements au nom de leurs employés doivent être exclus (par exemple, l’impôt sur le revenu des particuliers / impôts retenus à la source, cotisations des employés pour la sécurité sociale) car ils ne sont pas considérés comme étant des paiements par des entreprises au gouvernement.
F15: 5. Si des paiements sont recensés dans le Rapport ITIE mais ne correspondent pas aux catégories SFP, veuillez les lister dans la case ci-dessous dénommée « Informations supplémentaires ».
F16: Si vous avez des questions, veuillez contacter data@eiti.org
F18: Total des recettes de l’État provenant du secteur extractif (utilisant la classification SFP) | M18: Cadre SFP pour le rapportage ITIE
M19: Exigence ITIE 5.1.b: Classification des revenus
F20: Exigence ITIE 4.1.d: Divulgation exhaustive de la part du gouvernement
B21: GFS Niveau 1 | C21: GFS Niveau 2 | D21: GFS Niveau 3 | E21: GFS Niveau 4 | F21: Classification SFP | G21: Secteur | H21: Nom du flux de revenus | I21: Entité de l’État | J21: Valeur des revenus | K21: Devise | M21: En quoi consiste le SFP ?
B22: =IFERROR(VLOOKUP(Government_revenues_table[[#This Row],[Classification SFP]],Table6_GFS_codes_classification[],COLUMNS($F:F)+3,FALSE),"Do not enter data") -> Autre revenu (14E) | C22: =IFERROR(VLOOKUP(Government_revenues_table[[#This Row],[Classification SFP]],Table6_GFS_codes_classification[],COLUMNS($F:G)+3,FALSE),"Do not enter data") -> Revenu dégagé de la propriété (141E) | D22: =IFERROR(VLOOKUP(Government_revenues_table[[#This Row],[Classification SFP]],Table6_GFS_codes_classification[],COLUMNS($F:H)+3,FALSE),"Do not enter data") -> Loyers (1415E) | E22: =IFERROR(VLOOKUP(Government_revenues_table[[#This Row],[Classification SFP]],Table6_GFS_codes_classification[],COLUMNS($F:I)+3,FALSE),"Do not enter data") -> Redevances (1415E1) | F22: Redevances (1415E1) | G22: Minier | H22: Redevance minière | I22: Direction Générale des Mines | J22: 42108704590 | K22: XOF | M22: SFP, sigle pour «Statistiques de Finances Publiques », est un cadre international pour la classification des flux de revenus afin de les rendre comparables d’un pays et d’une période à l’autre. Voir l’exemple de cadre complet ci-dessous. Le cadre utilisé ci-dessous a été élaboré par le FMI et le Secrétariat international de l’ITIE. Les chiffres à droite ont été spécifiquement conçus pour les entreprises du secteur extractif La lettre E dans la colonne des codes SFP signifie que ce sont les codes utilisés pour les revenus issus des entreprises extractives. Les chiffres situés à gauche de la lettre E sont les codes SFP réguliers.
B23: =IFERROR(VLOOKUP(Government_revenues_table[[#This Row],[Classification SFP]],Table6_GFS_codes_classification[],COLUMNS($F:F)+3,FALSE),"Do not enter data") -> Impôts (11E) | C23: =IFERROR(VLOOKUP(Government_revenues_table[[#This Row],[Classification SFP]],Table6_GFS_codes_classification[],COLUMNS($F:G)+3,FALSE),"Do not enter data") -> Impôts sur les biens et services (114E) | D23: =IFERROR(VLOOKUP(Government_revenues_table[[#This Row],[Classification SFP]],Table6_GFS_codes_classification[],COLUMNS($F:H)+3,FALSE),"Do not enter data") -> Impôts généraux sur les biens et services (TVA, taxes sur les ventes, taxes sur le chiffre d’affaires (1141E) | E23: =IFERROR(VLOOKUP(Government_revenues_table[[#This Row],[Classification SFP]],Table6_GFS_codes_classification[],COLUMNS($F:I)+3,FALSE),"Do not enter data") -> Impôts généraux sur les biens et services (TVA, taxes sur les ventes, taxes sur le chiffre d’affaires (1141E) | F23: Impôts généraux sur les biens et services (TVA, taxes sur les ventes, taxes sur le chiffre d’affaires)(1141E) | G23: Minier | H23: Taxe sur la valeur ajoutée reversée | I23: Direction Générale des Impôts et des Domaines | J23: 32526122862 | K23: XOF
B24: =IFERROR(VLOOKUP(Government_revenues_table[[#This Row],[Classification SFP]],Table6_GFS_codes_classification[],COLUMNS($F:F)+3,FALSE),"Do not enter data") -> Impôts (11E) | C24: =IFERROR(VLOOKUP(Government_revenues_table[[#This Row],[Classification SFP]],Table6_GFS_codes_classification[],COLUMNS($F:G)+3,FALSE),"Do not enter data") -> Impôts sur la masse salariale et la force de travail (112E) | D24: =IFERROR(VLOOKUP(Government_revenues_table[[#This Row],[Classification SFP]],Table6_GFS_codes_classification[],COLUMNS($F:H)+3,FALSE),"Do not enter data") -> Impôts sur la masse salariale et la force de travail (112E) | E24: =IFERROR(VLOOKUP(Government_revenues_table[[#This Row],[Classification SFP]],Table6_GFS_codes_classification[],COLUMNS($F:I)+3,FALSE),"Do not enter data") -> Impôts sur la masse salariale et la force de travail (112E) | F24: Impôts sur la masse salariale et la force de travail (112E) | G24: Minier | H24: Retenues à la source sur salaires (IR, TRIMF et CFCE) | I24: Direction Générale des Impôts et des Domaines | J24: 25990968213 | K24: XOF
B25: =IFERROR(VLOOKUP(Government_revenues_table[[#This Row],[Classification SFP]],Table6_GFS_codes_classification[],COLUMNS($F:F)+3,FALSE),"Do not enter data") -> Impôts (11E) | C25: =IFERROR(VLOOKUP(Government_revenues_table[[#This Row],[Classification SFP]],Table6_GFS_codes_classification[],COLUMNS($F:G)+3,FALSE),"Do not enter data") -> Taxes sur le commerce et les transactions au niveau international (115E) | D25: =IFERROR(VLOOKUP(Government_revenues_table[[#This Row],[Classification SFP]],Table6_GFS_codes_classification[],COLUMNS($F:H)+3,FALSE),"Do not enter data") -> Droits de douane et autres droits d’importation (1151E) | E25: =IFERROR(VLOOKUP(Government_revenues_table[[#This Row],[Classification SFP]],Table6_GFS_codes_classification[],COLUMNS($F:I)+3,FALSE),"Do not enter data") -> Droits de douane et autres droits d’importation (1151E) | F25: Droits de douane et autres droits d’importation (1151E) | G25: Minier | H25: Taxe sur la valeur ajoutée | I25: Direction Générale des Douanes | J25: 23377806013 | K25: XOF
B26: =IFERROR(VLOOKUP(Government_revenues_table[[#This Row],[Classification SFP]],Table6_GFS_codes_classification[],COLUMNS($F:F)+3,FALSE),"Do not enter data") -> Impôts (11E) | C26: =IFERROR(VLOOKUP(Government_revenues_table[[#This Row],[Classification SFP]],Table6_GFS_codes_classification[],COLUMNS($F:G)+3,FALSE),"Do not enter data") -> Impôts sur le revenu, le bénéfice et les plus-values | D26: =IFERROR(VLOOKUP(Government_revenues_table[[#This Row],[Classification SFP]],Table6_GFS_codes_classification[],COLUMNS($F:H)+3,FALSE),"Do not enter data") -> Impôts ordinaires sur le revenu, le bénéfice et les plus-values (1112E1) | E26: =IFERROR(VLOOKUP(Government_revenues_table[[#This Row],[Classification SFP]],Table6_GFS_codes_classification[],COLUMNS($F:I)+3,FALSE),"Do not enter data") -> Impôts ordinaires sur le revenu, le bénéfice et les plus-values (1112E1) | F26: Impôts ordinaires sur le revenu, le bénéfice et les plus-values (1112E1) | G26: Minier | H26: Impôt sur le revenu des valeurs mobilières | I26: Direction Générale des Impôts et des Domaines | J26: 22522304771 | K26: XOF
B27: =IFERROR(VLOOKUP(Government_revenues_table[[#This Row],[Classification SFP]],Table6_GFS_codes_classification[],COLUMNS($F:F)+3,FALSE),"Do not enter data") -> Autre revenu (14E) | C27: =IFERROR(VLOOKUP(Government_revenues_table[[#This Row],[Classification SFP]],Table6_GFS_codes_classification[],COLUMNS($F:G)+3,FALSE),"Do not enter data") -> Revenu dégagé de la propriété (141E) | D27: =IFERROR(VLOOKUP(Government_revenues_table[[#This Row],[Classification SFP]],Table6_GFS_codes_classification[],COLUMNS($F:H)+3,FALSE),"Do not enter data") -> Dividendes (1412E) | E27: =IFERROR(VLOOKUP(Government_revenues_table[[#This Row],[Classification SFP]],Table6_GFS_codes_classification[],COLUMNS($F:I)+3,FALSE),"Do not enter data") -> Provenant de la participation de l’État (1412E2) | F27: Provenant de la participation de l’État (1412E2) | G27: Minier | H27: Dividendes versés à l'Etat | I27: Direction Générale de la Comptabilité Publique et du Trésor | J27: 16599906089 | K27: XOF | M27: Pour plus d’orientations, visitez la page https://eiti.org/fr/document/modele-donnees-resumees-itie
B28: =IFERROR(VLOOKUP(Government_revenues_table[[#This Row],[Classification SFP]],Table6_GFS_codes_classification[],COLUMNS($F:F)+3,FALSE),"Do not enter data") -> Impôts (11E) | C28: =IFERROR(VLOOKUP(Government_revenues_table[[#This Row],[Classification SFP]],Table6_GFS_codes_classification[],COLUMNS($F:G)+3,FALSE),"Do not enter data") -> Impôts sur les biens et services (114E) | D28: =IFERROR(VLOOKUP(Government_revenues_table[[#This Row],[Classification SFP]],Table6_GFS_codes_classification[],COLUMNS($F:H)+3,FALSE),"Do not enter data") -> Impôts généraux sur les biens et services (TVA, taxes sur les ventes, taxes sur le chiffre d’affaires (1141E) | E28: =IFERROR(VLOOKUP(Government_revenues_table[[#This Row],[Classification SFP]],Table6_GFS_codes_classification[],COLUMNS($F:I)+3,FALSE),"Do not enter data") -> Impôts généraux sur les biens et services (TVA, taxes sur les ventes, taxes sur le chiffre d’affaires (1141E) | F28: Impôts généraux sur les biens et services (TVA, taxes sur les ventes, taxes sur le chiffre d’affaires)(1141E) | G28: Minier | H28: Taxe spéciale sur le ciment | I28: Direction Générale des Impôts et des Domaines | J28: 15433880734 | K28: XOF | M28: ou https://www.imf.org/external/pubs/ft/gfs/manual/pdf/2014companion/FrenchGFSM.pdf
B29: =IFERROR(VLOOKUP(Government_revenues_table[[#This Row],[Classification SFP]],Table6_GFS_codes_classification[],COLUMNS($F:F)+3,FALSE),"Do not enter data") -> Impôts (11E) | C29: =IFERROR(VLOOKUP(Government_revenues_table[[#This Row],[Classification SFP]],Table6_GFS_codes_classification[],COLUMNS($F:G)+3,FALSE),"Do not enter data") -> Impôts sur le revenu, le bénéfice et les plus-values | D29: =IFERROR(VLOOKUP(Government_revenues_table[[#This Row],[Classification SFP]],Table6_GFS_codes_classification[],COLUMNS($F:H)+3,FALSE),"Do not enter data") -> Impôts ordinaires sur le revenu, le bénéfice et les plus-values (1112E1) | E29: =IFERROR(VLOOKUP(Government_revenues_table[[#This Row],[Classification SFP]],Table6_GFS_codes_classification[],COLUMNS($F:I)+3,FALSE),"Do not enter data") -> Impôts ordinaires sur le revenu, le bénéfice et les plus-values (1112E1) | F29: Impôts ordinaires sur le revenu, le bénéfice et les plus-values (1112E1) | G29: Minier | H29: Impôt sur les sociétés | I29: Direction Générale des Impôts et des Domaines | J29: 13447825420 | K29: XOF
B30: =IFERROR(VLOOKUP(Government_revenues_table[[#This Row],[Classification SFP]],Table6_GFS_codes_classification[],COLUMNS($F:F)+3,FALSE),"Do not enter data") -> Impôts (11E) | C30: =IFERROR(VLOOKUP(Government_revenues_table[[#This Row],[Classification SFP]],Table6_GFS_codes_classification[],COLUMNS($F:G)+3,FALSE),"Do not enter data") -> Impôts sur les biens et services (114E) | D30: =IFERROR(VLOOKUP(Government_revenues_table[[#This Row],[Classification SFP]],Table6_GFS_codes_classification[],COLUMNS($F:H)+3,FALSE),"Do not enter data") -> Impôts généraux sur les biens et services (TVA, taxes sur les ventes, taxes sur le chiffre d’affaires (1141E) | E30: =IFERROR(VLOOKUP(Government_revenues_table[[#This Row],[Classification SFP]],Table6_GFS_codes_classification[],COLUMNS($F:I)+3,FALSE),"Do not enter data") -> Impôts généraux sur les biens et services (TVA, taxes sur les ventes, taxes sur le chiffre d’affaires (1141E) | F30: Impôts généraux sur les biens et services (TVA, taxes sur les ventes, taxes sur le chiffre d’affaires)(1141E) | G30: Minier | H30: Taxe sur le ciment | I30: Direction Générale des Impôts et des Domaines | J30: 10289539042 | K30: XOF
B31: =IFERROR(VLOOKUP(Government_revenues_table[[#This Row],[Classification SFP]],Table6_GFS_codes_classification[],COLUMNS($F:F)+3,FALSE),"Do not enter data") -> Impôts (11E) | C31: =IFERROR(VLOOKUP(Government_revenues_table[[#This Row],[Classification SFP]],Table6_GFS_codes_classification[],COLUMNS($F:G)+3,FALSE),"Do not enter data") -> Taxes sur le commerce et les transactions au niveau international (115E) | D31: =IFERROR(VLOOKUP(Government_revenues_table[[#This Row],[Classification SFP]],Table6_GFS_codes_classification[],COLUMNS($F:H)+3,FALSE),"Do not enter data") -> Droits de douane et autres droits d’importation (1151E) | E31: =IFERROR(VLOOKUP(Government_revenues_table[[#This Row],[Classification SFP]],Table6_GFS_codes_classification[],COLUMNS($F:I)+3,FALSE),"Do not enter data") -> Droits de douane et autres droits d’importation (1151E) | F31: Droits de douane et autres droits d’importation (1151E) | G31: Minier | H31: Droits de douane | I31: Direction Générale des Douanes | J31: 9617818617 | K31: XOF
B32: =IFERROR(VLOOKUP(Government_revenues_table[[#This Row],[Classification SFP]],Table6_GFS_codes_classification[],COLUMNS($F:F)+3,FALSE),"Do not enter data") -> Impôts (11E) | C32: =IFERROR(VLOOKUP(Government_revenues_table[[#This Row],[Classification SFP]],Table6_GFS_codes_classification[],COLUMNS($F:G)+3,FALSE),"Do not enter data") -> Impôts sur la masse salariale et la force de travail (112E) | D32: =IFERROR(VLOOKUP(Government_revenues_table[[#This Row],[Classification SFP]],Table6_GFS_codes_classification[],COLUMNS($F:H)+3,FALSE),"Do not enter data") -> Impôts sur la masse salariale et la force de travail (112E) | E32: =IFERROR(VLOOKUP(Government_revenues_table[[#This Row],[Classification SFP]],Table6_GFS_codes_classification[],COLUMNS($F:I)+3,FALSE),"Do not enter data") -> Impôts sur la masse salariale et la force de travail (112E) | F32: Impôts sur la masse salariale et la force de travail (112E) | G32: Pétrole & Gaz | H32: Retenues à la source sur salaires (IR, TRIMF et CFCE) | I32: Direction Générale des Impôts et des Domaines | J32: 6582588951 | K32: XOF
B33: =IFERROR(VLOOKUP(Government_revenues_table[[#This Row],[Classification SFP]],Table6_GFS_codes_classification[],COLUMNS($F:F)+3,FALSE),"Do not enter data") -> Impôts (11E) | C33: =IFERROR(VLOOKUP(Government_revenues_table[[#This Row],[Classification SFP]],Table6_GFS_codes_classification[],COLUMNS($F:G)+3,FALSE),"Do not enter data") -> Impôts sur le revenu, le bénéfice et les plus-values | D33: =IFERROR(VLOOKUP(Government_revenues_table[[#This Row],[Classification SFP]],Table6_GFS_codes_classification[],COLUMNS($F:H)+3,FALSE),"Do not enter data") -> Impôts ordinaires sur le revenu, le bénéfice et les plus-values (1112E1) | E33: =IFERROR(VLOOKUP(Government_revenues_table[[#This Row],[Classification SFP]],Table6_GFS_codes_classification[],COLUMNS($F:I)+3,FALSE),"Do not enter data") -> Impôts ordinaires sur le revenu, le bénéfice et les plus-values (1112E1) | F33: Impôts ordinaires sur le revenu, le bénéfice et les plus-values (1112E1) | G33: Pétrole & Gaz | H33: Retenues à la source sur bénéfice non commercial | I33: Direction Générale des Impôts et des Domaines | J33: 5520710688 | K33: XOF
B34: =IFERROR(VLOOKUP(Government_revenues_table[[#This Row],[Classification SFP]],Table6_GFS_codes_classification[],COLUMNS($F:F)+3,FALSE),"Do not enter data") -> Impôts (11E) | C34: =IFERROR(VLOOKUP(Government_revenues_table[[#This Row],[Classification SFP]],Table6_GFS_codes_classification[],COLUMNS($F:G)+3,FALSE),"Do not enter data") -> Impôts sur le revenu, le bénéfice et les plus-values | D34: =IFERROR(VLOOKUP(Government_revenues_table[[#This Row],[Classification SFP]],Table6_GFS_codes_classification[],COLUMNS($F:H)+3,FALSE),"Do not enter data") -> Impôts ordinaires sur le revenu, le bénéfice et les plus-values (1112E1) | E34: =IFERROR(VLOOKUP(Government_revenues_table[[#This Row],[Classification SFP]],Table6_GFS_codes_classification[],COLUMNS($F:I)+3,FALSE),"Do not enter data") -> Impôts ordinaires sur le revenu, le bénéfice et les plus-values (1112E1) | F34: Impôts ordinaires sur le revenu, le bénéfice et les plus-values (1112E1) | G34: Pétrole & Gaz | H34: Retenue à la source sur sommes versées à des tiers | I34: Direction Générale des Impôts et des Domaines | J34: 5030892002 | K34: XOF
B35: =IFERROR(VLOOKUP(Government_revenues_table[[#This Row],[Classification SFP]],Table6_GFS_codes_classification[],COLUMNS($F:F)+3,FALSE),"Do not enter data") -> Cotisations sociales (12E) | C35: =IFERROR(VLOOKUP(Government_revenues_table[[#This Row],[Classification SFP]],Table6_GFS_codes_classification[],COLUMNS($F:G)+3,FALSE),"Do not enter data") -> Cotisations patronales à la sécurité sociale (1212E) | D35: =IFERROR(VLOOKUP(Government_revenues_table[[#This Row],[Classification SFP]],Table6_GFS_codes_classification[],COLUMNS($F:H)+3,FALSE),"Do not enter data") -> Cotisations patronales à la sécurité sociale (1212E) | E35: =IFERROR(VLOOKUP(Government_revenues_table[[#This Row],[Classification SFP]],Table6_GFS_codes_classification[],COLUMNS($F:I)+3,FALSE),"Do not enter data") -> Cotisations patronales à la sécurité sociale (1212E) | F35: Cotisations patronales à la sécurité sociale (1212E) | G35: Minier | H35: Cotisations sociales (y compris les pénalités)(IPRES) | I35: Institution de Prévoyance Retraite du Sénégal | J35: 4607220095 | K35: XOF
B36: =IFERROR(VLOOKUP(Government_revenues_table[[#This Row],[Classification SFP]],Table6_GFS_codes_classification[],COLUMNS($F:F)+3,FALSE),"Do not enter data") -> Impôts (11E) | C36: =IFERROR(VLOOKUP(Government_revenues_table[[#This Row],[Classification SFP]],Table6_GFS_codes_classification[],COLUMNS($F:G)+3,FALSE),"Do not enter data") -> Impôts sur le revenu, le bénéfice et les plus-values | D36: =IFERROR(VLOOKUP(Government_revenues_table[[#This Row],[Classification SFP]],Table6_GFS_codes_classification[],COLUMNS($F:H)+3,FALSE),"Do not enter data") -> Impôts ordinaires sur le revenu, le bénéfice et les plus-values (1112E1) | E36: =IFERROR(VLOOKUP(Government_revenues_table[[#This Row],[Classification SFP]],Table6_GFS_codes_classification[],COLUMNS($F:I)+3,FALSE),"Do not enter data") -> Impôts ordinaires sur le revenu, le bénéfice et les plus-values (1112E1) | F36: Impôts ordinaires sur le revenu, le bénéfice et les plus-values (1112E1) | G36: Minier | H36: Retenues à la source sur bénéfice non commercial | I36: Direction Générale des Impôts et des Domaines | J36: 3563953859 | K36: XOF
B37: =IFERROR(VLOOKUP(Government_revenues_table[[#This Row],[Classification SFP]],Table6_GFS_codes_classification[],COLUMNS($F:F)+3,FALSE),"Do not enter data") -> Impôts (11E) | C37: =IFERROR(VLOOKUP(Government_revenues_table[[#This Row],[Classification SFP]],Table6_GFS_codes_classification[],COLUMNS($F:G)+3,FALSE),"Do not enter data") -> Taxes sur le commerce et les transactions au niveau international (115E) | D37: =IFERROR(VLOOKUP(Government_revenues_table[[#This Row],[Classification SFP]],Table6_GFS_codes_classification[],COLUMNS($F:H)+3,FALSE),"Do not enter data") -> Droits de douane et autres droits d’importation (1151E) | E37: =IFERROR(VLOOKUP(Government_revenues_table[[#This Row],[Classification SFP]],Table6_GFS_codes_classification[],COLUMNS($F:I)+3,FALSE),"Do not enter data") -> Droits de douane et autres droits d’importation (1151E) | F37: Droits de douane et autres droits d’importation (1151E) | G37: Pétrole & Gaz | H37: Redevance statistique UEMOA | I37: Direction Générale des Douanes | J37: 2224611231 | K37: XOF
B38: =IFERROR(VLOOKUP(Government_revenues_table[[#This Row],[Classification SFP]],Table6_GFS_codes_classification[],COLUMNS($F:F)+3,FALSE),"Do not enter data") -> Impôts (11E) | C38: =IFERROR(VLOOKUP(Government_revenues_table[[#This Row],[Classification SFP]],Table6_GFS_codes_classification[],COLUMNS($F:G)+3,FALSE),"Do not enter data") -> Taxes sur le commerce et les transactions au niveau international (115E) | D38: =IFERROR(VLOOKUP(Government_revenues_table[[#This Row],[Classification SFP]],Table6_GFS_codes_classification[],COLUMNS($F:H)+3,FALSE),"Do not enter data") -> Droits de douane et autres droits d’importation (1151E) | E38: =IFERROR(VLOOKUP(Government_revenues_table[[#This Row],[Classification SFP]],Table6_GFS_codes_classification[],COLUMNS($F:I)+3,FALSE),"Do not enter data") -> Droits de douane et autres droits d’importation (1151E) | F38: Droits de douane et autres droits d’importation (1151E) | G38: Minier | H38: Redevance statistique UEMOA | I38: Direction Générale des Douanes | J38: 1786007941 | K38: XOF
B39: =IFERROR(VLOOKUP(Government_revenues_table[[#This Row],[Classification SFP]],Table6_GFS_codes_classification[],COLUMNS($F:F)+3,FALSE),"Do not enter data") -> Impôts (11E) | C39: =IFERROR(VLOOKUP(Government_revenues_table[[#This Row],[Classification SFP]],Table6_GFS_codes_classification[],COLUMNS($F:G)+3,FALSE),"Do not enter data") -> Taxes sur le commerce et les transactions au niveau international (115E) | D39: =IFERROR(VLOOKUP(Government_revenues_table[[#This Row],[Classification SFP]],Table6_GFS_codes_classification[],COLUMNS($F:H)+3,FALSE),"Do not enter data") -> Droits de douane et autres droits d’importation (1151E) | E39: =IFERROR(VLOOKUP(Government_revenues_table[[#This Row],[Classification SFP]],Table6_GFS_codes_classification[],COLUMNS($F:I)+3,FALSE),"Do not enter data") -> Droits de douane et autres droits d’importation (1151E) | F39: Droits de douane et autres droits d’importation (1151E) | G39: Pétrole & Gaz | H39: Prélèvement communautaire solidaire UEMOA | I39: Direction Générale des Douanes | J39: 1779688959 | K39: XOF
B40: =IFERROR(VLOOKUP(Government_revenues_table[[#This Row],[Classification SFP]],Table6_GFS_codes_classification[],COLUMNS($F:F)+3,FALSE),"Do not enter data") -> Impôts (11E) | C40: =IFERROR(VLOOKUP(Government_revenues_table[[#This Row],[Classification SFP]],Table6_GFS_codes_classification[],COLUMNS($F:G)+3,FALSE),"Do not enter data") -> Impôts sur le revenu, le bénéfice et les plus-values | D40: =IFERROR(VLOOKUP(Government_revenues_table[[#This Row],[Classification SFP]],Table6_GFS_codes_classification[],COLUMNS($F:H)+3,FALSE),"Do not enter data") -> Impôts ordinaires sur le revenu, le bénéfice et les plus-values (1112E1) | E40: =IFERROR(VLOOKUP(Government_revenues_table[[#This Row],[Classification SFP]],Table6_GFS_codes_classification[],COLUMNS($F:I)+3,FALSE),"Do not enter data") -> Impôts ordinaires sur le revenu, le bénéfice et les plus-values (1112E1) | F40: Impôts ordinaires sur le revenu, le bénéfice et les plus-values (1112E1) | G40: Minier | H40: Contribution économique locale (CEL VA et CEL VL) | I40: Direction Générale de la Comptabilité Publique et du Trésor | J40: 1770577202 | K40: XOF
... B46: =IFERROR(VLOOKUP(Government_revenues_table[[#This Row],[Classification SFP]],Table6_GFS_codes_classification[],COLUMNS($F:F)+3,FALSE),"Do not enter data") -> Cotisations sociales (12E) | C46: =IFERROR(VLOOKUP(Government_revenues_table[[#This Row],[Classification SFP]],Table6_GFS_codes_classification[],COLUMNS($F:G)+3,FALSE),"Do not enter data") -> Cotisations patronales à la sécurité sociale (1212E) | D46: =IFERROR(VLOOKUP(Government_revenues_table[[#This Row],[Classification SFP]],Table6_GFS_codes_classification[],COLUMNS($F:H)+3,FALSE),"Do not enter data") -> Cotisations patronales à la sécurité sociale (1212E) | E46: =IFERROR(VLOOKUP(Government_revenues_table[[#This Row],[Classification SFP]],Table6_GFS_codes_classification[],COLUMNS($F:I)+3,FALSE),"Do not enter data") -> Cotisations patronales à la sécurité sociale (1212E) | F46: Cotisations patronales à la sécurité sociale (1212E) | G46: Minier | H46: Cotisations sociales (y compris les pénalités) | I46: Caisse de Sécurité Sociale | J46: 856016492 | K46: XOF
F47: Autres paiements de loyer (1415E5) | G47: Pétrole & Gaz | H47: Loyer superficiaire | I47: Société des Pétroles du Sénégal | J47: 8.4118323e+08 | K47: XOF
F48: Impôts ordinaires sur le revenu, le bénéfice et les plus-values (1112E1) | G48: Minier | H48: Patente | I48: Direction Générale de la Comptabilité Publique et du Trésor | J48: 700210162 | K48: XOF
F49: Autres impôts payés par les entreprises exploitant des ressources naturelles (116E) | G49: Minier | H49: Appui institutionnel | I49: Direction Générale des Mines | J49: 597564136 | K49: XOF
F50: Impôts généraux sur les biens et services (TVA, taxes sur les ventes, taxes sur le chiffre d’affaires)(1141E) | G50: Pétrole & Gaz | H50: Taxe sur la valeur ajoutée reversée | I50: Direction Générale des Impôts et des Domaines | J50: 495067538 | K50: XOF
F51: Autres impôts payés par les entreprises exploitant des ressources naturelles (116E) | G51: Minier | H51: Appui Institutionnel (Fonds d'appui au Mini. De l'Env) | I51: Direction des Eaux, Forêts, Chasses et Conservation des Sols | J51: 488520113 | K51: XOF
F52: Livré/payé à une/des entreprise(s) d’État (1415E32) | G52: Pétrole & Gaz | H52: Appui à la promotion de la recherche et de l'exploitation | I52: Société des Pétroles du Sénégal | J52: 4.7502866e+08 | K52: XOF
F53: Impôts ordinaires sur le revenu, le bénéfice et les plus-values (1112E1) | G53: Minier | H53: Contribution spéciale sur les produits des mines et des carrières (CSMC) | I53: Direction Générale des Impôts et des Domaines | J53: 465851016 | K53: XOF
F54: Impôts ordinaires sur le revenu, le bénéfice et les plus-values (1112E1) | G54: Minier | H54: Autres flux de paiements significatifs (> 25 millions de FCFA) (reconciliables) | I54: Direction Générale des Impôts et des Domaines | J54: 447459127 | K54: XOF
F55: Redevances (1415E1) | G55: Minier | H55: Redevance superficiaire | I55: Direction Générale de la Comptabilité Publique et du Trésor | J55: 438801620 | K55: XOF
F56: Redevances (1415E1) | G56: Minier | H56: Redevance minière | I56: Direction Générale de la Comptabilité Publique et du Trésor | J56: 423355547 | K56: XOF
F57: Droits de douane et autres droits d’importation (1151E) | G57: Minier | H57: Prélèvement pour le Conseil Sénégalais des Chargeurs (COSEC) | I57: Direction Générale des Douanes | J57: 414253631 | K57: XOF
F58: Redevances (1415E1) | G58: Minier | H58: Redevance superficiaire | I58: Direction Générale des Mines | J58: 377603675 | K58: XOF
... F95: Droits de douane et autres droits d’importation (1151E) | G95: Pétrole & Gaz | H95: Prélèvement pour le Conseil Sénégalais des Chargeurs (COSEC) | I95: Direction Générale des Douanes | J95: 58404 | K95: XOF
J96: =SUBTOTAL(109,Government_revenues_table[Valeur des revenus]) -> 2.6041286e+11
I98: Total en USD | J98: =SUMIF(Government_revenues_table[Devise],"USD",Government_revenues_table[Valeur des revenus])+(IFERROR(SUMIF(Government_revenues_table[Devise],"<>USD",Government_revenues_table[Valeur des revenus])/'Partie 1 - Présentation'!$E$51,0)) -> 4.1926472e+08
I100: ="Total en "&'Partie 1 - Présentation'!$E$50 -> Total en XOF | J100: =IF('Partie 1 - Présentation'!$E$50="USD",0,SUMIF(Government_revenues_table[Devise],'Partie 1 - Présentation'!$E$50,Government_revenues_table[Valeur des revenus]))+(IFERROR(SUMIF(Government_revenues_table[Devise],"USD",Government_revenues_table[Valeur des revenus])*'Partie 1 - Présentation'!$E$51,0)) -> 2.6041286e+11
F104: Informations supplémentaires
F105: Ajouter ci-dessous, à titre de commentaire, toute information supplémentaire qu’il ne serait pas judicieux d’inclure dans le tableau ci-dessus.
F108: Commentaire 1 | G108: Veuillez inclure des commentaires ici.
F109: Commentaire 2 | G109: Insérer au besoin des lignes supplémentaires :
G110: Secteur | H110: Nom du flux de revenus | I110: Entité de l’État | J110: Valeur des revenus | K110: Devise
G111: Pétrole | H111: Retenues à la source sur salaires (IR, TRIMF et CFCE) | I111: Direction Générale des Impôts et des Domaines | K111: XOF
G112: Mines | H112: Retenues à la source sur salaires (IR, TRIMF et CFCE) | I112: Direction Générale des Impôts et des Domaines | K112: XOF
G113: Total | J113: =SUM(J111:J112) -> 0 | K113: XOF
B126: Pour plus d’information sur l’ITIE, visitez notre site Internet https://eiti.org/fr
B127: Vous voulez en savoir plus sur votre pays ? Vérifiez si votre pays met en œuvre la Norme ITIE en visitant https://eiti.org/fr/pays
B128: Pour la version la plus récente des modèles de données résumées, consultez https://eiti.org/fr/document/modele-donnees-resumees-itie
B129: Faites-nous connaître vos réactions ou signalez tout conflit au niveau des données ! Écrivez-nous à data@eiti.org
F131: Site Internet www.eiti.org Courriel secretariat@eiti.org Téléphone +47 22 20 08 00 Télécopieur +47 22 83 08 02
F132: Adresse EITI International Secretariat, Rådhusgata 26, 0151 Oslo, Norvège

Sheet Partie 5 - Données d’entreprise
C2: Partie 5 (Données d’entreprise) Elle contient des données venant des entreprises - et du niveau projet - par flux de revenus. Les entreprises et projets sont indiqués sur le menu déroulant car ils ont été saisis sur la feuille 3.
C3: Comment remplir cette feuille :
C4: 1. Sélectionnez le nom de l’entreprise sur le menu déroulant
C5: 2. Sélectionnez l’entité collectrice de l’État et le nom du paiement sur le menu déroulant
C6: 3. Indiquez si le flux de paiements est (i) perçu par projet et (ii) déclaré par projet
C7: 4. Inscrivez l’information de projet : nom du projet et devise de déclaration
C8: 5. Inscrivez la valeur des revenus telle que divulguée par le gouvernement et ajoutez tout commentaire pertinent.
C9: Si vous avez des questions, veuillez contacter data@eiti.org
C11: Recettes de l’État par entreprise et projet
C13: Exigence ITIE 4.1.c: Paiements des entreprises ; Exigence ITIE 4.7: Déclaration par projet
B14: Secteur | C14: Entreprise | D14: Entité de l’État | E14: Nom du paiement | F14: Perçu par projet (O/N) | G14: Déclaré par projet (O/N) | H14: Nom du projet | I14: Devise de déclaration | J14: Valeur de revenus | K14: Paiement effectué en nature? | L14: Volume en nature (si applicable) | M14: Unité (si applicable) | N14: Commentaires
B15: =VLOOKUP(C15,Companies[],3,FALSE) -> 4507995 2G3 | C15: African Investment Group SA (AIG) | D15: Direction Générale des Mines | E15: Redevance minière | F15: Oui | G15: Oui | H15: NC | I15: XOF | J15: 64914144
B16: =VLOOKUP(C16,Companies[],3,FALSE) -> 4507995 2G3 | C16: African Investment Group SA (AIG) | D16: Direction Générale des Mines | E16: Redevance superficiaire | F16: Oui | G16: Oui | H16: NC | I16: XOF | J16: 5654400
B17: =VLOOKUP(C17,Companies[],3,FALSE) -> 4507995 2G3 | C17: African Investment Group SA (AIG) | D17: Institution de Prévoyance Retraite du Sénégal | E17: Cotisations sociales (y compris les pénalités)(IPRES) | F17: Non | G17: Non | H17: NC | I17: XOF | J17: 500000
B18: =VLOOKUP(C18,Companies[],3,FALSE) -> 4151750 2Y2 | C18: Agem Sénégal Exploration SUARL (AGEM) | D18: Direction Générale des Impôts et des Domaines | E18: Retenues à la source sur salaires (IR, TRIMF et CFCE) | F18: Non | G18: Non | H18: NOUMOUFOUKHA | I18: XOF | J18: 379247187
B19: =VLOOKUP(C19,Companies[],3,FALSE) -> 4151750 2Y2 | C19: Agem Sénégal Exploration SUARL (AGEM) | D19: Institution de Prévoyance Retraite du Sénégal | E19: Cotisations sociales (y compris les pénalités)(IPRES) | F19: Non | G19: Non | H19: NOUMOUFOUKHA | I19: XOF | J19: 35032337
B20: =VLOOKUP(C20,Companies[],3,FALSE) -> 4151750 2Y2 | C20: Agem Sénégal Exploration SUARL (AGEM) | D20: Direction Générale des Mines | E20: Appui institutionnel | F20: Oui | G20: Oui | H20: DAORALA | I20: XOF | J20: 17500157
B21: =VLOOKUP(C21,Companies[],3,FALSE) -> 4151750 2Y2 | C21: Agem Sénégal Exploration SUARL (AGEM) | D21: Direction Générale des Mines | E21: Appui institutionnel | F21: Oui | G21: Oui | H21: NOUMOUFOUKHA | I21: XOF | J21: 17500157
B22: =VLOOKUP(C22,Companies[],3,FALSE) -> 4151750 2Y2 | C22: Agem Sénégal Exploration SUARL (AGEM) | D22: Direction Générale des Mines | E22: Appui institutionnel | F22: Oui | G22: Oui | H22: SENALA | I22: XOF | J22: 17500157
B23: =VLOOKUP(C23,Companies[],3,FALSE) -> 4151750 2Y2 | C23: Agem Sénégal Exploration SUARL (AGEM) | D23: Caisse de Sécurité Sociale | E23: Cotisations sociales (y compris les pénalités) | F23: Non | G23: Non | H23: NOUMOUFOUKHA | I23: XOF | J23: 7499995
B24: =VLOOKUP(C24,Companies[],3,FALSE) -> 4151750 2Y2 | C24: Agem Sénégal Exploration SUARL (AGEM) | D24: Direction Générale des Mines | E24: Redevance superficiaire | F24: Oui | G24: Oui | H24: NOUMOUFOUKHA | I24: XOF | J24: 3675000
B25: =VLOOKUP(C25,Companies[],3,FALSE) -> 4151750 2Y2 | C25: Agem Sénégal Exploration SUARL (AGEM) | D25: Direction Générale des Mines | E25: Droits d'entrée fixes | F25: Oui | G25: Oui | H25: NOUMOUFOUKHA | I25: XOF | J25: 2500000
C26: Agem Sénégal Exploration SUARL (AGEM) | D26: Direction Générale des Mines | E26: Redevance superficiaire | F26: Oui | G26: Oui | H26: SENALA | I26: XOF | J26: 2362500
C27: Agem Sénégal Exploration SUARL (AGEM) | D27: Direction Générale des Impôts et des Domaines | E27: Retenues à la source sur bénéfice non commercial | F27: Oui | G27: Oui | H27: NOUMOUFOUKHA | I27: XOF | J27: 1775459
C28: Agem Sénégal Exploration SUARL (AGEM) | D28: Direction Générale des Impôts et des Domaines | E28: Retenue à la source sur sommes versées à des tiers | F28: Non | G28: Non | H28: NOUMOUFOUKHA | I28: XOF | J28: 1744422
C29: Agem Sénégal Exploration SUARL (AGEM) | D29: Direction Générale des Impôts et des Domaines | E29: Impôt sur le revenu des valeurs mobilières | F29: Non | G29: Non | H29: NOUMOUFOUKHA | I29: XOF | J29: 1061897
C30: Agem Sénégal Exploration SUARL (AGEM) | D30: Direction Générale des Mines | E30: Redevance superficiaire | F30: Oui | G30: Oui | H30: DAORALA | I30: XOF | J30: 415000
C31: Baobab Mining and Chemical Corp SA | D31: Direction Générale des Impôts et des Domaines | E31: Impôt sur les sociétés | F31: Oui | G31: Oui | H31: NC | I31: XOF | J31: 550233854
C32: Baobab Mining and Chemical Corp SA | D32: Direction Générale des Mines | E32: Redevance minière | F32: Oui | G32: Oui | H32: NC | I32: XOF | J32: 80168375
C33: Baobab Mining and Chemical Corp SA | D33: Direction Générale des Impôts et des Domaines | E33: Retenues à la source sur salaires (IR, TRIMF et CFCE) | F33: Non | G33: Non | H33: NC | I33: XOF | J33: 70301928
C34: Baobab Mining and Chemical Corp SA | D34: Direction Générale des Mines | E34: Redevance superficiaire | F34: Oui | G34: Oui | H34: NC | I34: XOF | J34: 18632000
C35: Baobab Mining and Chemical Corp SA | D35: Institution de Prévoyance Retraite du Sénégal | E35: Cotisations sociales (y compris les pénalités)(IPRES) | F35: Non | G35: Non | H35: NC | I35: XOF | J35: 10200637
C36: Baobab Mining and Chemical Corp SA | D36: Direction Générale des Douanes | E36: Redevance statistique UEMOA | F36: Oui | G36: Oui | H36: NC | I36: XOF | J36: 5792675
C37: Baobab Mining and Chemical Corp SA | D37: Direction Générale des Impôts et des Domaines | E37: Impôt sur le revenu des valeurs mobilières | F37: Non | G37: Non | H37: NC | I37: XOF | J37: 4952376
... C182: Grande Côte Opérations (GCO) | D182: Direction Générale des Impôts et des Domaines | E182: Taxe sur la valeur ajoutée reversée | F182: Non | G182: Non | H182: DIOGO | I182: XOF | J182: 8874240
B183: =VLOOKUP(C183,Companies[],3,FALSE) -> 2849258 2G3 | C183: Grande Côte Opérations (GCO) | D183: Direction Générale des Impôts et des Domaines | E183: Retenue à la source sur sommes versées à des tiers | F183: Non | G183: Non | H183: DIOGO | I183: XOF | J183: 8195632
B184: =VLOOKUP(C184,Companies[],3,FALSE) -> 2849258 2G3 | C184: Grande Côte Opérations (GCO) | D184: Direction Générale des Douanes | E184: Taxe d'enregistrement des véhicules | F184: Oui | G184: Oui | H184: DIOGO | I184: XOF | J184: 1156317
B185: =VLOOKUP(C185,Companies[],3,FALSE) -> 2849258 2G3 | C185: Grande Côte Opérations (GCO) | D185: Direction Générale des Douanes | E185: Autres flux de paiements significatifs (> 25 millions de FCFA) (reconciliables) | F185: Non | G185: Non | H185: DIOGO | I185: XOF | J185: 1103470
C186: Iamgold BOTO | D186: Direction Générale des Impôts et des Domaines | E186: Retenues à la source sur salaires (IR, TRIMF et CFCE) | F186: Non | G186: Non | H186: Boto | I186: XOF | J186: 312064500
C187: Iamgold BOTO | D187: Direction Générale des Impôts et des Domaines | E187: Retenues à la source sur bénéfice non commercial | F187: Oui | G187: Oui | H187: Boto | I187: XOF | J187: 99024067
C188: Iamgold BOTO | D188: Direction de l'Environnement et des Etablissements Classés | E188: Appui Institutionnel (DEEC) | F188: Oui | G188: Oui | H188: Boto | I188: XOF | J188: 76953800
C189: Iamgold BOTO | D189: Direction des Eaux, Forêts, Chasses et Conservation des Sols | E189: Appui Institutionnel (Fonds d'appui au Mini. De l'Env) | F189: Oui | G189: Oui | H189: Boto | I189: XOF | J189: 51220000
C190: Iamgold BOTO | D190: Direction Générale des Mines | E190: Redevance superficiaire | F190: Oui | G190: Oui | H190: Boto | I190: XOF | J190: 37000000
C191: Iamgold BOTO | D191: Institution de Prévoyance Retraite du Sénégal | E191: Cotisations sociales (y compris les pénalités)(IPRES) | F191: Non | G191: Non | H191: Boto | I191: XOF | J191: 33077700
C192: Iamgold BOTO | D192: Direction Générale des Mines | E192: Appui institutionnel | F192: Oui | G192: Oui | H192: Boto | I192: XOF | J192: 29172544
C193: Iamgold BOTO | D193: Direction des Eaux, Forêts, Chasses et Conservation des Sols | E193: Taxes d'abattage | F193: Non | G193: Non | H193: Boto | I193: XOF | J193: 15006000
C194: Iamgold BOTO | D194: Direction Générale des Impôts et des Domaines | E194: Retenue à la source sur sommes versées à des tiers | F194: Non | G194: Non | H194: Boto | I194: XOF | J194: 4205204
C195: Iamgold BOTO | D195: Direction Générale des Impôts et des Domaines | E195: Impôt sur le revenu des valeurs mobilières | F195: Non | G195: Non | H195: Boto | I195: XOF | J195: 3549516
C196: Iamgold BOTO | D196: Caisse de Sécurité Sociale | E196: Cotisations sociales (y compris les pénalités) | F196: Non | G196: Non | H196: Boto | I196: XOF | J196: 3548505
C197: Industries Chimiques du Sénégal (ICS) | D197: Direction Générale des Impôts et des Domaines | E197: Retenues à la source sur salaires (IR, TRIMF et CFCE) | F197: Non | G197: Non | H197: Tobène | I197: XOF | J197: 3366746634
... C399: Woodside Energy Senegal | D399: Direction Générale des Douanes | E399: Prélèvement pour le Conseil Sénégalais des Chargeurs (COSEC) | F399: Oui | G399: Oui | H399: RSSD | I399: XOF | J399: 19424
I401: Total en USD | K401: =SUMIF(Table10[Devise de déclaration],"USD",Table10[Valeur de revenus])+(IFERROR(SUMIF(Table10[Devise de déclaration],"<>USD",Table10[Valeur de revenus])/'Partie 1 - Présentation'!$E$51,0)) -> 4.1437273e+08
I403: ="Total en "&'Partie 1 - Présentation'!$E$50 -> Total en XOF | K403: =IF('Partie 1 - Présentation'!$E$50="USD",0,SUMIF(Table10[Devise de déclaration],'Partie 1 - Présentation'!$E$50,Table10[Valeur de revenus]))+(IFERROR(SUMIF(Table10[Devise de déclaration],"USD",Table10[Valeur de revenus])*'Partie 1 - Présentation'!$E$51,0)) -> 2.5737436e+11
C405: AJOUTER UN SECTEUR
C406: Informations supplémentaires
C407: Ajouter ci-dessous, à titre de commentaire, toute information supplémentaire qu’il ne serait pas nécessaire d’inclure dans le tableau ci-dessus.
C409: Comment | D409: Veuillez inclure tout commentaire ici.
C410: Comment | D410: Veuillez inclure tout commentaire ici.
C411: Comment | D411: Veuillez inclure tout commentaire ici.
C412: Comment | D412: Veuillez inclure tout commentaire ici.
C413: Comment | D413: Ajoutez de nouvelles lignes au besoin, effectuez un clic droit sur le numéro de ligne à gauche, puis sélectionnez « Insérer »
C417: Pour plus d’information sur l’ITIE, visitez notre site Internet https://eiti.org/fr
C418: Vous voulez en savoir plus sur votre pays ? Vérifiez si votre pays met en œuvre la Norme ITIE en visitant https://eiti.org/fr/pays
C419: Pour la version la plus récente des modèles de données résumées, consultez https://eiti.org/fr/document/modele-donnees-resumees-itie
C420: Faites-nous connaître vos réactions ou signalez tout conflit au niveau des données ! Écrivez-nous à data@eiti.org
C422: Site Internet www.eiti.org Courriel secretariat@eiti.org Téléphone +47 22 20 08 00 Télécopieur +47 22 83 08 02
C423: Adresse EITI International Secretariat, Rådhusgata 26, 0151 Oslo, Norvège

Sheet Listes
A1: Tableau 1 - Codes de pays | I1: Tableau 2 - Options simples | K1: Tableau 3 - Options de déclaration | N1: Tableau 5 - Liste de matières premières | S1: Tableau 6 - Codes/Classification GFS | AA1: Tableau 7 - Secteurs | AC1: Tableau 8 - Phases de projet | AE1: Tableau 9 - Types d'agences gouvernementales
A2: Nom de pays ou région | B2: Code ISO de pays (alpha 2) | C2: Code ISO de devise (alpha 3) | D2: Code numérique ISO (UN M49) | E2: Code de devise (ISO 4217) | F2: Code numérique de devise (ISO 4217) | G2: Devise | I2: Liste | K2: Liste | N2: Code de produit HS | O2: Description de produit HS | P2: Description de produit HS av. volume | S2: Combiné | T2: Codes GFS des flux de revenus issus des entreprises extractives | U2: Code GFS | V2: GFS Niveau 1 | W2: GFS Niveau 2 | X2: GFS Niveau 3 | Y2: GFS Niveau 4 | AA2: Secteur (s) | AC2: Étapes du projet | AE2: Type d'Agence
A3: Afghanistan | B3: AF | C3: AFG | D3: 4 | E3: AFN | F3: 971 | G3: Afghani afghan | I3: <Sélectionner l’option> | K3: <Rapportage ITIE ou divulgation systématique?> | N3: 2606 | O3: Aluminium (2606) | P3: Aluminium (2606), volume | S3: Impôts ordinaires sur le revenu, le bénéfice et les plus-values (1112E1) | T3: Impôts ordinaires sur le revenu, le bénéfice et les plus-values | U3: 1112E1 | V3: Impôts (11E) | W3: Impôts sur le revenu, le bénéfice et les plus-values | X3: Impôts ordinaires sur le revenu, le bénéfice et les plus-values (1112E1) | Y3: Impôts ordinaires sur le revenu, le bénéfice et les plus-values (1112E1) | AA3: <Sélectionner le secteur> | AC3: <Sélectionner l’étape> | AE3: Administration centrale
A4: Afrique du Sud | B4: ZA | C4: ZAF | D4: 710 | E4: ZAR | F4: 710 | G4: Rand sud-africain | I4: Oui | K4: Oui, divulgation systématique | N4: 2524 | O4: Amiante (2524) | P4: Amiante (2524), volume | S4: Impôts extraordinaires sur le revenu, le bénéfice et les plus-values (1112E2) | T4: Impôts extraordinaires sur le revenu, le bénéfice et les plus-values | U4: 1112E2 | V4: Impôts (11E) | W4: Impôts sur le revenu, le bénéfice et les plus-values (111E) | X4: Impôts extraordinaires sur le revenu, le bénéfice et les plus-values (1112E2) | Y4: Impôts extraordinaires sur le revenu, le bénéfice et les plus-values (1112E2) | AA4: Pétrole | AC4: Prospection | AE4: Administration d'Etat fédéré
A5: Albanie | B5: AL | C5: ALB | D5: 8 | E5: ALL | F5: 8 | G5: Lek albanais | I5: Partiellement | K5: Oui, à travers le rapportage ITIE | N5: 2514 | O5: Ardoise (2514) | P5: Ardoise (2514), volume | S5: Impôts sur la masse salariale et la force de travail (112E) | T5: Impôts sur la masse salariale et la force de travail | U5: 112E | V5: Impôts (11E) | W5: Impôts sur la masse salariale et la force de travail (112E) | X5: Impôts sur la masse salariale et la force de travail (112E) | Y5: Impôts sur la masse salariale et la force de travail (112E) | AA5: Gaz | AC5: Production | AE5: Administration locale
A6: Algérie | B6: DZ | C6: DZA | D6: 12 | E6: DZD | F6: 12 | G6: Dinar algérien | I6: Non | K6: Sans objet. | N6: 7106 | O6: Argent (7106) | P6: Argent (7106), volume | S6: Impôts sur la propriété (113E) | T6: Impôts sur la propriété | U6: 113E | V6: Impôts (11E) | W6: Impôts sur la propriété (113E) | X6: Impôts sur la propriété (113E) | Y6: Impôts sur la propriété (113E) | AA6: Minier | AC6: Développement | AE6: Société publique financière et Entreprise d'Etat
A7: Allemagne | B7: DE | C7: DEU | D7: 276 | E7: EUR | F7: 978 | G7: Euro | I7: Sans objet | K7: Non disponible | N7: 7202 | O7: Ferro-alliages (7202) | P7: Ferro-alliages (7202), volume | S7: Impôts généraux sur les biens et services (TVA, taxes sur les ventes, taxes sur le chiffre d’affaires)(1141E) | T7: Impôts généraux sur les biens et services (TVA, taxes sur les ventes, taxes sur le chiffre d’affaires) | U7: 1141E | V7: Impôts (11E) | W7: Impôts sur les biens et services (114E) | X7: Impôts généraux sur les biens et services (TVA, taxes sur les ventes, taxes sur le chiffre d’affaires (1141E) | Y7: Impôts généraux sur les biens et services (TVA, taxes sur les ventes, taxes sur le chiffre d’affaires (1141E) | AA7: Sans objet | AC7: Autres | AE7: Autre
A8: Andorre | B8: AD | C8: AND | D8: 20 | E8: EUR | F8: 978 | G8: Euro | N8: 2509 | O8: Argile (2509) | P8: Argile (2509), volume | S8: Droits d’accise (1142E) | T8: Droits d’accise | U8: 1142E | V8: Impôts (11E) | W8: Impôts sur les biens et services (114E) | X8: Droits d’accise (1142E) | Y8: Droits d’accise (1142E) | AA8: Pétrole & Gaz | AC8: Sans objet
A9: Angola | B9: AO | C9: AGO | D9: 24 | E9: AOA | F9: 973 | G9: Kwanza angolais | I9: Tableau 4 - Liste des codes de devise | N9: 2617 | O9: Autres (2617) | P9: Autres (2617), volume | S9: Droits de licence (114521E) | T9: Droits de licence | U9: 114521E | V9: Impôts (11E) | W9: Impôts sur les biens et services (114E) | X9: Impôts sur l’usage de biens/permission d’utiliser des biens ou d’exécuter des activités (1145E) | Y9: Droits de licence (114521E) | AA9: Autres
A10: Anguilla | B10: AI | C10: AIA | D10: 660 | E10: XCD | F10: 951 | G10: Dollar des Caraïbes orientales | I10: Code de devise (ISO 4217) | J10: Code numérique de devise (ISO 4217) | K10: Devise | N10: 2508 | O10: Autres argiles (2508) | P10: Autres argiles (2508), volume | S10: Taxes sur les émissions et la pollution (114522E) | T10: Taxes sur les émissions et la pollution | U10: 114522E | V10: Impôts (11E) | W10: Impôts sur les biens et services (114E) | X10: Impôts sur l’usage de biens/permission d’utiliser des biens ou d’exécuter des activités (1145E) | Y10: Taxes sur les émissions et la pollution (114522E)
A11: Antigua et Barbuda | B11: AG | C11: ATG | D11: 28 | E11: XCD | F11: 951 | G11: Dollar des Caraïbes orientales | I11: AED | J11: 784 | K11: Dirham des émirats arabes unis | N11: 2621 | O11: Autres cendres et mâchefer (2621) | P11: Autres cendres et mâchefer (2621), volume | S11: Taxes sur les véhicules à moteur (11451E) | T11: Taxes sur les véhicules à moteur | U11: 11451E | V11: Impôts (11E) | W11: Impôts sur les biens et services (114E) | X11: Impôts sur l’usage de biens/permission d’utiliser des biens ou d’exécuter des activités (1145E) | Y11: Taxes sur les véhicules à moteur (11451E)
A12: Antilles néerlandaises | B12: AN | C12: ANT | D12: 530 | E12: ANG | F12: 532 | G12: Florin des Antilles néerlandaises | I12: AFN | J12: 971 | K12: Afghani afghan | N12: 2714 | O12: Bitume et asphalte (2714) | P12: Bitume et asphalte (2714), volume | S12: Droits de douane et autres droits d’importation (1151E) | T12: Droits de douane et autres droits d’importation | U12: 1151E | V12: Impôts (11E) | W12: Taxes sur le commerce et les transactions au niveau international (115E) | X12: Droits de douane et autres droits d’importation (1151E) | Y12: Droits de douane et autres droits d’importation (1151E)
A13: Arabie saoudite | B13: SA | C13: SAU | D13: 682 | E13: SAR | F13: 682 | G13: Rial saoudite | I13: ALL | J13: 8 | K13: Lek albanais | N13: 2528 | O13: Borates et concentrés naturels (2528) | P13: Borates et concentrés naturels (2528), volume | S13: Taxes sur les exportations (1152E) | T13: Taxes sur les exportations | U13: 1152E | V13: Impôts (11E) | W13: Taxes sur le commerce et les transactions au niveau international (115E) | X13: Taxes sur les exportations (1152E) | Y13: Taxes sur les exportations (1152E)
A14: Argentine | B14: AR | C14: ARG | D14: 32 | E14: ARS | F14: 32 | G14: Peso argentin | I14: AMD | J14: 51 | K14: Dram arménien | N14: 2517 | O14: Cailloux (2517) | P14: Cailloux (2517), volume | S14: Bénéfices des monopoles fiscaux sur les ressources naturelles (1153E1) | T14: Bénéfices des monopoles fiscaux sur les ressources naturelles | U14: 1153E1 | V14: Impôts (11E) | W14: Taxes sur le commerce et les transactions au niveau international (115E) | X14: Bénéfices des monopoles fiscaux sur les ressources naturelles (1153E1) | Y14: Bénéfices des monopoles fiscaux sur les ressources naturelles (1153E1)
A15: Arménie | B15: AM | C15: ARM | D15: 51 | E15: AMD | F15: 51 | G15: Dram arménien | I15: ANG | J15: 532 | K15: Florin des Antilles néerlandaises | N15: 2521 | O15: Calcaire (2521) | P15: Calcaire (2521), volume | S15: Autres impôts payés par les entreprises exploitant des ressources naturelles (116E) | T15: Autres impôts payés par les entreprises exploitant des ressources naturelles | U15: 116E | V15: Impôts (11E) | W15: Autres impôts payés par les entreprises exploitant des ressources naturelles (116E) | X15: Autres impôts payés par les entreprises exploitant des ressources naturelles (116E) | Y15: Autres impôts payés par les entreprises exploitant des ressources naturelles (116E)
A16: Aruba | B16: AW | C16: ABW | D16: 533 | E16: AWG | F16: 533 | G16: Florin d’Aruba | I16: AOA | J16: 973 | K16: Kwanza angolais | N16: 2519 | O16: Carbonate de magnésium naturel (2519) | P16: Carbonate de magnésium naturel (2519), volume | S16: Cotisations patronales à la sécurité sociale (1212E) | T16: Cotisations patronales à la sécurité sociale | U16: 1212E | V16: Cotisations sociales (12E) | W16: Cotisations patronales à la sécurité sociale (1212E) | X16: Cotisations patronales à la sécurité sociale (1212E) | Y16: Cotisations patronales à la sécurité sociale (1212E)
A17: Australie | B17: AU | C17: AUS | D17: 36 | E17: AUD | F17: 36 | G17: Dollar australien | I17: ARS | J17: 32 | K17: Peso argentin | N17: 2620 | O17: Cendres et résidus (2620) | P17: Cendres et résidus (2620), volume | S17: Des entreprises d’État (1412E1) | T17: Des entreprises d’État | U17: 1412E1 | V17: Autre revenu (14E) | W17: Revenu dégagé de la propriété (141E) | X17: Dividendes (1412E) | Y17: Des entreprises d’État (1412E1)
A18: Autriche | B18: AT | C18: AUT | D18: 40 | E18: EUR | F18: 978 | G18: Euro | I18: AUD | J18: 36 | K18: Dollar australien | N18: 2701 | O18: Charbon (2701) | P18: Charbon (2701), volume | S18: Provenant de la participation de l’État (1412E2) | T18: Provenant de la participation de l’État | U18: 1412E2 | V18: Autre revenu (14E) | W18: Revenu dégagé de la propriété (141E) | X18: Dividendes (1412E) | Y18: Provenant de la participation de l’État (1412E2)
A19: Azerbaïdjan | B19: AZ | C19: AZE | D19: 31 | E19: AZN | F19: 944 | G19: Manat azéri | I19: AWG | J19: 533 | K19: Florin d’Aruba | N19: 2522 | O19: Chaux vive (2522) | P19: Chaux vive (2522), volume | S19: Retraits à partir du revenu de quasi-sociétés (1413E) | T19: Retraits à partir du revenu de quasi-sociétés | U19: 1413E | V19: Autre revenu (14E) | W19: Revenu dégagé de la propriété (141E) | X19: Retraits à partir du revenu de quasi-sociétés (1413E) | Y19: Retraits à partir du revenu de quasi-sociétés (1413E)
A20: Bahamas | B20: BS | C20: BHS | D20: 44 | E20: BSD | F20: 44 | G20: Dollar bahamien | I20: AZN | J20: 944 | K20: Manat azéri | N20: 2610 | O20: Chrome (2610) | P20: Chrome (2610), volume | S20: Redevances (1415E1) | T20: Redevances | U20: 1415E1 | V20: Autre revenu (14E) | W20: Revenu dégagé de la propriété (141E) | X20: Loyers (1415E) | Y20: Redevances (1415E1)
A21: Bahreïn | B21: BH | C21: BHR | D21: 48 | E21: BHD | F21: 48 | G21: Dinar de Bahreïn | I21: BAM | J21: 977 | K21: Mark convertible de Bosnie-Herzégovine | N21: 2523 | O21: Ciment Portland (2523) | P21: Ciment Portland (2523), volume | S21: Primes (1415E2) | T21: Primes | U21: 1415E2 | V21: Autre revenu (14E) | W21: Revenu dégagé de la propriété (141E) | X21: Loyers (1415E) | Y21: Primes (1415E2)
A22: Bangladesh | B22: BD | C22: BGD | D22: 50 | E22: BDT | F22: 50 | G22: Taka bangladeshi | I22: BBD | J22: 52 | K22: Dollar de la Barbade | N22: 2605 | O22: Cobalt (2605) | P22: Cobalt (2605), volume | S22: Livré/payé directement à l’État (1415E31) | T22: Livré/payé directement à l’État | U22: 1415E31 | V22: Autre revenu (14E) | W22: Revenu dégagé de la propriété (141E) | X22: Loyers (1415E) | Y22: Droits sur la production (en nature ou en espèces)(1415E3)
... A30: Bolivie | B30: BO | C30: BOL | D30: 68 | E30: BOB | F30: 68 | G30: Boliviano bolivien | I30: BRL | J30: 986 | K30: Réal brésilien | N30: 2609 | O30: Étain (2609) | P30: Étain (2609), volume | S30: <Sélectionner à partir du menu> | T30: <Sélectionner à partir du menu> | U30: <Sélectionner à partir du menu> | V30: <Sélectionner à partir du menu> | W30: <Sélectionner à partir du menu> | X30: <Sélectionner à partir du menu> | Y30: <Sélectionner à partir du menu>
A31: Bosnie-Herzégovine | B31: BA | C31: BIH | D31: 70 | E31: BAM | F31: 977 | G31: Mark convertible de Bosnie-Herzégovine | I31: BSD | J31: 44 | K31: Dollar bahamien | N31: 2512 | O31: Farines siliceuses fossiles (2512) | P31: Farines siliceuses fossiles (2512), volume
A32: Botswana | B32: BW | C32: BWA | D32: 72 | E32: BWP | F32: 72 | G32: Pula du Botswana | I32: BTN | J32: 64 | K32: Nutum du Bhoutan | N32: 2529 | O32: Feldspath (2529) | P32: Feldspath (2529), volume
A33: Brésil | B33: BR | C33: BRA | D33: 76 | E33: BRL | F33: 986 | G33: Réal brésilien | I33: BWP | J33: 72 | K33: Pula du Botswana | N33: 2601 | O33: Fer (2601) | P33: Fer (2601), volume
A34: Bulgarie | B34: BG | C34: BGR | D34: 100 | E34: BGN | F34: 975 | G34: Lev bulgare (ancien) | I34: BYR | J34: 974 | K34: Rouble de Belarus | N34: 2705 | O34: Gaz de charbon (2705) | P34: Gaz de charbon (2705), volume
A35: Burkina Faso | B35: BF | C35: BFA | D35: 854 | E35: XOF | F35: 952 | G35: Franc CFA d’Afrique de l’Ouest | I35: BZD | J35: 84 | K35: Dollar de Belize | N35: 2711 | O35: Gaz naturel (2711) | P35: Gaz naturel (2711), volume
A36: Burundi | B36: BI | C36: BDI | D36: 108 | E36: BIF | F36: 108 | G36: Franc du Burundi | I36: CAD | J36: 124 | K36: Dollar canadien | N36: 2712 | O36: Gelée de pétrole (2712) | P36: Gelée de pétrole (2712), volume
A37: Cambodge | B37: KH | C37: KHM | D37: 116 | E37: KHR | F37: 116 | G37: Riel cambodgien | I37: CDF | J37: 976 | K37: Franc congolais | N37: 2706 | O37: Goudron distillé à partir de charbon (2706) | P37: Goudron distillé à partir de charbon (2706), volume
A38: Cameroun | B38: CM | C38: CMR | D38: 120 | E38: XAF | F38: 950 | G38: Franc CFA d’Afrique centrale | I38: CHF | J38: 756 | K38: Franc suisse | N38: 2516 | O38: Granite (2516) | P38: Granite (2516), volume
A39: Canada | B39: CA | C39: CAN | D39: 124 | E39: CAD | F39: 124 | G39: Dollar canadien | I39: CLF | J39: 990 | K39: Unidad de Fomento chilien | N39: 2504 | O39: Graphite naturel (2504) | P39: Graphite naturel (2504), volume
A40: Cap Vert | B40: CV | C40: CPV | D40: 132 | E40: CVE | F40: 132 | G40: Escudo cap-verdien | I40: CNH | J40: 0 | K40: Yuan renminbi chinois (off-shore) | N40: 2520 | O40: Gypse (2520) | P40: Gypse (2520), volume
A41: Chili | B41: CL | C41: CHL | D41: 152 | E41: CLF | F41: 990 | G41: Unidad de Fomento chilien | I41: COP | J41: 170 | K41: Peso colombien | N41: 2710 | O41: Huiles de pétrole hors pétrole brut (2710) | P41: Huiles de pétrole hors pétrole brut (2710), volume
A42: Chine | B42: CN | C42: CHN | D42: 156 | E42: CNH | F42: 0 | G42: Yuan renminbi chinois (off-shore) | I42: CRC | J42: 188 | K42: Colon costaricain | N42: 2507 | O42: Kaolin (2507) | P42: Kaolin (2507), volume
... A71: Géorgie | B71: GE | C71: GEO | D71: 268 | E71: GEL | F71: 981 | G71: Lari géorgien | I71: ILS | J71: 376 | K71: Nouveau shekel israélien | N71: 2611 | O71: Tungstène (2611) | P71: Tungstène (2611), volume
A72: Géorgie du Sud et les Îles Sandwich du Sud | B72: GS | C72: SGS | D72: 239 | I72: IMP | J72: 0 | K72: Livre de l’Île de Man | N72: 2612 | O72: Uranium ou thorium (2612) | P72: Uranium ou thorium (2612), volume
A73: Ghana | B73: GH | C73: GHA | D73: 288 | E73: GHS | F73: 936 | G73: Cedi ghanéen | I73: INR | J73: 356 | K73: Roupie indienne | N73: 2608 | O73: Zinc (2608) | P73: Zinc (2608), volume
A74: Gibraltar | B74: GI | C74: GIB | D74: 292 | E74: GIP | F74: 292 | G74: Livre de Gibraltar | I74: IQD | J74: 368 | K74: Dinar irakien | N74: 7103 | O74: Pierres gemmes (précieuses ou fines) autres que les diamants (7103) | P74: Pierres gemmes (précieuses ou fines) autres que les diamants (7103), volume
A75: Grèce | B75: GR | C75: GRC | D75: 300 | E75: EUR | F75: 978 | G75: Euro | I75: IRR | J75: 364 | K75: Rial iranien
A76: Grenade | B76: GD | C76: GRD | D76: 308 | E76: XCD | F76: 951 | G76: Dollar des Caraïbes orientales | I76: ISK | J76: 352 | K76: Couronne islandaise
A77: Groenland | B77: GL | C77: GRL | D77: 304 | E77: DKK | F77: 208 | G77: Couronne danoise | I77: JEP | J77: 0 | K77: Livre de Jersey
A78: Guadeloupe | B78: GP | C78: GLP | D78: 312 | E78: EUR | F78: 978 | G78: Euro | I78: JMD | J78: 388 | K78: Dollar de la Jamaïque
A79: Guam | B79: GU | C79: GUM | D79: 316 | E79: USD | F79: 840 | G79: Dollar des États-Unis | I79: JOD | J79: 400 | K79: Dinar jordanien
A80: Guatemala | B80: GT | C80: GTM | D80: 320 | E80: GTQ | F80: 320 | G80: Quetzal guatémaltèque | I80: JPY | J80: 392 | K80: Yen japonais
A81: Guernesey | B81: GG | C81: GGY | D81: 831 | E81: GGP | F81: 0 | G81: Livre | I81: KES | J81: 404 | K81: Shilling kenyan
A82: Guinée | B82: GN | C82: GIN | D82: 324 | E82: GNF | F82: 324 | G82: Franc guinéen | I82: KGS | J82: 417 | K82: Sum kirghize
A83: Guinée équatoriale | B83: GQ | C83: GNQ | D83: 226 | E83: XAF | F83: 950 | G83: Franc CFA d’Afrique centrale | I83: KHR | J83: 116 | K83: Riel cambodgien
A84: Guinée-Bissau | B84: GW | C84: GNB | D84: 624 | E84: XOF | F84: 952 | G84: Franc CFA d’Afrique de l’Ouest | I84: KMF | J84: 174 | K84: Franc comorien
A85: Guyana | B85: GY | C85: GUY | D85: 328 | E85: GYD | F85: 328 | G85: Dollar guyanais | I85: KPW | J85: 408 | K85: Won nord-coréen
A86: Guyane française | B86: GF | C86: GUF | D86: 254 | E86: EUR | F86: 978 | G86: Euro | I86: KRW | J86: 410 | K86: Won sud-coréen
... A93: Îles Féroé | B93: FO | C93: FRO | D93: 234 | E93: DKK | F93: 208 | G93: Couronne danoise | I93: LRD | J93: 430 | K93: Dollar du Libéria
A94: Îles Heard et McDonald | B94: HM | C94: HMD | D94: 334 | I94: LSL | J94: 426 | K94: Loti du Lesotho
A95: Îles Keeling | B95: CC | C95: CCK | D95: 166 | E95: AUD | F95: 36 | G95: Dollar australien | I95: LYD | J95: 434 | K95: Dinar libyen
A96: Îles Marianne septentrionales | B96: MP | C96: MNP | D96: 580 | E96: USD | F96: 840 | G96: Dollar des États-Unis | I96: MAD | J96: 504 | K96: Dirham marocain
A97: Îles Marshall | B97: MH | C97: MHL | D97: 584 | E97: USD | F97: 840 | G97: Dollar des États-Unis | I97: MDL | J97: 498 | K97: Leu moldave
A98: Îles Norfolk | B98: NF | C98: NFK | D98: 574 | I98: MGA | J98: 969 | K98: Ariary malgache
A99: Îles Salomon | B99: KY | C99: CYM | D99: 136 | E99: KYD | F99: 136 | G99: Dollar des Îles Caïman | I99: MKD | J99: 807 | K99: Denar macédonien
A100: Îles Salomon | B100: SB | C100: SLB | D100: 90 | E100: SBD | F100: 90 | G100: Dollar des Îles Salomon | I100: MMK | J100: 104 | K100: Kyat birman
A101: Îles Svalbard et Jan Mayen | B101: SJ | C101: SJM | D101: 744 | I101: MNT | J101: 496 | K101: Tugrik mongole
A102: Îles Turques et Caïques | B102: TC | C102: TCA | D102: 796 | E102: USD | F102: 840 | G102: Dollar des États-Unis | I102: MOP | J102: 446 | K102: Patca de Macao
A103: Îles Vierges britanniques | B103: VG | C103: VGB | D103: 92 | E103: USD | F103: 840 | G103: Dollar des États-Unis | I103: MRO | J103: 478 | K103: Ouguiya mauritanien
A104: Îles Vierges, États-Unis | B104: VI | C104: VIR | D104: 850 | E104: USD | F104: 840 | G104: Dollar des États-Unis | I104: MUR | J104: 480 | K104: Roupie mauricienne
A105: Îles Wallis et Futuna | B105: WF | C105: WLF | D105: 876 | I105: MVR | J105: 462 | K105: Rufiyaa des Maldives
A106: Îles Åland | B106: AX | C106: ALA | D106: 248 | E106: EUR | F106: 978 | G106: Euro | I106: MWK | J106: 454 | K106: Kwacha du Malawi
A107: Inde | B107: IN | C107: IND | D107: 356 | E107: INR | F107: 356 | G107: Roupie indienne | I107: MXN | J107: 484 | K107: Peso mexicain
A108: Indonésie | B108: ID | C108: IDN | D108: 360 | E108: IDR | F108: 360 | G108: Roupie indonésienne | I108: MYR | J108: 458 | K108: Ringgit malais
A109: Irak | B109: IQ | C109: IRQ | D109: 368 | E109: IQD | F109: 368 | G109: Dinar irakien | I109: MZN | J109: 943 | K109: Metical mozambicain
A110: Iran | B110: IR | C110: IRN | D110: 364 | E110: IRR | F110: 364 | G110: Rial iranien | I110: NAD | J110: 516 | K110: Dollar namibien
A111: Irlande | B111: IE | C111: IRL | D111: 372 | E111: EUR | F111: 978 | G111: Euro | I111: NGN | J111: 566 | K111: Naira nigérian
A112: Islande | B112: IS | C112: ISL | D112: 352 | E112: ISK | F112: 352 | G112: Couronne islandaise | I112: NIO | J112: 558 | K112: Cordoba oro nicaraguayen
A113: Israël | B113: IL | C113: ISR | D113: 376 | E113: ILS | F113: 376 | G113: Nouveau shekel israélien | I113: NOK | J113: 578 | K113: Couronne norvégienne
A114: Italie | B114: IT | C114: ITA | D114: 380 | E114: EUR | F114: 978 | G114: Euro | I114: NPR | J114: 524 | K114: Roupie népalaise
A115: Jamaïque | B115: JM | C115: JAM | D115: 388 | E115: JMD | F115: 388 | G115: Dollar de la Jamaïque | I115: NZD | J115: 554 | K115: Dollar néo-zélandais
A116: Japon | B116: JP | C116: JPN | D116: 392 | E116: JPY | F116: 392 | G116: Yen japonais | I116: OMR | J116: 512 | K116: Rial omanais
A117: Jersey | B117: JE | C117: JEY | D117: 832 | E117: JEP | F117: 0 | G117: Livre de Jersey | I117: PAB | J117: 590 | K117: Balboa panaméen
... A120: Kenya | B120: KE | C120: KEN | D120: 404 | E120: KES | F120: 404 | G120: Shilling kenyan | I120: PHP | J120: 608 | K120: Peso philippin
A121: Kiribati | B121: KI | C121: KIR | D121: 296 | I121: PKR | J121: 586 | K121: Roupie pakistanaise
A122: Kosovo | B122: XK | C122: XKX | D122: - | E122: EUR | F122: 978 | G122: Euro | I122: PLN | J122: 985 | K122: Zloty polonais
A123: Koweït | B123: KW | C123: KWT | D123: 414 | E123: KWD | F123: 414 | G123: Dinar koweitien | I123: PYG | J123: 600 | K123: Guarani paraguayen
A124: Lesotho | B124: LS | C124: LSO | D124: 426 | E124: LSL | F124: 426 | G124: Loti du Lesotho | I124: QAR | J124: 634 | K124: Riyal du Qatar
A125: Lettonie | B125: LV | C125: LVA | D125: 428 | E125: EUR | F125: 978 | G125: Euro | I125: RON | J125: 946 | K125: Leu roumain
A126: Liban | B126: LB | C126: LBN | D126: 422 | E126: LBP | F126: 422 | G126: Livre libanaise | I126: RSD | J126: 941 | K126: Dinar serbe
A127: Libéria | B127: LR | C127: LBR | D127: 430 | E127: LRD | F127: 430 | G127: Dollar du Libéria | I127: RUB | J127: 643 | K127: Rouble russe
A128: Libye | B128: LY | C128: LBY | D128: 434 | E128: LYD | F128: 434 | G128: Dinar libyen | I128: RWF | J128: 646 | K128: Franc rwandais
A129: Liechtenstein | B129: LI | C129: LIE | D129: 438 | E129: CHF | F129: 756 | G129: Franc suisse | I129: SAR | J129: 682 | K129: Rial saoudite
A130: Lituanie | B130: LT | C130: LTU | D130: 440 | E130: EUR | F130: 978 | G130: Euro | I130: SBD | J130: 90 | K130: Dollar des Îles Salomon
A131: Luxembourg | B131: LU | C131: LUX | D131: 442 | E131: EUR | F131: 978 | G131: Euro | I131: SCR | J131: 690 | K131: Roupie seychelloise
A132: Macao | B132: MO | C132: MAC | D132: 446 | E132: MOP | F132: 446 | G132: Patca de Macao | I132: SDG | J132: 938 | K132: Livre soudanaise
A133: Macédoine | B133: MK | C133: MKD | D133: 807 | E133: MKD | F133: 807 | G133: Denar macédonien | I133: SEK | J133: 752 | K133: Couronne suédoise
... A155: Namibie | B155: NA | C155: NAM | D155: 516 | E155: NAD | F155: 516 | G155: Dollar namibien | I155: USD | J155: 840 | K155: Dollar des États-Unis
A156: Nauru | B156: NR | C156: NRU | D156: 520 | I156: USD
A157: Népal | B157: NP | C157: NPL | D157: 524 | E157: NPR | F157: 524 | G157: Roupie népalaise | I157: UYU | J157: 858 | K157: Peso uruguayen
A158: Nicaragua | B158: NI | C158: NIC | D158: 558 | E158: NIO | F158: 558 | G158: Cordoba oro nicaraguayen | I158: UZS | J158: 860 | K158: Sum ouzbèque
A159: Niger | B159: NE | C159: NER | D159: 562 | E159: XOF | F159: 952 | G159: Franc CFA d’Afrique de l’Ouest | I159: VEF | J159: 937 | K159: Bolivar fuerte vénézuélien
A160: Nigeria | B160: NG | C160: NGA | D160: 566 | E160: NGN | F160: 566 | G160: Naira nigérian | I160: VND | J160: 704 | K160: Dong vietnamien
A161: Niue | B161: NU | C161: NIU | D161: 570 | I161: VUV | J161: 548 | K161: Vatu de Vanuatu
A162: Norvège | B162: NO | C162: NOR | D162: 578 | E162: NOK | F162: 578 | G162: Couronne norvégienne | I162: WST | J162: 882 | K162: Tala de Samoa
A163: Nouvelle Calédonie | B163: NC | C163: NCL | D163: 540 | I163: XAF | J163: 950 | K163: Franc CFA d’Afrique centrale
A164: Nouvelle-Zélande | B164: NZ | C164: NZL | D164: 554 | E164: NZD | F164: 554 | G164: Dollar néo-zélandaise | I164: XCD | J164: 951 | K164: Dollar des Caraïbes orientales
...
